Workbook

Sheet DATOS
B1: CIMENTACIONES SUPERFICIALES — ACI 318-19 · DATOS DE ENTRADA
B2: =$C$9&" · "&$C$10 -> Ejemplo — nave industrial · Columna tipo eje B-2 · muro eje 1
B3: HOJAS DEL LIBRO: DATOS → COMBINACIONES → AISLADA → AISLADA_CT → CORRIDA → LINDERO → CROQUIS → RESUMEN · de apoyo: TABLAS, REFERENCIAS, CROQUIS_DATOS
B4: CÓMO SE USA: sólo se tocan las celdas AMARILLAS con número AZUL (aquí y en las secciones 1 y 2 de AISLADA, AISLADA_CT, CORRIDA y LINDERO, y la 13 de AISLADA_CT y LINDERO). Todo lo demás son fórmulas. Los valores que trae son un EJEMPLO para que veas el formato: cámbialos por los de tu proyecto. El croquis se escoge en la hoja CROQUIS (celda amarilla de arriba).
B5: ALCANCE: ACI 318-19 cap. 13 y los capítulos a los que remite. Cuatro tipos: (1) zapata aislada, (2) zapata aislada ligada con contratrabes, (3) zapata corrida bajo muro, (4) zapata de lindero con o sin contratrabe de equilibrio. Revisa presiones de servicio contra qa, volteo, deslizamiento, penetración, cortante en una dirección, flexión, refuerzo mínimo y separaciones, desarrollo, aplastamiento dado-zapata y dovelas, y arroja el armado. NO incluye: zapatas de esquina, combinadas, losas de cimentación, pilotes, asentamientos, ni el diseño del dado como columna. El CROQUIS dibuja sólo los tipos 1 a 3.
B7: 1. PROYECTO
B8: Concepto | C8: Valor | D8: Unidad | E8: Cómo se calcula / de dónde sale | F8: Referencia
B9: Proyecto | C9: Ejemplo — nave industrial | D9: — | E9: CAPTURA. Sólo aparece en los encabezados. | F9: Datos del proyecto
B10: Elemento / eje | C10: Columna tipo eje B-2 · muro eje 1 | D10: — | E10: CAPTURA. Sólo aparece en los encabezados. | F10: Datos del proyecto
B11: Sistema de unidades | C11: t · m · cm · kg/cm² | D11: — | E11: Las ecuaciones del ACI 318-19 están en SI (MPa, mm). La hoja pasa f'c y fy a MPa, evalúa la ecuación tal como viene en el reglamento y regresa el resultado a kg/cm² o t. | F11: 1 MPa = 10.1972 kg/cm²
B13: 2. MATERIALES
B14: Concepto | C14: Valor | D14: Unidad | E14: Cómo se calcula / de dónde sale | F14: Referencia
B15: f'c — resistencia del concreto | C15: 250 | D15: kg/cm² | E15: CAPTURA. El ACI pide al menos 17 MPa (≈ 175 kg/cm²) en cimentaciones. | F15: ACI 318-19, Tabla 19.2.1.1 · 13.2.1.1, pág. 199
B16: f'c en MPa | C16: =$C$15/$C$89 -> 24.516534 | D16: MPa | E16: CALCULADA = f'c / 10.1972. | F16: Conversión de unidades
B17: √f'c usada en cortante y desarrollo | C17: =MIN(SQRT($C$16),8.3) -> 4.9514174 | D17: √MPa | E17: CALCULADA = √f'c con el tope de 8.3 MPa del reglamento. | F17: ACI 318-19, 22.5.3.1, 22.6.3.1 y 25.4.1.4
B18: fy — fluencia del refuerzo | C18: 4200 | D18: kg/cm² | E18: CAPTURA. Varilla corrugada grado 42. | F18: NMX-C-407-ONNCCE · ACI 318-19, 20.2.2.4
B19: fy en MPa | C19: =$C$18/$C$89 -> 411.87777 | D19: MPa | E19: CALCULADA = fy / 10.1972. | F19: Conversión de unidades
B20: Es — módulo del acero | C20: =200000*$C$89 -> 2039440 | D20: kg/cm² | E20: CALCULADA = 200,000 MPa pasado a kg/cm². | F20: ACI 318-19, 20.2.2.2
B21: εty — deformación de fluencia | C21: =$C$18/$C$20 -> 0.0020593889 | D21: — | E21: CALCULADA = fy / Es. | F21: ACI 318-19, 21.2.2.1
B22: β₁ — factor del bloque de compresión | C22: =IF($C$16<=28,0.85,IF($C$16>=55,0.65,0.85-0.05*($C$16-28)/7)) -> 0.85 | D22: — | E22: CALCULADA con f'c en MPa: 0.85 hasta 28 MPa, baja 0.05 por cada 7 MPa, mínimo 0.65. | F22: ACI 318-19, Tabla 22.2.2.4.3
B23: λ — factor de concreto ligero | C23: 1 | D23: — | E23: CAPTURA. 1.00 para concreto de peso normal. | F23: ACI 318-19, 19.2.4.2 (Tabla 19.2.4.2)
B24: γc — peso volumétrico del concreto reforzado | C24: 2.4 | D24: t/m³ | E24: CAPTURA. | F24: Práctica de ingeniería
B25: Tamaño máximo del agregado grueso | C25: 19 | D25: mm | E25: CAPTURA. 19 mm = 3/4". Sirve para la separación libre mínima entre varillas. | F25: ACI 318-19, 25.2.1
B26: ψg — factor por grado del refuerzo | C26: =IF($C$19<=420,1,IF($C$19<=550,1.15,1.3)) -> 1 | D26: — | E26: CALCULADA: 1.00 para grado 280 y 420; 1.15 para 550; 1.30 para 690. | F26: ACI 318-19, Tabla 25.4.2.5
B28: 3. SUELO — sin estudio de mecánica de suelos, estos son datos de entrada que tú propones
B29: Concepto | C29: Valor | D29: Unidad | E29: Cómo se calcula / de dónde sale | F29: Referencia
B30: qa — capacidad de carga admisible (bruta) al nivel de desplante | C30: 18 | D30: t/m² | E30: CAPTURA. Presión total admisible (incluye peso de zapata y relleno). SIN ESTUDIO: orienta el valor con la tabla presuntiva de TABLAS y confírmalo antes de construir. | F30: Estudio de mecánica de suelos · orientación: NAVFAC DM 7.02, Tabla 1, págs. 7.2-142 y 7.2-143 · ACI 318-19, 13.3.1.1, pág. 203
B31: Incremento de qa en combinaciones con acción accidental | C31: 1 | D31: — | E31: CAPTURA. Déjalo en 1.00 salvo que el estudio permita aumentar la capacidad para cargas de corta duración (típico 1.33). | F31: Estudio de mecánica de suelos · Bowles 5ª ed., §4.15, pág. 275
B32: γs — peso volumétrico del relleno sobre la zapata | C32: 1.6 | D32: t/m³ | E32: CAPTURA. Relleno compactado. | F32: Estudio de mecánica de suelos · práctica
B33: μ — factor de fricción suelo-concreto (tan δ) | C33: 0.45 | D33: — | E33: CAPTURA. Ver la tabla 4 de TABLAS. No se cuenta el empuje pasivo del relleno lateral (queda del lado seguro). | F33: NAVFAC DM 7.02, Cap. 3, Tabla 1, pág. 7.2-63
B34: FS exigido contra volteo | C34: 1.5 | D34: — | E34: CAPTURA. Se revisa con TODAS las combinaciones de servicio, incluida la de 0.6D (queda del lado seguro). | F34: ACI 318-19, 13.2.6.1, págs. 199–200 · Bowles 5ª ed., Tabla 4-9, pág. 276
B35: FS exigido contra deslizamiento | C35: 1.5 | D35: — | E35: CAPTURA. Igual criterio que el de volteo. | F35: ACI 318-19, 13.2.6.1, págs. 199–200 · Bowles 5ª ed., Tabla 4-9, pág. 276
B37: 4. ACCIÓN ACCIDENTAL Y COMBINACIONES
B38: Concepto | C38: Valor | D38: Unidad | E38: Cómo se calcula / de dónde sale | F38: Referencia
B39: Acción accidental A que se captura abajo | C39: SISMO | D39: — | E39: CAPTURA (lista). Cambia los factores de servicio: sismo 0.7E y 0.525E; viento 0.6W y 0.45W. Las de resistencia usan 1.0 en ambos casos. | F39: ASCE/SEI 7-16, §2.4.1 · ACI 318-19, Tabla 5.3.1
B40: Factor de la carga viva en las combinaciones de resistencia con A | C40: 1 | D40: — | E40: CAPTURA. 1.0, o 0.5 si L ≤ 4.8 kPa (≈ 490 kg/m²) y no es estacionamiento ni lugar de reunión. | F40: ACI 318-19, 5.3.3
B41: Tabla completa de combinaciones | C41: Hoja COMBINACIONES | D41: — | E41: La A entra con los dos signos: se toma la que suma a los momentos de D y L, y en P la que suma (S4, U4) y la que resta (S5, U5). | F41: ACI 318-19, 13.2.6.1 y 13.2.6.3, pág. 200
B43: 5. CARGAS DE SERVICIO EN LA BASE DE LA COLUMNA — para AISLADA, AISLADA_CT y LINDERO (por caso de carga, sin factorizar)
B44: Concepto | C44: Valor | D44: Unidad | E44: Cómo se calcula / de dónde sale | F44: Referencia
B45: EJES: X y Y en planta. Mx gira alrededor de X y produce excentricidad ey; My gira alrededor de Y y produce ex. En STAAD (Y vertical): FY → P, MX → Mx, MZ → My, FX → Vx, FZ → Vy. Los momentos y cortantes se usan en valor absoluto (la zapata es simétrica).
B46: P — carga axial, carga muerta (D) | C46: 30 | D46: t | E46: CAPTURA. Reacción vertical del caso D tal como sale del modelo. | F46: Modelo de análisis (STAAD) · tabla de reacciones
B47: P — carga axial, carga viva (L) | C47: 12 | D47: t | E47: CAPTURA. Reacción vertical del caso L tal como sale del modelo. | F47: Modelo de análisis (STAAD) · tabla de reacciones
B48: P — carga axial, carga accidental (A) | C48: 6 | D48: t | E48: CAPTURA. Reacción vertical del caso A tal como sale del modelo. | F48: Modelo de análisis (STAAD) · tabla de reacciones
B49: Mx — momento alrededor de X, carga muerta (D) | C49: 0.8 | D49: t·m | E49: CAPTURA. Momento del caso D tal como sale del modelo. | F49: Modelo de análisis (STAAD) · tabla de reacciones
B50: Mx — momento alrededor de X, carga viva (L) | C50: 0.4 | D50: t·m | E50: CAPTURA. Momento del caso L tal como sale del modelo. | F50: Modelo de análisis (STAAD) · tabla de reacciones
B51: Mx — momento alrededor de X, carga accidental (A) | C51: 5.5 | D51: t·m | E51: CAPTURA. Momento del caso A tal como sale del modelo. | F51: Modelo de análisis (STAAD) · tabla de reacciones
B52: My — momento alrededor de Y, carga muerta (D) | C52: 0.6 | D52: t·m | E52: CAPTURA. Momento del caso D tal como sale del modelo. | F52: Modelo de análisis (STAAD) · tabla de reacciones
B53: My — momento alrededor de Y, carga viva (L) | C53: 0.3 | D53: t·m | E53: CAPTURA. Momento del caso L tal como sale del modelo. | F53: Modelo de análisis (STAAD) · tabla de reacciones
B54: My — momento alrededor de Y, carga accidental (A) | C54: 6.5 | D54: t·m | E54: CAPTURA. Momento del caso A tal como sale del modelo. | F54: Modelo de análisis (STAAD) · tabla de reacciones
B55: Vx — cortante en dirección X, carga muerta (D) | C55: 0.2 | D55: t | E55: CAPTURA. Cortante del caso D tal como sale del modelo. | F55: Modelo de análisis (STAAD) · tabla de reacciones
B56: Vx — cortante en dirección X, carga viva (L) | C56: 0.1 | D56: t | E56: CAPTURA. Cortante del caso L tal como sale del modelo. | F56: Modelo de análisis (STAAD) · tabla de reacciones
B57: Vx — cortante en dirección X, carga accidental (A) | C57: 2.5 | D57: t | E57: CAPTURA. Cortante del caso A tal como sale del modelo. | F57: Modelo de análisis (STAAD) · tabla de reacciones
... B60: Vy — cortante en dirección Y, carga accidental (A) | C60: 2 | D60: t | E60: CAPTURA. Cortante del caso A tal como sale del modelo. | F60: Modelo de análisis (STAAD) · tabla de reacciones
B62: 6. DADO (PEDESTAL) — para AISLADA y AISLADA_CT
B63: Concepto | C63: Valor | D63: Unidad | E63: Cómo se calcula / de dónde sale | F63: Referencia
B64: cx — lado del dado en X | C64: 0.5 | D64: m | E64: CAPTURA. Si una placa base apoya DIRECTO sobre la zapata, captura el promedio entre el lado de la columna y el de la placa. | F64: ACI 318-19, Tabla 13.2.7.1, págs. 201–202
B65: cy — lado del dado en Y | C65: 0.5 | D65: m | E65: CAPTURA. Mismo criterio. | F65: ACI 318-19, Tabla 13.2.7.1, págs. 201–202
B66: Altura del dado arriba del nivel de terreno | C66: 0.15 | D66: m | E66: CAPTURA. Del nivel de terreno a la cara superior del dado. | F66: Proyecto arquitectónico / estructural
B67: Varilla longitudinal del dado (dovelas) | C67: 6 | D67: # | E67: CAPTURA (lista). Se usa para las dovelas y su desarrollo a compresión. | F67: ACI 318-19, 16.3.4.1 y 25.4.9
B68: db de la varilla del dado | C68: =INDEX(TABLAS!$C$6:$C$13,MATCH($C$67,TABLAS!$B$6:$B$13,0)) -> 1.91 | D68: cm | E68: CALCULADA con la tabla de varillas. | F68: TABLAS, tabla 1
B69: Área de una varilla del dado | C69: =INDEX(TABLAS!$D$6:$D$13,MATCH($C$67,TABLAS!$B$6:$B$13,0)) -> 2.85 | D69: cm² | E69: CALCULADA con la tabla de varillas. | F69: TABLAS, tabla 1
B70: ¿Dónde entrega las reacciones el modelo? | C70: CARA SUPERIOR DEL DADO | D70: — | E70: CAPTURA (lista). Define el brazo con el que el cortante V genera momento: hasta el desplante y hasta la cara de la zapata. | F70: Modelo de análisis (nudo de apoyo)
B72: 7. CARGAS DE SERVICIO DEL MURO, POR METRO — para CORRIDA (al nivel de terreno, sobre el cimiento)
B73: Concepto | C73: Valor | D73: Unidad | E73: Cómo se calcula / de dónde sale | F73: Referencia
B74: w — carga vertical por metro, carga muerta (D) | C74: 5 | D74: t/m | E74: CAPTURA. Si el modelo da reacciones por nudo, divídelas entre el ancho tributario. | F74: Bajada de cargas / modelo de análisis
B75: w — carga vertical por metro, carga viva (L) | C75: 1.5 | D75: t/m | E75: CAPTURA. Si el modelo da reacciones por nudo, divídelas entre el ancho tributario. | F75: Bajada de cargas / modelo de análisis
B76: w — carga vertical por metro, carga accidental (A) | C76: 0.8 | D76: t/m | E76: CAPTURA. Si el modelo da reacciones por nudo, divídelas entre el ancho tributario. | F76: Bajada de cargas / modelo de análisis
B77: Mw — momento por metro (gira alrededor del eje del muro), carga muerta (D) | C77: 0 | D77: t·m/m | E77: CAPTURA. Si el modelo da reacciones por nudo, divídelas entre el ancho tributario. | F77: Bajada de cargas / modelo de análisis
B78: Mw — momento por metro (gira alrededor del eje del muro), carga viva (L) | C78: 0 | D78: t·m/m | E78: CAPTURA. Si el modelo da reacciones por nudo, divídelas entre el ancho tributario. | F78: Bajada de cargas / modelo de análisis
B79: Mw — momento por metro (gira alrededor del eje del muro), carga accidental (A) | C79: 0.3 | D79: t·m/m | E79: CAPTURA. Si el modelo da reacciones por nudo, divídelas entre el ancho tributario. | F79: Bajada de cargas / modelo de análisis
B80: Vw — cortante por metro, perpendicular al muro, carga muerta (D) | C80: 0 | D80: t/m | E80: CAPTURA. Si el modelo da reacciones por nudo, divídelas entre el ancho tributario. | F80: Bajada de cargas / modelo de análisis
B81: Vw — cortante por metro, perpendicular al muro, carga viva (L) | C81: 0 | D81: t/m | E81: CAPTURA. Si el modelo da reacciones por nudo, divídelas entre el ancho tributario. | F81: Bajada de cargas / modelo de análisis
B82: Vw — cortante por metro, perpendicular al muro, carga accidental (A) | C82: 0.4 | D82: t/m | E82: CAPTURA. Si el modelo da reacciones por nudo, divídelas entre el ancho tributario. | F82: Bajada de cargas / modelo de análisis
B84: 8. CONSTANTES DEL REGLAMENTO Y CRITERIOS COMUNES
B85: Concepto | C85: Valor | D85: Unidad | E85: Cómo se calcula / de dónde sale | F85: Referencia
B86: φ flexión (sección controlada por tensión) | C86: 0.9 | D86: — | E86: FIJO. Se verifica εt ≥ εty + 0.003 en cada armado. | F86: ACI 318-19, Tablas 21.2.1(a) y 21.2.2
B87: φ cortante | C87: 0.75 | D87: — | E87: FIJO. | F87: ACI 318-19, Tabla 21.2.1(b)
B88: φ aplastamiento | C88: 0.65 | D88: — | E88: FIJO. | F88: ACI 318-19, Tabla 21.2.1(d)
B89: Conversión 1 MPa | C89: 10.1972 | D89: kg/cm² | E89: FIJO. | F89: Conversión de unidades
B90: ¿Despreciar el factor de tamaño λs en zapatas? | C90: SÍ | D90: — | E90: CAPTURA (lista). El cap. 13 lo permite en zapatas aisladas, corridas y losas; con NO se calcula λs = √(2/(1+0.004d)) ≤ 1. | F90: ACI 318-19, 13.2.6.2, pág. 200 · 22.5.5.1.3
B91: Redondeo de separaciones (hacia abajo) | C91: 2.5 | D91: cm | E91: CAPTURA. Múltiplo al que se redondea la separación calculada. | F91: Práctica de armado
B92: ρ mín — refuerzo mínimo de losas y zapatas (flexión y temperatura) | C92: =IF($C$19<410,0.002,MAX(0.0014,0.0018*420/MAX($C$19,420))) -> 0.0018 | D92: — | E92: CALCULADA con fy en MPa: 0.0020 si fy < 420 MPa; si no, el mayor de 0.0018·420/fy y 0.0014. La varilla grado 42 (4200 kg/cm² = 412 MPa) es el grado 420 del ACI, por eso se acepta como 420 desde 410 MPa. | F92: ACI 318-19, Tablas 7.6.1.1, 8.6.1.1 y 24.4.3.2

Sheet COMBINACIONES
B1: COMBINACIONES DE CARGA — ASCE/SEI 7-16 · ACI 318-19, 5.3
B2: De servicio (S) para presiones contra qa, volteo y deslizamiento (ACI R13.2.6.1, págs. 199–200); de resistencia (U) para cortante, flexión y aplastamiento (ACI 13.2.6.3, pág. 200). Aquí no se captura nada: los factores de A cambian solos con la lista de DATOS.
B4: 1. FACTORES DE CARGA
B5: Clave | C5: Combinación | D5: Uso | E5: γD | F5: γL | G5: γA | H5: signo de P_A | I5: — | J5: Referencia
B6: S1 | C6: ="D + L" -> D + L | D6: Servicio | E6: 1 | F6: 1 | G6: 0 | H6: 1 | I6: — | J6: ASCE 7-16 §2.4.1 comb. 2
B7: S2 | C7: ="D + "&TEXT(IF(DATOS!$C$39="SISMO",0.7,0.6),"0.0##")&IF(DATOS!$C$39="SISMO","E","W") -> D + 0.7E | D7: Servicio | E7: 1 | F7: 0 | G7: =IF(DATOS!$C$39="SISMO",0.7,0.6) -> 0.7 | H7: 1 | I7: — | J7: ASCE 7-16 §2.4.1 comb. 5
B8: S3 | C8: ="D + 0.75L + "&TEXT(IF(DATOS!$C$39="SISMO",0.525,0.45),"0.0##")&IF(DATOS!$C$39="SISMO","E","W") -> D + 0.75L + 0.525E | D8: Servicio | E8: 1 | F8: 0.75 | G8: =IF(DATOS!$C$39="SISMO",0.525,0.45) -> 0.525 | H8: 1 | I8: — | J8: ASCE 7-16 §2.4.1 comb. 6
B9: S4 | C9: ="0.6D + "&TEXT(IF(DATOS!$C$39="SISMO",0.7,0.6),"0.0##")&IF(DATOS!$C$39="SISMO","E","W")&" (P de A suma)" -> 0.6D + 0.7E (P de A suma) | D9: Servicio | E9: 0.6 | F9: 0 | G9: =IF(DATOS!$C$39="SISMO",0.7,0.6) -> 0.7 | H9: 1 | I9: — | J9: ASCE 7-16 §2.4.1 comb. 7 y 8
B10: S5 | C10: ="0.6D + "&TEXT(IF(DATOS!$C$39="SISMO",0.7,0.6),"0.0##")&IF(DATOS!$C$39="SISMO","E","W")&" (P de A resta)" -> 0.6D + 0.7E (P de A resta) | D10: Servicio (levantamiento) | E10: 0.6 | F10: 0 | G10: =IF(DATOS!$C$39="SISMO",0.7,0.6) -> 0.7 | H10: -1 | I10: — | J10: ASCE 7-16 §2.4.1 comb. 7 y 8
B11: U1 | C11: ="1.4D" -> 1.4D | D11: Resistencia | E11: 1.4 | F11: 0 | G11: 0 | H11: 1 | I11: — | J11: ACI 318-19 ec. 5.3.1a
B12: U2 | C12: ="1.2D + 1.6L" -> 1.2D + 1.6L | D12: Resistencia | E12: 1.2 | F12: 1.6 | G12: 0 | H12: 1 | I12: — | J12: ACI 318-19 ec. 5.3.1b
B13: U3 | C13: ="1.2D + "&TEXT(DATOS!$C$40,"0.0")&"L + 1.0"&IF(DATOS!$C$39="SISMO","E","W") -> 1.2D + 1.0L + 1.0E | D13: Resistencia | E13: 1.2 | F13: =DATOS!$C$40 -> 1 | G13: 1 | H13: 1 | I13: — | J13: ACI 318-19 ec. 5.3.1d / 5.3.1e
B14: U4 | C14: ="0.9D + 1.0"&IF(DATOS!$C$39="SISMO","E","W")&" (P de A suma)" -> 0.9D + 1.0E (P de A suma) | D14: Resistencia | E14: 0.9 | F14: 0 | G14: 1 | H14: 1 | I14: — | J14: ACI 318-19 ec. 5.3.1f / 5.3.1g
B15: U5 | C15: ="0.9D + 1.0"&IF(DATOS!$C$39="SISMO","E","W")&" (P de A resta)" -> 0.9D + 1.0E (P de A resta) | D15: Resistencia (levantamiento) | E15: 0.9 | F15: 0 | G15: 1 | H15: -1 | I15: — | J15: ACI 318-19 ec. 5.3.1f / 5.3.1g
B17: 2. CARGAS COMBINADAS EN LA BASE DE LA COLUMNA — para AISLADA y AISLADA_CT (t, t·m)
B18: Clave | C18: Combinación | D18: Uso | E18: P | F18: Mx | G18: My | H18: Vx | I18: Vy | J18: Cómo se calcula
B19: S1 | C19: =C6 -> D + L | D19: =D6 -> Servicio | E19: =E6*DATOS!$C$46+F6*DATOS!$C$47+H6*G6*ABS(DATOS!$C$48) -> 42 | F19: =ABS(E6*DATOS!$C$49+F6*DATOS!$C$50)+G6*ABS(DATOS!$C$51) -> 1.2 | G19: =ABS(E6*DATOS!$C$52+F6*DATOS!$C$53)+G6*ABS(DATOS!$C$54) -> 0.9 | H19: =ABS(E6*DATOS!$C$55+F6*DATOS!$C$56)+G6*ABS(DATOS!$C$57) -> 0.3 | I19: =ABS(E6*DATOS!$C$58+F6*DATOS!$C$59)+G6*ABS(DATOS!$C$60) -> 0.4 | J19: P = γD·PD + γL·PL ± γA·|PA| ; M, V = |γD·D + γL·L| + γA·|A|
B20: S2 | C20: =C7 -> D + 0.7E | D20: =D7 -> Servicio | E20: =E7*DATOS!$C$46+F7*DATOS!$C$47+H7*G7*ABS(DATOS!$C$48) -> 34.2 | F20: =ABS(E7*DATOS!$C$49+F7*DATOS!$C$50)+G7*ABS(DATOS!$C$51) -> 4.65 | G20: =ABS(E7*DATOS!$C$52+F7*DATOS!$C$53)+G7*ABS(DATOS!$C$54) -> 5.15 | H20: =ABS(E7*DATOS!$C$55+F7*DATOS!$C$56)+G7*ABS(DATOS!$C$57) -> 1.95 | I20: =ABS(E7*DATOS!$C$58+F7*DATOS!$C$59)+G7*ABS(DATOS!$C$60) -> 1.7 | J20: P = γD·PD + γL·PL ± γA·|PA| ; M, V = |γD·D + γL·L| + γA·|A|
B21: S3 | C21: =C8 -> D + 0.75L + 0.525E | D21: =D8 -> Servicio | E21: =E8*DATOS!$C$46+F8*DATOS!$C$47+H8*G8*ABS(DATOS!$C$48) -> 42.15 | F21: =ABS(E8*DATOS!$C$49+F8*DATOS!$C$50)+G8*ABS(DATOS!$C$51) -> 3.9875 | G21: =ABS(E8*DATOS!$C$52+F8*DATOS!$C$53)+G8*ABS(DATOS!$C$54) -> 4.2375 | H21: =ABS(E8*DATOS!$C$55+F8*DATOS!$C$56)+G8*ABS(DATOS!$C$57) -> 1.5875 | I21: =ABS(E8*DATOS!$C$58+F8*DATOS!$C$59)+G8*ABS(DATOS!$C$60) -> 1.425 | J21: P = γD·PD + γL·PL ± γA·|PA| ; M, V = |γD·D + γL·L| + γA·|A|
B22: S4 | C22: =C9 -> 0.6D + 0.7E (P de A suma) | D22: =D9 -> Servicio | E22: =E9*DATOS!$C$46+F9*DATOS!$C$47+H9*G9*ABS(DATOS!$C$48) -> 22.2 | F22: =ABS(E9*DATOS!$C$49+F9*DATOS!$C$50)+G9*ABS(DATOS!$C$51) -> 4.33 | G22: =ABS(E9*DATOS!$C$52+F9*DATOS!$C$53)+G9*ABS(DATOS!$C$54) -> 4.91 | H22: =ABS(E9*DATOS!$C$55+F9*DATOS!$C$56)+G9*ABS(DATOS!$C$57) -> 1.87 | I22: =ABS(E9*DATOS!$C$58+F9*DATOS!$C$59)+G9*ABS(DATOS!$C$60) -> 1.58 | J22: P = γD·PD + γL·PL ± γA·|PA| ; M, V = |γD·D + γL·L| + γA·|A|
B23: S5 | C23: =C10 -> 0.6D + 0.7E (P de A resta) | D23: =D10 -> Servicio (levantamiento) | E23: =E10*DATOS!$C$46+F10*DATOS!$C$47+H10*G10*ABS(DATOS!$C$48) -> 13.8 | F23: =ABS(E10*DATOS!$C$49+F10*DATOS!$C$50)+G10*ABS(DATOS!$C$51) -> 4.33 | G23: =ABS(E10*DATOS!$C$52+F10*DATOS!$C$53)+G10*ABS(DATOS!$C$54) -> 4.91 | H23: =ABS(E10*DATOS!$C$55+F10*DATOS!$C$56)+G10*ABS(DATOS!$C$57) -> 1.87 | I23: =ABS(E10*DATOS!$C$58+F10*DATOS!$C$59)+G10*ABS(DATOS!$C$60) -> 1.58 | J23: P = γD·PD + γL·PL ± γA·|PA| ; M, V = |γD·D + γL·L| + γA·|A|
B24: U1 | C24: =C11 -> 1.4D | D24: =D11 -> Resistencia | E24: =E11*DATOS!$C$46+F11*DATOS!$C$47+H11*G11*ABS(DATOS!$C$48) -> 42 | F24: =ABS(E11*DATOS!$C$49+F11*DATOS!$C$50)+G11*ABS(DATOS!$C$51) -> 1.12 | G24: =ABS(E11*DATOS!$C$52+F11*DATOS!$C$53)+G11*ABS(DATOS!$C$54) -> 0.84 | H24: =ABS(E11*DATOS!$C$55+F11*DATOS!$C$56)+G11*ABS(DATOS!$C$57) -> 0.28 | I24: =ABS(E11*DATOS!$C$58+F11*DATOS!$C$59)+G11*ABS(DATOS!$C$60) -> 0.42 | J24: P = γD·PD + γL·PL ± γA·|PA| ; M, V = |γD·D + γL·L| + γA·|A|
B25: U2 | C25: =C12 -> 1.2D + 1.6L | D25: =D12 -> Resistencia | E25: =E12*DATOS!$C$46+F12*DATOS!$C$47+H12*G12*ABS(DATOS!$C$48) -> 55.2 | F25: =ABS(E12*DATOS!$C$49+F12*DATOS!$C$50)+G12*ABS(DATOS!$C$51) -> 1.6 | G25: =ABS(E12*DATOS!$C$52+F12*DATOS!$C$53)+G12*ABS(DATOS!$C$54) -> 1.2 | H25: =ABS(E12*DATOS!$C$55+F12*DATOS!$C$56)+G12*ABS(DATOS!$C$57) -> 0.4 | I25: =ABS(E12*DATOS!$C$58+F12*DATOS!$C$59)+G12*ABS(DATOS!$C$60) -> 0.52 | J25: P = γD·PD + γL·PL ± γA·|PA| ; M, V = |γD·D + γL·L| + γA·|A|
B26: U3 | C26: =C13 -> 1.2D + 1.0L + 1.0E | D26: =D13 -> Resistencia | E26: =E13*DATOS!$C$46+F13*DATOS!$C$47+H13*G13*ABS(DATOS!$C$48) -> 54 | F26: =ABS(E13*DATOS!$C$49+F13*DATOS!$C$50)+G13*ABS(DATOS!$C$51) -> 6.86 | G26: =ABS(E13*DATOS!$C$52+F13*DATOS!$C$53)+G13*ABS(DATOS!$C$54) -> 7.52 | H26: =ABS(E13*DATOS!$C$55+F13*DATOS!$C$56)+G13*ABS(DATOS!$C$57) -> 2.84 | I26: =ABS(E13*DATOS!$C$58+F13*DATOS!$C$59)+G13*ABS(DATOS!$C$60) -> 2.46 | J26: P = γD·PD + γL·PL ± γA·|PA| ; M, V = |γD·D + γL·L| + γA·|A|
B27: U4 | C27: =C14 -> 0.9D + 1.0E (P de A suma) | D27: =D14 -> Resistencia | E27: =E14*DATOS!$C$46+F14*DATOS!$C$47+H14*G14*ABS(DATOS!$C$48) -> 33 | F27: =ABS(E14*DATOS!$C$49+F14*DATOS!$C$50)+G14*ABS(DATOS!$C$51) -> 6.22 | G27: =ABS(E14*DATOS!$C$52+F14*DATOS!$C$53)+G14*ABS(DATOS!$C$54) -> 7.04 | H27: =ABS(E14*DATOS!$C$55+F14*DATOS!$C$56)+G14*ABS(DATOS!$C$57) -> 2.68 | I27: =ABS(E14*DATOS!$C$58+F14*DATOS!$C$59)+G14*ABS(DATOS!$C$60) -> 2.27 | J27: P = γD·PD + γL·PL ± γA·|PA| ; M, V = |γD·D + γL·L| + γA·|A|
B28: U5 | C28: =C15 -> 0.9D + 1.0E (P de A resta) | D28: =D15 -> Resistencia (levantamiento) | E28: =E15*DATOS!$C$46+F15*DATOS!$C$47+H15*G15*ABS(DATOS!$C$48) -> 21 | F28: =ABS(E15*DATOS!$C$49+F15*DATOS!$C$50)+G15*ABS(DATOS!$C$51) -> 6.22 | G28: =ABS(E15*DATOS!$C$52+F15*DATOS!$C$53)+G15*ABS(DATOS!$C$54) -> 7.04 | H28: =ABS(E15*DATOS!$C$55+F15*DATOS!$C$56)+G15*ABS(DATOS!$C$57) -> 2.68 | I28: =ABS(E15*DATOS!$C$58+F15*DATOS!$C$59)+G15*ABS(DATOS!$C$60) -> 2.27 | J28: P = γD·PD + γL·PL ± γA·|PA| ; M, V = |γD·D + γL·L| + γA·|A|
B30: 3. CARGAS COMBINADAS DEL MURO, POR METRO — para CORRIDA (t/m, t·m/m)
B31: Clave | C31: Combinación | D31: Uso | E31: w | F31: Mw | G31: Vw | H31: — | I31: — | J31: Cómo se calcula
B32: S1 | C32: =C6 -> D + L | D32: =D6 -> Servicio | E32: =E6*DATOS!$C$74+F6*DATOS!$C$75+H6*G6*ABS(DATOS!$C$76) -> 6.5 | F32: =ABS(E6*DATOS!$C$77+F6*DATOS!$C$78)+G6*ABS(DATOS!$C$79) -> 0 | G32: =ABS(E6*DATOS!$C$80+F6*DATOS!$C$81)+G6*ABS(DATOS!$C$82) -> 0 | H32: — | I32: — | J32: w = γD·wD + γL·wL ± γA·|wA| ; M, V igual que arriba
B33: S2 | C33: =C7 -> D + 0.7E | D33: =D7 -> Servicio | E33: =E7*DATOS!$C$74+F7*DATOS!$C$75+H7*G7*ABS(DATOS!$C$76) -> 5.56 | F33: =ABS(E7*DATOS!$C$77+F7*DATOS!$C$78)+G7*ABS(DATOS!$C$79) -> 0.21 | G33: =ABS(E7*DATOS!$C$80+F7*DATOS!$C$81)+G7*ABS(DATOS!$C$82) -> 0.28 | H33: — | I33: — | J33: w = γD·wD + γL·wL ± γA·|wA| ; M, V igual que arriba
B34: S3 | C34: =C8 -> D + 0.75L + 0.525E | D34: =D8 -> Servicio | E34: =E8*DATOS!$C$74+F8*DATOS!$C$75+H8*G8*ABS(DATOS!$C$76) -> 6.545 | F34: =ABS(E8*DATOS!$C$77+F8*DATOS!$C$78)+G8*ABS(DATOS!$C$79) -> 0.1575 | G34: =ABS(E8*DATOS!$C$80+F8*DATOS!$C$81)+G8*ABS(DATOS!$C$82) -> 0.21 | H34: — | I34: — | J34: w = γD·wD + γL·wL ± γA·|wA| ; M, V igual que arriba
B35: S4 | C35: =C9 -> 0.6D + 0.7E (P de A suma) | D35: =D9 -> Servicio | E35: =E9*DATOS!$C$74+F9*DATOS!$C$75+H9*G9*ABS(DATOS!$C$76) -> 3.56 | F35: =ABS(E9*DATOS!$C$77+F9*DATOS!$C$78)+G9*ABS(DATOS!$C$79) -> 0.21 | G35: =ABS(E9*DATOS!$C$80+F9*DATOS!$C$81)+G9*ABS(DATOS!$C$82) -> 0.28 | H35: — | I35: — | J35: w = γD·wD + γL·wL ± γA·|wA| ; M, V igual que arriba
B36: S5 | C36: =C10 -> 0.6D + 0.7E (P de A resta) | D36: =D10 -> Servicio (levantamiento) | E36: =E10*DATOS!$C$74+F10*DATOS!$C$75+H10*G10*ABS(DATOS!$C$76) -> 2.44 | F36: =ABS(E10*DATOS!$C$77+F10*DATOS!$C$78)+G10*ABS(DATOS!$C$79) -> 0.21 | G36: =ABS(E10*DATOS!$C$80+F10*DATOS!$C$81)+G10*ABS(DATOS!$C$82) -> 0.28 | H36: — | I36: — | J36: w = γD·wD + γL·wL ± γA·|wA| ; M, V igual que arriba
B37: U1 | C37: =C11 -> 1.4D | D37: =D11 -> Resistencia | E37: =E11*DATOS!$C$74+F11*DATOS!$C$75+H11*G11*ABS(DATOS!$C$76) -> 7 | F37: =ABS(E11*DATOS!$C$77+F11*DATOS!$C$78)+G11*ABS(DATOS!$C$79) -> 0 | G37: =ABS(E11*DATOS!$C$80+F11*DATOS!$C$81)+G11*ABS(DATOS!$C$82) -> 0 | H37: — | I37: — | J37: w = γD·wD + γL·wL ± γA·|wA| ; M, V igual que arriba
B38: U2 | C38: =C12 -> 1.2D + 1.6L | D38: =D12 -> Resistencia | E38: =E12*DATOS!$C$74+F12*DATOS!$C$75+H12*G12*ABS(DATOS!$C$76) -> 8.4 | F38: =ABS(E12*DATOS!$C$77+F12*DATOS!$C$78)+G12*ABS(DATOS!$C$79) -> 0 | G38: =ABS(E12*DATOS!$C$80+F12*DATOS!$C$81)+G12*ABS(DATOS!$C$82) -> 0 | H38: — | I38: — | J38: w = γD·wD + γL·wL ± γA·|wA| ; M, V igual que arriba
B39: U3 | C39: =C13 -> 1.2D + 1.0L + 1.0E | D39: =D13 -> Resistencia | E39: =E13*DATOS!$C$74+F13*DATOS!$C$75+H13*G13*ABS(DATOS!$C$76) -> 8.3 | F39: =ABS(E13*DATOS!$C$77+F13*DATOS!$C$78)+G13*ABS(DATOS!$C$79) -> 0.3 | G39: =ABS(E13*DATOS!$C$80+F13*DATOS!$C$81)+G13*ABS(DATOS!$C$82) -> 0.4 | H39: — | I39: — | J39: w = γD·wD + γL·wL ± γA·|wA| ; M, V igual que arriba
B40: U4 | C40: =C14 -> 0.9D + 1.0E (P de A suma) | D40: =D14 -> Resistencia | E40: =E14*DATOS!$C$74+F14*DATOS!$C$75+H14*G14*ABS(DATOS!$C$76) -> 5.3 | F40: =ABS(E14*DATOS!$C$77+F14*DATOS!$C$78)+G14*ABS(DATOS!$C$79) -> 0.3 | G40: =ABS(E14*DATOS!$C$80+F14*DATOS!$C$81)+G14*ABS(DATOS!$C$82) -> 0.4 | H40: — | I40: — | J40: w = γD·wD + γL·wL ± γA·|wA| ; M, V igual que arriba
B41: U5 | C41: =C15 -> 0.9D + 1.0E (P de A resta) | D41: =D15 -> Resistencia (levantamiento) | E41: =E15*DATOS!$C$74+F15*DATOS!$C$75+H15*G15*ABS(DATOS!$C$76) -> 3.7 | F41: =ABS(E15*DATOS!$C$77+F15*DATOS!$C$78)+G15*ABS(DATOS!$C$79) -> 0.3 | G41: =ABS(E15*DATOS!$C$80+F15*DATOS!$C$81)+G15*ABS(DATOS!$C$82) -> 0.4 | H41: — | I41: — | J41: w = γD·wD + γL·wL ± γA·|wA| ; M, V igual que arriba

Sheet AISLADA
B1: ZAPATA AISLADA — ACI 318-19 | H1: TABLA POR COMBINACIÓN — la memoria (col. B–F) toma de aquí lo que rige
B2: =DATOS!$C$9&" · "&DATOS!$C$10 -> Ejemplo — nave industrial · Columna tipo eje B-2 · muro eje 1 | H2: Cada columna es una combinación de la hoja COMBINACIONES. Bloque S: presiones y estabilidad con la carga TOTAL (incluye zapata, relleno y dado, multiplicados por su γD). Bloque U: diseño estructural con presión NETA (se descuenta el peso de zapata y relleno), ACI 13.2.6.3 y R13.2.6.3.
B3: Se capturan sólo las celdas amarillas de las secciones 1 y 2; cargas, materiales y suelo vienen de DATOS. A la derecha (columnas H a N) está la tabla por combinación de donde salen los valores que rigen.
H4: BLOQUE S — SERVICIO
B5: 1. GEOMETRÍA DE LA ZAPATA | H5: Combinación | I5: =COMBINACIONES!$B$6 -> S1 | J5: =COMBINACIONES!$B$7 -> S2 | K5: =COMBINACIONES!$B$8 -> S3 | L5: =COMBINACIONES!$B$9 -> S4 | M5: =COMBINACIONES!$B$10 -> S5
B6: Concepto | C6: Valor | D6: Unidad | E6: Cómo se calcula / de dónde sale | F6: Referencia | H6: Descripción | I6: =COMBINACIONES!$C$6 -> D + L | J6: =COMBINACIONES!$C$7 -> D + 0.7E | K6: =COMBINACIONES!$C$8 -> D + 0.75L + 0.525E | L6: =COMBINACIONES!$C$9 -> 0.6D + 0.7E (P de A suma) | M6: =COMBINACIONES!$C$10 -> 0.6D + 0.7E (P de A resta)
B7: Lx — lado de la zapata en dirección X | C7: 2.6 | D7: m | E7: CAPTURA. Se ajusta hasta que la presión máxima de la sección 5 quede por debajo de qa. | F7: Propuesta — se verifica en la sección 5 | H7: γD | I7: =COMBINACIONES!$E$6 -> 1 | J7: =COMBINACIONES!$E$7 -> 1 | K7: =COMBINACIONES!$E$8 -> 1 | L7: =COMBINACIONES!$E$9 -> 0.6 | M7: =COMBINACIONES!$E$10 -> 0.6
B8: Ly — lado de la zapata en dirección Y | C8: 2.6 | D8: m | E8: CAPTURA. | F8: Propuesta — se verifica en la sección 5 | H8: γA | I8: =COMBINACIONES!$G$6 -> 0 | J8: =COMBINACIONES!$G$7 -> 0.7 | K8: =COMBINACIONES!$G$8 -> 0.525 | L8: =COMBINACIONES!$G$9 -> 0.7 | M8: =COMBINACIONES!$G$10 -> 0.7
B9: h — peralte total de la zapata | C9: 0.5 | D9: m | E9: CAPTURA. Los mínimos por penetración y por dovelas salen en las secciones 4 y 12. | F9: Propuesta — se verifica en las secciones 6, 9 y 12 | H9: P de la columna | I9: =COMBINACIONES!$E$19 -> 42 | J9: =COMBINACIONES!$E$20 -> 34.2 | K9: =COMBINACIONES!$E$21 -> 42.15 | L9: =COMBINACIONES!$E$22 -> 22.2 | M9: =COMBINACIONES!$E$23 -> 13.8 | N9: t
B10: Df — profundidad de desplante | C10: 1.5 | D10: m | E10: CAPTURA. Del nivel de terreno a la cara inferior de la zapata. | F10: Estudio de mecánica de suelos / proyecto | H10: Mx de la columna | I10: =COMBINACIONES!$F$19 -> 1.2 | J10: =COMBINACIONES!$F$20 -> 4.65 | K10: =COMBINACIONES!$F$21 -> 3.9875 | L10: =COMBINACIONES!$F$22 -> 4.33 | M10: =COMBINACIONES!$F$23 -> 4.33 | N10: t·m
B11: r — recubrimiento libre inferior | C11: 7.5 | D11: cm | E11: CAPTURA. Concreto colado contra el suelo: 75 mm. | F11: ACI 318-19, Tabla 20.5.1.3.1 (ver TABLAS) | H11: My de la columna | I11: =COMBINACIONES!$G$19 -> 0.9 | J11: =COMBINACIONES!$G$20 -> 5.15 | K11: =COMBINACIONES!$G$21 -> 4.2375 | L11: =COMBINACIONES!$G$22 -> 4.91 | M11: =COMBINACIONES!$G$23 -> 4.91 | N11: t·m
B12: r_lat — recubrimiento en las puntas de las varillas | C12: 7.5 | D12: cm | E12: CAPTURA. Caras laterales coladas contra el suelo. | F12: ACI 318-19, Tabla 20.5.1.3.1 | H12: Vx de la columna | I12: =COMBINACIONES!$H$19 -> 0.3 | J12: =COMBINACIONES!$H$20 -> 1.95 | K12: =COMBINACIONES!$H$21 -> 1.5875 | L12: =COMBINACIONES!$H$22 -> 1.87 | M12: =COMBINACIONES!$H$23 -> 1.87 | N12: t
B13: r_sup — recubrimiento superior | C13: 5 | D13: cm | E13: CAPTURA. Cara superior en contacto con el relleno: 50 mm (40 mm para #5 y menores). | F13: ACI 318-19, Tabla 20.5.1.3.1 | H13: Vy de la columna | I13: =COMBINACIONES!$I$19 -> 0.4 | J13: =COMBINACIONES!$I$20 -> 1.7 | K13: =COMBINACIONES!$I$21 -> 1.425 | L13: =COMBINACIONES!$I$22 -> 1.58 | M13: =COMBINACIONES!$I$23 -> 1.58 | N13: t
B14: α — fracción del momento que toma una contratrabe | C14: 0 | D14: — | E14: FIJO = 0. Zapata aislada sin contratrabe: la zapata toma todo el momento. | F14: Tipo de cimentación | H14: γD · ΣW (zapata + relleno + dado) | I14: =I7*$C$54 -> 19.218 | J14: =J7*$C$54 -> 19.218 | K14: =K7*$C$54 -> 19.218 | L14: =L7*$C$54 -> 11.5308 | M14: =M7*$C$54 -> 11.5308 | N14: t
B15: A — área de la zapata | C15: =$C$7*$C$8 -> 6.76 | D15: m² | E15: CALCULADA = Lx · Ly. | F15: Geometría | H15: P total sobre el terreno | I15: =I9+I14 -> 61.218 | J15: =J9+J14 -> 53.418 | K15: =K9+K14 -> 61.368 | L15: =L9+L14 -> 33.7308 | M15: =M9+M14 -> 25.3308 | N15: t
B16: h_rell — relleno sobre la zapata | C16: =$C$10-$C$9 -> 1 | D16: m | E16: CALCULADA = Df − h. | F16: Geometría | H16: Mx en el desplante = (1−α)(Mx + Vy·brazo) | I16: =(1-$C$14)*(I10+I13*$C$18) -> 1.86 | J16: =(1-$C$14)*(J10+J13*$C$18) -> 7.455 | K16: =(1-$C$14)*(K10+K13*$C$18) -> 6.33875 | L16: =(1-$C$14)*(L10+L13*$C$18) -> 6.937 | M16: =(1-$C$14)*(M10+M13*$C$18) -> 6.937 | N16: t·m
B17: H_dado — altura del dado sobre la zapata | C17: =$C$10-$C$9+DATOS!$C$66 -> 1.15 | D17: m | E17: CALCULADA = Df − h + altura del dado sobre el terreno (DATOS). | F17: Geometría | H17: My en el desplante = (1−α)(My + Vx·brazo) | I17: =(1-$C$14)*(I11+I12*$C$18) -> 1.395 | J17: =(1-$C$14)*(J11+J12*$C$18) -> 8.3675 | K17: =(1-$C$14)*(K11+K12*$C$18) -> 6.856875 | L17: =(1-$C$14)*(L11+L12*$C$18) -> 7.9955 | M17: =(1-$C$14)*(M11+M12*$C$18) -> 7.9955 | N17: t·m
B18: Brazo del cortante V hasta el desplante | C18: =IF(DATOS!$C$70="CARA SUPERIOR DEL DADO",$C$17+$C$9,$C$9) -> 1.65 | D18: m | E18: CALCULADA. Del punto donde el modelo entrega la reacción a la cara inferior de la zapata: M_desplante = M + V·brazo. | F18: Estática · DATOS, sección 6 | H18: ex = My / P | I18: =IF(I15>0,I17/I15,99) -> 0.022787415 | J18: =IF(J15>0,J17/J15,99) -> 0.15664196 | K18: =IF(K15>0,K17/K15,99) -> 0.11173372 | L18: =IF(L15>0,L17/L15,99) -> 0.23703855 | M18: =IF(M15>0,M17/M15,99) -> 0.31564341 | N18: m
B19: Brazo del cortante V hasta la cara superior de la zapata | C19: =IF(DATOS!$C$70="CARA SUPERIOR DEL DADO",$C$17,0) -> 1.15 | D19: m | E19: CALCULADA. Sirve para el momento que el dado le transmite a la zapata (penetración) y a la contratrabe. | F19: Estática | H19: ey = Mx / P | I19: =IF(I15>0,I16/I15,99) -> 0.030383221 | J19: =IF(J15>0,J16/J15,99) -> 0.1395597 | K19: =IF(K15>0,K16/K15,99) -> 0.1032908 | L19: =IF(L15>0,L16/L15,99) -> 0.20565774 | M19: =IF(M15>0,M16/M15,99) -> 0.27385633 | N19: m
B20: β — relación lado largo / lado corto | C20: =MAX($C$7,$C$8)/MIN($C$7,$C$8) -> 1 | D20: — | E20: CALCULADA. | F20: ACI 318-19, 13.3.3.3, pág. 204 | H20: Índice de núcleo 6ex/Lx + 6ey/Ly (≤ 1: contacto total) | I20: =6*I18/$C$7+6*I19/$C$8 -> 0.12270147 | J20: =6*J18/$C$7+6*J19/$C$8 -> 0.68354228 | K20: =6*K18/$C$7+6*K19/$C$8 -> 0.49621044 | L20: =6*L18/$C$7+6*L19/$C$8 -> 1.0216068 | M20: =6*M18/$C$7+6*M19/$C$8 -> 1.360384 | N20: —
B21: Ix — momento de inercia de la base (gira alrededor de X) | C21: =$C$7*$C$8^3/12 -> 3.8081333 | D21: m⁴ | E21: CALCULADA = Lx·Ly³/12. | F21: Mecánica de materiales | H21: Kx (factor uniaxial en X) | I21: =IF(I18<=$C$7/6,1+6*I18/$C$7,IF(I18<$C$7/2,4*$C$7/(3*($C$7-2*I18)),999)) -> 1.0525863 | J21: =IF(J18<=$C$7/6,1+6*J18/$C$7,IF(J18<$C$7/2,4*$C$7/(3*($C$7-2*J18)),999)) -> 1.3614814 | K21: =IF(K18<=$C$7/6,1+6*K18/$C$7,IF(K18<$C$7/2,4*$C$7/(3*($C$7-2*K18)),999)) -> 1.257847 | L21: =IF(L18<=$C$7/6,1+6*L18/$C$7,IF(L18<$C$7/2,4*$C$7/(3*($C$7-2*L18)),999)) -> 1.547012 | M21: =IF(M18<=$C$7/6,1+6*M18/$C$7,IF(M18<$C$7/2,4*$C$7/(3*($C$7-2*M18)),999)) -> 1.7284079 | N21: —
B22: Iy — momento de inercia de la base (gira alrededor de Y) | C22: =$C$8*$C$7^3/12 -> 3.8081333 | D22: m⁴ | E22: CALCULADA = Ly·Lx³/12. | F22: Mecánica de materiales | H22: Ky (factor uniaxial en Y) | I22: =IF(I19<=$C$8/6,1+6*I19/$C$8,IF(I19<$C$8/2,4*$C$8/(3*($C$8-2*I19)),999)) -> 1.0701151 | J22: =IF(J19<=$C$8/6,1+6*J19/$C$8,IF(J19<$C$8/2,4*$C$8/(3*($C$8-2*J19)),999)) -> 1.3220608 | K22: =IF(K19<=$C$8/6,1+6*K19/$C$8,IF(K19<$C$8/2,4*$C$8/(3*($C$8-2*K19)),999)) -> 1.2383634 | L22: =IF(L19<=$C$8/6,1+6*L19/$C$8,IF(L19<$C$8/2,4*$C$8/(3*($C$8-2*L19)),999)) -> 1.4745948 | M22: =IF(M19<=$C$8/6,1+6*M19/$C$8,IF(M19<$C$8/2,4*$C$8/(3*($C$8-2*M19)),999)) -> 1.6319762 | N22: —
B23: Sección crítica por flexión, distancia al centro en X | C23: =DATOS!$C$64/2 -> 0.25 | D23: m | E23: CALCULADA = cx/2: en la cara del dado. | F23: ACI 318-19, Tabla 13.2.7.1, págs. 201–202 | H23: q máx | I23: =IF(I15<=0,999,IF(I20<=1,I15/$C$15*(1+I20),MIN(999,I15/$C$15*I21*I22))) -> 10.167091 | J23: =IF(J15<=0,999,IF(J20<=1,J15/$C$15*(1+J20),MIN(999,J15/$C$15*J21*J22))) -> 13.303471 | K23: =IF(K15<=0,999,IF(K20<=1,K15/$C$15*(1+K20),MIN(999,K15/$C$15*K21*K22))) -> 13.582758 | L23: =IF(L15<=0,999,IF(L20<=1,L15/$C$15*(1+L20),MIN(999,L15/$C$15*L21*L22))) -> 11.382727 | M23: =IF(M15<=0,999,IF(M20<=1,M15/$C$15*(1+M20),MIN(999,M15/$C$15*M21*M22))) -> 10.56969 | N23: t/m²
B24: Sección crítica por flexión, distancia al centro en Y | C24: =DATOS!$C$65/2 -> 0.25 | D24: m | E24: CALCULADA = cy/2. | F24: ACI 318-19, Tabla 13.2.7.1, págs. 201–202 | H24: q mín (0 = despegue) | I24: =IF(I15<=0,0,IF(I20<=1,I15/$C$15*(1-I20),0)) -> 7.9447428 | J24: =IF(J15<=0,0,IF(J20<=1,J15/$C$15*(1-J20),0)) -> 2.5006714 | K24: =IF(K15<=0,0,IF(K20<=1,K15/$C$15*(1-K20),0)) -> 4.5734553 | L24: =IF(L15<=0,0,IF(L20<=1,L15/$C$15*(1-L20),0)) -> 0 | M24: =IF(M15<=0,0,IF(M20<=1,M15/$C$15*(1-M20),0)) -> 0 | N24: t/m²
B25: Volado en X desde la cara del dado | C25: =$C$7/2-$C$23 -> 1.05 | D25: m | E25: CALCULADA = (Lx − cx)/2. | F25: Geometría | H25: Contacto | I25: =IF(I20<=1,"TOTAL","PARCIAL") -> TOTAL | J25: =IF(J20<=1,"TOTAL","PARCIAL") -> TOTAL | K25: =IF(K20<=1,"TOTAL","PARCIAL") -> TOTAL | L25: =IF(L20<=1,"TOTAL","PARCIAL") -> PARCIAL | M25: =IF(M20<=1,"TOTAL","PARCIAL") -> PARCIAL
B26: Volado en Y desde la cara del dado | C26: =$C$8/2-$C$24 -> 1.05 | D26: m | E26: CALCULADA = (Ly − cy)/2. | F26: Geometría | H26: q adm (con incremento si hay A) | I26: =DATOS!$C$30*IF(I8>0,DATOS!$C$31,1) -> 18 | J26: =DATOS!$C$30*IF(J8>0,DATOS!$C$31,1) -> 18 | K26: =DATOS!$C$30*IF(K8>0,DATOS!$C$31,1) -> 18 | L26: =DATOS!$C$30*IF(L8>0,DATOS!$C$31,1) -> 18 | M26: =DATOS!$C$30*IF(M8>0,DATOS!$C$31,1) -> 18 | N26: t/m²
B27: ¿La geometría es coherente? | C27: =IF(AND($C$25>0,$C$26>0,$C$16>=0),"CUMPLE","NO CUMPLE — la zapata debe ser mayor que el dado y Df ≥ h") -> CUMPLE | D27: — | E27: Revisa que haya volado en las dos direcciones y que el desplante no quede arriba de la cara superior. | F27: Geometría | H27: q máx / q adm | I27: =I23/I26 -> 0.56483842 | J27: =J23/J26 -> 0.7390817 | K27: =K23/K26 -> 0.75459765 | L27: =L23/L26 -> 0.63237374 | M27: =M23/M26 -> 0.587205 | N27: —
H28: FS volteo X = Lx/(2ex) | I28: =IF(I18>0.0001,$C$7/(2*I18),99) -> 57.049032 | J28: =IF(J18>0.0001,$C$7/(2*J18),99) -> 8.2991814 | K28: =IF(K18>0.0001,$C$7/(2*K18),99) -> 11.634804 | L28: =IF(L18>0.0001,$C$7/(2*L18),99) -> 5.4843399 | M28: =IF(M18>0.0001,$C$7/(2*M18),99) -> 4.1185717 | N28: —
B29: 2. VARILLAS Y PERALTES EFECTIVOS | H29: FS volteo Y = Ly/(2ey) | I29: =IF(I19>0.0001,$C$8/(2*I19),99) -> 42.786774 | J29: =IF(J19>0.0001,$C$8/(2*J19),99) -> 9.3150101 | K29: =IF(K19>0.0001,$C$8/(2*K19),99) -> 12.585825 | L29: =IF(L19>0.0001,$C$8/(2*L19),99) -> 6.3211821 | M29: =IF(M19>0.0001,$C$8/(2*M19),99) -> 4.7470146 | N29: —
B30: Concepto | C30: Valor | D30: Unidad | E30: Cómo se calcula / de dónde sale | F30: Referencia | H30: V horizontal = (1−α)√(Vx²+Vy²) | I30: =(1-$C$14)*SQRT(I12^2+I13^2) -> 0.5 | J30: =(1-$C$14)*SQRT(J12^2+J13^2) -> 2.5869867 | K30: =(1-$C$14)*SQRT(K12^2+K13^2) -> 2.133256 | L30: =(1-$C$14)*SQRT(L12^2+L13^2) -> 2.4481217 | M30: =(1-$C$14)*SQRT(M12^2+M13^2) -> 2.4481217 | N30: t
B31: Varilla del lecho inferior ‖ X (se reparte sobre Ly) | C31: 5 | D31: # | E31: CAPTURA (lista). | F31: Propuesta | H31: FS deslizamiento = μ·P/V | I31: =IF(I30>0.0001,DATOS!$C$33*I15/I30,99) -> 55.0962 | J31: =IF(J30>0.0001,DATOS!$C$33*J15/J30,99) -> 9.2919304 | K31: =IF(K30>0.0001,DATOS!$C$33*K15/K30,99) -> 12.945282 | L31: =IF(L30>0.0001,DATOS!$C$33*L15/L30,99) -> 6.2002064 | M31: =IF(M30>0.0001,DATOS!$C$33*M15/M30,99) -> 4.6561655 | N31: —
B32: Varilla del lecho inferior ‖ Y (se reparte sobre Lx) | C32: 5 | D32: # | E32: CAPTURA (lista). | F32: Propuesta
B33: ¿Qué varillas van hasta abajo? | C33: ‖ X | D33: — | E33: CAPTURA (lista). Conviene abajo la dirección del volado más largo, que es la que tiene más momento. | F33: Práctica de armado | H33: BLOQUE U — RESISTENCIA (cargas factorizadas)
B34: Separación ‖ X que tú fijas (0 = la calcula la hoja) | C34: 0 | D34: cm | E34: CAPTURA. Déjala en 0 para que la hoja proponga la separación; si pones un valor, la hoja la revisa. | F34: Propuesta | H34: Combinación | I34: =COMBINACIONES!$B$11 -> U1 | J34: =COMBINACIONES!$B$12 -> U2 | K34: =COMBINACIONES!$B$13 -> U3 | L34: =COMBINACIONES!$B$14 -> U4 | M34: =COMBINACIONES!$B$15 -> U5
B35: Separación ‖ Y que tú fijas (0 = la calcula la hoja) | C35: 0 | D35: cm | E35: CAPTURA. Mismo criterio. | F35: Propuesta | H35: Descripción | I35: =COMBINACIONES!$C$11 -> 1.4D | J35: =COMBINACIONES!$C$12 -> 1.2D + 1.6L | K35: =COMBINACIONES!$C$13 -> 1.2D + 1.0L + 1.0E | L35: =COMBINACIONES!$C$14 -> 0.9D + 1.0E (P de A suma) | M35: =COMBINACIONES!$C$15 -> 0.9D + 1.0E (P de A resta)
B36: ¿Lleva parrilla superior? | C36: NO | D36: — | E36: CAPTURA (lista). El ACI no la exige en zapatas; se vuelve obligatoria si hay momento negativo por despegue (sección 10). | F36: Práctica · sección 10 de esta hoja | H36: γD | I36: =COMBINACIONES!$E$11 -> 1.4 | J36: =COMBINACIONES!$E$12 -> 1.2 | K36: =COMBINACIONES!$E$13 -> 1.2 | L36: =COMBINACIONES!$E$14 -> 0.9 | M36: =COMBINACIONES!$E$15 -> 0.9
B37: Varilla de la parrilla superior | C37: 4 | D37: # | E37: CAPTURA (lista). Sólo se usa si hay parrilla superior. | F37: Propuesta | H37: Pu de la columna | I37: =COMBINACIONES!$E$24 -> 42 | J37: =COMBINACIONES!$E$25 -> 55.2 | K37: =COMBINACIONES!$E$26 -> 54 | L37: =COMBINACIONES!$E$27 -> 33 | M37: =COMBINACIONES!$E$28 -> 21 | N37: t
B38: db ‖ X | C38: =INDEX(TABLAS!$C$6:$C$13,MATCH($C$31,TABLAS!$B$6:$B$13,0)) -> 1.59 | D38: cm | E38: CALCULADA con la tabla de varillas. | F38: TABLAS, tabla 1 | H38: Mux de la columna | I38: =COMBINACIONES!$F$24 -> 1.12 | J38: =COMBINACIONES!$F$25 -> 1.6 | K38: =COMBINACIONES!$F$26 -> 6.86 | L38: =COMBINACIONES!$F$27 -> 6.22 | M38: =COMBINACIONES!$F$28 -> 6.22 | N38: t·m
B39: Área de una varilla ‖ X | C39: =INDEX(TABLAS!$D$6:$D$13,MATCH($C$31,TABLAS!$B$6:$B$13,0)) -> 1.98 | D39: cm² | E39: CALCULADA con la tabla de varillas. | F39: TABLAS, tabla 1 | H39: Muy de la columna | I39: =COMBINACIONES!$G$24 -> 0.84 | J39: =COMBINACIONES!$G$25 -> 1.2 | K39: =COMBINACIONES!$G$26 -> 7.52 | L39: =COMBINACIONES!$G$27 -> 7.04 | M39: =COMBINACIONES!$G$28 -> 7.04 | N39: t·m
B40: db ‖ Y | C40: =INDEX(TABLAS!$C$6:$C$13,MATCH($C$32,TABLAS!$B$6:$B$13,0)) -> 1.59 | D40: cm | E40: CALCULADA. | F40: TABLAS, tabla 1 | H40: Vux de la columna | I40: =COMBINACIONES!$H$24 -> 0.28 | J40: =COMBINACIONES!$H$25 -> 0.4 | K40: =COMBINACIONES!$H$26 -> 2.84 | L40: =COMBINACIONES!$H$27 -> 2.68 | M40: =COMBINACIONES!$H$28 -> 2.68 | N40: t
B41: Área de una varilla ‖ Y | C41: =INDEX(TABLAS!$D$6:$D$13,MATCH($C$32,TABLAS!$B$6:$B$13,0)) -> 1.98 | D41: cm² | E41: CALCULADA. | F41: TABLAS, tabla 1 | H41: Vuy de la columna | I41: =COMBINACIONES!$I$24 -> 0.42 | J41: =COMBINACIONES!$I$25 -> 0.52 | K41: =COMBINACIONES!$I$26 -> 2.46 | L41: =COMBINACIONES!$I$27 -> 2.27 | M41: =COMBINACIONES!$I$28 -> 2.27 | N41: t
B42: db de la parrilla superior | C42: =INDEX(TABLAS!$C$6:$C$13,MATCH($C$37,TABLAS!$B$6:$B$13,0)) -> 1.27 | D42: cm | E42: CALCULADA. | F42: TABLAS, tabla 1 | H42: Pu sobre la zapata = Pu + γD·W_dado | I42: =I37+I36*$C$53 -> 42.966 | J42: =J37+J36*$C$53 -> 56.028 | K42: =K37+K36*$C$53 -> 54.828 | L42: =L37+L36*$C$53 -> 33.621 | M42: =M37+M36*$C$53 -> 21.621 | N42: t
B43: Área de una varilla de la parrilla superior | C43: =INDEX(TABLAS!$D$6:$D$13,MATCH($C$37,TABLAS!$B$6:$B$13,0)) -> 1.27 | D43: cm² | E43: CALCULADA. | F43: TABLAS, tabla 1 | H43: γD · (W_zap + W_rell) | I43: =I36*($C$51+$C$52) -> 25.9392 | J43: =J36*($C$51+$C$52) -> 22.2336 | K43: =K36*($C$51+$C$52) -> 22.2336 | L43: =L36*($C$51+$C$52) -> 16.6752 | M43: =M36*($C$51+$C$52) -> 16.6752 | N43: t
B44: dx — peralte efectivo de las varillas ‖ X | C44: =$C$9*100-$C$11-IF($C$33="‖ X",$C$38/2,$C$40+$C$38/2) -> 41.705 | D44: cm | E44: CALCULADA = h − r − db/2, restando además el lecho de abajo si ‖ X va encima. | F44: Geometría | H44: w_u = peso factorizado repartido | I44: =I43/$C$15 -> 3.8371598 | J44: =J43/$C$15 -> 3.2889941 | K44: =K43/$C$15 -> 3.2889941 | L44: =L43/$C$15 -> 2.4667456 | M44: =M43/$C$15 -> 2.4667456 | N44: t/m²
B45: dy — peralte efectivo de las varillas ‖ Y | C45: =$C$9*100-$C$11-IF($C$33="‖ Y",$C$40/2,$C$38+$C$40/2) -> 40.115 | D45: cm | E45: CALCULADA con el mismo criterio. | F45: Geometría | H45: P total factorizada | I45: =I42+I43 -> 68.9052 | J45: =J42+J43 -> 78.2616 | K45: =K42+K43 -> 77.0616 | L45: =L42+L43 -> 50.2962 | M45: =M42+M43 -> 38.2962 | N45: t
B46: d_prom — peralte efectivo promedio | C46: =($C$44+$C$45)/2 -> 40.91 | D46: cm | E46: CALCULADA. Es el que se usa en penetración. | F46: Geometría | H46: Mux en el desplante = (1−α)(Mx + Vy·brazo) | I46: =(1-$C$14)*(I38+I41*$C$18) -> 1.813 | J46: =(1-$C$14)*(J38+J41*$C$18) -> 2.458 | K46: =(1-$C$14)*(K38+K41*$C$18) -> 10.919 | L46: =(1-$C$14)*(L38+L41*$C$18) -> 9.9655 | M46: =(1-$C$14)*(M38+M41*$C$18) -> 9.9655 | N46: t·m
B47: ¿El peralte efectivo es de al menos 15 cm? | C47: =IF(MIN($C$44,$C$45)>=15,"CUMPLE","NO CUMPLE — aumentar h") -> CUMPLE | D47: — | E47: El peralte efectivo del refuerzo inferior debe ser de al menos 150 mm. | F47: ACI 318-19, 13.3.1.2, pág. 203 | H47: Muy en el desplante = (1−α)(My + Vx·brazo) | I47: =(1-$C$14)*(I39+I40*$C$18) -> 1.302 | J47: =(1-$C$14)*(J39+J40*$C$18) -> 1.86 | K47: =(1-$C$14)*(K39+K40*$C$18) -> 12.206 | L47: =(1-$C$14)*(L39+L40*$C$18) -> 11.462 | M47: =(1-$C$14)*(M39+M40*$C$18) -> 11.462 | N47: t·m
H48: ex = M/P total | I48: =IF(I45>0,I47/I45,99) -> 0.018895526 | J48: =IF(J45>0,J47/J45,99) -> 0.023766445 | K48: =IF(K45>0,K47/K45,99) -> 0.15839277 | L48: =IF(L45>0,L47/L45,99) -> 0.22788998 | M48: =IF(M45>0,M47/M45,99) -> 0.29929862 | N48: m
B49: 3. PESO DE LA CIMENTACIÓN Y DEL RELLENO (servicio, sin factorizar) | H49: Contacto en X | I49: =IF(I48<=$C$7/6,"TOTAL",IF(I48<$C$7/2,"PARCIAL","INESTABLE")) -> TOTAL | J49: =IF(J48<=$C$7/6,"TOTAL",IF(J48<$C$7/2,"PARCIAL","INESTABLE")) -> TOTAL | K49: =IF(K48<=$C$7/6,"TOTAL",IF(K48<$C$7/2,"PARCIAL","INESTABLE")) -> TOTAL | L49: =IF(L48<=$C$7/6,"TOTAL",IF(L48<$C$7/2,"PARCIAL","INESTABLE")) -> TOTAL | M49: =IF(M48<=$C$7/6,"TOTAL",IF(M48<$C$7/2,"PARCIAL","INESTABLE")) -> TOTAL
B50: Concepto | C50: Valor | D50: Unidad | E50: Cómo se calcula / de dónde sale | F50: Referencia | H50: q total en la orilla cargada (X) | I50: =IF(I48<=$C$7/6,I45/($C$7*$C$8)+I47*($C$7/2)/$C$22,IF(I48<$C$7/2,2*I45/(3*$C$8*($C$7/2-I48)),999)) -> 10.637547 | J50: =IF(J48<=$C$7/6,J45/($C$7*$C$8)+J47*($C$7/2)/$C$22,IF(J48<$C$7/2,2*J45/(3*$C$8*($C$7/2-J48)),999)) -> 12.212117 | K50: =IF(K48<=$C$7/6,K45/($C$7*$C$8)+K47*($C$7/2)/$C$22,IF(K48<$C$7/2,2*K45/(3*$C$8*($C$7/2-K48)),999)) -> 15.566463 | L50: =IF(L48<=$C$7/6,L45/($C$7*$C$8)+L47*($C$7/2)/$C$22,IF(L48<$C$7/2,2*L45/(3*$C$8*($C$7/2-L48)),999)) -> 11.353102 | M50: =IF(M48<=$C$7/6,M45/($C$7*$C$8)+M47*($C$7/2)/$C$22,IF(M48<$C$7/2,2*M45/(3*$C$8*($C$7/2-M48)),999)) -> 9.577954 | N50: t/m²
B51: W_zap — peso de la zapata | C51: =$C$7*$C$8*$C$9*DATOS!$C$24 -> 8.112 | D51: t | E51: CALCULADA = Lx · Ly · h · γc. | F51: Geometría | H51: pendiente de q (X) | I51: =IF(I48<=$C$7/6,I47/$C$22,IF(I48<$C$7/2,I50/(3*($C$7/2-I48)),0)) -> 0.34189979 | J51: =IF(J48<=$C$7/6,J47/$C$22,IF(J48<$C$7/2,J50/(3*($C$7/2-J48)),0)) -> 0.48842828 | K51: =IF(K48<=$C$7/6,K47/$C$22,IF(K48<$C$7/2,K50/(3*($C$7/2-K48)),0)) -> 3.2052449 | L51: =IF(L48<=$C$7/6,L47/$C$22,IF(L48<$C$7/2,L50/(3*($C$7/2-L48)),0)) -> 3.0098736 | M51: =IF(M48<=$C$7/6,M47/$C$22,IF(M48<$C$7/2,M50/(3*($C$7/2-M48)),0)) -> 3.0098736 | N51: t/m³
B52: W_rell — relleno sobre la zapata | C52: =($C$15-DATOS!$C$64*DATOS!$C$65)*$C$16*DATOS!$C$32 -> 10.416 | D52: t | E52: CALCULADA = (A − área del dado) · h_rell · γs. | F52: Geometría | H52: q total al centro (ordenada) | I52: =I50-I51*$C$7/2 -> 10.193077 | J52: =J50-J51*$C$7/2 -> 11.57716 | K52: =K50-K51*$C$7/2 -> 11.399645 | L52: =L50-L51*$C$7/2 -> 7.4402663 | M52: =M50-M51*$C$7/2 -> 5.6651183 | N52: t/m²
B53: W_dado — peso del dado | C53: =DATOS!$C$64*DATOS!$C$65*$C$17*DATOS!$C$24 -> 0.69 | D53: t | E53: CALCULADA = cx · cy · H_dado · γc. | F53: Geometría | H53: inicio del contacto útil para Mu | I53: =IF(I51>0,MAX($C$23,-I52/I51),$C$23) -> 0.25 | J53: =IF(J51>0,MAX($C$23,-J52/J51),$C$23) -> 0.25 | K53: =IF(K51>0,MAX($C$23,-K52/K51),$C$23) -> 0.25 | L53: =IF(L51>0,MAX($C$23,-L52/L51),$C$23) -> 0.25 | M53: =IF(M51>0,MAX($C$23,-M52/M51),$C$23) -> 0.25 | N53: m
B54: ΣW — peso total | C54: =$C$51+$C$52+$C$53 -> 19.218 | D54: t | E54: CALCULADA. En cada combinación se multiplica por su γD (con 0.6D también se reduce el peso propio). | F54: ASCE/SEI 7-16, §2.4.1 | H54: Mu en la cara del dado, varillas ‖ X | I54: =$C$8*IF(I53<$C$7/2,(I52-I51*$C$23)*(($C$7/2)^2-I53^2)/2+I51*(($C$7/2)^3-I53^3)/3-I52*$C$23*($C$7/2-I53),0)-I44*$C$8*$C$25^2/2 -> 9.5751448 | J54: =$C$8*IF(J53<$C$7/2,(J52-J51*$C$23)*(($C$7/2)^2-J53^2)/2+J51*(($C$7/2)^3-J53^3)/3-J52*$C$23*($C$7/2-J53),0)-J44*$C$8*$C$25^2/2 -> 12.544051 | K54: =$C$8*IF(K53<$C$7/2,(K52-K51*$C$23)*(($C$7/2)^2-K53^2)/2+K51*(($C$7/2)^3-K53^3)/3-K52*$C$23*($C$7/2-K53),0)-K44*$C$8*$C$25^2/2 -> 15.988812 | L54: =$C$8*IF(L53<$C$7/2,(L52-L51*$C$23)*(($C$7/2)^2-L53^2)/2+L51*(($C$7/2)^3-L53^3)/3-L52*$C$23*($C$7/2-L53),0)-L44*$C$8*$C$25^2/2 -> 11.226505 | M54: =$C$8*IF(M53<$C$7/2,(M52-M51*$C$23)*(($C$7/2)^2-M53^2)/2+M51*(($C$7/2)^3-M53^3)/3-M52*$C$23*($C$7/2-M53),0)-M44*$C$8*$C$25^2/2 -> 8.6822741 | N54: t·m
H55: sección de cortante (a d de la cara) | I55: =$C$23+$C$44/100 -> 0.66705 | J55: =$C$23+$C$44/100 -> 0.66705 | K55: =$C$23+$C$44/100 -> 0.66705 | L55: =$C$23+$C$44/100 -> 0.66705 | M55: =$C$23+$C$44/100 -> 0.66705 | N55: m
B56: 4. DIMENSIONES MÍNIMAS SUGERIDAS (orientativas — la revisión formal está en las secciones 5 a 12) | H56: inicio del contacto útil para Vu | I56: =IF(I51>0,MAX(I55,-I52/I51),I55) -> 0.66705 | J56: =IF(J51>0,MAX(J55,-J52/J51),J55) -> 0.66705 | K56: =IF(K51>0,MAX(K55,-K52/K51),K55) -> 0.66705 | L56: =IF(L51>0,MAX(L55,-L52/L51),L55) -> 0.66705 | M56: =IF(M51>0,MAX(M55,-M52/M51),M55) -> 0.66705 | N56: m
B57: Concepto | C57: Valor | D57: Unidad | E57: Cómo se calcula / de dónde sale | F57: Referencia | H57: Vu en una dirección, X | I57: =IF(I55>=$C$7/2,0,MAX(0,$C$8*IF(I56<$C$7/2,I52*($C$7/2-I56)+I51*(($C$7/2)^2-I56^2)/2,0)-I44*$C$8*($C$7/2-I55))) -> 11.013127 | J57: =IF(J55>=$C$7/2,0,MAX(0,$C$8*IF(J56<$C$7/2,J52*($C$7/2-J56)+J51*(($C$7/2)^2-J56^2)/2,0)-J44*$C$8*($C$7/2-J55))) -> 14.430135 | K57: =IF(K55>=$C$7/2,0,MAX(0,$C$8*IF(K56<$C$7/2,K52*($C$7/2-K56)+K51*(($C$7/2)^2-K56^2)/2,0)-K44*$C$8*($C$7/2-K55))) -> 18.535328 | L57: =IF(L55>=$C$7/2,0,MAX(0,$C$8*IF(L56<$C$7/2,L52*($C$7/2-L56)+L51*(($C$7/2)^2-L56^2)/2,0)-L44*$C$8*($C$7/2-L55))) -> 13.056428 | M57: =IF(M55>=$C$7/2,0,MAX(0,$C$8*IF(M56<$C$7/2,M52*($C$7/2-M56)+M51*(($C$7/2)^2-M56^2)/2,0)-M44*$C$8*($C$7/2-M55))) -> 10.13512 | N57: t
B58: q_neta — capacidad que queda para la columna | C58: =DATOS!$C$30-($C$9*DATOS!$C$24+$C$16*DATOS!$C$32) -> 15.2 | D58: t/m² | E58: CALCULADA = qa − (h·γc + h_rell·γs). Es la parte de qa que no se gasta en el peso propio. | F58: Bowles 5ª ed., §8.2, pág. 404 | H58: fin del contacto en el lado ligero | I58: =IF(I51>0,MIN($C$7/2,I52/I51),$C$7/2) -> 1.3 | J58: =IF(J51>0,MIN($C$7/2,J52/J51),$C$7/2) -> 1.3 | K58: =IF(K51>0,MIN($C$7/2,K52/K51),$C$7/2) -> 1.3 | L58: =IF(L51>0,MIN($C$7/2,L52/L51),$C$7/2) -> 1.3 | M58: =IF(M51>0,MIN($C$7/2,M52/M51),$C$7/2) -> 1.3 | N58: m
B59: P de servicio S1 + peso del dado | C59: =COMBINACIONES!$E$19+$C$53 -> 42.69 | D59: t | E59: CALCULADA = P(D + L) de COMBINACIONES + W_dado. | F59: COMBINACIONES, sección 2 | H59: M con tensión arriba, lado ligero ‖ X | I59: =I44*$C$8*$C$25^2/2-$C$8*IF(I58>$C$23,(I52+I51*$C$23)*(I58^2-$C$23^2)/2-I51*(I58^3-$C$23^3)/3-I52*$C$23*(I58-$C$23),0) -> -8.6440918 | J59: =J44*$C$8*$C$25^2/2-$C$8*IF(J58>$C$23,(J52+J51*$C$23)*(J58^2-$C$23^2)/2-J51*(J58^3-$C$23^3)/3-J52*$C$23*(J58-$C$23),0) -> -11.213976 | K59: =K44*$C$8*$C$25^2/2-$C$8*IF(K58>$C$23,(K52+K51*$C$23)*(K58^2-$C$23^2)/2-K51*(K58^3-$C$23^3)/3-K52*$C$23*(K58-$C$23),0) -> -7.260369 | L59: =L44*$C$8*$C$25^2/2-$C$8*IF(L58>$C$23,(L52+L51*$C$23)*(L58^2-$C$23^2)/2-L51*(L58^3-$C$23^3)/3-L52*$C$23*(L58-$C$23),0) -> -3.0300923 | M59: =M44*$C$8*$C$25^2/2-$C$8*IF(M58>$C$23,(M52+M51*$C$23)*(M58^2-$C$23^2)/2-M51*(M58^3-$C$23^3)/3-M52*$C$23*(M58-$C$23),0) -> -0.48586151 | N59: t·m
B60: Área mínima con carga concéntrica | C60: =IF($C$58>0,$C$59/$C$58,999) -> 2.8085526 | D60: m² | E60: CALCULADA = P / q_neta. | F60: ACI 318-19, 13.3.1.1, pág. 203 | H60: ey = M/P total | I60: =IF(I45>0,I46/I45,99) -> 0.026311512 | J60: =IF(J45>0,J46/J45,99) -> 0.031407485 | K60: =IF(K45>0,K46/K45,99) -> 0.14169184 | L60: =IF(L45>0,L46/L45,99) -> 0.19813624 | M60: =IF(M45>0,M46/M45,99) -> 0.26022164 | N60: m
B61: Lado mínimo si fuera cuadrada | C61: =SQRT($C$60) -> 1.6758737 | D61: m | E61: CALCULADA = √A. Con momento se necesita más: eso lo dice la sección 5. | F61: Geometría | H61: Contacto en Y | I61: =IF(I60<=$C$8/6,"TOTAL",IF(I60<$C$8/2,"PARCIAL","INESTABLE")) -> TOTAL | J61: =IF(J60<=$C$8/6,"TOTAL",IF(J60<$C$8/2,"PARCIAL","INESTABLE")) -> TOTAL | K61: =IF(K60<=$C$8/6,"TOTAL",IF(K60<$C$8/2,"PARCIAL","INESTABLE")) -> TOTAL | L61: =IF(L60<=$C$8/6,"TOTAL",IF(L60<$C$8/2,"PARCIAL","INESTABLE")) -> TOTAL | M61: =IF(M60<=$C$8/6,"TOTAL",IF(M60<$C$8/2,"PARCIAL","INESTABLE")) -> TOTAL
B62: ¿El área capturada alcanza para la carga concéntrica? | C62: =IF($C$15>=$C$60,"CUMPLE","NO CUMPLE — aumentar Lx · Ly") -> CUMPLE | D62: — | E62: Sólo es un primer filtro. | F62: ACI 318-19, 13.3.1.1, pág. 203 | H62: q total en la orilla cargada (Y) | I62: =IF(I60<=$C$8/6,I45/($C$8*$C$7)+I46*($C$8/2)/$C$21,IF(I60<$C$8/2,2*I45/(3*$C$7*($C$8/2-I60)),999)) -> 10.811989 | J62: =IF(J60<=$C$8/6,J45/($C$8*$C$7)+J46*($C$8/2)/$C$21,IF(J60<$C$8/2,2*J45/(3*$C$7*($C$8/2-J60)),999)) -> 12.416259 | K62: =IF(K60<=$C$8/6,K45/($C$8*$C$7)+K46*($C$8/2)/$C$21,IF(K60<$C$8/2,2*K45/(3*$C$7*($C$8/2-K60)),999)) -> 15.127114 | L62: =IF(L60<=$C$8/6,L45/($C$8*$C$7)+L46*($C$8/2)/$C$21,IF(L60<$C$8/2,2*L45/(3*$C$7*($C$8/2-L60)),999)) -> 10.842235 | M62: =IF(M60<=$C$8/6,M45/($C$8*$C$7)+M46*($C$8/2)/$C$21,IF(M60<$C$8/2,2*M45/(3*$C$7*($C$8/2-M60)),999)) -> 9.0670869 | N62: t/m²
B63: φ·vc de penetración pasado a t/m² (λs = 1) | C63: =DATOS!$C$87*0.33*DATOS!$C$23*DATOS!$C$17*DATOS!$C$89*10 -> 124.96422 | D63: t/m² | E63: CALCULADA = φ · 0.33 λ √f'c [MPa] → kg/cm² → t/m². | F63: ACI 318-19, Tabla 22.6.5.2(a) | H63: pendiente de q (Y) | I63: =IF(I60<=$C$8/6,I46/$C$21,IF(I60<$C$8/2,I62/(3*($C$8/2-I60)),0)) -> 0.47608627 | J63: =IF(J60<=$C$8/6,J46/$C$21,IF(J60<$C$8/2,J62/(3*($C$8/2-J60)),0)) -> 0.64546059 | K63: =IF(K60<=$C$8/6,K46/$C$21,IF(K60<$C$8/2,K62/(3*($C$8/2-K60)),0)) -> 2.8672841 | L63: =IF(L60<=$C$8/6,L46/$C$21,IF(L60<$C$8/2,L62/(3*($C$8/2-L60)),0)) -> 2.6168989 | M63: =IF(M60<=$C$8/6,M46/$C$21,IF(M60<$C$8/2,M62/(3*($C$8/2-M60)),0)) -> 2.6168989 | N63: t/m³
B64: Pu máxima (con peso del dado) | C64: =MAX($I$42:$M$42) -> 56.028 | D64: t | E64: CALCULADA = máximo de la tabla por combinación. | F64: Tabla por combinación (col. H–N) | H64: q total al centro (ordenada) | I64: =I62-I63*$C$8/2 -> 10.193077 | J64: =J62-J63*$C$8/2 -> 11.57716 | K64: =K62-K63*$C$8/2 -> 11.399645 | L64: =L62-L63*$C$8/2 -> 7.4402663 | M64: =M62-M63*$C$8/2 -> 5.6651183 | N64: t/m²
B65: d mínimo por penetración (carga concéntrica) | C65: =100*(-(2*$C$63+$C$64/$C$15)*(DATOS!$C$64+DATOS!$C$65)+SQRT(((2*$C$63+$C$64/$C$15)*(DATOS!$C$64+DATOS!$C$65))^2-4*(4*$C$63+$C$64/$C$15)*($C$64/$C$15*DATOS!$C$64*DATOS!$C$65-$C$64)))/(2*(4*$C$63+$C$64/$C$15)) -> 15.912648 | D65: cm | E65: CALCULADA despejando d de Pu(1 − (cx+d)(cy+d)/A) = φvc·2(cx+cy+2d)·d. Sin momento: el valor formal sale en la sección 6. | F65: ACI 318-19, 22.6.4.1 y Tabla 22.6.5.2 | H65: inicio del contacto útil para Mu | I65: =IF(I63>0,MAX($C$24,-I64/I63),$C$24) -> 0.25 | J65: =IF(J63>0,MAX($C$24,-J64/J63),$C$24) -> 0.25 | K65: =IF(K63>0,MAX($C$24,-K64/K63),$C$24) -> 0.25 | L65: =IF(L63>0,MAX($C$24,-L64/L63),$C$24) -> 0.25 | M65: =IF(M63>0,MAX($C$24,-M64/M63),$C$24) -> 0.25 | N65: m
B66: h mínimo sugerido por penetración | C66: =$C$65+$C$11+MAX($C$38,$C$40) -> 25.002648 | D66: cm | E66: CALCULADA = d_mín + r + db. | F66: Geometría | H66: Mu en la cara del dado, varillas ‖ Y | I66: =$C$7*IF(I65<$C$8/2,(I64-I63*$C$24)*(($C$8/2)^2-I65^2)/2+I63*(($C$8/2)^3-I65^3)/3-I64*$C$24*($C$8/2-I65),0)-I44*$C$7*$C$26^2/2 -> 9.7578514 | J66: =$C$7*IF(J65<$C$8/2,(J64-J63*$C$24)*(($C$8/2)^2-J65^2)/2+J63*(($C$8/2)^3-J65^3)/3-J64*$C$24*($C$8/2-J65),0)-J44*$C$7*$C$26^2/2 -> 12.757865 | K66: =$C$7*IF(K65<$C$8/2,(K64-K63*$C$24)*(($C$8/2)^2-K65^2)/2+K63*(($C$8/2)^3-K65^3)/3-K64*$C$24*($C$8/2-K65),0)-K44*$C$7*$C$26^2/2 -> 15.528649 | L66: =$C$7*IF(L65<$C$8/2,(L64-L63*$C$24)*(($C$8/2)^2-L65^2)/2+L63*(($C$8/2)^3-L65^3)/3-L64*$C$24*($C$8/2-L65),0)-L44*$C$7*$C$26^2/2 -> 10.691435 | M66: =$C$7*IF(M65<$C$8/2,(M64-M63*$C$24)*(($C$8/2)^2-M65^2)/2+M63*(($C$8/2)^3-M65^3)/3-M64*$C$24*($C$8/2-M65),0)-M44*$C$7*$C$26^2/2 -> 8.1472046 | N66: t·m
H67: sección de cortante (a d de la cara) | I67: =$C$24+$C$45/100 -> 0.65115 | J67: =$C$24+$C$45/100 -> 0.65115 | K67: =$C$24+$C$45/100 -> 0.65115 | L67: =$C$24+$C$45/100 -> 0.65115 | M67: =$C$24+$C$45/100 -> 0.65115 | N67: m
B68: 5. PRESIONES DE SERVICIO, VOLTEO Y DESLIZAMIENTO (sale de la tabla por combinación, bloque S) | H68: inicio del contacto útil para Vu | I68: =IF(I63>0,MAX(I67,-I64/I63),I67) -> 0.65115 | J68: =IF(J63>0,MAX(J67,-J64/J63),J67) -> 0.65115 | K68: =IF(K63>0,MAX(K67,-K64/K63),K67) -> 0.65115 | L68: =IF(L63>0,MAX(L67,-L64/L63),L67) -> 0.65115 | M68: =IF(M63>0,MAX(M67,-M64/M63),M67) -> 0.65115 | N68: m
B69: Concepto | C69: Valor | D69: Unidad | E69: Cómo se calcula / de dónde sale | F69: Referencia | H69: Vu en una dirección, Y | I69: =IF(I67>=$C$8/2,0,MAX(0,$C$7*IF(I68<$C$8/2,I64*($C$8/2-I68)+I63*(($C$8/2)^2-I68^2)/2,0)-I44*$C$7*($C$8/2-I67))) -> 11.506041 | J69: =IF(J67>=$C$8/2,0,MAX(0,$C$7*IF(J68<$C$8/2,J64*($C$8/2-J68)+J63*(($C$8/2)^2-J68^2)/2,0)-J44*$C$7*($C$8/2-J67))) -> 15.044521 | K69: =IF(K67>=$C$8/2,0,MAX(0,$C$7*IF(K68<$C$8/2,K64*($C$8/2-K68)+K63*(($C$8/2)^2-K68^2)/2,0)-K44*$C$7*($C$8/2-K67))) -> 18.401739 | L69: =IF(L67>=$C$8/2,0,MAX(0,$C$7*IF(L68<$C$8/2,L64*($C$8/2-L68)+L63*(($C$8/2)^2-L68^2)/2,0)-L44*$C$7*($C$8/2-L67))) -> 12.697284 | M69: =IF(M67>=$C$8/2,0,MAX(0,$C$7*IF(M68<$C$8/2,M64*($C$8/2-M68)+M63*(($C$8/2)^2-M68^2)/2,0)-M44*$C$7*($C$8/2-M67))) -> 9.7025916 | N69: t
B70: q_máx — presión máxima de servicio que rige | C70: =MAX($I$23:$M$23) -> 13.582758 | D70: t/m² | E70: CALCULADA. Dentro del núcleo: P/A(1 + 6ex/Lx + 6ey/Ly). Con despegue: P/A·Kx·Ky (producto de los factores uniaxiales, aproximación del lado seguro). | F70: Bowles 5ª ed., §8.10, págs. 449–453 · ACI 318-19, R13.2.6.1, págs. 199–200 | H70: fin del contacto en el lado ligero | I70: =IF(I63>0,MIN($C$8/2,I64/I63),$C$8/2) -> 1.3 | J70: =IF(J63>0,MIN($C$8/2,J64/J63),$C$8/2) -> 1.3 | K70: =IF(K63>0,MIN($C$8/2,K64/K63),$C$8/2) -> 1.3 | L70: =IF(L63>0,MIN($C$8/2,L64/L63),$C$8/2) -> 1.3 | M70: =IF(M63>0,MIN($C$8/2,M64/M63),$C$8/2) -> 1.3 | N70: m
B71: Combinación que da q_máx | C71: =INDEX($I$5:$M$5,MATCH($C$70,$I$23:$M$23,0)) -> S3 | D71: — | E71: CALCULADA. | F71: COMBINACIONES | H71: M con tensión arriba, lado ligero ‖ Y | I71: =I44*$C$7*$C$26^2/2-$C$7*IF(I70>$C$24,(I64+I63*$C$24)*(I70^2-$C$24^2)/2-I63*(I70^3-$C$24^3)/3-I64*$C$24*(I70-$C$24),0) -> -8.4613852 | J71: =J44*$C$7*$C$26^2/2-$C$7*IF(J70>$C$24,(J64+J63*$C$24)*(J70^2-$C$24^2)/2-J63*(J70^3-$C$24^3)/3-J64*$C$24*(J70-$C$24),0) -> -11.000162 | K71: =K44*$C$7*$C$26^2/2-$C$7*IF(K70>$C$24,(K64+K63*$C$24)*(K70^2-$C$24^2)/2-K63*(K70^3-$C$24^3)/3-K64*$C$24*(K70-$C$24),0) -> -7.7205323 | L71: =L44*$C$7*$C$26^2/2-$C$7*IF(L70>$C$24,(L64+L63*$C$24)*(L70^2-$C$24^2)/2-L63*(L70^3-$C$24^3)/3-L64*$C$24*(L70-$C$24),0) -> -3.5651617 | M71: =M44*$C$7*$C$26^2/2-$C$7*IF(M70>$C$24,(M64+M63*$C$24)*(M70^2-$C$24^2)/2-M63*(M70^3-$C$24^3)/3-M64*$C$24*(M70-$C$24),0) -> -1.0209309 | N71: t·m
B72: q_máx / q_adm (la más desfavorable) | C72: =MAX($I$27:$M$27) -> 0.75459765 | D72: — | E72: CALCULADA. q_adm = qa, multiplicada por el incremento de DATOS en combinaciones con A. | F72: DATOS, sección 3 | H72: Índice de núcleo con cargas factorizadas | I72: =6*I48/$C$7+6*I60/$C$8 -> 0.10432393 | J72: =6*J48/$C$7+6*J60/$C$8 -> 0.12732445 | K72: =6*K48/$C$7+6*K60/$C$8 -> 0.69250294 | L72: =6*L48/$C$7+6*L60/$C$8 -> 0.98313743 | M72: =6*M48/$C$7+6*M60/$C$8 -> 1.2912006 | N72: —
B73: Presión máxima contra la admisible | C73: =IF($C$72<=1,"CUMPLE","NO CUMPLE — aumentar Lx y/o Ly") -> CUMPLE | D73: — | E73: Compara cada combinación contra su q_adm. | F73: ACI 318-19, 13.3.1.1, pág. 203 | H73: Vu de penetración = Pu(1 − A_crit/A) | I73: =IF(I72<=1,I42*(1-$C$90/$C$15),I42) -> 37.713071 | J73: =IF(J72<=1,J42*(1-$C$90/$C$15),J42) -> 49.178139 | K73: =IF(K72<=1,K42*(1-$C$90/$C$15),K42) -> 48.124849 | L73: =IF(L72<=1,L42*(1-$C$90/$C$15),L42) -> 29.51057 | M73: =IF(M72<=1,M42*(1-$C$90/$C$15),M42) -> 21.621 | N73: t
B74: q_mín — presión mínima (0 = hay despegue) | C74: =MIN($I$24:$M$24) -> 0 | D74: t/m² | E74: CALCULADA. | F74: Bowles 5ª ed., §8.10, pág. 453 | H74: Msc alrededor de X = (1−α)(|Mx| + |Vy|·brazo dado) | I74: =(1-$C$14)*(ABS(I38)+ABS(I41)*$C$19) -> 1.603 | J74: =(1-$C$14)*(ABS(J38)+ABS(J41)*$C$19) -> 2.198 | K74: =(1-$C$14)*(ABS(K38)+ABS(K41)*$C$19) -> 9.689 | L74: =(1-$C$14)*(ABS(L38)+ABS(L41)*$C$19) -> 8.8305 | M74: =(1-$C$14)*(ABS(M38)+ABS(M41)*$C$19) -> 8.8305 | N74: t·m
B75: Con carga sostenida (S1 = D + L), ¿toda la zapata está comprimida? | C75: =IF(INDEX($I$20:$M$20,1)<=1,"CUMPLE — resultante dentro del núcleo central","NO CUMPLE — con D + L no debe haber despegue: aumentar dimensiones") -> CUMPLE — resultante dentro del núcleo central | D75: — | E75: Criterio: 6ex/Lx + 6ey/Ly ≤ 1 con la combinación permanente. | F75: Bowles 5ª ed., §8.10, pág. 453 (e ≤ L/6) | H75: Msc alrededor de Y = (1−α)(|My| + |Vx|·brazo dado) | I75: =(1-$C$14)*(ABS(I39)+ABS(I40)*$C$19) -> 1.162 | J75: =(1-$C$14)*(ABS(J39)+ABS(J40)*$C$19) -> 1.66 | K75: =(1-$C$14)*(ABS(K39)+ABS(K40)*$C$19) -> 10.786 | L75: =(1-$C$14)*(ABS(L39)+ABS(L40)*$C$19) -> 10.122 | M75: =(1-$C$14)*(ABS(M39)+ABS(M40)*$C$19) -> 10.122 | N75: t·m
B76: Combinaciones con contacto parcial (despegue) | C76: =COUNTIF($I$25:$M$25,"PARCIAL") -> 2 | D76: — | E76: CALCULADA. Se aceptan en combinaciones accidentales si cumplen presión, volteo y deslizamiento. | F76: Tabla por combinación | H76: vu máx de penetración | I76: =I73*1000/($C$89*$C$46)+$C$100*I75*100000*($C$87/2)/$C$101+$C$103*I74*100000*($C$88/2)/$C$104 -> 2.76859 | J76: =J73*1000/($C$89*$C$46)+$C$100*J75*100000*($C$87/2)/$C$101+$C$103*J74*100000*($C$88/2)/$C$104 -> 3.6315808 | K76: =K73*1000/($C$89*$C$46)+$C$100*K75*100000*($C$87/2)/$C$101+$C$103*K74*100000*($C$88/2)/$C$104 -> 4.9641507 | L76: =L73*1000/($C$89*$C$46)+$C$100*L75*100000*($C$87/2)/$C$101+$C$103*L74*100000*($C$88/2)/$C$104 -> 3.5843166 | M76: =M73*1000/($C$89*$C$46)+$C$100*M75*100000*($C$87/2)/$C$101+$C$103*M74*100000*($C$88/2)/$C$104 -> 3.0539792 | N76: kg/cm²
B77: P total mínima sobre el terreno | C77: =MIN($I$15:$M$15) -> 25.3308 | D77: t | E77: CALCULADA. | F77: Tabla por combinación
B78: ¿Hay levantamiento neto? | C78: =IF($C$77>0,"CUMPLE — no hay levantamiento","NO CUMPLE — tensión neta: lastrar o anclar") -> CUMPLE — no hay levantamiento | D78: — | E78: La carga total debe quedar a compresión en todas las combinaciones. | F78: ACI 318-19, 13.2.6.1, págs. 199–200
B79: FS al volteo mínimo, dirección X | C79: =MIN($I$28:$M$28) -> 4.1185717 | D79: — | E79: CALCULADA = Lx / (2 ex) = P·(Lx/2) / M. | F79: Bowles 5ª ed., §8.10, pág. 450
B80: FS al volteo mínimo, dirección Y | C80: =MIN($I$29:$M$29) -> 4.7470146 | D80: — | E80: CALCULADA = Ly / (2 ey). | F80: Bowles 5ª ed., §8.10, pág. 450
B81: Revisión por volteo | C81: =IF(MIN($C$79,$C$80)>=DATOS!$C$34,"CUMPLE","NO CUMPLE — aumentar dimensiones o peso") -> CUMPLE | D81: — | E81: Compara contra el FS exigido en DATOS. | F81: ACI 318-19, 13.2.6.1, págs. 199–200
B82: FS al deslizamiento mínimo | C82: =MIN($I$31:$M$31) -> 4.6561655 | D82: — | E82: CALCULADA = μ · P_total / √(Vx² + Vy²). Sin empuje pasivo. | F82: NAVFAC DM 7.02, Tabla 1, pág. 7.2-63
B83: Revisión por deslizamiento | C83: =IF($C$82>=DATOS!$C$35,"CUMPLE","NO CUMPLE — aumentar peso, dentellón o contratrabe") -> CUMPLE | D83: — | E83: Compara contra el FS exigido en DATOS. | F83: ACI 318-19, 13.2.6.1, págs. 199–200
B85: 6. CORTANTE EN DOS DIRECCIONES (PENETRACIÓN) — sección crítica a d/2 del dado
B86: Concepto | C86: Valor | D86: Unidad | E86: Cómo se calcula / de dónde sale | F86: Referencia
B87: b₁ — lado de la sección crítica en X | C87: =DATOS!$C$64*100+$C$46 -> 90.91 | D87: cm | E87: CALCULADA = cx + d. | F87: ACI 318-19, 22.6.4.1
B88: b₂ — lado de la sección crítica en Y | C88: =DATOS!$C$65*100+$C$46 -> 90.91 | D88: cm | E88: CALCULADA = cy + d. | F88: ACI 318-19, 22.6.4.1
B89: b₀ — perímetro crítico | C89: =2*($C$87+$C$88) -> 363.64 | D89: cm | E89: CALCULADA. | F89: ACI 318-19, 22.6.4.1
B90: Área dentro de la sección crítica | C90: =$C$87*$C$88/10000 -> 0.82646281 | D90: m² | E90: CALCULADA. Su reacción no aporta al cortante. | F90: ACI 318-19, 13.2.7.2, pág. 202
B91: β — relación de lados del dado | C91: =MAX(DATOS!$C$64,DATOS!$C$65)/MIN(DATOS!$C$64,DATOS!$C$65) -> 1 | D91: — | E91: CALCULADA. | F91: ACI 318-19, Tabla 22.6.5.2
B92: αs — columna interior | C92: 40 | D92: — | E92: FIJO. La zapata rodea al dado por los 4 lados. | F92: ACI 318-19, Tabla 22.6.5.2 · TABLAS, tabla 5
B93: λs — factor de tamaño | C93: =IF(DATOS!$C$90="SÍ",1,MIN(1,SQRT(2/(1+0.004*$C$46*10)))) -> 1 | D93: — | E93: CALCULADA. Con SÍ en DATOS vale 1 (13.2.6.2); con NO, √(2/(1+0.004d)) con d en mm. | F93: ACI 318-19, 13.2.6.2, pág. 200 · 22.5.5.1.3
B94: vc (a) = 0.33 λs λ √f'c | C94: =0.33*$C$93*DATOS!$C$23*DATOS!$C$17*DATOS!$C$89 -> 16.661896 | D94: kg/cm² | E94: CALCULADA en MPa y pasada a kg/cm². | F94: ACI 318-19, Tabla 22.6.5.2(a)
B95: vc (b) = 0.17 (1 + 2/β) λs λ √f'c | C95: =0.17*(1+2/$C$91)*$C$93*DATOS!$C$23*DATOS!$C$17*DATOS!$C$89 -> 25.750203 | D95: kg/cm² | E95: CALCULADA. | F95: ACI 318-19, Tabla 22.6.5.2(b)
B96: vc (c) = 0.083 (2 + αs d/b₀) λs λ √f'c | C96: =0.083*(2+$C$92*$C$46/$C$89)*$C$93*DATOS!$C$23*DATOS!$C$17*DATOS!$C$89 -> 27.239906 | D96: kg/cm² | E96: CALCULADA. | F96: ACI 318-19, Tabla 22.6.5.2(c)
B97: vc — el menor de los tres | C97: =MIN($C$94,$C$95,$C$96) -> 16.661896 | D97: kg/cm² | E97: CALCULADA. | F97: ACI 318-19, 22.6.5.2
B98: φ vc | C98: =DATOS!$C$87*$C$97 -> 12.496422 | D98: kg/cm² | E98: CALCULADA con φ = 0.75. | F98: ACI 318-19, Tabla 21.2.1(b)
B99: γf para el momento alrededor de Y | C99: =1/(1+2/3*SQRT($C$87/$C$88)) -> 0.6 | D99: — | E99: CALCULADA = 1/(1 + ⅔√(b₁/b₂)). | F99: ACI 318-19, ec. 8.4.2.2.2
B100: γv para el momento alrededor de Y | C100: =1-$C$99 -> 0.4 | D100: — | E100: CALCULADA = 1 − γf. Fracción que se transmite por cortante excéntrico. | F100: ACI 318-19, 8.4.4.2.2
B101: Jc para el momento alrededor de Y | C101: =$C$46*$C$87^3/6+$C$87*$C$46^3/6+$C$46*$C$88*$C$87^2/2 -> 21528880 | D101: cm⁴ | E101: CALCULADA = d b₁³/6 + b₁ d³/6 + d b₂ b₁²/2 (columna interior). | F101: ACI 318-19, R8.4.4.2.3
...

Sheet AISLADA_CT
B1: ZAPATA AISLADA LIGADA CON CONTRATRABES — ACI 318-19 | H1: TABLA POR COMBINACIÓN — la memoria (col. B–F) toma de aquí lo que rige
B2: =DATOS!$C$9&" · "&DATOS!$C$10 -> Ejemplo — nave industrial · Columna tipo eje B-2 · muro eje 1 | H2: Cada columna es una combinación de la hoja COMBINACIONES. Bloque S: presiones y estabilidad con la carga TOTAL (incluye zapata, relleno y dado, multiplicados por su γD). Bloque U: diseño estructural con presión NETA (se descuenta el peso de zapata y relleno), ACI 13.2.6.3 y R13.2.6.3.
B3: Se capturan sólo las celdas amarillas de las secciones 1 y 2 y 13; cargas, materiales y suelo vienen de DATOS. A la derecha (columnas H a N) está la tabla por combinación de donde salen los valores que rigen.
B4: POR QUÉ LA CONTRATRABE: con la columna empotrada en la base, a la zapata le llega momento. La contratrabe liga las zapatas y se lleva la fracción α del momento y del cortante de la base; la zapata queda trabajando casi a carga axial y sale más chica. Con α = 1.00 (práctica usual) la zapata se diseña sólo por carga axial y la contratrabe por todo el momento. | H4: BLOQUE S — SERVICIO
H5: Combinación | I5: =COMBINACIONES!$B$6 -> S1 | J5: =COMBINACIONES!$B$7 -> S2 | K5: =COMBINACIONES!$B$8 -> S3 | L5: =COMBINACIONES!$B$9 -> S4 | M5: =COMBINACIONES!$B$10 -> S5
B6: 1. GEOMETRÍA DE LA ZAPATA | H6: Descripción | I6: =COMBINACIONES!$C$6 -> D + L | J6: =COMBINACIONES!$C$7 -> D + 0.7E | K6: =COMBINACIONES!$C$8 -> D + 0.75L + 0.525E | L6: =COMBINACIONES!$C$9 -> 0.6D + 0.7E (P de A suma) | M6: =COMBINACIONES!$C$10 -> 0.6D + 0.7E (P de A resta)
B7: Concepto | C7: Valor | D7: Unidad | E7: Cómo se calcula / de dónde sale | F7: Referencia | H7: γD | I7: =COMBINACIONES!$E$6 -> 1 | J7: =COMBINACIONES!$E$7 -> 1 | K7: =COMBINACIONES!$E$8 -> 1 | L7: =COMBINACIONES!$E$9 -> 0.6 | M7: =COMBINACIONES!$E$10 -> 0.6
B8: Lx — lado de la zapata en dirección X | C8: 2 | D8: m | E8: CAPTURA. Se ajusta hasta que la presión máxima de la sección 5 quede por debajo de qa. | F8: Propuesta — se verifica en la sección 5 | H8: γA | I8: =COMBINACIONES!$G$6 -> 0 | J8: =COMBINACIONES!$G$7 -> 0.7 | K8: =COMBINACIONES!$G$8 -> 0.525 | L8: =COMBINACIONES!$G$9 -> 0.7 | M8: =COMBINACIONES!$G$10 -> 0.7
B9: Ly — lado de la zapata en dirección Y | C9: 2 | D9: m | E9: CAPTURA. | F9: Propuesta — se verifica en la sección 5 | H9: P de la columna | I9: =COMBINACIONES!$E$19 -> 42 | J9: =COMBINACIONES!$E$20 -> 34.2 | K9: =COMBINACIONES!$E$21 -> 42.15 | L9: =COMBINACIONES!$E$22 -> 22.2 | M9: =COMBINACIONES!$E$23 -> 13.8 | N9: t
B10: h — peralte total de la zapata | C10: 0.5 | D10: m | E10: CAPTURA. Los mínimos por penetración y por dovelas salen en las secciones 4 y 12. | F10: Propuesta — se verifica en las secciones 6, 9 y 12 | H10: Mx de la columna | I10: =COMBINACIONES!$F$19 -> 1.2 | J10: =COMBINACIONES!$F$20 -> 4.65 | K10: =COMBINACIONES!$F$21 -> 3.9875 | L10: =COMBINACIONES!$F$22 -> 4.33 | M10: =COMBINACIONES!$F$23 -> 4.33 | N10: t·m
B11: Df — profundidad de desplante | C11: 1.5 | D11: m | E11: CAPTURA. Del nivel de terreno a la cara inferior de la zapata. | F11: Estudio de mecánica de suelos / proyecto | H11: My de la columna | I11: =COMBINACIONES!$G$19 -> 0.9 | J11: =COMBINACIONES!$G$20 -> 5.15 | K11: =COMBINACIONES!$G$21 -> 4.2375 | L11: =COMBINACIONES!$G$22 -> 4.91 | M11: =COMBINACIONES!$G$23 -> 4.91 | N11: t·m
B12: r — recubrimiento libre inferior | C12: 7.5 | D12: cm | E12: CAPTURA. Concreto colado contra el suelo: 75 mm. | F12: ACI 318-19, Tabla 20.5.1.3.1 (ver TABLAS) | H12: Vx de la columna | I12: =COMBINACIONES!$H$19 -> 0.3 | J12: =COMBINACIONES!$H$20 -> 1.95 | K12: =COMBINACIONES!$H$21 -> 1.5875 | L12: =COMBINACIONES!$H$22 -> 1.87 | M12: =COMBINACIONES!$H$23 -> 1.87 | N12: t
B13: r_lat — recubrimiento en las puntas de las varillas | C13: 7.5 | D13: cm | E13: CAPTURA. Caras laterales coladas contra el suelo. | F13: ACI 318-19, Tabla 20.5.1.3.1 | H13: Vy de la columna | I13: =COMBINACIONES!$I$19 -> 0.4 | J13: =COMBINACIONES!$I$20 -> 1.7 | K13: =COMBINACIONES!$I$21 -> 1.425 | L13: =COMBINACIONES!$I$22 -> 1.58 | M13: =COMBINACIONES!$I$23 -> 1.58 | N13: t
B14: r_sup — recubrimiento superior | C14: 5 | D14: cm | E14: CAPTURA. Cara superior en contacto con el relleno: 50 mm (40 mm para #5 y menores). | F14: ACI 318-19, Tabla 20.5.1.3.1 | H14: γD · ΣW (zapata + relleno + dado) | I14: =I7*$C$55 -> 11.49 | J14: =J7*$C$55 -> 11.49 | K14: =K7*$C$55 -> 11.49 | L14: =L7*$C$55 -> 6.894 | M14: =M7*$C$55 -> 6.894 | N14: t
B15: α — fracción del momento y del cortante de la base que toma la contratrabe | C15: 1 | D15: — | E15: CAPTURA. 1.00 = la contratrabe se lleva todo (práctica usual); con menos, la zapata toma (1 − α). | F15: Criterio de diseño — la contratrabe se revisa en la sección 13 | H15: P total sobre el terreno | I15: =I9+I14 -> 53.49 | J15: =J9+J14 -> 45.69 | K15: =K9+K14 -> 53.64 | L15: =L9+L14 -> 29.094 | M15: =M9+M14 -> 20.694 | N15: t
B16: A — área de la zapata | C16: =$C$8*$C$9 -> 4 | D16: m² | E16: CALCULADA = Lx · Ly. | F16: Geometría | H16: Mx en el desplante = (1−α)(Mx + Vy·brazo) | I16: =(1-$C$15)*(I10+I13*$C$19) -> 0 | J16: =(1-$C$15)*(J10+J13*$C$19) -> 0 | K16: =(1-$C$15)*(K10+K13*$C$19) -> 0 | L16: =(1-$C$15)*(L10+L13*$C$19) -> 0 | M16: =(1-$C$15)*(M10+M13*$C$19) -> 0 | N16: t·m
B17: h_rell — relleno sobre la zapata | C17: =$C$11-$C$10 -> 1 | D17: m | E17: CALCULADA = Df − h. | F17: Geometría | H17: My en el desplante = (1−α)(My + Vx·brazo) | I17: =(1-$C$15)*(I11+I12*$C$19) -> 0 | J17: =(1-$C$15)*(J11+J12*$C$19) -> 0 | K17: =(1-$C$15)*(K11+K12*$C$19) -> 0 | L17: =(1-$C$15)*(L11+L12*$C$19) -> 0 | M17: =(1-$C$15)*(M11+M12*$C$19) -> 0 | N17: t·m
B18: H_dado — altura del dado sobre la zapata | C18: =$C$11-$C$10+DATOS!$C$66 -> 1.15 | D18: m | E18: CALCULADA = Df − h + altura del dado sobre el terreno (DATOS). | F18: Geometría | H18: ex = My / P | I18: =IF(I15>0,I17/I15,99) -> 0 | J18: =IF(J15>0,J17/J15,99) -> 0 | K18: =IF(K15>0,K17/K15,99) -> 0 | L18: =IF(L15>0,L17/L15,99) -> 0 | M18: =IF(M15>0,M17/M15,99) -> 0 | N18: m
B19: Brazo del cortante V hasta el desplante | C19: =IF(DATOS!$C$70="CARA SUPERIOR DEL DADO",$C$18+$C$10,$C$10) -> 1.65 | D19: m | E19: CALCULADA. Del punto donde el modelo entrega la reacción a la cara inferior de la zapata: M_desplante = M + V·brazo. | F19: Estática · DATOS, sección 6 | H19: ey = Mx / P | I19: =IF(I15>0,I16/I15,99) -> 0 | J19: =IF(J15>0,J16/J15,99) -> 0 | K19: =IF(K15>0,K16/K15,99) -> 0 | L19: =IF(L15>0,L16/L15,99) -> 0 | M19: =IF(M15>0,M16/M15,99) -> 0 | N19: m
B20: Brazo del cortante V hasta la cara superior de la zapata | C20: =IF(DATOS!$C$70="CARA SUPERIOR DEL DADO",$C$18,0) -> 1.15 | D20: m | E20: CALCULADA. Sirve para el momento que el dado le transmite a la zapata (penetración) y a la contratrabe. | F20: Estática | H20: Índice de núcleo 6ex/Lx + 6ey/Ly (≤ 1: contacto total) | I20: =6*I18/$C$8+6*I19/$C$9 -> 0 | J20: =6*J18/$C$8+6*J19/$C$9 -> 0 | K20: =6*K18/$C$8+6*K19/$C$9 -> 0 | L20: =6*L18/$C$8+6*L19/$C$9 -> 0 | M20: =6*M18/$C$8+6*M19/$C$9 -> 0 | N20: —
B21: β — relación lado largo / lado corto | C21: =MAX($C$8,$C$9)/MIN($C$8,$C$9) -> 1 | D21: — | E21: CALCULADA. | F21: ACI 318-19, 13.3.3.3, pág. 204 | H21: Kx (factor uniaxial en X) | I21: =IF(I18<=$C$8/6,1+6*I18/$C$8,IF(I18<$C$8/2,4*$C$8/(3*($C$8-2*I18)),999)) -> 1 | J21: =IF(J18<=$C$8/6,1+6*J18/$C$8,IF(J18<$C$8/2,4*$C$8/(3*($C$8-2*J18)),999)) -> 1 | K21: =IF(K18<=$C$8/6,1+6*K18/$C$8,IF(K18<$C$8/2,4*$C$8/(3*($C$8-2*K18)),999)) -> 1 | L21: =IF(L18<=$C$8/6,1+6*L18/$C$8,IF(L18<$C$8/2,4*$C$8/(3*($C$8-2*L18)),999)) -> 1 | M21: =IF(M18<=$C$8/6,1+6*M18/$C$8,IF(M18<$C$8/2,4*$C$8/(3*($C$8-2*M18)),999)) -> 1 | N21: —
B22: Ix — momento de inercia de la base (gira alrededor de X) | C22: =$C$8*$C$9^3/12 -> 1.3333333 | D22: m⁴ | E22: CALCULADA = Lx·Ly³/12. | F22: Mecánica de materiales | H22: Ky (factor uniaxial en Y) | I22: =IF(I19<=$C$9/6,1+6*I19/$C$9,IF(I19<$C$9/2,4*$C$9/(3*($C$9-2*I19)),999)) -> 1 | J22: =IF(J19<=$C$9/6,1+6*J19/$C$9,IF(J19<$C$9/2,4*$C$9/(3*($C$9-2*J19)),999)) -> 1 | K22: =IF(K19<=$C$9/6,1+6*K19/$C$9,IF(K19<$C$9/2,4*$C$9/(3*($C$9-2*K19)),999)) -> 1 | L22: =IF(L19<=$C$9/6,1+6*L19/$C$9,IF(L19<$C$9/2,4*$C$9/(3*($C$9-2*L19)),999)) -> 1 | M22: =IF(M19<=$C$9/6,1+6*M19/$C$9,IF(M19<$C$9/2,4*$C$9/(3*($C$9-2*M19)),999)) -> 1 | N22: —
B23: Iy — momento de inercia de la base (gira alrededor de Y) | C23: =$C$9*$C$8^3/12 -> 1.3333333 | D23: m⁴ | E23: CALCULADA = Ly·Lx³/12. | F23: Mecánica de materiales | H23: q máx | I23: =IF(I15<=0,999,IF(I20<=1,I15/$C$16*(1+I20),MIN(999,I15/$C$16*I21*I22))) -> 13.3725 | J23: =IF(J15<=0,999,IF(J20<=1,J15/$C$16*(1+J20),MIN(999,J15/$C$16*J21*J22))) -> 11.4225 | K23: =IF(K15<=0,999,IF(K20<=1,K15/$C$16*(1+K20),MIN(999,K15/$C$16*K21*K22))) -> 13.41 | L23: =IF(L15<=0,999,IF(L20<=1,L15/$C$16*(1+L20),MIN(999,L15/$C$16*L21*L22))) -> 7.2735 | M23: =IF(M15<=0,999,IF(M20<=1,M15/$C$16*(1+M20),MIN(999,M15/$C$16*M21*M22))) -> 5.1735 | N23: t/m²
B24: Sección crítica por flexión, distancia al centro en X | C24: =DATOS!$C$64/2 -> 0.25 | D24: m | E24: CALCULADA = cx/2: en la cara del dado. | F24: ACI 318-19, Tabla 13.2.7.1, págs. 201–202 | H24: q mín (0 = despegue) | I24: =IF(I15<=0,0,IF(I20<=1,I15/$C$16*(1-I20),0)) -> 13.3725 | J24: =IF(J15<=0,0,IF(J20<=1,J15/$C$16*(1-J20),0)) -> 11.4225 | K24: =IF(K15<=0,0,IF(K20<=1,K15/$C$16*(1-K20),0)) -> 13.41 | L24: =IF(L15<=0,0,IF(L20<=1,L15/$C$16*(1-L20),0)) -> 7.2735 | M24: =IF(M15<=0,0,IF(M20<=1,M15/$C$16*(1-M20),0)) -> 5.1735 | N24: t/m²
B25: Sección crítica por flexión, distancia al centro en Y | C25: =DATOS!$C$65/2 -> 0.25 | D25: m | E25: CALCULADA = cy/2. | F25: ACI 318-19, Tabla 13.2.7.1, págs. 201–202 | H25: Contacto | I25: =IF(I20<=1,"TOTAL","PARCIAL") -> TOTAL | J25: =IF(J20<=1,"TOTAL","PARCIAL") -> TOTAL | K25: =IF(K20<=1,"TOTAL","PARCIAL") -> TOTAL | L25: =IF(L20<=1,"TOTAL","PARCIAL") -> TOTAL | M25: =IF(M20<=1,"TOTAL","PARCIAL") -> TOTAL
B26: Volado en X desde la cara del dado | C26: =$C$8/2-$C$24 -> 0.75 | D26: m | E26: CALCULADA = (Lx − cx)/2. | F26: Geometría | H26: q adm (con incremento si hay A) | I26: =DATOS!$C$30*IF(I8>0,DATOS!$C$31,1) -> 18 | J26: =DATOS!$C$30*IF(J8>0,DATOS!$C$31,1) -> 18 | K26: =DATOS!$C$30*IF(K8>0,DATOS!$C$31,1) -> 18 | L26: =DATOS!$C$30*IF(L8>0,DATOS!$C$31,1) -> 18 | M26: =DATOS!$C$30*IF(M8>0,DATOS!$C$31,1) -> 18 | N26: t/m²
B27: Volado en Y desde la cara del dado | C27: =$C$9/2-$C$25 -> 0.75 | D27: m | E27: CALCULADA = (Ly − cy)/2. | F27: Geometría | H27: q máx / q adm | I27: =I23/I26 -> 0.74291667 | J27: =J23/J26 -> 0.63458333 | K27: =K23/K26 -> 0.745 | L27: =L23/L26 -> 0.40408333 | M27: =M23/M26 -> 0.28741667 | N27: —
B28: ¿La geometría es coherente? | C28: =IF(AND($C$26>0,$C$27>0,$C$17>=0),"CUMPLE","NO CUMPLE — la zapata debe ser mayor que el dado y Df ≥ h") -> CUMPLE | D28: — | E28: Revisa que haya volado en las dos direcciones y que el desplante no quede arriba de la cara superior. | F28: Geometría | H28: FS volteo X = Lx/(2ex) | I28: =IF(I18>0.0001,$C$8/(2*I18),99) -> 99 | J28: =IF(J18>0.0001,$C$8/(2*J18),99) -> 99 | K28: =IF(K18>0.0001,$C$8/(2*K18),99) -> 99 | L28: =IF(L18>0.0001,$C$8/(2*L18),99) -> 99 | M28: =IF(M18>0.0001,$C$8/(2*M18),99) -> 99 | N28: —
H29: FS volteo Y = Ly/(2ey) | I29: =IF(I19>0.0001,$C$9/(2*I19),99) -> 99 | J29: =IF(J19>0.0001,$C$9/(2*J19),99) -> 99 | K29: =IF(K19>0.0001,$C$9/(2*K19),99) -> 99 | L29: =IF(L19>0.0001,$C$9/(2*L19),99) -> 99 | M29: =IF(M19>0.0001,$C$9/(2*M19),99) -> 99 | N29: —
B30: 2. VARILLAS Y PERALTES EFECTIVOS | H30: V horizontal = (1−α)√(Vx²+Vy²) | I30: =(1-$C$15)*SQRT(I12^2+I13^2) -> 0 | J30: =(1-$C$15)*SQRT(J12^2+J13^2) -> 0 | K30: =(1-$C$15)*SQRT(K12^2+K13^2) -> 0 | L30: =(1-$C$15)*SQRT(L12^2+L13^2) -> 0 | M30: =(1-$C$15)*SQRT(M12^2+M13^2) -> 0 | N30: t
B31: Concepto | C31: Valor | D31: Unidad | E31: Cómo se calcula / de dónde sale | F31: Referencia | H31: FS deslizamiento = μ·P/V | I31: =IF(I30>0.0001,DATOS!$C$33*I15/I30,99) -> 99 | J31: =IF(J30>0.0001,DATOS!$C$33*J15/J30,99) -> 99 | K31: =IF(K30>0.0001,DATOS!$C$33*K15/K30,99) -> 99 | L31: =IF(L30>0.0001,DATOS!$C$33*L15/L30,99) -> 99 | M31: =IF(M30>0.0001,DATOS!$C$33*M15/M30,99) -> 99 | N31: —
B32: Varilla del lecho inferior ‖ X (se reparte sobre Ly) | C32: 5 | D32: # | E32: CAPTURA (lista). | F32: Propuesta
B33: Varilla del lecho inferior ‖ Y (se reparte sobre Lx) | C33: 5 | D33: # | E33: CAPTURA (lista). | F33: Propuesta | H33: BLOQUE U — RESISTENCIA (cargas factorizadas)
B34: ¿Qué varillas van hasta abajo? | C34: ‖ X | D34: — | E34: CAPTURA (lista). Conviene abajo la dirección del volado más largo, que es la que tiene más momento. | F34: Práctica de armado | H34: Combinación | I34: =COMBINACIONES!$B$11 -> U1 | J34: =COMBINACIONES!$B$12 -> U2 | K34: =COMBINACIONES!$B$13 -> U3 | L34: =COMBINACIONES!$B$14 -> U4 | M34: =COMBINACIONES!$B$15 -> U5
B35: Separación ‖ X que tú fijas (0 = la calcula la hoja) | C35: 0 | D35: cm | E35: CAPTURA. Déjala en 0 para que la hoja proponga la separación; si pones un valor, la hoja la revisa. | F35: Propuesta | H35: Descripción | I35: =COMBINACIONES!$C$11 -> 1.4D | J35: =COMBINACIONES!$C$12 -> 1.2D + 1.6L | K35: =COMBINACIONES!$C$13 -> 1.2D + 1.0L + 1.0E | L35: =COMBINACIONES!$C$14 -> 0.9D + 1.0E (P de A suma) | M35: =COMBINACIONES!$C$15 -> 0.9D + 1.0E (P de A resta)
B36: Separación ‖ Y que tú fijas (0 = la calcula la hoja) | C36: 0 | D36: cm | E36: CAPTURA. Mismo criterio. | F36: Propuesta | H36: γD | I36: =COMBINACIONES!$E$11 -> 1.4 | J36: =COMBINACIONES!$E$12 -> 1.2 | K36: =COMBINACIONES!$E$13 -> 1.2 | L36: =COMBINACIONES!$E$14 -> 0.9 | M36: =COMBINACIONES!$E$15 -> 0.9
B37: ¿Lleva parrilla superior? | C37: NO | D37: — | E37: CAPTURA (lista). El ACI no la exige en zapatas; se vuelve obligatoria si hay momento negativo por despegue (sección 10). | F37: Práctica · sección 10 de esta hoja | H37: Pu de la columna | I37: =COMBINACIONES!$E$24 -> 42 | J37: =COMBINACIONES!$E$25 -> 55.2 | K37: =COMBINACIONES!$E$26 -> 54 | L37: =COMBINACIONES!$E$27 -> 33 | M37: =COMBINACIONES!$E$28 -> 21 | N37: t
B38: Varilla de la parrilla superior | C38: 4 | D38: # | E38: CAPTURA (lista). Sólo se usa si hay parrilla superior. | F38: Propuesta | H38: Mux de la columna | I38: =COMBINACIONES!$F$24 -> 1.12 | J38: =COMBINACIONES!$F$25 -> 1.6 | K38: =COMBINACIONES!$F$26 -> 6.86 | L38: =COMBINACIONES!$F$27 -> 6.22 | M38: =COMBINACIONES!$F$28 -> 6.22 | N38: t·m
B39: db ‖ X | C39: =INDEX(TABLAS!$C$6:$C$13,MATCH($C$32,TABLAS!$B$6:$B$13,0)) -> 1.59 | D39: cm | E39: CALCULADA con la tabla de varillas. | F39: TABLAS, tabla 1 | H39: Muy de la columna | I39: =COMBINACIONES!$G$24 -> 0.84 | J39: =COMBINACIONES!$G$25 -> 1.2 | K39: =COMBINACIONES!$G$26 -> 7.52 | L39: =COMBINACIONES!$G$27 -> 7.04 | M39: =COMBINACIONES!$G$28 -> 7.04 | N39: t·m
B40: Área de una varilla ‖ X | C40: =INDEX(TABLAS!$D$6:$D$13,MATCH($C$32,TABLAS!$B$6:$B$13,0)) -> 1.98 | D40: cm² | E40: CALCULADA con la tabla de varillas. | F40: TABLAS, tabla 1 | H40: Vux de la columna | I40: =COMBINACIONES!$H$24 -> 0.28 | J40: =COMBINACIONES!$H$25 -> 0.4 | K40: =COMBINACIONES!$H$26 -> 2.84 | L40: =COMBINACIONES!$H$27 -> 2.68 | M40: =COMBINACIONES!$H$28 -> 2.68 | N40: t
B41: db ‖ Y | C41: =INDEX(TABLAS!$C$6:$C$13,MATCH($C$33,TABLAS!$B$6:$B$13,0)) -> 1.59 | D41: cm | E41: CALCULADA. | F41: TABLAS, tabla 1 | H41: Vuy de la columna | I41: =COMBINACIONES!$I$24 -> 0.42 | J41: =COMBINACIONES!$I$25 -> 0.52 | K41: =COMBINACIONES!$I$26 -> 2.46 | L41: =COMBINACIONES!$I$27 -> 2.27 | M41: =COMBINACIONES!$I$28 -> 2.27 | N41: t
B42: Área de una varilla ‖ Y | C42: =INDEX(TABLAS!$D$6:$D$13,MATCH($C$33,TABLAS!$B$6:$B$13,0)) -> 1.98 | D42: cm² | E42: CALCULADA. | F42: TABLAS, tabla 1 | H42: Pu sobre la zapata = Pu + γD·W_dado | I42: =I37+I36*$C$54 -> 42.966 | J42: =J37+J36*$C$54 -> 56.028 | K42: =K37+K36*$C$54 -> 54.828 | L42: =L37+L36*$C$54 -> 33.621 | M42: =M37+M36*$C$54 -> 21.621 | N42: t
B43: db de la parrilla superior | C43: =INDEX(TABLAS!$C$6:$C$13,MATCH($C$38,TABLAS!$B$6:$B$13,0)) -> 1.27 | D43: cm | E43: CALCULADA. | F43: TABLAS, tabla 1 | H43: γD · (W_zap + W_rell) | I43: =I36*($C$52+$C$53) -> 15.12 | J43: =J36*($C$52+$C$53) -> 12.96 | K43: =K36*($C$52+$C$53) -> 12.96 | L43: =L36*($C$52+$C$53) -> 9.72 | M43: =M36*($C$52+$C$53) -> 9.72 | N43: t
B44: Área de una varilla de la parrilla superior | C44: =INDEX(TABLAS!$D$6:$D$13,MATCH($C$38,TABLAS!$B$6:$B$13,0)) -> 1.27 | D44: cm² | E44: CALCULADA. | F44: TABLAS, tabla 1 | H44: w_u = peso factorizado repartido | I44: =I43/$C$16 -> 3.78 | J44: =J43/$C$16 -> 3.24 | K44: =K43/$C$16 -> 3.24 | L44: =L43/$C$16 -> 2.43 | M44: =M43/$C$16 -> 2.43 | N44: t/m²
B45: dx — peralte efectivo de las varillas ‖ X | C45: =$C$10*100-$C$12-IF($C$34="‖ X",$C$39/2,$C$41+$C$39/2) -> 41.705 | D45: cm | E45: CALCULADA = h − r − db/2, restando además el lecho de abajo si ‖ X va encima. | F45: Geometría | H45: P total factorizada | I45: =I42+I43 -> 58.086 | J45: =J42+J43 -> 68.988 | K45: =K42+K43 -> 67.788 | L45: =L42+L43 -> 43.341 | M45: =M42+M43 -> 31.341 | N45: t
B46: dy — peralte efectivo de las varillas ‖ Y | C46: =$C$10*100-$C$12-IF($C$34="‖ Y",$C$41/2,$C$39+$C$41/2) -> 40.115 | D46: cm | E46: CALCULADA con el mismo criterio. | F46: Geometría | H46: Mux en el desplante = (1−α)(Mx + Vy·brazo) | I46: =(1-$C$15)*(I38+I41*$C$19) -> 0 | J46: =(1-$C$15)*(J38+J41*$C$19) -> 0 | K46: =(1-$C$15)*(K38+K41*$C$19) -> 0 | L46: =(1-$C$15)*(L38+L41*$C$19) -> 0 | M46: =(1-$C$15)*(M38+M41*$C$19) -> 0 | N46: t·m
B47: d_prom — peralte efectivo promedio | C47: =($C$45+$C$46)/2 -> 40.91 | D47: cm | E47: CALCULADA. Es el que se usa en penetración. | F47: Geometría | H47: Muy en el desplante = (1−α)(My + Vx·brazo) | I47: =(1-$C$15)*(I39+I40*$C$19) -> 0 | J47: =(1-$C$15)*(J39+J40*$C$19) -> 0 | K47: =(1-$C$15)*(K39+K40*$C$19) -> 0 | L47: =(1-$C$15)*(L39+L40*$C$19) -> 0 | M47: =(1-$C$15)*(M39+M40*$C$19) -> 0 | N47: t·m
B48: ¿El peralte efectivo es de al menos 15 cm? | C48: =IF(MIN($C$45,$C$46)>=15,"CUMPLE","NO CUMPLE — aumentar h") -> CUMPLE | D48: — | E48: El peralte efectivo del refuerzo inferior debe ser de al menos 150 mm. | F48: ACI 318-19, 13.3.1.2, pág. 203 | H48: ex = M/P total | I48: =IF(I45>0,I47/I45,99) -> 0 | J48: =IF(J45>0,J47/J45,99) -> 0 | K48: =IF(K45>0,K47/K45,99) -> 0 | L48: =IF(L45>0,L47/L45,99) -> 0 | M48: =IF(M45>0,M47/M45,99) -> 0 | N48: m
H49: Contacto en X | I49: =IF(I48<=$C$8/6,"TOTAL",IF(I48<$C$8/2,"PARCIAL","INESTABLE")) -> TOTAL | J49: =IF(J48<=$C$8/6,"TOTAL",IF(J48<$C$8/2,"PARCIAL","INESTABLE")) -> TOTAL | K49: =IF(K48<=$C$8/6,"TOTAL",IF(K48<$C$8/2,"PARCIAL","INESTABLE")) -> TOTAL | L49: =IF(L48<=$C$8/6,"TOTAL",IF(L48<$C$8/2,"PARCIAL","INESTABLE")) -> TOTAL | M49: =IF(M48<=$C$8/6,"TOTAL",IF(M48<$C$8/2,"PARCIAL","INESTABLE")) -> TOTAL
B50: 3. PESO DE LA CIMENTACIÓN Y DEL RELLENO (servicio, sin factorizar) | H50: q total en la orilla cargada (X) | I50: =IF(I48<=$C$8/6,I45/($C$8*$C$9)+I47*($C$8/2)/$C$23,IF(I48<$C$8/2,2*I45/(3*$C$9*($C$8/2-I48)),999)) -> 14.5215 | J50: =IF(J48<=$C$8/6,J45/($C$8*$C$9)+J47*($C$8/2)/$C$23,IF(J48<$C$8/2,2*J45/(3*$C$9*($C$8/2-J48)),999)) -> 17.247 | K50: =IF(K48<=$C$8/6,K45/($C$8*$C$9)+K47*($C$8/2)/$C$23,IF(K48<$C$8/2,2*K45/(3*$C$9*($C$8/2-K48)),999)) -> 16.947 | L50: =IF(L48<=$C$8/6,L45/($C$8*$C$9)+L47*($C$8/2)/$C$23,IF(L48<$C$8/2,2*L45/(3*$C$9*($C$8/2-L48)),999)) -> 10.83525 | M50: =IF(M48<=$C$8/6,M45/($C$8*$C$9)+M47*($C$8/2)/$C$23,IF(M48<$C$8/2,2*M45/(3*$C$9*($C$8/2-M48)),999)) -> 7.83525 | N50: t/m²
B51: Concepto | C51: Valor | D51: Unidad | E51: Cómo se calcula / de dónde sale | F51: Referencia | H51: pendiente de q (X) | I51: =IF(I48<=$C$8/6,I47/$C$23,IF(I48<$C$8/2,I50/(3*($C$8/2-I48)),0)) -> 0 | J51: =IF(J48<=$C$8/6,J47/$C$23,IF(J48<$C$8/2,J50/(3*($C$8/2-J48)),0)) -> 0 | K51: =IF(K48<=$C$8/6,K47/$C$23,IF(K48<$C$8/2,K50/(3*($C$8/2-K48)),0)) -> 0 | L51: =IF(L48<=$C$8/6,L47/$C$23,IF(L48<$C$8/2,L50/(3*($C$8/2-L48)),0)) -> 0 | M51: =IF(M48<=$C$8/6,M47/$C$23,IF(M48<$C$8/2,M50/(3*($C$8/2-M48)),0)) -> 0 | N51: t/m³
B52: W_zap — peso de la zapata | C52: =$C$8*$C$9*$C$10*DATOS!$C$24 -> 4.8 | D52: t | E52: CALCULADA = Lx · Ly · h · γc. | F52: Geometría | H52: q total al centro (ordenada) | I52: =I50-I51*$C$8/2 -> 14.5215 | J52: =J50-J51*$C$8/2 -> 17.247 | K52: =K50-K51*$C$8/2 -> 16.947 | L52: =L50-L51*$C$8/2 -> 10.83525 | M52: =M50-M51*$C$8/2 -> 7.83525 | N52: t/m²
B53: W_rell — relleno sobre la zapata | C53: =($C$16-DATOS!$C$64*DATOS!$C$65)*$C$17*DATOS!$C$32 -> 6 | D53: t | E53: CALCULADA = (A − área del dado) · h_rell · γs. | F53: Geometría | H53: inicio del contacto útil para Mu | I53: =IF(I51>0,MAX($C$24,-I52/I51),$C$24) -> 0.25 | J53: =IF(J51>0,MAX($C$24,-J52/J51),$C$24) -> 0.25 | K53: =IF(K51>0,MAX($C$24,-K52/K51),$C$24) -> 0.25 | L53: =IF(L51>0,MAX($C$24,-L52/L51),$C$24) -> 0.25 | M53: =IF(M51>0,MAX($C$24,-M52/M51),$C$24) -> 0.25 | N53: m
B54: W_dado — peso del dado | C54: =DATOS!$C$64*DATOS!$C$65*$C$18*DATOS!$C$24 -> 0.69 | D54: t | E54: CALCULADA = cx · cy · H_dado · γc. | F54: Geometría | H54: Mu en la cara del dado, varillas ‖ X | I54: =$C$9*IF(I53<$C$8/2,(I52-I51*$C$24)*(($C$8/2)^2-I53^2)/2+I51*(($C$8/2)^3-I53^3)/3-I52*$C$24*($C$8/2-I53),0)-I44*$C$9*$C$26^2/2 -> 6.0420938 | J54: =$C$9*IF(J53<$C$8/2,(J52-J51*$C$24)*(($C$8/2)^2-J53^2)/2+J51*(($C$8/2)^3-J53^3)/3-J52*$C$24*($C$8/2-J53),0)-J44*$C$9*$C$26^2/2 -> 7.8789375 | K54: =$C$9*IF(K53<$C$8/2,(K52-K51*$C$24)*(($C$8/2)^2-K53^2)/2+K51*(($C$8/2)^3-K53^3)/3-K52*$C$24*($C$8/2-K53),0)-K44*$C$9*$C$26^2/2 -> 7.7101875 | L54: =$C$9*IF(L53<$C$8/2,(L52-L51*$C$24)*(($C$8/2)^2-L53^2)/2+L51*(($C$8/2)^3-L53^3)/3-L52*$C$24*($C$8/2-L53),0)-L44*$C$9*$C$26^2/2 -> 4.7279531 | M54: =$C$9*IF(M53<$C$8/2,(M52-M51*$C$24)*(($C$8/2)^2-M53^2)/2+M51*(($C$8/2)^3-M53^3)/3-M52*$C$24*($C$8/2-M53),0)-M44*$C$9*$C$26^2/2 -> 3.0404531 | N54: t·m
B55: ΣW — peso total | C55: =$C$52+$C$53+$C$54 -> 11.49 | D55: t | E55: CALCULADA. En cada combinación se multiplica por su γD (con 0.6D también se reduce el peso propio). | F55: ASCE/SEI 7-16, §2.4.1 | H55: sección de cortante (a d de la cara) | I55: =$C$24+$C$45/100 -> 0.66705 | J55: =$C$24+$C$45/100 -> 0.66705 | K55: =$C$24+$C$45/100 -> 0.66705 | L55: =$C$24+$C$45/100 -> 0.66705 | M55: =$C$24+$C$45/100 -> 0.66705 | N55: m
H56: inicio del contacto útil para Vu | I56: =IF(I51>0,MAX(I55,-I52/I51),I55) -> 0.66705 | J56: =IF(J51>0,MAX(J55,-J52/J51),J55) -> 0.66705 | K56: =IF(K51>0,MAX(K55,-K52/K51),K55) -> 0.66705 | L56: =IF(L51>0,MAX(L55,-L52/L51),L55) -> 0.66705 | M56: =IF(M51>0,MAX(M55,-M52/M51),M55) -> 0.66705 | N56: m
B57: 4. DIMENSIONES MÍNIMAS SUGERIDAS (orientativas — la revisión formal está en las secciones 5 a 12) | H57: Vu en una dirección, X | I57: =IF(I55>=$C$8/2,0,MAX(0,$C$9*IF(I56<$C$8/2,I52*($C$8/2-I56)+I51*(($C$8/2)^2-I56^2)/2,0)-I44*$C$9*($C$8/2-I55))) -> 7.1527648 | J57: =IF(J55>=$C$8/2,0,MAX(0,$C$9*IF(J56<$C$8/2,J52*($C$8/2-J56)+J51*(($C$8/2)^2-J56^2)/2,0)-J44*$C$9*($C$8/2-J55))) -> 9.3272613 | K57: =IF(K55>=$C$8/2,0,MAX(0,$C$9*IF(K56<$C$8/2,K52*($C$8/2-K56)+K51*(($C$8/2)^2-K56^2)/2,0)-K44*$C$9*($C$8/2-K55))) -> 9.1274913 | L57: =IF(L55>=$C$8/2,0,MAX(0,$C$9*IF(L56<$C$8/2,L52*($C$8/2-L56)+L51*(($C$8/2)^2-L56^2)/2,0)-L44*$C$9*($C$8/2-L55))) -> 5.597056 | M57: =IF(M55>=$C$8/2,0,MAX(0,$C$9*IF(M56<$C$8/2,M52*($C$8/2-M56)+M51*(($C$8/2)^2-M56^2)/2,0)-M44*$C$9*($C$8/2-M55))) -> 3.599356 | N57: t
B58: Concepto | C58: Valor | D58: Unidad | E58: Cómo se calcula / de dónde sale | F58: Referencia | H58: fin del contacto en el lado ligero | I58: =IF(I51>0,MIN($C$8/2,I52/I51),$C$8/2) -> 1 | J58: =IF(J51>0,MIN($C$8/2,J52/J51),$C$8/2) -> 1 | K58: =IF(K51>0,MIN($C$8/2,K52/K51),$C$8/2) -> 1 | L58: =IF(L51>0,MIN($C$8/2,L52/L51),$C$8/2) -> 1 | M58: =IF(M51>0,MIN($C$8/2,M52/M51),$C$8/2) -> 1 | N58: m
B59: q_neta — capacidad que queda para la columna | C59: =DATOS!$C$30-($C$10*DATOS!$C$24+$C$17*DATOS!$C$32) -> 15.2 | D59: t/m² | E59: CALCULADA = qa − (h·γc + h_rell·γs). Es la parte de qa que no se gasta en el peso propio. | F59: Bowles 5ª ed., §8.2, pág. 404 | H59: M con tensión arriba, lado ligero ‖ X | I59: =I44*$C$9*$C$26^2/2-$C$9*IF(I58>$C$24,(I52+I51*$C$24)*(I58^2-$C$24^2)/2-I51*(I58^3-$C$24^3)/3-I52*$C$24*(I58-$C$24),0) -> -6.0420938 | J59: =J44*$C$9*$C$26^2/2-$C$9*IF(J58>$C$24,(J52+J51*$C$24)*(J58^2-$C$24^2)/2-J51*(J58^3-$C$24^3)/3-J52*$C$24*(J58-$C$24),0) -> -7.8789375 | K59: =K44*$C$9*$C$26^2/2-$C$9*IF(K58>$C$24,(K52+K51*$C$24)*(K58^2-$C$24^2)/2-K51*(K58^3-$C$24^3)/3-K52*$C$24*(K58-$C$24),0) -> -7.7101875 | L59: =L44*$C$9*$C$26^2/2-$C$9*IF(L58>$C$24,(L52+L51*$C$24)*(L58^2-$C$24^2)/2-L51*(L58^3-$C$24^3)/3-L52*$C$24*(L58-$C$24),0) -> -4.7279531 | M59: =M44*$C$9*$C$26^2/2-$C$9*IF(M58>$C$24,(M52+M51*$C$24)*(M58^2-$C$24^2)/2-M51*(M58^3-$C$24^3)/3-M52*$C$24*(M58-$C$24),0) -> -3.0404531 | N59: t·m
B60: P de servicio S1 + peso del dado | C60: =COMBINACIONES!$E$19+$C$54 -> 42.69 | D60: t | E60: CALCULADA = P(D + L) de COMBINACIONES + W_dado. | F60: COMBINACIONES, sección 2 | H60: ey = M/P total | I60: =IF(I45>0,I46/I45,99) -> 0 | J60: =IF(J45>0,J46/J45,99) -> 0 | K60: =IF(K45>0,K46/K45,99) -> 0 | L60: =IF(L45>0,L46/L45,99) -> 0 | M60: =IF(M45>0,M46/M45,99) -> 0 | N60: m
B61: Área mínima con carga concéntrica | C61: =IF($C$59>0,$C$60/$C$59,999) -> 2.8085526 | D61: m² | E61: CALCULADA = P / q_neta. | F61: ACI 318-19, 13.3.1.1, pág. 203 | H61: Contacto en Y | I61: =IF(I60<=$C$9/6,"TOTAL",IF(I60<$C$9/2,"PARCIAL","INESTABLE")) -> TOTAL | J61: =IF(J60<=$C$9/6,"TOTAL",IF(J60<$C$9/2,"PARCIAL","INESTABLE")) -> TOTAL | K61: =IF(K60<=$C$9/6,"TOTAL",IF(K60<$C$9/2,"PARCIAL","INESTABLE")) -> TOTAL | L61: =IF(L60<=$C$9/6,"TOTAL",IF(L60<$C$9/2,"PARCIAL","INESTABLE")) -> TOTAL | M61: =IF(M60<=$C$9/6,"TOTAL",IF(M60<$C$9/2,"PARCIAL","INESTABLE")) -> TOTAL
B62: Lado mínimo si fuera cuadrada | C62: =SQRT($C$61) -> 1.6758737 | D62: m | E62: CALCULADA = √A. Con momento se necesita más: eso lo dice la sección 5. | F62: Geometría | H62: q total en la orilla cargada (Y) | I62: =IF(I60<=$C$9/6,I45/($C$9*$C$8)+I46*($C$9/2)/$C$22,IF(I60<$C$9/2,2*I45/(3*$C$8*($C$9/2-I60)),999)) -> 14.5215 | J62: =IF(J60<=$C$9/6,J45/($C$9*$C$8)+J46*($C$9/2)/$C$22,IF(J60<$C$9/2,2*J45/(3*$C$8*($C$9/2-J60)),999)) -> 17.247 | K62: =IF(K60<=$C$9/6,K45/($C$9*$C$8)+K46*($C$9/2)/$C$22,IF(K60<$C$9/2,2*K45/(3*$C$8*($C$9/2-K60)),999)) -> 16.947 | L62: =IF(L60<=$C$9/6,L45/($C$9*$C$8)+L46*($C$9/2)/$C$22,IF(L60<$C$9/2,2*L45/(3*$C$8*($C$9/2-L60)),999)) -> 10.83525 | M62: =IF(M60<=$C$9/6,M45/($C$9*$C$8)+M46*($C$9/2)/$C$22,IF(M60<$C$9/2,2*M45/(3*$C$8*($C$9/2-M60)),999)) -> 7.83525 | N62: t/m²
B63: ¿El área capturada alcanza para la carga concéntrica? | C63: =IF($C$16>=$C$61,"CUMPLE","NO CUMPLE — aumentar Lx · Ly") -> CUMPLE | D63: — | E63: Sólo es un primer filtro. | F63: ACI 318-19, 13.3.1.1, pág. 203 | H63: pendiente de q (Y) | I63: =IF(I60<=$C$9/6,I46/$C$22,IF(I60<$C$9/2,I62/(3*($C$9/2-I60)),0)) -> 0 | J63: =IF(J60<=$C$9/6,J46/$C$22,IF(J60<$C$9/2,J62/(3*($C$9/2-J60)),0)) -> 0 | K63: =IF(K60<=$C$9/6,K46/$C$22,IF(K60<$C$9/2,K62/(3*($C$9/2-K60)),0)) -> 0 | L63: =IF(L60<=$C$9/6,L46/$C$22,IF(L60<$C$9/2,L62/(3*($C$9/2-L60)),0)) -> 0 | M63: =IF(M60<=$C$9/6,M46/$C$22,IF(M60<$C$9/2,M62/(3*($C$9/2-M60)),0)) -> 0 | N63: t/m³
B64: φ·vc de penetración pasado a t/m² (λs = 1) | C64: =DATOS!$C$87*0.33*DATOS!$C$23*DATOS!$C$17*DATOS!$C$89*10 -> 124.96422 | D64: t/m² | E64: CALCULADA = φ · 0.33 λ √f'c [MPa] → kg/cm² → t/m². | F64: ACI 318-19, Tabla 22.6.5.2(a) | H64: q total al centro (ordenada) | I64: =I62-I63*$C$9/2 -> 14.5215 | J64: =J62-J63*$C$9/2 -> 17.247 | K64: =K62-K63*$C$9/2 -> 16.947 | L64: =L62-L63*$C$9/2 -> 10.83525 | M64: =M62-M63*$C$9/2 -> 7.83525 | N64: t/m²
B65: Pu máxima (con peso del dado) | C65: =MAX($I$42:$M$42) -> 56.028 | D65: t | E65: CALCULADA = máximo de la tabla por combinación. | F65: Tabla por combinación (col. H–N) | H65: inicio del contacto útil para Mu | I65: =IF(I63>0,MAX($C$25,-I64/I63),$C$25) -> 0.25 | J65: =IF(J63>0,MAX($C$25,-J64/J63),$C$25) -> 0.25 | K65: =IF(K63>0,MAX($C$25,-K64/K63),$C$25) -> 0.25 | L65: =IF(L63>0,MAX($C$25,-L64/L63),$C$25) -> 0.25 | M65: =IF(M63>0,MAX($C$25,-M64/M63),$C$25) -> 0.25 | N65: m
B66: d mínimo por penetración (carga concéntrica) | C66: =100*(-(2*$C$64+$C$65/$C$16)*(DATOS!$C$64+DATOS!$C$65)+SQRT(((2*$C$64+$C$65/$C$16)*(DATOS!$C$64+DATOS!$C$65))^2-4*(4*$C$64+$C$65/$C$16)*($C$65/$C$16*DATOS!$C$64*DATOS!$C$65-$C$65)))/(2*(4*$C$64+$C$65/$C$16)) -> 15.327316 | D66: cm | E66: CALCULADA despejando d de Pu(1 − (cx+d)(cy+d)/A) = φvc·2(cx+cy+2d)·d. Sin momento: el valor formal sale en la sección 6. | F66: ACI 318-19, 22.6.4.1 y Tabla 22.6.5.2 | H66: Mu en la cara del dado, varillas ‖ Y | I66: =$C$8*IF(I65<$C$9/2,(I64-I63*$C$25)*(($C$9/2)^2-I65^2)/2+I63*(($C$9/2)^3-I65^3)/3-I64*$C$25*($C$9/2-I65),0)-I44*$C$8*$C$27^2/2 -> 6.0420938 | J66: =$C$8*IF(J65<$C$9/2,(J64-J63*$C$25)*(($C$9/2)^2-J65^2)/2+J63*(($C$9/2)^3-J65^3)/3-J64*$C$25*($C$9/2-J65),0)-J44*$C$8*$C$27^2/2 -> 7.8789375 | K66: =$C$8*IF(K65<$C$9/2,(K64-K63*$C$25)*(($C$9/2)^2-K65^2)/2+K63*(($C$9/2)^3-K65^3)/3-K64*$C$25*($C$9/2-K65),0)-K44*$C$8*$C$27^2/2 -> 7.7101875 | L66: =$C$8*IF(L65<$C$9/2,(L64-L63*$C$25)*(($C$9/2)^2-L65^2)/2+L63*(($C$9/2)^3-L65^3)/3-L64*$C$25*($C$9/2-L65),0)-L44*$C$8*$C$27^2/2 -> 4.7279531 | M66: =$C$8*IF(M65<$C$9/2,(M64-M63*$C$25)*(($C$9/2)^2-M65^2)/2+M63*(($C$9/2)^3-M65^3)/3-M64*$C$25*($C$9/2-M65),0)-M44*$C$8*$C$27^2/2 -> 3.0404531 | N66: t·m
B67: h mínimo sugerido por penetración | C67: =$C$66+$C$12+MAX($C$39,$C$41) -> 24.417316 | D67: cm | E67: CALCULADA = d_mín + r + db. | F67: Geometría | H67: sección de cortante (a d de la cara) | I67: =$C$25+$C$46/100 -> 0.65115 | J67: =$C$25+$C$46/100 -> 0.65115 | K67: =$C$25+$C$46/100 -> 0.65115 | L67: =$C$25+$C$46/100 -> 0.65115 | M67: =$C$25+$C$46/100 -> 0.65115 | N67: m
H68: inicio del contacto útil para Vu | I68: =IF(I63>0,MAX(I67,-I64/I63),I67) -> 0.65115 | J68: =IF(J63>0,MAX(J67,-J64/J63),J67) -> 0.65115 | K68: =IF(K63>0,MAX(K67,-K64/K63),K67) -> 0.65115 | L68: =IF(L63>0,MAX(L67,-L64/L63),L67) -> 0.65115 | M68: =IF(M63>0,MAX(M67,-M64/M63),M67) -> 0.65115 | N68: m
B69: 5. PRESIONES DE SERVICIO, VOLTEO Y DESLIZAMIENTO (sale de la tabla por combinación, bloque S) | H69: Vu en una dirección, Y | I69: =IF(I67>=$C$9/2,0,MAX(0,$C$8*IF(I68<$C$9/2,I64*($C$9/2-I68)+I63*(($C$9/2)^2-I68^2)/2,0)-I44*$C$8*($C$9/2-I67))) -> 7.4943446 | J69: =IF(J67>=$C$9/2,0,MAX(0,$C$8*IF(J68<$C$9/2,J64*($C$9/2-J68)+J63*(($C$9/2)^2-J68^2)/2,0)-J44*$C$8*($C$9/2-J67))) -> 9.7726839 | K69: =IF(K67>=$C$9/2,0,MAX(0,$C$8*IF(K68<$C$9/2,K64*($C$9/2-K68)+K63*(($C$9/2)^2-K68^2)/2,0)-K44*$C$8*($C$9/2-K67))) -> 9.5633739 | L69: =IF(L67>=$C$9/2,0,MAX(0,$C$8*IF(L68<$C$9/2,L64*($C$9/2-L68)+L63*(($C$9/2)^2-L68^2)/2,0)-L44*$C$8*($C$9/2-L67))) -> 5.8643429 | M69: =IF(M67>=$C$9/2,0,MAX(0,$C$8*IF(M68<$C$9/2,M64*($C$9/2-M68)+M63*(($C$9/2)^2-M68^2)/2,0)-M44*$C$8*($C$9/2-M67))) -> 3.7712429 | N69: t
B70: Concepto | C70: Valor | D70: Unidad | E70: Cómo se calcula / de dónde sale | F70: Referencia | H70: fin del contacto en el lado ligero | I70: =IF(I63>0,MIN($C$9/2,I64/I63),$C$9/2) -> 1 | J70: =IF(J63>0,MIN($C$9/2,J64/J63),$C$9/2) -> 1 | K70: =IF(K63>0,MIN($C$9/2,K64/K63),$C$9/2) -> 1 | L70: =IF(L63>0,MIN($C$9/2,L64/L63),$C$9/2) -> 1 | M70: =IF(M63>0,MIN($C$9/2,M64/M63),$C$9/2) -> 1 | N70: m
B71: q_máx — presión máxima de servicio que rige | C71: =MAX($I$23:$M$23) -> 13.41 | D71: t/m² | E71: CALCULADA. Dentro del núcleo: P/A(1 + 6ex/Lx + 6ey/Ly). Con despegue: P/A·Kx·Ky (producto de los factores uniaxiales, aproximación del lado seguro). | F71: Bowles 5ª ed., §8.10, págs. 449–453 · ACI 318-19, R13.2.6.1, págs. 199–200 | H71: M con tensión arriba, lado ligero ‖ Y | I71: =I44*$C$8*$C$27^2/2-$C$8*IF(I70>$C$25,(I64+I63*$C$25)*(I70^2-$C$25^2)/2-I63*(I70^3-$C$25^3)/3-I64*$C$25*(I70-$C$25),0) -> -6.0420938 | J71: =J44*$C$8*$C$27^2/2-$C$8*IF(J70>$C$25,(J64+J63*$C$25)*(J70^2-$C$25^2)/2-J63*(J70^3-$C$25^3)/3-J64*$C$25*(J70-$C$25),0) -> -7.8789375 | K71: =K44*$C$8*$C$27^2/2-$C$8*IF(K70>$C$25,(K64+K63*$C$25)*(K70^2-$C$25^2)/2-K63*(K70^3-$C$25^3)/3-K64*$C$25*(K70-$C$25),0) -> -7.7101875 | L71: =L44*$C$8*$C$27^2/2-$C$8*IF(L70>$C$25,(L64+L63*$C$25)*(L70^2-$C$25^2)/2-L63*(L70^3-$C$25^3)/3-L64*$C$25*(L70-$C$25),0) -> -4.7279531 | M71: =M44*$C$8*$C$27^2/2-$C$8*IF(M70>$C$25,(M64+M63*$C$25)*(M70^2-$C$25^2)/2-M63*(M70^3-$C$25^3)/3-M64*$C$25*(M70-$C$25),0) -> -3.0404531 | N71: t·m
B72: Combinación que da q_máx | C72: =INDEX($I$5:$M$5,MATCH($C$71,$I$23:$M$23,0)) -> S3 | D72: — | E72: CALCULADA. | F72: COMBINACIONES | H72: Índice de núcleo con cargas factorizadas | I72: =6*I48/$C$8+6*I60/$C$9 -> 0 | J72: =6*J48/$C$8+6*J60/$C$9 -> 0 | K72: =6*K48/$C$8+6*K60/$C$9 -> 0 | L72: =6*L48/$C$8+6*L60/$C$9 -> 0 | M72: =6*M48/$C$8+6*M60/$C$9 -> 0 | N72: —
B73: q_máx / q_adm (la más desfavorable) | C73: =MAX($I$27:$M$27) -> 0.745 | D73: — | E73: CALCULADA. q_adm = qa, multiplicada por el incremento de DATOS en combinaciones con A. | F73: DATOS, sección 3 | H73: Vu de penetración = Pu(1 − A_crit/A) | I73: =IF(I72<=1,I42*(1-$C$91/$C$16),I42) -> 34.08855 | J73: =IF(J72<=1,J42*(1-$C$91/$C$16),J42) -> 44.451735 | K73: =IF(K72<=1,K42*(1-$C$91/$C$16),K42) -> 43.499674 | L73: =IF(L72<=1,L42*(1-$C$91/$C$16),L42) -> 26.674373 | M73: =IF(M72<=1,M42*(1-$C$91/$C$16),M42) -> 17.153762 | N73: t
B74: Presión máxima contra la admisible | C74: =IF($C$73<=1,"CUMPLE","NO CUMPLE — aumentar Lx y/o Ly") -> CUMPLE | D74: — | E74: Compara cada combinación contra su q_adm. | F74: ACI 318-19, 13.3.1.1, pág. 203 | H74: Msc alrededor de X = (1−α)(|Mx| + |Vy|·brazo dado) | I74: =(1-$C$15)*(ABS(I38)+ABS(I41)*$C$20) -> 0 | J74: =(1-$C$15)*(ABS(J38)+ABS(J41)*$C$20) -> 0 | K74: =(1-$C$15)*(ABS(K38)+ABS(K41)*$C$20) -> 0 | L74: =(1-$C$15)*(ABS(L38)+ABS(L41)*$C$20) -> 0 | M74: =(1-$C$15)*(ABS(M38)+ABS(M41)*$C$20) -> 0 | N74: t·m
B75: q_mín — presión mínima (0 = hay despegue) | C75: =MIN($I$24:$M$24) -> 5.1735 | D75: t/m² | E75: CALCULADA. | F75: Bowles 5ª ed., §8.10, pág. 453 | H75: Msc alrededor de Y = (1−α)(|My| + |Vx|·brazo dado) | I75: =(1-$C$15)*(ABS(I39)+ABS(I40)*$C$20) -> 0 | J75: =(1-$C$15)*(ABS(J39)+ABS(J40)*$C$20) -> 0 | K75: =(1-$C$15)*(ABS(K39)+ABS(K40)*$C$20) -> 0 | L75: =(1-$C$15)*(ABS(L39)+ABS(L40)*$C$20) -> 0 | M75: =(1-$C$15)*(ABS(M39)+ABS(M40)*$C$20) -> 0 | N75: t·m
B76: Con carga sostenida (S1 = D + L), ¿toda la zapata está comprimida? | C76: =IF(INDEX($I$20:$M$20,1)<=1,"CUMPLE — resultante dentro del núcleo central","NO CUMPLE — con D + L no debe haber despegue: aumentar dimensiones") -> CUMPLE — resultante dentro del núcleo central | D76: — | E76: Criterio: 6ex/Lx + 6ey/Ly ≤ 1 con la combinación permanente. | F76: Bowles 5ª ed., §8.10, pág. 453 (e ≤ L/6) | H76: vu máx de penetración | I76: =I73*1000/($C$90*$C$47)+$C$101*I75*100000*($C$88/2)/$C$102+$C$104*I74*100000*($C$89/2)/$C$105 -> 2.2914342 | J76: =J73*1000/($C$90*$C$47)+$C$101*J75*100000*($C$88/2)/$C$102+$C$104*J74*100000*($C$89/2)/$C$105 -> 2.9880482 | K76: =K73*1000/($C$90*$C$47)+$C$101*K75*100000*($C$88/2)/$C$102+$C$104*K74*100000*($C$89/2)/$C$105 -> 2.9240505 | L76: =L73*1000/($C$90*$C$47)+$C$101*L75*100000*($C$88/2)/$C$102+$C$104*L74*100000*($C$89/2)/$C$105 -> 1.7930529 | M76: =M73*1000/($C$90*$C$47)+$C$101*M75*100000*($C$88/2)/$C$102+$C$104*M74*100000*($C$89/2)/$C$105 -> 1.1530768 | N76: kg/cm²
B77: Combinaciones con contacto parcial (despegue) | C77: =COUNTIF($I$25:$M$25,"PARCIAL") -> 0 | D77: — | E77: CALCULADA. Se aceptan en combinaciones accidentales si cumplen presión, volteo y deslizamiento. | F77: Tabla por combinación
B78: P total mínima sobre el terreno | C78: =MIN($I$15:$M$15) -> 20.694 | D78: t | E78: CALCULADA. | F78: Tabla por combinación | H78: BLOQUE U — CONTRATRABE (por contratrabe)
B79: ¿Hay levantamiento neto? | C79: =IF($C$78>0,"CUMPLE — no hay levantamiento","NO CUMPLE — tensión neta: lastrar o anclar") -> CUMPLE — no hay levantamiento | D79: — | E79: La carga total debe quedar a compresión en todas las combinaciones. | F79: ACI 318-19, 13.2.6.1, págs. 199–200 | H79: M que toma la contratrabe en X = α(|My| + |Vx|·brazo)/n | I79: =$C$15*(ABS(I39)+ABS(I40)*$C$20)/$C$230 -> 1.162 | J79: =$C$15*(ABS(J39)+ABS(J40)*$C$20)/$C$230 -> 1.66 | K79: =$C$15*(ABS(K39)+ABS(K40)*$C$20)/$C$230 -> 10.786 | L79: =$C$15*(ABS(L39)+ABS(L40)*$C$20)/$C$230 -> 10.122 | M79: =$C$15*(ABS(M39)+ABS(M40)*$C$20)/$C$230 -> 10.122 | N79: t·m
B80: FS al volteo mínimo, dirección X | C80: =MIN($I$28:$M$28) -> 99 | D80: — | E80: CALCULADA = Lx / (2 ex) = P·(Lx/2) / M. | F80: Bowles 5ª ed., §8.10, pág. 450 | H80: M que toma la contratrabe en Y = α(|Mx| + |Vy|·brazo)/n | I80: =$C$15*(ABS(I38)+ABS(I41)*$C$20)/$C$230 -> 1.603 | J80: =$C$15*(ABS(J38)+ABS(J41)*$C$20)/$C$230 -> 2.198 | K80: =$C$15*(ABS(K38)+ABS(K41)*$C$20)/$C$230 -> 9.689 | L80: =$C$15*(ABS(L38)+ABS(L41)*$C$20)/$C$230 -> 8.8305 | M80: =$C$15*(ABS(M38)+ABS(M41)*$C$20)/$C$230 -> 8.8305 | N80: t·m
B81: FS al volteo mínimo, dirección Y | C81: =MIN($I$29:$M$29) -> 99 | D81: — | E81: CALCULADA = Ly / (2 ey). | F81: Bowles 5ª ed., §8.10, pág. 450 | H81: w_u sobre la contratrabe = γD·w_D | I81: =I36*$C$243 -> 0.6048 | J81: =J36*$C$243 -> 0.5184 | K81: =K36*$C$243 -> 0.5184 | L81: =L36*$C$243 -> 0.3888 | M81: =M36*$C$243 -> 0.3888 | N81: t/m
B82: Revisión por volteo | C82: =IF(MIN($C$80,$C$81)>=DATOS!$C$34,"CUMPLE","NO CUMPLE — aumentar dimensiones o peso") -> CUMPLE | D82: — | E82: Compara contra el FS exigido en DATOS. | F82: ACI 318-19, 13.2.6.1, págs. 199–200 | H82: Mu arriba (extremo), X | I82: =I79+I81*$C$228^2/12 -> 2.6866 | J82: =J79+J81*$C$228^2/12 -> 2.9668 | K82: =K79+K81*$C$228^2/12 -> 12.0928 | L82: =L79+L81*$C$228^2/12 -> 11.1021 | M82: =M79+M81*$C$228^2/12 -> 11.1021 | N82: t·m
B83: FS al deslizamiento mínimo | C83: =MIN($I$31:$M$31) -> 99 | D83: — | E83: CALCULADA = μ · P_total / √(Vx² + Vy²). Sin empuje pasivo. | F83: NAVFAC DM 7.02, Tabla 1, pág. 7.2-63 | H83: Mu abajo, X | I83: =MAX(I79-I81*$C$228^2/12,I81*$C$228^2/24) -> 0.7623 | J83: =MAX(J79-J81*$C$228^2/12,J81*$C$228^2/24) -> 0.6534 | K83: =MAX(K79-K81*$C$228^2/12,K81*$C$228^2/24) -> 9.4792 | L83: =MAX(L79-L81*$C$228^2/12,L81*$C$228^2/24) -> 9.1419 | M83: =MAX(M79-M81*$C$228^2/12,M81*$C$228^2/24) -> 9.1419 | N83: t·m
B84: Revisión por deslizamiento | C84: =IF($C$83>=DATOS!$C$35,"CUMPLE","NO CUMPLE — aumentar peso, dentellón o contratrabe") -> CUMPLE | D84: — | E84: Compara contra el FS exigido en DATOS. | F84: ACI 318-19, 13.2.6.1, págs. 199–200 | H84: Vu, X | I84: =2*I79/$C$228+I81*$C$228/2 -> 2.0857455 | J84: =2*J79/$C$228+J81*$C$228/2 -> 2.0292364 | K84: =2*K79/$C$228+K81*$C$228/2 -> 5.3477818 | L84: =2*L79/$C$228+L81*$C$228/2 -> 4.7499273 | M84: =2*M79/$C$228+M81*$C$228/2 -> 4.7499273 | N84: t
H85: Mu arriba (extremo), Y | I85: =I80+I81*$C$229^2/12 -> 3.1276 | J85: =J80+J81*$C$229^2/12 -> 3.5048 | K85: =K80+K81*$C$229^2/12 -> 10.9958 | L85: =L80+L81*$C$229^2/12 -> 9.8106 | M85: =M80+M81*$C$229^2/12 -> 9.8106 | N85: t·m
B86: 6. CORTANTE EN DOS DIRECCIONES (PENETRACIÓN) — sección crítica a d/2 del dado | H86: Mu abajo, Y | I86: =MAX(I80-I81*$C$229^2/12,I81*$C$229^2/24) -> 0.7623 | J86: =MAX(J80-J81*$C$229^2/12,J81*$C$229^2/24) -> 0.8912 | K86: =MAX(K80-K81*$C$229^2/12,K81*$C$229^2/24) -> 8.3822 | L86: =MAX(L80-L81*$C$229^2/12,L81*$C$229^2/24) -> 7.8504 | M86: =MAX(M80-M81*$C$229^2/12,M81*$C$229^2/24) -> 7.8504 | N86: t·m
B87: Concepto | C87: Valor | D87: Unidad | E87: Cómo se calcula / de dónde sale | F87: Referencia | H87: Vu, Y | I87: =2*I80/$C$229+I81*$C$229/2 -> 2.2461091 | J87: =2*J80/$C$229+J81*$C$229/2 -> 2.2248727 | K87: =2*K80/$C$229+K81*$C$229/2 -> 4.9488727 | L87: =2*L80/$C$229+L81*$C$229/2 -> 4.2802909 | M87: =2*M80/$C$229+M81*$C$229/2 -> 4.2802909 | N87: t
B88: b₁ — lado de la sección crítica en X | C88: =DATOS!$C$64*100+$C$47 -> 90.91 | D88: cm | E88: CALCULADA = cx + d. | F88: ACI 318-19, 22.6.4.1 | H88: Nu de amarre = máx(fracción·Pu ; α·V) | I88: =MAX($C$235*I42,$C$15*MAX(ABS(I40),ABS(I41))) -> 4.2966 | J88: =MAX($C$235*J42,$C$15*MAX(ABS(J40),ABS(J41))) -> 5.6028 | K88: =MAX($C$235*K42,$C$15*MAX(ABS(K40),ABS(K41))) -> 5.4828 | L88: =MAX($C$235*L42,$C$15*MAX(ABS(L40),ABS(L41))) -> 3.3621 | M88: =MAX($C$235*M42,$C$15*MAX(ABS(M40),ABS(M41))) -> 2.68 | N88: t
B89: b₂ — lado de la sección crítica en Y | C89: =DATOS!$C$65*100+$C$47 -> 90.91 | D89: cm | E89: CALCULADA = cy + d. | F89: ACI 318-19, 22.6.4.1
B90: b₀ — perímetro crítico | C90: =2*($C$88+$C$89) -> 363.64 | D90: cm | E90: CALCULADA. | F90: ACI 318-19, 22.6.4.1
B91: Área dentro de la sección crítica | C91: =$C$88*$C$89/10000 -> 0.82646281 | D91: m² | E91: CALCULADA. Su reacción no aporta al cortante. | F91: ACI 318-19, 13.2.7.2, pág. 202
B92: β — relación de lados del dado | C92: =MAX(DATOS!$C$64,DATOS!$C$65)/MIN(DATOS!$C$64,DATOS!$C$65) -> 1 | D92: — | E92: CALCULADA. | F92: ACI 318-19, Tabla 22.6.5.2
B93: αs — columna interior | C93: 40 | D93: — | E93: FIJO. La zapata rodea al dado por los 4 lados. | F93: ACI 318-19, Tabla 22.6.5.2 · TABLAS, tabla 5
B94: λs — factor de tamaño | C94: =IF(DATOS!$C$90="SÍ",1,MIN(1,SQRT(2/(1+0.004*$C$47*10)))) -> 1 | D94: — | E94: CALCULADA. Con SÍ en DATOS vale 1 (13.2.6.2); con NO, √(2/(1+0.004d)) con d en mm. | F94: ACI 318-19, 13.2.6.2, pág. 200 · 22.5.5.1.3
B95: vc (a) = 0.33 λs λ √f'c | C95: =0.33*$C$94*DATOS!$C$23*DATOS!$C$17*DATOS!$C$89 -> 16.661896 | D95: kg/cm² | E95: CALCULADA en MPa y pasada a kg/cm². | F95: ACI 318-19, Tabla 22.6.5.2(a)
B96: vc (b) = 0.17 (1 + 2/β) λs λ √f'c | C96: =0.17*(1+2/$C$92)*$C$94*DATOS!$C$23*DATOS!$C$17*DATOS!$C$89 -> 25.750203 | D96: kg/cm² | E96: CALCULADA. | F96: ACI 318-19, Tabla 22.6.5.2(b)
B97: vc (c) = 0.083 (2 + αs d/b₀) λs λ √f'c | C97: =0.083*(2+$C$93*$C$47/$C$90)*$C$94*DATOS!$C$23*DATOS!$C$17*DATOS!$C$89 -> 27.239906 | D97: kg/cm² | E97: CALCULADA. | F97: ACI 318-19, Tabla 22.6.5.2(c)
B98: vc — el menor de los tres | C98: =MIN($C$95,$C$96,$C$97) -> 16.661896 | D98: kg/cm² | E98: CALCULADA. | F98: ACI 318-19, 22.6.5.2
B99: φ vc | C99: =DATOS!$C$87*$C$98 -> 12.496422 | D99: kg/cm² | E99: CALCULADA con φ = 0.75. | F99: ACI 318-19, Tabla 21.2.1(b)
B100: γf para el momento alrededor de Y | C100: =1/(1+2/3*SQRT($C$88/$C$89)) -> 0.6 | D100: — | E100: CALCULADA = 1/(1 + ⅔√(b₁/b₂)). | F100: ACI 318-19, ec. 8.4.2.2.2
...

Sheet CORRIDA
B1: ZAPATA CORRIDA BAJO MURO — ACI 318-19 (por metro de longitud) | H1: TABLA POR COMBINACIÓN — por metro de muro
B2: =DATOS!$C$9&" · "&DATOS!$C$10 -> Ejemplo — nave industrial · Columna tipo eje B-2 · muro eje 1 | H2: Bloque S con carga total (incluye zapata, relleno y muro enterrado por su γD); bloque U con presión neta para el diseño estructural (ACI 13.2.6.3).
B3: Se capturan sólo las celdas amarillas de las secciones 1 y 2; las cargas por metro vienen de DATOS (sección 7). A la derecha (columnas H a N) está la tabla por combinación.
H4: BLOQUE S — SERVICIO
B5: 1. GEOMETRÍA (por metro de muro) | H5: Combinación | I5: =COMBINACIONES!$B$6 -> S1 | J5: =COMBINACIONES!$B$7 -> S2 | K5: =COMBINACIONES!$B$8 -> S3 | L5: =COMBINACIONES!$B$9 -> S4 | M5: =COMBINACIONES!$B$10 -> S5
B6: Concepto | C6: Valor | D6: Unidad | E6: Cómo se calcula / de dónde sale | F6: Referencia | H6: Descripción | I6: =COMBINACIONES!$C$6 -> D + L | J6: =COMBINACIONES!$C$7 -> D + 0.7E | K6: =COMBINACIONES!$C$8 -> D + 0.75L + 0.525E | L6: =COMBINACIONES!$C$9 -> 0.6D + 0.7E (P de A suma) | M6: =COMBINACIONES!$C$10 -> 0.6D + 0.7E (P de A resta)
B7: B — ancho de la zapata | C7: 0.9 | D7: m | E7: CAPTURA. Se ajusta hasta que la presión de la sección 5 quede abajo de qa. | F7: Propuesta — se verifica en la sección 5 | H7: γD | I7: =COMBINACIONES!$E$6 -> 1 | J7: =COMBINACIONES!$E$7 -> 1 | K7: =COMBINACIONES!$E$8 -> 1 | L7: =COMBINACIONES!$E$9 -> 0.6 | M7: =COMBINACIONES!$E$10 -> 0.6
B8: h — peralte total | C8: 0.25 | D8: m | E8: CAPTURA. | F8: Propuesta — se verifica en las secciones 6 y 7 | H8: γA | I8: =COMBINACIONES!$G$6 -> 0 | J8: =COMBINACIONES!$G$7 -> 0.7 | K8: =COMBINACIONES!$G$8 -> 0.525 | L8: =COMBINACIONES!$G$9 -> 0.7 | M8: =COMBINACIONES!$G$10 -> 0.7
B9: Df — profundidad de desplante | C9: 0.8 | D9: m | E9: CAPTURA. | F9: Estudio de mecánica de suelos / proyecto | H9: w del muro | I9: =COMBINACIONES!$E$32 -> 6.5 | J9: =COMBINACIONES!$E$33 -> 5.56 | K9: =COMBINACIONES!$E$34 -> 6.545 | L9: =COMBINACIONES!$E$35 -> 3.56 | M9: =COMBINACIONES!$E$36 -> 2.44 | N9: t/m
B10: t — ancho del muro (o del dado corrido) sobre la zapata | C10: 0.2 | D10: m | E10: CAPTURA. | F10: Proyecto | H10: M del muro | I10: =COMBINACIONES!$F$32 -> 0 | J10: =COMBINACIONES!$F$33 -> 0.21 | K10: =COMBINACIONES!$F$34 -> 0.1575 | L10: =COMBINACIONES!$F$35 -> 0.21 | M10: =COMBINACIONES!$F$36 -> 0.21 | N10: t·m/m
B11: Tipo de muro que se apoya | C11: MAMPOSTERÍA | D11: — | E11: CAPTURA (lista). Define la sección crítica: cara del muro si es de concreto; a la mitad entre el eje y la cara si es de mampostería. | F11: ACI 318-19, Tabla 13.2.7.1, págs. 201–202 | H11: V del muro | I11: =COMBINACIONES!$G$32 -> 0 | J11: =COMBINACIONES!$G$33 -> 0.28 | K11: =COMBINACIONES!$G$34 -> 0.21 | L11: =COMBINACIONES!$G$35 -> 0.28 | M11: =COMBINACIONES!$G$36 -> 0.28 | N11: t/m
B12: γ del muro o dado bajo el terreno | C12: 2 | D12: t/m³ | E12: CAPTURA. Del nivel de terreno a la cara de la zapata. | F12: Práctica | H12: γD · ΣW | I12: =I7*$C$40 -> 1.376 | J12: =J7*$C$40 -> 1.376 | K12: =K7*$C$40 -> 1.376 | L12: =L7*$C$40 -> 0.8256 | M12: =M7*$C$40 -> 0.8256 | N12: t/m
B13: r — recubrimiento libre inferior | C13: 7.5 | D13: cm | E13: CAPTURA. Colado contra el suelo: 75 mm. | F13: ACI 318-19, Tabla 20.5.1.3.1 | H13: w total | I13: =I9+I12 -> 7.876 | J13: =J9+J12 -> 6.936 | K13: =K9+K12 -> 7.921 | L13: =L9+L12 -> 4.3856 | M13: =M9+M12 -> 3.2656 | N13: t/m
B14: r_lat — recubrimiento en las puntas | C14: 7.5 | D14: cm | E14: CAPTURA. | F14: ACI 318-19, Tabla 20.5.1.3.1 | H14: M en el desplante = M + V·Df | I14: =I10+I11*$C$20 -> 0 | J14: =J10+J11*$C$20 -> 0.434 | K14: =K10+K11*$C$20 -> 0.3255 | L14: =L10+L11*$C$20 -> 0.434 | M14: =M10+M11*$C$20 -> 0.434 | N14: t·m/m
B15: Tramo de zapata que se dibuja en el croquis | C15: 2 | D15: m | E15: CAPTURA. Sólo para el dibujo. | F15: CROQUIS | H15: e = M / w | I15: =IF(I13>0,I14/I13,99) -> 0 | J15: =IF(J13>0,J14/J13,99) -> 0.062572088 | K15: =IF(K13>0,K14/K13,99) -> 0.041093296 | L15: =IF(L13>0,L14/L13,99) -> 0.098960233 | M15: =IF(M13>0,M14/M13,99) -> 0.13290054 | N15: m
B16: h_rell — relleno sobre la zapata | C16: =$C$9-$C$8 -> 0.55 | D16: m | E16: CALCULADA = Df − h. | F16: Geometría | H16: q máx | I16: =IF(I13<=0,999,IF(I15<=$C$7/6,I13/$C$7*(1+6*I15/$C$7),IF(I15<$C$7/2,2*I13/(3*($C$7/2-I15)),999))) -> 8.7511111 | J16: =IF(J13<=0,999,IF(J15<=$C$7/6,J13/$C$7*(1+6*J15/$C$7),IF(J15<$C$7/2,2*J13/(3*($C$7/2-J15)),999))) -> 10.921481 | K16: =IF(K13<=0,999,IF(K15<=$C$7/6,K13/$C$7*(1+6*K15/$C$7),IF(K15<$C$7/2,2*K13/(3*($C$7/2-K15)),999))) -> 11.212222 | L16: =IF(L13<=0,999,IF(L15<=$C$7/6,L13/$C$7*(1+6*L15/$C$7),IF(L15<$C$7/2,2*L13/(3*($C$7/2-L15)),999))) -> 8.0877037 | M16: =IF(M13<=0,999,IF(M15<=$C$7/6,M13/$C$7*(1+6*M15/$C$7),IF(M15<$C$7/2,2*M13/(3*($C$7/2-M15)),999))) -> 6.8432593 | N16: t/m²
B17: Sección crítica, distancia al eje del muro | C17: =IF($C$11="MAMPOSTERÍA",$C$10/4,$C$10/2) -> 0.05 | D17: m | E17: CALCULADA: t/2 (cara) para concreto; t/4 (mitad entre eje y cara) para mampostería. | F17: ACI 318-19, Tabla 13.2.7.1, págs. 201–202 | H17: q mín | I17: =IF(I13<=0,0,IF(I15<=$C$7/6,I13/$C$7*(1-6*I15/$C$7),0)) -> 8.7511111 | J17: =IF(J13<=0,0,IF(J15<=$C$7/6,J13/$C$7*(1-6*J15/$C$7),0)) -> 4.4918519 | K17: =IF(K13<=0,0,IF(K15<=$C$7/6,K13/$C$7*(1-6*K15/$C$7),0)) -> 6.39 | L17: =IF(L13<=0,0,IF(L15<=$C$7/6,L13/$C$7*(1-6*L15/$C$7),0)) -> 1.6580741 | M17: =IF(M13<=0,0,IF(M15<=$C$7/6,M13/$C$7*(1-6*M15/$C$7),0)) -> 0.41362963 | N17: t/m²
B18: Volado de cálculo desde la sección crítica | C18: =$C$7/2-$C$17 -> 0.4 | D18: m | E18: CALCULADA. | F18: Geometría | H18: Contacto | I18: =IF(I15<=$C$7/6,"TOTAL","PARCIAL") -> TOTAL | J18: =IF(J15<=$C$7/6,"TOTAL","PARCIAL") -> TOTAL | K18: =IF(K15<=$C$7/6,"TOTAL","PARCIAL") -> TOTAL | L18: =IF(L15<=$C$7/6,"TOTAL","PARCIAL") -> TOTAL | M18: =IF(M15<=$C$7/6,"TOTAL","PARCIAL") -> TOTAL
B19: I de la base por metro de muro | C19: =$C$7^3/12 -> 0.06075 | D19: m⁴/m | E19: CALCULADA = 1·B³/12. | F19: Mecánica de materiales | H19: q adm | I19: =DATOS!$C$30*IF(I8>0,DATOS!$C$31,1) -> 18 | J19: =DATOS!$C$30*IF(J8>0,DATOS!$C$31,1) -> 18 | K19: =DATOS!$C$30*IF(K8>0,DATOS!$C$31,1) -> 18 | L19: =DATOS!$C$30*IF(L8>0,DATOS!$C$31,1) -> 18 | M19: =DATOS!$C$30*IF(M8>0,DATOS!$C$31,1) -> 18 | N19: t/m²
B20: Brazo del cortante V hasta el desplante | C20: =$C$9 -> 0.8 | D20: m | E20: CALCULADA = Df (la carga llega al nivel de terreno). | F20: Estática | H20: q máx / q adm | I20: =I16/I19 -> 0.48617284 | J20: =J16/J19 -> 0.60674897 | K20: =K16/K19 -> 0.62290123 | L20: =L16/L19 -> 0.44931687 | M20: =M16/M19 -> 0.38018107 | N20: —
B21: ¿La geometría es coherente? | C21: =IF(AND($C$7>$C$10,$C$16>=0),"CUMPLE","NO CUMPLE — B debe ser mayor que t y Df ≥ h") -> CUMPLE | D21: — | E21: Revisión de datos. | F21: Geometría | H21: FS volteo = B/(2e) | I21: =IF(I15>0.0001,$C$7/(2*I15),99) -> 99 | J21: =IF(J15>0.0001,$C$7/(2*J15),99) -> 7.1917051 | K21: =IF(K15>0.0001,$C$7/(2*K15),99) -> 10.950691 | L21: =IF(L15>0.0001,$C$7/(2*L15),99) -> 4.5472811 | M21: =IF(M15>0.0001,$C$7/(2*M15),99) -> 3.3859908 | N21: —
H22: FS deslizamiento = μ w / V | I22: =IF(I11>0.0001,DATOS!$C$33*I13/I11,99) -> 99 | J22: =IF(J11>0.0001,DATOS!$C$33*J13/J11,99) -> 11.147143 | K22: =IF(K11>0.0001,DATOS!$C$33*K13/K11,99) -> 16.973571 | L22: =IF(L11>0.0001,DATOS!$C$33*L13/L11,99) -> 7.0482857 | M22: =IF(M11>0.0001,DATOS!$C$33*M13/M11,99) -> 5.2482857 | N22: —
B23: 2. VARILLAS Y PERALTE EFECTIVO
B24: Concepto | C24: Valor | D24: Unidad | E24: Cómo se calcula / de dónde sale | F24: Referencia | H24: BLOQUE U — RESISTENCIA
B25: Varilla transversal (principal, lecho inferior) | C25: 4 | D25: # | E25: CAPTURA (lista). | F25: Propuesta | H25: Combinación | I25: =COMBINACIONES!$B$11 -> U1 | J25: =COMBINACIONES!$B$12 -> U2 | K25: =COMBINACIONES!$B$13 -> U3 | L25: =COMBINACIONES!$B$14 -> U4 | M25: =COMBINACIONES!$B$15 -> U5
B26: Varilla longitudinal (por temperatura, encima de la transversal) | C26: 3 | D26: # | E26: CAPTURA (lista). | F26: Propuesta | H26: Descripción | I26: =COMBINACIONES!$C$11 -> 1.4D | J26: =COMBINACIONES!$C$12 -> 1.2D + 1.6L | K26: =COMBINACIONES!$C$13 -> 1.2D + 1.0L + 1.0E | L26: =COMBINACIONES!$C$14 -> 0.9D + 1.0E (P de A suma) | M26: =COMBINACIONES!$C$15 -> 0.9D + 1.0E (P de A resta)
B27: Separación transversal que tú fijas (0 = la calcula la hoja) | C27: 0 | D27: cm | E27: CAPTURA. | F27: Propuesta | H27: γD | I27: =COMBINACIONES!$E$11 -> 1.4 | J27: =COMBINACIONES!$E$12 -> 1.2 | K27: =COMBINACIONES!$E$13 -> 1.2 | L27: =COMBINACIONES!$E$14 -> 0.9 | M27: =COMBINACIONES!$E$15 -> 0.9
B28: db transversal | C28: =INDEX(TABLAS!$C$6:$C$13,MATCH($C$25,TABLAS!$B$6:$B$13,0)) -> 1.27 | D28: cm | E28: CALCULADA. | F28: TABLAS, tabla 1 | H28: wu del muro | I28: =COMBINACIONES!$E$37 -> 7 | J28: =COMBINACIONES!$E$38 -> 8.4 | K28: =COMBINACIONES!$E$39 -> 8.3 | L28: =COMBINACIONES!$E$40 -> 5.3 | M28: =COMBINACIONES!$E$41 -> 3.7 | N28: t/m
B29: Área de una varilla transversal | C29: =INDEX(TABLAS!$D$6:$D$13,MATCH($C$25,TABLAS!$B$6:$B$13,0)) -> 1.27 | D29: cm² | E29: CALCULADA. | F29: TABLAS, tabla 1 | H29: Mu del muro | I29: =COMBINACIONES!$F$37 -> 0 | J29: =COMBINACIONES!$F$38 -> 0 | K29: =COMBINACIONES!$F$39 -> 0.3 | L29: =COMBINACIONES!$F$40 -> 0.3 | M29: =COMBINACIONES!$F$41 -> 0.3 | N29: t·m/m
B30: db longitudinal | C30: =INDEX(TABLAS!$C$6:$C$13,MATCH($C$26,TABLAS!$B$6:$B$13,0)) -> 0.95 | D30: cm | E30: CALCULADA. | F30: TABLAS, tabla 1 | H30: Vu del muro | I30: =COMBINACIONES!$G$37 -> 0 | J30: =COMBINACIONES!$G$38 -> 0 | K30: =COMBINACIONES!$G$39 -> 0.4 | L30: =COMBINACIONES!$G$40 -> 0.4 | M30: =COMBINACIONES!$G$41 -> 0.4 | N30: t/m
B31: Área de una varilla longitudinal | C31: =INDEX(TABLAS!$D$6:$D$13,MATCH($C$26,TABLAS!$B$6:$B$13,0)) -> 0.71 | D31: cm² | E31: CALCULADA. | F31: TABLAS, tabla 1 | H31: wu sobre la zapata = wu + γD·W_muro | I31: =I28+I27*$C$39 -> 7.308 | J31: =J28+J27*$C$39 -> 8.664 | K31: =K28+K27*$C$39 -> 8.564 | L31: =L28+L27*$C$39 -> 5.498 | M31: =M28+M27*$C$39 -> 3.898 | N31: t/m
B32: d — peralte efectivo de la transversal | C32: =$C$8*100-$C$13-$C$28/2 -> 16.865 | D32: cm | E32: CALCULADA = h − r − db/2. | F32: Geometría | H32: γD · (W_zap + W_rell) | I32: =I27*($C$37+$C$38) -> 1.6184 | J32: =J27*($C$37+$C$38) -> 1.3872 | K32: =K27*($C$37+$C$38) -> 1.3872 | L32: =L27*($C$37+$C$38) -> 1.0404 | M32: =M27*($C$37+$C$38) -> 1.0404 | N32: t/m
B33: ¿El peralte efectivo es de al menos 15 cm? | C33: =IF($C$32>=15,"CUMPLE","NO CUMPLE — aumentar h") -> CUMPLE | D33: — | E33: Mínimo 150 mm. | F33: ACI 318-19, 13.3.1.2, pág. 203 | H33: w_u repartido | I33: =I32/$C$7 -> 1.7982222 | J33: =J32/$C$7 -> 1.5413333 | K33: =K32/$C$7 -> 1.5413333 | L33: =L32/$C$7 -> 1.156 | M33: =M32/$C$7 -> 1.156 | N33: t/m²
H34: w total factorizada | I34: =I31+I32 -> 8.9264 | J34: =J31+J32 -> 10.0512 | K34: =K31+K32 -> 9.9512 | L34: =L31+L32 -> 6.5384 | M34: =M31+M32 -> 4.9384 | N34: t/m
B35: 3. PESOS POR METRO (servicio) | H35: Mu en el desplante = M + V·Df | I35: =I29+I30*$C$20 -> 0 | J35: =J29+J30*$C$20 -> 0 | K35: =K29+K30*$C$20 -> 0.62 | L35: =L29+L30*$C$20 -> 0.62 | M35: =M29+M30*$C$20 -> 0.62 | N35: t·m/m
B36: Concepto | C36: Valor | D36: Unidad | E36: Cómo se calcula / de dónde sale | F36: Referencia | H36: ex = M/P total | I36: =IF(I34>0,I35/I34,99) -> 0 | J36: =IF(J34>0,J35/J34,99) -> 0 | K36: =IF(K34>0,K35/K34,99) -> 0.062304044 | L36: =IF(L34>0,L35/L34,99) -> 0.094824422 | M36: =IF(M34>0,M35/M34,99) -> 0.12554674 | N36: m
B37: W_zap — zapata | C37: =$C$7*$C$8*DATOS!$C$24 -> 0.54 | D37: t/m | E37: CALCULADA = B · h · γc. | F37: Geometría | H37: Contacto en X | I37: =IF(I36<=$C$7/6,"TOTAL",IF(I36<$C$7/2,"PARCIAL","INESTABLE")) -> TOTAL | J37: =IF(J36<=$C$7/6,"TOTAL",IF(J36<$C$7/2,"PARCIAL","INESTABLE")) -> TOTAL | K37: =IF(K36<=$C$7/6,"TOTAL",IF(K36<$C$7/2,"PARCIAL","INESTABLE")) -> TOTAL | L37: =IF(L36<=$C$7/6,"TOTAL",IF(L36<$C$7/2,"PARCIAL","INESTABLE")) -> TOTAL | M37: =IF(M36<=$C$7/6,"TOTAL",IF(M36<$C$7/2,"PARCIAL","INESTABLE")) -> TOTAL
B38: W_rell — relleno a los lados del muro | C38: =($C$7-$C$10)*$C$16*DATOS!$C$32 -> 0.616 | D38: t/m | E38: CALCULADA = (B − t) · h_rell · γs. | F38: Geometría | H38: q total en la orilla cargada (X) | I38: =IF(I36<=$C$7/6,I34/($C$7*1)+I35*($C$7/2)/$C$19,IF(I36<$C$7/2,2*I34/(3*1*($C$7/2-I36)),999)) -> 9.9182222 | J38: =IF(J36<=$C$7/6,J34/($C$7*1)+J35*($C$7/2)/$C$19,IF(J36<$C$7/2,2*J34/(3*1*($C$7/2-J36)),999)) -> 11.168 | K38: =IF(K36<=$C$7/6,K34/($C$7*1)+K35*($C$7/2)/$C$19,IF(K36<$C$7/2,2*K34/(3*1*($C$7/2-K36)),999)) -> 15.649481 | L38: =IF(L36<=$C$7/6,L34/($C$7*1)+L35*($C$7/2)/$C$19,IF(L36<$C$7/2,2*L34/(3*1*($C$7/2-L36)),999)) -> 11.857481 | M38: =IF(M36<=$C$7/6,M34/($C$7*1)+M35*($C$7/2)/$C$19,IF(M36<$C$7/2,2*M34/(3*1*($C$7/2-M36)),999)) -> 10.079704 | N38: t/m²
B39: W_muro — muro o dado bajo el terreno | C39: =$C$10*$C$16*$C$12 -> 0.22 | D39: t/m | E39: CALCULADA = t · h_rell · γm. | F39: Geometría | H39: pendiente de q (X) | I39: =IF(I36<=$C$7/6,I35/$C$19,IF(I36<$C$7/2,I38/(3*($C$7/2-I36)),0)) -> 0 | J39: =IF(J36<=$C$7/6,J35/$C$19,IF(J36<$C$7/2,J38/(3*($C$7/2-J36)),0)) -> 0 | K39: =IF(K36<=$C$7/6,K35/$C$19,IF(K36<$C$7/2,K38/(3*($C$7/2-K36)),0)) -> 10.205761 | L39: =IF(L36<=$C$7/6,L35/$C$19,IF(L36<$C$7/2,L38/(3*($C$7/2-L36)),0)) -> 10.205761 | M39: =IF(M36<=$C$7/6,M35/$C$19,IF(M36<$C$7/2,M38/(3*($C$7/2-M36)),0)) -> 10.205761 | N39: t/m³
B40: ΣW | C40: =$C$37+$C$38+$C$39 -> 1.376 | D40: t/m | E40: CALCULADA. En cada combinación se multiplica por su γD. | F40: ASCE/SEI 7-16, §2.4.1 | H40: q total al centro (ordenada) | I40: =I38-I39*$C$7/2 -> 9.9182222 | J40: =J38-J39*$C$7/2 -> 11.168 | K40: =K38-K39*$C$7/2 -> 11.056889 | L40: =L38-L39*$C$7/2 -> 7.2648889 | M40: =M38-M39*$C$7/2 -> 5.4871111 | N40: t/m²
H41: inicio del contacto útil para Mu | I41: =IF(I39>0,MAX($C$17,-I40/I39),$C$17) -> 0.05 | J41: =IF(J39>0,MAX($C$17,-J40/J39),$C$17) -> 0.05 | K41: =IF(K39>0,MAX($C$17,-K40/K39),$C$17) -> 0.05 | L41: =IF(L39>0,MAX($C$17,-L40/L39),$C$17) -> 0.05 | M41: =IF(M39>0,MAX($C$17,-M40/M39),$C$17) -> 0.05 | N41: m
B42: 4. ANCHO MÍNIMO SUGERIDO (orientativo) | H42: Mu en la cara del dado, varillas ‖ X | I42: =1*IF(I41<$C$7/2,(I40-I39*$C$17)*(($C$7/2)^2-I41^2)/2+I39*(($C$7/2)^3-I41^3)/3-I40*$C$17*($C$7/2-I41),0)-I33*1*$C$18^2/2 -> 0.6496 | J42: =1*IF(J41<$C$7/2,(J40-J39*$C$17)*(($C$7/2)^2-J41^2)/2+J39*(($C$7/2)^3-J41^3)/3-J40*$C$17*($C$7/2-J41),0)-J33*1*$C$18^2/2 -> 0.77013333 | K42: =1*IF(K41<$C$7/2,(K40-K39*$C$17)*(($C$7/2)^2-K41^2)/2+K39*(($C$7/2)^3-K41^3)/3-K40*$C$17*($C$7/2-K41),0)-K33*1*$C$18^2/2 -> 1.0197904 | L42: =1*IF(L41<$C$7/2,(L40-L39*$C$17)*(($C$7/2)^2-L41^2)/2+L39*(($C$7/2)^3-L41^3)/3-L40*$C$17*($C$7/2-L41),0)-L33*1*$C$18^2/2 -> 0.74725706 | M42: =1*IF(M41<$C$7/2,(M40-M39*$C$17)*(($C$7/2)^2-M41^2)/2+M39*(($C$7/2)^3-M41^3)/3-M40*$C$17*($C$7/2-M41),0)-M33*1*$C$18^2/2 -> 0.60503484 | N42: t·m
B43: Concepto | C43: Valor | D43: Unidad | E43: Cómo se calcula / de dónde sale | F43: Referencia | H43: sección de cortante (a d de la cara) | I43: =$C$17+$C$32/100 -> 0.21865 | J43: =$C$17+$C$32/100 -> 0.21865 | K43: =$C$17+$C$32/100 -> 0.21865 | L43: =$C$17+$C$32/100 -> 0.21865 | M43: =$C$17+$C$32/100 -> 0.21865 | N43: m
B44: q_neta — capacidad que queda para el muro | C44: =DATOS!$C$30-($C$8*DATOS!$C$24+$C$16*DATOS!$C$32) -> 16.52 | D44: t/m² | E44: CALCULADA = qa − (h·γc + h_rell·γs). | F44: Bowles 5ª ed., §8.2, pág. 404 | H44: inicio del contacto útil para Vu | I44: =IF(I39>0,MAX(I43,-I40/I39),I43) -> 0.21865 | J44: =IF(J39>0,MAX(J43,-J40/J39),J43) -> 0.21865 | K44: =IF(K39>0,MAX(K43,-K40/K39),K43) -> 0.21865 | L44: =IF(L39>0,MAX(L43,-L40/L39),L43) -> 0.21865 | M44: =IF(M39>0,MAX(M43,-M40/M39),M43) -> 0.21865 | N44: m
B45: w de servicio S1 + muro enterrado | C45: =COMBINACIONES!$E$32+$C$39 -> 6.72 | D45: t/m | E45: CALCULADA. | F45: COMBINACIONES, sección 3 | H45: Vu en una dirección, X | I45: =IF(I43>=1/2,0,MAX(0,1*IF(I44<1/2,I40*(1/2-I44)+I39*((1/2)^2-I44^2)/2,0)-I33*1*(1/2-I43))) -> 2.284562 | J45: =IF(J43>=1/2,0,MAX(0,1*IF(J44<1/2,J40*(1/2-J44)+J39*((1/2)^2-J44^2)/2,0)-J33*1*(1/2-J43))) -> 2.7084627 | K45: =IF(K43>=1/2,0,MAX(0,1*IF(K44<1/2,K40*(1/2-K44)+K39*((1/2)^2-K44^2)/2,0)-K33*1*(1/2-K43))) -> 3.7089641 | L45: =IF(L43>=1/2,0,MAX(0,1*IF(L44<1/2,L40*(1/2-L44)+L39*((1/2)^2-L44^2)/2,0)-L33*1*(1/2-L43))) -> 2.7504984 | M45: =IF(M43>=1/2,0,MAX(0,1*IF(M44<1/2,M40*(1/2-M44)+M39*((1/2)^2-M44^2)/2,0)-M33*1*(1/2-M43))) -> 2.2503207 | N45: t
B46: B mínimo con carga concéntrica | C46: =IF($C$44>0,$C$45/$C$44,999) -> 0.40677966 | D46: m | E46: CALCULADA = w / q_neta. | F46: ACI 318-19, 13.3.1.1, pág. 203 | H46: fin del contacto en el lado ligero | I46: =IF(I39>0,MIN($C$7/2,I40/I39),$C$7/2) -> 0.45 | J46: =IF(J39>0,MIN($C$7/2,J40/J39),$C$7/2) -> 0.45 | K46: =IF(K39>0,MIN($C$7/2,K40/K39),$C$7/2) -> 0.45 | L46: =IF(L39>0,MIN($C$7/2,L40/L39),$C$7/2) -> 0.45 | M46: =IF(M39>0,MIN($C$7/2,M40/M39),$C$7/2) -> 0.45 | N46: m
B47: ¿El ancho capturado alcanza para la carga concéntrica? | C47: =IF($C$7>=$C$46,"CUMPLE","NO CUMPLE — aumentar B") -> CUMPLE | D47: — | E47: Primer filtro. | F47: ACI 318-19, 13.3.1.1, pág. 203 | H47: M con tensión arriba, lado ligero ‖ X | I47: =I33*1*$C$18^2/2-1*IF(I46>$C$17,(I40+I39*$C$17)*(I46^2-$C$17^2)/2-I39*(I46^3-$C$17^3)/3-I40*$C$17*(I46-$C$17),0) -> -0.6496 | J47: =J33*1*$C$18^2/2-1*IF(J46>$C$17,(J40+J39*$C$17)*(J46^2-$C$17^2)/2-J39*(J46^3-$C$17^3)/3-J40*$C$17*(J46-$C$17),0) -> -0.77013333 | K47: =K33*1*$C$18^2/2-1*IF(K46>$C$17,(K40+K39*$C$17)*(K46^2-$C$17^2)/2-K39*(K46^3-$C$17^3)/3-K40*$C$17*(K46-$C$17),0) -> -0.50269849 | L47: =L33*1*$C$18^2/2-1*IF(L46>$C$17,(L40+L39*$C$17)*(L46^2-$C$17^2)/2-L39*(L46^3-$C$17^3)/3-L40*$C$17*(L46-$C$17),0) -> -0.23016516 | M47: =M33*1*$C$18^2/2-1*IF(M46>$C$17,(M40+M39*$C$17)*(M46^2-$C$17^2)/2-M39*(M46^3-$C$17^3)/3-M40*$C$17*(M46-$C$17),0) -> -0.087942936 | N47: t·m
B49: 5. PRESIONES DE SERVICIO, VOLTEO Y DESLIZAMIENTO (bloque S de la tabla)
B50: Concepto | C50: Valor | D50: Unidad | E50: Cómo se calcula / de dónde sale | F50: Referencia
B51: q_máx que rige | C51: =MAX($I$16:$M$16) -> 11.212222 | D51: t/m² | E51: CALCULADA. e ≤ B/6: P/B(1 + 6e/B); e > B/6: 2P/(3(B/2 − e)). | F51: Bowles 5ª ed., §8.10, págs. 449–453
B52: Combinación que da q_máx | C52: =INDEX($I$5:$M$5,MATCH($C$51,$I$16:$M$16,0)) -> S3 | D52: — | E52: CALCULADA. | F52: COMBINACIONES
B53: q_máx / q_adm (la más desfavorable) | C53: =MAX($I$20:$M$20) -> 0.62290123 | D53: — | E53: CALCULADA. | F53: DATOS, sección 3
B54: Presión máxima contra la admisible | C54: =IF($C$53<=1,"CUMPLE","NO CUMPLE — aumentar B") -> CUMPLE | D54: — | E54: Cada combinación contra su q_adm. | F54: ACI 318-19, 13.3.1.1, pág. 203
B55: q_mín (0 = despegue) | C55: =MIN($I$17:$M$17) -> 0.41362963 | D55: t/m² | E55: CALCULADA. | F55: Bowles 5ª ed., §8.10, pág. 453
B56: Con carga sostenida (S1), ¿toda la zapata está comprimida? | C56: =IF(INDEX($I$15:$M$15,1)<=$C$7/6,"CUMPLE — resultante dentro del tercio medio","NO CUMPLE — aumentar B") -> CUMPLE — resultante dentro del tercio medio | D56: — | E56: e ≤ B/6 con D + L. | F56: Bowles 5ª ed., §8.10, pág. 453
B57: w total mínima sobre el terreno | C57: =MIN($I$13:$M$13) -> 3.2656 | D57: t/m | E57: CALCULADA. | F57: Tabla por combinación
B58: ¿Hay levantamiento neto? | C58: =IF($C$57>0,"CUMPLE — no hay levantamiento","NO CUMPLE — tensión neta") -> CUMPLE — no hay levantamiento | D58: — | E58: Carga total a compresión. | F58: ACI 318-19, 13.2.6.1, págs. 199–200
B59: FS al volteo mínimo = B/(2e) | C59: =MIN($I$21:$M$21) -> 3.3859908 | D59: — | E59: CALCULADA. | F59: Bowles 5ª ed., §8.10, pág. 450
B60: Revisión por volteo | C60: =IF($C$59>=DATOS!$C$34,"CUMPLE","NO CUMPLE — aumentar B") -> CUMPLE | D60: — | E60: Contra el FS de DATOS. | F60: ACI 318-19, 13.2.6.1, págs. 199–200
B61: FS al deslizamiento mínimo = μ w / V | C61: =MIN($I$22:$M$22) -> 5.2482857 | D61: — | E61: CALCULADA. Sin empuje pasivo. | F61: NAVFAC DM 7.02, Tabla 1, pág. 7.2-63
B62: Revisión por deslizamiento | C62: =IF($C$61>=DATOS!$C$35,"CUMPLE","NO CUMPLE — dentellón o más peso") -> CUMPLE | D62: — | E62: Contra el FS de DATOS. | F62: ACI 318-19, 13.2.6.1, págs. 199–200
B64: 6. FLEXIÓN TRANSVERSAL (por metro)
B65: Concepto | C65: Valor | D65: Unidad | E65: Cómo se calcula / de dónde sale | F65: Referencia
B66: Mu en la sección crítica | C66: =MAX($I$42:$M$42) -> 1.0197904 | D66: t·m/m | E66: CALCULADA con presión neta factorizada en todo el volado. | F66: ACI 318-19, 13.2.6.6 y 13.2.7.1, pág. 201 y 202
B67: Combinación que rige | C67: =INDEX($I$25:$M$25,MATCH($C$66,$I$42:$M$42,0)) -> U3 | D67: — | E67: CALCULADA. | F67: COMBINACIONES
B68: As requerida | C68: =IF($C$66<=0,0,IF((1-2*$C$66*100000/(DATOS!$C$86*0.85*DATOS!$C$15*100*$C$32^2))<0,9999,0.85*DATOS!$C$15*100/DATOS!$C$18*$C$32*(1-SQRT((1-2*$C$66*100000/(DATOS!$C$86*0.85*DATOS!$C$15*100*$C$32^2)))))) -> 1.6149614 | D68: cm²/m | E68: CALCULADA con b = 100 cm, φ = 0.90. | F68: ACI 318-19, 22.3
B69: As mínima = ρmín · b · h | C69: =DATOS!$C$92*100*$C$8*100 -> 4.5 | D69: cm²/m | E69: CALCULADA. | F69: ACI 318-19, 7.6.1.1
B70: As de diseño | C70: =MAX($C$68,$C$69) -> 4.5 | D70: cm²/m | E70: CALCULADA. | F70: ACI 318-19, 7.6.1.1
B71: Separación calculada | C71: =MAX(DATOS!$C$91,FLOOR($C$29/$C$70*100,DATOS!$C$91)) -> 27.5 | D71: cm | E71: CALCULADA = área de varilla / As por cm, redondeada. | F71: Práctica
B72: Separación máxima = menor de 3h y 45 cm | C72: =MIN(3*$C$8*100,45) -> 45 | D72: cm | E72: CALCULADA. | F72: ACI 318-19, 7.7.2.3
B73: Separación mínima centro a centro | C73: =$C$28+MAX(2.5,$C$28,4/3*DATOS!$C$25/10) -> 3.8033333 | D73: cm | E73: CALCULADA. | F73: ACI 318-19, 25.2.1
B74: SEPARACIÓN ADOPTADA | C74: =IF($C$27>0,$C$27,MIN($C$71,FLOOR($C$72,DATOS!$C$91))) -> 27.5 | D74: cm | E74: CALCULADA. | F74: Práctica
B75: As colocada | C75: =$C$29*100/$C$74 -> 4.6181818 | D75: cm²/m | E75: CALCULADA. | F75: Geometría
B76: ¿El armado cubre el As de diseño? | C76: =IF($C$75>=$C$70-0.0001,"CUMPLE","NO CUMPLE — cerrar la separación") -> CUMPLE | D76: — | E76: As colocada ≥ As de diseño. | F76: ACI 318-19, 7.6.1.1
B77: ¿La separación está dentro de los límites? | C77: =IF($C$74>$C$72,"NO CUMPLE — mayor que la máxima",IF($C$74<$C$73,"NO CUMPLE — muy juntas","CUMPLE")) -> CUMPLE | D77: — | E77: Máxima y mínima. | F77: ACI 318-19, 7.7.2.3 y 25.2.1
B78: a — bloque de compresión | C78: =$C$75*DATOS!$C$18/(0.85*DATOS!$C$15*100) -> 0.91277005 | D78: cm | E78: CALCULADA. | F78: ACI 318-19, 22.2.2.4.1
B79: εt | C79: =0.003*($C$32-$C$78/DATOS!$C$22)/($C$78/DATOS!$C$22) -> 0.044115645 | D79: — | E79: CALCULADA. | F79: ACI 318-19, 22.2.2.1
B80: φ según εt | C80: =IF($C$79>=DATOS!$C$21+0.003,0.9,IF($C$79<=DATOS!$C$21,0.65,0.65+0.25*($C$79-DATOS!$C$21)/0.003)) -> 0.9 | D80: — | E80: CALCULADA. | F80: ACI 318-19, Tabla 21.2.2
B81: φMn | C81: =$C$80*$C$75*DATOS!$C$18*($C$32-$C$78/2)/100000 -> 2.8644072 | D81: t·m/m | E81: CALCULADA. | F81: ACI 318-19, 22.3
B82: φMn contra Mu | C82: =IF(AND($C$81>=$C$66,$C$79>=DATOS!$C$21+0.003),"CUMPLE","NO CUMPLE — aumentar h o el armado") -> CUMPLE | D82: — | E82: φMn ≥ Mu. | F82: ACI 318-19, 7.3.3.1 y 22.3
B83: ARMADO TRANSVERSAL | C83: ="#"&$C$25&" @ "&TEXT($C$74,"0.0")&" cm" -> #4 @ 27.5 cm | D83: — | E83: Resultado. | F83: Resultado
B85: 7. CORTANTE EN UNA DIRECCIÓN (por metro) — a d de la sección crítica
B86: Concepto | C86: Valor | D86: Unidad | E86: Cómo se calcula / de dónde sale | F86: Referencia
B87: Vu en la sección crítica | C87: =MAX($I$45:$M$45) -> 3.7089641 | D87: t/m | E87: CALCULADA. | F87: ACI 318-19, 13.2.7.2, pág. 202
B88: ρw con el armado colocado | C88: =$C$75/(100*$C$32) -> 0.002738323 | D88: — | E88: CALCULADA. | F88: ACI 318-19, 22.5.5.1
B89: λs | C89: =IF(DATOS!$C$90="SÍ",1,MIN(1,SQRT(2/(1+0.004*$C$32*10)))) -> 1 | D89: — | E89: CALCULADA. | F89: ACI 318-19, 13.2.6.2, pág. 200
B90: Vc = 0.66 λs λ ρw^⅓ √f'c b d | C90: =0.66*$C$89*DATOS!$C$23*$C$88^(1/3)*DATOS!$C$17*DATOS!$C$89*100*$C$32/1000 -> 7.8626507 | D90: t/m | E90: CALCULADA en MPa → t. | F90: ACI 318-19, Tabla 22.5.5.1(c)
B91: Vc máximo = 0.42 λ √f'c b d | C91: =0.42*DATOS!$C$23*DATOS!$C$17*DATOS!$C$89*100*$C$32/1000 -> 35.764002 | D91: t/m | E91: CALCULADA. | F91: ACI 318-19, 22.5.5.1.1
B92: φVc | C92: =DATOS!$C$87*MIN($C$90,$C$91) -> 5.896988 | D92: t/m | E92: CALCULADA. | F92: ACI 318-19, Tabla 21.2.1(b)
B93: Revisión por cortante | C93: =IF($C$92>=$C$87,"CUMPLE","NO CUMPLE — aumentar h o el armado") -> CUMPLE | D93: — | E93: Vu ≤ φVc. | F93: ACI 318-19, 22.5.1.1
B94: Momento con tensión arriba (despegue) | C94: =MAX(0,MAX($I$47:$M$47)) -> 0 | D94: t·m/m | E94: CALCULADA en el lado ligero. | F94: ACI 318-19, 13.2.6.6, pág. 201
B95: As superior que pediría ese momento | C95: =IF($C$94<=0,0,IF((1-2*$C$94*100000/(DATOS!$C$86*0.85*DATOS!$C$15*100*($C$8*100-5-$C$28/2)^2))<0,9999,0.85*DATOS!$C$15*100/DATOS!$C$18*($C$8*100-5-$C$28/2)*(1-SQRT((1-2*$C$94*100000/(DATOS!$C$86*0.85*DATOS!$C$15*100*($C$8*100-5-$C$28/2)^2)))))) -> 0 | D95: cm²/m | E95: CALCULADA con d = h − 5 cm − db/2. Si es mayor que cero, usa al menos ρmín b h arriba. | F95: ACI 318-19, 22.3 y 7.6.1.1
B96: ¿Hace falta acero arriba? | C96: =IF($C$94>0.001,"REVISAR — hay tensión arriba: agrega acero superior (ver renglón anterior)","CUMPLE — no hay tensión arriba") -> CUMPLE — no hay tensión arriba | D96: — | E96: Sólo aparece con momentos grandes en el muro. | F96: Revisión de esta hoja
B98: 8. REFUERZO LONGITUDINAL POR CONTRACCIÓN Y TEMPERATURA
B99: Concepto | C99: Valor | D99: Unidad | E99: Cómo se calcula / de dónde sale | F99: Referencia
B100: As longitudinal = ρmín · B · h | C100: =DATOS!$C$92*$C$7*100*$C$8*100 -> 4.05 | D100: cm² | E100: CALCULADA sobre la sección transversal completa. | F100: ACI 318-19, 24.4.3.2
B101: Separación máxima = menor de 5h y 45 cm | C101: =MIN(5*$C$8*100,45) -> 45 | D101: cm | E101: CALCULADA. | F101: ACI 318-19, 24.4.3.3
B102: Varillas longitudinales | C102: =MAX(2,CEILING($C$100/$C$31,1),CEILING(($C$7*100-2*$C$14-$C$30)/$C$101,1)+1) -> 6 | D102: pzas | E102: CALCULADA. | F102: ACI 318-19, 24.4.3.2 y 24.4.3.3 · 13.3.2.2, pág. 203
B103: Separación longitudinal | C103: =($C$7*100-2*$C$14-$C$30)/($C$102-1) -> 14.81 | D103: cm | E103: CALCULADA: repartidas en todo el ancho. | F103: ACI 318-19, 13.3.2.2, pág. 203
B104: Refuerzo longitudinal | C104: =IF(AND($C$102*$C$31>=$C$100,$C$103<=$C$101),"CUMPLE","NO CUMPLE — más varillas") -> CUMPLE | D104: — | E104: As y separación. | F104: ACI 318-19, 24.4.3
...

Sheet LINDERO
B1: ZAPATA DE LINDERO (COLUMNA AL PAÑO DEL LINDERO) — ACI 318-19 | H1: TABLA POR COMBINACIÓN — la memoria (col. B–F) toma de aquí lo que rige
B2: =DATOS!$C$9&" · "&DATOS!$C$10 -> Ejemplo — nave industrial · Columna tipo eje B-2 · muro eje 1 | H2: Cada columna es una combinación de la hoja COMBINACIONES. Bloque S: presiones y estabilidad con la carga TOTAL (zapata, relleno y dado por su γD). Bloque U: diseño con presión NETA, ACI 13.2.6.3 y R13.2.6.3. X es perpendicular al lindero.
B3: Se capturan sólo las celdas amarillas de las secciones 1, 2 y 13; cargas, materiales y suelo vienen de DATOS. A la derecha (columnas H a N) está la tabla por combinación de donde salen los valores que rigen.
B4: CÓMO TRABAJA: el dado queda al paño del lindero y la zapata crece hacia adentro, así que la carga cae a una distancia e del centro. Con CONTRATRABE DE EQUILIBRIO (liga a la columna interior) la contratrabe toma P·e y el momento en X, y la zapata recibe presión uniforme en X. SIN contratrabe el suelo toma toda la excentricidad y casi nunca pasa con D + L. | H4: BLOQUE S — SERVICIO
H5: Combinación | I5: =COMBINACIONES!$B$6 -> S1 | J5: =COMBINACIONES!$B$7 -> S2 | K5: =COMBINACIONES!$B$8 -> S3 | L5: =COMBINACIONES!$B$9 -> S4 | M5: =COMBINACIONES!$B$10 -> S5
B6: 1. GEOMETRÍA — el dado queda al paño del lindero; X es perpendicular al lindero | H6: Descripción | I6: =COMBINACIONES!$C$6 -> D + L | J6: =COMBINACIONES!$C$7 -> D + 0.7E | K6: =COMBINACIONES!$C$8 -> D + 0.75L + 0.525E | L6: =COMBINACIONES!$C$9 -> 0.6D + 0.7E (P de A suma) | M6: =COMBINACIONES!$C$10 -> 0.6D + 0.7E (P de A resta)
B7: Concepto | C7: Valor | D7: Unidad | E7: Cómo se calcula / de dónde sale | F7: Referencia | H7: γD | I7: =COMBINACIONES!$E$6 -> 1 | J7: =COMBINACIONES!$E$7 -> 1 | K7: =COMBINACIONES!$E$8 -> 1 | L7: =COMBINACIONES!$E$9 -> 0.6 | M7: =COMBINACIONES!$E$10 -> 0.6 | N7: —
B8: Lx — lado perpendicular al lindero | C8: 1.8 | D8: m | E8: CAPTURA. La zapata sólo crece hacia adentro del predio. | F8: Propuesta — se verifica en la sección 5 | H8: γA | I8: =COMBINACIONES!$G$6 -> 0 | J8: =COMBINACIONES!$G$7 -> 0.7 | K8: =COMBINACIONES!$G$8 -> 0.525 | L8: =COMBINACIONES!$G$9 -> 0.7 | M8: =COMBINACIONES!$G$10 -> 0.7 | N8: —
B9: Ly — lado paralelo al lindero | C9: 2.6 | D9: m | E9: CAPTURA. La columna queda centrada en Ly. | F9: Propuesta — se verifica en la sección 5 | H9: P de la columna | I9: =COMBINACIONES!$E$19 -> 42 | J9: =COMBINACIONES!$E$20 -> 34.2 | K9: =COMBINACIONES!$E$21 -> 42.15 | L9: =COMBINACIONES!$E$22 -> 22.2 | M9: =COMBINACIONES!$E$23 -> 13.8 | N9: t
B10: h — peralte total de la zapata | C10: 0.5 | D10: m | E10: CAPTURA. Los mínimos por penetración y por dovelas salen en las secciones 4 y 12. | F10: Propuesta — se verifica en las secciones 6, 9 y 12 | H10: Mx de la columna | I10: =COMBINACIONES!$F$19 -> 1.2 | J10: =COMBINACIONES!$F$20 -> 4.65 | K10: =COMBINACIONES!$F$21 -> 3.9875 | L10: =COMBINACIONES!$F$22 -> 4.33 | M10: =COMBINACIONES!$F$23 -> 4.33 | N10: t·m
B11: Df — profundidad de desplante | C11: 1.5 | D11: m | E11: CAPTURA. Del nivel de terreno a la cara inferior de la zapata. | F11: Estudio de mecánica de suelos / proyecto | H11: My de la columna | I11: =COMBINACIONES!$G$19 -> 0.9 | J11: =COMBINACIONES!$G$20 -> 5.15 | K11: =COMBINACIONES!$G$21 -> 4.2375 | L11: =COMBINACIONES!$G$22 -> 4.91 | M11: =COMBINACIONES!$G$23 -> 4.91 | N11: t·m
B12: r — recubrimiento libre inferior | C12: 7.5 | D12: cm | E12: CAPTURA. Concreto colado contra el suelo: 75 mm. | F12: ACI 318-19, Tabla 20.5.1.3.1 (ver TABLAS) | H12: Vx de la columna | I12: =COMBINACIONES!$H$19 -> 0.3 | J12: =COMBINACIONES!$H$20 -> 1.95 | K12: =COMBINACIONES!$H$21 -> 1.5875 | L12: =COMBINACIONES!$H$22 -> 1.87 | M12: =COMBINACIONES!$H$23 -> 1.87 | N12: t
B13: r_lat — recubrimiento en las puntas de las varillas | C13: 7.5 | D13: cm | E13: CAPTURA. Caras laterales coladas contra el suelo (también la del lindero). | F13: ACI 318-19, Tabla 20.5.1.3.1 | H13: Vy de la columna | I13: =COMBINACIONES!$I$19 -> 0.4 | J13: =COMBINACIONES!$I$20 -> 1.7 | K13: =COMBINACIONES!$I$21 -> 1.425 | L13: =COMBINACIONES!$I$22 -> 1.58 | M13: =COMBINACIONES!$I$23 -> 1.58 | N13: t
B14: r_sup — recubrimiento superior | C14: 5 | D14: cm | E14: CAPTURA. Cara superior bajo relleno: 50 mm (40 mm para #5 y menores). | F14: ACI 318-19, Tabla 20.5.1.3.1 | H14: P en el eje de la columna = P + γD·W_dado | I14: =I9+I7*$C$57 -> 42.69 | J14: =J9+J7*$C$57 -> 34.89 | K14: =K9+K7*$C$57 -> 42.84 | L14: =L9+L7*$C$57 -> 22.614 | M14: =M9+M7*$C$57 -> 14.214 | N14: t
B15: ¿Lleva contratrabe de equilibrio a la columna interior? | C15: SÍ | D15: — | E15: CAPTURA (lista). SÍ: la contratrabe toma P·e y el momento de la columna en X, y la zapata recibe presión uniforme en X. NO: el suelo toma toda la excentricidad. | F15: ACI 318-19, 13.2.6.4, pág. 200 · Bowles 5ª ed., §9.4 | H15: My en el desplante = My + Vx·brazo | I15: =I11+I12*$C$22 -> 1.395 | J15: =J11+J12*$C$22 -> 8.3675 | K15: =K11+K12*$C$22 -> 6.856875 | L15: =L11+L12*$C$22 -> 7.9955 | M15: =M11+M12*$C$22 -> 7.9955 | N15: t·m
B16: Ls — distancia entre ejes, columna de lindero a columna interior | C16: 6 | D16: m | E16: CAPTURA. Sólo se usa con contratrabe. | F16: Retícula del proyecto | H16: Mx en el desplante = Mx + Vy·brazo | I16: =I10+I13*$C$22 -> 1.86 | J16: =J10+J13*$C$22 -> 7.455 | K16: =K10+K13*$C$22 -> 6.33875 | L16: =L10+L13*$C$22 -> 6.937 | M16: =M10+M13*$C$22 -> 6.937 | N16: t·m
B17: P muerta de servicio de la columna interior (caso D) | C17: 30 | D17: t | E17: CAPTURA. Para revisar que la contratrabe no levante la columna interior. Sólo con contratrabe. | F17: Modelo de análisis (STAAD) · tabla de reacciones | H17: R — carga de la columna que toma la zapata (con contratrabe = (P·Ls + My)/(Ls − e)) | I17: =IF($C$15="SÍ",(I14*$C$16+I15)/($C$16-$C$24),I14) -> 48.137383 | J17: =IF($C$15="SÍ",(J14*$C$16+J15)/($C$16-$C$24),J14) -> 40.692991 | K17: =IF($C$15="SÍ",(K14*$C$16+K15)/($C$16-$C$24),K14) -> 49.326519 | L17: =IF($C$15="SÍ",(L14*$C$16+L15)/($C$16-$C$24),L14) -> 26.855981 | M17: =IF($C$15="SÍ",(M14*$C$16+M15)/($C$16-$C$24),M14) -> 17.435421 | N17: t
B18: A — área de la zapata | C18: =$C$8*$C$9 -> 4.68 | D18: m² | E18: CALCULADA = Lx · Ly. | F18: Geometría | H18: ΔP = R − P (se lo quita a la columna interior) | I18: =I17-I14 -> 5.4473832 | J18: =J17-J14 -> 5.8029907 | K18: =K17-K14 -> 6.4865187 | L18: =L17-L14 -> 4.2419813 | M18: =M17-M14 -> 3.2214206 | N18: t
B19: β — relación lado largo / lado corto | C19: =MAX($C$8,$C$9)/MIN($C$8,$C$9) -> 1.4444444 | D19: — | E19: CALCULADA. | F19: ACI 318-19, 13.3.3.3, pág. 204 | H19: γD · (W_zap + W_rell) | I19: =I7*$C$58 -> 12.704 | J19: =J7*$C$58 -> 12.704 | K19: =K7*$C$58 -> 12.704 | L19: =L7*$C$58 -> 7.6224 | M19: =M7*$C$58 -> 7.6224 | N19: t
B20: h_rell — relleno sobre la zapata | C20: =$C$11-$C$10 -> 1 | D20: m | E20: CALCULADA = Df − h. | F20: Geometría | H20: P total sobre el terreno | I20: =I17+I19 -> 60.841383 | J20: =J17+J19 -> 53.396991 | K20: =K17+K19 -> 62.030519 | L20: =L17+L19 -> 34.478381 | M20: =M17+M19 -> 25.057821 | N20: t
B21: H_dado — altura del dado sobre la zapata | C21: =$C$11-$C$10+DATOS!$C$66 -> 1.15 | D21: m | E21: CALCULADA = Df − h + altura del dado sobre el terreno (DATOS). | F21: Geometría | H21: M en X respecto al centro de la zapata (sin contratrabe = P·e + My) | I21: =IF($C$15="SÍ",0,I14*$C$24+I15) -> 0 | J21: =IF($C$15="SÍ",0,J14*$C$24+J15) -> 0 | K21: =IF($C$15="SÍ",0,K14*$C$24+K15) -> 0 | L21: =IF($C$15="SÍ",0,L14*$C$24+L15) -> 0 | M21: =IF($C$15="SÍ",0,M14*$C$24+M15) -> 0 | N21: t·m
B22: Brazo del cortante V hasta el desplante | C22: =IF(DATOS!$C$70="CARA SUPERIOR DEL DADO",$C$21+$C$10,$C$10) -> 1.65 | D22: m | E22: CALCULADA. M_desplante = M + V·brazo. | F22: Estática · DATOS, sección 6 | H22: ex = M / P | I22: =IF(I20>0,I21/I20,99) -> 0 | J22: =IF(J20>0,J21/J20,99) -> 0 | K22: =IF(K20>0,K21/K20,99) -> 0 | L22: =IF(L20>0,L21/L20,99) -> 0 | M22: =IF(M20>0,M21/M20,99) -> 0 | N22: m
B23: Brazo del cortante V hasta la cara superior de la zapata | C23: =IF(DATOS!$C$70="CARA SUPERIOR DEL DADO",$C$21,0) -> 1.15 | D23: m | E23: CALCULADA. Para el momento que el dado le pasa a la zapata (penetración). | F23: Estática | H23: ey = Mx / P | I23: =IF(I20>0,I16/I20,99) -> 0.030571297 | J23: =IF(J20>0,J16/J20,99) -> 0.13961461 | K23: =IF(K20>0,K16/K20,99) -> 0.1021876 | L23: =IF(L20>0,L16/L20,99) -> 0.20119854 | M23: =IF(M20>0,M16/M20,99) -> 0.27683972 | N23: m
B24: e — del eje de la columna al centro de la zapata | C24: =$C$8/2-DATOS!$C$64/2 -> 0.65 | D24: m | E24: CALCULADA = Lx/2 − cx/2. | F24: Geometría | H24: Índice de núcleo 6ex/Lx + 6ey/Ly (≤ 1: contacto total) | I24: =6*I22/$C$8+6*I23/$C$9 -> 0.070549147 | J24: =6*J22/$C$8+6*J23/$C$9 -> 0.32218756 | K24: =6*K22/$C$8+6*K23/$C$9 -> 0.23581754 | L24: =6*L22/$C$8+6*L23/$C$9 -> 0.46430432 | M24: =6*M22/$C$8+6*M23/$C$9 -> 0.63886089 | N24: —
B25: Ix — momento de inercia de la base (gira alrededor de X) | C25: =$C$8*$C$9^3/12 -> 2.6364 | D25: m⁴ | E25: CALCULADA = Lx·Ly³/12. | F25: Mecánica de materiales | H25: Kx (factor uniaxial en X) | I25: =IF(I22<=$C$8/6,1+6*I22/$C$8,IF(I22<$C$8/2,4*$C$8/(3*($C$8-2*I22)),999)) -> 1 | J25: =IF(J22<=$C$8/6,1+6*J22/$C$8,IF(J22<$C$8/2,4*$C$8/(3*($C$8-2*J22)),999)) -> 1 | K25: =IF(K22<=$C$8/6,1+6*K22/$C$8,IF(K22<$C$8/2,4*$C$8/(3*($C$8-2*K22)),999)) -> 1 | L25: =IF(L22<=$C$8/6,1+6*L22/$C$8,IF(L22<$C$8/2,4*$C$8/(3*($C$8-2*L22)),999)) -> 1 | M25: =IF(M22<=$C$8/6,1+6*M22/$C$8,IF(M22<$C$8/2,4*$C$8/(3*($C$8-2*M22)),999)) -> 1 | N25: —
B26: Iy — momento de inercia de la base (gira alrededor de Y) | C26: =$C$9*$C$8^3/12 -> 1.2636 | D26: m⁴ | E26: CALCULADA = Ly·Lx³/12. | F26: Mecánica de materiales | H26: Ky (factor uniaxial en Y) | I26: =IF(I23<=$C$9/6,1+6*I23/$C$9,IF(I23<$C$9/2,4*$C$9/(3*($C$9-2*I23)),999)) -> 1.0705491 | J26: =IF(J23<=$C$9/6,1+6*J23/$C$9,IF(J23<$C$9/2,4*$C$9/(3*($C$9-2*J23)),999)) -> 1.3221876 | K26: =IF(K23<=$C$9/6,1+6*K23/$C$9,IF(K23<$C$9/2,4*$C$9/(3*($C$9-2*K23)),999)) -> 1.2358175 | L26: =IF(L23<=$C$9/6,1+6*L23/$C$9,IF(L23<$C$9/2,4*$C$9/(3*($C$9-2*L23)),999)) -> 1.4643043 | M26: =IF(M23<=$C$9/6,1+6*M23/$C$9,IF(M23<$C$9/2,4*$C$9/(3*($C$9-2*M23)),999)) -> 1.6388609 | N26: —
B27: Ancho del apoyo para las varillas ‖ Y | C27: =IF($C$15="SÍ",MIN(DATOS!$C$65,$C$238),DATOS!$C$65) -> 0.4 | D27: m | E27: CALCULADA: con contratrabe, el menor entre cy y el ancho de la contratrabe; sin ella, cy. | F27: ACI 318-19, Tabla 13.2.7.1, pág. 202 | H27: q máx | I27: =IF(I20<=0,999,IF(I24<=1,I20/$C$18*(1+I24),MIN(999,I20/$C$18*I25*I26))) -> 13.917455 | J27: =IF(J20<=0,999,IF(J24<=1,J20/$C$18*(1+J24),MIN(999,J20/$C$18*J25*J26))) -> 15.085649 | K27: =IF(K20<=0,999,IF(K24<=1,K20/$C$18*(1+K24),MIN(999,K20/$C$18*K25*K26))) -> 16.380001 | L27: =IF(L20<=0,999,IF(L24<=1,L20/$C$18*(1+L24),MIN(999,L20/$C$18*L25*L26))) -> 10.787787 | M27: =IF(M20<=0,999,IF(M24<=1,M20/$C$18*(1+M24),MIN(999,M20/$C$18*M25*M26))) -> 8.7748466 | N27: t/m²
B28: Volado en X desde la cara interior del dado | C28: =$C$8-DATOS!$C$64 -> 1.3 | D28: m | E28: CALCULADA = Lx − cx. | F28: Geometría | H28: q mín (0 = despegue) | I28: =IF(I20<=0,0,IF(I24<=1,I20/$C$18*(1-I24),0)) -> 12.083136 | J28: =IF(J20<=0,0,IF(J24<=1,J20/$C$18*(1-J24),0)) -> 7.7335779 | K28: =IF(K20<=0,0,IF(K24<=1,K20/$C$18*(1-K24),0)) -> 10.128768 | L28: =IF(L20<=0,0,IF(L24<=1,L20/$C$18*(1-L24),0)) -> 3.9465641 | M28: =IF(M20<=0,0,IF(M24<=1,M20/$C$18*(1-M24),0)) -> 1.9336237 | N28: t/m²
B29: Volado en Y desde la cara del apoyo | C29: =($C$9-$C$27)/2 -> 1.1 | D29: m | E29: CALCULADA = (Ly − ancho del apoyo)/2. | F29: Geometría | H29: Contacto | I29: =IF(I24<=1,"TOTAL","PARCIAL") -> TOTAL | J29: =IF(J24<=1,"TOTAL","PARCIAL") -> TOTAL | K29: =IF(K24<=1,"TOTAL","PARCIAL") -> TOTAL | L29: =IF(L24<=1,"TOTAL","PARCIAL") -> TOTAL | M29: =IF(M24<=1,"TOTAL","PARCIAL") -> TOTAL | N29: —
B30: Ln — claro libre de la contratrabe | C30: =IF($C$15="SÍ",$C$16-$C$8,0) -> 4.2 | D30: m | E30: CALCULADA = Ls − Lx: de la orilla interior de la zapata al paño del dado interior (dados iguales). | F30: Geometría | H30: q adm (con incremento si hay A) | I30: =DATOS!$C$30*IF(I8>0,DATOS!$C$31,1) -> 18 | J30: =DATOS!$C$30*IF(J8>0,DATOS!$C$31,1) -> 18 | K30: =DATOS!$C$30*IF(K8>0,DATOS!$C$31,1) -> 18 | L30: =DATOS!$C$30*IF(L8>0,DATOS!$C$31,1) -> 18 | M30: =DATOS!$C$30*IF(M8>0,DATOS!$C$31,1) -> 18 | N30: t/m²
B31: ¿La geometría es coherente? | C31: =IF(AND($C$28>0,$C$29>0,$C$20>=0,OR($C$15="NO",$C$30>0)),"CUMPLE","NO CUMPLE — Lx > cx, Ly > apoyo, Df ≥ h y Ls > Lx") -> CUMPLE | D31: — | E31: Revisa volados, desplante y que la contratrabe tenga claro. | F31: Geometría | H31: q máx / q adm | I31: =I27/I30 -> 0.77319196 | J31: =J27/J30 -> 0.83809161 | K31: =K27/K30 -> 0.91000004 | L31: =L27/L30 -> 0.5993215 | M31: =M27/M30 -> 0.48749148 | N31: —
H32: FS volteo X = Lx/(2ex) | I32: =IF(I22>0.0001,$C$8/(2*I22),99) -> 99 | J32: =IF(J22>0.0001,$C$8/(2*J22),99) -> 99 | K32: =IF(K22>0.0001,$C$8/(2*K22),99) -> 99 | L32: =IF(L22>0.0001,$C$8/(2*L22),99) -> 99 | M32: =IF(M22>0.0001,$C$8/(2*M22),99) -> 99 | N32: —
B33: 2. VARILLAS Y PERALTES EFECTIVOS | H33: FS volteo Y = Ly/(2ey) | I33: =IF(I23>0.0001,$C$9/(2*I23),99) -> 42.523547 | J33: =IF(J23>0.0001,$C$9/(2*J23),99) -> 9.3113465 | K33: =IF(K23>0.0001,$C$9/(2*K23),99) -> 12.7217 | L33: =IF(L23>0.0001,$C$9/(2*L23),99) -> 6.4612795 | M33: =IF(M23>0.0001,$C$9/(2*M23),99) -> 4.695858 | N33: —
B34: Concepto | C34: Valor | D34: Unidad | E34: Cómo se calcula / de dónde sale | F34: Referencia | H34: V horizontal = √(Vx² + Vy²) | I34: =SQRT(I12^2+I13^2) -> 0.5 | J34: =SQRT(J12^2+J13^2) -> 2.5869867 | K34: =SQRT(K12^2+K13^2) -> 2.133256 | L34: =SQRT(L12^2+L13^2) -> 2.4481217 | M34: =SQRT(M12^2+M13^2) -> 2.4481217 | N34: t
B35: Varilla del lecho inferior ‖ X (se reparte sobre Ly) | C35: 5 | D35: # | E35: CAPTURA (lista). | F35: Propuesta | H35: FS deslizamiento = μ·P/V | I35: =IF(I34>0.0001,DATOS!$C$33*I20/I34,99) -> 54.757245 | J35: =IF(J34>0.0001,DATOS!$C$33*J20/J34,99) -> 9.2882759 | K35: =IF(K34>0.0001,DATOS!$C$33*K20/K34,99) -> 13.085037 | L35: =IF(L34>0.0001,DATOS!$C$33*L20/L34,99) -> 6.3376226 | M35: =IF(M34>0.0001,DATOS!$C$33*M20/M34,99) -> 4.605988 | N35: —
B36: Varilla del lecho inferior ‖ Y (se reparte sobre Lx) | C36: 5 | D36: # | E36: CAPTURA (lista). | F36: Propuesta | H36: Margen en la columna interior = γD·PD,int − ΔP | I36: =IF($C$15="SÍ",I7*$C$17-I18,0) -> 24.552617 | J36: =IF($C$15="SÍ",J7*$C$17-J18,0) -> 24.197009 | K36: =IF($C$15="SÍ",K7*$C$17-K18,0) -> 23.513481 | L36: =IF($C$15="SÍ",L7*$C$17-L18,0) -> 13.758019 | M36: =IF($C$15="SÍ",M7*$C$17-M18,0) -> 14.778579 | N36: t
B37: ¿Qué varillas van hasta abajo? | C37: ‖ Y | D37: — | E37: CAPTURA (lista). Con contratrabe conviene abajo ‖ Y (es la dirección que trabaja); sin ella, ‖ X. | F37: Práctica de armado
B38: Separación ‖ X que tú fijas (0 = la calcula la hoja) | C38: 0 | D38: cm | E38: CAPTURA. Déjala en 0 para que la hoja proponga la separación; si pones un valor, la hoja la revisa. | F38: Propuesta | H38: BLOQUE U — RESISTENCIA (cargas factorizadas)
B39: Separación ‖ Y que tú fijas (0 = la calcula la hoja) | C39: 0 | D39: cm | E39: CAPTURA. Mismo criterio. | F39: Propuesta | H39: Combinación | I39: =COMBINACIONES!$B$11 -> U1 | J39: =COMBINACIONES!$B$12 -> U2 | K39: =COMBINACIONES!$B$13 -> U3 | L39: =COMBINACIONES!$B$14 -> U4 | M39: =COMBINACIONES!$B$15 -> U5
B40: ¿Lleva parrilla superior? | C40: NO | D40: — | E40: CAPTURA (lista). Se vuelve obligatoria si hay momento negativo (sección 10). | F40: Práctica · sección 10 de esta hoja | H40: Descripción | I40: =COMBINACIONES!$C$11 -> 1.4D | J40: =COMBINACIONES!$C$12 -> 1.2D + 1.6L | K40: =COMBINACIONES!$C$13 -> 1.2D + 1.0L + 1.0E | L40: =COMBINACIONES!$C$14 -> 0.9D + 1.0E (P de A suma) | M40: =COMBINACIONES!$C$15 -> 0.9D + 1.0E (P de A resta)
B41: Varilla de la parrilla superior | C41: 4 | D41: # | E41: CAPTURA (lista). Sólo se usa si hay parrilla superior. | F41: Propuesta | H41: γD | I41: =COMBINACIONES!$E$11 -> 1.4 | J41: =COMBINACIONES!$E$12 -> 1.2 | K41: =COMBINACIONES!$E$13 -> 1.2 | L41: =COMBINACIONES!$E$14 -> 0.9 | M41: =COMBINACIONES!$E$15 -> 0.9 | N41: —
B42: db ‖ X | C42: =INDEX(TABLAS!$C$6:$C$13,MATCH($C$35,TABLAS!$B$6:$B$13,0)) -> 1.59 | D42: cm | E42: CALCULADA con la tabla de varillas. | F42: TABLAS, tabla 1 | H42: γA | I42: =COMBINACIONES!$G$11 -> 0 | J42: =COMBINACIONES!$G$12 -> 0 | K42: =COMBINACIONES!$G$13 -> 1 | L42: =COMBINACIONES!$G$14 -> 1 | M42: =COMBINACIONES!$G$15 -> 1 | N42: —
B43: Área de una varilla ‖ X | C43: =INDEX(TABLAS!$D$6:$D$13,MATCH($C$35,TABLAS!$B$6:$B$13,0)) -> 1.98 | D43: cm² | E43: CALCULADA con la tabla de varillas. | F43: TABLAS, tabla 1 | H43: Pu de la columna | I43: =COMBINACIONES!$E$24 -> 42 | J43: =COMBINACIONES!$E$25 -> 55.2 | K43: =COMBINACIONES!$E$26 -> 54 | L43: =COMBINACIONES!$E$27 -> 33 | M43: =COMBINACIONES!$E$28 -> 21 | N43: t
B44: db ‖ Y | C44: =INDEX(TABLAS!$C$6:$C$13,MATCH($C$36,TABLAS!$B$6:$B$13,0)) -> 1.59 | D44: cm | E44: CALCULADA. | F44: TABLAS, tabla 1 | H44: Mux de la columna | I44: =COMBINACIONES!$F$24 -> 1.12 | J44: =COMBINACIONES!$F$25 -> 1.6 | K44: =COMBINACIONES!$F$26 -> 6.86 | L44: =COMBINACIONES!$F$27 -> 6.22 | M44: =COMBINACIONES!$F$28 -> 6.22 | N44: t·m
B45: Área de una varilla ‖ Y | C45: =INDEX(TABLAS!$D$6:$D$13,MATCH($C$36,TABLAS!$B$6:$B$13,0)) -> 1.98 | D45: cm² | E45: CALCULADA. | F45: TABLAS, tabla 1 | H45: Muy de la columna | I45: =COMBINACIONES!$G$24 -> 0.84 | J45: =COMBINACIONES!$G$25 -> 1.2 | K45: =COMBINACIONES!$G$26 -> 7.52 | L45: =COMBINACIONES!$G$27 -> 7.04 | M45: =COMBINACIONES!$G$28 -> 7.04 | N45: t·m
B46: db de la parrilla superior | C46: =INDEX(TABLAS!$C$6:$C$13,MATCH($C$41,TABLAS!$B$6:$B$13,0)) -> 1.27 | D46: cm | E46: CALCULADA. | F46: TABLAS, tabla 1 | H46: Vux de la columna | I46: =COMBINACIONES!$H$24 -> 0.28 | J46: =COMBINACIONES!$H$25 -> 0.4 | K46: =COMBINACIONES!$H$26 -> 2.84 | L46: =COMBINACIONES!$H$27 -> 2.68 | M46: =COMBINACIONES!$H$28 -> 2.68 | N46: t
B47: Área de una varilla de la parrilla superior | C47: =INDEX(TABLAS!$D$6:$D$13,MATCH($C$41,TABLAS!$B$6:$B$13,0)) -> 1.27 | D47: cm² | E47: CALCULADA. | F47: TABLAS, tabla 1 | H47: Vuy de la columna | I47: =COMBINACIONES!$I$24 -> 0.42 | J47: =COMBINACIONES!$I$25 -> 0.52 | K47: =COMBINACIONES!$I$26 -> 2.46 | L47: =COMBINACIONES!$I$27 -> 2.27 | M47: =COMBINACIONES!$I$28 -> 2.27 | N47: t
B48: dx — peralte efectivo de las varillas ‖ X | C48: =$C$10*100-$C$12-IF($C$37="‖ X",$C$42/2,$C$44+$C$42/2) -> 40.115 | D48: cm | E48: CALCULADA = h − r − db/2, restando además el lecho de abajo si ‖ X va encima. | F48: Geometría | H48: Pu en el eje de la columna = Pu + γD·W_dado | I48: =I43+I41*$C$57 -> 42.966 | J48: =J43+J41*$C$57 -> 56.028 | K48: =K43+K41*$C$57 -> 54.828 | L48: =L43+L41*$C$57 -> 33.621 | M48: =M43+M41*$C$57 -> 21.621 | N48: t
B49: dy — peralte efectivo de las varillas ‖ Y | C49: =$C$10*100-$C$12-IF($C$37="‖ Y",$C$44/2,$C$42+$C$44/2) -> 41.705 | D49: cm | E49: CALCULADA con el mismo criterio. | F49: Geometría | H49: Muy en el desplante = Muy + Vux·brazo | I49: =I45+I46*$C$22 -> 1.302 | J49: =J45+J46*$C$22 -> 1.86 | K49: =K45+K46*$C$22 -> 12.206 | L49: =L45+L46*$C$22 -> 11.462 | M49: =M45+M46*$C$22 -> 11.462 | N49: t·m
B50: d_prom — peralte efectivo promedio | C50: =($C$48+$C$49)/2 -> 40.91 | D50: cm | E50: CALCULADA. Es el que se usa en penetración. | F50: Geometría | H50: Mux en el desplante = Mux + Vuy·brazo | I50: =I44+I47*$C$22 -> 1.813 | J50: =J44+J47*$C$22 -> 2.458 | K50: =K44+K47*$C$22 -> 10.919 | L50: =L44+L47*$C$22 -> 9.9655 | M50: =M44+M47*$C$22 -> 9.9655 | N50: t·m
B51: ¿El peralte efectivo es de al menos 15 cm? | C51: =IF(MIN($C$48,$C$49)>=15,"CUMPLE","NO CUMPLE — aumentar h") -> CUMPLE | D51: — | E51: Peralte efectivo del refuerzo inferior ≥ 150 mm. | F51: ACI 318-19, 13.3.1.2, pág. 203 | H51: Ru — carga factorizada que toma la zapata | I51: =IF($C$15="SÍ",(I48*$C$16+I49)/($C$16-$C$24),I48) -> 48.429533 | J51: =IF($C$15="SÍ",(J48*$C$16+J49)/($C$16-$C$24),J48) -> 63.182804 | K51: =IF($C$15="SÍ",(K48*$C$16+K49)/($C$16-$C$24),K48) -> 63.770841 | L51: =IF($C$15="SÍ",(L48*$C$16+L49)/($C$16-$C$24),L48) -> 39.848224 | M51: =IF($C$15="SÍ",(M48*$C$16+M49)/($C$16-$C$24),M48) -> 26.39028 | N51: t
H52: ΔPu = Ru − Pu | I52: =I51-I48 -> 5.4635327 | J52: =J51-J48 -> 7.1548037 | K52: =K51-K48 -> 8.9428411 | L52: =L51-L48 -> 6.2272243 | M52: =M51-M48 -> 4.7692804 | N52: t
B53: 3. PESO DE LA CIMENTACIÓN Y DEL RELLENO (servicio, sin factorizar) | H53: γD · (W_zap + W_rell) | I53: =I41*$C$58 -> 17.7856 | J53: =J41*$C$58 -> 15.2448 | K53: =K41*$C$58 -> 15.2448 | L53: =L41*$C$58 -> 11.4336 | M53: =M41*$C$58 -> 11.4336 | N53: t
B54: Concepto | C54: Valor | D54: Unidad | E54: Cómo se calcula / de dónde sale | F54: Referencia | H54: w_u = peso factorizado repartido | I54: =I53/$C$18 -> 3.8003419 | J54: =J53/$C$18 -> 3.2574359 | K54: =K53/$C$18 -> 3.2574359 | L54: =L53/$C$18 -> 2.4430769 | M54: =M53/$C$18 -> 2.4430769 | N54: t/m²
B55: W_zap — peso de la zapata | C55: =$C$8*$C$9*$C$10*DATOS!$C$24 -> 5.616 | D55: t | E55: CALCULADA = Lx · Ly · h · γc. | F55: Geometría | H55: P total factorizada | I55: =I51+I53 -> 66.215133 | J55: =J51+J53 -> 78.427604 | K55: =K51+K53 -> 79.015641 | L55: =L51+L53 -> 51.281824 | M55: =M51+M53 -> 37.82388 | N55: t
B56: W_rell — relleno sobre la zapata | C56: =($C$18-DATOS!$C$64*DATOS!$C$65)*$C$20*DATOS!$C$32 -> 7.088 | D56: t | E56: CALCULADA = (A − área del dado) · h_rell · γs. | F56: Geometría | H56: M en X respecto al centro (sin contratrabe = Pu·e + Muy) | I56: =IF($C$15="SÍ",0,I48*$C$24+I49) -> 0 | J56: =IF($C$15="SÍ",0,J48*$C$24+J49) -> 0 | K56: =IF($C$15="SÍ",0,K48*$C$24+K49) -> 0 | L56: =IF($C$15="SÍ",0,L48*$C$24+L49) -> 0 | M56: =IF($C$15="SÍ",0,M48*$C$24+M49) -> 0 | N56: t·m
B57: W_dado — peso del dado | C57: =DATOS!$C$64*DATOS!$C$65*$C$21*DATOS!$C$24 -> 0.69 | D57: t | E57: CALCULADA = cx · cy · H_dado · γc. Cae en el eje de la columna, no en el centro de la zapata. | F57: Geometría | H57: ex = M / P total | I57: =IF(I55>0,I56/I55,99) -> 0 | J57: =IF(J55>0,J56/J55,99) -> 0 | K57: =IF(K55>0,K56/K55,99) -> 0 | L57: =IF(L55>0,L56/L55,99) -> 0 | M57: =IF(M55>0,M56/M55,99) -> 0 | N57: m
B58: W_zap + W_rell (en el centro de la zapata) | C58: =$C$55+$C$56 -> 12.704 | D58: t | E58: CALCULADA. En cada combinación se multiplica por su γD. | F58: ASCE/SEI 7-16, §2.4.1 | H58: Contacto en X | I58: =IF(I57<=$C$8/6,"TOTAL",IF(I57<$C$8/2,"PARCIAL","INESTABLE")) -> TOTAL | J58: =IF(J57<=$C$8/6,"TOTAL",IF(J57<$C$8/2,"PARCIAL","INESTABLE")) -> TOTAL | K58: =IF(K57<=$C$8/6,"TOTAL",IF(K57<$C$8/2,"PARCIAL","INESTABLE")) -> TOTAL | L58: =IF(L57<=$C$8/6,"TOTAL",IF(L57<$C$8/2,"PARCIAL","INESTABLE")) -> TOTAL | M58: =IF(M57<=$C$8/6,"TOTAL",IF(M57<$C$8/2,"PARCIAL","INESTABLE")) -> TOTAL | N58: —
H59: q total en la orilla del lindero | I59: =IF(I57<=$C$8/6,I55/$C$18+I56*($C$8/2)/$C$26,IF(I57<$C$8/2,2*I55/(3*$C$9*($C$8/2-I57)),999)) -> 14.148533 | J59: =IF(J57<=$C$8/6,J55/$C$18+J56*($C$8/2)/$C$26,IF(J57<$C$8/2,2*J55/(3*$C$9*($C$8/2-J57)),999)) -> 16.758035 | K59: =IF(K57<=$C$8/6,K55/$C$18+K56*($C$8/2)/$C$26,IF(K57<$C$8/2,2*K55/(3*$C$9*($C$8/2-K57)),999)) -> 16.883684 | L59: =IF(L57<=$C$8/6,L55/$C$18+L56*($C$8/2)/$C$26,IF(L57<$C$8/2,2*L55/(3*$C$9*($C$8/2-L57)),999)) -> 10.957655 | M59: =IF(M57<=$C$8/6,M55/$C$18+M56*($C$8/2)/$C$26,IF(M57<$C$8/2,2*M55/(3*$C$9*($C$8/2-M57)),999)) -> 8.0820257 | N59: t/m²
B60: 4. DIMENSIONES MÍNIMAS SUGERIDAS (orientativas — la revisión formal está en las secciones 5 a 12) | H60: pendiente de q hacia adentro (X) | I60: =IF(I57<=$C$8/6,I56/$C$26,IF(I57<$C$8/2,I59/(3*($C$8/2-I57)),0)) -> 0 | J60: =IF(J57<=$C$8/6,J56/$C$26,IF(J57<$C$8/2,J59/(3*($C$8/2-J57)),0)) -> 0 | K60: =IF(K57<=$C$8/6,K56/$C$26,IF(K57<$C$8/2,K59/(3*($C$8/2-K57)),0)) -> 0 | L60: =IF(L57<=$C$8/6,L56/$C$26,IF(L57<$C$8/2,L59/(3*($C$8/2-L57)),0)) -> 0 | M60: =IF(M57<=$C$8/6,M56/$C$26,IF(M57<$C$8/2,M59/(3*($C$8/2-M57)),0)) -> 0 | N60: t/m³
B61: Concepto | C61: Valor | D61: Unidad | E61: Cómo se calcula / de dónde sale | F61: Referencia | H61: fin del contacto, medido desde el lindero | I61: =IF(I60>0,MIN($C$8,I59/I60),$C$8) -> 1.8 | J61: =IF(J60>0,MIN($C$8,J59/J60),$C$8) -> 1.8 | K61: =IF(K60>0,MIN($C$8,K59/K60),$C$8) -> 1.8 | L61: =IF(L60>0,MIN($C$8,L59/L60),$C$8) -> 1.8 | M61: =IF(M60>0,MIN($C$8,M59/M60),$C$8) -> 1.8 | N61: m
B62: q_neta — capacidad que queda para la columna | C62: =DATOS!$C$30-($C$10*DATOS!$C$24+$C$20*DATOS!$C$32) -> 15.2 | D62: t/m² | E62: CALCULADA = qa − (h·γc + h_rell·γs). | F62: Bowles 5ª ed., §8.2, pág. 404 | H62: Mu en la cara interior del dado, varillas ‖ X (+ = tensión abajo) | I62: =IF($C$15="SÍ",0,$C$9*((I59-I60*DATOS!$C$64)*MAX(0,I61-DATOS!$C$64)^2/2-I60*MAX(0,I61-DATOS!$C$64)^3/3)-I54*$C$9*$C$28^2/2) -> 0 | J62: =IF($C$15="SÍ",0,$C$9*((J59-J60*DATOS!$C$64)*MAX(0,J61-DATOS!$C$64)^2/2-J60*MAX(0,J61-DATOS!$C$64)^3/3)-J54*$C$9*$C$28^2/2) -> 0 | K62: =IF($C$15="SÍ",0,$C$9*((K59-K60*DATOS!$C$64)*MAX(0,K61-DATOS!$C$64)^2/2-K60*MAX(0,K61-DATOS!$C$64)^3/3)-K54*$C$9*$C$28^2/2) -> 0 | L62: =IF($C$15="SÍ",0,$C$9*((L59-L60*DATOS!$C$64)*MAX(0,L61-DATOS!$C$64)^2/2-L60*MAX(0,L61-DATOS!$C$64)^3/3)-L54*$C$9*$C$28^2/2) -> 0 | M62: =IF($C$15="SÍ",0,$C$9*((M59-M60*DATOS!$C$64)*MAX(0,M61-DATOS!$C$64)^2/2-M60*MAX(0,M61-DATOS!$C$64)^3/3)-M54*$C$9*$C$28^2/2) -> 0 | N62: t·m
B63: P de servicio S1 + peso del dado | C63: =COMBINACIONES!$E$19+$C$57 -> 42.69 | D63: t | E63: CALCULADA = P(D + L) de COMBINACIONES + W_dado. | F63: COMBINACIONES, sección 2 | H63: sección de cortante ‖ X (a d de la cara), desde el lindero | I63: =DATOS!$C$64+$C$48/100 -> 0.90115 | J63: =DATOS!$C$64+$C$48/100 -> 0.90115 | K63: =DATOS!$C$64+$C$48/100 -> 0.90115 | L63: =DATOS!$C$64+$C$48/100 -> 0.90115 | M63: =DATOS!$C$64+$C$48/100 -> 0.90115 | N63: m
B64: R — carga que baja a la zapata con S1 | C64: =IF($C$15="SÍ",$C$63*$C$16/($C$16-$C$24),$C$63) -> 47.876636 | D64: t | E64: CALCULADA. Con contratrabe R = P·Ls/(Ls − e), mayor que P; sin ella R = P. | F64: Estática (momentos respecto a la columna interior) · Bowles 5ª ed., §9.4 | H64: Vu en una dirección, X | I64: =IF(OR($C$15="SÍ",I63>=$C$8),0,MAX(0,$C$9*((I59-I60*I63)*MAX(0,I61-I63)-I60*MAX(0,I61-I63)^2/2)-I54*$C$9*($C$8-I63))) -> 0 | J64: =IF(OR($C$15="SÍ",J63>=$C$8),0,MAX(0,$C$9*((J59-J60*J63)*MAX(0,J61-J63)-J60*MAX(0,J61-J63)^2/2)-J54*$C$9*($C$8-J63))) -> 0 | K64: =IF(OR($C$15="SÍ",K63>=$C$8),0,MAX(0,$C$9*((K59-K60*K63)*MAX(0,K61-K63)-K60*MAX(0,K61-K63)^2/2)-K54*$C$9*($C$8-K63))) -> 0 | L64: =IF(OR($C$15="SÍ",L63>=$C$8),0,MAX(0,$C$9*((L59-L60*L63)*MAX(0,L61-L63)-L60*MAX(0,L61-L63)^2/2)-L54*$C$9*($C$8-L63))) -> 0 | M64: =IF(OR($C$15="SÍ",M63>=$C$8),0,MAX(0,$C$9*((M59-M60*M63)*MAX(0,M61-M63)-M60*MAX(0,M61-M63)^2/2)-M54*$C$9*($C$8-M63))) -> 0 | N64: t
B65: Área mínima con presión uniforme | C65: =IF($C$62>0,$C$64/$C$62,999) -> 3.1497787 | D65: m² | E65: CALCULADA = R / q_neta. Sin contratrabe la presión no es uniforme y hace falta más (sección 5). | F65: ACI 318-19, 13.3.1.1, pág. 203 | H65: M con tensión arriba ‖ X | I65: =-I62 -> 0 | J65: =-J62 -> 0 | K65: =-K62 -> 0 | L65: =-L62 -> 0 | M65: =-M62 -> 0 | N65: t·m
B66: ¿El área capturada alcanza? | C66: =IF($C$18>=$C$65,"CUMPLE","NO CUMPLE — aumentar Lx · Ly") -> CUMPLE | D66: — | E66: Sólo es un primer filtro. | F66: ACI 318-19, 13.3.1.1, pág. 203 | H66: ey = Mx / P total | I66: =IF(I55>0,I50/I55,99) -> 0.027380448 | J66: =IF(J55>0,J50/J55,99) -> 0.031341006 | K66: =IF(K55>0,K50/K55,99) -> 0.13818783 | L66: =IF(L55>0,L50/L55,99) -> 0.19432811 | M66: =IF(M55>0,M50/M55,99) -> 0.26347112 | N66: m
B67: φ·vc de penetración pasado a t/m² (λs = 1) | C67: =DATOS!$C$87*0.33*DATOS!$C$23*DATOS!$C$17*DATOS!$C$89*10 -> 124.96422 | D67: t/m² | E67: CALCULADA = φ · 0.33 λ √f'c [MPa] → kg/cm² → t/m². | F67: ACI 318-19, Tabla 22.6.5.2(a) | H67: Contacto en Y | I67: =IF(I66<=$C$9/6,"TOTAL",IF(I66<$C$9/2,"PARCIAL","INESTABLE")) -> TOTAL | J67: =IF(J66<=$C$9/6,"TOTAL",IF(J66<$C$9/2,"PARCIAL","INESTABLE")) -> TOTAL | K67: =IF(K66<=$C$9/6,"TOTAL",IF(K66<$C$9/2,"PARCIAL","INESTABLE")) -> TOTAL | L67: =IF(L66<=$C$9/6,"TOTAL",IF(L66<$C$9/2,"PARCIAL","INESTABLE")) -> TOTAL | M67: =IF(M66<=$C$9/6,"TOTAL",IF(M66<$C$9/2,"PARCIAL","INESTABLE")) -> TOTAL | N67: —
B68: Pu máxima de la columna (con peso del dado) | C68: =MAX($I$48:$M$48) -> 56.028 | D68: t | E68: CALCULADA. | F68: Tabla por combinación (col. H–N) | H68: q total en la orilla cargada (Y) | I68: =IF(I66<=$C$9/6,I55/($C$9*$C$8)+I50*($C$9/2)/$C$25,IF(I66<$C$9/2,2*I55/(3*$C$8*($C$9/2-I66)),999)) -> 15.042517 | J68: =IF(J66<=$C$9/6,J55/($C$9*$C$8)+J50*($C$9/2)/$C$25,IF(J66<$C$9/2,2*J55/(3*$C$8*($C$9/2-J66)),999)) -> 17.970067 | K68: =IF(K66<=$C$9/6,K55/($C$9*$C$8)+K50*($C$9/2)/$C$25,IF(K66<$C$9/2,2*K55/(3*$C$8*($C$9/2-K66)),999)) -> 22.267806 | L68: =IF(L66<=$C$9/6,L55/($C$9*$C$8)+L50*($C$9/2)/$C$25,IF(L66<$C$9/2,2*L55/(3*$C$8*($C$9/2-L66)),999)) -> 15.871609 | M68: =IF(M66<=$C$9/6,M55/($C$9*$C$8)+M50*($C$9/2)/$C$25,IF(M66<$C$9/2,2*M55/(3*$C$8*($C$9/2-M66)),999)) -> 12.99598 | N68: t/m²
B69: Presión neta factorizada media máxima | C69: =MAX($I$51:$M$51)/$C$18 -> 13.626248 | D69: t/m² | E69: CALCULADA = Ru / A. | F69: Tabla por combinación | H69: pendiente de q (Y) | I69: =IF(I66<=$C$9/6,I50/$C$25,IF(I66<$C$9/2,I68/(3*($C$9/2-I66)),0)) -> 0.68768017 | J69: =IF(J66<=$C$9/6,J50/$C$25,IF(J66<$C$9/2,J68/(3*($C$9/2-J66)),0)) -> 0.93233197 | K69: =IF(K66<=$C$9/6,K50/$C$25,IF(K66<$C$9/2,K68/(3*($C$9/2-K66)),0)) -> 4.1416325 | L69: =IF(L66<=$C$9/6,L50/$C$25,IF(L66<$C$9/2,L68/(3*($C$9/2-L66)),0)) -> 3.7799651 | M69: =IF(M66<=$C$9/6,M50/$C$25,IF(M66<$C$9/2,M68/(3*($C$9/2-M66)),0)) -> 3.7799651 | N69: t/m³
B70: d mínimo por penetración (perímetro de 3 lados, sin momento) | C70: =100*(-($C$67*(2*DATOS!$C$64+DATOS!$C$65)+$C$69*(DATOS!$C$64+DATOS!$C$65/2))+SQRT(($C$67*(2*DATOS!$C$64+DATOS!$C$65)+$C$69*(DATOS!$C$64+DATOS!$C$65/2))^2-4*(2*$C$67+$C$69/2)*($C$69*DATOS!$C$64*DATOS!$C$65-$C$68)))/(2*(2*$C$67+$C$69/2)) -> 20.930981 | D70: cm | E70: CALCULADA de φvc·b₀·d = Pu − q·A_crít con b₀ = 2(cx + d/2) + (cy + d). | F70: ACI 318-19, 22.6.4.1 y Tabla 22.6.5.2 | H70: q total al centro (ordenada) | I70: =I68-I69*$C$9/2 -> 14.148533 | J70: =J68-J69*$C$9/2 -> 16.758035 | K70: =K68-K69*$C$9/2 -> 16.883684 | L70: =L68-L69*$C$9/2 -> 10.957655 | M70: =M68-M69*$C$9/2 -> 8.0820257 | N70: t/m²
B71: h mínimo sugerido por penetración | C71: =$C$70+$C$12+MAX($C$42,$C$44) -> 30.020981 | D71: cm | E71: CALCULADA = d + r + db. | F71: Geometría | H71: inicio del contacto útil para Mu | I71: =IF(I69>0,MAX($C$27/2,-I70/I69),$C$27/2) -> 0.2 | J71: =IF(J69>0,MAX($C$27/2,-J70/J69),$C$27/2) -> 0.2 | K71: =IF(K69>0,MAX($C$27/2,-K70/K69),$C$27/2) -> 0.2 | L71: =IF(L69>0,MAX($C$27/2,-L70/L69),$C$27/2) -> 0.2 | M71: =IF(M69>0,MAX($C$27/2,-M70/M69),$C$27/2) -> 0.2 | N71: m
H72: Mu en la cara del apoyo, varillas ‖ Y | I72: =$C$8*IF(I71<$C$9/2,(I70-I69*$C$27/2)*(($C$9/2)^2-I71^2)/2+I69*(($C$9/2)^3-I71^3)/3-I70*$C$27/2*($C$9/2-I71),0)-I54*$C$8*$C$29^2/2 -> 11.968138 | J72: =$C$8*IF(J71<$C$9/2,(J70-J69*$C$27/2)*(($C$9/2)^2-J71^2)/2+J69*(($C$9/2)^3-J71^3)/3-J70*$C$27/2*($C$9/2-J71),0)-J54*$C$8*$C$29^2/2 -> 15.649775 | K72: =$C$8*IF(K71<$C$9/2,(K70-K69*$C$27/2)*(($C$9/2)^2-K71^2)/2+K69*(($C$9/2)^3-K71^3)/3-K70*$C$27/2*($C$9/2-K71),0)-K54*$C$8*$C$29^2/2 -> 19.048539 | L72: =$C$8*IF(L71<$C$9/2,(L70-L69*$C$27/2)*(($C$9/2)^2-L71^2)/2+L69*(($C$9/2)^3-L71^3)/3-L70*$C$27/2*($C$9/2-L71),0)-L54*$C$8*$C$29^2/2 -> 13.114332 | M72: =$C$8*IF(M71<$C$9/2,(M70-M69*$C$27/2)*(($C$9/2)^2-M71^2)/2+M69*(($C$9/2)^3-M71^3)/3-M70*$C$27/2*($C$9/2-M71),0)-M54*$C$8*$C$29^2/2 -> 9.9827718 | N72: t·m
B73: 5. PRESIONES DE SERVICIO, VOLTEO, DESLIZAMIENTO Y LEVANTAMIENTO (sale de la tabla por combinación) | H73: sección de cortante (a d de la cara) | I73: =$C$27/2+$C$49/100 -> 0.61705 | J73: =$C$27/2+$C$49/100 -> 0.61705 | K73: =$C$27/2+$C$49/100 -> 0.61705 | L73: =$C$27/2+$C$49/100 -> 0.61705 | M73: =$C$27/2+$C$49/100 -> 0.61705 | N73: m
B74: Concepto | C74: Valor | D74: Unidad | E74: Cómo se calcula / de dónde sale | F74: Referencia | H74: inicio del contacto útil para Vu | I74: =IF(I69>0,MAX(I73,-I70/I69),I73) -> 0.61705 | J74: =IF(J69>0,MAX(J73,-J70/J69),J73) -> 0.61705 | K74: =IF(K69>0,MAX(K73,-K70/K69),K73) -> 0.61705 | L74: =IF(L69>0,MAX(L73,-L70/L69),L73) -> 0.61705 | M74: =IF(M69>0,MAX(M73,-M70/M69),M73) -> 0.61705 | N74: m
B75: q_máx — presión máxima de servicio que rige | C75: =MAX($I$27:$M$27) -> 16.380001 | D75: t/m² | E75: CALCULADA. Presión total (incluye zapata, relleno y dado). | F75: Bowles 5ª ed., §8.10, págs. 449–453 · ACI 318-19, R13.2.6.3, pág. 200 | H75: Vu en una dirección, Y | I75: =IF(I73>=$C$9/2,0,MAX(0,$C$8*IF(I74<$C$9/2,I70*($C$9/2-I74)+I69*(($C$9/2)^2-I74^2)/2,0)-I54*$C$8*($C$9/2-I73))) -> 13.531445 | J75: =IF(J73>=$C$9/2,0,MAX(0,$C$8*IF(J74<$C$9/2,J70*($C$9/2-J74)+J69*(($C$9/2)^2-J74^2)/2,0)-J54*$C$8*($C$9/2-J73))) -> 17.695011 | K75: =IF(K73>=$C$9/2,0,MAX(0,$C$8*IF(K74<$C$9/2,K70*($C$9/2-K74)+K69*(($C$9/2)^2-K74^2)/2,0)-K54*$C$8*($C$9/2-K73))) -> 21.63107 | L75: =IF(L73>=$C$9/2,0,MAX(0,$C$8*IF(L74<$C$9/2,L70*($C$9/2-L74)+L69*(($C$9/2)^2-L74^2)/2,0)-L54*$C$8*($C$9/2-L73))) -> 14.921081 | M75: =IF(M73>=$C$9/2,0,MAX(0,$C$8*IF(M74<$C$9/2,M70*($C$9/2-M74)+M69*(($C$9/2)^2-M74^2)/2,0)-M54*$C$8*($C$9/2-M73))) -> 11.386041 | N75: t
B76: Combinación que da q_máx | C76: =INDEX($I$5:$M$5,MATCH($C$75,$I$27:$M$27,0)) -> S3 | D76: — | E76: CALCULADA. | F76: COMBINACIONES | H76: fin del contacto en el lado ligero | I76: =IF(I69>0,MIN($C$9/2,I70/I69),$C$9/2) -> 1.3 | J76: =IF(J69>0,MIN($C$9/2,J70/J69),$C$9/2) -> 1.3 | K76: =IF(K69>0,MIN($C$9/2,K70/K69),$C$9/2) -> 1.3 | L76: =IF(L69>0,MIN($C$9/2,L70/L69),$C$9/2) -> 1.3 | M76: =IF(M69>0,MIN($C$9/2,M70/M69),$C$9/2) -> 1.3 | N76: m
B77: q_máx / q_adm (la más desfavorable) | C77: =MAX($I$31:$M$31) -> 0.91000004 | D77: — | E77: CALCULADA. | F77: DATOS, sección 3 | H77: M con tensión arriba, lado ligero ‖ Y | I77: =I54*$C$8*$C$29^2/2-$C$8*IF(I76>$C$27/2,(I70+I69*$C$27/2)*(I76^2-($C$27/2)^2)/2-I69*(I76^3-($C$27/2)^3)/3-I70*$C$27/2*(I76-$C$27/2),0) -> -10.570222 | J77: =J54*$C$8*$C$29^2/2-$C$8*IF(J76>$C$27/2,(J70+J69*$C$27/2)*(J76^2-($C$27/2)^2)/2-J69*(J76^3-($C$27/2)^3)/3-J70*$C$27/2*(J76-$C$27/2),0) -> -13.75453 | K77: =K54*$C$8*$C$29^2/2-$C$8*IF(K76>$C$27/2,(K70+K69*$C$27/2)*(K76^2-($C$27/2)^2)/2-K69*(K76^3-($C$27/2)^3)/3-K70*$C$27/2*(K76-$C$27/2),0) -> -10.629429 | L77: =L54*$C$8*$C$29^2/2-$C$8*IF(L76>$C$27/2,(L70+L69*$C$27/2)*(L76^2-($C$27/2)^2)/2-L69*(L76^3-($C$27/2)^3)/3-L70*$C$27/2*(L76-$C$27/2),0) -> -5.4304187 | M77: =M54*$C$8*$C$29^2/2-$C$8*IF(M76>$C$27/2,(M70+M69*$C$27/2)*(M76^2-($C$27/2)^2)/2-M69*(M76^3-($C$27/2)^3)/3-M70*$C$27/2*(M76-$C$27/2),0) -> -2.2988587 | N77: t·m
B78: Presión máxima contra la admisible | C78: =IF($C$77<=1,"CUMPLE","NO CUMPLE — aumentar Lx y/o Ly") -> CUMPLE | D78: — | E78: q_máx ≤ qa (con el incremento si hay acción accidental). | F78: ACI 318-19, 13.3.1.1, pág. 203 | H78: Índice de núcleo con cargas factorizadas | I78: =6*I57/$C$8+6*I66/$C$9 -> 0.063185649 | J78: =6*J57/$C$8+6*J66/$C$9 -> 0.072325398 | K78: =6*K57/$C$8+6*K66/$C$9 -> 0.31889499 | L78: =6*L57/$C$8+6*L66/$C$9 -> 0.44844948 | M78: =6*M57/$C$8+6*M66/$C$9 -> 0.60801027 | N78: —
B79: q_mín — presión mínima (0 = hay despegue) | C79: =MIN($I$28:$M$28) -> 1.9336237 | D79: t/m² | E79: CALCULADA. | F79: Bowles 5ª ed., §8.10, pág. 453 | H79: Vu de penetración = Pu − (Ru/A)·A_crít | I79: =IF(I78<=1,I48-I51*$C$97/$C$18,I48) -> 36.337918 | J79: =IF(J78<=1,J48-J51*$C$97/$C$18,J48) -> 47.38078 | K79: =IF(K78<=1,K48-K51*$C$97/$C$18,K48) -> 46.100301 | L79: =IF(L78<=1,L48-L51*$C$97/$C$18,L48) -> 28.167358 | M79: =IF(M78<=1,M48-M51*$C$97/$C$18,M48) -> 18.009217 | N79: t
B80: Con carga sostenida (S1 = D + L), ¿toda la zapata está comprimida? | C80: =IF(INDEX($I$24:$M$24,1)<=1,"CUMPLE — resultante dentro del núcleo central","NO CUMPLE — con D + L no debe haber despegue: usa contratrabe o agranda la zapata") -> CUMPLE — resultante dentro del núcleo central | D80: — | E80: Sin contratrabe casi nunca cumple: la carga de la columna cae en la orilla. | F80: Bowles 5ª ed., §8.10, pág. 453 (e ≤ L/6) | H80: Msc alrededor de Y = (sin contratrabe: |Muy| + |Vux|·brazo) + Vu·excentricidad | I80: =IF($C$15="SÍ",0,ABS(I45)+ABS(I46)*$C$23)+I79*$C$100/100 -> 8.7364478 | J80: =IF($C$15="SÍ",0,ABS(J45)+ABS(J46)*$C$23)+J79*$C$100/100 -> 11.391399 | K80: =IF($C$15="SÍ",0,ABS(K45)+ABS(K46)*$C$23)+K79*$C$100/100 -> 11.083543 | L80: =IF($C$15="SÍ",0,ABS(L45)+ABS(L46)*$C$23)+L79*$C$100/100 -> 6.7720627 | M80: =IF($C$15="SÍ",0,ABS(M45)+ABS(M46)*$C$23)+M79*$C$100/100 -> 4.3298184 | N80: t·m
B81: Combinaciones con contacto parcial (despegue) | C81: =COUNTIF($I$29:$M$29,"PARCIAL") -> 0 | D81: — | E81: CALCULADA. | F81: Tabla por combinación | H81: Msc alrededor de X = |Mux| + |Vuy|·brazo dado | I81: =ABS(I44)+ABS(I47)*$C$23 -> 1.603 | J81: =ABS(J44)+ABS(J47)*$C$23 -> 2.198 | K81: =ABS(K44)+ABS(K47)*$C$23 -> 9.689 | L81: =ABS(L44)+ABS(L47)*$C$23 -> 8.8305 | M81: =ABS(M44)+ABS(M47)*$C$23 -> 8.8305 | N81: t·m
B82: P total mínima sobre el terreno | C82: =MIN($I$20:$M$20) -> 25.057821 | D82: t | E82: CALCULADA. | F82: Tabla por combinación | H82: vu máx de penetración | I82: =I79*1000/($C$96*$C$50)+$C$110*I80*100000*$C$115/$C$111+$C$113*I81*100000*($C$95/2)/$C$114 -> 6.6846902 | J82: =J79*1000/($C$96*$C$50)+$C$110*J80*100000*$C$115/$C$111+$C$113*J81*100000*($C$95/2)/$C$114 -> 8.7302189 | K82: =K79*1000/($C$96*$C$50)+$C$110*K80*100000*$C$115/$C$111+$C$113*K81*100000*($C$95/2)/$C$114 -> 9.4808904 | L82: =L79*1000/($C$96*$C$50)+$C$110*L80*100000*$C$115/$C$111+$C$113*L81*100000*($C$95/2)/$C$114 -> 6.173154 | M82: =M79*1000/($C$96*$C$50)+$C$110*M80*100000*$C$115/$C$111+$C$113*M81*100000*($C$95/2)/$C$114 -> 4.3630264 | N82: kg/cm²
B83: ¿Hay levantamiento neto? | C83: =IF($C$82>0,"CUMPLE — no hay levantamiento","NO CUMPLE — tensión neta: lastrar o anclar") -> CUMPLE — no hay levantamiento | D83: — | E83: P total > 0 en todas las combinaciones. | F83: ACI 318-19, 13.2.6.1, págs. 199–200
B84: FS al volteo mínimo, dirección X | C84: =MIN($I$32:$M$32) -> 99 | D84: — | E84: CALCULADA. Con contratrabe no hay volteo en X (99). | F84: Bowles 5ª ed., §8.10, pág. 450 | H84: BLOQUE U — CONTRATRABE DE EQUILIBRIO
B85: FS al volteo mínimo, dirección Y | C85: =MIN($I$33:$M$33) -> 4.695858 | D85: — | E85: CALCULADA. | F85: Bowles 5ª ed., §8.10, pág. 450 | H85: w = Ru / Lx (reacción neta, por metro de contratrabe) | I85: =IF($C$15="SÍ",I51/$C$8,0) -> 26.905296 | J85: =IF($C$15="SÍ",J51/$C$8,0) -> 35.101558 | K85: =IF($C$15="SÍ",K51/$C$8,0) -> 35.428245 | L85: =IF($C$15="SÍ",L51/$C$8,0) -> 22.137902 | M85: =IF($C$15="SÍ",M51/$C$8,0) -> 14.661267 | N85: t/m
B86: Revisión por volteo | C86: =IF(MIN($C$84,$C$85)>=DATOS!$C$34,"CUMPLE","NO CUMPLE — aumentar dimensiones o usar contratrabe") -> CUMPLE | D86: — | E86: FS ≥ el exigido en DATOS. | F86: ACI 318-19, 13.2.6.1, págs. 199–200 | H86: del eje de la columna al punto de cortante nulo | I86: =IF(I85>0,MAX(0,I48/I85-DATOS!$C$64/2),0) -> 1.3469347 | J86: =IF(J85>0,MAX(0,J48/J85-DATOS!$C$64/2),0) -> 1.3461685 | K86: =IF(K85>0,MAX(0,K48/K85-DATOS!$C$64/2),0) -> 1.2975788 | L86: =IF(L85>0,MAX(0,L48/L85-DATOS!$C$64/2),0) -> 1.2687076 | M86: =IF(M85>0,MAX(0,M48/M85-DATOS!$C$64/2),0) -> 1.224702 | N86: m
B87: FS al deslizamiento mínimo | C87: =MIN($I$35:$M$35) -> 4.605988 | D87: — | E87: CALCULADA = μ·P total / V. Todo el cortante se le deja a la zapata (del lado seguro). | F87: NAVFAC DM 7.02, Tabla 1, pág. 7.2-63 | H87: Mu con tensión arriba = Pu·s₀ + Muy − w(s₀ + cx/2)²/2 | I87: =IF($C$15="SÍ",MAX(0,I48*I86+I49-I85*(I86+DATOS!$C$64/2)^2/2),0) -> 24.867448 | J87: =IF($C$15="SÍ",MAX(0,J48*J86+J49-J85*(J86+DATOS!$C$64/2)^2/2),0) -> 32.568064 | K87: =IF($C$15="SÍ",MAX(0,K48*K86+K49-K85*(K86+DATOS!$C$64/2)^2/2),0) -> 40.924324 | L87: =IF($C$15="SÍ",MAX(0,L48*L86+L49-L85*(L86+DATOS!$C$64/2)^2/2),0) -> 28.586984 | M87: =IF($C$15="SÍ",MAX(0,M48*M86+M49-M85*(M86+DATOS!$C$64/2)^2/2),0) -> 21.999016 | N87: t·m
B88: Revisión por deslizamiento | C88: =IF($C$87>=DATOS!$C$35,"CUMPLE","NO CUMPLE — aumentar peso, dentellón o contratrabe") -> CUMPLE | D88: — | E88: FS ≥ el exigido en DATOS. | F88: ACI 318-19, 13.2.6.1, págs. 199–200 | H88: Mu con tensión abajo (Muy en sentido contrario, en el paño) | I88: =IF($C$15="SÍ",MAX(0,I49-I48*DATOS!$C$64/2+(I48*$C$16-I49)/($C$16-$C$24)/$C$8*DATOS!$C$64^2/2),0) -> 0 | J88: =IF($C$15="SÍ",MAX(0,J49-J48*DATOS!$C$64/2+(J48*$C$16-J49)/($C$16-$C$24)/$C$8*DATOS!$C$64^2/2),0) -> 0 | K88: =IF($C$15="SÍ",MAX(0,K49-K48*DATOS!$C$64/2+(K48*$C$16-K49)/($C$16-$C$24)/$C$8*DATOS!$C$64^2/2),0) -> 2.6106563 | L88: =IF($C$15="SÍ",MAX(0,L49-L48*DATOS!$C$64/2+(L48*$C$16-L49)/($C$16-$C$24)/$C$8*DATOS!$C$64^2/2),0) -> 5.5264281 | M88: =IF($C$15="SÍ",MAX(0,M49-M48*DATOS!$C$64/2+(M48*$C$16-M49)/($C$16-$C$24)/$C$8*DATOS!$C$64^2/2),0) -> 7.5918487 | N88: t·m
B89: ΔP máximo — lo que la contratrabe le quita a la columna interior | C89: =MAX($I$18:$M$18) -> 6.4865187 | D89: t | E89: CALCULADA = R − P. | F89: Estática | H89: Vu = máx(Pu − w(cx + d) ; ΔPu) | I89: =IF($C$15="SÍ",MAX(ABS(I48-I85*(DATOS!$C$64+$C$251/100)),ABS(I52)),0) -> 7.2424933 | J89: =IF($C$15="SÍ",MAX(ABS(J48-J85*(DATOS!$C$64+$C$251/100)),ABS(J52)),0) -> 9.4219069 | K89: =IF($C$15="SÍ",MAX(ABS(K48-K85*(DATOS!$C$64+$C$251/100)),ABS(K52)),0) -> 8.9428411 | L89: =IF($C$15="SÍ",MAX(ABS(L48-L85*(DATOS!$C$64+$C$251/100)),ABS(L52)),0) -> 6.2272243 | M89: =IF($C$15="SÍ",MAX(ABS(M48-M85*(DATOS!$C$64+$C$251/100)),ABS(M52)),0) -> 4.7692804 | N89: t
B90: ¿La contratrabe levanta la columna interior? | C90: =IF($C$15="NO","CUMPLE — no aplica",IF(MIN($I$36:$M$36)>=0,"CUMPLE — γD·PD interior ≥ ΔP en todas","NO CUMPLE — la columna interior se levanta: más Ls o lastre")) -> CUMPLE — γD·PD interior ≥ ΔP en todas | D90: — | E90: Se revisa con cada combinación (con 0.6D en S4 y S5). La zapata interior se diseña sin descontar ΔP. | F90: Bowles 5ª ed., §9.4 | H90: Vu de gravedad (combinaciones sin A) | I90: =IF(I42=0,I89,0) -> 7.2424933 | J90: =IF(J42=0,J89,0) -> 9.4219069 | K90: =IF(K42=0,K89,0) -> 0 | L90: =IF(L42=0,L89,0) -> 0 | M90: =IF(M42=0,M89,0) -> 0 | N90: t
H91: Nu de amarre = máx(fracción·Pu ; Vux) | I91: =IF($C$15="SÍ",MAX($C$244*I48,ABS(I46)),0) -> 4.2966 | J91: =IF($C$15="SÍ",MAX($C$244*J48,ABS(J46)),0) -> 5.6028 | K91: =IF($C$15="SÍ",MAX($C$244*K48,ABS(K46)),0) -> 5.4828 | L91: =IF($C$15="SÍ",MAX($C$244*L48,ABS(L46)),0) -> 3.3621 | M91: =IF($C$15="SÍ",MAX($C$244*M48,ABS(M46)),0) -> 2.68 | N91: t
B92: 6. CORTANTE EN DOS DIRECCIONES (PENETRACIÓN) — columna de borde, perímetro de 3 lados a d/2
B93: Concepto | C93: Valor | D93: Unidad | E93: Cómo se calcula / de dónde sale | F93: Referencia
B94: b₁ — lado perpendicular al lindero = cx + d/2 | C94: =DATOS!$C$64*100+$C$50/2 -> 70.455 | D94: cm | E94: CALCULADA: el perímetro crítico se corta en el lindero. | F94: ACI 318-19, 22.6.4.1
B95: b₂ — lado paralelo al lindero = cy + d | C95: =DATOS!$C$65*100+$C$50 -> 90.91 | D95: cm | E95: CALCULADA. | F95: ACI 318-19, 22.6.4.1
B96: b₀ — perímetro crítico = 2b₁ + b₂ | C96: =2*$C$94+$C$95 -> 231.82 | D96: cm | E96: CALCULADA (tres lados). | F96: ACI 318-19, 22.6.4.1
B97: Área dentro de la sección crítica | C97: =$C$94*$C$95/10000 -> 0.64050641 | D97: m² | E97: CALCULADA. | F97: ACI 318-19, 13.2.7.2, pág. 202
B98: c_AB — del centroide de la sección crítica a su cara interior | C98: =$C$94^2/(2*$C$94+$C$95) -> 21.412764 | D98: cm | E98: CALCULADA = b₁²/(2b₁ + b₂). | F98: ACI 318-19, R8.4.4.2.3
B99: c_CD — del centroide al lindero | C99: =$C$94-$C$98 -> 49.042236 | D99: cm | E99: CALCULADA = b₁ − c_AB. | F99: ACI 318-19, R8.4.4.2.3
B100: Del eje de la columna al centroide de la sección crítica | C100: =ABS($C$99-DATOS!$C$64*100/2) -> 24.042236 | D100: cm | E100: CALCULADA. Vu llevado a ese centroide genera momento. | F100: ACI 318-19, R8.4.4.2.3
...

Sheet CROQUIS
B1: CROQUIS DE LA CIMENTACIÓN — se redibuja solo con los datos
B2: =DATOS!$C$9&" · "&DATOS!$C$10 -> Ejemplo — nave industrial · Columna tipo eje B-2 · muro eje 1
B3: Escoge el tipo en la celda amarilla. Las cotas están en metros; el armado es el que arrojó la hoja del tipo elegido.
B4: CÓMO SE LEE: gris oscuro grueso = concreto; ROJO = varillas del lecho inferior, dovelas y contratrabe (punto rojo = varilla cortada); AZUL = parrilla superior; VERDE = estribos del dado y de la contratrabe; café = terreno; gris punteado = plantilla; raya-punto gris = eje; azul claro = cotas; azul marino = rótulos con flecha. El corte A-A es a lo largo de X por el eje del dado (en la corrida, a través del ancho B).
B6: 1. CIMENTACIÓN QUE SE DIBUJA
B7: Concepto | C7: Valor | D7: Unidad | E7: Cómo se calcula / de dónde sale | F7: Referencia
B8: Cimentación a dibujar | C8: 1 · ZAPATA AISLADA | D8: — | E8: CAPTURA (lista). | F8: AISLADA / AISLADA_CT / CORRIDA
B9: Cimentación | C9: =CHOOSE(VALUE(LEFT($C$8,1)),AISLADA!$C$225,AISLADA_CT!$C$292,CORRIDA!$C$129) -> Lx × Ly × h = 2.60 × 2.60 × 0.50 m; Df = 1.50 m
B10: Lecho inferior | C10: =CHOOSE(VALUE(LEFT($C$8,1)),AISLADA!$C$226,AISLADA_CT!$C$293,"Transversal: "&CORRIDA!$C$130&" · longitudinal: "&CORRIDA!$C$131) -> ‖ X: #5 @ 20.0 cm (13 pzas) · ‖ Y: #5 @ 20.0 cm (13 pzas)
B11: Remate / parrilla superior | C11: =CHOOSE(VALUE(LEFT($C$8,1)),AISLADA!$C$227&" · parrilla sup.: "&AISLADA!$C$228,AISLADA_CT!$C$294&" · parrilla sup.: "&AISLADA_CT!$C$295,"Remate: "&CORRIDA!$C$114) -> ‖ X: RECTA · ‖ Y: RECTA · parrilla sup.: No lleva
B12: Dovelas / anclaje del muro | C12: =CHOOSE(VALUE(LEFT($C$8,1)),AISLADA!$C$229,AISLADA_CT!$C$296,CORRIDA!$C$125) -> mín. 5 dovelas #6 con gancho 90° apoyado en la parrilla inferior
B13: Contratrabe | C13: =IF(VALUE(LEFT($C$8,1))=2,AISLADA_CT!$C$287&" · "&AISLADA_CT!$C$288,"No lleva") -> No lleva
B14: Revisiones en rojo en la hoja del tipo elegido | C14: =CHOOSE(VALUE(LEFT($C$8,1)),AISLADA!$C$230,AISLADA_CT!$C$297,CORRIDA!$C$132) -> 0 | D14: — | E14: Si no es cero, el croquis dibuja algo que todavía no cumple. | F14: Hoja del tipo elegido
B15: Estado del diseño dibujado | C15: =IF($C$14=0,"CUMPLE — todas las revisiones de la hoja","NO CUMPLE — hay revisiones en rojo en la hoja del tipo elegido") -> CUMPLE — todas las revisiones de la hoja
B17: 2. DIBUJOS (planta y corte A-A con armado; planta y corte acotados; sección de la contratrabe)

Sheet RESUMEN
B1: RESUMEN — LOS CUATRO TIPOS DE CIMENTACIÓN
B2: =DATOS!$C$9&" · "&DATOS!$C$10 -> Ejemplo — nave industrial · Columna tipo eje B-2 · muro eje 1
B3: Todo sale de las hojas de cada tipo; aquí no se captura nada. El tipo que se dibuja se escoge en CROQUIS.
B4: CÓMO SE LEE: cada bloque trae la geometría, el armado que se adopta, las relaciones demanda/capacidad que mandan (≤ 1.00 cumple) y una cuantificación aproximada por zapata (o por metro). Si el estado dice NO CUMPLE, ve a la hoja del tipo y busca las celdas en rojo.
B6: 0. DATOS COMUNES
B7: Concepto | C7: Valor | D7: Unidad | E7: Cómo se calcula / de dónde sale | F7: Referencia
B8: Materiales | C8: ="f'c = "&DATOS!$C$15&" kg/cm² · fy = "&DATOS!$C$18&" kg/cm² · γc = "&TEXT(DATOS!$C$24,"0.00")&" t/m³" -> f'c = 250 kg/cm² · fy = 4200 kg/cm² · γc = 2.40 t/m³
B9: Suelo (datos propuestos, sin estudio) | C9: ="qa = "&TEXT(DATOS!$C$30,"0.0")&" t/m² · γs = "&TEXT(DATOS!$C$32,"0.00")&" t/m³ · μ = "&TEXT(DATOS!$C$33,"0.00")&" · FS volteo = "&TEXT(DATOS!$C$34,"0.0")&" · FS deslizamiento = "&TEXT(DATOS!$C$35,"0.0") -> qa = 18.0 t/m² · γs = 1.60 t/m³ · μ = 0.45 · FS volteo = 1.5 · FS deslizamiento = 1.5
B10: Acción accidental | C10: =DATOS!$C$39&" · combinaciones ASCE/SEI 7-16 y ACI 318-19 Tabla 5.3.1 (hoja COMBINACIONES)" -> SISMO · combinaciones ASCE/SEI 7-16 y ACI 318-19 Tabla 5.3.1 (hoja COMBINACIONES)
B11: Tipo que se dibuja en CROQUIS | C11: =CROQUIS!$C$8 -> 1 · ZAPATA AISLADA
B13: 1. ZAPATA AISLADA
B14: Concepto | C14: Valor | D14: Unidad | E14: Cómo se calcula / de dónde sale | F14: Referencia
B15: Zapata | C15: =AISLADA!$C$225 -> Lx × Ly × h = 2.60 × 2.60 × 0.50 m; Df = 1.50 m
B16: Lecho inferior | C16: =AISLADA!$C$226 -> ‖ X: #5 @ 20.0 cm (13 pzas) · ‖ Y: #5 @ 20.0 cm (13 pzas)
B17: Remate de las varillas | C17: =AISLADA!$C$227 -> ‖ X: RECTA · ‖ Y: RECTA
B18: Parrilla superior | C18: =AISLADA!$C$228 -> No lleva
B19: Dovelas | C19: =AISLADA!$C$229 -> mín. 5 dovelas #6 con gancho 90° apoyado en la parrilla inferior
B20: q_máx / q_adm | C20: =AISLADA!$C$72 -> 0.75459765 | D20: — | E20: Presión de servicio contra la admisible. | F20: Hoja AISLADA, sección 5
B21: FS mínimo al volteo / FS exigido | C21: =MIN(10,MIN(AISLADA!$C$79,AISLADA!$C$80)/DATOS!$C$34) -> 2.7457145 | D21: — | E21: ≥ 1.00 cumple (se muestra hasta 10). | F21: Hoja AISLADA, sección 5
B22: FS mínimo al deslizamiento / FS exigido | C22: =MIN(10,AISLADA!$C$82/DATOS!$C$35) -> 3.1041104 | D22: — | E22: ≥ 1.00 cumple (se muestra hasta 10). | F22: Hoja AISLADA, sección 5
B23: Penetración: vu / φvc | C23: =AISLADA!$C$107 -> 0.39724577 | D23: — | E23: ≤ 1.00 cumple. | F23: Hoja AISLADA, sección 6 · ACI 318-19, 22.6
B24: Cortante en una dirección: Vu / φVc (la peor) | C24: =MAX(AISLADA!$C$160/AISLADA!$C$165,AISLADA!$C$167/AISLADA!$C$172) -> 0.52238045 | D24: — | E24: ≤ 1.00 cumple. | F24: Hoja AISLADA, sección 9 · ACI 318-19, Tabla 22.5.5.1
B25: Flexión: Mu / φMn (la peor) | C25: =MAX(AISLADA!$C$112/AISLADA!$C$130,AISLADA!$C$136/AISLADA!$C$154) -> 0.40780233 | D25: — | E25: ≤ 1.00 cumple. | F25: Hoja AISLADA, secciones 7 y 8
B26: Dovelas: ldc / peralte disponible | C26: =AISLADA!$C$217/AISLADA!$C$218 -> 0.96977262 | D26: — | E26: ≤ 1.00 cumple. | F26: Hoja AISLADA, sección 12 · ACI 318-19, 25.4.9
B27: Concreto de la zapata | C27: =AISLADA!$C$7*AISLADA!$C$8*AISLADA!$C$9 -> 3.38 | D27: m³ | E27: Lx · Ly · h. | F27: Cuantificación
B28: Concreto del dado | C28: =DATOS!$C$64*DATOS!$C$65*AISLADA!$C$17 -> 0.2875 | D28: m³ | E28: cx · cy · H_dado. | F28: Cuantificación
B29: Acero de la zapata (lechos inferior y superior) | C29: =AISLADA!$C$123*(AISLADA!$C$7-2*AISLADA!$C$12/100+IF(AISLADA!$C$196="GANCHO 90°",2*12*AISLADA!$C$38/100,0))*INDEX(TABLAS!$E$6:$E$13,MATCH(AISLADA!$C$31,TABLAS!$B$6:$B$13,0))+AISLADA!$C$147*(AISLADA!$C$8-2*AISLADA!$C$12/100+IF(AISLADA!$C$203="GANCHO 90°",2*12*AISLADA!$C$40/100,0))*INDEX(TABLAS!$E$6:$E$13,MATCH(AISLADA!$C$32,TABLAS!$B$6:$B$13,0))+AISLADA!$C$184*(AISLADA!$C$7-2*AISLADA!$C$12/100)*INDEX(TABLAS!$E$6:$E$13,MATCH(AISLADA!$C$37,TABLAS!$B$6:$B$13,0))+AISLADA!$C$185*(AISLADA!$C$8-2*AISLADA!$C$12/100)*INDEX(TABLAS!$E$6:$E$13,MATCH(AISLADA!$C$37,TABLAS!$B$6:$B$13,0)) -> 98.8624 | D29: kg | E29: Varillas × longitud (con ganchos si los lleva) × peso lineal. No incluye dovelas ni traslapes. | F29: TABLAS, tabla 1
B30: ESTADO | C30: =IF(AISLADA!$C$230=0,"CUMPLE — todas las revisiones","NO CUMPLE — "&AISLADA!$C$230&" revisión(es) en rojo en la hoja AISLADA") -> CUMPLE — todas las revisiones
B32: 2. ZAPATA AISLADA LIGADA CON CONTRATRABES
B33: Concepto | C33: Valor | D33: Unidad | E33: Cómo se calcula / de dónde sale | F33: Referencia
B34: Zapata | C34: =AISLADA_CT!$C$292 -> Lx × Ly × h = 2.00 × 2.00 × 0.50 m; Df = 1.50 m
B35: Lecho inferior | C35: =AISLADA_CT!$C$293 -> ‖ X: #5 @ 20.0 cm (10 pzas) · ‖ Y: #5 @ 20.0 cm (10 pzas)
B36: Remate de las varillas | C36: =AISLADA_CT!$C$294 -> ‖ X: RECTA · ‖ Y: RECTA
B37: Parrilla superior | C37: =AISLADA_CT!$C$295 -> No lleva
B38: Dovelas | C38: =AISLADA_CT!$C$296 -> mín. 5 dovelas #6 con gancho 90° apoyado en la parrilla inferior
B39: Contratrabe — longitudinal | C39: =AISLADA_CT!$C$287 -> 3 #6 arriba + 3 #6 abajo, corridas
B40: Contratrabe — estribos | C40: =AISLADA_CT!$C$288 -> E#3 (2 ramas) @ 10.0 cm en 1.20 m desde cada paño; resto @ 15.0 cm
B41: q_máx / q_adm | C41: =AISLADA_CT!$C$73 -> 0.745 | D41: — | E41: Presión de servicio contra la admisible. | F41: Hoja AISLADA_CT, sección 5
B42: FS mínimo al volteo / FS exigido | C42: =MIN(10,MIN(AISLADA_CT!$C$80,AISLADA_CT!$C$81)/DATOS!$C$34) -> 10 | D42: — | E42: ≥ 1.00 cumple (se muestra hasta 10). | F42: Hoja AISLADA_CT, sección 5
B43: FS mínimo al deslizamiento / FS exigido | C43: =MIN(10,AISLADA_CT!$C$83/DATOS!$C$35) -> 10 | D43: — | E43: ≥ 1.00 cumple (se muestra hasta 10). | F43: Hoja AISLADA_CT, sección 5
B44: Penetración: vu / φvc | C44: =AISLADA_CT!$C$108 -> 0.2391123 | D44: — | E44: ≤ 1.00 cumple. | F44: Hoja AISLADA_CT, sección 6 · ACI 318-19, 22.6
B45: Cortante en una dirección: Vu / φVc (la peor) | C45: =MAX(AISLADA_CT!$C$161/AISLADA_CT!$C$166,AISLADA_CT!$C$168/AISLADA_CT!$C$173) -> 0.36064943 | D45: — | E45: ≤ 1.00 cumple. | F45: Hoja AISLADA_CT, sección 9 · ACI 318-19, Tabla 22.5.5.1
B46: Flexión: Mu / φMn (la peor) | C46: =MAX(AISLADA_CT!$C$113/AISLADA_CT!$C$131,AISLADA_CT!$C$137/AISLADA_CT!$C$155) -> 0.26898437 | D46: — | E46: ≤ 1.00 cumple. | F46: Hoja AISLADA_CT, secciones 7 y 8
B47: Dovelas: ldc / peralte disponible | C47: =AISLADA_CT!$C$218/AISLADA_CT!$C$219 -> 0.96977262 | D47: — | E47: ≤ 1.00 cumple. | F47: Hoja AISLADA_CT, sección 12 · ACI 318-19, 25.4.9
B48: Concreto de la zapata | C48: =AISLADA_CT!$C$8*AISLADA_CT!$C$9*AISLADA_CT!$C$10 -> 2 | D48: m³ | E48: Lx · Ly · h. | F48: Cuantificación
B49: Concreto del dado | C49: =DATOS!$C$64*DATOS!$C$65*AISLADA_CT!$C$18 -> 0.2875 | D49: m³ | E49: cx · cy · H_dado. | F49: Cuantificación
B50: Acero de la zapata (lechos inferior y superior) | C50: =AISLADA_CT!$C$124*(AISLADA_CT!$C$8-2*AISLADA_CT!$C$13/100+IF(AISLADA_CT!$C$197="GANCHO 90°",2*12*AISLADA_CT!$C$39/100,0))*INDEX(TABLAS!$E$6:$E$13,MATCH(AISLADA_CT!$C$32,TABLAS!$B$6:$B$13,0))+AISLADA_CT!$C$148*(AISLADA_CT!$C$9-2*AISLADA_CT!$C$13/100+IF(AISLADA_CT!$C$204="GANCHO 90°",2*12*AISLADA_CT!$C$41/100,0))*INDEX(TABLAS!$E$6:$E$13,MATCH(AISLADA_CT!$C$33,TABLAS!$B$6:$B$13,0))+AISLADA_CT!$C$185*(AISLADA_CT!$C$8-2*AISLADA_CT!$C$13/100)*INDEX(TABLAS!$E$6:$E$13,MATCH(AISLADA_CT!$C$38,TABLAS!$B$6:$B$13,0))+AISLADA_CT!$C$186*(AISLADA_CT!$C$9-2*AISLADA_CT!$C$13/100)*INDEX(TABLAS!$E$6:$E$13,MATCH(AISLADA_CT!$C$38,TABLAS!$B$6:$B$13,0)) -> 57.424 | D50: kg | E50: Varillas × longitud (con ganchos si los lleva) × peso lineal. No incluye dovelas ni traslapes. | F50: TABLAS, tabla 1
B51: Contratrabe: concreto por metro | C51: =AISLADA_CT!$C$226*AISLADA_CT!$C$227 -> 0.18 | D51: m³/m | E51: b · h. | F51: Cuantificación
B52: Contratrabe: acero por metro (aprox.) | C52: =(AISLADA_CT!$C$253+AISLADA_CT!$C$255)*INDEX(TABLAS!$E$6:$E$13,MATCH(AISLADA_CT!$C$232,TABLAS!$B$6:$B$13,0))+(AISLADA_CT!$C$234*(AISLADA_CT!$C$227-2*AISLADA_CT!$C$231/100)+2*(AISLADA_CT!$C$226-2*AISLADA_CT!$C$231/100)+0.2)*INDEX(TABLAS!$E$6:$E$13,MATCH(AISLADA_CT!$C$233,TABLAS!$B$6:$B$13,0))*100/AISLADA_CT!$C$281 -> 19.372667 | D52: kg/m | E52: Longitudinal + estribos con la separación del centro (la zona confinada lleva un poco más). | F52: TABLAS, tabla 1
B53: ESTADO | C53: =IF(AISLADA_CT!$C$297=0,"CUMPLE — todas las revisiones","NO CUMPLE — "&AISLADA_CT!$C$297&" revisión(es) en rojo en la hoja AISLADA_CT") -> CUMPLE — todas las revisiones
B55: 3. ZAPATA CORRIDA BAJO MURO (por metro)
B56: Concepto | C56: Valor | D56: Unidad | E56: Cómo se calcula / de dónde sale | F56: Referencia
B57: Zapata | C57: =CORRIDA!$C$129 -> B × h = 0.90 × 0.25 m; Df = 0.80 m; muro t = 0.20 m
B58: Transversal (lecho inferior) | C58: =CORRIDA!$C$130 -> #4 @ 27.5 cm · remate: RECTA
B59: Longitudinal | C59: =CORRIDA!$C$131 -> 6 #3 corridas @ 14.8 cm
B60: q_máx / q_adm | C60: =CORRIDA!$C$53 -> 0.62290123 | D60: — | E60: Presión de servicio contra la admisible. | F60: Hoja CORRIDA, sección 5
B61: FS mínimo al volteo / FS exigido | C61: =MIN(10,CORRIDA!$C$59/DATOS!$C$34) -> 2.2573272 | D61: — | E61: ≥ 1.00 cumple (se muestra hasta 10). | F61: Hoja CORRIDA, sección 5
B62: FS mínimo al deslizamiento / FS exigido | C62: =MIN(10,CORRIDA!$C$61/DATOS!$C$35) -> 3.4988571 | D62: — | E62: ≥ 1.00 cumple (se muestra hasta 10). | F62: Hoja CORRIDA, sección 5
B63: Cortante: Vu / φVc | C63: =CORRIDA!$C$87/CORRIDA!$C$92 -> 0.62895907 | D63: — | E63: ≤ 1.00 cumple. | F63: Hoja CORRIDA, sección 7
B64: Flexión: Mu / φMn | C64: =CORRIDA!$C$66/CORRIDA!$C$81 -> 0.35602145 | D64: — | E64: ≤ 1.00 cumple. | F64: Hoja CORRIDA, sección 6
B65: Concreto por metro | C65: =CORRIDA!$C$7*CORRIDA!$C$8 -> 0.225 | D65: m³/m | E65: B · h. | F65: Cuantificación
B66: Acero por metro | C66: =100/CORRIDA!$C$74*(CORRIDA!$C$7-2*CORRIDA!$C$14/100+IF(CORRIDA!$C$114="GANCHO 90°",2*12*CORRIDA!$C$28/100,0))*INDEX(TABLAS!$E$6:$E$13,MATCH(CORRIDA!$C$25,TABLAS!$B$6:$B$13,0))+CORRIDA!$C$102*INDEX(TABLAS!$E$6:$E$13,MATCH(CORRIDA!$C$26,TABLAS!$B$6:$B$13,0)) -> 6.0649091 | D66: kg/m | E66: Transversal + longitudinal. | F66: TABLAS, tabla 1
B67: ESTADO | C67: =IF(CORRIDA!$C$132=0,"CUMPLE — todas las revisiones","NO CUMPLE — "&CORRIDA!$C$132&" revisión(es) en rojo en la hoja CORRIDA") -> CUMPLE — todas las revisiones
B69: 4. ZAPATA DE LINDERO (dado al paño del lindero)
B70: Concepto | C70: Valor | D70: Unidad | E70: Cómo se calcula / de dónde sale | F70: Referencia
B71: Zapata | C71: =LINDERO!$C$302 -> Lx × Ly × h = 1.80 × 2.60 × 0.50 m; Df = 1.50 m; dado al paño del lindero
B72: Lecho inferior | C72: =LINDERO!$C$303 -> ‖ X: #5 @ 20.0 cm (13 pzas) · ‖ Y: #5 @ 20.0 cm (9 pzas)
B73: Remate de las varillas | C73: =LINDERO!$C$304 -> ‖ X: RECTA en el lindero, RECTA adentro · ‖ Y: RECTA
B74: Parrilla superior | C74: =LINDERO!$C$305 -> No lleva
B75: Dovelas | C75: =LINDERO!$C$306 -> mín. 5 dovelas #6 con gancho 90° apoyado en la parrilla inferior
B76: Contratrabe de equilibrio — longitudinal | C76: =LINDERO!$C$307 -> 6 #6 arriba + 5 #6 abajo, corridas
B77: Contratrabe de equilibrio — estribos | C77: =LINDERO!$C$308 -> E#4 (2 ramas) @ 10.0 cm en 1.80 m desde cada paño; resto @ 15.0 cm
B78: q_máx / q_adm | C78: =LINDERO!$C$77 -> 0.91000004 | D78: — | E78: Presión de servicio contra la admisible. | F78: Hoja LINDERO, sección 5
B79: FS mínimo al volteo / FS exigido | C79: =MIN(10,MIN(LINDERO!$C$84,LINDERO!$C$85)/DATOS!$C$34) -> 3.130572 | D79: — | E79: ≥ 1.00 cumple (se muestra hasta 10). | F79: Hoja LINDERO, sección 5
B80: FS mínimo al deslizamiento / FS exigido | C80: =MIN(10,LINDERO!$C$87/DATOS!$C$35) -> 3.0706587 | D80: — | E80: ≥ 1.00 cumple (se muestra hasta 10). | F80: Hoja LINDERO, sección 5
B81: Penetración: vu / φvc (columna de borde) | C81: =LINDERO!$C$118 -> 0.75868841 | D81: — | E81: ≤ 1.00 cumple. | F81: Hoja LINDERO, sección 6 · ACI 318-19, 22.6
B82: Cortante en una dirección: Vu / φVc (la peor) | C82: =MAX(LINDERO!$C$171/LINDERO!$C$176,LINDERO!$C$178/LINDERO!$C$183) -> 0.86427643 | D82: — | E82: ≤ 1.00 cumple. | F82: Hoja LINDERO, sección 9 · ACI 318-19, Tabla 22.5.5.1
B83: Flexión de la zapata: Mu / φMn (la peor) | C83: =MAX(LINDERO!$C$123/LINDERO!$C$141,LINDERO!$C$147/LINDERO!$C$165) -> 0.69435813 | D83: — | E83: ≤ 1.00 cumple. | F83: Hoja LINDERO, secciones 7 y 8
B84: Contratrabe: Mu / φMn (la peor) | C84: =IF(LINDERO!$C$15="SÍ",MAX(LINDERO!$C$253/LINDERO!$C$272,LINDERO!$C$254/LINDERO!$C$276),0) -> 0.84057594 | D84: — | E84: ≤ 1.00 cumple. 0 si no lleva contratrabe. | F84: Hoja LINDERO, sección 13
B85: Dovelas: ldc / peralte disponible | C85: =LINDERO!$C$230/LINDERO!$C$231 -> 0.96977262 | D85: — | E85: ≤ 1.00 cumple. | F85: Hoja LINDERO, sección 12 · ACI 318-19, 25.4.9
B86: Concreto de la zapata | C86: =LINDERO!$C$8*LINDERO!$C$9*LINDERO!$C$10 -> 2.34 | D86: m³ | E86: Lx · Ly · h. | F86: Cuantificación
B87: Concreto del dado | C87: =DATOS!$C$64*DATOS!$C$65*LINDERO!$C$21 -> 0.2875 | D87: m³ | E87: cx · cy · H_dado. | F87: Cuantificación
B88: Acero de la zapata (lechos inferior y superior) | C88: =LINDERO!$C$134*(LINDERO!$C$8-2*LINDERO!$C$13/100+IF(LINDERO!$C$209="GANCHO 90°",12*LINDERO!$C$42/100,0)+IF(LINDERO!$C$207="GANCHO 90°",12*LINDERO!$C$42/100,0))*INDEX(TABLAS!$E$6:$E$13,MATCH(LINDERO!$C$35,TABLAS!$B$6:$B$13,0))+LINDERO!$C$158*(LINDERO!$C$9-2*LINDERO!$C$13/100+IF(LINDERO!$C$216="GANCHO 90°",2*12*LINDERO!$C$44/100,0))*INDEX(TABLAS!$E$6:$E$13,MATCH(LINDERO!$C$36,TABLAS!$B$6:$B$13,0))+LINDERO!$C$195*(LINDERO!$C$8-2*LINDERO!$C$13/100)*INDEX(TABLAS!$E$6:$E$13,MATCH(LINDERO!$C$41,TABLAS!$B$6:$B$13,0))+LINDERO!$C$196*(LINDERO!$C$9-2*LINDERO!$C$13/100)*INDEX(TABLAS!$E$6:$E$13,MATCH(LINDERO!$C$41,TABLAS!$B$6:$B$13,0)) -> 67.512 | D88: kg | E88: Varillas × longitud (con ganchos si los lleva) × peso lineal. No incluye dovelas ni traslapes. | F88: TABLAS, tabla 1
B89: Contratrabe: concreto por metro | C89: =IF(LINDERO!$C$15="SÍ",LINDERO!$C$238*LINDERO!$C$239,0) -> 0.36 | D89: m³/m | E89: b · h. | F89: Cuantificación
B90: Contratrabe: acero por metro (aprox.) | C90: =IF(LINDERO!$C$15="SÍ",(LINDERO!$C$263+LINDERO!$C$265)*INDEX(TABLAS!$E$6:$E$13,MATCH(LINDERO!$C$241,TABLAS!$B$6:$B$13,0))+(LINDERO!$C$243*(LINDERO!$C$239-2*LINDERO!$C$240/100)+2*(LINDERO!$C$238-2*LINDERO!$C$240/100)+0.2)*INDEX(TABLAS!$E$6:$E$13,MATCH(LINDERO!$C$242,TABLAS!$B$6:$B$13,0))*100/LINDERO!$C$291,0) -> 40.489 | D90: kg/m | E90: Longitudinal + estribos con la separación del centro (la zona confinada lleva un poco más). | F90: TABLAS, tabla 1
B91: ESTADO | C91: =IF(LINDERO!$C$309=0,"CUMPLE — todas las revisiones","NO CUMPLE — "&LINDERO!$C$309&" revisión(es) en rojo en la hoja LINDERO") -> CUMPLE — todas las revisiones

Sheet TABLAS
B1: TABLAS AUXILIARES
B2: Todas las hojas leen de aquí con INDEX/MATCH. Las tablas 3 y 4 son de ORIENTACIÓN para capturar qa y μ mientras no haya estudio de mecánica de suelos.
B4: 1. VARILLA CORRUGADA — GRADO 42 (fy = 4,200 kg/cm²)
B5: No. de varilla | C5: db (cm) | D5: As (cm²) | E5: Peso (kg/m) | F5: Equivalencia ACI 318-19 (SI) · referencia
B6: 2.5 | C6: 0.79 | D6: 0.49 | E6: 0.384 | F6: Sólo estribos · ≈ No. 8 (SI) — NMX-C-407-ONNCCE / ASTM A615M
B7: 3 | C7: 0.95 | D7: 0.71 | E7: 0.559 | F7: No. 10 (SI) — NMX-C-407-ONNCCE / ASTM A615M
B8: 4 | C8: 1.27 | D8: 1.27 | E8: 0.994 | F8: No. 13 (SI) — NMX-C-407-ONNCCE / ASTM A615M
B9: 5 | C9: 1.59 | D9: 1.98 | E9: 1.552 | F9: No. 16 (SI) — NMX-C-407-ONNCCE / ASTM A615M
B10: 6 | C10: 1.91 | D10: 2.85 | E10: 2.235 | F10: No. 19 (SI) — NMX-C-407-ONNCCE / ASTM A615M
B11: 8 | C11: 2.54 | D11: 5.07 | E11: 3.973 | F11: No. 25 (SI) — NMX-C-407-ONNCCE / ASTM A615M
B12: 10 | C12: 3.18 | D12: 7.92 | E12: 6.225 | F12: No. 32 (SI) — NMX-C-407-ONNCCE / ASTM A615M
B13: 12 | C13: 3.81 | D13: 11.4 | E13: 8.938 | F13: NMX (≈ No. 36 para los factores ψ) — NMX-C-407-ONNCCE / ASTM A615M
B14: La varilla 2.5 sólo se usa para estribos. Para los factores ψs de desarrollo (ACI 318-19, Tabla 25.4.2.5) cuentan como «No. 19 y menores» las del #6 para abajo.
B16: 2. RECUBRIMIENTO ESPECIFICADO — ACI 318-19, Tabla 20.5.1.3.1 (concreto colado en sitio no preesforzado)
B17: Condición de exposición | C17: Elemento | D17: Refuerzo | E17: Recubrimiento (mm) | F17: Dónde se usa en este libro
B18: Colado contra el suelo y permanentemente en contacto con él | C18: Todos | D18: Todos | E18: 75 | F18: Lecho inferior y caras laterales de zapatas (AISLADA, AISLADA_CT, CORRIDA, LINDERO)
B19: Expuesto a la intemperie o en contacto con el suelo | C19: Todos | D19: No. 19 a No. 57 | E19: 50 | F19: Cara superior de zapatas bajo relleno; contratrabes cimbradas
B20: Expuesto a la intemperie o en contacto con el suelo | C20: Todos | D20: No. 16 y menores | E20: 40 | F20: Ídem, varilla #5 o menor
B21: No expuesto a la intemperie ni en contacto con el suelo | C21: Vigas, columnas, pedestales | D21: Refuerzo principal, estribos | E21: 40 | F21: Sólo referencia
B23: 3. CAPACIDAD DE CARGA PRESUNTIVA — NAVFAC DM 7.02, Cap. 4, Tabla 1, págs. 7.2-142 y 7.2-143
B24: Material de apoyo | C24: Consistencia en sitio | D24: Rango (ton/ft²) | E24: Recomendado (ton/ft²) | F24: Recomendado (t/m²) = ton/ft² × 9.765
B25: Roca ígnea o metamórfica masiva cristalina: granito, diorita, basalto, gneis; conglomerado bien cementado | C25: Dura y sana | D25: 60 a 100 | E25: 80 | F25: =E25*9.765 -> 781.2
B26: Roca metamórfica foliada: pizarra, esquisto | C26: Medianamente dura y sana | D26: 30 a 40 | E26: 35 | F26: =E26*9.765 -> 341.775
B27: Roca sedimentaria: lutita dura cementada, limolita, arenisca, caliza sin cavidades | C27: Medianamente dura y sana | D27: 15 a 25 | E27: 20 | F27: =E27*9.765 -> 195.3
B28: Roca intemperizada o fracturada de cualquier tipo (excepto muy arcillosa), RQD < 25 | C28: Roca blanda | D28: 8 a 12 | E28: 10 | F28: =E28*9.765 -> 97.65
B29: Lutita compactada u otra roca muy arcillosa en condición sana | C29: Roca blanda | D29: 8 a 12 | E29: 10 | F29: =E29*9.765 -> 97.65
B30: Mezcla bien graduada de suelo fino y grueso: till, hardpan, arcilla con boleos (GW-GC, GC, SC) | C30: Muy compacta | D30: 8 a 12 | E30: 10 | F30: =E30*9.765 -> 97.65
B31: Grava, mezclas grava-arena, gravas con boleos (GW, GP, SW, SP) | C31: Muy compacta | D31: 6 a 10 | E31: 7 | F31: =E31*9.765 -> 68.355
B32: Grava, mezclas grava-arena, gravas con boleos (GW, GP, SW, SP) | C32: Media a compacta | D32: 4 a 7 | E32: 5 | F32: =E32*9.765 -> 48.825
B33: Grava, mezclas grava-arena, gravas con boleos (GW, GP, SW, SP) | C33: Suelta | D33: 2 a 6 | E33: 3 | F33: =E33*9.765 -> 29.295
B34: Arena gruesa a media, arena con poca grava (SW, SP) | C34: Muy compacta | D34: 4 a 6 | E34: 4 | F34: =E34*9.765 -> 39.06
B35: Arena gruesa a media, arena con poca grava (SW, SP) | C35: Media a compacta | D35: 2 a 4 | E35: 3 | F35: =E35*9.765 -> 29.295
B36: Arena gruesa a media, arena con poca grava (SW, SP) | C36: Suelta | D36: 1 a 3 | E36: 1.5 | F36: =E36*9.765 -> 14.6475
... B45: Limo inorgánico, limo arenoso o arcilloso, limo-arcilla-arena fina varvada | C45: Blanda | D45: 0.5 a 1 | E45: 0.5 | F45: =E45*9.765 -> 4.8825
