Workbook

Sheet DATOS
B1: PRESIONES DE VIENTO EN NAVES — EL SALVADOR (NORMA TÉCNICA PARA DISEÑO POR VIENTO 1997) — DATOS | AA1: auxiliar del croquis (no se toca)
B2: P = C_p·C_z·K·P_o (ec. 4.1). Nave rectangular de una crujía con techo a dos aguas, a un agua (hacia el muro que elijas), plano o curvo. La hoja resuelve de una vez los cuatro vientos (±X, ±Z) con puertas cerradas y con puertas abiertas (PA) y arma las cargas para STAAD. | AA2: s_k | AB2: h_k | AC2: eje dibujo | AE2: M1 u | AF2: M1 v | AG2: M1 x' | AH2: M1 y' | AI2: M2 u | AJ2: M2 v | AK2: M2 x' | AL2: M2 y' | AM2: M3 u | AN2: M3 v | AO2: M3 x' | AP2: M3 y' | AQ2: M4 u | AR2: M4 v | AS2: M4 x' | AT2: M4 y' | AU2: techo x' | AV2: techo y' | AY2: parámetro | AZ2: valor | BA2: flecha M1 x' | BB2: flecha M1 y' | BC2: flecha M2 x' | BD2: flecha M2 y' | BE2: flecha M3 x' | BF2: flecha M3 y' | BG2: flecha M4 x' | BH2: flecha M4 y' | BI2: eje X x' | BJ2: eje X y' | BK2: eje Y x' | BL2: eje Y y' | BM2: eje Z x' | BN2: eje Z y' | BO2: A1 fija x' | BP2: A1 fija y' | BQ2: A1 oper x' | BR2: A1 oper y' | BS2: A2 fija x' | BT2: A2 fija y' | BU2: A2 oper x' | BV2: A2 oper y' | BW2: A3 fija x' | BX2: A3 fija y' | BY2: A3 oper x' | BZ2: A3 oper y' | CA2: A4 fija x' | CB2: A4 fija y' | CC2: A4 oper x' | CD2: A4 oper y' | CE2: A5 fija x' | CF2: A5 fija y' | CG2: A5 oper x' | CH2: A5 oper y' | CI2: A6 fija x' | CJ2: A6 fija y' | CK2: A6 oper x' | CL2: A6 oper y' | CM2: A7 fija x' | CN2: A7 fija y' | CO2: A7 oper x' | CP2: A7 oper y' | CQ2: A8 fija x' | CR2: A8 fija y' | CS2: A8 oper x' | CT2: A8 oper y' | CU2: A9 fija x' | CV2: A9 fija y' | CW2: A9 oper x' | CX2: A9 oper y' | CY2: A10 fija x' | CZ2: A10 fija y' | DA2: A10 oper x' | DB2: A10 oper y' | DC2: A11 fija x' | DD2: A11 fija y' | DE2: A11 oper x' | DF2: A11 oper y' | DG2: A12 fija x' | DH2: A12 fija y' | DI2: A12 oper x' | DJ2: A12 oper y' | DK2: A13 fija x' | DL2: A13 fija y' | DM2: A13 oper x' | DN2: A13 oper y' | DO2: A14 fija x' | DP2: A14 fija y' | DQ2: A14 oper x' | DR2: A14 oper y' | DS2: A15 fija x' | DT2: A15 fija y' | DU2: A15 oper x' | DV2: A15 oper y' | DW2: A16 fija x' | DX2: A16 fija y' | DY2: A16 oper x' | DZ2: A16 oper y' | EA2: A17 fija x' | EB2: A17 fija y' | EC2: A17 oper x' | ED2: A17 oper y' | EE2: A18 fija x' | EF2: A18 fija y' | EG2: A18 oper x' | EH2: A18 oper y' | EI2: A19 fija x' | EJ2: A19 fija y' | EK2: A19 oper x' | EL2: A19 oper y' | EM2: A20 fija x' | EN2: A20 fija y' | EO2: A20 oper x' | EP2: A20 oper y'
B3: CÓMO SE LLENA: sólo celdas amarillas con letra azul (aquí, en ABERTURAS y en LINEAS). Muro 1 = atrás (Z = 0: puerta y cortina), Muro 2 = frente (Z = L: abierto, sin muro en STAAD), Muro 3 = izquierdo (X = 0), Muro 4 = derecho (X = B), como se ven en el croquis. Los marcos quedan en el plano X-Y. Lo marcado EJEMPLO es del NOSE DOCK H5-H6 (modelo R3): cámbialo para otra nave. | AA3: =$C$23*0/8 -> 0 | AB3: =IF($C$14="PLANO",$C$17,IF($C$14="DOS AGUAS",$C$17+($C$18-$C$17)*(1-ABS(2*($AA$3)/$C$23-1)),IF($C$14="UN AGUA",IF(N($C$25)=0,$C$18-($C$18-$C$17)*($AA$3)/$C$23,$C$17+($C$18-$C$17)*($AA$3)/$C$23),$C$17+4*($C$18-$C$17)*($AA$3)/$C$23*(1-($AA$3)/$C$23)))) -> 10.62 | AC3: =IF($C$22="Z","Z","X") -> Z | AE3: =0 -> 0 | AF3: =0 -> 0 | AG3: =((($AZ$5+$AE3*($C$12-2*$AZ$5)/$C$12)-$AZ$3*$C$13)+$AZ$39)/$AZ$38 -> 0.56267062 | AH3: =((IF($AF3>0,$AF3-$AZ$5,0)+$AZ$4*$C$13)+$AZ$40)/$AZ$38 -> 0.35505194 | AI3: =0 -> 0 | AJ3: =0 -> 0 | AK3: =((($AZ$5+$AI3*($C$12-2*$AZ$5)/$C$12))+$AZ$39)/$AZ$38 -> 0.87995107 | AL3: =((IF($AJ3>0,$AJ3-$AZ$5,0))+$AZ$40)/$AZ$38 -> 0.15864023 | AM3: =0 -> 0 | AN3: =0 -> 0 | AO3: =((-$AZ$3*($C$13-($AZ$5+$AM3*($C$13-2*$AZ$5)/$C$13)))+$AZ$39)/$AZ$38 -> 0.55390763 | AP3: =((IF($AN3>0,$AN3-$AZ$5,0)+$AZ$4*($C$13-($AZ$5+$AM3*($C$13-2*$AZ$5)/$C$13)))+$AZ$40)/$AZ$38 -> 0.3511237 | AQ3: =0 -> 0 | AR3: =0 -> 0 | AS3: =(($C$12-$AZ$3*($C$13-($AZ$5+$AQ3*($C$13-2*$AZ$5)/$C$13)))+$AZ$39)/$AZ$38 -> 1.0298283 | AT3: =((IF($AR3>0,$AR3-$AZ$5,0)+$AZ$4*($C$13-($AZ$5+$AQ3*($C$13-2*$AZ$5)/$C$13)))+$AZ$40)/$AZ$38 -> 0.3511237 | AU3: =((IF($AC$3="Z",0,$AA$3)-$AZ$3*($C$13-IF($AC$3="Z",$AA$3,0)))+$AZ$39)/$AZ$38 -> 0.54756202 | AV3: =(($AB$3+$AZ$4*($C$13-IF($AC$3="Z",$AA$3,0)))+$AZ$40)/$AZ$38 -> 0.85646837 | AY3: kx | AZ3: =0.42 -> 0.42 | BA3: =(($AZ$17)+$AZ$39)/$AZ$38 -> 0.78552236 | BB3: =(($AZ$18)+$AZ$40)/$AZ$38 -> 0.93654391 | BC3: =(($AZ$21)+$AZ$39)/$AZ$38 -> 1.1028028 | BD3: =(($AZ$22)+$AZ$40)/$AZ$38 -> 0.063456091 | BE3: =(($AZ$25)+$AZ$39)/$AZ$38 -> 0.6388969 | BF3: =(($AZ$26)+$AZ$40)/$AZ$38 -> 0.18954073 | BG3: =(($AZ$29)+$AZ$39)/$AZ$38 -> 1.2494283 | BH3: =(($AZ$30)+$AZ$40)/$AZ$38 -> 0.79157353 | BI3: =(($AZ$31)+$AZ$39)/$AZ$38 -> 1.4994034 | BJ3: =(($AZ$32)+$AZ$40)/$AZ$38 -> 0.23796034 | BK3: =(($AZ$31)+$AZ$39)/$AZ$38 -> 1.4994034 | BL3: =(($AZ$32)+$AZ$40)/$AZ$38 -> 0.23796034 | BM3: =(($AZ$31)+$AZ$39)/$AZ$38 -> 1.4994034 | BN3: =(($AZ$32)+$AZ$40)/$AZ$38 -> 0.23796034 | BO3: =((IF(AND(ABERTURAS!$K$7="OK",ABERTURAS!$E$7="FIJA"),CHOOSE(ABERTURAS!$N$7,ABERTURAS!$O$7-$AZ$3*$C$13,ABERTURAS!$O$7,-$AZ$3*($C$13-ABERTURAS!$O$7),$C$12-$AZ$3*($C$13-ABERTURAS!$O$7)),0))+$AZ$39)/$AZ$38 -> 0.86484248 | BP3: =((IF(AND(ABERTURAS!$K$7="OK",ABERTURAS!$E$7="FIJA"),ABERTURAS!$Q$7+CHOOSE(ABERTURAS!$N$7,$AZ$4*$C$13,0,$AZ$4*($C$13-ABERTURAS!$O$7),$AZ$4*($C$13-ABERTURAS!$O$7)),0))+$AZ$40)/$AZ$38 -> 0.15864023 | BQ3: =((IF(AND(ABERTURAS!$K$7="OK",ABERTURAS!$E$7="OPERABLE"),CHOOSE(ABERTURAS!$N$7,ABERTURAS!$O$7-$AZ$3*$C$13,ABERTURAS!$O$7,-$AZ$3*($C$13-ABERTURAS!$O$7),$C$12-$AZ$3*($C$13-ABERTURAS!$O$7)),0))+$AZ$39)/$AZ$38 -> 0.57789724 | BR3: =((IF(AND(ABERTURAS!$K$7="OK",ABERTURAS!$E$7="OPERABLE"),ABERTURAS!$Q$7+CHOOSE(ABERTURAS!$N$7,$AZ$4*$C$13,0,$AZ$4*($C$13-ABERTURAS!$O$7),$AZ$4*($C$13-ABERTURAS!$O$7)),0))+$AZ$40)/$AZ$38 -> 0.35505194 | BS3: =((IF(AND(ABERTURAS!$K$8="OK",ABERTURAS!$E$8="FIJA"),CHOOSE(ABERTURAS!$N$8,ABERTURAS!$O$8-$AZ$3*$C$13,ABERTURAS!$O$8,-$AZ$3*($C$13-ABERTURAS!$O$8),$C$12-$AZ$3*($C$13-ABERTURAS!$O$8)),0))+$AZ$39)/$AZ$38 -> 0.86484248 | BT3: =((IF(AND(ABERTURAS!$K$8="OK",ABERTURAS!$E$8="FIJA"),ABERTURAS!$Q$8+CHOOSE(ABERTURAS!$N$8,$AZ$4*$C$13,0,$AZ$4*($C$13-ABERTURAS!$O$8),$AZ$4*($C$13-ABERTURAS!$O$8)),0))+$AZ$40)/$AZ$38 -> 0.15864023 | BU3: =((IF(AND(ABERTURAS!$K$8="OK",ABERTURAS!$E$8="OPERABLE"),CHOOSE(ABERTURAS!$N$8,ABERTURAS!$O$8-$AZ$3*$C$13,ABERTURAS!$O$8,-$AZ$3*($C$13-ABERTURAS!$O$8),$C$12-$AZ$3*($C$13-ABERTURAS!$O$8)),0))+$AZ$39)/$AZ$38 -> 0.6649794 | BV3: =((IF(AND(ABERTURAS!$K$8="OK",ABERTURAS!$E$8="OPERABLE"),ABERTURAS!$Q$8+CHOOSE(ABERTURAS!$N$8,$AZ$4*$C$13,0,$AZ$4*($C$13-ABERTURAS!$O$8),$AZ$4*($C$13-ABERTURAS!$O$8)),0))+$AZ$40)/$AZ$38 -> 0.35505194 | BW3: =((IF(AND(ABERTURAS!$K$9="OK",ABERTURAS!$E$9="FIJA"),CHOOSE(ABERTURAS!$N$9,ABERTURAS!$O$9-$AZ$3*$C$13,ABERTURAS!$O$9,-$AZ$3*($C$13-ABERTURAS!$O$9),$C$12-$AZ$3*($C$13-ABERTURAS!$O$9)),0))+$AZ$39)/$AZ$38 -> 0.86484248 | BX3: =((IF(AND(ABERTURAS!$K$9="OK",ABERTURAS!$E$9="FIJA"),ABERTURAS!$Q$9+CHOOSE(ABERTURAS!$N$9,$AZ$4*$C$13,0,$AZ$4*($C$13-ABERTURAS!$O$9),$AZ$4*($C$13-ABERTURAS!$O$9)),0))+$AZ$40)/$AZ$38 -> 0.15864023 | BY3: =((IF(AND(ABERTURAS!$K$9="OK",ABERTURAS!$E$9="OPERABLE"),CHOOSE(ABERTURAS!$N$9,ABERTURAS!$O$9-$AZ$3*$C$13,ABERTURAS!$O$9,-$AZ$3*($C$13-ABERTURAS!$O$9),$C$12-$AZ$3*($C$13-ABERTURAS!$O$9)),0))+$AZ$39)/$AZ$38 -> 0.86484248 | BZ3: =((IF(AND(ABERTURAS!$K$9="OK",ABERTURAS!$E$9="OPERABLE"),ABERTURAS!$Q$9+CHOOSE(ABERTURAS!$N$9,$AZ$4*$C$13,0,$AZ$4*($C$13-ABERTURAS!$O$9),$AZ$4*($C$13-ABERTURAS!$O$9)),0))+$AZ$40)/$AZ$38 -> 0.15864023 | CA3: =((IF(AND(ABERTURAS!$K$10="OK",ABERTURAS!$E$10="FIJA"),CHOOSE(ABERTURAS!$N$10,ABERTURAS!$O$10-$AZ$3*$C$13,ABERTURAS!$O$10,-$AZ$3*($C$13-ABERTURAS!$O$10),$C$12-$AZ$3*($C$13-ABERTURAS!$O$10)),0))+$AZ$39)/$AZ$38 -> 0.86484248 | CB3: =((IF(AND(ABERTURAS!$K$10="OK",ABERTURAS!$E$10="FIJA"),ABERTURAS!$Q$10+CHOOSE(ABERTURAS!$N$10,$AZ$4*$C$13,0,$AZ$4*($C$13-ABERTURAS!$O$10),$AZ$4*($C$13-ABERTURAS!$O$10)),0))+$AZ$40)/$AZ$38 -> 0.15864023 | CC3: =((IF(AND(ABERTURAS!$K$10="OK",ABERTURAS!$E$10="OPERABLE"),CHOOSE(ABERTURAS!$N$10,ABERTURAS!$O$10-$AZ$3*$C$13,ABERTURAS!$O$10,-$AZ$3*($C$13-ABERTURAS!$O$10),$C$12-$AZ$3*($C$13-ABERTURAS!$O$10)),0))+$AZ$39)/$AZ$38 -> 0.86484248 | CD3: =((IF(AND(ABERTURAS!$K$10="OK",ABERTURAS!$E$10="OPERABLE"),ABERTURAS!$Q$10+CHOOSE(ABERTURAS!$N$10,$AZ$4*$C$13,0,$AZ$4*($C$13-ABERTURAS!$O$10),$AZ$4*($C$13-ABERTURAS!$O$10)),0))+$AZ$40)/$AZ$38 -> 0.15864023 | CE3: =((IF(AND(ABERTURAS!$K$11="OK",ABERTURAS!$E$11="FIJA"),CHOOSE(ABERTURAS!$N$11,ABERTURAS!$O$11-$AZ$3*$C$13,ABERTURAS!$O$11,-$AZ$3*($C$13-ABERTURAS!$O$11),$C$12-$AZ$3*($C$13-ABERTURAS!$O$11)),0))+$AZ$39)/$AZ$38 -> 0.86484248 | CF3: =((IF(AND(ABERTURAS!$K$11="OK",ABERTURAS!$E$11="FIJA"),ABERTURAS!$Q$11+CHOOSE(ABERTURAS!$N$11,$AZ$4*$C$13,0,$AZ$4*($C$13-ABERTURAS!$O$11),$AZ$4*($C$13-ABERTURAS!$O$11)),0))+$AZ$40)/$AZ$38 -> 0.15864023 | CG3: =((IF(AND(ABERTURAS!$K$11="OK",ABERTURAS!$E$11="OPERABLE"),CHOOSE(ABERTURAS!$N$11,ABERTURAS!$O$11-$AZ$3*$C$13,ABERTURAS!$O$11,-$AZ$3*($C$13-ABERTURAS!$O$11),$C$12-$AZ$3*($C$13-ABERTURAS!$O$11)),0))+$AZ$39)/$AZ$38 -> 0.86484248 | CH3: =((IF(AND(ABERTURAS!$K$11="OK",ABERTURAS!$E$11="OPERABLE"),ABERTURAS!$Q$11+CHOOSE(ABERTURAS!$N$11,$AZ$4*$C$13,0,$AZ$4*($C$13-ABERTURAS!$O$11),$AZ$4*($C$13-ABERTURAS!$O$11)),0))+$AZ$40)/$AZ$38 -> 0.15864023 | CI3: =((IF(AND(ABERTURAS!$K$12="OK",ABERTURAS!$E$12="FIJA"),CHOOSE(ABERTURAS!$N$12,ABERTURAS!$O$12-$AZ$3*$C$13,ABERTURAS!$O$12,-$AZ$3*($C$13-ABERTURAS!$O$12),$C$12-$AZ$3*($C$13-ABERTURAS!$O$12)),0))+$AZ$39)/$AZ$38 -> 0.86484248 | CJ3: =((IF(AND(ABERTURAS!$K$12="OK",ABERTURAS!$E$12="FIJA"),ABERTURAS!$Q$12+CHOOSE(ABERTURAS!$N$12,$AZ$4*$C$13,0,$AZ$4*($C$13-ABERTURAS!$O$12),$AZ$4*($C$13-ABERTURAS!$O$12)),0))+$AZ$40)/$AZ$38 -> 0.15864023 | CK3: =((IF(AND(ABERTURAS!$K$12="OK",ABERTURAS!$E$12="OPERABLE"),CHOOSE(ABERTURAS!$N$12,ABERTURAS!$O$12-$AZ$3*$C$13,ABERTURAS!$O$12,-$AZ$3*($C$13-ABERTURAS!$O$12),$C$12-$AZ$3*($C$13-ABERTURAS!$O$12)),0))+$AZ$39)/$AZ$38 -> 0.86484248 | CL3: =((IF(AND(ABERTURAS!$K$12="OK",ABERTURAS!$E$12="OPERABLE"),ABERTURAS!$Q$12+CHOOSE(ABERTURAS!$N$12,$AZ$4*$C$13,0,$AZ$4*($C$13-ABERTURAS!$O$12),$AZ$4*($C$13-ABERTURAS!$O$12)),0))+$AZ$40)/$AZ$38 -> 0.15864023 | CM3: =((IF(AND(ABERTURAS!$K$13="OK",ABERTURAS!$E$13="FIJA"),CHOOSE(ABERTURAS!$N$13,ABERTURAS!$O$13-$AZ$3*$C$13,ABERTURAS!$O$13,-$AZ$3*($C$13-ABERTURAS!$O$13),$C$12-$AZ$3*($C$13-ABERTURAS!$O$13)),0))+$AZ$39)/$AZ$38 -> 0.86484248 | CN3: =((IF(AND(ABERTURAS!$K$13="OK",ABERTURAS!$E$13="FIJA"),ABERTURAS!$Q$13+CHOOSE(ABERTURAS!$N$13,$AZ$4*$C$13,0,$AZ$4*($C$13-ABERTURAS!$O$13),$AZ$4*($C$13-ABERTURAS!$O$13)),0))+$AZ$40)/$AZ$38 -> 0.15864023 | CO3: =((IF(AND(ABERTURAS!$K$13="OK",ABERTURAS!$E$13="OPERABLE"),CHOOSE(ABERTURAS!$N$13,ABERTURAS!$O$13-$AZ$3*$C$13,ABERTURAS!$O$13,-$AZ$3*($C$13-ABERTURAS!$O$13),$C$12-$AZ$3*($C$13-ABERTURAS!$O$13)),0))+$AZ$39)/$AZ$38 -> 0.86484248 | CP3: =((IF(AND(ABERTURAS!$K$13="OK",ABERTURAS!$E$13="OPERABLE"),ABERTURAS!$Q$13+CHOOSE(ABERTURAS!$N$13,$AZ$4*$C$13,0,$AZ$4*($C$13-ABERTURAS!$O$13),$AZ$4*($C$13-ABERTURAS!$O$13)),0))+$AZ$40)/$AZ$38 -> 0.15864023 | CQ3: =((IF(AND(ABERTURAS!$K$14="OK",ABERTURAS!$E$14="FIJA"),CHOOSE(ABERTURAS!$N$14,ABERTURAS!$O$14-$AZ$3*$C$13,ABERTURAS!$O$14,-$AZ$3*($C$13-ABERTURAS!$O$14),$C$12-$AZ$3*($C$13-ABERTURAS!$O$14)),0))+$AZ$39)/$AZ$38 -> 0.86484248 | CR3: =((IF(AND(ABERTURAS!$K$14="OK",ABERTURAS!$E$14="FIJA"),ABERTURAS!$Q$14+CHOOSE(ABERTURAS!$N$14,$AZ$4*$C$13,0,$AZ$4*($C$13-ABERTURAS!$O$14),$AZ$4*($C$13-ABERTURAS!$O$14)),0))+$AZ$40)/$AZ$38 -> 0.15864023 | CS3: =((IF(AND(ABERTURAS!$K$14="OK",ABERTURAS!$E$14="OPERABLE"),CHOOSE(ABERTURAS!$N$14,ABERTURAS!$O$14-$AZ$3*$C$13,ABERTURAS!$O$14,-$AZ$3*($C$13-ABERTURAS!$O$14),$C$12-$AZ$3*($C$13-ABERTURAS!$O$14)),0))+$AZ$39)/$AZ$38 -> 0.86484248 | CT3: =((IF(AND(ABERTURAS!$K$14="OK",ABERTURAS!$E$14="OPERABLE"),ABERTURAS!$Q$14+CHOOSE(ABERTURAS!$N$14,$AZ$4*$C$13,0,$AZ$4*($C$13-ABERTURAS!$O$14),$AZ$4*($C$13-ABERTURAS!$O$14)),0))+$AZ$40)/$AZ$38 -> 0.15864023 | CU3: =((IF(AND(ABERTURAS!$K$15="OK",ABERTURAS!$E$15="FIJA"),CHOOSE(ABERTURAS!$N$15,ABERTURAS!$O$15-$AZ$3*$C$13,ABERTURAS!$O$15,-$AZ$3*($C$13-ABERTURAS!$O$15),$C$12-$AZ$3*($C$13-ABERTURAS!$O$15)),0))+$AZ$39)/$AZ$38 -> 0.86484248 | CV3: =((IF(AND(ABERTURAS!$K$15="OK",ABERTURAS!$E$15="FIJA"),ABERTURAS!$Q$15+CHOOSE(ABERTURAS!$N$15,$AZ$4*$C$13,0,$AZ$4*($C$13-ABERTURAS!$O$15),$AZ$4*($C$13-ABERTURAS!$O$15)),0))+$AZ$40)/$AZ$38 -> 0.15864023 | CW3: =((IF(AND(ABERTURAS!$K$15="OK",ABERTURAS!$E$15="OPERABLE"),CHOOSE(ABERTURAS!$N$15,ABERTURAS!$O$15-$AZ$3*$C$13,ABERTURAS!$O$15,-$AZ$3*($C$13-ABERTURAS!$O$15),$C$12-$AZ$3*($C$13-ABERTURAS!$O$15)),0))+$AZ$39)/$AZ$38 -> 0.86484248 | CX3: =((IF(AND(ABERTURAS!$K$15="OK",ABERTURAS!$E$15="OPERABLE"),ABERTURAS!$Q$15+CHOOSE(ABERTURAS!$N$15,$AZ$4*$C$13,0,$AZ$4*($C$13-ABERTURAS!$O$15),$AZ$4*($C$13-ABERTURAS!$O$15)),0))+$AZ$40)/$AZ$38 -> 0.15864023 | CY3: =((IF(AND(ABERTURAS!$K$16="OK",ABERTURAS!$E$16="FIJA"),CHOOSE(ABERTURAS!$N$16,ABERTURAS!$O$16-$AZ$3*$C$13,ABERTURAS!$O$16,-$AZ$3*($C$13-ABERTURAS!$O$16),$C$12-$AZ$3*($C$13-ABERTURAS!$O$16)),0))+$AZ$39)/$AZ$38 -> 0.86484248 | CZ3: =((IF(AND(ABERTURAS!$K$16="OK",ABERTURAS!$E$16="FIJA"),ABERTURAS!$Q$16+CHOOSE(ABERTURAS!$N$16,$AZ$4*$C$13,0,$AZ$4*($C$13-ABERTURAS!$O$16),$AZ$4*($C$13-ABERTURAS!$O$16)),0))+$AZ$40)/$AZ$38 -> 0.15864023 | DA3: =((IF(AND(ABERTURAS!$K$16="OK",ABERTURAS!$E$16="OPERABLE"),CHOOSE(ABERTURAS!$N$16,ABERTURAS!$O$16-$AZ$3*$C$13,ABERTURAS!$O$16,-$AZ$3*($C$13-ABERTURAS!$O$16),$C$12-$AZ$3*($C$13-ABERTURAS!$O$16)),0))+$AZ$39)/$AZ$38 -> 0.86484248 | DB3: =((IF(AND(ABERTURAS!$K$16="OK",ABERTURAS!$E$16="OPERABLE"),ABERTURAS!$Q$16+CHOOSE(ABERTURAS!$N$16,$AZ$4*$C$13,0,$AZ$4*($C$13-ABERTURAS!$O$16),$AZ$4*($C$13-ABERTURAS!$O$16)),0))+$AZ$40)/$AZ$38 -> 0.15864023 | DC3: =((IF(AND(ABERTURAS!$K$17="OK",ABERTURAS!$E$17="FIJA"),CHOOSE(ABERTURAS!$N$17,ABERTURAS!$O$17-$AZ$3*$C$13,ABERTURAS!$O$17,-$AZ$3*($C$13-ABERTURAS!$O$17),$C$12-$AZ$3*($C$13-ABERTURAS!$O$17)),0))+$AZ$39)/$AZ$38 -> 0.86484248 | DD3: =((IF(AND(ABERTURAS!$K$17="OK",ABERTURAS!$E$17="FIJA"),ABERTURAS!$Q$17+CHOOSE(ABERTURAS!$N$17,$AZ$4*$C$13,0,$AZ$4*($C$13-ABERTURAS!$O$17),$AZ$4*($C$13-ABERTURAS!$O$17)),0))+$AZ$40)/$AZ$38 -> 0.15864023 | DE3: =((IF(AND(ABERTURAS!$K$17="OK",ABERTURAS!$E$17="OPERABLE"),CHOOSE(ABERTURAS!$N$17,ABERTURAS!$O$17-$AZ$3*$C$13,ABERTURAS!$O$17,-$AZ$3*($C$13-ABERTURAS!$O$17),$C$12-$AZ$3*($C$13-ABERTURAS!$O$17)),0))+$AZ$39)/$AZ$38 -> 0.86484248 | DF3: =((IF(AND(ABERTURAS!$K$17="OK",ABERTURAS!$E$17="OPERABLE"),ABERTURAS!$Q$17+CHOOSE(ABERTURAS!$N$17,$AZ$4*$C$13,0,$AZ$4*($C$13-ABERTURAS!$O$17),$AZ$4*($C$13-ABERTURAS!$O$17)),0))+$AZ$40)/$AZ$38 -> 0.15864023 | DG3: =((IF(AND(ABERTURAS!$K$18="OK",ABERTURAS!$E$18="FIJA"),CHOOSE(ABERTURAS!$N$18,ABERTURAS!$O$18-$AZ$3*$C$13,ABERTURAS!$O$18,-$AZ$3*($C$13-ABERTURAS!$O$18),$C$12-$AZ$3*($C$13-ABERTURAS!$O$18)),0))+$AZ$39)/$AZ$38 -> 0.86484248 | DH3: =((IF(AND(ABERTURAS!$K$18="OK",ABERTURAS!$E$18="FIJA"),ABERTURAS!$Q$18+CHOOSE(ABERTURAS!$N$18,$AZ$4*$C$13,0,$AZ$4*($C$13-ABERTURAS!$O$18),$AZ$4*($C$13-ABERTURAS!$O$18)),0))+$AZ$40)/$AZ$38 -> 0.15864023 | DI3: =((IF(AND(ABERTURAS!$K$18="OK",ABERTURAS!$E$18="OPERABLE"),CHOOSE(ABERTURAS!$N$18,ABERTURAS!$O$18-$AZ$3*$C$13,ABERTURAS!$O$18,-$AZ$3*($C$13-ABERTURAS!$O$18),$C$12-$AZ$3*($C$13-ABERTURAS!$O$18)),0))+$AZ$39)/$AZ$38 -> 0.86484248 | DJ3: =((IF(AND(ABERTURAS!$K$18="OK",ABERTURAS!$E$18="OPERABLE"),ABERTURAS!$Q$18+CHOOSE(ABERTURAS!$N$18,$AZ$4*$C$13,0,$AZ$4*($C$13-ABERTURAS!$O$18),$AZ$4*($C$13-ABERTURAS!$O$18)),0))+$AZ$40)/$AZ$38 -> 0.15864023 | DK3: =((IF(AND(ABERTURAS!$K$19="OK",ABERTURAS!$E$19="FIJA"),CHOOSE(ABERTURAS!$N$19,ABERTURAS!$O$19-$AZ$3*$C$13,ABERTURAS!$O$19,-$AZ$3*($C$13-ABERTURAS!$O$19),$C$12-$AZ$3*($C$13-ABERTURAS!$O$19)),0))+$AZ$39)/$AZ$38 -> 0.86484248 | DL3: =((IF(AND(ABERTURAS!$K$19="OK",ABERTURAS!$E$19="FIJA"),ABERTURAS!$Q$19+CHOOSE(ABERTURAS!$N$19,$AZ$4*$C$13,0,$AZ$4*($C$13-ABERTURAS!$O$19),$AZ$4*($C$13-ABERTURAS!$O$19)),0))+$AZ$40)/$AZ$38 -> 0.15864023 | DM3: =((IF(AND(ABERTURAS!$K$19="OK",ABERTURAS!$E$19="OPERABLE"),CHOOSE(ABERTURAS!$N$19,ABERTURAS!$O$19-$AZ$3*$C$13,ABERTURAS!$O$19,-$AZ$3*($C$13-ABERTURAS!$O$19),$C$12-$AZ$3*($C$13-ABERTURAS!$O$19)),0))+$AZ$39)/$AZ$38 -> 0.86484248 | DN3: =((IF(AND(ABERTURAS!$K$19="OK",ABERTURAS!$E$19="OPERABLE"),ABERTURAS!$Q$19+CHOOSE(ABERTURAS!$N$19,$AZ$4*$C$13,0,$AZ$4*($C$13-ABERTURAS!$O$19),$AZ$4*($C$13-ABERTURAS!$O$19)),0))+$AZ$40)/$AZ$38 -> 0.15864023 | DO3: =((IF(AND(ABERTURAS!$K$20="OK",ABERTURAS!$E$20="FIJA"),CHOOSE(ABERTURAS!$N$20,ABERTURAS!$O$20-$AZ$3*$C$13,ABERTURAS!$O$20,-$AZ$3*($C$13-ABERTURAS!$O$20),$C$12-$AZ$3*($C$13-ABERTURAS!$O$20)),0))+$AZ$39)/$AZ$38 -> 0.86484248 | DP3: =((IF(AND(ABERTURAS!$K$20="OK",ABERTURAS!$E$20="FIJA"),ABERTURAS!$Q$20+CHOOSE(ABERTURAS!$N$20,$AZ$4*$C$13,0,$AZ$4*($C$13-ABERTURAS!$O$20),$AZ$4*($C$13-ABERTURAS!$O$20)),0))+$AZ$40)/$AZ$38 -> 0.15864023 | DQ3: =((IF(AND(ABERTURAS!$K$20="OK",ABERTURAS!$E$20="OPERABLE"),CHOOSE(ABERTURAS!$N$20,ABERTURAS!$O$20-$AZ$3*$C$13,ABERTURAS!$O$20,-$AZ$3*($C$13-ABERTURAS!$O$20),$C$12-$AZ$3*($C$13-ABERTURAS!$O$20)),0))+$AZ$39)/$AZ$38 -> 0.86484248 | DR3: =((IF(AND(ABERTURAS!$K$20="OK",ABERTURAS!$E$20="OPERABLE"),ABERTURAS!$Q$20+CHOOSE(ABERTURAS!$N$20,$AZ$4*$C$13,0,$AZ$4*($C$13-ABERTURAS!$O$20),$AZ$4*($C$13-ABERTURAS!$O$20)),0))+$AZ$40)/$AZ$38 -> 0.15864023 | DS3: =((IF(AND(ABERTURAS!$K$21="OK",ABERTURAS!$E$21="FIJA"),CHOOSE(ABERTURAS!$N$21,ABERTURAS!$O$21-$AZ$3*$C$13,ABERTURAS!$O$21,-$AZ$3*($C$13-ABERTURAS!$O$21),$C$12-$AZ$3*($C$13-ABERTURAS!$O$21)),0))+$AZ$39)/$AZ$38 -> 0.86484248 | DT3: =((IF(AND(ABERTURAS!$K$21="OK",ABERTURAS!$E$21="FIJA"),ABERTURAS!$Q$21+CHOOSE(ABERTURAS!$N$21,$AZ$4*$C$13,0,$AZ$4*($C$13-ABERTURAS!$O$21),$AZ$4*($C$13-ABERTURAS!$O$21)),0))+$AZ$40)/$AZ$38 -> 0.15864023 | DU3: =((IF(AND(ABERTURAS!$K$21="OK",ABERTURAS!$E$21="OPERABLE"),CHOOSE(ABERTURAS!$N$21,ABERTURAS!$O$21-$AZ$3*$C$13,ABERTURAS!$O$21,-$AZ$3*($C$13-ABERTURAS!$O$21),$C$12-$AZ$3*($C$13-ABERTURAS!$O$21)),0))+$AZ$39)/$AZ$38 -> 0.86484248 | DV3: =((IF(AND(ABERTURAS!$K$21="OK",ABERTURAS!$E$21="OPERABLE"),ABERTURAS!$Q$21+CHOOSE(ABERTURAS!$N$21,$AZ$4*$C$13,0,$AZ$4*($C$13-ABERTURAS!$O$21),$AZ$4*($C$13-ABERTURAS!$O$21)),0))+$AZ$40)/$AZ$38 -> 0.15864023 | DW3: =((IF(AND(ABERTURAS!$K$22="OK",ABERTURAS!$E$22="FIJA"),CHOOSE(ABERTURAS!$N$22,ABERTURAS!$O$22-$AZ$3*$C$13,ABERTURAS!$O$22,-$AZ$3*($C$13-ABERTURAS!$O$22),$C$12-$AZ$3*($C$13-ABERTURAS!$O$22)),0))+$AZ$39)/$AZ$38 -> 0.86484248 | DX3: =((IF(AND(ABERTURAS!$K$22="OK",ABERTURAS!$E$22="FIJA"),ABERTURAS!$Q$22+CHOOSE(ABERTURAS!$N$22,$AZ$4*$C$13,0,$AZ$4*($C$13-ABERTURAS!$O$22),$AZ$4*($C$13-ABERTURAS!$O$22)),0))+$AZ$40)/$AZ$38 -> 0.15864023 | DY3: =((IF(AND(ABERTURAS!$K$22="OK",ABERTURAS!$E$22="OPERABLE"),CHOOSE(ABERTURAS!$N$22,ABERTURAS!$O$22-$AZ$3*$C$13,ABERTURAS!$O$22,-$AZ$3*($C$13-ABERTURAS!$O$22),$C$12-$AZ$3*($C$13-ABERTURAS!$O$22)),0))+$AZ$39)/$AZ$38 -> 0.86484248 | DZ3: =((IF(AND(ABERTURAS!$K$22="OK",ABERTURAS!$E$22="OPERABLE"),ABERTURAS!$Q$22+CHOOSE(ABERTURAS!$N$22,$AZ$4*$C$13,0,$AZ$4*($C$13-ABERTURAS!$O$22),$AZ$4*($C$13-ABERTURAS!$O$22)),0))+$AZ$40)/$AZ$38 -> 0.15864023 | EA3: =((IF(AND(ABERTURAS!$K$23="OK",ABERTURAS!$E$23="FIJA"),CHOOSE(ABERTURAS!$N$23,ABERTURAS!$O$23-$AZ$3*$C$13,ABERTURAS!$O$23,-$AZ$3*($C$13-ABERTURAS!$O$23),$C$12-$AZ$3*($C$13-ABERTURAS!$O$23)),0))+$AZ$39)/$AZ$38 -> 0.86484248 | EB3: =((IF(AND(ABERTURAS!$K$23="OK",ABERTURAS!$E$23="FIJA"),ABERTURAS!$Q$23+CHOOSE(ABERTURAS!$N$23,$AZ$4*$C$13,0,$AZ$4*($C$13-ABERTURAS!$O$23),$AZ$4*($C$13-ABERTURAS!$O$23)),0))+$AZ$40)/$AZ$38 -> 0.15864023 | EC3: =((IF(AND(ABERTURAS!$K$23="OK",ABERTURAS!$E$23="OPERABLE"),CHOOSE(ABERTURAS!$N$23,ABERTURAS!$O$23-$AZ$3*$C$13,ABERTURAS!$O$23,-$AZ$3*($C$13-ABERTURAS!$O$23),$C$12-$AZ$3*($C$13-ABERTURAS!$O$23)),0))+$AZ$39)/$AZ$38 -> 0.86484248 | ED3: =((IF(AND(ABERTURAS!$K$23="OK",ABERTURAS!$E$23="OPERABLE"),ABERTURAS!$Q$23+CHOOSE(ABERTURAS!$N$23,$AZ$4*$C$13,0,$AZ$4*($C$13-ABERTURAS!$O$23),$AZ$4*($C$13-ABERTURAS!$O$23)),0))+$AZ$40)/$AZ$38 -> 0.15864023 | EE3: =((IF(AND(ABERTURAS!$K$24="OK",ABERTURAS!$E$24="FIJA"),CHOOSE(ABERTURAS!$N$24,ABERTURAS!$O$24-$AZ$3*$C$13,ABERTURAS!$O$24,-$AZ$3*($C$13-ABERTURAS!$O$24),$C$12-$AZ$3*($C$13-ABERTURAS!$O$24)),0))+$AZ$39)/$AZ$38 -> 0.86484248 | EF3: =((IF(AND(ABERTURAS!$K$24="OK",ABERTURAS!$E$24="FIJA"),ABERTURAS!$Q$24+CHOOSE(ABERTURAS!$N$24,$AZ$4*$C$13,0,$AZ$4*($C$13-ABERTURAS!$O$24),$AZ$4*($C$13-ABERTURAS!$O$24)),0))+$AZ$40)/$AZ$38 -> 0.15864023 | EG3: =((IF(AND(ABERTURAS!$K$24="OK",ABERTURAS!$E$24="OPERABLE"),CHOOSE(ABERTURAS!$N$24,ABERTURAS!$O$24-$AZ$3*$C$13,ABERTURAS!$O$24,-$AZ$3*($C$13-ABERTURAS!$O$24),$C$12-$AZ$3*($C$13-ABERTURAS!$O$24)),0))+$AZ$39)/$AZ$38 -> 0.86484248 | EH3: =((IF(AND(ABERTURAS!$K$24="OK",ABERTURAS!$E$24="OPERABLE"),ABERTURAS!$Q$24+CHOOSE(ABERTURAS!$N$24,$AZ$4*$C$13,0,$AZ$4*($C$13-ABERTURAS!$O$24),$AZ$4*($C$13-ABERTURAS!$O$24)),0))+$AZ$40)/$AZ$38 -> 0.15864023 | EI3: =((IF(AND(ABERTURAS!$K$25="OK",ABERTURAS!$E$25="FIJA"),CHOOSE(ABERTURAS!$N$25,ABERTURAS!$O$25-$AZ$3*$C$13,ABERTURAS!$O$25,-$AZ$3*($C$13-ABERTURAS!$O$25),$C$12-$AZ$3*($C$13-ABERTURAS!$O$25)),0))+$AZ$39)/$AZ$38 -> 0.86484248 | EJ3: =((IF(AND(ABERTURAS!$K$25="OK",ABERTURAS!$E$25="FIJA"),ABERTURAS!$Q$25+CHOOSE(ABERTURAS!$N$25,$AZ$4*$C$13,0,$AZ$4*($C$13-ABERTURAS!$O$25),$AZ$4*($C$13-ABERTURAS!$O$25)),0))+$AZ$40)/$AZ$38 -> 0.15864023 | EK3: =((IF(AND(ABERTURAS!$K$25="OK",ABERTURAS!$E$25="OPERABLE"),CHOOSE(ABERTURAS!$N$25,ABERTURAS!$O$25-$AZ$3*$C$13,ABERTURAS!$O$25,-$AZ$3*($C$13-ABERTURAS!$O$25),$C$12-$AZ$3*($C$13-ABERTURAS!$O$25)),0))+$AZ$39)/$AZ$38 -> 0.86484248 | EL3: =((IF(AND(ABERTURAS!$K$25="OK",ABERTURAS!$E$25="OPERABLE"),ABERTURAS!$Q$25+CHOOSE(ABERTURAS!$N$25,$AZ$4*$C$13,0,$AZ$4*($C$13-ABERTURAS!$O$25),$AZ$4*($C$13-ABERTURAS!$O$25)),0))+$AZ$40)/$AZ$38 -> 0.15864023 | EM3: =((IF(AND(ABERTURAS!$K$26="OK",ABERTURAS!$E$26="FIJA"),CHOOSE(ABERTURAS!$N$26,ABERTURAS!$O$26-$AZ$3*$C$13,ABERTURAS!$O$26,-$AZ$3*($C$13-ABERTURAS!$O$26),$C$12-$AZ$3*($C$13-ABERTURAS!$O$26)),0))+$AZ$39)/$AZ$38 -> 0.86484248 | EN3: =((IF(AND(ABERTURAS!$K$26="OK",ABERTURAS!$E$26="FIJA"),ABERTURAS!$Q$26+CHOOSE(ABERTURAS!$N$26,$AZ$4*$C$13,0,$AZ$4*($C$13-ABERTURAS!$O$26),$AZ$4*($C$13-ABERTURAS!$O$26)),0))+$AZ$40)/$AZ$38 -> 0.15864023 | EO3: =((IF(AND(ABERTURAS!$K$26="OK",ABERTURAS!$E$26="OPERABLE"),CHOOSE(ABERTURAS!$N$26,ABERTURAS!$O$26-$AZ$3*$C$13,ABERTURAS!$O$26,-$AZ$3*($C$13-ABERTURAS!$O$26),$C$12-$AZ$3*($C$13-ABERTURAS!$O$26)),0))+$AZ$39)/$AZ$38 -> 0.86484248 | EP3: =((IF(AND(ABERTURAS!$K$26="OK",ABERTURAS!$E$26="OPERABLE"),ABERTURAS!$Q$26+CHOOSE(ABERTURAS!$N$26,$AZ$4*$C$13,0,$AZ$4*($C$13-ABERTURAS!$O$26),$AZ$4*($C$13-ABERTURAS!$O$26)),0))+$AZ$40)/$AZ$38 -> 0.15864023
AA4: =$C$23*1/8 -> 2 | AB4: =IF($C$14="PLANO",$C$17,IF($C$14="DOS AGUAS",$C$17+($C$18-$C$17)*(1-ABS(2*($AA$4)/$C$23-1)),IF($C$14="UN AGUA",IF(N($C$25)=0,$C$18-($C$18-$C$17)*($AA$4)/$C$23,$C$17+($C$18-$C$17)*($AA$4)/$C$23),$C$17+4*($C$18-$C$17)*($AA$4)/$C$23*(1-($AA$4)/$C$23)))) -> 10.52 | AE4: =ABERTURAS!$D$51 -> 10.08 | AF4: =0 -> 0 | AG4: =((($AZ$5+$AE4*($C$12-2*$AZ$5)/$C$12)-$AZ$3*$C$13)+$AZ$39)/$AZ$38 -> 1.0083741 | AH4: =((IF($AF4>0,$AF4-$AZ$5,0)+$AZ$4*$C$13)+$AZ$40)/$AZ$38 -> 0.35505194 | AI4: =ABERTURAS!$D$52 -> 10.08 | AJ4: =0 -> 0 | AK4: =((($AZ$5+$AI4*($C$12-2*$AZ$5)/$C$12))+$AZ$39)/$AZ$38 -> 1.3256546 | AL4: =((IF($AJ4>0,$AJ4-$AZ$5,0))+$AZ$40)/$AZ$38 -> 0.15864023 | AM4: =ABERTURAS!$D$53 -> 16 | AN4: =0 -> 0 | AO4: =((-$AZ$3*($C$13-($AZ$5+$AM4*($C$13-2*$AZ$5)/$C$13)))+$AZ$39)/$AZ$38 -> 0.85849687 | AP4: =((IF($AN4>0,$AN4-$AZ$5,0)+$AZ$4*($C$13-($AZ$5+$AM4*($C$13-2*$AZ$5)/$C$13)))+$AZ$40)/$AZ$38 -> 0.16256846 | AQ4: =ABERTURAS!$D$54 -> 16 | AR4: =0 -> 0 | AS4: =(($C$12-$AZ$3*($C$13-($AZ$5+$AQ4*($C$13-2*$AZ$5)/$C$13)))+$AZ$39)/$AZ$38 -> 1.3344175 | AT4: =((IF($AR4>0,$AR4-$AZ$5,0)+$AZ$4*($C$13-($AZ$5+$AQ4*($C$13-2*$AZ$5)/$C$13)))+$AZ$40)/$AZ$38 -> 0.16256846 | AU4: =((IF($AC$3="Z",0,$AA$4)-$AZ$3*($C$13-IF($AC$3="Z",$AA$4,0)))+$AZ$39)/$AZ$38 -> 0.58722208 | AV4: =(($AB$4+$AZ$4*($C$13-IF($AC$3="Z",$AA$4,0)))+$AZ$40)/$AZ$38 -> 0.82719547 | AY4: ky | AZ4: =0.26 -> 0.26 | BA4: =(($AZ$15)+$AZ$39)/$AZ$38 -> 0.78552236 | BB4: =(($AZ$16)+$AZ$40)/$AZ$38 -> 0.84135977 | BC4: =(($AZ$19)+$AZ$39)/$AZ$38 -> 1.1028028 | BD4: =(($AZ$20)+$AZ$40)/$AZ$38 -> 0.15864023 | BE4: =(($AZ$23)+$AZ$39)/$AZ$38 -> 0.70620225 | BF4: =(($AZ$24)+$AZ$40)/$AZ$38 -> 0.25684608 | BG4: =(($AZ$27)+$AZ$39)/$AZ$38 -> 1.1821229 | BH4: =(($AZ$28)+$AZ$40)/$AZ$38 -> 0.72426818 | BI4: =(($AZ$31+$AZ$12)+$AZ$39)/$AZ$38 -> 1.5707915 | BJ4: =(($AZ$32)+$AZ$40)/$AZ$38 -> 0.23796034 | BK4: =(($AZ$31)+$AZ$39)/$AZ$38 -> 1.4994034 | BL4: =(($AZ$32+$AZ$12)+$AZ$40)/$AZ$38 -> 0.30934844 | BM4: =(($AZ$31+$AZ$12*$AZ$3/SQRT($AZ$3^2+$AZ$4^2))+$AZ$39)/$AZ$38 -> 1.5601022 | BN4: =(($AZ$32-$AZ$12*$AZ$4/SQRT($AZ$3^2+$AZ$4^2))+$AZ$40)/$AZ$38 -> 0.20038488 | BO4: =((IF(AND(ABERTURAS!$K$7="OK",ABERTURAS!$E$7="FIJA"),CHOOSE(ABERTURAS!$N$7,ABERTURAS!$P$7-$AZ$3*$C$13,ABERTURAS!$P$7,-$AZ$3*($C$13-ABERTURAS!$P$7),$C$12-$AZ$3*($C$13-ABERTURAS!$P$7)),0))+$AZ$39)/$AZ$38 -> 0.86484248 | BP4: =((IF(AND(ABERTURAS!$K$7="OK",ABERTURAS!$E$7="FIJA"),ABERTURAS!$Q$7+CHOOSE(ABERTURAS!$N$7,$AZ$4*$C$13,0,$AZ$4*($C$13-ABERTURAS!$P$7),$AZ$4*($C$13-ABERTURAS!$P$7)),0))+$AZ$40)/$AZ$38 -> 0.15864023 | BQ4: =((IF(AND(ABERTURAS!$K$7="OK",ABERTURAS!$E$7="OPERABLE"),CHOOSE(ABERTURAS!$N$7,ABERTURAS!$P$7-$AZ$3*$C$13,ABERTURAS!$P$7,-$AZ$3*($C$13-ABERTURAS!$P$7),$C$12-$AZ$3*($C$13-ABERTURAS!$P$7)),0))+$AZ$39)/$AZ$38 -> 0.639342 | BR4: =((IF(AND(ABERTURAS!$K$7="OK",ABERTURAS!$E$7="OPERABLE"),ABERTURAS!$Q$7+CHOOSE(ABERTURAS!$N$7,$AZ$4*$C$13,0,$AZ$4*($C$13-ABERTURAS!$P$7),$AZ$4*($C$13-ABERTURAS!$P$7)),0))+$AZ$40)/$AZ$38 -> 0.35505194 | BS4: =((IF(AND(ABERTURAS!$K$8="OK",ABERTURAS!$E$8="FIJA"),CHOOSE(ABERTURAS!$N$8,ABERTURAS!$P$8-$AZ$3*$C$13,ABERTURAS!$P$8,-$AZ$3*($C$13-ABERTURAS!$P$8),$C$12-$AZ$3*($C$13-ABERTURAS!$P$8)),0))+$AZ$39)/$AZ$38 -> 0.86484248 | BT4: =((IF(AND(ABERTURAS!$K$8="OK",ABERTURAS!$E$8="FIJA"),ABERTURAS!$Q$8+CHOOSE(ABERTURAS!$N$8,$AZ$4*$C$13,0,$AZ$4*($C$13-ABERTURAS!$P$8),$AZ$4*($C$13-ABERTURAS!$P$8)),0))+$AZ$40)/$AZ$38 -> 0.15864023 | BU4: =((IF(AND(ABERTURAS!$K$8="OK",ABERTURAS!$E$8="OPERABLE"),CHOOSE(ABERTURAS!$N$8,ABERTURAS!$P$8-$AZ$3*$C$13,ABERTURAS!$P$8,-$AZ$3*($C$13-ABERTURAS!$P$8),$C$12-$AZ$3*($C$13-ABERTURAS!$P$8)),0))+$AZ$39)/$AZ$38 -> 0.90584814 | BV4: =((IF(AND(ABERTURAS!$K$8="OK",ABERTURAS!$E$8="OPERABLE"),ABERTURAS!$Q$8+CHOOSE(ABERTURAS!$N$8,$AZ$4*$C$13,0,$AZ$4*($C$13-ABERTURAS!$P$8),$AZ$4*($C$13-ABERTURAS!$P$8)),0))+$AZ$40)/$AZ$38 -> 0.35505194 | BW4: =((IF(AND(ABERTURAS!$K$9="OK",ABERTURAS!$E$9="FIJA"),CHOOSE(ABERTURAS!$N$9,ABERTURAS!$P$9-$AZ$3*$C$13,ABERTURAS!$P$9,-$AZ$3*($C$13-ABERTURAS!$P$9),$C$12-$AZ$3*($C$13-ABERTURAS!$P$9)),0))+$AZ$39)/$AZ$38 -> 1.3407632 | BX4: =((IF(AND(ABERTURAS!$K$9="OK",ABERTURAS!$E$9="FIJA"),ABERTURAS!$Q$9+CHOOSE(ABERTURAS!$N$9,$AZ$4*$C$13,0,$AZ$4*($C$13-ABERTURAS!$P$9),$AZ$4*($C$13-ABERTURAS!$P$9)),0))+$AZ$40)/$AZ$38 -> 0.15864023 | BY4: =((IF(AND(ABERTURAS!$K$9="OK",ABERTURAS!$E$9="OPERABLE"),CHOOSE(ABERTURAS!$N$9,ABERTURAS!$P$9-$AZ$3*$C$13,ABERTURAS!$P$9,-$AZ$3*($C$13-ABERTURAS!$P$9),$C$12-$AZ$3*($C$13-ABERTURAS!$P$9)),0))+$AZ$39)/$AZ$38 -> 0.86484248 | BZ4: =((IF(AND(ABERTURAS!$K$9="OK",ABERTURAS!$E$9="OPERABLE"),ABERTURAS!$Q$9+CHOOSE(ABERTURAS!$N$9,$AZ$4*$C$13,0,$AZ$4*($C$13-ABERTURAS!$P$9),$AZ$4*($C$13-ABERTURAS!$P$9)),0))+$AZ$40)/$AZ$38 -> 0.15864023 | CA4: =((IF(AND(ABERTURAS!$K$10="OK",ABERTURAS!$E$10="FIJA"),CHOOSE(ABERTURAS!$N$10,ABERTURAS!$P$10-$AZ$3*$C$13,ABERTURAS!$P$10,-$AZ$3*($C$13-ABERTURAS!$P$10),$C$12-$AZ$3*($C$13-ABERTURAS!$P$10)),0))+$AZ$39)/$AZ$38 -> 0.86484248 | CB4: =((IF(AND(ABERTURAS!$K$10="OK",ABERTURAS!$E$10="FIJA"),ABERTURAS!$Q$10+CHOOSE(ABERTURAS!$N$10,$AZ$4*$C$13,0,$AZ$4*($C$13-ABERTURAS!$P$10),$AZ$4*($C$13-ABERTURAS!$P$10)),0))+$AZ$40)/$AZ$38 -> 0.15864023 | CC4: =((IF(AND(ABERTURAS!$K$10="OK",ABERTURAS!$E$10="OPERABLE"),CHOOSE(ABERTURAS!$N$10,ABERTURAS!$P$10-$AZ$3*$C$13,ABERTURAS!$P$10,-$AZ$3*($C$13-ABERTURAS!$P$10),$C$12-$AZ$3*($C$13-ABERTURAS!$P$10)),0))+$AZ$39)/$AZ$38 -> 0.86484248 | CD4: =((IF(AND(ABERTURAS!$K$10="OK",ABERTURAS!$E$10="OPERABLE"),ABERTURAS!$Q$10+CHOOSE(ABERTURAS!$N$10,$AZ$4*$C$13,0,$AZ$4*($C$13-ABERTURAS!$P$10),$AZ$4*($C$13-ABERTURAS!$P$10)),0))+$AZ$40)/$AZ$38 -> 0.15864023 | CE4: =((IF(AND(ABERTURAS!$K$11="OK",ABERTURAS!$E$11="FIJA"),CHOOSE(ABERTURAS!$N$11,ABERTURAS!$P$11-$AZ$3*$C$13,ABERTURAS!$P$11,-$AZ$3*($C$13-ABERTURAS!$P$11),$C$12-$AZ$3*($C$13-ABERTURAS!$P$11)),0))+$AZ$39)/$AZ$38 -> 0.86484248 | CF4: =((IF(AND(ABERTURAS!$K$11="OK",ABERTURAS!$E$11="FIJA"),ABERTURAS!$Q$11+CHOOSE(ABERTURAS!$N$11,$AZ$4*$C$13,0,$AZ$4*($C$13-ABERTURAS!$P$11),$AZ$4*($C$13-ABERTURAS!$P$11)),0))+$AZ$40)/$AZ$38 -> 0.15864023 | CG4: =((IF(AND(ABERTURAS!$K$11="OK",ABERTURAS!$E$11="OPERABLE"),CHOOSE(ABERTURAS!$N$11,ABERTURAS!$P$11-$AZ$3*$C$13,ABERTURAS!$P$11,-$AZ$3*($C$13-ABERTURAS!$P$11),$C$12-$AZ$3*($C$13-ABERTURAS!$P$11)),0))+$AZ$39)/$AZ$38 -> 0.86484248 | CH4: =((IF(AND(ABERTURAS!$K$11="OK",ABERTURAS!$E$11="OPERABLE"),ABERTURAS!$Q$11+CHOOSE(ABERTURAS!$N$11,$AZ$4*$C$13,0,$AZ$4*($C$13-ABERTURAS!$P$11),$AZ$4*($C$13-ABERTURAS!$P$11)),0))+$AZ$40)/$AZ$38 -> 0.15864023 | CI4: =((IF(AND(ABERTURAS!$K$12="OK",ABERTURAS!$E$12="FIJA"),CHOOSE(ABERTURAS!$N$12,ABERTURAS!$P$12-$AZ$3*$C$13,ABERTURAS!$P$12,-$AZ$3*($C$13-ABERTURAS!$P$12),$C$12-$AZ$3*($C$13-ABERTURAS!$P$12)),0))+$AZ$39)/$AZ$38 -> 0.86484248 | CJ4: =((IF(AND(ABERTURAS!$K$12="OK",ABERTURAS!$E$12="FIJA"),ABERTURAS!$Q$12+CHOOSE(ABERTURAS!$N$12,$AZ$4*$C$13,0,$AZ$4*($C$13-ABERTURAS!$P$12),$AZ$4*($C$13-ABERTURAS!$P$12)),0))+$AZ$40)/$AZ$38 -> 0.15864023 | CK4: =((IF(AND(ABERTURAS!$K$12="OK",ABERTURAS!$E$12="OPERABLE"),CHOOSE(ABERTURAS!$N$12,ABERTURAS!$P$12-$AZ$3*$C$13,ABERTURAS!$P$12,-$AZ$3*($C$13-ABERTURAS!$P$12),$C$12-$AZ$3*($C$13-ABERTURAS!$P$12)),0))+$AZ$39)/$AZ$38 -> 0.86484248 | CL4: =((IF(AND(ABERTURAS!$K$12="OK",ABERTURAS!$E$12="OPERABLE"),ABERTURAS!$Q$12+CHOOSE(ABERTURAS!$N$12,$AZ$4*$C$13,0,$AZ$4*($C$13-ABERTURAS!$P$12),$AZ$4*($C$13-ABERTURAS!$P$12)),0))+$AZ$40)/$AZ$38 -> 0.15864023 | CM4: =((IF(AND(ABERTURAS!$K$13="OK",ABERTURAS!$E$13="FIJA"),CHOOSE(ABERTURAS!$N$13,ABERTURAS!$P$13-$AZ$3*$C$13,ABERTURAS!$P$13,-$AZ$3*($C$13-ABERTURAS!$P$13),$C$12-$AZ$3*($C$13-ABERTURAS!$P$13)),0))+$AZ$39)/$AZ$38 -> 0.86484248 | CN4: =((IF(AND(ABERTURAS!$K$13="OK",ABERTURAS!$E$13="FIJA"),ABERTURAS!$Q$13+CHOOSE(ABERTURAS!$N$13,$AZ$4*$C$13,0,$AZ$4*($C$13-ABERTURAS!$P$13),$AZ$4*($C$13-ABERTURAS!$P$13)),0))+$AZ$40)/$AZ$38 -> 0.15864023 | CO4: =((IF(AND(ABERTURAS!$K$13="OK",ABERTURAS!$E$13="OPERABLE"),CHOOSE(ABERTURAS!$N$13,ABERTURAS!$P$13-$AZ$3*$C$13,ABERTURAS!$P$13,-$AZ$3*($C$13-ABERTURAS!$P$13),$C$12-$AZ$3*($C$13-ABERTURAS!$P$13)),0))+$AZ$39)/$AZ$38 -> 0.86484248 | CP4: =((IF(AND(ABERTURAS!$K$13="OK",ABERTURAS!$E$13="OPERABLE"),ABERTURAS!$Q$13+CHOOSE(ABERTURAS!$N$13,$AZ$4*$C$13,0,$AZ$4*($C$13-ABERTURAS!$P$13),$AZ$4*($C$13-ABERTURAS!$P$13)),0))+$AZ$40)/$AZ$38 -> 0.15864023 | CQ4: =((IF(AND(ABERTURAS!$K$14="OK",ABERTURAS!$E$14="FIJA"),CHOOSE(ABERTURAS!$N$14,ABERTURAS!$P$14-$AZ$3*$C$13,ABERTURAS!$P$14,-$AZ$3*($C$13-ABERTURAS!$P$14),$C$12-$AZ$3*($C$13-ABERTURAS!$P$14)),0))+$AZ$39)/$AZ$38 -> 0.86484248 | CR4: =((IF(AND(ABERTURAS!$K$14="OK",ABERTURAS!$E$14="FIJA"),ABERTURAS!$Q$14+CHOOSE(ABERTURAS!$N$14,$AZ$4*$C$13,0,$AZ$4*($C$13-ABERTURAS!$P$14),$AZ$4*($C$13-ABERTURAS!$P$14)),0))+$AZ$40)/$AZ$38 -> 0.15864023 | CS4: =((IF(AND(ABERTURAS!$K$14="OK",ABERTURAS!$E$14="OPERABLE"),CHOOSE(ABERTURAS!$N$14,ABERTURAS!$P$14-$AZ$3*$C$13,ABERTURAS!$P$14,-$AZ$3*($C$13-ABERTURAS!$P$14),$C$12-$AZ$3*($C$13-ABERTURAS!$P$14)),0))+$AZ$39)/$AZ$38 -> 0.86484248 | CT4: =((IF(AND(ABERTURAS!$K$14="OK",ABERTURAS!$E$14="OPERABLE"),ABERTURAS!$Q$14+CHOOSE(ABERTURAS!$N$14,$AZ$4*$C$13,0,$AZ$4*($C$13-ABERTURAS!$P$14),$AZ$4*($C$13-ABERTURAS!$P$14)),0))+$AZ$40)/$AZ$38 -> 0.15864023 | CU4: =((IF(AND(ABERTURAS!$K$15="OK",ABERTURAS!$E$15="FIJA"),CHOOSE(ABERTURAS!$N$15,ABERTURAS!$P$15-$AZ$3*$C$13,ABERTURAS!$P$15,-$AZ$3*($C$13-ABERTURAS!$P$15),$C$12-$AZ$3*($C$13-ABERTURAS!$P$15)),0))+$AZ$39)/$AZ$38 -> 0.86484248 | CV4: =((IF(AND(ABERTURAS!$K$15="OK",ABERTURAS!$E$15="FIJA"),ABERTURAS!$Q$15+CHOOSE(ABERTURAS!$N$15,$AZ$4*$C$13,0,$AZ$4*($C$13-ABERTURAS!$P$15),$AZ$4*($C$13-ABERTURAS!$P$15)),0))+$AZ$40)/$AZ$38 -> 0.15864023 | CW4: =((IF(AND(ABERTURAS!$K$15="OK",ABERTURAS!$E$15="OPERABLE"),CHOOSE(ABERTURAS!$N$15,ABERTURAS!$P$15-$AZ$3*$C$13,ABERTURAS!$P$15,-$AZ$3*($C$13-ABERTURAS!$P$15),$C$12-$AZ$3*($C$13-ABERTURAS!$P$15)),0))+$AZ$39)/$AZ$38 -> 0.86484248 | CX4: =((IF(AND(ABERTURAS!$K$15="OK",ABERTURAS!$E$15="OPERABLE"),ABERTURAS!$Q$15+CHOOSE(ABERTURAS!$N$15,$AZ$4*$C$13,0,$AZ$4*($C$13-ABERTURAS!$P$15),$AZ$4*($C$13-ABERTURAS!$P$15)),0))+$AZ$40)/$AZ$38 -> 0.15864023 | CY4: =((IF(AND(ABERTURAS!$K$16="OK",ABERTURAS!$E$16="FIJA"),CHOOSE(ABERTURAS!$N$16,ABERTURAS!$P$16-$AZ$3*$C$13,ABERTURAS!$P$16,-$AZ$3*($C$13-ABERTURAS!$P$16),$C$12-$AZ$3*($C$13-ABERTURAS!$P$16)),0))+$AZ$39)/$AZ$38 -> 0.86484248 | CZ4: =((IF(AND(ABERTURAS!$K$16="OK",ABERTURAS!$E$16="FIJA"),ABERTURAS!$Q$16+CHOOSE(ABERTURAS!$N$16,$AZ$4*$C$13,0,$AZ$4*($C$13-ABERTURAS!$P$16),$AZ$4*($C$13-ABERTURAS!$P$16)),0))+$AZ$40)/$AZ$38 -> 0.15864023 | DA4: =((IF(AND(ABERTURAS!$K$16="OK",ABERTURAS!$E$16="OPERABLE"),CHOOSE(ABERTURAS!$N$16,ABERTURAS!$P$16-$AZ$3*$C$13,ABERTURAS!$P$16,-$AZ$3*($C$13-ABERTURAS!$P$16),$C$12-$AZ$3*($C$13-ABERTURAS!$P$16)),0))+$AZ$39)/$AZ$38 -> 0.86484248 | DB4: =((IF(AND(ABERTURAS!$K$16="OK",ABERTURAS!$E$16="OPERABLE"),ABERTURAS!$Q$16+CHOOSE(ABERTURAS!$N$16,$AZ$4*$C$13,0,$AZ$4*($C$13-ABERTURAS!$P$16),$AZ$4*($C$13-ABERTURAS!$P$16)),0))+$AZ$40)/$AZ$38 -> 0.15864023 | DC4: =((IF(AND(ABERTURAS!$K$17="OK",ABERTURAS!$E$17="FIJA"),CHOOSE(ABERTURAS!$N$17,ABERTURAS!$P$17-$AZ$3*$C$13,ABERTURAS!$P$17,-$AZ$3*($C$13-ABERTURAS!$P$17),$C$12-$AZ$3*($C$13-ABERTURAS!$P$17)),0))+$AZ$39)/$AZ$38 -> 0.86484248 | DD4: =((IF(AND(ABERTURAS!$K$17="OK",ABERTURAS!$E$17="FIJA"),ABERTURAS!$Q$17+CHOOSE(ABERTURAS!$N$17,$AZ$4*$C$13,0,$AZ$4*($C$13-ABERTURAS!$P$17),$AZ$4*($C$13-ABERTURAS!$P$17)),0))+$AZ$40)/$AZ$38 -> 0.15864023 | DE4: =((IF(AND(ABERTURAS!$K$17="OK",ABERTURAS!$E$17="OPERABLE"),CHOOSE(ABERTURAS!$N$17,ABERTURAS!$P$17-$AZ$3*$C$13,ABERTURAS!$P$17,-$AZ$3*($C$13-ABERTURAS!$P$17),$C$12-$AZ$3*($C$13-ABERTURAS!$P$17)),0))+$AZ$39)/$AZ$38 -> 0.86484248 | DF4: =((IF(AND(ABERTURAS!$K$17="OK",ABERTURAS!$E$17="OPERABLE"),ABERTURAS!$Q$17+CHOOSE(ABERTURAS!$N$17,$AZ$4*$C$13,0,$AZ$4*($C$13-ABERTURAS!$P$17),$AZ$4*($C$13-ABERTURAS!$P$17)),0))+$AZ$40)/$AZ$38 -> 0.15864023 | DG4: =((IF(AND(ABERTURAS!$K$18="OK",ABERTURAS!$E$18="FIJA"),CHOOSE(ABERTURAS!$N$18,ABERTURAS!$P$18-$AZ$3*$C$13,ABERTURAS!$P$18,-$AZ$3*($C$13-ABERTURAS!$P$18),$C$12-$AZ$3*($C$13-ABERTURAS!$P$18)),0))+$AZ$39)/$AZ$38 -> 0.86484248 | DH4: =((IF(AND(ABERTURAS!$K$18="OK",ABERTURAS!$E$18="FIJA"),ABERTURAS!$Q$18+CHOOSE(ABERTURAS!$N$18,$AZ$4*$C$13,0,$AZ$4*($C$13-ABERTURAS!$P$18),$AZ$4*($C$13-ABERTURAS!$P$18)),0))+$AZ$40)/$AZ$38 -> 0.15864023 | DI4: =((IF(AND(ABERTURAS!$K$18="OK",ABERTURAS!$E$18="OPERABLE"),CHOOSE(ABERTURAS!$N$18,ABERTURAS!$P$18-$AZ$3*$C$13,ABERTURAS!$P$18,-$AZ$3*($C$13-ABERTURAS!$P$18),$C$12-$AZ$3*($C$13-ABERTURAS!$P$18)),0))+$AZ$39)/$AZ$38 -> 0.86484248 | DJ4: =((IF(AND(ABERTURAS!$K$18="OK",ABERTURAS!$E$18="OPERABLE"),ABERTURAS!$Q$18+CHOOSE(ABERTURAS!$N$18,$AZ$4*$C$13,0,$AZ$4*($C$13-ABERTURAS!$P$18),$AZ$4*($C$13-ABERTURAS!$P$18)),0))+$AZ$40)/$AZ$38 -> 0.15864023 | DK4: =((IF(AND(ABERTURAS!$K$19="OK",ABERTURAS!$E$19="FIJA"),CHOOSE(ABERTURAS!$N$19,ABERTURAS!$P$19-$AZ$3*$C$13,ABERTURAS!$P$19,-$AZ$3*($C$13-ABERTURAS!$P$19),$C$12-$AZ$3*($C$13-ABERTURAS!$P$19)),0))+$AZ$39)/$AZ$38 -> 0.86484248 | DL4: =((IF(AND(ABERTURAS!$K$19="OK",ABERTURAS!$E$19="FIJA"),ABERTURAS!$Q$19+CHOOSE(ABERTURAS!$N$19,$AZ$4*$C$13,0,$AZ$4*($C$13-ABERTURAS!$P$19),$AZ$4*($C$13-ABERTURAS!$P$19)),0))+$AZ$40)/$AZ$38 -> 0.15864023 | DM4: =((IF(AND(ABERTURAS!$K$19="OK",ABERTURAS!$E$19="OPERABLE"),CHOOSE(ABERTURAS!$N$19,ABERTURAS!$P$19-$AZ$3*$C$13,ABERTURAS!$P$19,-$AZ$3*($C$13-ABERTURAS!$P$19),$C$12-$AZ$3*($C$13-ABERTURAS!$P$19)),0))+$AZ$39)/$AZ$38 -> 0.86484248 | DN4: =((IF(AND(ABERTURAS!$K$19="OK",ABERTURAS!$E$19="OPERABLE"),ABERTURAS!$Q$19+CHOOSE(ABERTURAS!$N$19,$AZ$4*$C$13,0,$AZ$4*($C$13-ABERTURAS!$P$19),$AZ$4*($C$13-ABERTURAS!$P$19)),0))+$AZ$40)/$AZ$38 -> 0.15864023 | DO4: =((IF(AND(ABERTURAS!$K$20="OK",ABERTURAS!$E$20="FIJA"),CHOOSE(ABERTURAS!$N$20,ABERTURAS!$P$20-$AZ$3*$C$13,ABERTURAS!$P$20,-$AZ$3*($C$13-ABERTURAS!$P$20),$C$12-$AZ$3*($C$13-ABERTURAS!$P$20)),0))+$AZ$39)/$AZ$38 -> 0.86484248 | DP4: =((IF(AND(ABERTURAS!$K$20="OK",ABERTURAS!$E$20="FIJA"),ABERTURAS!$Q$20+CHOOSE(ABERTURAS!$N$20,$AZ$4*$C$13,0,$AZ$4*($C$13-ABERTURAS!$P$20),$AZ$4*($C$13-ABERTURAS!$P$20)),0))+$AZ$40)/$AZ$38 -> 0.15864023 | DQ4: =((IF(AND(ABERTURAS!$K$20="OK",ABERTURAS!$E$20="OPERABLE"),CHOOSE(ABERTURAS!$N$20,ABERTURAS!$P$20-$AZ$3*$C$13,ABERTURAS!$P$20,-$AZ$3*($C$13-ABERTURAS!$P$20),$C$12-$AZ$3*($C$13-ABERTURAS!$P$20)),0))+$AZ$39)/$AZ$38 -> 0.86484248 | DR4: =((IF(AND(ABERTURAS!$K$20="OK",ABERTURAS!$E$20="OPERABLE"),ABERTURAS!$Q$20+CHOOSE(ABERTURAS!$N$20,$AZ$4*$C$13,0,$AZ$4*($C$13-ABERTURAS!$P$20),$AZ$4*($C$13-ABERTURAS!$P$20)),0))+$AZ$40)/$AZ$38 -> 0.15864023 | DS4: =((IF(AND(ABERTURAS!$K$21="OK",ABERTURAS!$E$21="FIJA"),CHOOSE(ABERTURAS!$N$21,ABERTURAS!$P$21-$AZ$3*$C$13,ABERTURAS!$P$21,-$AZ$3*($C$13-ABERTURAS!$P$21),$C$12-$AZ$3*($C$13-ABERTURAS!$P$21)),0))+$AZ$39)/$AZ$38 -> 0.86484248 | DT4: =((IF(AND(ABERTURAS!$K$21="OK",ABERTURAS!$E$21="FIJA"),ABERTURAS!$Q$21+CHOOSE(ABERTURAS!$N$21,$AZ$4*$C$13,0,$AZ$4*($C$13-ABERTURAS!$P$21),$AZ$4*($C$13-ABERTURAS!$P$21)),0))+$AZ$40)/$AZ$38 -> 0.15864023 | DU4: =((IF(AND(ABERTURAS!$K$21="OK",ABERTURAS!$E$21="OPERABLE"),CHOOSE(ABERTURAS!$N$21,ABERTURAS!$P$21-$AZ$3*$C$13,ABERTURAS!$P$21,-$AZ$3*($C$13-ABERTURAS!$P$21),$C$12-$AZ$3*($C$13-ABERTURAS!$P$21)),0))+$AZ$39)/$AZ$38 -> 0.86484248 | DV4: =((IF(AND(ABERTURAS!$K$21="OK",ABERTURAS!$E$21="OPERABLE"),ABERTURAS!$Q$21+CHOOSE(ABERTURAS!$N$21,$AZ$4*$C$13,0,$AZ$4*($C$13-ABERTURAS!$P$21),$AZ$4*($C$13-ABERTURAS!$P$21)),0))+$AZ$40)/$AZ$38 -> 0.15864023 | DW4: =((IF(AND(ABERTURAS!$K$22="OK",ABERTURAS!$E$22="FIJA"),CHOOSE(ABERTURAS!$N$22,ABERTURAS!$P$22-$AZ$3*$C$13,ABERTURAS!$P$22,-$AZ$3*($C$13-ABERTURAS!$P$22),$C$12-$AZ$3*($C$13-ABERTURAS!$P$22)),0))+$AZ$39)/$AZ$38 -> 0.86484248 | DX4: =((IF(AND(ABERTURAS!$K$22="OK",ABERTURAS!$E$22="FIJA"),ABERTURAS!$Q$22+CHOOSE(ABERTURAS!$N$22,$AZ$4*$C$13,0,$AZ$4*($C$13-ABERTURAS!$P$22),$AZ$4*($C$13-ABERTURAS!$P$22)),0))+$AZ$40)/$AZ$38 -> 0.15864023 | DY4: =((IF(AND(ABERTURAS!$K$22="OK",ABERTURAS!$E$22="OPERABLE"),CHOOSE(ABERTURAS!$N$22,ABERTURAS!$P$22-$AZ$3*$C$13,ABERTURAS!$P$22,-$AZ$3*($C$13-ABERTURAS!$P$22),$C$12-$AZ$3*($C$13-ABERTURAS!$P$22)),0))+$AZ$39)/$AZ$38 -> 0.86484248 | DZ4: =((IF(AND(ABERTURAS!$K$22="OK",ABERTURAS!$E$22="OPERABLE"),ABERTURAS!$Q$22+CHOOSE(ABERTURAS!$N$22,$AZ$4*$C$13,0,$AZ$4*($C$13-ABERTURAS!$P$22),$AZ$4*($C$13-ABERTURAS!$P$22)),0))+$AZ$40)/$AZ$38 -> 0.15864023 | EA4: =((IF(AND(ABERTURAS!$K$23="OK",ABERTURAS!$E$23="FIJA"),CHOOSE(ABERTURAS!$N$23,ABERTURAS!$P$23-$AZ$3*$C$13,ABERTURAS!$P$23,-$AZ$3*($C$13-ABERTURAS!$P$23),$C$12-$AZ$3*($C$13-ABERTURAS!$P$23)),0))+$AZ$39)/$AZ$38 -> 0.86484248 | EB4: =((IF(AND(ABERTURAS!$K$23="OK",ABERTURAS!$E$23="FIJA"),ABERTURAS!$Q$23+CHOOSE(ABERTURAS!$N$23,$AZ$4*$C$13,0,$AZ$4*($C$13-ABERTURAS!$P$23),$AZ$4*($C$13-ABERTURAS!$P$23)),0))+$AZ$40)/$AZ$38 -> 0.15864023 | EC4: =((IF(AND(ABERTURAS!$K$23="OK",ABERTURAS!$E$23="OPERABLE"),CHOOSE(ABERTURAS!$N$23,ABERTURAS!$P$23-$AZ$3*$C$13,ABERTURAS!$P$23,-$AZ$3*($C$13-ABERTURAS!$P$23),$C$12-$AZ$3*($C$13-ABERTURAS!$P$23)),0))+$AZ$39)/$AZ$38 -> 0.86484248 | ED4: =((IF(AND(ABERTURAS!$K$23="OK",ABERTURAS!$E$23="OPERABLE"),ABERTURAS!$Q$23+CHOOSE(ABERTURAS!$N$23,$AZ$4*$C$13,0,$AZ$4*($C$13-ABERTURAS!$P$23),$AZ$4*($C$13-ABERTURAS!$P$23)),0))+$AZ$40)/$AZ$38 -> 0.15864023 | EE4: =((IF(AND(ABERTURAS!$K$24="OK",ABERTURAS!$E$24="FIJA"),CHOOSE(ABERTURAS!$N$24,ABERTURAS!$P$24-$AZ$3*$C$13,ABERTURAS!$P$24,-$AZ$3*($C$13-ABERTURAS!$P$24),$C$12-$AZ$3*($C$13-ABERTURAS!$P$24)),0))+$AZ$39)/$AZ$38 -> 0.86484248 | EF4: =((IF(AND(ABERTURAS!$K$24="OK",ABERTURAS!$E$24="FIJA"),ABERTURAS!$Q$24+CHOOSE(ABERTURAS!$N$24,$AZ$4*$C$13,0,$AZ$4*($C$13-ABERTURAS!$P$24),$AZ$4*($C$13-ABERTURAS!$P$24)),0))+$AZ$40)/$AZ$38 -> 0.15864023 | EG4: =((IF(AND(ABERTURAS!$K$24="OK",ABERTURAS!$E$24="OPERABLE"),CHOOSE(ABERTURAS!$N$24,ABERTURAS!$P$24-$AZ$3*$C$13,ABERTURAS!$P$24,-$AZ$3*($C$13-ABERTURAS!$P$24),$C$12-$AZ$3*($C$13-ABERTURAS!$P$24)),0))+$AZ$39)/$AZ$38 -> 0.86484248 | EH4: =((IF(AND(ABERTURAS!$K$24="OK",ABERTURAS!$E$24="OPERABLE"),ABERTURAS!$Q$24+CHOOSE(ABERTURAS!$N$24,$AZ$4*$C$13,0,$AZ$4*($C$13-ABERTURAS!$P$24),$AZ$4*($C$13-ABERTURAS!$P$24)),0))+$AZ$40)/$AZ$38 -> 0.15864023 | EI4: =((IF(AND(ABERTURAS!$K$25="OK",ABERTURAS!$E$25="FIJA"),CHOOSE(ABERTURAS!$N$25,ABERTURAS!$P$25-$AZ$3*$C$13,ABERTURAS!$P$25,-$AZ$3*($C$13-ABERTURAS!$P$25),$C$12-$AZ$3*($C$13-ABERTURAS!$P$25)),0))+$AZ$39)/$AZ$38 -> 0.86484248 | EJ4: =((IF(AND(ABERTURAS!$K$25="OK",ABERTURAS!$E$25="FIJA"),ABERTURAS!$Q$25+CHOOSE(ABERTURAS!$N$25,$AZ$4*$C$13,0,$AZ$4*($C$13-ABERTURAS!$P$25),$AZ$4*($C$13-ABERTURAS!$P$25)),0))+$AZ$40)/$AZ$38 -> 0.15864023 | EK4: =((IF(AND(ABERTURAS!$K$25="OK",ABERTURAS!$E$25="OPERABLE"),CHOOSE(ABERTURAS!$N$25,ABERTURAS!$P$25-$AZ$3*$C$13,ABERTURAS!$P$25,-$AZ$3*($C$13-ABERTURAS!$P$25),$C$12-$AZ$3*($C$13-ABERTURAS!$P$25)),0))+$AZ$39)/$AZ$38 -> 0.86484248 | EL4: =((IF(AND(ABERTURAS!$K$25="OK",ABERTURAS!$E$25="OPERABLE"),ABERTURAS!$Q$25+CHOOSE(ABERTURAS!$N$25,$AZ$4*$C$13,0,$AZ$4*($C$13-ABERTURAS!$P$25),$AZ$4*($C$13-ABERTURAS!$P$25)),0))+$AZ$40)/$AZ$38 -> 0.15864023 | EM4: =((IF(AND(ABERTURAS!$K$26="OK",ABERTURAS!$E$26="FIJA"),CHOOSE(ABERTURAS!$N$26,ABERTURAS!$P$26-$AZ$3*$C$13,ABERTURAS!$P$26,-$AZ$3*($C$13-ABERTURAS!$P$26),$C$12-$AZ$3*($C$13-ABERTURAS!$P$26)),0))+$AZ$39)/$AZ$38 -> 0.86484248 | EN4: =((IF(AND(ABERTURAS!$K$26="OK",ABERTURAS!$E$26="FIJA"),ABERTURAS!$Q$26+CHOOSE(ABERTURAS!$N$26,$AZ$4*$C$13,0,$AZ$4*($C$13-ABERTURAS!$P$26),$AZ$4*($C$13-ABERTURAS!$P$26)),0))+$AZ$40)/$AZ$38 -> 0.15864023 | EO4: =((IF(AND(ABERTURAS!$K$26="OK",ABERTURAS!$E$26="OPERABLE"),CHOOSE(ABERTURAS!$N$26,ABERTURAS!$P$26-$AZ$3*$C$13,ABERTURAS!$P$26,-$AZ$3*($C$13-ABERTURAS!$P$26),$C$12-$AZ$3*($C$13-ABERTURAS!$P$26)),0))+$AZ$39)/$AZ$38 -> 0.86484248 | EP4: =((IF(AND(ABERTURAS!$K$26="OK",ABERTURAS!$E$26="OPERABLE"),ABERTURAS!$Q$26+CHOOSE(ABERTURAS!$N$26,$AZ$4*$C$13,0,$AZ$4*($C$13-ABERTURAS!$P$26),$AZ$4*($C$13-ABERTURAS!$P$26)),0))+$AZ$40)/$AZ$38 -> 0.15864023
B5: 1. PROYECTO | AA5: =$C$23*2/8 -> 4 | AB5: =IF($C$14="PLANO",$C$17,IF($C$14="DOS AGUAS",$C$17+($C$18-$C$17)*(1-ABS(2*($AA$5)/$C$23-1)),IF($C$14="UN AGUA",IF(N($C$25)=0,$C$18-($C$18-$C$17)*($AA$5)/$C$23,$C$17+($C$18-$C$17)*($AA$5)/$C$23),$C$17+4*($C$18-$C$17)*($AA$5)/$C$23*(1-($AA$5)/$C$23)))) -> 10.42 | AE5: =ABERTURAS!$D$51*8/8 -> 10.08 | AF5: =IF(ABERTURAS!$E$51="SÍ",$AB$11,ABERTURAS!$F$51) -> 10.62 | AG5: =((($AZ$5+$AE5*($C$12-2*$AZ$5)/$C$12)-$AZ$3*$C$13)+$AZ$39)/$AZ$38 -> 1.0083741 | AH5: =((IF($AF5>0,$AF5-$AZ$5,0)+$AZ$4*$C$13)+$AZ$40)/$AZ$38 -> 0.84135977 | AI5: =ABERTURAS!$D$52*8/8 -> 10.08 | AJ5: =IF(ABERTURAS!$E$52="SÍ",$AB$11,ABERTURAS!$F$52) -> 9.82 | AK5: =((($AZ$5+$AI5*($C$12-2*$AZ$5)/$C$12))+$AZ$39)/$AZ$38 -> 1.3256546 | AL5: =((IF($AJ5>0,$AJ5-$AZ$5,0))+$AZ$40)/$AZ$38 -> 0.60717658 | AM5: =ABERTURAS!$D$53*8/8 -> 16 | AN5: =IF(ABERTURAS!$E$53="SÍ",$AB$11,ABERTURAS!$F$53) -> 9.82 | AO5: =((-$AZ$3*($C$13-($AZ$5+$AM5*($C$13-2*$AZ$5)/$C$13)))+$AZ$39)/$AZ$38 -> 0.85849687 | AP5: =((IF($AN5>0,$AN5-$AZ$5,0)+$AZ$4*($C$13-($AZ$5+$AM5*($C$13-2*$AZ$5)/$C$13)))+$AZ$40)/$AZ$38 -> 0.61110482 | AQ5: =ABERTURAS!$D$54*8/8 -> 16 | AR5: =IF(ABERTURAS!$E$54="SÍ",$AB$11,ABERTURAS!$F$54) -> 9.82 | AS5: =(($C$12-$AZ$3*($C$13-($AZ$5+$AQ5*($C$13-2*$AZ$5)/$C$13)))+$AZ$39)/$AZ$38 -> 1.3344175 | AT5: =((IF($AR5>0,$AR5-$AZ$5,0)+$AZ$4*($C$13-($AZ$5+$AQ5*($C$13-2*$AZ$5)/$C$13)))+$AZ$40)/$AZ$38 -> 0.61110482 | AU5: =((IF($AC$3="Z",0,$AA$5)-$AZ$3*($C$13-IF($AC$3="Z",$AA$5,0)))+$AZ$39)/$AZ$38 -> 0.62688214 | AV5: =(($AB$5+$AZ$4*($C$13-IF($AC$3="Z",$AA$5,0)))+$AZ$40)/$AZ$38 -> 0.79792257 | AY5: hueco entre muros | AZ5: =0.02*MAX($C$12,$C$13) -> 0.32 | BA5: =BA4-($AZ$11/$AZ$38)*((BA4-BA3)*$AZ$13-(BB4-BB3)*$AZ$14)/SQRT((BA4-BA3)^2+(BB4-BB3)^2) -> 0.77248887 | BB5: =BB4-($AZ$11/$AZ$38)*((BA4-BA3)*$AZ$14+(BB4-BB3)*$AZ$13)/SQRT((BA4-BA3)^2+(BB4-BB3)^2) -> 0.8658722 | BC5: =BC4-($AZ$11/$AZ$38)*((BC4-BC3)*$AZ$13-(BD4-BD3)*$AZ$14)/SQRT((BC4-BC3)^2+(BD4-BD3)^2) -> 1.1158363 | BD5: =BD4-($AZ$11/$AZ$38)*((BC4-BC3)*$AZ$14+(BD4-BD3)*$AZ$13)/SQRT((BC4-BC3)^2+(BD4-BD3)^2) -> 0.1341278 | BE5: =BE4-($AZ$11/$AZ$38)*((BE4-BE3)*$AZ$13-(BF4-BF3)*$AZ$14)/SQRT((BE4-BE3)^2+(BF4-BF3)^2) -> 0.69808541 | BF5: =BF4-($AZ$11/$AZ$38)*((BE4-BE3)*$AZ$14+(BF4-BF3)*$AZ$13)/SQRT((BE4-BE3)^2+(BF4-BF3)^2) -> 0.23029711 | BG5: =BG4-($AZ$11/$AZ$38)*((BG4-BG3)*$AZ$13-(BH4-BH3)*$AZ$14)/SQRT((BG4-BG3)^2+(BH4-BH3)^2) -> 1.1902398 | BH5: =BH4-($AZ$11/$AZ$38)*((BG4-BG3)*$AZ$14+(BH4-BH3)*$AZ$13)/SQRT((BG4-BG3)^2+(BH4-BH3)^2) -> 0.75081715 | BI5: =BI4-($AZ$11/$AZ$38)*((BI4-BI3)*$AZ$13-(BJ4-BJ3)*$AZ$14)/SQRT((BI4-BI3)^2+(BJ4-BJ3)^2) -> 1.5462791 | BJ5: =BJ4-($AZ$11/$AZ$38)*((BI4-BI3)*$AZ$14+(BJ4-BJ3)*$AZ$13)/SQRT((BI4-BI3)^2+(BJ4-BJ3)^2) -> 0.22492685 | BK5: =BK4-($AZ$11/$AZ$38)*((BK4-BK3)*$AZ$13-(BL4-BL3)*$AZ$14)/SQRT((BK4-BK3)^2+(BL4-BL3)^2) -> 1.5124369 | BL5: =BL4-($AZ$11/$AZ$38)*((BK4-BK3)*$AZ$14+(BL4-BL3)*$AZ$13)/SQRT((BK4-BK3)^2+(BL4-BL3)^2) -> 0.28483602 | BM5: =BM4-($AZ$11/$AZ$38)*((BM4-BM3)*$AZ$13-(BN4-BN3)*$AZ$14)/SQRT((BM4-BM3)^2+(BN4-BN3)^2) -> 1.5323999 | BN5: =BN4-($AZ$11/$AZ$38)*((BM4-BM3)*$AZ$14+(BN4-BN3)*$AZ$13)/SQRT((BM4-BM3)^2+(BN4-BN3)^2) -> 0.20220519 | BO5: =((IF(AND(ABERTURAS!$K$7="OK",ABERTURAS!$E$7="FIJA"),CHOOSE(ABERTURAS!$N$7,ABERTURAS!$P$7-$AZ$3*$C$13,ABERTURAS!$P$7,-$AZ$3*($C$13-ABERTURAS!$P$7),$C$12-$AZ$3*($C$13-ABERTURAS!$P$7)),0))+$AZ$39)/$AZ$38 -> 0.86484248 | BP5: =((IF(AND(ABERTURAS!$K$7="OK",ABERTURAS!$E$7="FIJA"),ABERTURAS!$R$7+CHOOSE(ABERTURAS!$N$7,$AZ$4*$C$13,0,$AZ$4*($C$13-ABERTURAS!$P$7),$AZ$4*($C$13-ABERTURAS!$P$7)),0))+$AZ$40)/$AZ$38 -> 0.15864023 | BQ5: =((IF(AND(ABERTURAS!$K$7="OK",ABERTURAS!$E$7="OPERABLE"),CHOOSE(ABERTURAS!$N$7,ABERTURAS!$P$7-$AZ$3*$C$13,ABERTURAS!$P$7,-$AZ$3*($C$13-ABERTURAS!$P$7),$C$12-$AZ$3*($C$13-ABERTURAS!$P$7)),0))+$AZ$39)/$AZ$38 -> 0.639342 | BR5: =((IF(AND(ABERTURAS!$K$7="OK",ABERTURAS!$E$7="OPERABLE"),ABERTURAS!$R$7+CHOOSE(ABERTURAS!$N$7,$AZ$4*$C$13,0,$AZ$4*($C$13-ABERTURAS!$P$7),$AZ$4*($C$13-ABERTURAS!$P$7)),0))+$AZ$40)/$AZ$38 -> 0.46836638 | BS5: =((IF(AND(ABERTURAS!$K$8="OK",ABERTURAS!$E$8="FIJA"),CHOOSE(ABERTURAS!$N$8,ABERTURAS!$P$8-$AZ$3*$C$13,ABERTURAS!$P$8,-$AZ$3*($C$13-ABERTURAS!$P$8),$C$12-$AZ$3*($C$13-ABERTURAS!$P$8)),0))+$AZ$39)/$AZ$38 -> 0.86484248 | BT5: =((IF(AND(ABERTURAS!$K$8="OK",ABERTURAS!$E$8="FIJA"),ABERTURAS!$R$8+CHOOSE(ABERTURAS!$N$8,$AZ$4*$C$13,0,$AZ$4*($C$13-ABERTURAS!$P$8),$AZ$4*($C$13-ABERTURAS!$P$8)),0))+$AZ$40)/$AZ$38 -> 0.15864023 | BU5: =((IF(AND(ABERTURAS!$K$8="OK",ABERTURAS!$E$8="OPERABLE"),CHOOSE(ABERTURAS!$N$8,ABERTURAS!$P$8-$AZ$3*$C$13,ABERTURAS!$P$8,-$AZ$3*($C$13-ABERTURAS!$P$8),$C$12-$AZ$3*($C$13-ABERTURAS!$P$8)),0))+$AZ$39)/$AZ$38 -> 0.90584814 | BV5: =((IF(AND(ABERTURAS!$K$8="OK",ABERTURAS!$E$8="OPERABLE"),ABERTURAS!$R$8+CHOOSE(ABERTURAS!$N$8,$AZ$4*$C$13,0,$AZ$4*($C$13-ABERTURAS!$P$8),$AZ$4*($C$13-ABERTURAS!$P$8)),0))+$AZ$40)/$AZ$38 -> 0.65391879 | BW5: =((IF(AND(ABERTURAS!$K$9="OK",ABERTURAS!$E$9="FIJA"),CHOOSE(ABERTURAS!$N$9,ABERTURAS!$P$9-$AZ$3*$C$13,ABERTURAS!$P$9,-$AZ$3*($C$13-ABERTURAS!$P$9),$C$12-$AZ$3*($C$13-ABERTURAS!$P$9)),0))+$AZ$39)/$AZ$38 -> 1.3407632 | BX5: =((IF(AND(ABERTURAS!$K$9="OK",ABERTURAS!$E$9="FIJA"),ABERTURAS!$R$9+CHOOSE(ABERTURAS!$N$9,$AZ$4*$C$13,0,$AZ$4*($C$13-ABERTURAS!$P$9),$AZ$4*($C$13-ABERTURAS!$P$9)),0))+$AZ$40)/$AZ$38 -> 0.62228517 | BY5: =((IF(AND(ABERTURAS!$K$9="OK",ABERTURAS!$E$9="OPERABLE"),CHOOSE(ABERTURAS!$N$9,ABERTURAS!$P$9-$AZ$3*$C$13,ABERTURAS!$P$9,-$AZ$3*($C$13-ABERTURAS!$P$9),$C$12-$AZ$3*($C$13-ABERTURAS!$P$9)),0))+$AZ$39)/$AZ$38 -> 0.86484248 | BZ5: =((IF(AND(ABERTURAS!$K$9="OK",ABERTURAS!$E$9="OPERABLE"),ABERTURAS!$R$9+CHOOSE(ABERTURAS!$N$9,$AZ$4*$C$13,0,$AZ$4*($C$13-ABERTURAS!$P$9),$AZ$4*($C$13-ABERTURAS!$P$9)),0))+$AZ$40)/$AZ$38 -> 0.15864023 | CA5: =((IF(AND(ABERTURAS!$K$10="OK",ABERTURAS!$E$10="FIJA"),CHOOSE(ABERTURAS!$N$10,ABERTURAS!$P$10-$AZ$3*$C$13,ABERTURAS!$P$10,-$AZ$3*($C$13-ABERTURAS!$P$10),$C$12-$AZ$3*($C$13-ABERTURAS!$P$10)),0))+$AZ$39)/$AZ$38 -> 0.86484248 | CB5: =((IF(AND(ABERTURAS!$K$10="OK",ABERTURAS!$E$10="FIJA"),ABERTURAS!$R$10+CHOOSE(ABERTURAS!$N$10,$AZ$4*$C$13,0,$AZ$4*($C$13-ABERTURAS!$P$10),$AZ$4*($C$13-ABERTURAS!$P$10)),0))+$AZ$40)/$AZ$38 -> 0.15864023 | CC5: =((IF(AND(ABERTURAS!$K$10="OK",ABERTURAS!$E$10="OPERABLE"),CHOOSE(ABERTURAS!$N$10,ABERTURAS!$P$10-$AZ$3*$C$13,ABERTURAS!$P$10,-$AZ$3*($C$13-ABERTURAS!$P$10),$C$12-$AZ$3*($C$13-ABERTURAS!$P$10)),0))+$AZ$39)/$AZ$38 -> 0.86484248 | CD5: =((IF(AND(ABERTURAS!$K$10="OK",ABERTURAS!$E$10="OPERABLE"),ABERTURAS!$R$10+CHOOSE(ABERTURAS!$N$10,$AZ$4*$C$13,0,$AZ$4*($C$13-ABERTURAS!$P$10),$AZ$4*($C$13-ABERTURAS!$P$10)),0))+$AZ$40)/$AZ$38 -> 0.15864023 | CE5: =((IF(AND(ABERTURAS!$K$11="OK",ABERTURAS!$E$11="FIJA"),CHOOSE(ABERTURAS!$N$11,ABERTURAS!$P$11-$AZ$3*$C$13,ABERTURAS!$P$11,-$AZ$3*($C$13-ABERTURAS!$P$11),$C$12-$AZ$3*($C$13-ABERTURAS!$P$11)),0))+$AZ$39)/$AZ$38 -> 0.86484248 | CF5: =((IF(AND(ABERTURAS!$K$11="OK",ABERTURAS!$E$11="FIJA"),ABERTURAS!$R$11+CHOOSE(ABERTURAS!$N$11,$AZ$4*$C$13,0,$AZ$4*($C$13-ABERTURAS!$P$11),$AZ$4*($C$13-ABERTURAS!$P$11)),0))+$AZ$40)/$AZ$38 -> 0.15864023 | CG5: =((IF(AND(ABERTURAS!$K$11="OK",ABERTURAS!$E$11="OPERABLE"),CHOOSE(ABERTURAS!$N$11,ABERTURAS!$P$11-$AZ$3*$C$13,ABERTURAS!$P$11,-$AZ$3*($C$13-ABERTURAS!$P$11),$C$12-$AZ$3*($C$13-ABERTURAS!$P$11)),0))+$AZ$39)/$AZ$38 -> 0.86484248 | CH5: =((IF(AND(ABERTURAS!$K$11="OK",ABERTURAS!$E$11="OPERABLE"),ABERTURAS!$R$11+CHOOSE(ABERTURAS!$N$11,$AZ$4*$C$13,0,$AZ$4*($C$13-ABERTURAS!$P$11),$AZ$4*($C$13-ABERTURAS!$P$11)),0))+$AZ$40)/$AZ$38 -> 0.15864023 | CI5: =((IF(AND(ABERTURAS!$K$12="OK",ABERTURAS!$E$12="FIJA"),CHOOSE(ABERTURAS!$N$12,ABERTURAS!$P$12-$AZ$3*$C$13,ABERTURAS!$P$12,-$AZ$3*($C$13-ABERTURAS!$P$12),$C$12-$AZ$3*($C$13-ABERTURAS!$P$12)),0))+$AZ$39)/$AZ$38 -> 0.86484248 | CJ5: =((IF(AND(ABERTURAS!$K$12="OK",ABERTURAS!$E$12="FIJA"),ABERTURAS!$R$12+CHOOSE(ABERTURAS!$N$12,$AZ$4*$C$13,0,$AZ$4*($C$13-ABERTURAS!$P$12),$AZ$4*($C$13-ABERTURAS!$P$12)),0))+$AZ$40)/$AZ$38 -> 0.15864023 | CK5: =((IF(AND(ABERTURAS!$K$12="OK",ABERTURAS!$E$12="OPERABLE"),CHOOSE(ABERTURAS!$N$12,ABERTURAS!$P$12-$AZ$3*$C$13,ABERTURAS!$P$12,-$AZ$3*($C$13-ABERTURAS!$P$12),$C$12-$AZ$3*($C$13-ABERTURAS!$P$12)),0))+$AZ$39)/$AZ$38 -> 0.86484248 | CL5: =((IF(AND(ABERTURAS!$K$12="OK",ABERTURAS!$E$12="OPERABLE"),ABERTURAS!$R$12+CHOOSE(ABERTURAS!$N$12,$AZ$4*$C$13,0,$AZ$4*($C$13-ABERTURAS!$P$12),$AZ$4*($C$13-ABERTURAS!$P$12)),0))+$AZ$40)/$AZ$38 -> 0.15864023 | CM5: =((IF(AND(ABERTURAS!$K$13="OK",ABERTURAS!$E$13="FIJA"),CHOOSE(ABERTURAS!$N$13,ABERTURAS!$P$13-$AZ$3*$C$13,ABERTURAS!$P$13,-$AZ$3*($C$13-ABERTURAS!$P$13),$C$12-$AZ$3*($C$13-ABERTURAS!$P$13)),0))+$AZ$39)/$AZ$38 -> 0.86484248 | CN5: =((IF(AND(ABERTURAS!$K$13="OK",ABERTURAS!$E$13="FIJA"),ABERTURAS!$R$13+CHOOSE(ABERTURAS!$N$13,$AZ$4*$C$13,0,$AZ$4*($C$13-ABERTURAS!$P$13),$AZ$4*($C$13-ABERTURAS!$P$13)),0))+$AZ$40)/$AZ$38 -> 0.15864023 | CO5: =((IF(AND(ABERTURAS!$K$13="OK",ABERTURAS!$E$13="OPERABLE"),CHOOSE(ABERTURAS!$N$13,ABERTURAS!$P$13-$AZ$3*$C$13,ABERTURAS!$P$13,-$AZ$3*($C$13-ABERTURAS!$P$13),$C$12-$AZ$3*($C$13-ABERTURAS!$P$13)),0))+$AZ$39)/$AZ$38 -> 0.86484248 | CP5: =((IF(AND(ABERTURAS!$K$13="OK",ABERTURAS!$E$13="OPERABLE"),ABERTURAS!$R$13+CHOOSE(ABERTURAS!$N$13,$AZ$4*$C$13,0,$AZ$4*($C$13-ABERTURAS!$P$13),$AZ$4*($C$13-ABERTURAS!$P$13)),0))+$AZ$40)/$AZ$38 -> 0.15864023 | CQ5: =((IF(AND(ABERTURAS!$K$14="OK",ABERTURAS!$E$14="FIJA"),CHOOSE(ABERTURAS!$N$14,ABERTURAS!$P$14-$AZ$3*$C$13,ABERTURAS!$P$14,-$AZ$3*($C$13-ABERTURAS!$P$14),$C$12-$AZ$3*($C$13-ABERTURAS!$P$14)),0))+$AZ$39)/$AZ$38 -> 0.86484248 | CR5: =((IF(AND(ABERTURAS!$K$14="OK",ABERTURAS!$E$14="FIJA"),ABERTURAS!$R$14+CHOOSE(ABERTURAS!$N$14,$AZ$4*$C$13,0,$AZ$4*($C$13-ABERTURAS!$P$14),$AZ$4*($C$13-ABERTURAS!$P$14)),0))+$AZ$40)/$AZ$38 -> 0.15864023 | CS5: =((IF(AND(ABERTURAS!$K$14="OK",ABERTURAS!$E$14="OPERABLE"),CHOOSE(ABERTURAS!$N$14,ABERTURAS!$P$14-$AZ$3*$C$13,ABERTURAS!$P$14,-$AZ$3*($C$13-ABERTURAS!$P$14),$C$12-$AZ$3*($C$13-ABERTURAS!$P$14)),0))+$AZ$39)/$AZ$38 -> 0.86484248 | CT5: =((IF(AND(ABERTURAS!$K$14="OK",ABERTURAS!$E$14="OPERABLE"),ABERTURAS!$R$14+CHOOSE(ABERTURAS!$N$14,$AZ$4*$C$13,0,$AZ$4*($C$13-ABERTURAS!$P$14),$AZ$4*($C$13-ABERTURAS!$P$14)),0))+$AZ$40)/$AZ$38 -> 0.15864023 | CU5: =((IF(AND(ABERTURAS!$K$15="OK",ABERTURAS!$E$15="FIJA"),CHOOSE(ABERTURAS!$N$15,ABERTURAS!$P$15-$AZ$3*$C$13,ABERTURAS!$P$15,-$AZ$3*($C$13-ABERTURAS!$P$15),$C$12-$AZ$3*($C$13-ABERTURAS!$P$15)),0))+$AZ$39)/$AZ$38 -> 0.86484248 | CV5: =((IF(AND(ABERTURAS!$K$15="OK",ABERTURAS!$E$15="FIJA"),ABERTURAS!$R$15+CHOOSE(ABERTURAS!$N$15,$AZ$4*$C$13,0,$AZ$4*($C$13-ABERTURAS!$P$15),$AZ$4*($C$13-ABERTURAS!$P$15)),0))+$AZ$40)/$AZ$38 -> 0.15864023 | CW5: =((IF(AND(ABERTURAS!$K$15="OK",ABERTURAS!$E$15="OPERABLE"),CHOOSE(ABERTURAS!$N$15,ABERTURAS!$P$15-$AZ$3*$C$13,ABERTURAS!$P$15,-$AZ$3*($C$13-ABERTURAS!$P$15),$C$12-$AZ$3*($C$13-ABERTURAS!$P$15)),0))+$AZ$39)/$AZ$38 -> 0.86484248 | CX5: =((IF(AND(ABERTURAS!$K$15="OK",ABERTURAS!$E$15="OPERABLE"),ABERTURAS!$R$15+CHOOSE(ABERTURAS!$N$15,$AZ$4*$C$13,0,$AZ$4*($C$13-ABERTURAS!$P$15),$AZ$4*($C$13-ABERTURAS!$P$15)),0))+$AZ$40)/$AZ$38 -> 0.15864023 | CY5: =((IF(AND(ABERTURAS!$K$16="OK",ABERTURAS!$E$16="FIJA"),CHOOSE(ABERTURAS!$N$16,ABERTURAS!$P$16-$AZ$3*$C$13,ABERTURAS!$P$16,-$AZ$3*($C$13-ABERTURAS!$P$16),$C$12-$AZ$3*($C$13-ABERTURAS!$P$16)),0))+$AZ$39)/$AZ$38 -> 0.86484248 | CZ5: =((IF(AND(ABERTURAS!$K$16="OK",ABERTURAS!$E$16="FIJA"),ABERTURAS!$R$16+CHOOSE(ABERTURAS!$N$16,$AZ$4*$C$13,0,$AZ$4*($C$13-ABERTURAS!$P$16),$AZ$4*($C$13-ABERTURAS!$P$16)),0))+$AZ$40)/$AZ$38 -> 0.15864023 | DA5: =((IF(AND(ABERTURAS!$K$16="OK",ABERTURAS!$E$16="OPERABLE"),CHOOSE(ABERTURAS!$N$16,ABERTURAS!$P$16-$AZ$3*$C$13,ABERTURAS!$P$16,-$AZ$3*($C$13-ABERTURAS!$P$16),$C$12-$AZ$3*($C$13-ABERTURAS!$P$16)),0))+$AZ$39)/$AZ$38 -> 0.86484248 | DB5: =((IF(AND(ABERTURAS!$K$16="OK",ABERTURAS!$E$16="OPERABLE"),ABERTURAS!$R$16+CHOOSE(ABERTURAS!$N$16,$AZ$4*$C$13,0,$AZ$4*($C$13-ABERTURAS!$P$16),$AZ$4*($C$13-ABERTURAS!$P$16)),0))+$AZ$40)/$AZ$38 -> 0.15864023 | DC5: =((IF(AND(ABERTURAS!$K$17="OK",ABERTURAS!$E$17="FIJA"),CHOOSE(ABERTURAS!$N$17,ABERTURAS!$P$17-$AZ$3*$C$13,ABERTURAS!$P$17,-$AZ$3*($C$13-ABERTURAS!$P$17),$C$12-$AZ$3*($C$13-ABERTURAS!$P$17)),0))+$AZ$39)/$AZ$38 -> 0.86484248 | DD5: =((IF(AND(ABERTURAS!$K$17="OK",ABERTURAS!$E$17="FIJA"),ABERTURAS!$R$17+CHOOSE(ABERTURAS!$N$17,$AZ$4*$C$13,0,$AZ$4*($C$13-ABERTURAS!$P$17),$AZ$4*($C$13-ABERTURAS!$P$17)),0))+$AZ$40)/$AZ$38 -> 0.15864023 | DE5: =((IF(AND(ABERTURAS!$K$17="OK",ABERTURAS!$E$17="OPERABLE"),CHOOSE(ABERTURAS!$N$17,ABERTURAS!$P$17-$AZ$3*$C$13,ABERTURAS!$P$17,-$AZ$3*($C$13-ABERTURAS!$P$17),$C$12-$AZ$3*($C$13-ABERTURAS!$P$17)),0))+$AZ$39)/$AZ$38 -> 0.86484248 | DF5: =((IF(AND(ABERTURAS!$K$17="OK",ABERTURAS!$E$17="OPERABLE"),ABERTURAS!$R$17+CHOOSE(ABERTURAS!$N$17,$AZ$4*$C$13,0,$AZ$4*($C$13-ABERTURAS!$P$17),$AZ$4*($C$13-ABERTURAS!$P$17)),0))+$AZ$40)/$AZ$38 -> 0.15864023 | DG5: =((IF(AND(ABERTURAS!$K$18="OK",ABERTURAS!$E$18="FIJA"),CHOOSE(ABERTURAS!$N$18,ABERTURAS!$P$18-$AZ$3*$C$13,ABERTURAS!$P$18,-$AZ$3*($C$13-ABERTURAS!$P$18),$C$12-$AZ$3*($C$13-ABERTURAS!$P$18)),0))+$AZ$39)/$AZ$38 -> 0.86484248 | DH5: =((IF(AND(ABERTURAS!$K$18="OK",ABERTURAS!$E$18="FIJA"),ABERTURAS!$R$18+CHOOSE(ABERTURAS!$N$18,$AZ$4*$C$13,0,$AZ$4*($C$13-ABERTURAS!$P$18),$AZ$4*($C$13-ABERTURAS!$P$18)),0))+$AZ$40)/$AZ$38 -> 0.15864023 | DI5: =((IF(AND(ABERTURAS!$K$18="OK",ABERTURAS!$E$18="OPERABLE"),CHOOSE(ABERTURAS!$N$18,ABERTURAS!$P$18-$AZ$3*$C$13,ABERTURAS!$P$18,-$AZ$3*($C$13-ABERTURAS!$P$18),$C$12-$AZ$3*($C$13-ABERTURAS!$P$18)),0))+$AZ$39)/$AZ$38 -> 0.86484248 | DJ5: =((IF(AND(ABERTURAS!$K$18="OK",ABERTURAS!$E$18="OPERABLE"),ABERTURAS!$R$18+CHOOSE(ABERTURAS!$N$18,$AZ$4*$C$13,0,$AZ$4*($C$13-ABERTURAS!$P$18),$AZ$4*($C$13-ABERTURAS!$P$18)),0))+$AZ$40)/$AZ$38 -> 0.15864023 | DK5: =((IF(AND(ABERTURAS!$K$19="OK",ABERTURAS!$E$19="FIJA"),CHOOSE(ABERTURAS!$N$19,ABERTURAS!$P$19-$AZ$3*$C$13,ABERTURAS!$P$19,-$AZ$3*($C$13-ABERTURAS!$P$19),$C$12-$AZ$3*($C$13-ABERTURAS!$P$19)),0))+$AZ$39)/$AZ$38 -> 0.86484248 | DL5: =((IF(AND(ABERTURAS!$K$19="OK",ABERTURAS!$E$19="FIJA"),ABERTURAS!$R$19+CHOOSE(ABERTURAS!$N$19,$AZ$4*$C$13,0,$AZ$4*($C$13-ABERTURAS!$P$19),$AZ$4*($C$13-ABERTURAS!$P$19)),0))+$AZ$40)/$AZ$38 -> 0.15864023 | DM5: =((IF(AND(ABERTURAS!$K$19="OK",ABERTURAS!$E$19="OPERABLE"),CHOOSE(ABERTURAS!$N$19,ABERTURAS!$P$19-$AZ$3*$C$13,ABERTURAS!$P$19,-$AZ$3*($C$13-ABERTURAS!$P$19),$C$12-$AZ$3*($C$13-ABERTURAS!$P$19)),0))+$AZ$39)/$AZ$38 -> 0.86484248 | DN5: =((IF(AND(ABERTURAS!$K$19="OK",ABERTURAS!$E$19="OPERABLE"),ABERTURAS!$R$19+CHOOSE(ABERTURAS!$N$19,$AZ$4*$C$13,0,$AZ$4*($C$13-ABERTURAS!$P$19),$AZ$4*($C$13-ABERTURAS!$P$19)),0))+$AZ$40)/$AZ$38 -> 0.15864023 | DO5: =((IF(AND(ABERTURAS!$K$20="OK",ABERTURAS!$E$20="FIJA"),CHOOSE(ABERTURAS!$N$20,ABERTURAS!$P$20-$AZ$3*$C$13,ABERTURAS!$P$20,-$AZ$3*($C$13-ABERTURAS!$P$20),$C$12-$AZ$3*($C$13-ABERTURAS!$P$20)),0))+$AZ$39)/$AZ$38 -> 0.86484248 | DP5: =((IF(AND(ABERTURAS!$K$20="OK",ABERTURAS!$E$20="FIJA"),ABERTURAS!$R$20+CHOOSE(ABERTURAS!$N$20,$AZ$4*$C$13,0,$AZ$4*($C$13-ABERTURAS!$P$20),$AZ$4*($C$13-ABERTURAS!$P$20)),0))+$AZ$40)/$AZ$38 -> 0.15864023 | DQ5: =((IF(AND(ABERTURAS!$K$20="OK",ABERTURAS!$E$20="OPERABLE"),CHOOSE(ABERTURAS!$N$20,ABERTURAS!$P$20-$AZ$3*$C$13,ABERTURAS!$P$20,-$AZ$3*($C$13-ABERTURAS!$P$20),$C$12-$AZ$3*($C$13-ABERTURAS!$P$20)),0))+$AZ$39)/$AZ$38 -> 0.86484248 | DR5: =((IF(AND(ABERTURAS!$K$20="OK",ABERTURAS!$E$20="OPERABLE"),ABERTURAS!$R$20+CHOOSE(ABERTURAS!$N$20,$AZ$4*$C$13,0,$AZ$4*($C$13-ABERTURAS!$P$20),$AZ$4*($C$13-ABERTURAS!$P$20)),0))+$AZ$40)/$AZ$38 -> 0.15864023 | DS5: =((IF(AND(ABERTURAS!$K$21="OK",ABERTURAS!$E$21="FIJA"),CHOOSE(ABERTURAS!$N$21,ABERTURAS!$P$21-$AZ$3*$C$13,ABERTURAS!$P$21,-$AZ$3*($C$13-ABERTURAS!$P$21),$C$12-$AZ$3*($C$13-ABERTURAS!$P$21)),0))+$AZ$39)/$AZ$38 -> 0.86484248 | DT5: =((IF(AND(ABERTURAS!$K$21="OK",ABERTURAS!$E$21="FIJA"),ABERTURAS!$R$21+CHOOSE(ABERTURAS!$N$21,$AZ$4*$C$13,0,$AZ$4*($C$13-ABERTURAS!$P$21),$AZ$4*($C$13-ABERTURAS!$P$21)),0))+$AZ$40)/$AZ$38 -> 0.15864023 | DU5: =((IF(AND(ABERTURAS!$K$21="OK",ABERTURAS!$E$21="OPERABLE"),CHOOSE(ABERTURAS!$N$21,ABERTURAS!$P$21-$AZ$3*$C$13,ABERTURAS!$P$21,-$AZ$3*($C$13-ABERTURAS!$P$21),$C$12-$AZ$3*($C$13-ABERTURAS!$P$21)),0))+$AZ$39)/$AZ$38 -> 0.86484248 | DV5: =((IF(AND(ABERTURAS!$K$21="OK",ABERTURAS!$E$21="OPERABLE"),ABERTURAS!$R$21+CHOOSE(ABERTURAS!$N$21,$AZ$4*$C$13,0,$AZ$4*($C$13-ABERTURAS!$P$21),$AZ$4*($C$13-ABERTURAS!$P$21)),0))+$AZ$40)/$AZ$38 -> 0.15864023 | DW5: =((IF(AND(ABERTURAS!$K$22="OK",ABERTURAS!$E$22="FIJA"),CHOOSE(ABERTURAS!$N$22,ABERTURAS!$P$22-$AZ$3*$C$13,ABERTURAS!$P$22,-$AZ$3*($C$13-ABERTURAS!$P$22),$C$12-$AZ$3*($C$13-ABERTURAS!$P$22)),0))+$AZ$39)/$AZ$38 -> 0.86484248 | DX5: =((IF(AND(ABERTURAS!$K$22="OK",ABERTURAS!$E$22="FIJA"),ABERTURAS!$R$22+CHOOSE(ABERTURAS!$N$22,$AZ$4*$C$13,0,$AZ$4*($C$13-ABERTURAS!$P$22),$AZ$4*($C$13-ABERTURAS!$P$22)),0))+$AZ$40)/$AZ$38 -> 0.15864023 | DY5: =((IF(AND(ABERTURAS!$K$22="OK",ABERTURAS!$E$22="OPERABLE"),CHOOSE(ABERTURAS!$N$22,ABERTURAS!$P$22-$AZ$3*$C$13,ABERTURAS!$P$22,-$AZ$3*($C$13-ABERTURAS!$P$22),$C$12-$AZ$3*($C$13-ABERTURAS!$P$22)),0))+$AZ$39)/$AZ$38 -> 0.86484248 | DZ5: =((IF(AND(ABERTURAS!$K$22="OK",ABERTURAS!$E$22="OPERABLE"),ABERTURAS!$R$22+CHOOSE(ABERTURAS!$N$22,$AZ$4*$C$13,0,$AZ$4*($C$13-ABERTURAS!$P$22),$AZ$4*($C$13-ABERTURAS!$P$22)),0))+$AZ$40)/$AZ$38 -> 0.15864023 | EA5: =((IF(AND(ABERTURAS!$K$23="OK",ABERTURAS!$E$23="FIJA"),CHOOSE(ABERTURAS!$N$23,ABERTURAS!$P$23-$AZ$3*$C$13,ABERTURAS!$P$23,-$AZ$3*($C$13-ABERTURAS!$P$23),$C$12-$AZ$3*($C$13-ABERTURAS!$P$23)),0))+$AZ$39)/$AZ$38 -> 0.86484248 | EB5: =((IF(AND(ABERTURAS!$K$23="OK",ABERTURAS!$E$23="FIJA"),ABERTURAS!$R$23+CHOOSE(ABERTURAS!$N$23,$AZ$4*$C$13,0,$AZ$4*($C$13-ABERTURAS!$P$23),$AZ$4*($C$13-ABERTURAS!$P$23)),0))+$AZ$40)/$AZ$38 -> 0.15864023 | EC5: =((IF(AND(ABERTURAS!$K$23="OK",ABERTURAS!$E$23="OPERABLE"),CHOOSE(ABERTURAS!$N$23,ABERTURAS!$P$23-$AZ$3*$C$13,ABERTURAS!$P$23,-$AZ$3*($C$13-ABERTURAS!$P$23),$C$12-$AZ$3*($C$13-ABERTURAS!$P$23)),0))+$AZ$39)/$AZ$38 -> 0.86484248 | ED5: =((IF(AND(ABERTURAS!$K$23="OK",ABERTURAS!$E$23="OPERABLE"),ABERTURAS!$R$23+CHOOSE(ABERTURAS!$N$23,$AZ$4*$C$13,0,$AZ$4*($C$13-ABERTURAS!$P$23),$AZ$4*($C$13-ABERTURAS!$P$23)),0))+$AZ$40)/$AZ$38 -> 0.15864023 | EE5: =((IF(AND(ABERTURAS!$K$24="OK",ABERTURAS!$E$24="FIJA"),CHOOSE(ABERTURAS!$N$24,ABERTURAS!$P$24-$AZ$3*$C$13,ABERTURAS!$P$24,-$AZ$3*($C$13-ABERTURAS!$P$24),$C$12-$AZ$3*($C$13-ABERTURAS!$P$24)),0))+$AZ$39)/$AZ$38 -> 0.86484248 | EF5: =((IF(AND(ABERTURAS!$K$24="OK",ABERTURAS!$E$24="FIJA"),ABERTURAS!$R$24+CHOOSE(ABERTURAS!$N$24,$AZ$4*$C$13,0,$AZ$4*($C$13-ABERTURAS!$P$24),$AZ$4*($C$13-ABERTURAS!$P$24)),0))+$AZ$40)/$AZ$38 -> 0.15864023 | EG5: =((IF(AND(ABERTURAS!$K$24="OK",ABERTURAS!$E$24="OPERABLE"),CHOOSE(ABERTURAS!$N$24,ABERTURAS!$P$24-$AZ$3*$C$13,ABERTURAS!$P$24,-$AZ$3*($C$13-ABERTURAS!$P$24),$C$12-$AZ$3*($C$13-ABERTURAS!$P$24)),0))+$AZ$39)/$AZ$38 -> 0.86484248 | EH5: =((IF(AND(ABERTURAS!$K$24="OK",ABERTURAS!$E$24="OPERABLE"),ABERTURAS!$R$24+CHOOSE(ABERTURAS!$N$24,$AZ$4*$C$13,0,$AZ$4*($C$13-ABERTURAS!$P$24),$AZ$4*($C$13-ABERTURAS!$P$24)),0))+$AZ$40)/$AZ$38 -> 0.15864023 | EI5: =((IF(AND(ABERTURAS!$K$25="OK",ABERTURAS!$E$25="FIJA"),CHOOSE(ABERTURAS!$N$25,ABERTURAS!$P$25-$AZ$3*$C$13,ABERTURAS!$P$25,-$AZ$3*($C$13-ABERTURAS!$P$25),$C$12-$AZ$3*($C$13-ABERTURAS!$P$25)),0))+$AZ$39)/$AZ$38 -> 0.86484248 | EJ5: =((IF(AND(ABERTURAS!$K$25="OK",ABERTURAS!$E$25="FIJA"),ABERTURAS!$R$25+CHOOSE(ABERTURAS!$N$25,$AZ$4*$C$13,0,$AZ$4*($C$13-ABERTURAS!$P$25),$AZ$4*($C$13-ABERTURAS!$P$25)),0))+$AZ$40)/$AZ$38 -> 0.15864023 | EK5: =((IF(AND(ABERTURAS!$K$25="OK",ABERTURAS!$E$25="OPERABLE"),CHOOSE(ABERTURAS!$N$25,ABERTURAS!$P$25-$AZ$3*$C$13,ABERTURAS!$P$25,-$AZ$3*($C$13-ABERTURAS!$P$25),$C$12-$AZ$3*($C$13-ABERTURAS!$P$25)),0))+$AZ$39)/$AZ$38 -> 0.86484248 | EL5: =((IF(AND(ABERTURAS!$K$25="OK",ABERTURAS!$E$25="OPERABLE"),ABERTURAS!$R$25+CHOOSE(ABERTURAS!$N$25,$AZ$4*$C$13,0,$AZ$4*($C$13-ABERTURAS!$P$25),$AZ$4*($C$13-ABERTURAS!$P$25)),0))+$AZ$40)/$AZ$38 -> 0.15864023 | EM5: =((IF(AND(ABERTURAS!$K$26="OK",ABERTURAS!$E$26="FIJA"),CHOOSE(ABERTURAS!$N$26,ABERTURAS!$P$26-$AZ$3*$C$13,ABERTURAS!$P$26,-$AZ$3*($C$13-ABERTURAS!$P$26),$C$12-$AZ$3*($C$13-ABERTURAS!$P$26)),0))+$AZ$39)/$AZ$38 -> 0.86484248 | EN5: =((IF(AND(ABERTURAS!$K$26="OK",ABERTURAS!$E$26="FIJA"),ABERTURAS!$R$26+CHOOSE(ABERTURAS!$N$26,$AZ$4*$C$13,0,$AZ$4*($C$13-ABERTURAS!$P$26),$AZ$4*($C$13-ABERTURAS!$P$26)),0))+$AZ$40)/$AZ$38 -> 0.15864023 | EO5: =((IF(AND(ABERTURAS!$K$26="OK",ABERTURAS!$E$26="OPERABLE"),CHOOSE(ABERTURAS!$N$26,ABERTURAS!$P$26-$AZ$3*$C$13,ABERTURAS!$P$26,-$AZ$3*($C$13-ABERTURAS!$P$26),$C$12-$AZ$3*($C$13-ABERTURAS!$P$26)),0))+$AZ$39)/$AZ$38 -> 0.86484248 | EP5: =((IF(AND(ABERTURAS!$K$26="OK",ABERTURAS!$E$26="OPERABLE"),ABERTURAS!$R$26+CHOOSE(ABERTURAS!$N$26,$AZ$4*$C$13,0,$AZ$4*($C$13-ABERTURAS!$P$26),$AZ$4*($C$13-ABERTURAS!$P$26)),0))+$AZ$40)/$AZ$38 -> 0.15864023
B6: Concepto | C6: Valor | D6: Unidad | E6: Cómo se calcula / de dónde sale | F6: Referencia | AA6: =$C$23*3/8 -> 6 | AB6: =IF($C$14="PLANO",$C$17,IF($C$14="DOS AGUAS",$C$17+($C$18-$C$17)*(1-ABS(2*($AA$6)/$C$23-1)),IF($C$14="UN AGUA",IF(N($C$25)=0,$C$18-($C$18-$C$17)*($AA$6)/$C$23,$C$17+($C$18-$C$17)*($AA$6)/$C$23),$C$17+4*($C$18-$C$17)*($AA$6)/$C$23*(1-($AA$6)/$C$23)))) -> 10.32 | AE6: =ABERTURAS!$D$51*7/8 -> 8.82 | AF6: =IF(ABERTURAS!$E$51="SÍ",$AB$10,ABERTURAS!$F$51) -> 10.62 | AG6: =((($AZ$5+$AE6*($C$12-2*$AZ$5)/$C$12)-$AZ$3*$C$13)+$AZ$39)/$AZ$38 -> 0.95266117 | AH6: =((IF($AF6>0,$AF6-$AZ$5,0)+$AZ$4*$C$13)+$AZ$40)/$AZ$38 -> 0.84135977 | AI6: =ABERTURAS!$D$52*7/8 -> 8.82 | AJ6: =IF(ABERTURAS!$E$52="SÍ",$AB$10,ABERTURAS!$F$52) -> 9.82 | AK6: =((($AZ$5+$AI6*($C$12-2*$AZ$5)/$C$12))+$AZ$39)/$AZ$38 -> 1.2699416 | AL6: =((IF($AJ6>0,$AJ6-$AZ$5,0))+$AZ$40)/$AZ$38 -> 0.60717658 | AM6: =ABERTURAS!$D$53*7/8 -> 14 | AN6: =IF(ABERTURAS!$E$53="SÍ",$AB$10,ABERTURAS!$F$53) -> 9.92 | AO6: =((-$AZ$3*($C$13-($AZ$5+$AM6*($C$13-2*$AZ$5)/$C$13)))+$AZ$39)/$AZ$38 -> 0.82042321 | AP6: =((IF($AN6>0,$AN6-$AZ$5,0)+$AZ$4*($C$13-($AZ$5+$AM6*($C$13-2*$AZ$5)/$C$13)))+$AZ$40)/$AZ$38 -> 0.63939566 | AQ6: =ABERTURAS!$D$54*7/8 -> 14 | AR6: =IF(ABERTURAS!$E$54="SÍ",$AB$10,ABERTURAS!$F$54) -> 9.92 | AS6: =(($C$12-$AZ$3*($C$13-($AZ$5+$AQ6*($C$13-2*$AZ$5)/$C$13)))+$AZ$39)/$AZ$38 -> 1.2963439 | AT6: =((IF($AR6>0,$AR6-$AZ$5,0)+$AZ$4*($C$13-($AZ$5+$AQ6*($C$13-2*$AZ$5)/$C$13)))+$AZ$40)/$AZ$38 -> 0.63939566 | AU6: =((IF($AC$3="Z",0,$AA$6)-$AZ$3*($C$13-IF($AC$3="Z",$AA$6,0)))+$AZ$39)/$AZ$38 -> 0.66654219 | AV6: =(($AB$6+$AZ$4*($C$13-IF($AC$3="Z",$AA$6,0)))+$AZ$40)/$AZ$38 -> 0.76864967 | AY6: x' mín nave | AZ6: =-$AZ$3*$C$13 -> -6.72 | BA6: =BA4 -> 0.78552236 | BB6: =BB4 -> 0.84135977 | BC6: =BC4 -> 1.1028028 | BD6: =BD4 -> 0.15864023 | BE6: =BE4 -> 0.70620225 | BF6: =BF4 -> 0.25684608 | BG6: =BG4 -> 1.1821229 | BH6: =BH4 -> 0.72426818 | ... BN6: =BN4 -> 0.20038488 | BO6: =((IF(AND(ABERTURAS!$K$7="OK",ABERTURAS!$E$7="FIJA"),CHOOSE(ABERTURAS!$N$7,ABERTURAS!$O$7-$AZ$3*$C$13,ABERTURAS!$O$7,-$AZ$3*($C$13-ABERTURAS!$O$7),$C$12-$AZ$3*($C$13-ABERTURAS!$O$7)),0))+$AZ$39)/$AZ$38 -> 0.86484248 | BP6: =((IF(AND(ABERTURAS!$K$7="OK",ABERTURAS!$E$7="FIJA"),ABERTURAS!$R$7+CHOOSE(ABERTURAS!$N$7,$AZ$4*$C$13,0,$AZ$4*($C$13-ABERTURAS!$O$7),$AZ$4*($C$13-ABERTURAS!$O$7)),0))+$AZ$40)/$AZ$38 -> 0.15864023 | BQ6: =((IF(AND(ABERTURAS!$K$7="OK",ABERTURAS!$E$7="OPERABLE"),CHOOSE(ABERTURAS!$N$7,ABERTURAS!$O$7-$AZ$3*$C$13,ABERTURAS!$O$7,-$AZ$3*($C$13-ABERTURAS!$O$7),$C$12-$AZ$3*($C$13-ABERTURAS!$O$7)),0))+$AZ$39)/$AZ$38 -> 0.57789724 | BR6: =((IF(AND(ABERTURAS!$K$7="OK",ABERTURAS!$E$7="OPERABLE"),ABERTURAS!$R$7+CHOOSE(ABERTURAS!$N$7,$AZ$4*$C$13,0,$AZ$4*($C$13-ABERTURAS!$O$7),$AZ$4*($C$13-ABERTURAS!$O$7)),0))+$AZ$40)/$AZ$38 -> 0.46836638 | BS6: =((IF(AND(ABERTURAS!$K$8="OK",ABERTURAS!$E$8="FIJA"),CHOOSE(ABERTURAS!$N$8,ABERTURAS!$O$8-$AZ$3*$C$13,ABERTURAS!$O$8,-$AZ$3*($C$13-ABERTURAS!$O$8),$C$12-$AZ$3*($C$13-ABERTURAS!$O$8)),0))+$AZ$39)/$AZ$38 -> 0.86484248 | BT6: =((IF(AND(ABERTURAS!$K$8="OK",ABERTURAS!$E$8="FIJA"),ABERTURAS!$R$8+CHOOSE(ABERTURAS!$N$8,$AZ$4*$C$13,0,$AZ$4*($C$13-ABERTURAS!$O$8),$AZ$4*($C$13-ABERTURAS!$O$8)),0))+$AZ$40)/$AZ$38 -> 0.15864023 | BU6: =((IF(AND(ABERTURAS!$K$8="OK",ABERTURAS!$E$8="OPERABLE"),CHOOSE(ABERTURAS!$N$8,ABERTURAS!$O$8-$AZ$3*$C$13,ABERTURAS!$O$8,-$AZ$3*($C$13-ABERTURAS!$O$8),$C$12-$AZ$3*($C$13-ABERTURAS!$O$8)),0))+$AZ$39)/$AZ$38 -> 0.6649794 | BV6: =((IF(AND(ABERTURAS!$K$8="OK",ABERTURAS!$E$8="OPERABLE"),ABERTURAS!$R$8+CHOOSE(ABERTURAS!$N$8,$AZ$4*$C$13,0,$AZ$4*($C$13-ABERTURAS!$O$8),$AZ$4*($C$13-ABERTURAS!$O$8)),0))+$AZ$40)/$AZ$38 -> 0.65391879 | BW6: =((IF(AND(ABERTURAS!$K$9="OK",ABERTURAS!$E$9="FIJA"),CHOOSE(ABERTURAS!$N$9,ABERTURAS!$O$9-$AZ$3*$C$13,ABERTURAS!$O$9,-$AZ$3*($C$13-ABERTURAS!$O$9),$C$12-$AZ$3*($C$13-ABERTURAS!$O$9)),0))+$AZ$39)/$AZ$38 -> 0.86484248 | BX6: =((IF(AND(ABERTURAS!$K$9="OK",ABERTURAS!$E$9="FIJA"),ABERTURAS!$R$9+CHOOSE(ABERTURAS!$N$9,$AZ$4*$C$13,0,$AZ$4*($C$13-ABERTURAS!$O$9),$AZ$4*($C$13-ABERTURAS!$O$9)),0))+$AZ$40)/$AZ$38 -> 0.62228517 | BY6: =((IF(AND(ABERTURAS!$K$9="OK",ABERTURAS!$E$9="OPERABLE"),CHOOSE(ABERTURAS!$N$9,ABERTURAS!$O$9-$AZ$3*$C$13,ABERTURAS!$O$9,-$AZ$3*($C$13-ABERTURAS!$O$9),$C$12-$AZ$3*($C$13-ABERTURAS!$O$9)),0))+$AZ$39)/$AZ$38 -> 0.86484248 | BZ6: =((IF(AND(ABERTURAS!$K$9="OK",ABERTURAS!$E$9="OPERABLE"),ABERTURAS!$R$9+CHOOSE(ABERTURAS!$N$9,$AZ$4*$C$13,0,$AZ$4*($C$13-ABERTURAS!$O$9),$AZ$4*($C$13-ABERTURAS!$O$9)),0))+$AZ$40)/$AZ$38 -> 0.15864023 | CA6: =((IF(AND(ABERTURAS!$K$10="OK",ABERTURAS!$E$10="FIJA"),CHOOSE(ABERTURAS!$N$10,ABERTURAS!$O$10-$AZ$3*$C$13,ABERTURAS!$O$10,-$AZ$3*($C$13-ABERTURAS!$O$10),$C$12-$AZ$3*($C$13-ABERTURAS!$O$10)),0))+$AZ$39)/$AZ$38 -> 0.86484248 | CB6: =((IF(AND(ABERTURAS!$K$10="OK",ABERTURAS!$E$10="FIJA"),ABERTURAS!$R$10+CHOOSE(ABERTURAS!$N$10,$AZ$4*$C$13,0,$AZ$4*($C$13-ABERTURAS!$O$10),$AZ$4*($C$13-ABERTURAS!$O$10)),0))+$AZ$40)/$AZ$38 -> 0.15864023 | CC6: =((IF(AND(ABERTURAS!$K$10="OK",ABERTURAS!$E$10="OPERABLE"),CHOOSE(ABERTURAS!$N$10,ABERTURAS!$O$10-$AZ$3*$C$13,ABERTURAS!$O$10,-$AZ$3*($C$13-ABERTURAS!$O$10),$C$12-$AZ$3*($C$13-ABERTURAS!$O$10)),0))+$AZ$39)/$AZ$38 -> 0.86484248 | CD6: =((IF(AND(ABERTURAS!$K$10="OK",ABERTURAS!$E$10="OPERABLE"),ABERTURAS!$R$10+CHOOSE(ABERTURAS!$N$10,$AZ$4*$C$13,0,$AZ$4*($C$13-ABERTURAS!$O$10),$AZ$4*($C$13-ABERTURAS!$O$10)),0))+$AZ$40)/$AZ$38 -> 0.15864023 | CE6: =((IF(AND(ABERTURAS!$K$11="OK",ABERTURAS!$E$11="FIJA"),CHOOSE(ABERTURAS!$N$11,ABERTURAS!$O$11-$AZ$3*$C$13,ABERTURAS!$O$11,-$AZ$3*($C$13-ABERTURAS!$O$11),$C$12-$AZ$3*($C$13-ABERTURAS!$O$11)),0))+$AZ$39)/$AZ$38 -> 0.86484248 | CF6: =((IF(AND(ABERTURAS!$K$11="OK",ABERTURAS!$E$11="FIJA"),ABERTURAS!$R$11+CHOOSE(ABERTURAS!$N$11,$AZ$4*$C$13,0,$AZ$4*($C$13-ABERTURAS!$O$11),$AZ$4*($C$13-ABERTURAS!$O$11)),0))+$AZ$40)/$AZ$38 -> 0.15864023 | CG6: =((IF(AND(ABERTURAS!$K$11="OK",ABERTURAS!$E$11="OPERABLE"),CHOOSE(ABERTURAS!$N$11,ABERTURAS!$O$11-$AZ$3*$C$13,ABERTURAS!$O$11,-$AZ$3*($C$13-ABERTURAS!$O$11),$C$12-$AZ$3*($C$13-ABERTURAS!$O$11)),0))+$AZ$39)/$AZ$38 -> 0.86484248 | CH6: =((IF(AND(ABERTURAS!$K$11="OK",ABERTURAS!$E$11="OPERABLE"),ABERTURAS!$R$11+CHOOSE(ABERTURAS!$N$11,$AZ$4*$C$13,0,$AZ$4*($C$13-ABERTURAS!$O$11),$AZ$4*($C$13-ABERTURAS!$O$11)),0))+$AZ$40)/$AZ$38 -> 0.15864023 | CI6: =((IF(AND(ABERTURAS!$K$12="OK",ABERTURAS!$E$12="FIJA"),CHOOSE(ABERTURAS!$N$12,ABERTURAS!$O$12-$AZ$3*$C$13,ABERTURAS!$O$12,-$AZ$3*($C$13-ABERTURAS!$O$12),$C$12-$AZ$3*($C$13-ABERTURAS!$O$12)),0))+$AZ$39)/$AZ$38 -> 0.86484248 | CJ6: =((IF(AND(ABERTURAS!$K$12="OK",ABERTURAS!$E$12="FIJA"),ABERTURAS!$R$12+CHOOSE(ABERTURAS!$N$12,$AZ$4*$C$13,0,$AZ$4*($C$13-ABERTURAS!$O$12),$AZ$4*($C$13-ABERTURAS!$O$12)),0))+$AZ$40)/$AZ$38 -> 0.15864023 | CK6: =((IF(AND(ABERTURAS!$K$12="OK",ABERTURAS!$E$12="OPERABLE"),CHOOSE(ABERTURAS!$N$12,ABERTURAS!$O$12-$AZ$3*$C$13,ABERTURAS!$O$12,-$AZ$3*($C$13-ABERTURAS!$O$12),$C$12-$AZ$3*($C$13-ABERTURAS!$O$12)),0))+$AZ$39)/$AZ$38 -> 0.86484248 | CL6: =((IF(AND(ABERTURAS!$K$12="OK",ABERTURAS!$E$12="OPERABLE"),ABERTURAS!$R$12+CHOOSE(ABERTURAS!$N$12,$AZ$4*$C$13,0,$AZ$4*($C$13-ABERTURAS!$O$12),$AZ$4*($C$13-ABERTURAS!$O$12)),0))+$AZ$40)/$AZ$38 -> 0.15864023 | CM6: =((IF(AND(ABERTURAS!$K$13="OK",ABERTURAS!$E$13="FIJA"),CHOOSE(ABERTURAS!$N$13,ABERTURAS!$O$13-$AZ$3*$C$13,ABERTURAS!$O$13,-$AZ$3*($C$13-ABERTURAS!$O$13),$C$12-$AZ$3*($C$13-ABERTURAS!$O$13)),0))+$AZ$39)/$AZ$38 -> 0.86484248 | CN6: =((IF(AND(ABERTURAS!$K$13="OK",ABERTURAS!$E$13="FIJA"),ABERTURAS!$R$13+CHOOSE(ABERTURAS!$N$13,$AZ$4*$C$13,0,$AZ$4*($C$13-ABERTURAS!$O$13),$AZ$4*($C$13-ABERTURAS!$O$13)),0))+$AZ$40)/$AZ$38 -> 0.15864023 | CO6: =((IF(AND(ABERTURAS!$K$13="OK",ABERTURAS!$E$13="OPERABLE"),CHOOSE(ABERTURAS!$N$13,ABERTURAS!$O$13-$AZ$3*$C$13,ABERTURAS!$O$13,-$AZ$3*($C$13-ABERTURAS!$O$13),$C$12-$AZ$3*($C$13-ABERTURAS!$O$13)),0))+$AZ$39)/$AZ$38 -> 0.86484248 | CP6: =((IF(AND(ABERTURAS!$K$13="OK",ABERTURAS!$E$13="OPERABLE"),ABERTURAS!$R$13+CHOOSE(ABERTURAS!$N$13,$AZ$4*$C$13,0,$AZ$4*($C$13-ABERTURAS!$O$13),$AZ$4*($C$13-ABERTURAS!$O$13)),0))+$AZ$40)/$AZ$38 -> 0.15864023 | CQ6: =((IF(AND(ABERTURAS!$K$14="OK",ABERTURAS!$E$14="FIJA"),CHOOSE(ABERTURAS!$N$14,ABERTURAS!$O$14-$AZ$3*$C$13,ABERTURAS!$O$14,-$AZ$3*($C$13-ABERTURAS!$O$14),$C$12-$AZ$3*($C$13-ABERTURAS!$O$14)),0))+$AZ$39)/$AZ$38 -> 0.86484248 | CR6: =((IF(AND(ABERTURAS!$K$14="OK",ABERTURAS!$E$14="FIJA"),ABERTURAS!$R$14+CHOOSE(ABERTURAS!$N$14,$AZ$4*$C$13,0,$AZ$4*($C$13-ABERTURAS!$O$14),$AZ$4*($C$13-ABERTURAS!$O$14)),0))+$AZ$40)/$AZ$38 -> 0.15864023 | CS6: =((IF(AND(ABERTURAS!$K$14="OK",ABERTURAS!$E$14="OPERABLE"),CHOOSE(ABERTURAS!$N$14,ABERTURAS!$O$14-$AZ$3*$C$13,ABERTURAS!$O$14,-$AZ$3*($C$13-ABERTURAS!$O$14),$C$12-$AZ$3*($C$13-ABERTURAS!$O$14)),0))+$AZ$39)/$AZ$38 -> 0.86484248 | CT6: =((IF(AND(ABERTURAS!$K$14="OK",ABERTURAS!$E$14="OPERABLE"),ABERTURAS!$R$14+CHOOSE(ABERTURAS!$N$14,$AZ$4*$C$13,0,$AZ$4*($C$13-ABERTURAS!$O$14),$AZ$4*($C$13-ABERTURAS!$O$14)),0))+$AZ$40)/$AZ$38 -> 0.15864023 | CU6: =((IF(AND(ABERTURAS!$K$15="OK",ABERTURAS!$E$15="FIJA"),CHOOSE(ABERTURAS!$N$15,ABERTURAS!$O$15-$AZ$3*$C$13,ABERTURAS!$O$15,-$AZ$3*($C$13-ABERTURAS!$O$15),$C$12-$AZ$3*($C$13-ABERTURAS!$O$15)),0))+$AZ$39)/$AZ$38 -> 0.86484248 | CV6: =((IF(AND(ABERTURAS!$K$15="OK",ABERTURAS!$E$15="FIJA"),ABERTURAS!$R$15+CHOOSE(ABERTURAS!$N$15,$AZ$4*$C$13,0,$AZ$4*($C$13-ABERTURAS!$O$15),$AZ$4*($C$13-ABERTURAS!$O$15)),0))+$AZ$40)/$AZ$38 -> 0.15864023 | CW6: =((IF(AND(ABERTURAS!$K$15="OK",ABERTURAS!$E$15="OPERABLE"),CHOOSE(ABERTURAS!$N$15,ABERTURAS!$O$15-$AZ$3*$C$13,ABERTURAS!$O$15,-$AZ$3*($C$13-ABERTURAS!$O$15),$C$12-$AZ$3*($C$13-ABERTURAS!$O$15)),0))+$AZ$39)/$AZ$38 -> 0.86484248 | CX6: =((IF(AND(ABERTURAS!$K$15="OK",ABERTURAS!$E$15="OPERABLE"),ABERTURAS!$R$15+CHOOSE(ABERTURAS!$N$15,$AZ$4*$C$13,0,$AZ$4*($C$13-ABERTURAS!$O$15),$AZ$4*($C$13-ABERTURAS!$O$15)),0))+$AZ$40)/$AZ$38 -> 0.15864023 | CY6: =((IF(AND(ABERTURAS!$K$16="OK",ABERTURAS!$E$16="FIJA"),CHOOSE(ABERTURAS!$N$16,ABERTURAS!$O$16-$AZ$3*$C$13,ABERTURAS!$O$16,-$AZ$3*($C$13-ABERTURAS!$O$16),$C$12-$AZ$3*($C$13-ABERTURAS!$O$16)),0))+$AZ$39)/$AZ$38 -> 0.86484248 | CZ6: =((IF(AND(ABERTURAS!$K$16="OK",ABERTURAS!$E$16="FIJA"),ABERTURAS!$R$16+CHOOSE(ABERTURAS!$N$16,$AZ$4*$C$13,0,$AZ$4*($C$13-ABERTURAS!$O$16),$AZ$4*($C$13-ABERTURAS!$O$16)),0))+$AZ$40)/$AZ$38 -> 0.15864023 | DA6: =((IF(AND(ABERTURAS!$K$16="OK",ABERTURAS!$E$16="OPERABLE"),CHOOSE(ABERTURAS!$N$16,ABERTURAS!$O$16-$AZ$3*$C$13,ABERTURAS!$O$16,-$AZ$3*($C$13-ABERTURAS!$O$16),$C$12-$AZ$3*($C$13-ABERTURAS!$O$16)),0))+$AZ$39)/$AZ$38 -> 0.86484248 | DB6: =((IF(AND(ABERTURAS!$K$16="OK",ABERTURAS!$E$16="OPERABLE"),ABERTURAS!$R$16+CHOOSE(ABERTURAS!$N$16,$AZ$4*$C$13,0,$AZ$4*($C$13-ABERTURAS!$O$16),$AZ$4*($C$13-ABERTURAS!$O$16)),0))+$AZ$40)/$AZ$38 -> 0.15864023 | DC6: =((IF(AND(ABERTURAS!$K$17="OK",ABERTURAS!$E$17="FIJA"),CHOOSE(ABERTURAS!$N$17,ABERTURAS!$O$17-$AZ$3*$C$13,ABERTURAS!$O$17,-$AZ$3*($C$13-ABERTURAS!$O$17),$C$12-$AZ$3*($C$13-ABERTURAS!$O$17)),0))+$AZ$39)/$AZ$38 -> 0.86484248 | DD6: =((IF(AND(ABERTURAS!$K$17="OK",ABERTURAS!$E$17="FIJA"),ABERTURAS!$R$17+CHOOSE(ABERTURAS!$N$17,$AZ$4*$C$13,0,$AZ$4*($C$13-ABERTURAS!$O$17),$AZ$4*($C$13-ABERTURAS!$O$17)),0))+$AZ$40)/$AZ$38 -> 0.15864023 | DE6: =((IF(AND(ABERTURAS!$K$17="OK",ABERTURAS!$E$17="OPERABLE"),CHOOSE(ABERTURAS!$N$17,ABERTURAS!$O$17-$AZ$3*$C$13,ABERTURAS!$O$17,-$AZ$3*($C$13-ABERTURAS!$O$17),$C$12-$AZ$3*($C$13-ABERTURAS!$O$17)),0))+$AZ$39)/$AZ$38 -> 0.86484248 | DF6: =((IF(AND(ABERTURAS!$K$17="OK",ABERTURAS!$E$17="OPERABLE"),ABERTURAS!$R$17+CHOOSE(ABERTURAS!$N$17,$AZ$4*$C$13,0,$AZ$4*($C$13-ABERTURAS!$O$17),$AZ$4*($C$13-ABERTURAS!$O$17)),0))+$AZ$40)/$AZ$38 -> 0.15864023 | DG6: =((IF(AND(ABERTURAS!$K$18="OK",ABERTURAS!$E$18="FIJA"),CHOOSE(ABERTURAS!$N$18,ABERTURAS!$O$18-$AZ$3*$C$13,ABERTURAS!$O$18,-$AZ$3*($C$13-ABERTURAS!$O$18),$C$12-$AZ$3*($C$13-ABERTURAS!$O$18)),0))+$AZ$39)/$AZ$38 -> 0.86484248 | DH6: =((IF(AND(ABERTURAS!$K$18="OK",ABERTURAS!$E$18="FIJA"),ABERTURAS!$R$18+CHOOSE(ABERTURAS!$N$18,$AZ$4*$C$13,0,$AZ$4*($C$13-ABERTURAS!$O$18),$AZ$4*($C$13-ABERTURAS!$O$18)),0))+$AZ$40)/$AZ$38 -> 0.15864023 | DI6: =((IF(AND(ABERTURAS!$K$18="OK",ABERTURAS!$E$18="OPERABLE"),CHOOSE(ABERTURAS!$N$18,ABERTURAS!$O$18-$AZ$3*$C$13,ABERTURAS!$O$18,-$AZ$3*($C$13-ABERTURAS!$O$18),$C$12-$AZ$3*($C$13-ABERTURAS!$O$18)),0))+$AZ$39)/$AZ$38 -> 0.86484248 | DJ6: =((IF(AND(ABERTURAS!$K$18="OK",ABERTURAS!$E$18="OPERABLE"),ABERTURAS!$R$18+CHOOSE(ABERTURAS!$N$18,$AZ$4*$C$13,0,$AZ$4*($C$13-ABERTURAS!$O$18),$AZ$4*($C$13-ABERTURAS!$O$18)),0))+$AZ$40)/$AZ$38 -> 0.15864023 | DK6: =((IF(AND(ABERTURAS!$K$19="OK",ABERTURAS!$E$19="FIJA"),CHOOSE(ABERTURAS!$N$19,ABERTURAS!$O$19-$AZ$3*$C$13,ABERTURAS!$O$19,-$AZ$3*($C$13-ABERTURAS!$O$19),$C$12-$AZ$3*($C$13-ABERTURAS!$O$19)),0))+$AZ$39)/$AZ$38 -> 0.86484248 | DL6: =((IF(AND(ABERTURAS!$K$19="OK",ABERTURAS!$E$19="FIJA"),ABERTURAS!$R$19+CHOOSE(ABERTURAS!$N$19,$AZ$4*$C$13,0,$AZ$4*($C$13-ABERTURAS!$O$19),$AZ$4*($C$13-ABERTURAS!$O$19)),0))+$AZ$40)/$AZ$38 -> 0.15864023 | DM6: =((IF(AND(ABERTURAS!$K$19="OK",ABERTURAS!$E$19="OPERABLE"),CHOOSE(ABERTURAS!$N$19,ABERTURAS!$O$19-$AZ$3*$C$13,ABERTURAS!$O$19,-$AZ$3*($C$13-ABERTURAS!$O$19),$C$12-$AZ$3*($C$13-ABERTURAS!$O$19)),0))+$AZ$39)/$AZ$38 -> 0.86484248 | DN6: =((IF(AND(ABERTURAS!$K$19="OK",ABERTURAS!$E$19="OPERABLE"),ABERTURAS!$R$19+CHOOSE(ABERTURAS!$N$19,$AZ$4*$C$13,0,$AZ$4*($C$13-ABERTURAS!$O$19),$AZ$4*($C$13-ABERTURAS!$O$19)),0))+$AZ$40)/$AZ$38 -> 0.15864023 | DO6: =((IF(AND(ABERTURAS!$K$20="OK",ABERTURAS!$E$20="FIJA"),CHOOSE(ABERTURAS!$N$20,ABERTURAS!$O$20-$AZ$3*$C$13,ABERTURAS!$O$20,-$AZ$3*($C$13-ABERTURAS!$O$20),$C$12-$AZ$3*($C$13-ABERTURAS!$O$20)),0))+$AZ$39)/$AZ$38 -> 0.86484248 | DP6: =((IF(AND(ABERTURAS!$K$20="OK",ABERTURAS!$E$20="FIJA"),ABERTURAS!$R$20+CHOOSE(ABERTURAS!$N$20,$AZ$4*$C$13,0,$AZ$4*($C$13-ABERTURAS!$O$20),$AZ$4*($C$13-ABERTURAS!$O$20)),0))+$AZ$40)/$AZ$38 -> 0.15864023 | DQ6: =((IF(AND(ABERTURAS!$K$20="OK",ABERTURAS!$E$20="OPERABLE"),CHOOSE(ABERTURAS!$N$20,ABERTURAS!$O$20-$AZ$3*$C$13,ABERTURAS!$O$20,-$AZ$3*($C$13-ABERTURAS!$O$20),$C$12-$AZ$3*($C$13-ABERTURAS!$O$20)),0))+$AZ$39)/$AZ$38 -> 0.86484248 | DR6: =((IF(AND(ABERTURAS!$K$20="OK",ABERTURAS!$E$20="OPERABLE"),ABERTURAS!$R$20+CHOOSE(ABERTURAS!$N$20,$AZ$4*$C$13,0,$AZ$4*($C$13-ABERTURAS!$O$20),$AZ$4*($C$13-ABERTURAS!$O$20)),0))+$AZ$40)/$AZ$38 -> 0.15864023 | DS6: =((IF(AND(ABERTURAS!$K$21="OK",ABERTURAS!$E$21="FIJA"),CHOOSE(ABERTURAS!$N$21,ABERTURAS!$O$21-$AZ$3*$C$13,ABERTURAS!$O$21,-$AZ$3*($C$13-ABERTURAS!$O$21),$C$12-$AZ$3*($C$13-ABERTURAS!$O$21)),0))+$AZ$39)/$AZ$38 -> 0.86484248 | DT6: =((IF(AND(ABERTURAS!$K$21="OK",ABERTURAS!$E$21="FIJA"),ABERTURAS!$R$21+CHOOSE(ABERTURAS!$N$21,$AZ$4*$C$13,0,$AZ$4*($C$13-ABERTURAS!$O$21),$AZ$4*($C$13-ABERTURAS!$O$21)),0))+$AZ$40)/$AZ$38 -> 0.15864023 | DU6: =((IF(AND(ABERTURAS!$K$21="OK",ABERTURAS!$E$21="OPERABLE"),CHOOSE(ABERTURAS!$N$21,ABERTURAS!$O$21-$AZ$3*$C$13,ABERTURAS!$O$21,-$AZ$3*($C$13-ABERTURAS!$O$21),$C$12-$AZ$3*($C$13-ABERTURAS!$O$21)),0))+$AZ$39)/$AZ$38 -> 0.86484248 | DV6: =((IF(AND(ABERTURAS!$K$21="OK",ABERTURAS!$E$21="OPERABLE"),ABERTURAS!$R$21+CHOOSE(ABERTURAS!$N$21,$AZ$4*$C$13,0,$AZ$4*($C$13-ABERTURAS!$O$21),$AZ$4*($C$13-ABERTURAS!$O$21)),0))+$AZ$40)/$AZ$38 -> 0.15864023 | DW6: =((IF(AND(ABERTURAS!$K$22="OK",ABERTURAS!$E$22="FIJA"),CHOOSE(ABERTURAS!$N$22,ABERTURAS!$O$22-$AZ$3*$C$13,ABERTURAS!$O$22,-$AZ$3*($C$13-ABERTURAS!$O$22),$C$12-$AZ$3*($C$13-ABERTURAS!$O$22)),0))+$AZ$39)/$AZ$38 -> 0.86484248 | DX6: =((IF(AND(ABERTURAS!$K$22="OK",ABERTURAS!$E$22="FIJA"),ABERTURAS!$R$22+CHOOSE(ABERTURAS!$N$22,$AZ$4*$C$13,0,$AZ$4*($C$13-ABERTURAS!$O$22),$AZ$4*($C$13-ABERTURAS!$O$22)),0))+$AZ$40)/$AZ$38 -> 0.15864023 | DY6: =((IF(AND(ABERTURAS!$K$22="OK",ABERTURAS!$E$22="OPERABLE"),CHOOSE(ABERTURAS!$N$22,ABERTURAS!$O$22-$AZ$3*$C$13,ABERTURAS!$O$22,-$AZ$3*($C$13-ABERTURAS!$O$22),$C$12-$AZ$3*($C$13-ABERTURAS!$O$22)),0))+$AZ$39)/$AZ$38 -> 0.86484248 | DZ6: =((IF(AND(ABERTURAS!$K$22="OK",ABERTURAS!$E$22="OPERABLE"),ABERTURAS!$R$22+CHOOSE(ABERTURAS!$N$22,$AZ$4*$C$13,0,$AZ$4*($C$13-ABERTURAS!$O$22),$AZ$4*($C$13-ABERTURAS!$O$22)),0))+$AZ$40)/$AZ$38 -> 0.15864023 | EA6: =((IF(AND(ABERTURAS!$K$23="OK",ABERTURAS!$E$23="FIJA"),CHOOSE(ABERTURAS!$N$23,ABERTURAS!$O$23-$AZ$3*$C$13,ABERTURAS!$O$23,-$AZ$3*($C$13-ABERTURAS!$O$23),$C$12-$AZ$3*($C$13-ABERTURAS!$O$23)),0))+$AZ$39)/$AZ$38 -> 0.86484248 | EB6: =((IF(AND(ABERTURAS!$K$23="OK",ABERTURAS!$E$23="FIJA"),ABERTURAS!$R$23+CHOOSE(ABERTURAS!$N$23,$AZ$4*$C$13,0,$AZ$4*($C$13-ABERTURAS!$O$23),$AZ$4*($C$13-ABERTURAS!$O$23)),0))+$AZ$40)/$AZ$38 -> 0.15864023 | EC6: =((IF(AND(ABERTURAS!$K$23="OK",ABERTURAS!$E$23="OPERABLE"),CHOOSE(ABERTURAS!$N$23,ABERTURAS!$O$23-$AZ$3*$C$13,ABERTURAS!$O$23,-$AZ$3*($C$13-ABERTURAS!$O$23),$C$12-$AZ$3*($C$13-ABERTURAS!$O$23)),0))+$AZ$39)/$AZ$38 -> 0.86484248 | ED6: =((IF(AND(ABERTURAS!$K$23="OK",ABERTURAS!$E$23="OPERABLE"),ABERTURAS!$R$23+CHOOSE(ABERTURAS!$N$23,$AZ$4*$C$13,0,$AZ$4*($C$13-ABERTURAS!$O$23),$AZ$4*($C$13-ABERTURAS!$O$23)),0))+$AZ$40)/$AZ$38 -> 0.15864023 | EE6: =((IF(AND(ABERTURAS!$K$24="OK",ABERTURAS!$E$24="FIJA"),CHOOSE(ABERTURAS!$N$24,ABERTURAS!$O$24-$AZ$3*$C$13,ABERTURAS!$O$24,-$AZ$3*($C$13-ABERTURAS!$O$24),$C$12-$AZ$3*($C$13-ABERTURAS!$O$24)),0))+$AZ$39)/$AZ$38 -> 0.86484248 | EF6: =((IF(AND(ABERTURAS!$K$24="OK",ABERTURAS!$E$24="FIJA"),ABERTURAS!$R$24+CHOOSE(ABERTURAS!$N$24,$AZ$4*$C$13,0,$AZ$4*($C$13-ABERTURAS!$O$24),$AZ$4*($C$13-ABERTURAS!$O$24)),0))+$AZ$40)/$AZ$38 -> 0.15864023 | EG6: =((IF(AND(ABERTURAS!$K$24="OK",ABERTURAS!$E$24="OPERABLE"),CHOOSE(ABERTURAS!$N$24,ABERTURAS!$O$24-$AZ$3*$C$13,ABERTURAS!$O$24,-$AZ$3*($C$13-ABERTURAS!$O$24),$C$12-$AZ$3*($C$13-ABERTURAS!$O$24)),0))+$AZ$39)/$AZ$38 -> 0.86484248 | EH6: =((IF(AND(ABERTURAS!$K$24="OK",ABERTURAS!$E$24="OPERABLE"),ABERTURAS!$R$24+CHOOSE(ABERTURAS!$N$24,$AZ$4*$C$13,0,$AZ$4*($C$13-ABERTURAS!$O$24),$AZ$4*($C$13-ABERTURAS!$O$24)),0))+$AZ$40)/$AZ$38 -> 0.15864023 | EI6: =((IF(AND(ABERTURAS!$K$25="OK",ABERTURAS!$E$25="FIJA"),CHOOSE(ABERTURAS!$N$25,ABERTURAS!$O$25-$AZ$3*$C$13,ABERTURAS!$O$25,-$AZ$3*($C$13-ABERTURAS!$O$25),$C$12-$AZ$3*($C$13-ABERTURAS!$O$25)),0))+$AZ$39)/$AZ$38 -> 0.86484248 | EJ6: =((IF(AND(ABERTURAS!$K$25="OK",ABERTURAS!$E$25="FIJA"),ABERTURAS!$R$25+CHOOSE(ABERTURAS!$N$25,$AZ$4*$C$13,0,$AZ$4*($C$13-ABERTURAS!$O$25),$AZ$4*($C$13-ABERTURAS!$O$25)),0))+$AZ$40)/$AZ$38 -> 0.15864023 | EK6: =((IF(AND(ABERTURAS!$K$25="OK",ABERTURAS!$E$25="OPERABLE"),CHOOSE(ABERTURAS!$N$25,ABERTURAS!$O$25-$AZ$3*$C$13,ABERTURAS!$O$25,-$AZ$3*($C$13-ABERTURAS!$O$25),$C$12-$AZ$3*($C$13-ABERTURAS!$O$25)),0))+$AZ$39)/$AZ$38 -> 0.86484248 | EL6: =((IF(AND(ABERTURAS!$K$25="OK",ABERTURAS!$E$25="OPERABLE"),ABERTURAS!$R$25+CHOOSE(ABERTURAS!$N$25,$AZ$4*$C$13,0,$AZ$4*($C$13-ABERTURAS!$O$25),$AZ$4*($C$13-ABERTURAS!$O$25)),0))+$AZ$40)/$AZ$38 -> 0.15864023 | EM6: =((IF(AND(ABERTURAS!$K$26="OK",ABERTURAS!$E$26="FIJA"),CHOOSE(ABERTURAS!$N$26,ABERTURAS!$O$26-$AZ$3*$C$13,ABERTURAS!$O$26,-$AZ$3*($C$13-ABERTURAS!$O$26),$C$12-$AZ$3*($C$13-ABERTURAS!$O$26)),0))+$AZ$39)/$AZ$38 -> 0.86484248 | EN6: =((IF(AND(ABERTURAS!$K$26="OK",ABERTURAS!$E$26="FIJA"),ABERTURAS!$R$26+CHOOSE(ABERTURAS!$N$26,$AZ$4*$C$13,0,$AZ$4*($C$13-ABERTURAS!$O$26),$AZ$4*($C$13-ABERTURAS!$O$26)),0))+$AZ$40)/$AZ$38 -> 0.15864023 | EO6: =((IF(AND(ABERTURAS!$K$26="OK",ABERTURAS!$E$26="OPERABLE"),CHOOSE(ABERTURAS!$N$26,ABERTURAS!$O$26-$AZ$3*$C$13,ABERTURAS!$O$26,-$AZ$3*($C$13-ABERTURAS!$O$26),$C$12-$AZ$3*($C$13-ABERTURAS!$O$26)),0))+$AZ$39)/$AZ$38 -> 0.86484248 | EP6: =((IF(AND(ABERTURAS!$K$26="OK",ABERTURAS!$E$26="OPERABLE"),ABERTURAS!$R$26+CHOOSE(ABERTURAS!$N$26,$AZ$4*$C$13,0,$AZ$4*($C$13-ABERTURAS!$O$26),$AZ$4*($C$13-ABERTURAS!$O$26)),0))+$AZ$40)/$AZ$38 -> 0.15864023
B7: Proyecto | C7: HANGAR NOSE-DOCK H5-H6 | E7: CAPTURA. Sólo para identificar la corrida. | F7: — | AA7: =$C$23*4/8 -> 8 | AB7: =IF($C$14="PLANO",$C$17,IF($C$14="DOS AGUAS",$C$17+($C$18-$C$17)*(1-ABS(2*($AA$7)/$C$23-1)),IF($C$14="UN AGUA",IF(N($C$25)=0,$C$18-($C$18-$C$17)*($AA$7)/$C$23,$C$17+($C$18-$C$17)*($AA$7)/$C$23),$C$17+4*($C$18-$C$17)*($AA$7)/$C$23*(1-($AA$7)/$C$23)))) -> 10.22 | AE7: =ABERTURAS!$D$51*6/8 -> 7.56 | AF7: =IF(ABERTURAS!$E$51="SÍ",$AB$9,ABERTURAS!$F$51) -> 10.62 | AG7: =((($AZ$5+$AE7*($C$12-2*$AZ$5)/$C$12)-$AZ$3*$C$13)+$AZ$39)/$AZ$38 -> 0.89694824 | AH7: =((IF($AF7>0,$AF7-$AZ$5,0)+$AZ$4*$C$13)+$AZ$40)/$AZ$38 -> 0.84135977 | AI7: =ABERTURAS!$D$52*6/8 -> 7.56 | AJ7: =IF(ABERTURAS!$E$52="SÍ",$AB$9,ABERTURAS!$F$52) -> 9.82 | AK7: =((($AZ$5+$AI7*($C$12-2*$AZ$5)/$C$12))+$AZ$39)/$AZ$38 -> 1.2142287 | AL7: =((IF($AJ7>0,$AJ7-$AZ$5,0))+$AZ$40)/$AZ$38 -> 0.60717658 | AM7: =ABERTURAS!$D$53*6/8 -> 12 | AN7: =IF(ABERTURAS!$E$53="SÍ",$AB$9,ABERTURAS!$F$53) -> 10.02 | AO7: =((-$AZ$3*($C$13-($AZ$5+$AM7*($C$13-2*$AZ$5)/$C$13)))+$AZ$39)/$AZ$38 -> 0.78234956 | AP7: =((IF($AN7>0,$AN7-$AZ$5,0)+$AZ$4*($C$13-($AZ$5+$AM7*($C$13-2*$AZ$5)/$C$13)))+$AZ$40)/$AZ$38 -> 0.6676865 | AQ7: =ABERTURAS!$D$54*6/8 -> 12 | AR7: =IF(ABERTURAS!$E$54="SÍ",$AB$9,ABERTURAS!$F$54) -> 10.02 | AS7: =(($C$12-$AZ$3*($C$13-($AZ$5+$AQ7*($C$13-2*$AZ$5)/$C$13)))+$AZ$39)/$AZ$38 -> 1.2582702 | AT7: =((IF($AR7>0,$AR7-$AZ$5,0)+$AZ$4*($C$13-($AZ$5+$AQ7*($C$13-2*$AZ$5)/$C$13)))+$AZ$40)/$AZ$38 -> 0.6676865 | AU7: =((IF($AC$3="Z",0,$AA$7)-$AZ$3*($C$13-IF($AC$3="Z",$AA$7,0)))+$AZ$39)/$AZ$38 -> 0.70620225 | AV7: =(($AB$7+$AZ$4*($C$13-IF($AC$3="Z",$AA$7,0)))+$AZ$40)/$AZ$38 -> 0.73937677 | AY7: x' máx nave | AZ7: =$C$12 -> 10.08 | BA7: =BA4-($AZ$11/$AZ$38)*((BA4-BA3)*$AZ$13+(BB4-BB3)*$AZ$14)/SQRT((BA4-BA3)^2+(BB4-BB3)^2) -> 0.79855585 | BB7: =BB4-($AZ$11/$AZ$38)*(-(BA4-BA3)*$AZ$14+(BB4-BB3)*$AZ$13)/SQRT((BA4-BA3)^2+(BB4-BB3)^2) -> 0.8658722 | BC7: =BC4-($AZ$11/$AZ$38)*((BC4-BC3)*$AZ$13+(BD4-BD3)*$AZ$14)/SQRT((BC4-BC3)^2+(BD4-BD3)^2) -> 1.0897693 | BD7: =BD4-($AZ$11/$AZ$38)*(-(BC4-BC3)*$AZ$14+(BD4-BD3)*$AZ$13)/SQRT((BC4-BC3)^2+(BD4-BD3)^2) -> 0.1341278 | BE7: =BE4-($AZ$11/$AZ$38)*((BE4-BE3)*$AZ$13+(BF4-BF3)*$AZ$14)/SQRT((BE4-BE3)^2+(BF4-BF3)^2) -> 0.67965328 | BF7: =BF4-($AZ$11/$AZ$38)*(-(BE4-BE3)*$AZ$14+(BF4-BF3)*$AZ$13)/SQRT((BE4-BE3)^2+(BF4-BF3)^2) -> 0.24872925 | BG7: =BG4-($AZ$11/$AZ$38)*((BG4-BG3)*$AZ$13+(BH4-BH3)*$AZ$14)/SQRT((BG4-BG3)^2+(BH4-BH3)^2) -> 1.2086719 | BH7: =BH4-($AZ$11/$AZ$38)*(-(BG4-BG3)*$AZ$14+(BH4-BH3)*$AZ$13)/SQRT((BG4-BG3)^2+(BH4-BH3)^2) -> 0.73238501 | BI7: =BI4-($AZ$11/$AZ$38)*((BI4-BI3)*$AZ$13+(BJ4-BJ3)*$AZ$14)/SQRT((BI4-BI3)^2+(BJ4-BJ3)^2) -> 1.5462791 | BJ7: =BJ4-($AZ$11/$AZ$38)*(-(BI4-BI3)*$AZ$14+(BJ4-BJ3)*$AZ$13)/SQRT((BI4-BI3)^2+(BJ4-BJ3)^2) -> 0.25099383 | BK7: =BK4-($AZ$11/$AZ$38)*((BK4-BK3)*$AZ$13+(BL4-BL3)*$AZ$14)/SQRT((BK4-BK3)^2+(BL4-BL3)^2) -> 1.4863699 | BL7: =BL4-($AZ$11/$AZ$38)*(-(BK4-BK3)*$AZ$14+(BL4-BL3)*$AZ$13)/SQRT((BK4-BK3)^2+(BL4-BL3)^2) -> 0.28483602 | BM7: =BM4-($AZ$11/$AZ$38)*((BM4-BM3)*$AZ$13+(BN4-BN3)*$AZ$14)/SQRT((BM4-BM3)^2+(BN4-BN3)^2) -> 1.5461204 | BN7: =BN4-($AZ$11/$AZ$38)*(-(BM4-BM3)*$AZ$14+(BN4-BN3)*$AZ$13)/SQRT((BM4-BM3)^2+(BN4-BN3)^2) -> 0.22436903 | BO7: =((IF(AND(ABERTURAS!$K$7="OK",ABERTURAS!$E$7="FIJA"),CHOOSE(ABERTURAS!$N$7,ABERTURAS!$O$7-$AZ$3*$C$13,ABERTURAS!$O$7,-$AZ$3*($C$13-ABERTURAS!$O$7),$C$12-$AZ$3*($C$13-ABERTURAS!$O$7)),0))+$AZ$39)/$AZ$38 -> 0.86484248 | BP7: =((IF(AND(ABERTURAS!$K$7="OK",ABERTURAS!$E$7="FIJA"),ABERTURAS!$Q$7+CHOOSE(ABERTURAS!$N$7,$AZ$4*$C$13,0,$AZ$4*($C$13-ABERTURAS!$O$7),$AZ$4*($C$13-ABERTURAS!$O$7)),0))+$AZ$40)/$AZ$38 -> 0.15864023 | BQ7: =((IF(AND(ABERTURAS!$K$7="OK",ABERTURAS!$E$7="OPERABLE"),CHOOSE(ABERTURAS!$N$7,ABERTURAS!$O$7-$AZ$3*$C$13,ABERTURAS!$O$7,-$AZ$3*($C$13-ABERTURAS!$O$7),$C$12-$AZ$3*($C$13-ABERTURAS!$O$7)),0))+$AZ$39)/$AZ$38 -> 0.57789724 | BR7: =((IF(AND(ABERTURAS!$K$7="OK",ABERTURAS!$E$7="OPERABLE"),ABERTURAS!$Q$7+CHOOSE(ABERTURAS!$N$7,$AZ$4*$C$13,0,$AZ$4*($C$13-ABERTURAS!$O$7),$AZ$4*($C$13-ABERTURAS!$O$7)),0))+$AZ$40)/$AZ$38 -> 0.35505194 | BS7: =((IF(AND(ABERTURAS!$K$8="OK",ABERTURAS!$E$8="FIJA"),CHOOSE(ABERTURAS!$N$8,ABERTURAS!$O$8-$AZ$3*$C$13,ABERTURAS!$O$8,-$AZ$3*($C$13-ABERTURAS!$O$8),$C$12-$AZ$3*($C$13-ABERTURAS!$O$8)),0))+$AZ$39)/$AZ$38 -> 0.86484248 | BT7: =((IF(AND(ABERTURAS!$K$8="OK",ABERTURAS!$E$8="FIJA"),ABERTURAS!$Q$8+CHOOSE(ABERTURAS!$N$8,$AZ$4*$C$13,0,$AZ$4*($C$13-ABERTURAS!$O$8),$AZ$4*($C$13-ABERTURAS!$O$8)),0))+$AZ$40)/$AZ$38 -> 0.15864023 | BU7: =((IF(AND(ABERTURAS!$K$8="OK",ABERTURAS!$E$8="OPERABLE"),CHOOSE(ABERTURAS!$N$8,ABERTURAS!$O$8-$AZ$3*$C$13,ABERTURAS!$O$8,-$AZ$3*($C$13-ABERTURAS!$O$8),$C$12-$AZ$3*($C$13-ABERTURAS!$O$8)),0))+$AZ$39)/$AZ$38 -> 0.6649794 | BV7: =((IF(AND(ABERTURAS!$K$8="OK",ABERTURAS!$E$8="OPERABLE"),ABERTURAS!$Q$8+CHOOSE(ABERTURAS!$N$8,$AZ$4*$C$13,0,$AZ$4*($C$13-ABERTURAS!$O$8),$AZ$4*($C$13-ABERTURAS!$O$8)),0))+$AZ$40)/$AZ$38 -> 0.35505194 | BW7: =((IF(AND(ABERTURAS!$K$9="OK",ABERTURAS!$E$9="FIJA"),CHOOSE(ABERTURAS!$N$9,ABERTURAS!$O$9-$AZ$3*$C$13,ABERTURAS!$O$9,-$AZ$3*($C$13-ABERTURAS!$O$9),$C$12-$AZ$3*($C$13-ABERTURAS!$O$9)),0))+$AZ$39)/$AZ$38 -> 0.86484248 | BX7: =((IF(AND(ABERTURAS!$K$9="OK",ABERTURAS!$E$9="FIJA"),ABERTURAS!$Q$9+CHOOSE(ABERTURAS!$N$9,$AZ$4*$C$13,0,$AZ$4*($C$13-ABERTURAS!$O$9),$AZ$4*($C$13-ABERTURAS!$O$9)),0))+$AZ$40)/$AZ$38 -> 0.15864023 | BY7: =((IF(AND(ABERTURAS!$K$9="OK",ABERTURAS!$E$9="OPERABLE"),CHOOSE(ABERTURAS!$N$9,ABERTURAS!$O$9-$AZ$3*$C$13,ABERTURAS!$O$9,-$AZ$3*($C$13-ABERTURAS!$O$9),$C$12-$AZ$3*($C$13-ABERTURAS!$O$9)),0))+$AZ$39)/$AZ$38 -> 0.86484248 | BZ7: =((IF(AND(ABERTURAS!$K$9="OK",ABERTURAS!$E$9="OPERABLE"),ABERTURAS!$Q$9+CHOOSE(ABERTURAS!$N$9,$AZ$4*$C$13,0,$AZ$4*($C$13-ABERTURAS!$O$9),$AZ$4*($C$13-ABERTURAS!$O$9)),0))+$AZ$40)/$AZ$38 -> 0.15864023 | CA7: =((IF(AND(ABERTURAS!$K$10="OK",ABERTURAS!$E$10="FIJA"),CHOOSE(ABERTURAS!$N$10,ABERTURAS!$O$10-$AZ$3*$C$13,ABERTURAS!$O$10,-$AZ$3*($C$13-ABERTURAS!$O$10),$C$12-$AZ$3*($C$13-ABERTURAS!$O$10)),0))+$AZ$39)/$AZ$38 -> 0.86484248 | CB7: =((IF(AND(ABERTURAS!$K$10="OK",ABERTURAS!$E$10="FIJA"),ABERTURAS!$Q$10+CHOOSE(ABERTURAS!$N$10,$AZ$4*$C$13,0,$AZ$4*($C$13-ABERTURAS!$O$10),$AZ$4*($C$13-ABERTURAS!$O$10)),0))+$AZ$40)/$AZ$38 -> 0.15864023 | CC7: =((IF(AND(ABERTURAS!$K$10="OK",ABERTURAS!$E$10="OPERABLE"),CHOOSE(ABERTURAS!$N$10,ABERTURAS!$O$10-$AZ$3*$C$13,ABERTURAS!$O$10,-$AZ$3*($C$13-ABERTURAS!$O$10),$C$12-$AZ$3*($C$13-ABERTURAS!$O$10)),0))+$AZ$39)/$AZ$38 -> 0.86484248 | CD7: =((IF(AND(ABERTURAS!$K$10="OK",ABERTURAS!$E$10="OPERABLE"),ABERTURAS!$Q$10+CHOOSE(ABERTURAS!$N$10,$AZ$4*$C$13,0,$AZ$4*($C$13-ABERTURAS!$O$10),$AZ$4*($C$13-ABERTURAS!$O$10)),0))+$AZ$40)/$AZ$38 -> 0.15864023 | CE7: =((IF(AND(ABERTURAS!$K$11="OK",ABERTURAS!$E$11="FIJA"),CHOOSE(ABERTURAS!$N$11,ABERTURAS!$O$11-$AZ$3*$C$13,ABERTURAS!$O$11,-$AZ$3*($C$13-ABERTURAS!$O$11),$C$12-$AZ$3*($C$13-ABERTURAS!$O$11)),0))+$AZ$39)/$AZ$38 -> 0.86484248 | CF7: =((IF(AND(ABERTURAS!$K$11="OK",ABERTURAS!$E$11="FIJA"),ABERTURAS!$Q$11+CHOOSE(ABERTURAS!$N$11,$AZ$4*$C$13,0,$AZ$4*($C$13-ABERTURAS!$O$11),$AZ$4*($C$13-ABERTURAS!$O$11)),0))+$AZ$40)/$AZ$38 -> 0.15864023 | CG7: =((IF(AND(ABERTURAS!$K$11="OK",ABERTURAS!$E$11="OPERABLE"),CHOOSE(ABERTURAS!$N$11,ABERTURAS!$O$11-$AZ$3*$C$13,ABERTURAS!$O$11,-$AZ$3*($C$13-ABERTURAS!$O$11),$C$12-$AZ$3*($C$13-ABERTURAS!$O$11)),0))+$AZ$39)/$AZ$38 -> 0.86484248 | CH7: =((IF(AND(ABERTURAS!$K$11="OK",ABERTURAS!$E$11="OPERABLE"),ABERTURAS!$Q$11+CHOOSE(ABERTURAS!$N$11,$AZ$4*$C$13,0,$AZ$4*($C$13-ABERTURAS!$O$11),$AZ$4*($C$13-ABERTURAS!$O$11)),0))+$AZ$40)/$AZ$38 -> 0.15864023 | CI7: =((IF(AND(ABERTURAS!$K$12="OK",ABERTURAS!$E$12="FIJA"),CHOOSE(ABERTURAS!$N$12,ABERTURAS!$O$12-$AZ$3*$C$13,ABERTURAS!$O$12,-$AZ$3*($C$13-ABERTURAS!$O$12),$C$12-$AZ$3*($C$13-ABERTURAS!$O$12)),0))+$AZ$39)/$AZ$38 -> 0.86484248 | CJ7: =((IF(AND(ABERTURAS!$K$12="OK",ABERTURAS!$E$12="FIJA"),ABERTURAS!$Q$12+CHOOSE(ABERTURAS!$N$12,$AZ$4*$C$13,0,$AZ$4*($C$13-ABERTURAS!$O$12),$AZ$4*($C$13-ABERTURAS!$O$12)),0))+$AZ$40)/$AZ$38 -> 0.15864023 | CK7: =((IF(AND(ABERTURAS!$K$12="OK",ABERTURAS!$E$12="OPERABLE"),CHOOSE(ABERTURAS!$N$12,ABERTURAS!$O$12-$AZ$3*$C$13,ABERTURAS!$O$12,-$AZ$3*($C$13-ABERTURAS!$O$12),$C$12-$AZ$3*($C$13-ABERTURAS!$O$12)),0))+$AZ$39)/$AZ$38 -> 0.86484248 | CL7: =((IF(AND(ABERTURAS!$K$12="OK",ABERTURAS!$E$12="OPERABLE"),ABERTURAS!$Q$12+CHOOSE(ABERTURAS!$N$12,$AZ$4*$C$13,0,$AZ$4*($C$13-ABERTURAS!$O$12),$AZ$4*($C$13-ABERTURAS!$O$12)),0))+$AZ$40)/$AZ$38 -> 0.15864023 | CM7: =((IF(AND(ABERTURAS!$K$13="OK",ABERTURAS!$E$13="FIJA"),CHOOSE(ABERTURAS!$N$13,ABERTURAS!$O$13-$AZ$3*$C$13,ABERTURAS!$O$13,-$AZ$3*($C$13-ABERTURAS!$O$13),$C$12-$AZ$3*($C$13-ABERTURAS!$O$13)),0))+$AZ$39)/$AZ$38 -> 0.86484248 | CN7: =((IF(AND(ABERTURAS!$K$13="OK",ABERTURAS!$E$13="FIJA"),ABERTURAS!$Q$13+CHOOSE(ABERTURAS!$N$13,$AZ$4*$C$13,0,$AZ$4*($C$13-ABERTURAS!$O$13),$AZ$4*($C$13-ABERTURAS!$O$13)),0))+$AZ$40)/$AZ$38 -> 0.15864023 | CO7: =((IF(AND(ABERTURAS!$K$13="OK",ABERTURAS!$E$13="OPERABLE"),CHOOSE(ABERTURAS!$N$13,ABERTURAS!$O$13-$AZ$3*$C$13,ABERTURAS!$O$13,-$AZ$3*($C$13-ABERTURAS!$O$13),$C$12-$AZ$3*($C$13-ABERTURAS!$O$13)),0))+$AZ$39)/$AZ$38 -> 0.86484248 | CP7: =((IF(AND(ABERTURAS!$K$13="OK",ABERTURAS!$E$13="OPERABLE"),ABERTURAS!$Q$13+CHOOSE(ABERTURAS!$N$13,$AZ$4*$C$13,0,$AZ$4*($C$13-ABERTURAS!$O$13),$AZ$4*($C$13-ABERTURAS!$O$13)),0))+$AZ$40)/$AZ$38 -> 0.15864023 | CQ7: =((IF(AND(ABERTURAS!$K$14="OK",ABERTURAS!$E$14="FIJA"),CHOOSE(ABERTURAS!$N$14,ABERTURAS!$O$14-$AZ$3*$C$13,ABERTURAS!$O$14,-$AZ$3*($C$13-ABERTURAS!$O$14),$C$12-$AZ$3*($C$13-ABERTURAS!$O$14)),0))+$AZ$39)/$AZ$38 -> 0.86484248 | CR7: =((IF(AND(ABERTURAS!$K$14="OK",ABERTURAS!$E$14="FIJA"),ABERTURAS!$Q$14+CHOOSE(ABERTURAS!$N$14,$AZ$4*$C$13,0,$AZ$4*($C$13-ABERTURAS!$O$14),$AZ$4*($C$13-ABERTURAS!$O$14)),0))+$AZ$40)/$AZ$38 -> 0.15864023 | CS7: =((IF(AND(ABERTURAS!$K$14="OK",ABERTURAS!$E$14="OPERABLE"),CHOOSE(ABERTURAS!$N$14,ABERTURAS!$O$14-$AZ$3*$C$13,ABERTURAS!$O$14,-$AZ$3*($C$13-ABERTURAS!$O$14),$C$12-$AZ$3*($C$13-ABERTURAS!$O$14)),0))+$AZ$39)/$AZ$38 -> 0.86484248 | CT7: =((IF(AND(ABERTURAS!$K$14="OK",ABERTURAS!$E$14="OPERABLE"),ABERTURAS!$Q$14+CHOOSE(ABERTURAS!$N$14,$AZ$4*$C$13,0,$AZ$4*($C$13-ABERTURAS!$O$14),$AZ$4*($C$13-ABERTURAS!$O$14)),0))+$AZ$40)/$AZ$38 -> 0.15864023 | CU7: =((IF(AND(ABERTURAS!$K$15="OK",ABERTURAS!$E$15="FIJA"),CHOOSE(ABERTURAS!$N$15,ABERTURAS!$O$15-$AZ$3*$C$13,ABERTURAS!$O$15,-$AZ$3*($C$13-ABERTURAS!$O$15),$C$12-$AZ$3*($C$13-ABERTURAS!$O$15)),0))+$AZ$39)/$AZ$38 -> 0.86484248 | CV7: =((IF(AND(ABERTURAS!$K$15="OK",ABERTURAS!$E$15="FIJA"),ABERTURAS!$Q$15+CHOOSE(ABERTURAS!$N$15,$AZ$4*$C$13,0,$AZ$4*($C$13-ABERTURAS!$O$15),$AZ$4*($C$13-ABERTURAS!$O$15)),0))+$AZ$40)/$AZ$38 -> 0.15864023 | CW7: =((IF(AND(ABERTURAS!$K$15="OK",ABERTURAS!$E$15="OPERABLE"),CHOOSE(ABERTURAS!$N$15,ABERTURAS!$O$15-$AZ$3*$C$13,ABERTURAS!$O$15,-$AZ$3*($C$13-ABERTURAS!$O$15),$C$12-$AZ$3*($C$13-ABERTURAS!$O$15)),0))+$AZ$39)/$AZ$38 -> 0.86484248 | CX7: =((IF(AND(ABERTURAS!$K$15="OK",ABERTURAS!$E$15="OPERABLE"),ABERTURAS!$Q$15+CHOOSE(ABERTURAS!$N$15,$AZ$4*$C$13,0,$AZ$4*($C$13-ABERTURAS!$O$15),$AZ$4*($C$13-ABERTURAS!$O$15)),0))+$AZ$40)/$AZ$38 -> 0.15864023 | CY7: =((IF(AND(ABERTURAS!$K$16="OK",ABERTURAS!$E$16="FIJA"),CHOOSE(ABERTURAS!$N$16,ABERTURAS!$O$16-$AZ$3*$C$13,ABERTURAS!$O$16,-$AZ$3*($C$13-ABERTURAS!$O$16),$C$12-$AZ$3*($C$13-ABERTURAS!$O$16)),0))+$AZ$39)/$AZ$38 -> 0.86484248 | CZ7: =((IF(AND(ABERTURAS!$K$16="OK",ABERTURAS!$E$16="FIJA"),ABERTURAS!$Q$16+CHOOSE(ABERTURAS!$N$16,$AZ$4*$C$13,0,$AZ$4*($C$13-ABERTURAS!$O$16),$AZ$4*($C$13-ABERTURAS!$O$16)),0))+$AZ$40)/$AZ$38 -> 0.15864023 | DA7: =((IF(AND(ABERTURAS!$K$16="OK",ABERTURAS!$E$16="OPERABLE"),CHOOSE(ABERTURAS!$N$16,ABERTURAS!$O$16-$AZ$3*$C$13,ABERTURAS!$O$16,-$AZ$3*($C$13-ABERTURAS!$O$16),$C$12-$AZ$3*($C$13-ABERTURAS!$O$16)),0))+$AZ$39)/$AZ$38 -> 0.86484248 | DB7: =((IF(AND(ABERTURAS!$K$16="OK",ABERTURAS!$E$16="OPERABLE"),ABERTURAS!$Q$16+CHOOSE(ABERTURAS!$N$16,$AZ$4*$C$13,0,$AZ$4*($C$13-ABERTURAS!$O$16),$AZ$4*($C$13-ABERTURAS!$O$16)),0))+$AZ$40)/$AZ$38 -> 0.15864023 | DC7: =((IF(AND(ABERTURAS!$K$17="OK",ABERTURAS!$E$17="FIJA"),CHOOSE(ABERTURAS!$N$17,ABERTURAS!$O$17-$AZ$3*$C$13,ABERTURAS!$O$17,-$AZ$3*($C$13-ABERTURAS!$O$17),$C$12-$AZ$3*($C$13-ABERTURAS!$O$17)),0))+$AZ$39)/$AZ$38 -> 0.86484248 | DD7: =((IF(AND(ABERTURAS!$K$17="OK",ABERTURAS!$E$17="FIJA"),ABERTURAS!$Q$17+CHOOSE(ABERTURAS!$N$17,$AZ$4*$C$13,0,$AZ$4*($C$13-ABERTURAS!$O$17),$AZ$4*($C$13-ABERTURAS!$O$17)),0))+$AZ$40)/$AZ$38 -> 0.15864023 | DE7: =((IF(AND(ABERTURAS!$K$17="OK",ABERTURAS!$E$17="OPERABLE"),CHOOSE(ABERTURAS!$N$17,ABERTURAS!$O$17-$AZ$3*$C$13,ABERTURAS!$O$17,-$AZ$3*($C$13-ABERTURAS!$O$17),$C$12-$AZ$3*($C$13-ABERTURAS!$O$17)),0))+$AZ$39)/$AZ$38 -> 0.86484248 | DF7: =((IF(AND(ABERTURAS!$K$17="OK",ABERTURAS!$E$17="OPERABLE"),ABERTURAS!$Q$17+CHOOSE(ABERTURAS!$N$17,$AZ$4*$C$13,0,$AZ$4*($C$13-ABERTURAS!$O$17),$AZ$4*($C$13-ABERTURAS!$O$17)),0))+$AZ$40)/$AZ$38 -> 0.15864023 | DG7: =((IF(AND(ABERTURAS!$K$18="OK",ABERTURAS!$E$18="FIJA"),CHOOSE(ABERTURAS!$N$18,ABERTURAS!$O$18-$AZ$3*$C$13,ABERTURAS!$O$18,-$AZ$3*($C$13-ABERTURAS!$O$18),$C$12-$AZ$3*($C$13-ABERTURAS!$O$18)),0))+$AZ$39)/$AZ$38 -> 0.86484248 | DH7: =((IF(AND(ABERTURAS!$K$18="OK",ABERTURAS!$E$18="FIJA"),ABERTURAS!$Q$18+CHOOSE(ABERTURAS!$N$18,$AZ$4*$C$13,0,$AZ$4*($C$13-ABERTURAS!$O$18),$AZ$4*($C$13-ABERTURAS!$O$18)),0))+$AZ$40)/$AZ$38 -> 0.15864023 | DI7: =((IF(AND(ABERTURAS!$K$18="OK",ABERTURAS!$E$18="OPERABLE"),CHOOSE(ABERTURAS!$N$18,ABERTURAS!$O$18-$AZ$3*$C$13,ABERTURAS!$O$18,-$AZ$3*($C$13-ABERTURAS!$O$18),$C$12-$AZ$3*($C$13-ABERTURAS!$O$18)),0))+$AZ$39)/$AZ$38 -> 0.86484248 | DJ7: =((IF(AND(ABERTURAS!$K$18="OK",ABERTURAS!$E$18="OPERABLE"),ABERTURAS!$Q$18+CHOOSE(ABERTURAS!$N$18,$AZ$4*$C$13,0,$AZ$4*($C$13-ABERTURAS!$O$18),$AZ$4*($C$13-ABERTURAS!$O$18)),0))+$AZ$40)/$AZ$38 -> 0.15864023 | DK7: =((IF(AND(ABERTURAS!$K$19="OK",ABERTURAS!$E$19="FIJA"),CHOOSE(ABERTURAS!$N$19,ABERTURAS!$O$19-$AZ$3*$C$13,ABERTURAS!$O$19,-$AZ$3*($C$13-ABERTURAS!$O$19),$C$12-$AZ$3*($C$13-ABERTURAS!$O$19)),0))+$AZ$39)/$AZ$38 -> 0.86484248 | DL7: =((IF(AND(ABERTURAS!$K$19="OK",ABERTURAS!$E$19="FIJA"),ABERTURAS!$Q$19+CHOOSE(ABERTURAS!$N$19,$AZ$4*$C$13,0,$AZ$4*($C$13-ABERTURAS!$O$19),$AZ$4*($C$13-ABERTURAS!$O$19)),0))+$AZ$40)/$AZ$38 -> 0.15864023 | DM7: =((IF(AND(ABERTURAS!$K$19="OK",ABERTURAS!$E$19="OPERABLE"),CHOOSE(ABERTURAS!$N$19,ABERTURAS!$O$19-$AZ$3*$C$13,ABERTURAS!$O$19,-$AZ$3*($C$13-ABERTURAS!$O$19),$C$12-$AZ$3*($C$13-ABERTURAS!$O$19)),0))+$AZ$39)/$AZ$38 -> 0.86484248 | DN7: =((IF(AND(ABERTURAS!$K$19="OK",ABERTURAS!$E$19="OPERABLE"),ABERTURAS!$Q$19+CHOOSE(ABERTURAS!$N$19,$AZ$4*$C$13,0,$AZ$4*($C$13-ABERTURAS!$O$19),$AZ$4*($C$13-ABERTURAS!$O$19)),0))+$AZ$40)/$AZ$38 -> 0.15864023 | DO7: =((IF(AND(ABERTURAS!$K$20="OK",ABERTURAS!$E$20="FIJA"),CHOOSE(ABERTURAS!$N$20,ABERTURAS!$O$20-$AZ$3*$C$13,ABERTURAS!$O$20,-$AZ$3*($C$13-ABERTURAS!$O$20),$C$12-$AZ$3*($C$13-ABERTURAS!$O$20)),0))+$AZ$39)/$AZ$38 -> 0.86484248 | DP7: =((IF(AND(ABERTURAS!$K$20="OK",ABERTURAS!$E$20="FIJA"),ABERTURAS!$Q$20+CHOOSE(ABERTURAS!$N$20,$AZ$4*$C$13,0,$AZ$4*($C$13-ABERTURAS!$O$20),$AZ$4*($C$13-ABERTURAS!$O$20)),0))+$AZ$40)/$AZ$38 -> 0.15864023 | DQ7: =((IF(AND(ABERTURAS!$K$20="OK",ABERTURAS!$E$20="OPERABLE"),CHOOSE(ABERTURAS!$N$20,ABERTURAS!$O$20-$AZ$3*$C$13,ABERTURAS!$O$20,-$AZ$3*($C$13-ABERTURAS!$O$20),$C$12-$AZ$3*($C$13-ABERTURAS!$O$20)),0))+$AZ$39)/$AZ$38 -> 0.86484248 | DR7: =((IF(AND(ABERTURAS!$K$20="OK",ABERTURAS!$E$20="OPERABLE"),ABERTURAS!$Q$20+CHOOSE(ABERTURAS!$N$20,$AZ$4*$C$13,0,$AZ$4*($C$13-ABERTURAS!$O$20),$AZ$4*($C$13-ABERTURAS!$O$20)),0))+$AZ$40)/$AZ$38 -> 0.15864023 | DS7: =((IF(AND(ABERTURAS!$K$21="OK",ABERTURAS!$E$21="FIJA"),CHOOSE(ABERTURAS!$N$21,ABERTURAS!$O$21-$AZ$3*$C$13,ABERTURAS!$O$21,-$AZ$3*($C$13-ABERTURAS!$O$21),$C$12-$AZ$3*($C$13-ABERTURAS!$O$21)),0))+$AZ$39)/$AZ$38 -> 0.86484248 | DT7: =((IF(AND(ABERTURAS!$K$21="OK",ABERTURAS!$E$21="FIJA"),ABERTURAS!$Q$21+CHOOSE(ABERTURAS!$N$21,$AZ$4*$C$13,0,$AZ$4*($C$13-ABERTURAS!$O$21),$AZ$4*($C$13-ABERTURAS!$O$21)),0))+$AZ$40)/$AZ$38 -> 0.15864023 | DU7: =((IF(AND(ABERTURAS!$K$21="OK",ABERTURAS!$E$21="OPERABLE"),CHOOSE(ABERTURAS!$N$21,ABERTURAS!$O$21-$AZ$3*$C$13,ABERTURAS!$O$21,-$AZ$3*($C$13-ABERTURAS!$O$21),$C$12-$AZ$3*($C$13-ABERTURAS!$O$21)),0))+$AZ$39)/$AZ$38 -> 0.86484248 | DV7: =((IF(AND(ABERTURAS!$K$21="OK",ABERTURAS!$E$21="OPERABLE"),ABERTURAS!$Q$21+CHOOSE(ABERTURAS!$N$21,$AZ$4*$C$13,0,$AZ$4*($C$13-ABERTURAS!$O$21),$AZ$4*($C$13-ABERTURAS!$O$21)),0))+$AZ$40)/$AZ$38 -> 0.15864023 | DW7: =((IF(AND(ABERTURAS!$K$22="OK",ABERTURAS!$E$22="FIJA"),CHOOSE(ABERTURAS!$N$22,ABERTURAS!$O$22-$AZ$3*$C$13,ABERTURAS!$O$22,-$AZ$3*($C$13-ABERTURAS!$O$22),$C$12-$AZ$3*($C$13-ABERTURAS!$O$22)),0))+$AZ$39)/$AZ$38 -> 0.86484248 | DX7: =((IF(AND(ABERTURAS!$K$22="OK",ABERTURAS!$E$22="FIJA"),ABERTURAS!$Q$22+CHOOSE(ABERTURAS!$N$22,$AZ$4*$C$13,0,$AZ$4*($C$13-ABERTURAS!$O$22),$AZ$4*($C$13-ABERTURAS!$O$22)),0))+$AZ$40)/$AZ$38 -> 0.15864023 | DY7: =((IF(AND(ABERTURAS!$K$22="OK",ABERTURAS!$E$22="OPERABLE"),CHOOSE(ABERTURAS!$N$22,ABERTURAS!$O$22-$AZ$3*$C$13,ABERTURAS!$O$22,-$AZ$3*($C$13-ABERTURAS!$O$22),$C$12-$AZ$3*($C$13-ABERTURAS!$O$22)),0))+$AZ$39)/$AZ$38 -> 0.86484248 | DZ7: =((IF(AND(ABERTURAS!$K$22="OK",ABERTURAS!$E$22="OPERABLE"),ABERTURAS!$Q$22+CHOOSE(ABERTURAS!$N$22,$AZ$4*$C$13,0,$AZ$4*($C$13-ABERTURAS!$O$22),$AZ$4*($C$13-ABERTURAS!$O$22)),0))+$AZ$40)/$AZ$38 -> 0.15864023 | EA7: =((IF(AND(ABERTURAS!$K$23="OK",ABERTURAS!$E$23="FIJA"),CHOOSE(ABERTURAS!$N$23,ABERTURAS!$O$23-$AZ$3*$C$13,ABERTURAS!$O$23,-$AZ$3*($C$13-ABERTURAS!$O$23),$C$12-$AZ$3*($C$13-ABERTURAS!$O$23)),0))+$AZ$39)/$AZ$38 -> 0.86484248 | EB7: =((IF(AND(ABERTURAS!$K$23="OK",ABERTURAS!$E$23="FIJA"),ABERTURAS!$Q$23+CHOOSE(ABERTURAS!$N$23,$AZ$4*$C$13,0,$AZ$4*($C$13-ABERTURAS!$O$23),$AZ$4*($C$13-ABERTURAS!$O$23)),0))+$AZ$40)/$AZ$38 -> 0.15864023 | EC7: =((IF(AND(ABERTURAS!$K$23="OK",ABERTURAS!$E$23="OPERABLE"),CHOOSE(ABERTURAS!$N$23,ABERTURAS!$O$23-$AZ$3*$C$13,ABERTURAS!$O$23,-$AZ$3*($C$13-ABERTURAS!$O$23),$C$12-$AZ$3*($C$13-ABERTURAS!$O$23)),0))+$AZ$39)/$AZ$38 -> 0.86484248 | ED7: =((IF(AND(ABERTURAS!$K$23="OK",ABERTURAS!$E$23="OPERABLE"),ABERTURAS!$Q$23+CHOOSE(ABERTURAS!$N$23,$AZ$4*$C$13,0,$AZ$4*($C$13-ABERTURAS!$O$23),$AZ$4*($C$13-ABERTURAS!$O$23)),0))+$AZ$40)/$AZ$38 -> 0.15864023 | EE7: =((IF(AND(ABERTURAS!$K$24="OK",ABERTURAS!$E$24="FIJA"),CHOOSE(ABERTURAS!$N$24,ABERTURAS!$O$24-$AZ$3*$C$13,ABERTURAS!$O$24,-$AZ$3*($C$13-ABERTURAS!$O$24),$C$12-$AZ$3*($C$13-ABERTURAS!$O$24)),0))+$AZ$39)/$AZ$38 -> 0.86484248 | EF7: =((IF(AND(ABERTURAS!$K$24="OK",ABERTURAS!$E$24="FIJA"),ABERTURAS!$Q$24+CHOOSE(ABERTURAS!$N$24,$AZ$4*$C$13,0,$AZ$4*($C$13-ABERTURAS!$O$24),$AZ$4*($C$13-ABERTURAS!$O$24)),0))+$AZ$40)/$AZ$38 -> 0.15864023 | EG7: =((IF(AND(ABERTURAS!$K$24="OK",ABERTURAS!$E$24="OPERABLE"),CHOOSE(ABERTURAS!$N$24,ABERTURAS!$O$24-$AZ$3*$C$13,ABERTURAS!$O$24,-$AZ$3*($C$13-ABERTURAS!$O$24),$C$12-$AZ$3*($C$13-ABERTURAS!$O$24)),0))+$AZ$39)/$AZ$38 -> 0.86484248 | EH7: =((IF(AND(ABERTURAS!$K$24="OK",ABERTURAS!$E$24="OPERABLE"),ABERTURAS!$Q$24+CHOOSE(ABERTURAS!$N$24,$AZ$4*$C$13,0,$AZ$4*($C$13-ABERTURAS!$O$24),$AZ$4*($C$13-ABERTURAS!$O$24)),0))+$AZ$40)/$AZ$38 -> 0.15864023 | EI7: =((IF(AND(ABERTURAS!$K$25="OK",ABERTURAS!$E$25="FIJA"),CHOOSE(ABERTURAS!$N$25,ABERTURAS!$O$25-$AZ$3*$C$13,ABERTURAS!$O$25,-$AZ$3*($C$13-ABERTURAS!$O$25),$C$12-$AZ$3*($C$13-ABERTURAS!$O$25)),0))+$AZ$39)/$AZ$38 -> 0.86484248 | EJ7: =((IF(AND(ABERTURAS!$K$25="OK",ABERTURAS!$E$25="FIJA"),ABERTURAS!$Q$25+CHOOSE(ABERTURAS!$N$25,$AZ$4*$C$13,0,$AZ$4*($C$13-ABERTURAS!$O$25),$AZ$4*($C$13-ABERTURAS!$O$25)),0))+$AZ$40)/$AZ$38 -> 0.15864023 | EK7: =((IF(AND(ABERTURAS!$K$25="OK",ABERTURAS!$E$25="OPERABLE"),CHOOSE(ABERTURAS!$N$25,ABERTURAS!$O$25-$AZ$3*$C$13,ABERTURAS!$O$25,-$AZ$3*($C$13-ABERTURAS!$O$25),$C$12-$AZ$3*($C$13-ABERTURAS!$O$25)),0))+$AZ$39)/$AZ$38 -> 0.86484248 | EL7: =((IF(AND(ABERTURAS!$K$25="OK",ABERTURAS!$E$25="OPERABLE"),ABERTURAS!$Q$25+CHOOSE(ABERTURAS!$N$25,$AZ$4*$C$13,0,$AZ$4*($C$13-ABERTURAS!$O$25),$AZ$4*($C$13-ABERTURAS!$O$25)),0))+$AZ$40)/$AZ$38 -> 0.15864023 | EM7: =((IF(AND(ABERTURAS!$K$26="OK",ABERTURAS!$E$26="FIJA"),CHOOSE(ABERTURAS!$N$26,ABERTURAS!$O$26-$AZ$3*$C$13,ABERTURAS!$O$26,-$AZ$3*($C$13-ABERTURAS!$O$26),$C$12-$AZ$3*($C$13-ABERTURAS!$O$26)),0))+$AZ$39)/$AZ$38 -> 0.86484248 | EN7: =((IF(AND(ABERTURAS!$K$26="OK",ABERTURAS!$E$26="FIJA"),ABERTURAS!$Q$26+CHOOSE(ABERTURAS!$N$26,$AZ$4*$C$13,0,$AZ$4*($C$13-ABERTURAS!$O$26),$AZ$4*($C$13-ABERTURAS!$O$26)),0))+$AZ$40)/$AZ$38 -> 0.15864023 | EO7: =((IF(AND(ABERTURAS!$K$26="OK",ABERTURAS!$E$26="OPERABLE"),CHOOSE(ABERTURAS!$N$26,ABERTURAS!$O$26-$AZ$3*$C$13,ABERTURAS!$O$26,-$AZ$3*($C$13-ABERTURAS!$O$26),$C$12-$AZ$3*($C$13-ABERTURAS!$O$26)),0))+$AZ$39)/$AZ$38 -> 0.86484248 | EP7: =((IF(AND(ABERTURAS!$K$26="OK",ABERTURAS!$E$26="OPERABLE"),ABERTURAS!$Q$26+CHOOSE(ABERTURAS!$N$26,$AZ$4*$C$13,0,$AZ$4*($C$13-ABERTURAS!$O$26),$AZ$4*($C$13-ABERTURAS!$O$26)),0))+$AZ$40)/$AZ$38 -> 0.15864023
B8: Ubicación | C8: Departamento de LA PAZ, EL SALVADOR | E8: CAPTURA. | F8: — | AA8: =$C$23*5/8 -> 10 | AB8: =IF($C$14="PLANO",$C$17,IF($C$14="DOS AGUAS",$C$17+($C$18-$C$17)*(1-ABS(2*($AA$8)/$C$23-1)),IF($C$14="UN AGUA",IF(N($C$25)=0,$C$18-($C$18-$C$17)*($AA$8)/$C$23,$C$17+($C$18-$C$17)*($AA$8)/$C$23),$C$17+4*($C$18-$C$17)*($AA$8)/$C$23*(1-($AA$8)/$C$23)))) -> 10.12 | AE8: =ABERTURAS!$D$51*5/8 -> 6.3 | AF8: =IF(ABERTURAS!$E$51="SÍ",$AB$8,ABERTURAS!$F$51) -> 10.62 | AG8: =((($AZ$5+$AE8*($C$12-2*$AZ$5)/$C$12)-$AZ$3*$C$13)+$AZ$39)/$AZ$38 -> 0.8412353 | AH8: =((IF($AF8>0,$AF8-$AZ$5,0)+$AZ$4*$C$13)+$AZ$40)/$AZ$38 -> 0.84135977 | AI8: =ABERTURAS!$D$52*5/8 -> 6.3 | AJ8: =IF(ABERTURAS!$E$52="SÍ",$AB$8,ABERTURAS!$F$52) -> 9.82 | AK8: =((($AZ$5+$AI8*($C$12-2*$AZ$5)/$C$12))+$AZ$39)/$AZ$38 -> 1.1585158 | AL8: =((IF($AJ8>0,$AJ8-$AZ$5,0))+$AZ$40)/$AZ$38 -> 0.60717658 | AM8: =ABERTURAS!$D$53*5/8 -> 10 | AN8: =IF(ABERTURAS!$E$53="SÍ",$AB$8,ABERTURAS!$F$53) -> 10.12 | AO8: =((-$AZ$3*($C$13-($AZ$5+$AM8*($C$13-2*$AZ$5)/$C$13)))+$AZ$39)/$AZ$38 -> 0.7442759 | AP8: =((IF($AN8>0,$AN8-$AZ$5,0)+$AZ$4*($C$13-($AZ$5+$AM8*($C$13-2*$AZ$5)/$C$13)))+$AZ$40)/$AZ$38 -> 0.69597734 | AQ8: =ABERTURAS!$D$54*5/8 -> 10 | AR8: =IF(ABERTURAS!$E$54="SÍ",$AB$8,ABERTURAS!$F$54) -> 10.12 | AS8: =(($C$12-$AZ$3*($C$13-($AZ$5+$AQ8*($C$13-2*$AZ$5)/$C$13)))+$AZ$39)/$AZ$38 -> 1.2201966 | AT8: =((IF($AR8>0,$AR8-$AZ$5,0)+$AZ$4*($C$13-($AZ$5+$AQ8*($C$13-2*$AZ$5)/$C$13)))+$AZ$40)/$AZ$38 -> 0.69597734 | AU8: =((IF($AC$3="Z",0,$AA$8)-$AZ$3*($C$13-IF($AC$3="Z",$AA$8,0)))+$AZ$39)/$AZ$38 -> 0.74586231 | AV8: =(($AB$8+$AZ$4*($C$13-IF($AC$3="Z",$AA$8,0)))+$AZ$40)/$AZ$38 -> 0.71010387 | AY8: y' máx nave | AZ8: =$C$21+$AZ$4*$C$13 -> 14.78
AA9: =$C$23*6/8 -> 12 | AB9: =IF($C$14="PLANO",$C$17,IF($C$14="DOS AGUAS",$C$17+($C$18-$C$17)*(1-ABS(2*($AA$9)/$C$23-1)),IF($C$14="UN AGUA",IF(N($C$25)=0,$C$18-($C$18-$C$17)*($AA$9)/$C$23,$C$17+($C$18-$C$17)*($AA$9)/$C$23),$C$17+4*($C$18-$C$17)*($AA$9)/$C$23*(1-($AA$9)/$C$23)))) -> 10.02 | AE9: =ABERTURAS!$D$51*4/8 -> 5.04 | AF9: =IF(ABERTURAS!$E$51="SÍ",$AB$7,ABERTURAS!$F$51) -> 10.62 | AG9: =((($AZ$5+$AE9*($C$12-2*$AZ$5)/$C$12)-$AZ$3*$C$13)+$AZ$39)/$AZ$38 -> 0.78552236 | AH9: =((IF($AF9>0,$AF9-$AZ$5,0)+$AZ$4*$C$13)+$AZ$40)/$AZ$38 -> 0.84135977 | AI9: =ABERTURAS!$D$52*4/8 -> 5.04 | AJ9: =IF(ABERTURAS!$E$52="SÍ",$AB$7,ABERTURAS!$F$52) -> 9.82 | AK9: =((($AZ$5+$AI9*($C$12-2*$AZ$5)/$C$12))+$AZ$39)/$AZ$38 -> 1.1028028 | AL9: =((IF($AJ9>0,$AJ9-$AZ$5,0))+$AZ$40)/$AZ$38 -> 0.60717658 | AM9: =ABERTURAS!$D$53*4/8 -> 8 | AN9: =IF(ABERTURAS!$E$53="SÍ",$AB$7,ABERTURAS!$F$53) -> 10.22 | AO9: =((-$AZ$3*($C$13-($AZ$5+$AM9*($C$13-2*$AZ$5)/$C$13)))+$AZ$39)/$AZ$38 -> 0.70620225 | AP9: =((IF($AN9>0,$AN9-$AZ$5,0)+$AZ$4*($C$13-($AZ$5+$AM9*($C$13-2*$AZ$5)/$C$13)))+$AZ$40)/$AZ$38 -> 0.72426818 | AQ9: =ABERTURAS!$D$54*4/8 -> 8 | AR9: =IF(ABERTURAS!$E$54="SÍ",$AB$7,ABERTURAS!$F$54) -> 10.22 | AS9: =(($C$12-$AZ$3*($C$13-($AZ$5+$AQ9*($C$13-2*$AZ$5)/$C$13)))+$AZ$39)/$AZ$38 -> 1.1821229 | AT9: =((IF($AR9>0,$AR9-$AZ$5,0)+$AZ$4*($C$13-($AZ$5+$AQ9*($C$13-2*$AZ$5)/$C$13)))+$AZ$40)/$AZ$38 -> 0.72426818 | AU9: =((IF($AC$3="Z",0,$AA$9)-$AZ$3*($C$13-IF($AC$3="Z",$AA$9,0)))+$AZ$39)/$AZ$38 -> 0.78552236 | AV9: =(($AB$9+$AZ$4*($C$13-IF($AC$3="Z",$AA$9,0)))+$AZ$40)/$AZ$38 -> 0.68083097 | AY9: E | AZ9: =MAX($AZ$7-$AZ$6,$AZ$8) -> 16.8
B10: 2. GEOMETRÍA DE LA NAVE | AA10: =$C$23*7/8 -> 14 | AB10: =IF($C$14="PLANO",$C$17,IF($C$14="DOS AGUAS",$C$17+($C$18-$C$17)*(1-ABS(2*($AA$10)/$C$23-1)),IF($C$14="UN AGUA",IF(N($C$25)=0,$C$18-($C$18-$C$17)*($AA$10)/$C$23,$C$17+($C$18-$C$17)*($AA$10)/$C$23),$C$17+4*($C$18-$C$17)*($AA$10)/$C$23*(1-($AA$10)/$C$23)))) -> 9.92 | AE10: =ABERTURAS!$D$51*3/8 -> 3.78 | AF10: =IF(ABERTURAS!$E$51="SÍ",$AB$6,ABERTURAS!$F$51) -> 10.62 | AG10: =((($AZ$5+$AE10*($C$12-2*$AZ$5)/$C$12)-$AZ$3*$C$13)+$AZ$39)/$AZ$38 -> 0.72980943 | AH10: =((IF($AF10>0,$AF10-$AZ$5,0)+$AZ$4*$C$13)+$AZ$40)/$AZ$38 -> 0.84135977 | AI10: =ABERTURAS!$D$52*3/8 -> 3.78 | AJ10: =IF(ABERTURAS!$E$52="SÍ",$AB$6,ABERTURAS!$F$52) -> 9.82 | AK10: =((($AZ$5+$AI10*($C$12-2*$AZ$5)/$C$12))+$AZ$39)/$AZ$38 -> 1.0470899 | AL10: =((IF($AJ10>0,$AJ10-$AZ$5,0))+$AZ$40)/$AZ$38 -> 0.60717658 | AM10: =ABERTURAS!$D$53*3/8 -> 6 | AN10: =IF(ABERTURAS!$E$53="SÍ",$AB$6,ABERTURAS!$F$53) -> 10.32 | AO10: =((-$AZ$3*($C$13-($AZ$5+$AM10*($C$13-2*$AZ$5)/$C$13)))+$AZ$39)/$AZ$38 -> 0.66812859 | AP10: =((IF($AN10>0,$AN10-$AZ$5,0)+$AZ$4*($C$13-($AZ$5+$AM10*($C$13-2*$AZ$5)/$C$13)))+$AZ$40)/$AZ$38 -> 0.75255902 | AQ10: =ABERTURAS!$D$54*3/8 -> 6 | AR10: =IF(ABERTURAS!$E$54="SÍ",$AB$6,ABERTURAS!$F$54) -> 10.32 | AS10: =(($C$12-$AZ$3*($C$13-($AZ$5+$AQ10*($C$13-2*$AZ$5)/$C$13)))+$AZ$39)/$AZ$38 -> 1.1440493 | AT10: =((IF($AR10>0,$AR10-$AZ$5,0)+$AZ$4*($C$13-($AZ$5+$AQ10*($C$13-2*$AZ$5)/$C$13)))+$AZ$40)/$AZ$38 -> 0.75255902 | AU10: =((IF($AC$3="Z",0,$AA$10)-$AZ$3*($C$13-IF($AC$3="Z",$AA$10,0)))+$AZ$39)/$AZ$38 -> 0.82518242 | AV10: =(($AB$10+$AZ$4*($C$13-IF($AC$3="Z",$AA$10,0)))+$AZ$40)/$AZ$38 -> 0.65155807 | AY10: flecha | AZ10: =0.12*$AZ$9 -> 2.016
B11: Concepto | C11: Valor | D11: Unidad | E11: Cómo se calcula / de dónde sale | F11: Referencia | AA11: =$C$23*8/8 -> 16 | AB11: =IF($C$14="PLANO",$C$17,IF($C$14="DOS AGUAS",$C$17+($C$18-$C$17)*(1-ABS(2*($AA$11)/$C$23-1)),IF($C$14="UN AGUA",IF(N($C$25)=0,$C$18-($C$18-$C$17)*($AA$11)/$C$23,$C$17+($C$18-$C$17)*($AA$11)/$C$23),$C$17+4*($C$18-$C$17)*($AA$11)/$C$23*(1-($AA$11)/$C$23)))) -> 9.82 | AE11: =ABERTURAS!$D$51*2/8 -> 2.52 | AF11: =IF(ABERTURAS!$E$51="SÍ",$AB$5,ABERTURAS!$F$51) -> 10.62 | AG11: =((($AZ$5+$AE11*($C$12-2*$AZ$5)/$C$12)-$AZ$3*$C$13)+$AZ$39)/$AZ$38 -> 0.67409649 | AH11: =((IF($AF11>0,$AF11-$AZ$5,0)+$AZ$4*$C$13)+$AZ$40)/$AZ$38 -> 0.84135977 | AI11: =ABERTURAS!$D$52*2/8 -> 2.52 | AJ11: =IF(ABERTURAS!$E$52="SÍ",$AB$5,ABERTURAS!$F$52) -> 9.82 | AK11: =((($AZ$5+$AI11*($C$12-2*$AZ$5)/$C$12))+$AZ$39)/$AZ$38 -> 0.99137694 | AL11: =((IF($AJ11>0,$AJ11-$AZ$5,0))+$AZ$40)/$AZ$38 -> 0.60717658 | AM11: =ABERTURAS!$D$53*2/8 -> 4 | AN11: =IF(ABERTURAS!$E$53="SÍ",$AB$5,ABERTURAS!$F$53) -> 10.42 | AO11: =((-$AZ$3*($C$13-($AZ$5+$AM11*($C$13-2*$AZ$5)/$C$13)))+$AZ$39)/$AZ$38 -> 0.63005494 | AP11: =((IF($AN11>0,$AN11-$AZ$5,0)+$AZ$4*($C$13-($AZ$5+$AM11*($C$13-2*$AZ$5)/$C$13)))+$AZ$40)/$AZ$38 -> 0.78084986 | AQ11: =ABERTURAS!$D$54*2/8 -> 4 | AR11: =IF(ABERTURAS!$E$54="SÍ",$AB$5,ABERTURAS!$F$54) -> 10.42 | AS11: =(($C$12-$AZ$3*($C$13-($AZ$5+$AQ11*($C$13-2*$AZ$5)/$C$13)))+$AZ$39)/$AZ$38 -> 1.1059756 | AT11: =((IF($AR11>0,$AR11-$AZ$5,0)+$AZ$4*($C$13-($AZ$5+$AQ11*($C$13-2*$AZ$5)/$C$13)))+$AZ$40)/$AZ$38 -> 0.78084986 | AU11: =((IF($AC$3="Z",0,$AA$11)-$AZ$3*($C$13-IF($AC$3="Z",$AA$11,0)))+$AZ$39)/$AZ$38 -> 0.86484248 | AV11: =(($AB$11+$AZ$4*($C$13-IF($AC$3="Z",$AA$11,0)))+$AZ$40)/$AZ$38 -> 0.62228517 | AY11: punta | AZ11: =0.035*$AZ$9 -> 0.588
B12: B — ancho en X (de Muro 3 a Muro 4) | C12: 10.08 | D12: m | E12: CAPTURA. EJEMPLO: NOSE DOCK, X de 0 a 10.08 m (claro de los marcos). | F12: Modelo STAAD / arquitectónico | AE12: =ABERTURAS!$D$51*1/8 -> 1.26 | AF12: =IF(ABERTURAS!$E$51="SÍ",$AB$4,ABERTURAS!$F$51) -> 10.62 | AG12: =((($AZ$5+$AE12*($C$12-2*$AZ$5)/$C$12)-$AZ$3*$C$13)+$AZ$39)/$AZ$38 -> 0.61838355 | AH12: =((IF($AF12>0,$AF12-$AZ$5,0)+$AZ$4*$C$13)+$AZ$40)/$AZ$38 -> 0.84135977 | AI12: =ABERTURAS!$D$52*1/8 -> 1.26 | AJ12: =IF(ABERTURAS!$E$52="SÍ",$AB$4,ABERTURAS!$F$52) -> 9.82 | AK12: =((($AZ$5+$AI12*($C$12-2*$AZ$5)/$C$12))+$AZ$39)/$AZ$38 -> 0.93566401 | AL12: =((IF($AJ12>0,$AJ12-$AZ$5,0))+$AZ$40)/$AZ$38 -> 0.60717658 | AM12: =ABERTURAS!$D$53*1/8 -> 2 | AN12: =IF(ABERTURAS!$E$53="SÍ",$AB$4,ABERTURAS!$F$53) -> 10.52 | AO12: =((-$AZ$3*($C$13-($AZ$5+$AM12*($C$13-2*$AZ$5)/$C$13)))+$AZ$39)/$AZ$38 -> 0.59198129 | AP12: =((IF($AN12>0,$AN12-$AZ$5,0)+$AZ$4*($C$13-($AZ$5+$AM12*($C$13-2*$AZ$5)/$C$13)))+$AZ$40)/$AZ$38 -> 0.8091407 | AQ12: =ABERTURAS!$D$54*1/8 -> 2 | AR12: =IF(ABERTURAS!$E$54="SÍ",$AB$4,ABERTURAS!$F$54) -> 10.52 | AS12: =(($C$12-$AZ$3*($C$13-($AZ$5+$AQ12*($C$13-2*$AZ$5)/$C$13)))+$AZ$39)/$AZ$38 -> 1.067902 | AT12: =((IF($AR12>0,$AR12-$AZ$5,0)+$AZ$4*($C$13-($AZ$5+$AQ12*($C$13-2*$AZ$5)/$C$13)))+$AZ$40)/$AZ$38 -> 0.8091407 | AU12: =((IF($AC$3="Z",$C$12,$AA$11)-$AZ$3*($C$13-IF($AC$3="Z",$AA$11,$C$13)))+$AZ$39)/$AZ$38 -> 1.3407632 | AV12: =(($AB$11+$AZ$4*($C$13-IF($AC$3="Z",$AA$11,$C$13)))+$AZ$40)/$AZ$38 -> 0.62228517 | AY12: ejes | AZ12: =0.09*$AZ$9 -> 1.512
B13: L — largo en Z (de Muro 1 a Muro 2) | C13: 16 | D13: m | E13: CAPTURA. EJEMPLO: NOSE DOCK, Z de 0 a 16.00 m. | F13: Modelo STAAD / arquitectónico | AE13: =ABERTURAS!$D$51*0/8 -> 0 | AF13: =IF(ABERTURAS!$E$51="SÍ",$AB$3,ABERTURAS!$F$51) -> 10.62 | AG13: =((($AZ$5+$AE13*($C$12-2*$AZ$5)/$C$12)-$AZ$3*$C$13)+$AZ$39)/$AZ$38 -> 0.56267062 | AH13: =((IF($AF13>0,$AF13-$AZ$5,0)+$AZ$4*$C$13)+$AZ$40)/$AZ$38 -> 0.84135977 | AI13: =ABERTURAS!$D$52*0/8 -> 0 | AJ13: =IF(ABERTURAS!$E$52="SÍ",$AB$3,ABERTURAS!$F$52) -> 9.82 | AK13: =((($AZ$5+$AI13*($C$12-2*$AZ$5)/$C$12))+$AZ$39)/$AZ$38 -> 0.87995107 | AL13: =((IF($AJ13>0,$AJ13-$AZ$5,0))+$AZ$40)/$AZ$38 -> 0.60717658 | AM13: =ABERTURAS!$D$53*0/8 -> 0 | AN13: =IF(ABERTURAS!$E$53="SÍ",$AB$3,ABERTURAS!$F$53) -> 10.62 | AO13: =((-$AZ$3*($C$13-($AZ$5+$AM13*($C$13-2*$AZ$5)/$C$13)))+$AZ$39)/$AZ$38 -> 0.55390763 | AP13: =((IF($AN13>0,$AN13-$AZ$5,0)+$AZ$4*($C$13-($AZ$5+$AM13*($C$13-2*$AZ$5)/$C$13)))+$AZ$40)/$AZ$38 -> 0.83743154 | AQ13: =ABERTURAS!$D$54*0/8 -> 0 | AR13: =IF(ABERTURAS!$E$54="SÍ",$AB$3,ABERTURAS!$F$54) -> 10.62 | AS13: =(($C$12-$AZ$3*($C$13-($AZ$5+$AQ13*($C$13-2*$AZ$5)/$C$13)))+$AZ$39)/$AZ$38 -> 1.0298283 | AT13: =((IF($AR13>0,$AR13-$AZ$5,0)+$AZ$4*($C$13-($AZ$5+$AQ13*($C$13-2*$AZ$5)/$C$13)))+$AZ$40)/$AZ$38 -> 0.83743154 | AU13: =((IF($AC$3="Z",$C$12,$AA$10)-$AZ$3*($C$13-IF($AC$3="Z",$AA$10,$C$13)))+$AZ$39)/$AZ$38 -> 1.3011031 | AV13: =(($AB$10+$AZ$4*($C$13-IF($AC$3="Z",$AA$10,$C$13)))+$AZ$40)/$AZ$38 -> 0.65155807 | AY13: cos punta | AZ13: =COS(RADIANS(28)) -> 0.88294759
B14: Tipo de techo | C14: UN AGUA | D14: — | E14: SELECTOR: DOS AGUAS, UN AGUA, PLANO o CURVO. | F14: NTV 1997 · 4.3.1, pág. 5 · Tabla 4.2, pág. 6 | AE14: =0 -> 0 | AF14: =0 -> 0 | AG14: =((($AZ$5+$AE14*($C$12-2*$AZ$5)/$C$12)-$AZ$3*$C$13)+$AZ$39)/$AZ$38 -> 0.56267062 | AH14: =((IF($AF14>0,$AF14-$AZ$5,0)+$AZ$4*$C$13)+$AZ$40)/$AZ$38 -> 0.35505194 | AI14: =0 -> 0 | AJ14: =0 -> 0 | AK14: =((($AZ$5+$AI14*($C$12-2*$AZ$5)/$C$12))+$AZ$39)/$AZ$38 -> 0.87995107 | AL14: =((IF($AJ14>0,$AJ14-$AZ$5,0))+$AZ$40)/$AZ$38 -> 0.15864023 | AM14: =0 -> 0 | AN14: =0 -> 0 | AO14: =((-$AZ$3*($C$13-($AZ$5+$AM14*($C$13-2*$AZ$5)/$C$13)))+$AZ$39)/$AZ$38 -> 0.55390763 | AP14: =((IF($AN14>0,$AN14-$AZ$5,0)+$AZ$4*($C$13-($AZ$5+$AM14*($C$13-2*$AZ$5)/$C$13)))+$AZ$40)/$AZ$38 -> 0.3511237 | AQ14: =0 -> 0 | AR14: =0 -> 0 | AS14: =(($C$12-$AZ$3*($C$13-($AZ$5+$AQ14*($C$13-2*$AZ$5)/$C$13)))+$AZ$39)/$AZ$38 -> 1.0298283 | AT14: =((IF($AR14>0,$AR14-$AZ$5,0)+$AZ$4*($C$13-($AZ$5+$AQ14*($C$13-2*$AZ$5)/$C$13)))+$AZ$40)/$AZ$38 -> 0.3511237 | AU14: =((IF($AC$3="Z",$C$12,$AA$9)-$AZ$3*($C$13-IF($AC$3="Z",$AA$9,$C$13)))+$AZ$39)/$AZ$38 -> 1.261443 | AV14: =(($AB$9+$AZ$4*($C$13-IF($AC$3="Z",$AA$9,$C$13)))+$AZ$40)/$AZ$38 -> 0.68083097 | AY14: sen punta | AZ14: =SIN(RADIANS(28)) -> 0.46947156
B15: El agua escurre hacia (sólo UN AGUA) | C15: MURO 2 (Z = L) | D15: — | E15: SELECTOR. El muro por donde baja el agua; el lado alto queda en el muro opuesto. Muro 3 = izquierda, Muro 4 = derecha, Muro 1 = atrás, Muro 2 = frente (como en la vista de STAAD). EJEMPLO: NOSE DOCK, alto en el eje 1 y bajo en el eje 4. | F15: Croquis / arquitectónico | AU15: =((IF($AC$3="Z",$C$12,$AA$8)-$AZ$3*($C$13-IF($AC$3="Z",$AA$8,$C$13)))+$AZ$39)/$AZ$38 -> 1.221783 | AV15: =(($AB$8+$AZ$4*($C$13-IF($AC$3="Z",$AA$8,$C$13)))+$AZ$40)/$AZ$38 -> 0.71010387 | AY15: T1 x' | AZ15: =$C$12/2-$AZ$3*$C$13 -> -1.68
B16: Cumbrera (o eje del arco) paralela a (DOS AGUAS y CURVO) | C16: L (EJE Z) | D16: — | E16: SELECTOR. L (EJE Z): cumbrera a lo largo, hastiales en Muros 1 y 2. B (EJE X): cumbrera de lado a lado, hastiales en Muros 3 y 4. | F16: Croquis / arquitectónico | AU16: =((IF($AC$3="Z",$C$12,$AA$7)-$AZ$3*($C$13-IF($AC$3="Z",$AA$7,$C$13)))+$AZ$39)/$AZ$38 -> 1.1821229 | AV16: =(($AB$7+$AZ$4*($C$13-IF($AC$3="Z",$AA$7,$C$13)))+$AZ$40)/$AZ$38 -> 0.73937677 | AY16: T1 y' | AZ16: =$AF$9-$AZ$5+$AZ$4*$C$13 -> 14.46
B17: h_a — altura baja (alero, o lado bajo en UN AGUA) | C17: 9.82 | D17: m | E17: CAPTURA. Del piso al alero. EJEMPLO: NOSE DOCK, 9.82 m en el eje 4 (nodos 13 y 16). | F17: Modelo STAAD / arquitectónico | AU17: =((IF($AC$3="Z",$C$12,$AA$6)-$AZ$3*($C$13-IF($AC$3="Z",$AA$6,$C$13)))+$AZ$39)/$AZ$38 -> 1.1424629 | AV17: =(($AB$6+$AZ$4*($C$13-IF($AC$3="Z",$AA$6,$C$13)))+$AZ$40)/$AZ$38 -> 0.76864967 | AY17: A1 x' | AZ17: =$AZ$15 -> -1.68
B18: h_c — altura alta (cumbrera, clave o lado alto) | C18: 10.62 | D18: m | E18: CAPTURA. Con techo PLANO no se usa. EJEMPLO: NOSE DOCK, 10.62 m en el eje 1 (nodos 20 y 21). | F18: Modelo STAAD / arquitectónico | AU18: =((IF($AC$3="Z",$C$12,$AA$5)-$AZ$3*($C$13-IF($AC$3="Z",$AA$5,$C$13)))+$AZ$39)/$AZ$38 -> 1.1028028 | AV18: =(($AB$5+$AZ$4*($C$13-IF($AC$3="Z",$AA$5,$C$13)))+$AZ$40)/$AZ$38 -> 0.79792257 | AY18: A1 y' | AZ18: =$AZ$16+$AZ$10 -> 16.476
B19: ¿El arco arranca desde el suelo? (sólo CURVO) | C19: NO | D19: — | E19: SELECTOR. Con SÍ la zona A1 de la Tabla 4.2 pasa a empuje 1.4r ≤ 0.9. | F19: NTV 1997 · Tabla 4.2, pág. 6 | AU19: =((IF($AC$3="Z",$C$12,$AA$4)-$AZ$3*($C$13-IF($AC$3="Z",$AA$4,$C$13)))+$AZ$39)/$AZ$38 -> 1.0631428 | AV19: =(($AB$4+$AZ$4*($C$13-IF($AC$3="Z",$AA$4,$C$13)))+$AZ$40)/$AZ$38 -> 0.82719547 | AY19: T2 x' | AZ19: =$C$12/2 -> 5.04
B20: Separación típica entre marcos | C20: 6.75 | D20: m | E20: CAPTURA. Sólo para la carga de un marco intermedio en 2D (PRESIONES §F). EJEMPLO: ejes 1-2 y 2-3 del NOSE DOCK. | F20: Modelo STAAD / arquitectónico | AU20: =((IF($AC$3="Z",$C$12,$AA$3)-$AZ$3*($C$13-IF($AC$3="Z",$AA$3,$C$13)))+$AZ$39)/$AZ$38 -> 1.0234827 | AV20: =(($AB$3+$AZ$4*($C$13-IF($AC$3="Z",$AA$3,$C$13)))+$AZ$40)/$AZ$38 -> 0.85646837 | AY20: T2 y' | AZ20: =0 -> 0
B21: H — altura máxima de la nave | C21: =IF($C$14="PLANO",$C$17,MAX($C$17,$C$18)) -> 10.62 | D21: m | E21: CALCULADA. | F21: — | AU21: =((IF($AC$3="Z",0,$AA$3)-$AZ$3*($C$13-IF($AC$3="Z",$AA$3,0)))+$AZ$39)/$AZ$38 -> 0.54756202 | AV21: =(($AB$3+$AZ$4*($C$13-IF($AC$3="Z",$AA$3,0)))+$AZ$40)/$AZ$38 -> 0.85646837 | AY21: A2 x' | AZ21: =$AZ$19 -> 5.04
B22: Eje de la pendiente del techo | C22: =IF($C$14="PLANO","—",IF($C$14="UN AGUA",IF(OR(LEFT($C$15,6)="MURO 1",LEFT($C$15,6)="MURO 2"),"Z","X"),IF(LEFT($C$16,1)="L","X","Z"))) -> Z | D22: — | E22: CALCULADA. Dirección en la que cambia la altura del techo (s va de 0 a S en ese eje). | F22: Croquis | AU22: =((IF($AC$3="Z",0,$AA$5)-$AZ$3*($C$13-IF($AC$3="Z",$AA$5,0)))+$AZ$39)/$AZ$38 -> 0.62688214 | AV22: =(($AB$5+$AZ$4*($C$13-IF($AC$3="Z",$AA$5,0)))+$AZ$40)/$AZ$38 -> 0.79792257 | AY22: A2 y' | AZ22: =$AZ$20-$AZ$10 -> -2.016
B23: S — claro en el sentido de la pendiente | C23: =IF($C$22="Z",$C$13,$C$12) -> 16 | D23: m | E23: CALCULADA. | F23: — | AU23: =((IF($AC$3="Z",$C$12,$AA$5)-$AZ$3*($C$13-IF($AC$3="Z",$AA$5,$C$13)))+$AZ$39)/$AZ$38 -> 1.1028028 | AV23: =(($AB$5+$AZ$4*($C$13-IF($AC$3="Z",$AA$5,$C$13)))+$AZ$40)/$AZ$38 -> 0.79792257 | AY23: T3 x' | AZ23: =-$AZ$3*$C$13/2 -> -3.36
B24: Lado alto del techo (UN AGUA) | C24: =IF($C$14<>"UN AGUA","—",CHOOSE(VALUE(MID($C$15,6,1)),"MURO 2","MURO 1","MURO 4","MURO 3")) -> MURO 1 | D24: — | E24: CALCULADA: el muro opuesto al que escurre el agua. | F24: Croquis | AU24: =((IF($AC$3="Z",$C$12,$AA$7)-$AZ$3*($C$13-IF($AC$3="Z",$AA$7,$C$13)))+$AZ$39)/$AZ$38 -> 1.1821229 | AV24: =(($AB$7+$AZ$4*($C$13-IF($AC$3="Z",$AA$7,$C$13)))+$AZ$40)/$AZ$38 -> 0.73937677 | AY24: T3 y' | AZ24: =$AZ$4*$C$13/2 -> 2.08
B25: s del lado alto (UN AGUA) | C25: =IF($C$14<>"UN AGUA","—",IF(OR($C$24="MURO 1",$C$24="MURO 3"),0,$C$23)) -> 0 | D25: m | E25: CALCULADA. 0 si el lado alto está en X = 0 o Z = 0; S si está en el otro extremo. | F25: — | AU25: =((IF($AC$3="Z",0,$AA$7)-$AZ$3*($C$13-IF($AC$3="Z",$AA$7,0)))+$AZ$39)/$AZ$38 -> 0.70620225 | AV25: =(($AB$7+$AZ$4*($C$13-IF($AC$3="Z",$AA$7,0)))+$AZ$40)/$AZ$38 -> 0.73937677 | AY25: A3 x' | AZ25: =$AZ$23-SQRT(0.5)*$AZ$10 -> -4.7855273
B26: θ — inclinación del techo | C26: =IF($C$14="DOS AGUAS",DEGREES(ATAN(($C$18-$C$17)/($C$23/2))),IF($C$14="UN AGUA",DEGREES(ATAN(($C$18-$C$17)/$C$23)),0)) -> 2.8624052 | D26: ° | E26: CALCULADA. Decide el C_p del faldón de barlovento. | F26: NTV 1997 · 4.3.1, pág. 5 | AU26: =((IF($AC$3="Z",0,$AA$9)-$AZ$3*($C$13-IF($AC$3="Z",$AA$9,0)))+$AZ$39)/$AZ$38 -> 0.78552236 | AV26: =(($AB$9+$AZ$4*($C$13-IF($AC$3="Z",$AA$9,0)))+$AZ$40)/$AZ$38 -> 0.68083097 | AY26: A3 y' | AZ26: =$AZ$24-SQRT(0.5)*$AZ$10 -> 0.65447273
B27: Pendiente del techo | C27: =TAN(RADIANS($C$26)) -> 0.05 | D27: % | E27: CALCULADA. | F27: — | AU27: =((IF($AC$3="Z",$C$12,$AA$9)-$AZ$3*($C$13-IF($AC$3="Z",$AA$9,$C$13)))+$AZ$39)/$AZ$38 -> 1.261443 | AV27: =(($AB$9+$AZ$4*($C$13-IF($AC$3="Z",$AA$9,$C$13)))+$AZ$40)/$AZ$38 -> 0.68083097 | AY27: T4 x' | AZ27: =$C$12-$AZ$3*$C$13/2 -> 6.72
B28: Revisión de la geometría | C28: =IF(OR(N($C$12)<=0,N($C$13)<=0),"FALTA B o L",IF(AND(N($C$17)<=0,NOT(AND($C$14="CURVO",$C$19="SÍ"))),"FALTA h_a",IF(AND($C$14<>"PLANO",N($C$18)<=N($C$17)),"h_c debe ser mayor que h_a (salvo techo PLANO)",IF(AND($C$14="CURVO",PRESIONES!$C$17>0.6),"Techo curvo con r > 0.6: fuera de la Tabla 4.2","OK")))) -> OK | D28: — | E28: CALCULADA. Debe decir OK. | F28: — | AY28: T4 y' | AZ28: =$AR$9-$AZ$5+$AZ$4*$C$13/2 -> 11.98
B29: Croquis con tus datos (se actualiza solo), visto como en STAAD: X a la derecha, Y arriba y Z hacia ti. Muro 2 (Z = L) al frente, Muro 1 (Z = 0, puerta y cortina) al fondo, Muro 3 (X = 0) a la izquierda y Muro 4 (X = B) a la derecha. Rojo = abertura FIJA; naranja punteado = OPERABLE. | AY29: A4 x' | AZ29: =$AZ$27+SQRT(0.5)*$AZ$10 -> 8.1455273
AY30: A4 y' | AZ30: =$AZ$28+SQRT(0.5)*$AZ$10 -> 13.405527
AY31: ejes x0' | AZ31: =$AZ$7+0.2*$AZ$9 -> 13.44
AY32: ejes y0' | AZ32: =0.1*$AZ$9 -> 1.68
AY33: ext x' mín | AZ33: =MIN($AZ$6,$AZ$25-0.42*$AZ$9) -> -11.841527
AY34: ext x' máx | AZ34: =MAX($AZ$7,$AZ$29+0.42*$AZ$9,$AZ$31+$AZ$12+0.08*$AZ$9) -> 16.296
AY35: ext y' mín | AZ35: =MIN(0,$AZ$22-0.08*$AZ$9,$AZ$32-$AZ$12*$AZ$4/SQRT($AZ$3^2+$AZ$4^2)-0.08*$AZ$9) -> -3.36
AY36: ext y' máx | AZ36: =MAX($AZ$8,$AZ$18+0.08*$AZ$9,$AZ$32+$AZ$12+0.08*$AZ$9) -> 17.82
AY37: aspecto | AZ37: =1.94 -> 1.94
AY38: s | AZ38: =MAX(($AZ$34-$AZ$33)/$AZ$37,$AZ$36-$AZ$35) -> 21.18
AY39: offX | AZ39: =($AZ$37*$AZ$38-($AZ$34-$AZ$33))/2-$AZ$33 -> 18.317364
AY40: offY | AZ40: =($AZ$38-($AZ$36-$AZ$35))/2-$AZ$35 -> 3.36
B52: 3. EXPOSICIÓN Y TIPO DE ESTRUCTURA
B53: Concepto | C53: Valor | D53: Unidad | E53: Cómo se calcula / de dónde sale | F53: Referencia
B54: Zona de exposición | C54: C | D54: — | E54: SELECTOR. A: muchos edificios altos alrededor; B: construcciones medianas o bajas, o árboles; C: terreno abierto (aeropuertos, campo, costa). EJEMPLO: C por estar en aeropuerto. | F54: NTV 1997 · Tabla 4.1, pág. 5
B55: K — factor de exposición | C55: =INDEX(TABLAS!$D$7:$D$9,MATCH($C$54,TABLAS!$B$7:$B$9,0)) -> 1.6 | D55: — | E55: CALCULADA de la Tabla 4.1. | F55: NTV 1997 · Tabla 4.1, pág. 5
B56: a — exponente de variación con la altura | C56: =INDEX(TABLAS!$E$7:$E$9,MATCH($C$54,TABLAS!$B$7:$B$9,0)) -> 7 | D56: — | E56: CALCULADA. C_z = 1 hasta 10 m y (z/10)^(2/a) arriba. | F56: NTV 1997 · 4.2 y Tabla 4.1, pág. 5
B57: P_o — presión básica de diseño | C57: 30 | D57: kg/m² | E57: FIJA por la norma (80 km/h a 10 m). | F57: NTV 1997 · 2.1, pág. 2 · 4.1, pág. 5
B58: T — periodo natural de la nave | C58: 0.706 | D58: s | E58: CAPTURA. Periodo del modo dominante de STAAD | F58: NTV 1997 · 3.1, pág. 3
B59: Esbeltez = H / dimensión menor en planta | C59: =$C$21/MIN($C$12,$C$13) -> 1.0535714 | D59: — | E59: CALCULADA. | F59: NTV 1997 · 2.1, pág. 2 · 3.1, pág. 3
B60: Tipo de estructura | C60: =IF(AND($C$59<=5,$C$58<=2),"TIPO 1","TIPO 2") -> TIPO 1 | D60: — | E60: CALCULADA. Tipo 1: esbeltez ≤ 5 y T ≤ 2 s. Tipo 2: presiones × 1.3 por ráfaga. El Tipo 3 (vórtices) no lo cubre esta hoja. | F60: NTV 1997 · 3.1, pág. 3 · 4.6.1, pág. 7
B61: FR — factor por ráfaga | C61: =IF($C$60="TIPO 2",1.3,1) -> 1 | D61: — | E61: CALCULADA. | F61: NTV 1997 · 4.6.1, pág. 7
B63: 4. CASOS DE VIENTO PARA STAAD
B64: Concepto | C64: Valor | D64: Unidad | E64: Cómo se calcula / de dónde sale | F64: Referencia
B65: Unidades del modelo STAAD | C65: CM KG | D65: — | E65: SELECTOR: CM KG , METER KG o METER KN. Las cargas salen en kg/cm, kg/m o kN/m. | F65: Encabezado del .STD (UNIT)
B66: Número del primer caso de viento | C66: 8 | D66: — | E66: CAPTURA. Los 8 casos quedan seguidos. EJEMPLO: en el NOSE DOCK R3 los vientos son LOAD 8 a 15. | F66: 001_NOSE_DOCK_H5_H6_R3.STD
B67: Factor de unidades de la carga lineal | C67: =IF($C$65="CM KG",0.01,IF($C$65="METER KG",1,0.00980665)) -> 0.01 | D67: — | E67: CALCULADA. kg/m × factor = unidades de STAAD. | F67: —
B68: Formato del número en STAAD | C68: =IF($C$65="METER KG","0.00","0.0000") -> 0.0000 | D68: — | E68: CALCULADA. | F68: —
B69: Número del primer caso B (sólo si hace falta) | C69: 101 | D69: — | E69: CAPTURA. Los casos B sólo existen con techo de 30° a 50° (±0.4) o curvo con 0.2 ≤ r ≤ 0.3 (+0.3). Usa números libres. | F69: NTV 1997 · 4.3.1, pág. 5 · Tabla 4.2, pág. 6
B71: Caso en STAAD | C71: Viento | D71: Puertas | E71: Título en STAAD (lo puedes cambiar) | F71: Qué es
B72: ="LOAD "&($C$66+0) -> LOAD 8 | C72: +X | D72: CERRADAS | E72: VIENTO X | F72: Operables cerradas; sólo cuentan las aberturas FIJAS. Viento sopla hacia +X: pega primero en el Muro 3 (X = 0).
B73: ="LOAD "&($C$66+1) -> LOAD 9 | C73: −X | D73: CERRADAS | E73: VIENTO -X | F73: Operables cerradas; sólo cuentan las aberturas FIJAS. Viento sopla hacia −X: pega primero en el Muro 4 (X = B).
B74: ="LOAD "&($C$66+2) -> LOAD 10 | C74: +Z | D74: CERRADAS | E74: VIENTO Z | F74: Operables cerradas; sólo cuentan las aberturas FIJAS. Viento sopla hacia +Z: pega primero en el Muro 1 (Z = 0).
B75: ="LOAD "&($C$66+3) -> LOAD 11 | C75: −Z | D75: CERRADAS | E75: VIENTO -Z | F75: Operables cerradas; sólo cuentan las aberturas FIJAS. Viento sopla hacia −Z: pega primero en el Muro 2 (Z = L).
B76: ="LOAD "&($C$66+4) -> LOAD 12 | C76: +X | D76: ABIERTAS (PA) | E76: VIENTO X PA | F76: Operables abiertas (puerta o cortina abierta en la tormenta). Viento sopla hacia +X: pega primero en el Muro 3 (X = 0).
B77: ="LOAD "&($C$66+5) -> LOAD 13 | C77: −X | D77: ABIERTAS (PA) | E77: VIENTO -X PA | F77: Operables abiertas (puerta o cortina abierta en la tormenta). Viento sopla hacia −X: pega primero en el Muro 4 (X = B).
B78: ="LOAD "&($C$66+6) -> LOAD 14 | C78: +Z | D78: ABIERTAS (PA) | E78: VIENTO Z PA | F78: Operables abiertas (puerta o cortina abierta en la tormenta). Viento sopla hacia +Z: pega primero en el Muro 1 (Z = 0).
B79: ="LOAD "&($C$66+7) -> LOAD 15 | C79: −Z | D79: ABIERTAS (PA) | E79: VIENTO -Z PA | F79: Operables abiertas (puerta o cortina abierta en la tormenta). Viento sopla hacia −Z: pega primero en el Muro 2 (Z = L).

Sheet ABERTURAS
B1: ABERTURAS POR MURO (POSICIÓN Y TAMAÑO) Y PRESIÓN INTERIOR
B2: Captura cada abertura donde está: portones, cortinas, puertas, ventanas, louvers o un muro que no se forra. Con eso la hoja dibuja los muros, saca el área abierta de cada escenario, decide la presión interior (NTV 4.4, pág. 7) y descuenta las aberturas de las cargas de LINEAS.
B3: CÓMO SE LLENA: un renglón por abertura. x = distancia horizontal desde la esquina con el Muro 3 (en Muros 1 y 2, igual a la X de STAAD) o desde la esquina con el Muro 1 (en Muros 3 y 4, igual a la Z de STAAD); y = altura del piso a la parte baja. FIJA = siempre abierta (vano sin cerrar, louver, muro sin forro). OPERABLE = puerta o cortina: cerrada en los casos normales y abierta en los casos PA. Deja en blanco lo que no uses.
B5: A. LISTA DE ABERTURAS | N5: auxiliares (no se tocan) | Y5: auxiliares de la elevación (no se tocan)
B6: # | C6: Descripción | D6: Muro | E6: Tipo | F6: x desde (m) | G6: y desde (m) | H6: Ancho (m) | I6: Alto (m) | J6: Área (m²) | K6: ¿Cabe en el muro? | L6: Nota / de dónde sale | N6: nº muro | O6: u₁ | P6: u₂ | Q6: v₁ | R6: v₂ | S6: tope en u₁ | T6: tope en u₂ | U6: abierta CERR | V6: abierta PA | W6: largo muro | Y6: hueco | Z6: =MAX(1.5,0.1*MAX(DATOS!$C$12,DATOS!$C$13)) -> 1.6 | AA6: desfase | AB6: =0 -> 0 | AC6: =$D$51+$Z$6 -> 11.68 | AD6: =$D$51+$D$52+2*$Z$6 -> 23.36 | AE6: =$D$51+$D$52+$D$53+3*$Z$6 -> 40.96
B7: 1 | C7: Puerta de servicio (muro de atrás) | D7: MURO 1 | E7: OPERABLE | F7: 0.6425 | G7: 0 | H7: 1.3014 | I7: 2.4 | J7: =IF($K7="OK",$H7*$I7,0) -> 3.12336 | K7: =IF($D7="","",IF(OR($F7="",$G7=""),"FALTA POSICIÓN",IF(OR(N($H7)<=0,N($I7)<=0),"FALTA TAMAÑO",IF($E7="","FALTA TIPO",IF(OR(N($F7)<0,N($G7)<0,N($F7)+N($H7)>$W7+0.001),"SE SALE A LO LARGO",IF(N($G7)+N($I7)>MIN($S7,$T7)+0.001,"SE SALE POR ARRIBA","OK")))))) -> OK | L7: Modelo R1.5: jambas en X = 64.25 y 194.39 cm, dintel a 240 cm | N7: =IF($D7="",0,VALUE(MID($D7,6,1))) -> 1 | O7: =IF($K7="OK",N($F7),0) -> 0.6425 | P7: =IF($K7="OK",N($F7)+N($H7),0) -> 1.9439 | Q7: =IF($K7="OK",N($G7),0) -> 0 | R7: =IF($K7="OK",N($G7)+N($I7),0) -> 2.4 | S7: =IF($N7=0,0,IF(INDEX($E$51:$E$54,$N7)="SÍ",IF(DATOS!$C$14="PLANO",DATOS!$C$17,IF(DATOS!$C$14="DOS AGUAS",DATOS!$C$17+(DATOS!$C$18-DATOS!$C$17)*(1-ABS(2*(N($F7))/DATOS!$C$23-1)),IF(DATOS!$C$14="UN AGUA",IF(N(DATOS!$C$25)=0,DATOS!$C$18-(DATOS!$C$18-DATOS!$C$17)*(N($F7))/DATOS!$C$23,DATOS!$C$17+(DATOS!$C$18-DATOS!$C$17)*(N($F7))/DATOS!$C$23),DATOS!$C$17+4*(DATOS!$C$18-DATOS!$C$17)*(N($F7))/DATOS!$C$23*(1-(N($F7))/DATOS!$C$23)))),INDEX($F$51:$F$54,$N7))) -> 10.62 | T7: =IF($N7=0,0,IF(INDEX($E$51:$E$54,$N7)="SÍ",IF(DATOS!$C$14="PLANO",DATOS!$C$17,IF(DATOS!$C$14="DOS AGUAS",DATOS!$C$17+(DATOS!$C$18-DATOS!$C$17)*(1-ABS(2*(N($F7)+N($H7))/DATOS!$C$23-1)),IF(DATOS!$C$14="UN AGUA",IF(N(DATOS!$C$25)=0,DATOS!$C$18-(DATOS!$C$18-DATOS!$C$17)*(N($F7)+N($H7))/DATOS!$C$23,DATOS!$C$17+(DATOS!$C$18-DATOS!$C$17)*(N($F7)+N($H7))/DATOS!$C$23),DATOS!$C$17+4*(DATOS!$C$18-DATOS!$C$17)*(N($F7)+N($H7))/DATOS!$C$23*(1-(N($F7)+N($H7))/DATOS!$C$23)))),INDEX($F$51:$F$54,$N7))) -> 10.62 | U7: =IF(AND($K7="OK",$E7="FIJA"),1,0) -> 0 | V7: =IF($K7="OK",1,0) -> 1 | W7: =IF($N7=0,0,INDEX($D$51:$D$54,$N7)) -> 10.08 | Y7: =($AB$6+DATOS!$AE$3+$DL$12)/$DL$11 -> 0.069503846 | Z7: =(DATOS!$AF$3+$DL$13)/$DL$11 -> 0.069503846 | AA7: =($AC$6+DATOS!$AI$3+$DL$12)/$DL$11 -> 0.7821135 | AB7: =(DATOS!$AJ$3+$DL$13)/$DL$11 -> 0.069503846 | AC7: =($AD$6+DATOS!$AM$3+$DL$12)/$DL$11 -> 1.4947232 | AD7: =(DATOS!$AN$3+$DL$13)/$DL$11 -> 0.069503846 | AE7: =($AE$6+DATOS!$AQ$3+$DL$12)/$DL$11 -> 2.5685185 | AF7: =(DATOS!$AR$3+$DL$13)/$DL$11 -> 0.069503846 | AH7: =(IF(AND($K$7="OK",$E$7="FIJA"),CHOOSE($N$7,$AB$6,$AC$6,$AD$6,$AE$6)+$O$7,0)+$DL$12)/$DL$11 -> 0.069503846 | AI7: =(IF(AND($K$7="OK",$E$7="FIJA"),$Q$7,0)+$DL$13)/$DL$11 -> 0.069503846 | AJ7: =(IF(AND($K$7="OK",$E$7="OPERABLE"),CHOOSE($N$7,$AB$6,$AC$6,$AD$6,$AE$6)+$O$7,0)+$DL$12)/$DL$11 -> 0.10870348 | AK7: =(IF(AND($K$7="OK",$E$7="OPERABLE"),$Q$7,0)+$DL$13)/$DL$11 -> 0.069503846 | AL7: =(IF(AND($K$8="OK",$E$8="FIJA"),CHOOSE($N$8,$AB$6,$AC$6,$AD$6,$AE$6)+$O$8,0)+$DL$12)/$DL$11 -> 0.069503846 | AM7: =(IF(AND($K$8="OK",$E$8="FIJA"),$Q$8,0)+$DL$13)/$DL$11 -> 0.069503846 | AN7: =(IF(AND($K$8="OK",$E$8="OPERABLE"),CHOOSE($N$8,$AB$6,$AC$6,$AD$6,$AE$6)+$O$8,0)+$DL$12)/$DL$11 -> 0.22123235 | AO7: =(IF(AND($K$8="OK",$E$8="OPERABLE"),$Q$8,0)+$DL$13)/$DL$11 -> 0.069503846 | AP7: =(IF(AND($K$9="OK",$E$9="FIJA"),CHOOSE($N$9,$AB$6,$AC$6,$AD$6,$AE$6)+$O$9,0)+$DL$12)/$DL$11 -> 0.7821135 | AQ7: =(IF(AND($K$9="OK",$E$9="FIJA"),$Q$9,0)+$DL$13)/$DL$11 -> 0.069503846 | AR7: =(IF(AND($K$9="OK",$E$9="OPERABLE"),CHOOSE($N$9,$AB$6,$AC$6,$AD$6,$AE$6)+$O$9,0)+$DL$12)/$DL$11 -> 0.069503846 | AS7: =(IF(AND($K$9="OK",$E$9="OPERABLE"),$Q$9,0)+$DL$13)/$DL$11 -> 0.069503846 | AT7: =(IF(AND($K$10="OK",$E$10="FIJA"),CHOOSE($N$10,$AB$6,$AC$6,$AD$6,$AE$6)+$O$10,0)+$DL$12)/$DL$11 -> 0.069503846 | AU7: =(IF(AND($K$10="OK",$E$10="FIJA"),$Q$10,0)+$DL$13)/$DL$11 -> 0.069503846 | AV7: =(IF(AND($K$10="OK",$E$10="OPERABLE"),CHOOSE($N$10,$AB$6,$AC$6,$AD$6,$AE$6)+$O$10,0)+$DL$12)/$DL$11 -> 0.069503846 | AW7: =(IF(AND($K$10="OK",$E$10="OPERABLE"),$Q$10,0)+$DL$13)/$DL$11 -> 0.069503846 | AX7: =(IF(AND($K$11="OK",$E$11="FIJA"),CHOOSE($N$11,$AB$6,$AC$6,$AD$6,$AE$6)+$O$11,0)+$DL$12)/$DL$11 -> 0.069503846 | AY7: =(IF(AND($K$11="OK",$E$11="FIJA"),$Q$11,0)+$DL$13)/$DL$11 -> 0.069503846 | AZ7: =(IF(AND($K$11="OK",$E$11="OPERABLE"),CHOOSE($N$11,$AB$6,$AC$6,$AD$6,$AE$6)+$O$11,0)+$DL$12)/$DL$11 -> 0.069503846 | BA7: =(IF(AND($K$11="OK",$E$11="OPERABLE"),$Q$11,0)+$DL$13)/$DL$11 -> 0.069503846 | BB7: =(IF(AND($K$12="OK",$E$12="FIJA"),CHOOSE($N$12,$AB$6,$AC$6,$AD$6,$AE$6)+$O$12,0)+$DL$12)/$DL$11 -> 0.069503846 | BC7: =(IF(AND($K$12="OK",$E$12="FIJA"),$Q$12,0)+$DL$13)/$DL$11 -> 0.069503846 | BD7: =(IF(AND($K$12="OK",$E$12="OPERABLE"),CHOOSE($N$12,$AB$6,$AC$6,$AD$6,$AE$6)+$O$12,0)+$DL$12)/$DL$11 -> 0.069503846 | BE7: =(IF(AND($K$12="OK",$E$12="OPERABLE"),$Q$12,0)+$DL$13)/$DL$11 -> 0.069503846 | BF7: =(IF(AND($K$13="OK",$E$13="FIJA"),CHOOSE($N$13,$AB$6,$AC$6,$AD$6,$AE$6)+$O$13,0)+$DL$12)/$DL$11 -> 0.069503846 | BG7: =(IF(AND($K$13="OK",$E$13="FIJA"),$Q$13,0)+$DL$13)/$DL$11 -> 0.069503846 | BH7: =(IF(AND($K$13="OK",$E$13="OPERABLE"),CHOOSE($N$13,$AB$6,$AC$6,$AD$6,$AE$6)+$O$13,0)+$DL$12)/$DL$11 -> 0.069503846 | BI7: =(IF(AND($K$13="OK",$E$13="OPERABLE"),$Q$13,0)+$DL$13)/$DL$11 -> 0.069503846 | BJ7: =(IF(AND($K$14="OK",$E$14="FIJA"),CHOOSE($N$14,$AB$6,$AC$6,$AD$6,$AE$6)+$O$14,0)+$DL$12)/$DL$11 -> 0.069503846 | BK7: =(IF(AND($K$14="OK",$E$14="FIJA"),$Q$14,0)+$DL$13)/$DL$11 -> 0.069503846 | BL7: =(IF(AND($K$14="OK",$E$14="OPERABLE"),CHOOSE($N$14,$AB$6,$AC$6,$AD$6,$AE$6)+$O$14,0)+$DL$12)/$DL$11 -> 0.069503846 | BM7: =(IF(AND($K$14="OK",$E$14="OPERABLE"),$Q$14,0)+$DL$13)/$DL$11 -> 0.069503846 | BN7: =(IF(AND($K$15="OK",$E$15="FIJA"),CHOOSE($N$15,$AB$6,$AC$6,$AD$6,$AE$6)+$O$15,0)+$DL$12)/$DL$11 -> 0.069503846 | BO7: =(IF(AND($K$15="OK",$E$15="FIJA"),$Q$15,0)+$DL$13)/$DL$11 -> 0.069503846 | BP7: =(IF(AND($K$15="OK",$E$15="OPERABLE"),CHOOSE($N$15,$AB$6,$AC$6,$AD$6,$AE$6)+$O$15,0)+$DL$12)/$DL$11 -> 0.069503846 | BQ7: =(IF(AND($K$15="OK",$E$15="OPERABLE"),$Q$15,0)+$DL$13)/$DL$11 -> 0.069503846 | BR7: =(IF(AND($K$16="OK",$E$16="FIJA"),CHOOSE($N$16,$AB$6,$AC$6,$AD$6,$AE$6)+$O$16,0)+$DL$12)/$DL$11 -> 0.069503846 | BS7: =(IF(AND($K$16="OK",$E$16="FIJA"),$Q$16,0)+$DL$13)/$DL$11 -> 0.069503846 | BT7: =(IF(AND($K$16="OK",$E$16="OPERABLE"),CHOOSE($N$16,$AB$6,$AC$6,$AD$6,$AE$6)+$O$16,0)+$DL$12)/$DL$11 -> 0.069503846 | BU7: =(IF(AND($K$16="OK",$E$16="OPERABLE"),$Q$16,0)+$DL$13)/$DL$11 -> 0.069503846 | BV7: =(IF(AND($K$17="OK",$E$17="FIJA"),CHOOSE($N$17,$AB$6,$AC$6,$AD$6,$AE$6)+$O$17,0)+$DL$12)/$DL$11 -> 0.069503846 | BW7: =(IF(AND($K$17="OK",$E$17="FIJA"),$Q$17,0)+$DL$13)/$DL$11 -> 0.069503846 | BX7: =(IF(AND($K$17="OK",$E$17="OPERABLE"),CHOOSE($N$17,$AB$6,$AC$6,$AD$6,$AE$6)+$O$17,0)+$DL$12)/$DL$11 -> 0.069503846 | BY7: =(IF(AND($K$17="OK",$E$17="OPERABLE"),$Q$17,0)+$DL$13)/$DL$11 -> 0.069503846 | BZ7: =(IF(AND($K$18="OK",$E$18="FIJA"),CHOOSE($N$18,$AB$6,$AC$6,$AD$6,$AE$6)+$O$18,0)+$DL$12)/$DL$11 -> 0.069503846 | CA7: =(IF(AND($K$18="OK",$E$18="FIJA"),$Q$18,0)+$DL$13)/$DL$11 -> 0.069503846 | CB7: =(IF(AND($K$18="OK",$E$18="OPERABLE"),CHOOSE($N$18,$AB$6,$AC$6,$AD$6,$AE$6)+$O$18,0)+$DL$12)/$DL$11 -> 0.069503846 | CC7: =(IF(AND($K$18="OK",$E$18="OPERABLE"),$Q$18,0)+$DL$13)/$DL$11 -> 0.069503846 | CD7: =(IF(AND($K$19="OK",$E$19="FIJA"),CHOOSE($N$19,$AB$6,$AC$6,$AD$6,$AE$6)+$O$19,0)+$DL$12)/$DL$11 -> 0.069503846 | CE7: =(IF(AND($K$19="OK",$E$19="FIJA"),$Q$19,0)+$DL$13)/$DL$11 -> 0.069503846 | CF7: =(IF(AND($K$19="OK",$E$19="OPERABLE"),CHOOSE($N$19,$AB$6,$AC$6,$AD$6,$AE$6)+$O$19,0)+$DL$12)/$DL$11 -> 0.069503846 | CG7: =(IF(AND($K$19="OK",$E$19="OPERABLE"),$Q$19,0)+$DL$13)/$DL$11 -> 0.069503846 | CH7: =(IF(AND($K$20="OK",$E$20="FIJA"),CHOOSE($N$20,$AB$6,$AC$6,$AD$6,$AE$6)+$O$20,0)+$DL$12)/$DL$11 -> 0.069503846 | CI7: =(IF(AND($K$20="OK",$E$20="FIJA"),$Q$20,0)+$DL$13)/$DL$11 -> 0.069503846 | CJ7: =(IF(AND($K$20="OK",$E$20="OPERABLE"),CHOOSE($N$20,$AB$6,$AC$6,$AD$6,$AE$6)+$O$20,0)+$DL$12)/$DL$11 -> 0.069503846 | CK7: =(IF(AND($K$20="OK",$E$20="OPERABLE"),$Q$20,0)+$DL$13)/$DL$11 -> 0.069503846 | CL7: =(IF(AND($K$21="OK",$E$21="FIJA"),CHOOSE($N$21,$AB$6,$AC$6,$AD$6,$AE$6)+$O$21,0)+$DL$12)/$DL$11 -> 0.069503846 | CM7: =(IF(AND($K$21="OK",$E$21="FIJA"),$Q$21,0)+$DL$13)/$DL$11 -> 0.069503846 | CN7: =(IF(AND($K$21="OK",$E$21="OPERABLE"),CHOOSE($N$21,$AB$6,$AC$6,$AD$6,$AE$6)+$O$21,0)+$DL$12)/$DL$11 -> 0.069503846 | CO7: =(IF(AND($K$21="OK",$E$21="OPERABLE"),$Q$21,0)+$DL$13)/$DL$11 -> 0.069503846 | CP7: =(IF(AND($K$22="OK",$E$22="FIJA"),CHOOSE($N$22,$AB$6,$AC$6,$AD$6,$AE$6)+$O$22,0)+$DL$12)/$DL$11 -> 0.069503846 | CQ7: =(IF(AND($K$22="OK",$E$22="FIJA"),$Q$22,0)+$DL$13)/$DL$11 -> 0.069503846 | CR7: =(IF(AND($K$22="OK",$E$22="OPERABLE"),CHOOSE($N$22,$AB$6,$AC$6,$AD$6,$AE$6)+$O$22,0)+$DL$12)/$DL$11 -> 0.069503846 | CS7: =(IF(AND($K$22="OK",$E$22="OPERABLE"),$Q$22,0)+$DL$13)/$DL$11 -> 0.069503846 | CT7: =(IF(AND($K$23="OK",$E$23="FIJA"),CHOOSE($N$23,$AB$6,$AC$6,$AD$6,$AE$6)+$O$23,0)+$DL$12)/$DL$11 -> 0.069503846 | CU7: =(IF(AND($K$23="OK",$E$23="FIJA"),$Q$23,0)+$DL$13)/$DL$11 -> 0.069503846 | CV7: =(IF(AND($K$23="OK",$E$23="OPERABLE"),CHOOSE($N$23,$AB$6,$AC$6,$AD$6,$AE$6)+$O$23,0)+$DL$12)/$DL$11 -> 0.069503846 | CW7: =(IF(AND($K$23="OK",$E$23="OPERABLE"),$Q$23,0)+$DL$13)/$DL$11 -> 0.069503846 | CX7: =(IF(AND($K$24="OK",$E$24="FIJA"),CHOOSE($N$24,$AB$6,$AC$6,$AD$6,$AE$6)+$O$24,0)+$DL$12)/$DL$11 -> 0.069503846 | CY7: =(IF(AND($K$24="OK",$E$24="FIJA"),$Q$24,0)+$DL$13)/$DL$11 -> 0.069503846 | CZ7: =(IF(AND($K$24="OK",$E$24="OPERABLE"),CHOOSE($N$24,$AB$6,$AC$6,$AD$6,$AE$6)+$O$24,0)+$DL$12)/$DL$11 -> 0.069503846 | DA7: =(IF(AND($K$24="OK",$E$24="OPERABLE"),$Q$24,0)+$DL$13)/$DL$11 -> 0.069503846 | DB7: =(IF(AND($K$25="OK",$E$25="FIJA"),CHOOSE($N$25,$AB$6,$AC$6,$AD$6,$AE$6)+$O$25,0)+$DL$12)/$DL$11 -> 0.069503846 | DC7: =(IF(AND($K$25="OK",$E$25="FIJA"),$Q$25,0)+$DL$13)/$DL$11 -> 0.069503846 | DD7: =(IF(AND($K$25="OK",$E$25="OPERABLE"),CHOOSE($N$25,$AB$6,$AC$6,$AD$6,$AE$6)+$O$25,0)+$DL$12)/$DL$11 -> 0.069503846 | DE7: =(IF(AND($K$25="OK",$E$25="OPERABLE"),$Q$25,0)+$DL$13)/$DL$11 -> 0.069503846 | DF7: =(IF(AND($K$26="OK",$E$26="FIJA"),CHOOSE($N$26,$AB$6,$AC$6,$AD$6,$AE$6)+$O$26,0)+$DL$12)/$DL$11 -> 0.069503846 | DG7: =(IF(AND($K$26="OK",$E$26="FIJA"),$Q$26,0)+$DL$13)/$DL$11 -> 0.069503846 | DH7: =(IF(AND($K$26="OK",$E$26="OPERABLE"),CHOOSE($N$26,$AB$6,$AC$6,$AD$6,$AE$6)+$O$26,0)+$DL$12)/$DL$11 -> 0.069503846 | DI7: =(IF(AND($K$26="OK",$E$26="OPERABLE"),$Q$26,0)+$DL$13)/$DL$11 -> 0.069503846 | DK7: ext x | DL7: =$AE$6+$D$54 -> 56.96
B8: 2 | C8: Vano del nose dock, cortina de oruga (muro de atrás) | D8: MURO 1 | E8: OPERABLE | F8: 2.4869 | G8: 0 | H8: 5.1016 | I8: 6.33 | J8: =IF($K8="OK",$H8*$I8,0) -> 32.293128 | K8: =IF($D8="","",IF(OR($F8="",$G8=""),"FALTA POSICIÓN",IF(OR(N($H8)<=0,N($I8)<=0),"FALTA TAMAÑO",IF($E8="","FALTA TIPO",IF(OR(N($F8)<0,N($G8)<0,N($F8)+N($H8)>$W8+0.001),"SE SALE A LO LARGO",IF(N($G8)+N($I8)>MIN($S8,$T8)+0.001,"SE SALE POR ARRIBA","OK")))))) -> OK | L8: Modelo R1.5: jambas en X = 248.69 y 758.85 cm, dintel a 633 cm | N8: =IF($D8="",0,VALUE(MID($D8,6,1))) -> 1 | O8: =IF($K8="OK",N($F8),0) -> 2.4869 | P8: =IF($K8="OK",N($F8)+N($H8),0) -> 7.5885 | Q8: =IF($K8="OK",N($G8),0) -> 0 | R8: =IF($K8="OK",N($G8)+N($I8),0) -> 6.33 | S8: =IF($N8=0,0,IF(INDEX($E$51:$E$54,$N8)="SÍ",IF(DATOS!$C$14="PLANO",DATOS!$C$17,IF(DATOS!$C$14="DOS AGUAS",DATOS!$C$17+(DATOS!$C$18-DATOS!$C$17)*(1-ABS(2*(N($F8))/DATOS!$C$23-1)),IF(DATOS!$C$14="UN AGUA",IF(N(DATOS!$C$25)=0,DATOS!$C$18-(DATOS!$C$18-DATOS!$C$17)*(N($F8))/DATOS!$C$23,DATOS!$C$17+(DATOS!$C$18-DATOS!$C$17)*(N($F8))/DATOS!$C$23),DATOS!$C$17+4*(DATOS!$C$18-DATOS!$C$17)*(N($F8))/DATOS!$C$23*(1-(N($F8))/DATOS!$C$23)))),INDEX($F$51:$F$54,$N8))) -> 10.62 | T8: =IF($N8=0,0,IF(INDEX($E$51:$E$54,$N8)="SÍ",IF(DATOS!$C$14="PLANO",DATOS!$C$17,IF(DATOS!$C$14="DOS AGUAS",DATOS!$C$17+(DATOS!$C$18-DATOS!$C$17)*(1-ABS(2*(N($F8)+N($H8))/DATOS!$C$23-1)),IF(DATOS!$C$14="UN AGUA",IF(N(DATOS!$C$25)=0,DATOS!$C$18-(DATOS!$C$18-DATOS!$C$17)*(N($F8)+N($H8))/DATOS!$C$23,DATOS!$C$17+(DATOS!$C$18-DATOS!$C$17)*(N($F8)+N($H8))/DATOS!$C$23),DATOS!$C$17+4*(DATOS!$C$18-DATOS!$C$17)*(N($F8)+N($H8))/DATOS!$C$23*(1-(N($F8)+N($H8))/DATOS!$C$23)))),INDEX($F$51:$F$54,$N8))) -> 10.62 | U8: =IF(AND($K8="OK",$E8="FIJA"),1,0) -> 0 | V8: =IF($K8="OK",1,0) -> 1 | W8: =IF($N8=0,0,INDEX($D$51:$D$54,$N8)) -> 10.08 | Y8: =($AB$6+DATOS!$AE$4+$DL$12)/$DL$11 -> 0.68449574 | Z8: =(DATOS!$AF$4+$DL$13)/$DL$11 -> 0.069503846 | AA8: =($AC$6+DATOS!$AI$4+$DL$12)/$DL$11 -> 1.3971054 | AB8: =(DATOS!$AJ$4+$DL$13)/$DL$11 -> 0.069503846 | AC8: =($AD$6+DATOS!$AM$4+$DL$12)/$DL$11 -> 2.4709008 | AD8: =(DATOS!$AN$4+$DL$13)/$DL$11 -> 0.069503846 | AE8: =($AE$6+DATOS!$AQ$4+$DL$12)/$DL$11 -> 3.5446962 | AF8: =(DATOS!$AR$4+$DL$13)/$DL$11 -> 0.069503846 | AH8: =(IF(AND($K$7="OK",$E$7="FIJA"),CHOOSE($N$7,$AB$6,$AC$6,$AD$6,$AE$6)+$P$7,0)+$DL$12)/$DL$11 -> 0.069503846 | AI8: =(IF(AND($K$7="OK",$E$7="FIJA"),$Q$7,0)+$DL$13)/$DL$11 -> 0.069503846 | AJ8: =(IF(AND($K$7="OK",$E$7="OPERABLE"),CHOOSE($N$7,$AB$6,$AC$6,$AD$6,$AE$6)+$P$7,0)+$DL$12)/$DL$11 -> 0.18810333 | AK8: =(IF(AND($K$7="OK",$E$7="OPERABLE"),$Q$7,0)+$DL$13)/$DL$11 -> 0.069503846 | AL8: =(IF(AND($K$8="OK",$E$8="FIJA"),CHOOSE($N$8,$AB$6,$AC$6,$AD$6,$AE$6)+$P$8,0)+$DL$12)/$DL$11 -> 0.069503846 | AM8: =(IF(AND($K$8="OK",$E$8="FIJA"),$Q$8,0)+$DL$13)/$DL$11 -> 0.069503846 | AN8: =(IF(AND($K$8="OK",$E$8="OPERABLE"),CHOOSE($N$8,$AB$6,$AC$6,$AD$6,$AE$6)+$P$8,0)+$DL$12)/$DL$11 -> 0.53248659 | AO8: =(IF(AND($K$8="OK",$E$8="OPERABLE"),$Q$8,0)+$DL$13)/$DL$11 -> 0.069503846 | AP8: =(IF(AND($K$9="OK",$E$9="FIJA"),CHOOSE($N$9,$AB$6,$AC$6,$AD$6,$AE$6)+$P$9,0)+$DL$12)/$DL$11 -> 1.3971054 | AQ8: =(IF(AND($K$9="OK",$E$9="FIJA"),$Q$9,0)+$DL$13)/$DL$11 -> 0.069503846 | AR8: =(IF(AND($K$9="OK",$E$9="OPERABLE"),CHOOSE($N$9,$AB$6,$AC$6,$AD$6,$AE$6)+$P$9,0)+$DL$12)/$DL$11 -> 0.069503846 | AS8: =(IF(AND($K$9="OK",$E$9="OPERABLE"),$Q$9,0)+$DL$13)/$DL$11 -> 0.069503846 | AT8: =(IF(AND($K$10="OK",$E$10="FIJA"),CHOOSE($N$10,$AB$6,$AC$6,$AD$6,$AE$6)+$P$10,0)+$DL$12)/$DL$11 -> 0.069503846 | AU8: =(IF(AND($K$10="OK",$E$10="FIJA"),$Q$10,0)+$DL$13)/$DL$11 -> 0.069503846 | AV8: =(IF(AND($K$10="OK",$E$10="OPERABLE"),CHOOSE($N$10,$AB$6,$AC$6,$AD$6,$AE$6)+$P$10,0)+$DL$12)/$DL$11 -> 0.069503846 | AW8: =(IF(AND($K$10="OK",$E$10="OPERABLE"),$Q$10,0)+$DL$13)/$DL$11 -> 0.069503846 | AX8: =(IF(AND($K$11="OK",$E$11="FIJA"),CHOOSE($N$11,$AB$6,$AC$6,$AD$6,$AE$6)+$P$11,0)+$DL$12)/$DL$11 -> 0.069503846 | AY8: =(IF(AND($K$11="OK",$E$11="FIJA"),$Q$11,0)+$DL$13)/$DL$11 -> 0.069503846 | AZ8: =(IF(AND($K$11="OK",$E$11="OPERABLE"),CHOOSE($N$11,$AB$6,$AC$6,$AD$6,$AE$6)+$P$11,0)+$DL$12)/$DL$11 -> 0.069503846 | BA8: =(IF(AND($K$11="OK",$E$11="OPERABLE"),$Q$11,0)+$DL$13)/$DL$11 -> 0.069503846 | BB8: =(IF(AND($K$12="OK",$E$12="FIJA"),CHOOSE($N$12,$AB$6,$AC$6,$AD$6,$AE$6)+$P$12,0)+$DL$12)/$DL$11 -> 0.069503846 | BC8: =(IF(AND($K$12="OK",$E$12="FIJA"),$Q$12,0)+$DL$13)/$DL$11 -> 0.069503846 | BD8: =(IF(AND($K$12="OK",$E$12="OPERABLE"),CHOOSE($N$12,$AB$6,$AC$6,$AD$6,$AE$6)+$P$12,0)+$DL$12)/$DL$11 -> 0.069503846 | BE8: =(IF(AND($K$12="OK",$E$12="OPERABLE"),$Q$12,0)+$DL$13)/$DL$11 -> 0.069503846 | BF8: =(IF(AND($K$13="OK",$E$13="FIJA"),CHOOSE($N$13,$AB$6,$AC$6,$AD$6,$AE$6)+$P$13,0)+$DL$12)/$DL$11 -> 0.069503846 | BG8: =(IF(AND($K$13="OK",$E$13="FIJA"),$Q$13,0)+$DL$13)/$DL$11 -> 0.069503846 | BH8: =(IF(AND($K$13="OK",$E$13="OPERABLE"),CHOOSE($N$13,$AB$6,$AC$6,$AD$6,$AE$6)+$P$13,0)+$DL$12)/$DL$11 -> 0.069503846 | BI8: =(IF(AND($K$13="OK",$E$13="OPERABLE"),$Q$13,0)+$DL$13)/$DL$11 -> 0.069503846 | BJ8: =(IF(AND($K$14="OK",$E$14="FIJA"),CHOOSE($N$14,$AB$6,$AC$6,$AD$6,$AE$6)+$P$14,0)+$DL$12)/$DL$11 -> 0.069503846 | BK8: =(IF(AND($K$14="OK",$E$14="FIJA"),$Q$14,0)+$DL$13)/$DL$11 -> 0.069503846 | BL8: =(IF(AND($K$14="OK",$E$14="OPERABLE"),CHOOSE($N$14,$AB$6,$AC$6,$AD$6,$AE$6)+$P$14,0)+$DL$12)/$DL$11 -> 0.069503846 | BM8: =(IF(AND($K$14="OK",$E$14="OPERABLE"),$Q$14,0)+$DL$13)/$DL$11 -> 0.069503846 | BN8: =(IF(AND($K$15="OK",$E$15="FIJA"),CHOOSE($N$15,$AB$6,$AC$6,$AD$6,$AE$6)+$P$15,0)+$DL$12)/$DL$11 -> 0.069503846 | BO8: =(IF(AND($K$15="OK",$E$15="FIJA"),$Q$15,0)+$DL$13)/$DL$11 -> 0.069503846 | BP8: =(IF(AND($K$15="OK",$E$15="OPERABLE"),CHOOSE($N$15,$AB$6,$AC$6,$AD$6,$AE$6)+$P$15,0)+$DL$12)/$DL$11 -> 0.069503846 | BQ8: =(IF(AND($K$15="OK",$E$15="OPERABLE"),$Q$15,0)+$DL$13)/$DL$11 -> 0.069503846 | BR8: =(IF(AND($K$16="OK",$E$16="FIJA"),CHOOSE($N$16,$AB$6,$AC$6,$AD$6,$AE$6)+$P$16,0)+$DL$12)/$DL$11 -> 0.069503846 | BS8: =(IF(AND($K$16="OK",$E$16="FIJA"),$Q$16,0)+$DL$13)/$DL$11 -> 0.069503846 | BT8: =(IF(AND($K$16="OK",$E$16="OPERABLE"),CHOOSE($N$16,$AB$6,$AC$6,$AD$6,$AE$6)+$P$16,0)+$DL$12)/$DL$11 -> 0.069503846 | BU8: =(IF(AND($K$16="OK",$E$16="OPERABLE"),$Q$16,0)+$DL$13)/$DL$11 -> 0.069503846 | BV8: =(IF(AND($K$17="OK",$E$17="FIJA"),CHOOSE($N$17,$AB$6,$AC$6,$AD$6,$AE$6)+$P$17,0)+$DL$12)/$DL$11 -> 0.069503846 | BW8: =(IF(AND($K$17="OK",$E$17="FIJA"),$Q$17,0)+$DL$13)/$DL$11 -> 0.069503846 | BX8: =(IF(AND($K$17="OK",$E$17="OPERABLE"),CHOOSE($N$17,$AB$6,$AC$6,$AD$6,$AE$6)+$P$17,0)+$DL$12)/$DL$11 -> 0.069503846 | BY8: =(IF(AND($K$17="OK",$E$17="OPERABLE"),$Q$17,0)+$DL$13)/$DL$11 -> 0.069503846 | BZ8: =(IF(AND($K$18="OK",$E$18="FIJA"),CHOOSE($N$18,$AB$6,$AC$6,$AD$6,$AE$6)+$P$18,0)+$DL$12)/$DL$11 -> 0.069503846 | CA8: =(IF(AND($K$18="OK",$E$18="FIJA"),$Q$18,0)+$DL$13)/$DL$11 -> 0.069503846 | CB8: =(IF(AND($K$18="OK",$E$18="OPERABLE"),CHOOSE($N$18,$AB$6,$AC$6,$AD$6,$AE$6)+$P$18,0)+$DL$12)/$DL$11 -> 0.069503846 | CC8: =(IF(AND($K$18="OK",$E$18="OPERABLE"),$Q$18,0)+$DL$13)/$DL$11 -> 0.069503846 | CD8: =(IF(AND($K$19="OK",$E$19="FIJA"),CHOOSE($N$19,$AB$6,$AC$6,$AD$6,$AE$6)+$P$19,0)+$DL$12)/$DL$11 -> 0.069503846 | CE8: =(IF(AND($K$19="OK",$E$19="FIJA"),$Q$19,0)+$DL$13)/$DL$11 -> 0.069503846 | CF8: =(IF(AND($K$19="OK",$E$19="OPERABLE"),CHOOSE($N$19,$AB$6,$AC$6,$AD$6,$AE$6)+$P$19,0)+$DL$12)/$DL$11 -> 0.069503846 | CG8: =(IF(AND($K$19="OK",$E$19="OPERABLE"),$Q$19,0)+$DL$13)/$DL$11 -> 0.069503846 | CH8: =(IF(AND($K$20="OK",$E$20="FIJA"),CHOOSE($N$20,$AB$6,$AC$6,$AD$6,$AE$6)+$P$20,0)+$DL$12)/$DL$11 -> 0.069503846 | CI8: =(IF(AND($K$20="OK",$E$20="FIJA"),$Q$20,0)+$DL$13)/$DL$11 -> 0.069503846 | CJ8: =(IF(AND($K$20="OK",$E$20="OPERABLE"),CHOOSE($N$20,$AB$6,$AC$6,$AD$6,$AE$6)+$P$20,0)+$DL$12)/$DL$11 -> 0.069503846 | CK8: =(IF(AND($K$20="OK",$E$20="OPERABLE"),$Q$20,0)+$DL$13)/$DL$11 -> 0.069503846 | CL8: =(IF(AND($K$21="OK",$E$21="FIJA"),CHOOSE($N$21,$AB$6,$AC$6,$AD$6,$AE$6)+$P$21,0)+$DL$12)/$DL$11 -> 0.069503846 | CM8: =(IF(AND($K$21="OK",$E$21="FIJA"),$Q$21,0)+$DL$13)/$DL$11 -> 0.069503846 | CN8: =(IF(AND($K$21="OK",$E$21="OPERABLE"),CHOOSE($N$21,$AB$6,$AC$6,$AD$6,$AE$6)+$P$21,0)+$DL$12)/$DL$11 -> 0.069503846 | CO8: =(IF(AND($K$21="OK",$E$21="OPERABLE"),$Q$21,0)+$DL$13)/$DL$11 -> 0.069503846 | CP8: =(IF(AND($K$22="OK",$E$22="FIJA"),CHOOSE($N$22,$AB$6,$AC$6,$AD$6,$AE$6)+$P$22,0)+$DL$12)/$DL$11 -> 0.069503846 | CQ8: =(IF(AND($K$22="OK",$E$22="FIJA"),$Q$22,0)+$DL$13)/$DL$11 -> 0.069503846 | CR8: =(IF(AND($K$22="OK",$E$22="OPERABLE"),CHOOSE($N$22,$AB$6,$AC$6,$AD$6,$AE$6)+$P$22,0)+$DL$12)/$DL$11 -> 0.069503846 | CS8: =(IF(AND($K$22="OK",$E$22="OPERABLE"),$Q$22,0)+$DL$13)/$DL$11 -> 0.069503846 | CT8: =(IF(AND($K$23="OK",$E$23="FIJA"),CHOOSE($N$23,$AB$6,$AC$6,$AD$6,$AE$6)+$P$23,0)+$DL$12)/$DL$11 -> 0.069503846 | CU8: =(IF(AND($K$23="OK",$E$23="FIJA"),$Q$23,0)+$DL$13)/$DL$11 -> 0.069503846 | CV8: =(IF(AND($K$23="OK",$E$23="OPERABLE"),CHOOSE($N$23,$AB$6,$AC$6,$AD$6,$AE$6)+$P$23,0)+$DL$12)/$DL$11 -> 0.069503846 | CW8: =(IF(AND($K$23="OK",$E$23="OPERABLE"),$Q$23,0)+$DL$13)/$DL$11 -> 0.069503846 | CX8: =(IF(AND($K$24="OK",$E$24="FIJA"),CHOOSE($N$24,$AB$6,$AC$6,$AD$6,$AE$6)+$P$24,0)+$DL$12)/$DL$11 -> 0.069503846 | CY8: =(IF(AND($K$24="OK",$E$24="FIJA"),$Q$24,0)+$DL$13)/$DL$11 -> 0.069503846 | CZ8: =(IF(AND($K$24="OK",$E$24="OPERABLE"),CHOOSE($N$24,$AB$6,$AC$6,$AD$6,$AE$6)+$P$24,0)+$DL$12)/$DL$11 -> 0.069503846 | DA8: =(IF(AND($K$24="OK",$E$24="OPERABLE"),$Q$24,0)+$DL$13)/$DL$11 -> 0.069503846 | DB8: =(IF(AND($K$25="OK",$E$25="FIJA"),CHOOSE($N$25,$AB$6,$AC$6,$AD$6,$AE$6)+$P$25,0)+$DL$12)/$DL$11 -> 0.069503846 | DC8: =(IF(AND($K$25="OK",$E$25="FIJA"),$Q$25,0)+$DL$13)/$DL$11 -> 0.069503846 | DD8: =(IF(AND($K$25="OK",$E$25="OPERABLE"),CHOOSE($N$25,$AB$6,$AC$6,$AD$6,$AE$6)+$P$25,0)+$DL$12)/$DL$11 -> 0.069503846 | DE8: =(IF(AND($K$25="OK",$E$25="OPERABLE"),$Q$25,0)+$DL$13)/$DL$11 -> 0.069503846 | DF8: =(IF(AND($K$26="OK",$E$26="FIJA"),CHOOSE($N$26,$AB$6,$AC$6,$AD$6,$AE$6)+$P$26,0)+$DL$12)/$DL$11 -> 0.069503846 | DG8: =(IF(AND($K$26="OK",$E$26="FIJA"),$Q$26,0)+$DL$13)/$DL$11 -> 0.069503846 | DH8: =(IF(AND($K$26="OK",$E$26="OPERABLE"),CHOOSE($N$26,$AB$6,$AC$6,$AD$6,$AE$6)+$P$26,0)+$DL$12)/$DL$11 -> 0.069503846 | DI8: =(IF(AND($K$26="OK",$E$26="OPERABLE"),$Q$26,0)+$DL$13)/$DL$11 -> 0.069503846 | DK8: ext y | DL8: =DATOS!$C$21*1.22 -> 12.9564
B9: 3 | C9: Frente abierto (Z = L): en STAAD no hay muro ni largueros | D9: MURO 2 | E9: FIJA | F9: 0 | G9: 0 | H9: 10.08 | I9: 9.82 | J9: =IF($K9="OK",$H9*$I9,0) -> 98.9856 | K9: =IF($D9="","",IF(OR($F9="",$G9=""),"FALTA POSICIÓN",IF(OR(N($H9)<=0,N($I9)<=0),"FALTA TAMAÑO",IF($E9="","FALTA TIPO",IF(OR(N($F9)<0,N($G9)<0,N($F9)+N($H9)>$W9+0.001),"SE SALE A LO LARGO",IF(N($G9)+N($I9)>MIN($S9,$T9)+0.001,"SE SALE POR ARRIBA","OK")))))) -> OK | L9: Modelo R1.5: el eje 4 (Z = 16 m) no tiene muro ni largueros; se toma como frente abierto (NTV 4.4, pág. 7) | N9: =IF($D9="",0,VALUE(MID($D9,6,1))) -> 2 | O9: =IF($K9="OK",N($F9),0) -> 0 | P9: =IF($K9="OK",N($F9)+N($H9),0) -> 10.08 | Q9: =IF($K9="OK",N($G9),0) -> 0 | R9: =IF($K9="OK",N($G9)+N($I9),0) -> 9.82 | S9: =IF($N9=0,0,IF(INDEX($E$51:$E$54,$N9)="SÍ",IF(DATOS!$C$14="PLANO",DATOS!$C$17,IF(DATOS!$C$14="DOS AGUAS",DATOS!$C$17+(DATOS!$C$18-DATOS!$C$17)*(1-ABS(2*(N($F9))/DATOS!$C$23-1)),IF(DATOS!$C$14="UN AGUA",IF(N(DATOS!$C$25)=0,DATOS!$C$18-(DATOS!$C$18-DATOS!$C$17)*(N($F9))/DATOS!$C$23,DATOS!$C$17+(DATOS!$C$18-DATOS!$C$17)*(N($F9))/DATOS!$C$23),DATOS!$C$17+4*(DATOS!$C$18-DATOS!$C$17)*(N($F9))/DATOS!$C$23*(1-(N($F9))/DATOS!$C$23)))),INDEX($F$51:$F$54,$N9))) -> 9.82 | T9: =IF($N9=0,0,IF(INDEX($E$51:$E$54,$N9)="SÍ",IF(DATOS!$C$14="PLANO",DATOS!$C$17,IF(DATOS!$C$14="DOS AGUAS",DATOS!$C$17+(DATOS!$C$18-DATOS!$C$17)*(1-ABS(2*(N($F9)+N($H9))/DATOS!$C$23-1)),IF(DATOS!$C$14="UN AGUA",IF(N(DATOS!$C$25)=0,DATOS!$C$18-(DATOS!$C$18-DATOS!$C$17)*(N($F9)+N($H9))/DATOS!$C$23,DATOS!$C$17+(DATOS!$C$18-DATOS!$C$17)*(N($F9)+N($H9))/DATOS!$C$23),DATOS!$C$17+4*(DATOS!$C$18-DATOS!$C$17)*(N($F9)+N($H9))/DATOS!$C$23*(1-(N($F9)+N($H9))/DATOS!$C$23)))),INDEX($F$51:$F$54,$N9))) -> 9.82 | U9: =IF(AND($K9="OK",$E9="FIJA"),1,0) -> 1 | V9: =IF($K9="OK",1,0) -> 1 | W9: =IF($N9=0,0,INDEX($D$51:$D$54,$N9)) -> 10.08 | Y9: =($AB$6+DATOS!$AE$5+$DL$12)/$DL$11 -> 0.68449574 | Z9: =(DATOS!$AF$5+$DL$13)/$DL$11 -> 0.71744174 | AA9: =($AC$6+DATOS!$AI$5+$DL$12)/$DL$11 -> 1.3971054 | AB9: =(DATOS!$AJ$5+$DL$13)/$DL$11 -> 0.66863286 | AC9: =($AD$6+DATOS!$AM$5+$DL$12)/$DL$11 -> 2.4709008 | AD9: =(DATOS!$AN$5+$DL$13)/$DL$11 -> 0.66863286 | AE9: =($AE$6+DATOS!$AQ$5+$DL$12)/$DL$11 -> 3.5446962 | AF9: =(DATOS!$AR$5+$DL$13)/$DL$11 -> 0.66863286 | AH9: =(IF(AND($K$7="OK",$E$7="FIJA"),CHOOSE($N$7,$AB$6,$AC$6,$AD$6,$AE$6)+$P$7,0)+$DL$12)/$DL$11 -> 0.069503846 | AI9: =(IF(AND($K$7="OK",$E$7="FIJA"),$R$7,0)+$DL$13)/$DL$11 -> 0.069503846 | AJ9: =(IF(AND($K$7="OK",$E$7="OPERABLE"),CHOOSE($N$7,$AB$6,$AC$6,$AD$6,$AE$6)+$P$7,0)+$DL$12)/$DL$11 -> 0.18810333 | AK9: =(IF(AND($K$7="OK",$E$7="OPERABLE"),$R$7,0)+$DL$13)/$DL$11 -> 0.21593049 | AL9: =(IF(AND($K$8="OK",$E$8="FIJA"),CHOOSE($N$8,$AB$6,$AC$6,$AD$6,$AE$6)+$P$8,0)+$DL$12)/$DL$11 -> 0.069503846 | AM9: =(IF(AND($K$8="OK",$E$8="FIJA"),$R$8,0)+$DL$13)/$DL$11 -> 0.069503846 | AN9: =(IF(AND($K$8="OK",$E$8="OPERABLE"),CHOOSE($N$8,$AB$6,$AC$6,$AD$6,$AE$6)+$P$8,0)+$DL$12)/$DL$11 -> 0.53248659 | AO9: =(IF(AND($K$8="OK",$E$8="OPERABLE"),$R$8,0)+$DL$13)/$DL$11 -> 0.45570411 | AP9: =(IF(AND($K$9="OK",$E$9="FIJA"),CHOOSE($N$9,$AB$6,$AC$6,$AD$6,$AE$6)+$P$9,0)+$DL$12)/$DL$11 -> 1.3971054 | AQ9: =(IF(AND($K$9="OK",$E$9="FIJA"),$R$9,0)+$DL$13)/$DL$11 -> 0.66863286 | AR9: =(IF(AND($K$9="OK",$E$9="OPERABLE"),CHOOSE($N$9,$AB$6,$AC$6,$AD$6,$AE$6)+$P$9,0)+$DL$12)/$DL$11 -> 0.069503846 | AS9: =(IF(AND($K$9="OK",$E$9="OPERABLE"),$R$9,0)+$DL$13)/$DL$11 -> 0.069503846 | AT9: =(IF(AND($K$10="OK",$E$10="FIJA"),CHOOSE($N$10,$AB$6,$AC$6,$AD$6,$AE$6)+$P$10,0)+$DL$12)/$DL$11 -> 0.069503846 | AU9: =(IF(AND($K$10="OK",$E$10="FIJA"),$R$10,0)+$DL$13)/$DL$11 -> 0.069503846 | AV9: =(IF(AND($K$10="OK",$E$10="OPERABLE"),CHOOSE($N$10,$AB$6,$AC$6,$AD$6,$AE$6)+$P$10,0)+$DL$12)/$DL$11 -> 0.069503846 | AW9: =(IF(AND($K$10="OK",$E$10="OPERABLE"),$R$10,0)+$DL$13)/$DL$11 -> 0.069503846 | AX9: =(IF(AND($K$11="OK",$E$11="FIJA"),CHOOSE($N$11,$AB$6,$AC$6,$AD$6,$AE$6)+$P$11,0)+$DL$12)/$DL$11 -> 0.069503846 | AY9: =(IF(AND($K$11="OK",$E$11="FIJA"),$R$11,0)+$DL$13)/$DL$11 -> 0.069503846 | AZ9: =(IF(AND($K$11="OK",$E$11="OPERABLE"),CHOOSE($N$11,$AB$6,$AC$6,$AD$6,$AE$6)+$P$11,0)+$DL$12)/$DL$11 -> 0.069503846 | BA9: =(IF(AND($K$11="OK",$E$11="OPERABLE"),$R$11,0)+$DL$13)/$DL$11 -> 0.069503846 | BB9: =(IF(AND($K$12="OK",$E$12="FIJA"),CHOOSE($N$12,$AB$6,$AC$6,$AD$6,$AE$6)+$P$12,0)+$DL$12)/$DL$11 -> 0.069503846 | BC9: =(IF(AND($K$12="OK",$E$12="FIJA"),$R$12,0)+$DL$13)/$DL$11 -> 0.069503846 | BD9: =(IF(AND($K$12="OK",$E$12="OPERABLE"),CHOOSE($N$12,$AB$6,$AC$6,$AD$6,$AE$6)+$P$12,0)+$DL$12)/$DL$11 -> 0.069503846 | BE9: =(IF(AND($K$12="OK",$E$12="OPERABLE"),$R$12,0)+$DL$13)/$DL$11 -> 0.069503846 | BF9: =(IF(AND($K$13="OK",$E$13="FIJA"),CHOOSE($N$13,$AB$6,$AC$6,$AD$6,$AE$6)+$P$13,0)+$DL$12)/$DL$11 -> 0.069503846 | BG9: =(IF(AND($K$13="OK",$E$13="FIJA"),$R$13,0)+$DL$13)/$DL$11 -> 0.069503846 | BH9: =(IF(AND($K$13="OK",$E$13="OPERABLE"),CHOOSE($N$13,$AB$6,$AC$6,$AD$6,$AE$6)+$P$13,0)+$DL$12)/$DL$11 -> 0.069503846 | BI9: =(IF(AND($K$13="OK",$E$13="OPERABLE"),$R$13,0)+$DL$13)/$DL$11 -> 0.069503846 | BJ9: =(IF(AND($K$14="OK",$E$14="FIJA"),CHOOSE($N$14,$AB$6,$AC$6,$AD$6,$AE$6)+$P$14,0)+$DL$12)/$DL$11 -> 0.069503846 | BK9: =(IF(AND($K$14="OK",$E$14="FIJA"),$R$14,0)+$DL$13)/$DL$11 -> 0.069503846 | BL9: =(IF(AND($K$14="OK",$E$14="OPERABLE"),CHOOSE($N$14,$AB$6,$AC$6,$AD$6,$AE$6)+$P$14,0)+$DL$12)/$DL$11 -> 0.069503846 | BM9: =(IF(AND($K$14="OK",$E$14="OPERABLE"),$R$14,0)+$DL$13)/$DL$11 -> 0.069503846 | BN9: =(IF(AND($K$15="OK",$E$15="FIJA"),CHOOSE($N$15,$AB$6,$AC$6,$AD$6,$AE$6)+$P$15,0)+$DL$12)/$DL$11 -> 0.069503846 | BO9: =(IF(AND($K$15="OK",$E$15="FIJA"),$R$15,0)+$DL$13)/$DL$11 -> 0.069503846 | BP9: =(IF(AND($K$15="OK",$E$15="OPERABLE"),CHOOSE($N$15,$AB$6,$AC$6,$AD$6,$AE$6)+$P$15,0)+$DL$12)/$DL$11 -> 0.069503846 | BQ9: =(IF(AND($K$15="OK",$E$15="OPERABLE"),$R$15,0)+$DL$13)/$DL$11 -> 0.069503846 | BR9: =(IF(AND($K$16="OK",$E$16="FIJA"),CHOOSE($N$16,$AB$6,$AC$6,$AD$6,$AE$6)+$P$16,0)+$DL$12)/$DL$11 -> 0.069503846 | BS9: =(IF(AND($K$16="OK",$E$16="FIJA"),$R$16,0)+$DL$13)/$DL$11 -> 0.069503846 | BT9: =(IF(AND($K$16="OK",$E$16="OPERABLE"),CHOOSE($N$16,$AB$6,$AC$6,$AD$6,$AE$6)+$P$16,0)+$DL$12)/$DL$11 -> 0.069503846 | BU9: =(IF(AND($K$16="OK",$E$16="OPERABLE"),$R$16,0)+$DL$13)/$DL$11 -> 0.069503846 | BV9: =(IF(AND($K$17="OK",$E$17="FIJA"),CHOOSE($N$17,$AB$6,$AC$6,$AD$6,$AE$6)+$P$17,0)+$DL$12)/$DL$11 -> 0.069503846 | BW9: =(IF(AND($K$17="OK",$E$17="FIJA"),$R$17,0)+$DL$13)/$DL$11 -> 0.069503846 | BX9: =(IF(AND($K$17="OK",$E$17="OPERABLE"),CHOOSE($N$17,$AB$6,$AC$6,$AD$6,$AE$6)+$P$17,0)+$DL$12)/$DL$11 -> 0.069503846 | BY9: =(IF(AND($K$17="OK",$E$17="OPERABLE"),$R$17,0)+$DL$13)/$DL$11 -> 0.069503846 | BZ9: =(IF(AND($K$18="OK",$E$18="FIJA"),CHOOSE($N$18,$AB$6,$AC$6,$AD$6,$AE$6)+$P$18,0)+$DL$12)/$DL$11 -> 0.069503846 | CA9: =(IF(AND($K$18="OK",$E$18="FIJA"),$R$18,0)+$DL$13)/$DL$11 -> 0.069503846 | CB9: =(IF(AND($K$18="OK",$E$18="OPERABLE"),CHOOSE($N$18,$AB$6,$AC$6,$AD$6,$AE$6)+$P$18,0)+$DL$12)/$DL$11 -> 0.069503846 | CC9: =(IF(AND($K$18="OK",$E$18="OPERABLE"),$R$18,0)+$DL$13)/$DL$11 -> 0.069503846 | CD9: =(IF(AND($K$19="OK",$E$19="FIJA"),CHOOSE($N$19,$AB$6,$AC$6,$AD$6,$AE$6)+$P$19,0)+$DL$12)/$DL$11 -> 0.069503846 | CE9: =(IF(AND($K$19="OK",$E$19="FIJA"),$R$19,0)+$DL$13)/$DL$11 -> 0.069503846 | CF9: =(IF(AND($K$19="OK",$E$19="OPERABLE"),CHOOSE($N$19,$AB$6,$AC$6,$AD$6,$AE$6)+$P$19,0)+$DL$12)/$DL$11 -> 0.069503846 | CG9: =(IF(AND($K$19="OK",$E$19="OPERABLE"),$R$19,0)+$DL$13)/$DL$11 -> 0.069503846 | CH9: =(IF(AND($K$20="OK",$E$20="FIJA"),CHOOSE($N$20,$AB$6,$AC$6,$AD$6,$AE$6)+$P$20,0)+$DL$12)/$DL$11 -> 0.069503846 | CI9: =(IF(AND($K$20="OK",$E$20="FIJA"),$R$20,0)+$DL$13)/$DL$11 -> 0.069503846 | CJ9: =(IF(AND($K$20="OK",$E$20="OPERABLE"),CHOOSE($N$20,$AB$6,$AC$6,$AD$6,$AE$6)+$P$20,0)+$DL$12)/$DL$11 -> 0.069503846 | CK9: =(IF(AND($K$20="OK",$E$20="OPERABLE"),$R$20,0)+$DL$13)/$DL$11 -> 0.069503846 | CL9: =(IF(AND($K$21="OK",$E$21="FIJA"),CHOOSE($N$21,$AB$6,$AC$6,$AD$6,$AE$6)+$P$21,0)+$DL$12)/$DL$11 -> 0.069503846 | CM9: =(IF(AND($K$21="OK",$E$21="FIJA"),$R$21,0)+$DL$13)/$DL$11 -> 0.069503846 | CN9: =(IF(AND($K$21="OK",$E$21="OPERABLE"),CHOOSE($N$21,$AB$6,$AC$6,$AD$6,$AE$6)+$P$21,0)+$DL$12)/$DL$11 -> 0.069503846 | CO9: =(IF(AND($K$21="OK",$E$21="OPERABLE"),$R$21,0)+$DL$13)/$DL$11 -> 0.069503846 | CP9: =(IF(AND($K$22="OK",$E$22="FIJA"),CHOOSE($N$22,$AB$6,$AC$6,$AD$6,$AE$6)+$P$22,0)+$DL$12)/$DL$11 -> 0.069503846 | CQ9: =(IF(AND($K$22="OK",$E$22="FIJA"),$R$22,0)+$DL$13)/$DL$11 -> 0.069503846 | CR9: =(IF(AND($K$22="OK",$E$22="OPERABLE"),CHOOSE($N$22,$AB$6,$AC$6,$AD$6,$AE$6)+$P$22,0)+$DL$12)/$DL$11 -> 0.069503846 | CS9: =(IF(AND($K$22="OK",$E$22="OPERABLE"),$R$22,0)+$DL$13)/$DL$11 -> 0.069503846 | CT9: =(IF(AND($K$23="OK",$E$23="FIJA"),CHOOSE($N$23,$AB$6,$AC$6,$AD$6,$AE$6)+$P$23,0)+$DL$12)/$DL$11 -> 0.069503846 | CU9: =(IF(AND($K$23="OK",$E$23="FIJA"),$R$23,0)+$DL$13)/$DL$11 -> 0.069503846 | CV9: =(IF(AND($K$23="OK",$E$23="OPERABLE"),CHOOSE($N$23,$AB$6,$AC$6,$AD$6,$AE$6)+$P$23,0)+$DL$12)/$DL$11 -> 0.069503846 | CW9: =(IF(AND($K$23="OK",$E$23="OPERABLE"),$R$23,0)+$DL$13)/$DL$11 -> 0.069503846 | CX9: =(IF(AND($K$24="OK",$E$24="FIJA"),CHOOSE($N$24,$AB$6,$AC$6,$AD$6,$AE$6)+$P$24,0)+$DL$12)/$DL$11 -> 0.069503846 | CY9: =(IF(AND($K$24="OK",$E$24="FIJA"),$R$24,0)+$DL$13)/$DL$11 -> 0.069503846 | CZ9: =(IF(AND($K$24="OK",$E$24="OPERABLE"),CHOOSE($N$24,$AB$6,$AC$6,$AD$6,$AE$6)+$P$24,0)+$DL$12)/$DL$11 -> 0.069503846 | DA9: =(IF(AND($K$24="OK",$E$24="OPERABLE"),$R$24,0)+$DL$13)/$DL$11 -> 0.069503846 | DB9: =(IF(AND($K$25="OK",$E$25="FIJA"),CHOOSE($N$25,$AB$6,$AC$6,$AD$6,$AE$6)+$P$25,0)+$DL$12)/$DL$11 -> 0.069503846 | DC9: =(IF(AND($K$25="OK",$E$25="FIJA"),$R$25,0)+$DL$13)/$DL$11 -> 0.069503846 | DD9: =(IF(AND($K$25="OK",$E$25="OPERABLE"),CHOOSE($N$25,$AB$6,$AC$6,$AD$6,$AE$6)+$P$25,0)+$DL$12)/$DL$11 -> 0.069503846 | DE9: =(IF(AND($K$25="OK",$E$25="OPERABLE"),$R$25,0)+$DL$13)/$DL$11 -> 0.069503846 | DF9: =(IF(AND($K$26="OK",$E$26="FIJA"),CHOOSE($N$26,$AB$6,$AC$6,$AD$6,$AE$6)+$P$26,0)+$DL$12)/$DL$11 -> 0.069503846 | DG9: =(IF(AND($K$26="OK",$E$26="FIJA"),$R$26,0)+$DL$13)/$DL$11 -> 0.069503846 | DH9: =(IF(AND($K$26="OK",$E$26="OPERABLE"),CHOOSE($N$26,$AB$6,$AC$6,$AD$6,$AE$6)+$P$26,0)+$DL$12)/$DL$11 -> 0.069503846 | DI9: =(IF(AND($K$26="OK",$E$26="OPERABLE"),$R$26,0)+$DL$13)/$DL$11 -> 0.069503846 | DK9: margen | DL9: =0.02*$DL$7 -> 1.1392
B10: 4 | J10: =IF($K10="OK",$H10*$I10,0) -> 0 | K10: =IF($D10="","",IF(OR($F10="",$G10=""),"FALTA POSICIÓN",IF(OR(N($H10)<=0,N($I10)<=0),"FALTA TAMAÑO",IF($E10="","FALTA TIPO",IF(OR(N($F10)<0,N($G10)<0,N($F10)+N($H10)>$W10+0.001),"SE SALE A LO LARGO",IF(N($G10)+N($I10)>MIN($S10,$T10)+0.001,"SE SALE POR ARRIBA","OK")))))) | N10: =IF($D10="",0,VALUE(MID($D10,6,1))) -> 0 | O10: =IF($K10="OK",N($F10),0) -> 0 | P10: =IF($K10="OK",N($F10)+N($H10),0) -> 0 | Q10: =IF($K10="OK",N($G10),0) -> 0 | R10: =IF($K10="OK",N($G10)+N($I10),0) -> 0 | S10: =IF($N10=0,0,IF(INDEX($E$51:$E$54,$N10)="SÍ",IF(DATOS!$C$14="PLANO",DATOS!$C$17,IF(DATOS!$C$14="DOS AGUAS",DATOS!$C$17+(DATOS!$C$18-DATOS!$C$17)*(1-ABS(2*(N($F10))/DATOS!$C$23-1)),IF(DATOS!$C$14="UN AGUA",IF(N(DATOS!$C$25)=0,DATOS!$C$18-(DATOS!$C$18-DATOS!$C$17)*(N($F10))/DATOS!$C$23,DATOS!$C$17+(DATOS!$C$18-DATOS!$C$17)*(N($F10))/DATOS!$C$23),DATOS!$C$17+4*(DATOS!$C$18-DATOS!$C$17)*(N($F10))/DATOS!$C$23*(1-(N($F10))/DATOS!$C$23)))),INDEX($F$51:$F$54,$N10))) -> 0 | T10: =IF($N10=0,0,IF(INDEX($E$51:$E$54,$N10)="SÍ",IF(DATOS!$C$14="PLANO",DATOS!$C$17,IF(DATOS!$C$14="DOS AGUAS",DATOS!$C$17+(DATOS!$C$18-DATOS!$C$17)*(1-ABS(2*(N($F10)+N($H10))/DATOS!$C$23-1)),IF(DATOS!$C$14="UN AGUA",IF(N(DATOS!$C$25)=0,DATOS!$C$18-(DATOS!$C$18-DATOS!$C$17)*(N($F10)+N($H10))/DATOS!$C$23,DATOS!$C$17+(DATOS!$C$18-DATOS!$C$17)*(N($F10)+N($H10))/DATOS!$C$23),DATOS!$C$17+4*(DATOS!$C$18-DATOS!$C$17)*(N($F10)+N($H10))/DATOS!$C$23*(1-(N($F10)+N($H10))/DATOS!$C$23)))),INDEX($F$51:$F$54,$N10))) -> 0 | U10: =IF(AND($K10="OK",$E10="FIJA"),1,0) -> 0 | V10: =IF($K10="OK",1,0) -> 0 | W10: =IF($N10=0,0,INDEX($D$51:$D$54,$N10)) -> 0 | Y10: =($AB$6+DATOS!$AE$6+$DL$12)/$DL$11 -> 0.60762176 | Z10: =(DATOS!$AF$6+$DL$13)/$DL$11 -> 0.71744174 | AA10: =($AC$6+DATOS!$AI$6+$DL$12)/$DL$11 -> 1.3202314 | AB10: =(DATOS!$AJ$6+$DL$13)/$DL$11 -> 0.66863286 | AC10: =($AD$6+DATOS!$AM$6+$DL$12)/$DL$11 -> 2.3488786 | AD10: =(DATOS!$AN$6+$DL$13)/$DL$11 -> 0.67473397 | AE10: =($AE$6+DATOS!$AQ$6+$DL$12)/$DL$11 -> 3.422674 | AF10: =(DATOS!$AR$6+$DL$13)/$DL$11 -> 0.67473397 | AH10: =(IF(AND($K$7="OK",$E$7="FIJA"),CHOOSE($N$7,$AB$6,$AC$6,$AD$6,$AE$6)+$O$7,0)+$DL$12)/$DL$11 -> 0.069503846 | AI10: =(IF(AND($K$7="OK",$E$7="FIJA"),$R$7,0)+$DL$13)/$DL$11 -> 0.069503846 | AJ10: =(IF(AND($K$7="OK",$E$7="OPERABLE"),CHOOSE($N$7,$AB$6,$AC$6,$AD$6,$AE$6)+$O$7,0)+$DL$12)/$DL$11 -> 0.10870348 | AK10: =(IF(AND($K$7="OK",$E$7="OPERABLE"),$R$7,0)+$DL$13)/$DL$11 -> 0.21593049 | AL10: =(IF(AND($K$8="OK",$E$8="FIJA"),CHOOSE($N$8,$AB$6,$AC$6,$AD$6,$AE$6)+$O$8,0)+$DL$12)/$DL$11 -> 0.069503846 | AM10: =(IF(AND($K$8="OK",$E$8="FIJA"),$R$8,0)+$DL$13)/$DL$11 -> 0.069503846 | AN10: =(IF(AND($K$8="OK",$E$8="OPERABLE"),CHOOSE($N$8,$AB$6,$AC$6,$AD$6,$AE$6)+$O$8,0)+$DL$12)/$DL$11 -> 0.22123235 | AO10: =(IF(AND($K$8="OK",$E$8="OPERABLE"),$R$8,0)+$DL$13)/$DL$11 -> 0.45570411 | AP10: =(IF(AND($K$9="OK",$E$9="FIJA"),CHOOSE($N$9,$AB$6,$AC$6,$AD$6,$AE$6)+$O$9,0)+$DL$12)/$DL$11 -> 0.7821135 | AQ10: =(IF(AND($K$9="OK",$E$9="FIJA"),$R$9,0)+$DL$13)/$DL$11 -> 0.66863286 | AR10: =(IF(AND($K$9="OK",$E$9="OPERABLE"),CHOOSE($N$9,$AB$6,$AC$6,$AD$6,$AE$6)+$O$9,0)+$DL$12)/$DL$11 -> 0.069503846 | AS10: =(IF(AND($K$9="OK",$E$9="OPERABLE"),$R$9,0)+$DL$13)/$DL$11 -> 0.069503846 | AT10: =(IF(AND($K$10="OK",$E$10="FIJA"),CHOOSE($N$10,$AB$6,$AC$6,$AD$6,$AE$6)+$O$10,0)+$DL$12)/$DL$11 -> 0.069503846 | AU10: =(IF(AND($K$10="OK",$E$10="FIJA"),$R$10,0)+$DL$13)/$DL$11 -> 0.069503846 | AV10: =(IF(AND($K$10="OK",$E$10="OPERABLE"),CHOOSE($N$10,$AB$6,$AC$6,$AD$6,$AE$6)+$O$10,0)+$DL$12)/$DL$11 -> 0.069503846 | AW10: =(IF(AND($K$10="OK",$E$10="OPERABLE"),$R$10,0)+$DL$13)/$DL$11 -> 0.069503846 | AX10: =(IF(AND($K$11="OK",$E$11="FIJA"),CHOOSE($N$11,$AB$6,$AC$6,$AD$6,$AE$6)+$O$11,0)+$DL$12)/$DL$11 -> 0.069503846 | AY10: =(IF(AND($K$11="OK",$E$11="FIJA"),$R$11,0)+$DL$13)/$DL$11 -> 0.069503846 | AZ10: =(IF(AND($K$11="OK",$E$11="OPERABLE"),CHOOSE($N$11,$AB$6,$AC$6,$AD$6,$AE$6)+$O$11,0)+$DL$12)/$DL$11 -> 0.069503846 | BA10: =(IF(AND($K$11="OK",$E$11="OPERABLE"),$R$11,0)+$DL$13)/$DL$11 -> 0.069503846 | BB10: =(IF(AND($K$12="OK",$E$12="FIJA"),CHOOSE($N$12,$AB$6,$AC$6,$AD$6,$AE$6)+$O$12,0)+$DL$12)/$DL$11 -> 0.069503846 | BC10: =(IF(AND($K$12="OK",$E$12="FIJA"),$R$12,0)+$DL$13)/$DL$11 -> 0.069503846 | BD10: =(IF(AND($K$12="OK",$E$12="OPERABLE"),CHOOSE($N$12,$AB$6,$AC$6,$AD$6,$AE$6)+$O$12,0)+$DL$12)/$DL$11 -> 0.069503846 | BE10: =(IF(AND($K$12="OK",$E$12="OPERABLE"),$R$12,0)+$DL$13)/$DL$11 -> 0.069503846 | BF10: =(IF(AND($K$13="OK",$E$13="FIJA"),CHOOSE($N$13,$AB$6,$AC$6,$AD$6,$AE$6)+$O$13,0)+$DL$12)/$DL$11 -> 0.069503846 | BG10: =(IF(AND($K$13="OK",$E$13="FIJA"),$R$13,0)+$DL$13)/$DL$11 -> 0.069503846 | BH10: =(IF(AND($K$13="OK",$E$13="OPERABLE"),CHOOSE($N$13,$AB$6,$AC$6,$AD$6,$AE$6)+$O$13,0)+$DL$12)/$DL$11 -> 0.069503846 | BI10: =(IF(AND($K$13="OK",$E$13="OPERABLE"),$R$13,0)+$DL$13)/$DL$11 -> 0.069503846 | BJ10: =(IF(AND($K$14="OK",$E$14="FIJA"),CHOOSE($N$14,$AB$6,$AC$6,$AD$6,$AE$6)+$O$14,0)+$DL$12)/$DL$11 -> 0.069503846 | BK10: =(IF(AND($K$14="OK",$E$14="FIJA"),$R$14,0)+$DL$13)/$DL$11 -> 0.069503846 | BL10: =(IF(AND($K$14="OK",$E$14="OPERABLE"),CHOOSE($N$14,$AB$6,$AC$6,$AD$6,$AE$6)+$O$14,0)+$DL$12)/$DL$11 -> 0.069503846 | BM10: =(IF(AND($K$14="OK",$E$14="OPERABLE"),$R$14,0)+$DL$13)/$DL$11 -> 0.069503846 | BN10: =(IF(AND($K$15="OK",$E$15="FIJA"),CHOOSE($N$15,$AB$6,$AC$6,$AD$6,$AE$6)+$O$15,0)+$DL$12)/$DL$11 -> 0.069503846 | BO10: =(IF(AND($K$15="OK",$E$15="FIJA"),$R$15,0)+$DL$13)/$DL$11 -> 0.069503846 | BP10: =(IF(AND($K$15="OK",$E$15="OPERABLE"),CHOOSE($N$15,$AB$6,$AC$6,$AD$6,$AE$6)+$O$15,0)+$DL$12)/$DL$11 -> 0.069503846 | BQ10: =(IF(AND($K$15="OK",$E$15="OPERABLE"),$R$15,0)+$DL$13)/$DL$11 -> 0.069503846 | BR10: =(IF(AND($K$16="OK",$E$16="FIJA"),CHOOSE($N$16,$AB$6,$AC$6,$AD$6,$AE$6)+$O$16,0)+$DL$12)/$DL$11 -> 0.069503846 | BS10: =(IF(AND($K$16="OK",$E$16="FIJA"),$R$16,0)+$DL$13)/$DL$11 -> 0.069503846 | BT10: =(IF(AND($K$16="OK",$E$16="OPERABLE"),CHOOSE($N$16,$AB$6,$AC$6,$AD$6,$AE$6)+$O$16,0)+$DL$12)/$DL$11 -> 0.069503846 | BU10: =(IF(AND($K$16="OK",$E$16="OPERABLE"),$R$16,0)+$DL$13)/$DL$11 -> 0.069503846 | BV10: =(IF(AND($K$17="OK",$E$17="FIJA"),CHOOSE($N$17,$AB$6,$AC$6,$AD$6,$AE$6)+$O$17,0)+$DL$12)/$DL$11 -> 0.069503846 | BW10: =(IF(AND($K$17="OK",$E$17="FIJA"),$R$17,0)+$DL$13)/$DL$11 -> 0.069503846 | BX10: =(IF(AND($K$17="OK",$E$17="OPERABLE"),CHOOSE($N$17,$AB$6,$AC$6,$AD$6,$AE$6)+$O$17,0)+$DL$12)/$DL$11 -> 0.069503846 | BY10: =(IF(AND($K$17="OK",$E$17="OPERABLE"),$R$17,0)+$DL$13)/$DL$11 -> 0.069503846 | BZ10: =(IF(AND($K$18="OK",$E$18="FIJA"),CHOOSE($N$18,$AB$6,$AC$6,$AD$6,$AE$6)+$O$18,0)+$DL$12)/$DL$11 -> 0.069503846 | CA10: =(IF(AND($K$18="OK",$E$18="FIJA"),$R$18,0)+$DL$13)/$DL$11 -> 0.069503846 | CB10: =(IF(AND($K$18="OK",$E$18="OPERABLE"),CHOOSE($N$18,$AB$6,$AC$6,$AD$6,$AE$6)+$O$18,0)+$DL$12)/$DL$11 -> 0.069503846 | CC10: =(IF(AND($K$18="OK",$E$18="OPERABLE"),$R$18,0)+$DL$13)/$DL$11 -> 0.069503846 | CD10: =(IF(AND($K$19="OK",$E$19="FIJA"),CHOOSE($N$19,$AB$6,$AC$6,$AD$6,$AE$6)+$O$19,0)+$DL$12)/$DL$11 -> 0.069503846 | CE10: =(IF(AND($K$19="OK",$E$19="FIJA"),$R$19,0)+$DL$13)/$DL$11 -> 0.069503846 | CF10: =(IF(AND($K$19="OK",$E$19="OPERABLE"),CHOOSE($N$19,$AB$6,$AC$6,$AD$6,$AE$6)+$O$19,0)+$DL$12)/$DL$11 -> 0.069503846 | CG10: =(IF(AND($K$19="OK",$E$19="OPERABLE"),$R$19,0)+$DL$13)/$DL$11 -> 0.069503846 | CH10: =(IF(AND($K$20="OK",$E$20="FIJA"),CHOOSE($N$20,$AB$6,$AC$6,$AD$6,$AE$6)+$O$20,0)+$DL$12)/$DL$11 -> 0.069503846 | CI10: =(IF(AND($K$20="OK",$E$20="FIJA"),$R$20,0)+$DL$13)/$DL$11 -> 0.069503846 | CJ10: =(IF(AND($K$20="OK",$E$20="OPERABLE"),CHOOSE($N$20,$AB$6,$AC$6,$AD$6,$AE$6)+$O$20,0)+$DL$12)/$DL$11 -> 0.069503846 | CK10: =(IF(AND($K$20="OK",$E$20="OPERABLE"),$R$20,0)+$DL$13)/$DL$11 -> 0.069503846 | CL10: =(IF(AND($K$21="OK",$E$21="FIJA"),CHOOSE($N$21,$AB$6,$AC$6,$AD$6,$AE$6)+$O$21,0)+$DL$12)/$DL$11 -> 0.069503846 | CM10: =(IF(AND($K$21="OK",$E$21="FIJA"),$R$21,0)+$DL$13)/$DL$11 -> 0.069503846 | CN10: =(IF(AND($K$21="OK",$E$21="OPERABLE"),CHOOSE($N$21,$AB$6,$AC$6,$AD$6,$AE$6)+$O$21,0)+$DL$12)/$DL$11 -> 0.069503846 | CO10: =(IF(AND($K$21="OK",$E$21="OPERABLE"),$R$21,0)+$DL$13)/$DL$11 -> 0.069503846 | CP10: =(IF(AND($K$22="OK",$E$22="FIJA"),CHOOSE($N$22,$AB$6,$AC$6,$AD$6,$AE$6)+$O$22,0)+$DL$12)/$DL$11 -> 0.069503846 | CQ10: =(IF(AND($K$22="OK",$E$22="FIJA"),$R$22,0)+$DL$13)/$DL$11 -> 0.069503846 | CR10: =(IF(AND($K$22="OK",$E$22="OPERABLE"),CHOOSE($N$22,$AB$6,$AC$6,$AD$6,$AE$6)+$O$22,0)+$DL$12)/$DL$11 -> 0.069503846 | CS10: =(IF(AND($K$22="OK",$E$22="OPERABLE"),$R$22,0)+$DL$13)/$DL$11 -> 0.069503846 | CT10: =(IF(AND($K$23="OK",$E$23="FIJA"),CHOOSE($N$23,$AB$6,$AC$6,$AD$6,$AE$6)+$O$23,0)+$DL$12)/$DL$11 -> 0.069503846 | CU10: =(IF(AND($K$23="OK",$E$23="FIJA"),$R$23,0)+$DL$13)/$DL$11 -> 0.069503846 | CV10: =(IF(AND($K$23="OK",$E$23="OPERABLE"),CHOOSE($N$23,$AB$6,$AC$6,$AD$6,$AE$6)+$O$23,0)+$DL$12)/$DL$11 -> 0.069503846 | CW10: =(IF(AND($K$23="OK",$E$23="OPERABLE"),$R$23,0)+$DL$13)/$DL$11 -> 0.069503846 | CX10: =(IF(AND($K$24="OK",$E$24="FIJA"),CHOOSE($N$24,$AB$6,$AC$6,$AD$6,$AE$6)+$O$24,0)+$DL$12)/$DL$11 -> 0.069503846 | CY10: =(IF(AND($K$24="OK",$E$24="FIJA"),$R$24,0)+$DL$13)/$DL$11 -> 0.069503846 | CZ10: =(IF(AND($K$24="OK",$E$24="OPERABLE"),CHOOSE($N$24,$AB$6,$AC$6,$AD$6,$AE$6)+$O$24,0)+$DL$12)/$DL$11 -> 0.069503846 | DA10: =(IF(AND($K$24="OK",$E$24="OPERABLE"),$R$24,0)+$DL$13)/$DL$11 -> 0.069503846 | DB10: =(IF(AND($K$25="OK",$E$25="FIJA"),CHOOSE($N$25,$AB$6,$AC$6,$AD$6,$AE$6)+$O$25,0)+$DL$12)/$DL$11 -> 0.069503846 | DC10: =(IF(AND($K$25="OK",$E$25="FIJA"),$R$25,0)+$DL$13)/$DL$11 -> 0.069503846 | DD10: =(IF(AND($K$25="OK",$E$25="OPERABLE"),CHOOSE($N$25,$AB$6,$AC$6,$AD$6,$AE$6)+$O$25,0)+$DL$12)/$DL$11 -> 0.069503846 | DE10: =(IF(AND($K$25="OK",$E$25="OPERABLE"),$R$25,0)+$DL$13)/$DL$11 -> 0.069503846 | DF10: =(IF(AND($K$26="OK",$E$26="FIJA"),CHOOSE($N$26,$AB$6,$AC$6,$AD$6,$AE$6)+$O$26,0)+$DL$12)/$DL$11 -> 0.069503846 | DG10: =(IF(AND($K$26="OK",$E$26="FIJA"),$R$26,0)+$DL$13)/$DL$11 -> 0.069503846 | DH10: =(IF(AND($K$26="OK",$E$26="OPERABLE"),CHOOSE($N$26,$AB$6,$AC$6,$AD$6,$AE$6)+$O$26,0)+$DL$12)/$DL$11 -> 0.069503846 | DI10: =(IF(AND($K$26="OK",$E$26="OPERABLE"),$R$26,0)+$DL$13)/$DL$11 -> 0.069503846 | DK10: aspecto | DL10: =3.6142 -> 3.6142
B11: 5 | J11: =IF($K11="OK",$H11*$I11,0) -> 0 | K11: =IF($D11="","",IF(OR($F11="",$G11=""),"FALTA POSICIÓN",IF(OR(N($H11)<=0,N($I11)<=0),"FALTA TAMAÑO",IF($E11="","FALTA TIPO",IF(OR(N($F11)<0,N($G11)<0,N($F11)+N($H11)>$W11+0.001),"SE SALE A LO LARGO",IF(N($G11)+N($I11)>MIN($S11,$T11)+0.001,"SE SALE POR ARRIBA","OK")))))) | N11: =IF($D11="",0,VALUE(MID($D11,6,1))) -> 0 | O11: =IF($K11="OK",N($F11),0) -> 0 | P11: =IF($K11="OK",N($F11)+N($H11),0) -> 0 | Q11: =IF($K11="OK",N($G11),0) -> 0 | R11: =IF($K11="OK",N($G11)+N($I11),0) -> 0 | S11: =IF($N11=0,0,IF(INDEX($E$51:$E$54,$N11)="SÍ",IF(DATOS!$C$14="PLANO",DATOS!$C$17,IF(DATOS!$C$14="DOS AGUAS",DATOS!$C$17+(DATOS!$C$18-DATOS!$C$17)*(1-ABS(2*(N($F11))/DATOS!$C$23-1)),IF(DATOS!$C$14="UN AGUA",IF(N(DATOS!$C$25)=0,DATOS!$C$18-(DATOS!$C$18-DATOS!$C$17)*(N($F11))/DATOS!$C$23,DATOS!$C$17+(DATOS!$C$18-DATOS!$C$17)*(N($F11))/DATOS!$C$23),DATOS!$C$17+4*(DATOS!$C$18-DATOS!$C$17)*(N($F11))/DATOS!$C$23*(1-(N($F11))/DATOS!$C$23)))),INDEX($F$51:$F$54,$N11))) -> 0 | T11: =IF($N11=0,0,IF(INDEX($E$51:$E$54,$N11)="SÍ",IF(DATOS!$C$14="PLANO",DATOS!$C$17,IF(DATOS!$C$14="DOS AGUAS",DATOS!$C$17+(DATOS!$C$18-DATOS!$C$17)*(1-ABS(2*(N($F11)+N($H11))/DATOS!$C$23-1)),IF(DATOS!$C$14="UN AGUA",IF(N(DATOS!$C$25)=0,DATOS!$C$18-(DATOS!$C$18-DATOS!$C$17)*(N($F11)+N($H11))/DATOS!$C$23,DATOS!$C$17+(DATOS!$C$18-DATOS!$C$17)*(N($F11)+N($H11))/DATOS!$C$23),DATOS!$C$17+4*(DATOS!$C$18-DATOS!$C$17)*(N($F11)+N($H11))/DATOS!$C$23*(1-(N($F11)+N($H11))/DATOS!$C$23)))),INDEX($F$51:$F$54,$N11))) -> 0 | U11: =IF(AND($K11="OK",$E11="FIJA"),1,0) -> 0 | V11: =IF($K11="OK",1,0) -> 0 | W11: =IF($N11=0,0,INDEX($D$51:$D$54,$N11)) -> 0 | Y11: =($AB$6+DATOS!$AE$7+$DL$12)/$DL$11 -> 0.53074777 | Z11: =(DATOS!$AF$7+$DL$13)/$DL$11 -> 0.71744174 | AA11: =($AC$6+DATOS!$AI$7+$DL$12)/$DL$11 -> 1.2433574 | AB11: =(DATOS!$AJ$7+$DL$13)/$DL$11 -> 0.66863286 | AC11: =($AD$6+DATOS!$AM$7+$DL$12)/$DL$11 -> 2.2268564 | AD11: =(DATOS!$AN$7+$DL$13)/$DL$11 -> 0.68083508 | AE11: =($AE$6+DATOS!$AQ$7+$DL$12)/$DL$11 -> 3.3006518 | AF11: =(DATOS!$AR$7+$DL$13)/$DL$11 -> 0.68083508 | AH11: =(IF(AND($K$7="OK",$E$7="FIJA"),CHOOSE($N$7,$AB$6,$AC$6,$AD$6,$AE$6)+$O$7,0)+$DL$12)/$DL$11 -> 0.069503846 | AI11: =(IF(AND($K$7="OK",$E$7="FIJA"),$Q$7,0)+$DL$13)/$DL$11 -> 0.069503846 | AJ11: =(IF(AND($K$7="OK",$E$7="OPERABLE"),CHOOSE($N$7,$AB$6,$AC$6,$AD$6,$AE$6)+$O$7,0)+$DL$12)/$DL$11 -> 0.10870348 | AK11: =(IF(AND($K$7="OK",$E$7="OPERABLE"),$Q$7,0)+$DL$13)/$DL$11 -> 0.069503846 | AL11: =(IF(AND($K$8="OK",$E$8="FIJA"),CHOOSE($N$8,$AB$6,$AC$6,$AD$6,$AE$6)+$O$8,0)+$DL$12)/$DL$11 -> 0.069503846 | AM11: =(IF(AND($K$8="OK",$E$8="FIJA"),$Q$8,0)+$DL$13)/$DL$11 -> 0.069503846 | AN11: =(IF(AND($K$8="OK",$E$8="OPERABLE"),CHOOSE($N$8,$AB$6,$AC$6,$AD$6,$AE$6)+$O$8,0)+$DL$12)/$DL$11 -> 0.22123235 | AO11: =(IF(AND($K$8="OK",$E$8="OPERABLE"),$Q$8,0)+$DL$13)/$DL$11 -> 0.069503846 | AP11: =(IF(AND($K$9="OK",$E$9="FIJA"),CHOOSE($N$9,$AB$6,$AC$6,$AD$6,$AE$6)+$O$9,0)+$DL$12)/$DL$11 -> 0.7821135 | AQ11: =(IF(AND($K$9="OK",$E$9="FIJA"),$Q$9,0)+$DL$13)/$DL$11 -> 0.069503846 | AR11: =(IF(AND($K$9="OK",$E$9="OPERABLE"),CHOOSE($N$9,$AB$6,$AC$6,$AD$6,$AE$6)+$O$9,0)+$DL$12)/$DL$11 -> 0.069503846 | AS11: =(IF(AND($K$9="OK",$E$9="OPERABLE"),$Q$9,0)+$DL$13)/$DL$11 -> 0.069503846 | AT11: =(IF(AND($K$10="OK",$E$10="FIJA"),CHOOSE($N$10,$AB$6,$AC$6,$AD$6,$AE$6)+$O$10,0)+$DL$12)/$DL$11 -> 0.069503846 | AU11: =(IF(AND($K$10="OK",$E$10="FIJA"),$Q$10,0)+$DL$13)/$DL$11 -> 0.069503846 | AV11: =(IF(AND($K$10="OK",$E$10="OPERABLE"),CHOOSE($N$10,$AB$6,$AC$6,$AD$6,$AE$6)+$O$10,0)+$DL$12)/$DL$11 -> 0.069503846 | AW11: =(IF(AND($K$10="OK",$E$10="OPERABLE"),$Q$10,0)+$DL$13)/$DL$11 -> 0.069503846 | AX11: =(IF(AND($K$11="OK",$E$11="FIJA"),CHOOSE($N$11,$AB$6,$AC$6,$AD$6,$AE$6)+$O$11,0)+$DL$12)/$DL$11 -> 0.069503846 | AY11: =(IF(AND($K$11="OK",$E$11="FIJA"),$Q$11,0)+$DL$13)/$DL$11 -> 0.069503846 | AZ11: =(IF(AND($K$11="OK",$E$11="OPERABLE"),CHOOSE($N$11,$AB$6,$AC$6,$AD$6,$AE$6)+$O$11,0)+$DL$12)/$DL$11 -> 0.069503846 | BA11: =(IF(AND($K$11="OK",$E$11="OPERABLE"),$Q$11,0)+$DL$13)/$DL$11 -> 0.069503846 | BB11: =(IF(AND($K$12="OK",$E$12="FIJA"),CHOOSE($N$12,$AB$6,$AC$6,$AD$6,$AE$6)+$O$12,0)+$DL$12)/$DL$11 -> 0.069503846 | BC11: =(IF(AND($K$12="OK",$E$12="FIJA"),$Q$12,0)+$DL$13)/$DL$11 -> 0.069503846 | BD11: =(IF(AND($K$12="OK",$E$12="OPERABLE"),CHOOSE($N$12,$AB$6,$AC$6,$AD$6,$AE$6)+$O$12,0)+$DL$12)/$DL$11 -> 0.069503846 | BE11: =(IF(AND($K$12="OK",$E$12="OPERABLE"),$Q$12,0)+$DL$13)/$DL$11 -> 0.069503846 | BF11: =(IF(AND($K$13="OK",$E$13="FIJA"),CHOOSE($N$13,$AB$6,$AC$6,$AD$6,$AE$6)+$O$13,0)+$DL$12)/$DL$11 -> 0.069503846 | BG11: =(IF(AND($K$13="OK",$E$13="FIJA"),$Q$13,0)+$DL$13)/$DL$11 -> 0.069503846 | BH11: =(IF(AND($K$13="OK",$E$13="OPERABLE"),CHOOSE($N$13,$AB$6,$AC$6,$AD$6,$AE$6)+$O$13,0)+$DL$12)/$DL$11 -> 0.069503846 | BI11: =(IF(AND($K$13="OK",$E$13="OPERABLE"),$Q$13,0)+$DL$13)/$DL$11 -> 0.069503846 | BJ11: =(IF(AND($K$14="OK",$E$14="FIJA"),CHOOSE($N$14,$AB$6,$AC$6,$AD$6,$AE$6)+$O$14,0)+$DL$12)/$DL$11 -> 0.069503846 | BK11: =(IF(AND($K$14="OK",$E$14="FIJA"),$Q$14,0)+$DL$13)/$DL$11 -> 0.069503846 | BL11: =(IF(AND($K$14="OK",$E$14="OPERABLE"),CHOOSE($N$14,$AB$6,$AC$6,$AD$6,$AE$6)+$O$14,0)+$DL$12)/$DL$11 -> 0.069503846 | BM11: =(IF(AND($K$14="OK",$E$14="OPERABLE"),$Q$14,0)+$DL$13)/$DL$11 -> 0.069503846 | BN11: =(IF(AND($K$15="OK",$E$15="FIJA"),CHOOSE($N$15,$AB$6,$AC$6,$AD$6,$AE$6)+$O$15,0)+$DL$12)/$DL$11 -> 0.069503846 | BO11: =(IF(AND($K$15="OK",$E$15="FIJA"),$Q$15,0)+$DL$13)/$DL$11 -> 0.069503846 | BP11: =(IF(AND($K$15="OK",$E$15="OPERABLE"),CHOOSE($N$15,$AB$6,$AC$6,$AD$6,$AE$6)+$O$15,0)+$DL$12)/$DL$11 -> 0.069503846 | BQ11: =(IF(AND($K$15="OK",$E$15="OPERABLE"),$Q$15,0)+$DL$13)/$DL$11 -> 0.069503846 | BR11: =(IF(AND($K$16="OK",$E$16="FIJA"),CHOOSE($N$16,$AB$6,$AC$6,$AD$6,$AE$6)+$O$16,0)+$DL$12)/$DL$11 -> 0.069503846 | BS11: =(IF(AND($K$16="OK",$E$16="FIJA"),$Q$16,0)+$DL$13)/$DL$11 -> 0.069503846 | BT11: =(IF(AND($K$16="OK",$E$16="OPERABLE"),CHOOSE($N$16,$AB$6,$AC$6,$AD$6,$AE$6)+$O$16,0)+$DL$12)/$DL$11 -> 0.069503846 | BU11: =(IF(AND($K$16="OK",$E$16="OPERABLE"),$Q$16,0)+$DL$13)/$DL$11 -> 0.069503846 | BV11: =(IF(AND($K$17="OK",$E$17="FIJA"),CHOOSE($N$17,$AB$6,$AC$6,$AD$6,$AE$6)+$O$17,0)+$DL$12)/$DL$11 -> 0.069503846 | BW11: =(IF(AND($K$17="OK",$E$17="FIJA"),$Q$17,0)+$DL$13)/$DL$11 -> 0.069503846 | BX11: =(IF(AND($K$17="OK",$E$17="OPERABLE"),CHOOSE($N$17,$AB$6,$AC$6,$AD$6,$AE$6)+$O$17,0)+$DL$12)/$DL$11 -> 0.069503846 | BY11: =(IF(AND($K$17="OK",$E$17="OPERABLE"),$Q$17,0)+$DL$13)/$DL$11 -> 0.069503846 | BZ11: =(IF(AND($K$18="OK",$E$18="FIJA"),CHOOSE($N$18,$AB$6,$AC$6,$AD$6,$AE$6)+$O$18,0)+$DL$12)/$DL$11 -> 0.069503846 | CA11: =(IF(AND($K$18="OK",$E$18="FIJA"),$Q$18,0)+$DL$13)/$DL$11 -> 0.069503846 | CB11: =(IF(AND($K$18="OK",$E$18="OPERABLE"),CHOOSE($N$18,$AB$6,$AC$6,$AD$6,$AE$6)+$O$18,0)+$DL$12)/$DL$11 -> 0.069503846 | CC11: =(IF(AND($K$18="OK",$E$18="OPERABLE"),$Q$18,0)+$DL$13)/$DL$11 -> 0.069503846 | CD11: =(IF(AND($K$19="OK",$E$19="FIJA"),CHOOSE($N$19,$AB$6,$AC$6,$AD$6,$AE$6)+$O$19,0)+$DL$12)/$DL$11 -> 0.069503846 | CE11: =(IF(AND($K$19="OK",$E$19="FIJA"),$Q$19,0)+$DL$13)/$DL$11 -> 0.069503846 | CF11: =(IF(AND($K$19="OK",$E$19="OPERABLE"),CHOOSE($N$19,$AB$6,$AC$6,$AD$6,$AE$6)+$O$19,0)+$DL$12)/$DL$11 -> 0.069503846 | CG11: =(IF(AND($K$19="OK",$E$19="OPERABLE"),$Q$19,0)+$DL$13)/$DL$11 -> 0.069503846 | CH11: =(IF(AND($K$20="OK",$E$20="FIJA"),CHOOSE($N$20,$AB$6,$AC$6,$AD$6,$AE$6)+$O$20,0)+$DL$12)/$DL$11 -> 0.069503846 | CI11: =(IF(AND($K$20="OK",$E$20="FIJA"),$Q$20,0)+$DL$13)/$DL$11 -> 0.069503846 | CJ11: =(IF(AND($K$20="OK",$E$20="OPERABLE"),CHOOSE($N$20,$AB$6,$AC$6,$AD$6,$AE$6)+$O$20,0)+$DL$12)/$DL$11 -> 0.069503846 | CK11: =(IF(AND($K$20="OK",$E$20="OPERABLE"),$Q$20,0)+$DL$13)/$DL$11 -> 0.069503846 | CL11: =(IF(AND($K$21="OK",$E$21="FIJA"),CHOOSE($N$21,$AB$6,$AC$6,$AD$6,$AE$6)+$O$21,0)+$DL$12)/$DL$11 -> 0.069503846 | CM11: =(IF(AND($K$21="OK",$E$21="FIJA"),$Q$21,0)+$DL$13)/$DL$11 -> 0.069503846 | CN11: =(IF(AND($K$21="OK",$E$21="OPERABLE"),CHOOSE($N$21,$AB$6,$AC$6,$AD$6,$AE$6)+$O$21,0)+$DL$12)/$DL$11 -> 0.069503846 | CO11: =(IF(AND($K$21="OK",$E$21="OPERABLE"),$Q$21,0)+$DL$13)/$DL$11 -> 0.069503846 | CP11: =(IF(AND($K$22="OK",$E$22="FIJA"),CHOOSE($N$22,$AB$6,$AC$6,$AD$6,$AE$6)+$O$22,0)+$DL$12)/$DL$11 -> 0.069503846 | CQ11: =(IF(AND($K$22="OK",$E$22="FIJA"),$Q$22,0)+$DL$13)/$DL$11 -> 0.069503846 | CR11: =(IF(AND($K$22="OK",$E$22="OPERABLE"),CHOOSE($N$22,$AB$6,$AC$6,$AD$6,$AE$6)+$O$22,0)+$DL$12)/$DL$11 -> 0.069503846 | CS11: =(IF(AND($K$22="OK",$E$22="OPERABLE"),$Q$22,0)+$DL$13)/$DL$11 -> 0.069503846 | CT11: =(IF(AND($K$23="OK",$E$23="FIJA"),CHOOSE($N$23,$AB$6,$AC$6,$AD$6,$AE$6)+$O$23,0)+$DL$12)/$DL$11 -> 0.069503846 | CU11: =(IF(AND($K$23="OK",$E$23="FIJA"),$Q$23,0)+$DL$13)/$DL$11 -> 0.069503846 | CV11: =(IF(AND($K$23="OK",$E$23="OPERABLE"),CHOOSE($N$23,$AB$6,$AC$6,$AD$6,$AE$6)+$O$23,0)+$DL$12)/$DL$11 -> 0.069503846 | CW11: =(IF(AND($K$23="OK",$E$23="OPERABLE"),$Q$23,0)+$DL$13)/$DL$11 -> 0.069503846 | CX11: =(IF(AND($K$24="OK",$E$24="FIJA"),CHOOSE($N$24,$AB$6,$AC$6,$AD$6,$AE$6)+$O$24,0)+$DL$12)/$DL$11 -> 0.069503846 | CY11: =(IF(AND($K$24="OK",$E$24="FIJA"),$Q$24,0)+$DL$13)/$DL$11 -> 0.069503846 | CZ11: =(IF(AND($K$24="OK",$E$24="OPERABLE"),CHOOSE($N$24,$AB$6,$AC$6,$AD$6,$AE$6)+$O$24,0)+$DL$12)/$DL$11 -> 0.069503846 | DA11: =(IF(AND($K$24="OK",$E$24="OPERABLE"),$Q$24,0)+$DL$13)/$DL$11 -> 0.069503846 | DB11: =(IF(AND($K$25="OK",$E$25="FIJA"),CHOOSE($N$25,$AB$6,$AC$6,$AD$6,$AE$6)+$O$25,0)+$DL$12)/$DL$11 -> 0.069503846 | DC11: =(IF(AND($K$25="OK",$E$25="FIJA"),$Q$25,0)+$DL$13)/$DL$11 -> 0.069503846 | DD11: =(IF(AND($K$25="OK",$E$25="OPERABLE"),CHOOSE($N$25,$AB$6,$AC$6,$AD$6,$AE$6)+$O$25,0)+$DL$12)/$DL$11 -> 0.069503846 | DE11: =(IF(AND($K$25="OK",$E$25="OPERABLE"),$Q$25,0)+$DL$13)/$DL$11 -> 0.069503846 | DF11: =(IF(AND($K$26="OK",$E$26="FIJA"),CHOOSE($N$26,$AB$6,$AC$6,$AD$6,$AE$6)+$O$26,0)+$DL$12)/$DL$11 -> 0.069503846 | DG11: =(IF(AND($K$26="OK",$E$26="FIJA"),$Q$26,0)+$DL$13)/$DL$11 -> 0.069503846 | DH11: =(IF(AND($K$26="OK",$E$26="OPERABLE"),CHOOSE($N$26,$AB$6,$AC$6,$AD$6,$AE$6)+$O$26,0)+$DL$12)/$DL$11 -> 0.069503846 | DI11: =(IF(AND($K$26="OK",$E$26="OPERABLE"),$Q$26,0)+$DL$13)/$DL$11 -> 0.069503846 | DK11: s | DL11: =MAX(($DL$7+2*$DL$9)/$DL$10,$DL$8+2*$DL$9) -> 16.39046
B12: 6 | J12: =IF($K12="OK",$H12*$I12,0) -> 0 | K12: =IF($D12="","",IF(OR($F12="",$G12=""),"FALTA POSICIÓN",IF(OR(N($H12)<=0,N($I12)<=0),"FALTA TAMAÑO",IF($E12="","FALTA TIPO",IF(OR(N($F12)<0,N($G12)<0,N($F12)+N($H12)>$W12+0.001),"SE SALE A LO LARGO",IF(N($G12)+N($I12)>MIN($S12,$T12)+0.001,"SE SALE POR ARRIBA","OK")))))) | N12: =IF($D12="",0,VALUE(MID($D12,6,1))) -> 0 | O12: =IF($K12="OK",N($F12),0) -> 0 | P12: =IF($K12="OK",N($F12)+N($H12),0) -> 0 | Q12: =IF($K12="OK",N($G12),0) -> 0 | R12: =IF($K12="OK",N($G12)+N($I12),0) -> 0 | S12: =IF($N12=0,0,IF(INDEX($E$51:$E$54,$N12)="SÍ",IF(DATOS!$C$14="PLANO",DATOS!$C$17,IF(DATOS!$C$14="DOS AGUAS",DATOS!$C$17+(DATOS!$C$18-DATOS!$C$17)*(1-ABS(2*(N($F12))/DATOS!$C$23-1)),IF(DATOS!$C$14="UN AGUA",IF(N(DATOS!$C$25)=0,DATOS!$C$18-(DATOS!$C$18-DATOS!$C$17)*(N($F12))/DATOS!$C$23,DATOS!$C$17+(DATOS!$C$18-DATOS!$C$17)*(N($F12))/DATOS!$C$23),DATOS!$C$17+4*(DATOS!$C$18-DATOS!$C$17)*(N($F12))/DATOS!$C$23*(1-(N($F12))/DATOS!$C$23)))),INDEX($F$51:$F$54,$N12))) -> 0 | T12: =IF($N12=0,0,IF(INDEX($E$51:$E$54,$N12)="SÍ",IF(DATOS!$C$14="PLANO",DATOS!$C$17,IF(DATOS!$C$14="DOS AGUAS",DATOS!$C$17+(DATOS!$C$18-DATOS!$C$17)*(1-ABS(2*(N($F12)+N($H12))/DATOS!$C$23-1)),IF(DATOS!$C$14="UN AGUA",IF(N(DATOS!$C$25)=0,DATOS!$C$18-(DATOS!$C$18-DATOS!$C$17)*(N($F12)+N($H12))/DATOS!$C$23,DATOS!$C$17+(DATOS!$C$18-DATOS!$C$17)*(N($F12)+N($H12))/DATOS!$C$23),DATOS!$C$17+4*(DATOS!$C$18-DATOS!$C$17)*(N($F12)+N($H12))/DATOS!$C$23*(1-(N($F12)+N($H12))/DATOS!$C$23)))),INDEX($F$51:$F$54,$N12))) -> 0 | U12: =IF(AND($K12="OK",$E12="FIJA"),1,0) -> 0 | V12: =IF($K12="OK",1,0) -> 0 | W12: =IF($N12=0,0,INDEX($D$51:$D$54,$N12)) -> 0 | Y12: =($AB$6+DATOS!$AE$8+$DL$12)/$DL$11 -> 0.45387378 | Z12: =(DATOS!$AF$8+$DL$13)/$DL$11 -> 0.71744174 | AA12: =($AC$6+DATOS!$AI$8+$DL$12)/$DL$11 -> 1.1664834 | AB12: =(DATOS!$AJ$8+$DL$13)/$DL$11 -> 0.66863286 | AC12: =($AD$6+DATOS!$AM$8+$DL$12)/$DL$11 -> 2.1048342 | AD12: =(DATOS!$AN$8+$DL$13)/$DL$11 -> 0.68693619 | AE12: =($AE$6+DATOS!$AQ$8+$DL$12)/$DL$11 -> 3.1786295 | AF12: =(DATOS!$AR$8+$DL$13)/$DL$11 -> 0.68693619 | DK12: offX | DL12: =($DL$10*$DL$11-($DL$7+2*$DL$9))/2+$DL$9 -> 1.1392
B13: 7 | J13: =IF($K13="OK",$H13*$I13,0) -> 0 | K13: =IF($D13="","",IF(OR($F13="",$G13=""),"FALTA POSICIÓN",IF(OR(N($H13)<=0,N($I13)<=0),"FALTA TAMAÑO",IF($E13="","FALTA TIPO",IF(OR(N($F13)<0,N($G13)<0,N($F13)+N($H13)>$W13+0.001),"SE SALE A LO LARGO",IF(N($G13)+N($I13)>MIN($S13,$T13)+0.001,"SE SALE POR ARRIBA","OK")))))) | N13: =IF($D13="",0,VALUE(MID($D13,6,1))) -> 0 | O13: =IF($K13="OK",N($F13),0) -> 0 | P13: =IF($K13="OK",N($F13)+N($H13),0) -> 0 | Q13: =IF($K13="OK",N($G13),0) -> 0 | R13: =IF($K13="OK",N($G13)+N($I13),0) -> 0 | S13: =IF($N13=0,0,IF(INDEX($E$51:$E$54,$N13)="SÍ",IF(DATOS!$C$14="PLANO",DATOS!$C$17,IF(DATOS!$C$14="DOS AGUAS",DATOS!$C$17+(DATOS!$C$18-DATOS!$C$17)*(1-ABS(2*(N($F13))/DATOS!$C$23-1)),IF(DATOS!$C$14="UN AGUA",IF(N(DATOS!$C$25)=0,DATOS!$C$18-(DATOS!$C$18-DATOS!$C$17)*(N($F13))/DATOS!$C$23,DATOS!$C$17+(DATOS!$C$18-DATOS!$C$17)*(N($F13))/DATOS!$C$23),DATOS!$C$17+4*(DATOS!$C$18-DATOS!$C$17)*(N($F13))/DATOS!$C$23*(1-(N($F13))/DATOS!$C$23)))),INDEX($F$51:$F$54,$N13))) -> 0 | T13: =IF($N13=0,0,IF(INDEX($E$51:$E$54,$N13)="SÍ",IF(DATOS!$C$14="PLANO",DATOS!$C$17,IF(DATOS!$C$14="DOS AGUAS",DATOS!$C$17+(DATOS!$C$18-DATOS!$C$17)*(1-ABS(2*(N($F13)+N($H13))/DATOS!$C$23-1)),IF(DATOS!$C$14="UN AGUA",IF(N(DATOS!$C$25)=0,DATOS!$C$18-(DATOS!$C$18-DATOS!$C$17)*(N($F13)+N($H13))/DATOS!$C$23,DATOS!$C$17+(DATOS!$C$18-DATOS!$C$17)*(N($F13)+N($H13))/DATOS!$C$23),DATOS!$C$17+4*(DATOS!$C$18-DATOS!$C$17)*(N($F13)+N($H13))/DATOS!$C$23*(1-(N($F13)+N($H13))/DATOS!$C$23)))),INDEX($F$51:$F$54,$N13))) -> 0 | U13: =IF(AND($K13="OK",$E13="FIJA"),1,0) -> 0 | V13: =IF($K13="OK",1,0) -> 0 | W13: =IF($N13=0,0,INDEX($D$51:$D$54,$N13)) -> 0 | Y13: =($AB$6+DATOS!$AE$9+$DL$12)/$DL$11 -> 0.37699979 | Z13: =(DATOS!$AF$9+$DL$13)/$DL$11 -> 0.71744174 | AA13: =($AC$6+DATOS!$AI$9+$DL$12)/$DL$11 -> 1.0896095 | AB13: =(DATOS!$AJ$9+$DL$13)/$DL$11 -> 0.66863286 | AC13: =($AD$6+DATOS!$AM$9+$DL$12)/$DL$11 -> 1.982812 | AD13: =(DATOS!$AN$9+$DL$13)/$DL$11 -> 0.6930373 | AE13: =($AE$6+DATOS!$AQ$9+$DL$12)/$DL$11 -> 3.0566073 | AF13: =(DATOS!$AR$9+$DL$13)/$DL$11 -> 0.6930373 | DK13: offY | DL13: =$DL$9 -> 1.1392
B14: 8 | J14: =IF($K14="OK",$H14*$I14,0) -> 0 | K14: =IF($D14="","",IF(OR($F14="",$G14=""),"FALTA POSICIÓN",IF(OR(N($H14)<=0,N($I14)<=0),"FALTA TAMAÑO",IF($E14="","FALTA TIPO",IF(OR(N($F14)<0,N($G14)<0,N($F14)+N($H14)>$W14+0.001),"SE SALE A LO LARGO",IF(N($G14)+N($I14)>MIN($S14,$T14)+0.001,"SE SALE POR ARRIBA","OK")))))) | N14: =IF($D14="",0,VALUE(MID($D14,6,1))) -> 0 | O14: =IF($K14="OK",N($F14),0) -> 0 | P14: =IF($K14="OK",N($F14)+N($H14),0) -> 0 | Q14: =IF($K14="OK",N($G14),0) -> 0 | R14: =IF($K14="OK",N($G14)+N($I14),0) -> 0 | S14: =IF($N14=0,0,IF(INDEX($E$51:$E$54,$N14)="SÍ",IF(DATOS!$C$14="PLANO",DATOS!$C$17,IF(DATOS!$C$14="DOS AGUAS",DATOS!$C$17+(DATOS!$C$18-DATOS!$C$17)*(1-ABS(2*(N($F14))/DATOS!$C$23-1)),IF(DATOS!$C$14="UN AGUA",IF(N(DATOS!$C$25)=0,DATOS!$C$18-(DATOS!$C$18-DATOS!$C$17)*(N($F14))/DATOS!$C$23,DATOS!$C$17+(DATOS!$C$18-DATOS!$C$17)*(N($F14))/DATOS!$C$23),DATOS!$C$17+4*(DATOS!$C$18-DATOS!$C$17)*(N($F14))/DATOS!$C$23*(1-(N($F14))/DATOS!$C$23)))),INDEX($F$51:$F$54,$N14))) -> 0 | T14: =IF($N14=0,0,IF(INDEX($E$51:$E$54,$N14)="SÍ",IF(DATOS!$C$14="PLANO",DATOS!$C$17,IF(DATOS!$C$14="DOS AGUAS",DATOS!$C$17+(DATOS!$C$18-DATOS!$C$17)*(1-ABS(2*(N($F14)+N($H14))/DATOS!$C$23-1)),IF(DATOS!$C$14="UN AGUA",IF(N(DATOS!$C$25)=0,DATOS!$C$18-(DATOS!$C$18-DATOS!$C$17)*(N($F14)+N($H14))/DATOS!$C$23,DATOS!$C$17+(DATOS!$C$18-DATOS!$C$17)*(N($F14)+N($H14))/DATOS!$C$23),DATOS!$C$17+4*(DATOS!$C$18-DATOS!$C$17)*(N($F14)+N($H14))/DATOS!$C$23*(1-(N($F14)+N($H14))/DATOS!$C$23)))),INDEX($F$51:$F$54,$N14))) -> 0 | U14: =IF(AND($K14="OK",$E14="FIJA"),1,0) -> 0 | V14: =IF($K14="OK",1,0) -> 0 | W14: =IF($N14=0,0,INDEX($D$51:$D$54,$N14)) -> 0 | Y14: =($AB$6+DATOS!$AE$10+$DL$12)/$DL$11 -> 0.30012581 | Z14: =(DATOS!$AF$10+$DL$13)/$DL$11 -> 0.71744174 | AA14: =($AC$6+DATOS!$AI$10+$DL$12)/$DL$11 -> 1.0127355 | AB14: =(DATOS!$AJ$10+$DL$13)/$DL$11 -> 0.66863286 | AC14: =($AD$6+DATOS!$AM$10+$DL$12)/$DL$11 -> 1.8607898 | AD14: =(DATOS!$AN$10+$DL$13)/$DL$11 -> 0.69913841 | AE14: =($AE$6+DATOS!$AQ$10+$DL$12)/$DL$11 -> 2.9345851 | AF14: =(DATOS!$AR$10+$DL$13)/$DL$11 -> 0.69913841
B15: 9 | J15: =IF($K15="OK",$H15*$I15,0) -> 0 | K15: =IF($D15="","",IF(OR($F15="",$G15=""),"FALTA POSICIÓN",IF(OR(N($H15)<=0,N($I15)<=0),"FALTA TAMAÑO",IF($E15="","FALTA TIPO",IF(OR(N($F15)<0,N($G15)<0,N($F15)+N($H15)>$W15+0.001),"SE SALE A LO LARGO",IF(N($G15)+N($I15)>MIN($S15,$T15)+0.001,"SE SALE POR ARRIBA","OK")))))) | N15: =IF($D15="",0,VALUE(MID($D15,6,1))) -> 0 | O15: =IF($K15="OK",N($F15),0) -> 0 | P15: =IF($K15="OK",N($F15)+N($H15),0) -> 0 | Q15: =IF($K15="OK",N($G15),0) -> 0 | R15: =IF($K15="OK",N($G15)+N($I15),0) -> 0 | S15: =IF($N15=0,0,IF(INDEX($E$51:$E$54,$N15)="SÍ",IF(DATOS!$C$14="PLANO",DATOS!$C$17,IF(DATOS!$C$14="DOS AGUAS",DATOS!$C$17+(DATOS!$C$18-DATOS!$C$17)*(1-ABS(2*(N($F15))/DATOS!$C$23-1)),IF(DATOS!$C$14="UN AGUA",IF(N(DATOS!$C$25)=0,DATOS!$C$18-(DATOS!$C$18-DATOS!$C$17)*(N($F15))/DATOS!$C$23,DATOS!$C$17+(DATOS!$C$18-DATOS!$C$17)*(N($F15))/DATOS!$C$23),DATOS!$C$17+4*(DATOS!$C$18-DATOS!$C$17)*(N($F15))/DATOS!$C$23*(1-(N($F15))/DATOS!$C$23)))),INDEX($F$51:$F$54,$N15))) -> 0 | T15: =IF($N15=0,0,IF(INDEX($E$51:$E$54,$N15)="SÍ",IF(DATOS!$C$14="PLANO",DATOS!$C$17,IF(DATOS!$C$14="DOS AGUAS",DATOS!$C$17+(DATOS!$C$18-DATOS!$C$17)*(1-ABS(2*(N($F15)+N($H15))/DATOS!$C$23-1)),IF(DATOS!$C$14="UN AGUA",IF(N(DATOS!$C$25)=0,DATOS!$C$18-(DATOS!$C$18-DATOS!$C$17)*(N($F15)+N($H15))/DATOS!$C$23,DATOS!$C$17+(DATOS!$C$18-DATOS!$C$17)*(N($F15)+N($H15))/DATOS!$C$23),DATOS!$C$17+4*(DATOS!$C$18-DATOS!$C$17)*(N($F15)+N($H15))/DATOS!$C$23*(1-(N($F15)+N($H15))/DATOS!$C$23)))),INDEX($F$51:$F$54,$N15))) -> 0 | U15: =IF(AND($K15="OK",$E15="FIJA"),1,0) -> 0 | V15: =IF($K15="OK",1,0) -> 0 | W15: =IF($N15=0,0,INDEX($D$51:$D$54,$N15)) -> 0 | Y15: =($AB$6+DATOS!$AE$11+$DL$12)/$DL$11 -> 0.22325182 | Z15: =(DATOS!$AF$11+$DL$13)/$DL$11 -> 0.71744174 | AA15: =($AC$6+DATOS!$AI$11+$DL$12)/$DL$11 -> 0.93586148 | AB15: =(DATOS!$AJ$11+$DL$13)/$DL$11 -> 0.66863286 | AC15: =($AD$6+DATOS!$AM$11+$DL$12)/$DL$11 -> 1.7387676 | AD15: =(DATOS!$AN$11+$DL$13)/$DL$11 -> 0.70523952 | AE15: =($AE$6+DATOS!$AQ$11+$DL$12)/$DL$11 -> 2.8125629 | AF15: =(DATOS!$AR$11+$DL$13)/$DL$11 -> 0.70523952
B16: 10 | J16: =IF($K16="OK",$H16*$I16,0) -> 0 | K16: =IF($D16="","",IF(OR($F16="",$G16=""),"FALTA POSICIÓN",IF(OR(N($H16)<=0,N($I16)<=0),"FALTA TAMAÑO",IF($E16="","FALTA TIPO",IF(OR(N($F16)<0,N($G16)<0,N($F16)+N($H16)>$W16+0.001),"SE SALE A LO LARGO",IF(N($G16)+N($I16)>MIN($S16,$T16)+0.001,"SE SALE POR ARRIBA","OK")))))) | N16: =IF($D16="",0,VALUE(MID($D16,6,1))) -> 0 | O16: =IF($K16="OK",N($F16),0) -> 0 | P16: =IF($K16="OK",N($F16)+N($H16),0) -> 0 | Q16: =IF($K16="OK",N($G16),0) -> 0 | R16: =IF($K16="OK",N($G16)+N($I16),0) -> 0 | S16: =IF($N16=0,0,IF(INDEX($E$51:$E$54,$N16)="SÍ",IF(DATOS!$C$14="PLANO",DATOS!$C$17,IF(DATOS!$C$14="DOS AGUAS",DATOS!$C$17+(DATOS!$C$18-DATOS!$C$17)*(1-ABS(2*(N($F16))/DATOS!$C$23-1)),IF(DATOS!$C$14="UN AGUA",IF(N(DATOS!$C$25)=0,DATOS!$C$18-(DATOS!$C$18-DATOS!$C$17)*(N($F16))/DATOS!$C$23,DATOS!$C$17+(DATOS!$C$18-DATOS!$C$17)*(N($F16))/DATOS!$C$23),DATOS!$C$17+4*(DATOS!$C$18-DATOS!$C$17)*(N($F16))/DATOS!$C$23*(1-(N($F16))/DATOS!$C$23)))),INDEX($F$51:$F$54,$N16))) -> 0 | T16: =IF($N16=0,0,IF(INDEX($E$51:$E$54,$N16)="SÍ",IF(DATOS!$C$14="PLANO",DATOS!$C$17,IF(DATOS!$C$14="DOS AGUAS",DATOS!$C$17+(DATOS!$C$18-DATOS!$C$17)*(1-ABS(2*(N($F16)+N($H16))/DATOS!$C$23-1)),IF(DATOS!$C$14="UN AGUA",IF(N(DATOS!$C$25)=0,DATOS!$C$18-(DATOS!$C$18-DATOS!$C$17)*(N($F16)+N($H16))/DATOS!$C$23,DATOS!$C$17+(DATOS!$C$18-DATOS!$C$17)*(N($F16)+N($H16))/DATOS!$C$23),DATOS!$C$17+4*(DATOS!$C$18-DATOS!$C$17)*(N($F16)+N($H16))/DATOS!$C$23*(1-(N($F16)+N($H16))/DATOS!$C$23)))),INDEX($F$51:$F$54,$N16))) -> 0 | U16: =IF(AND($K16="OK",$E16="FIJA"),1,0) -> 0 | V16: =IF($K16="OK",1,0) -> 0 | W16: =IF($N16=0,0,INDEX($D$51:$D$54,$N16)) -> 0 | Y16: =($AB$6+DATOS!$AE$12+$DL$12)/$DL$11 -> 0.14637783 | Z16: =(DATOS!$AF$12+$DL$13)/$DL$11 -> 0.71744174 | AA16: =($AC$6+DATOS!$AI$12+$DL$12)/$DL$11 -> 0.85898749 | AB16: =(DATOS!$AJ$12+$DL$13)/$DL$11 -> 0.66863286 | AC16: =($AD$6+DATOS!$AM$12+$DL$12)/$DL$11 -> 1.6167454 | AD16: =(DATOS!$AN$12+$DL$13)/$DL$11 -> 0.71134063 | AE16: =($AE$6+DATOS!$AQ$12+$DL$12)/$DL$11 -> 2.6905407 | AF16: =(DATOS!$AR$12+$DL$13)/$DL$11 -> 0.71134063
B17: 11 | J17: =IF($K17="OK",$H17*$I17,0) -> 0 | K17: =IF($D17="","",IF(OR($F17="",$G17=""),"FALTA POSICIÓN",IF(OR(N($H17)<=0,N($I17)<=0),"FALTA TAMAÑO",IF($E17="","FALTA TIPO",IF(OR(N($F17)<0,N($G17)<0,N($F17)+N($H17)>$W17+0.001),"SE SALE A LO LARGO",IF(N($G17)+N($I17)>MIN($S17,$T17)+0.001,"SE SALE POR ARRIBA","OK")))))) | N17: =IF($D17="",0,VALUE(MID($D17,6,1))) -> 0 | O17: =IF($K17="OK",N($F17),0) -> 0 | P17: =IF($K17="OK",N($F17)+N($H17),0) -> 0 | Q17: =IF($K17="OK",N($G17),0) -> 0 | R17: =IF($K17="OK",N($G17)+N($I17),0) -> 0 | S17: =IF($N17=0,0,IF(INDEX($E$51:$E$54,$N17)="SÍ",IF(DATOS!$C$14="PLANO",DATOS!$C$17,IF(DATOS!$C$14="DOS AGUAS",DATOS!$C$17+(DATOS!$C$18-DATOS!$C$17)*(1-ABS(2*(N($F17))/DATOS!$C$23-1)),IF(DATOS!$C$14="UN AGUA",IF(N(DATOS!$C$25)=0,DATOS!$C$18-(DATOS!$C$18-DATOS!$C$17)*(N($F17))/DATOS!$C$23,DATOS!$C$17+(DATOS!$C$18-DATOS!$C$17)*(N($F17))/DATOS!$C$23),DATOS!$C$17+4*(DATOS!$C$18-DATOS!$C$17)*(N($F17))/DATOS!$C$23*(1-(N($F17))/DATOS!$C$23)))),INDEX($F$51:$F$54,$N17))) -> 0 | T17: =IF($N17=0,0,IF(INDEX($E$51:$E$54,$N17)="SÍ",IF(DATOS!$C$14="PLANO",DATOS!$C$17,IF(DATOS!$C$14="DOS AGUAS",DATOS!$C$17+(DATOS!$C$18-DATOS!$C$17)*(1-ABS(2*(N($F17)+N($H17))/DATOS!$C$23-1)),IF(DATOS!$C$14="UN AGUA",IF(N(DATOS!$C$25)=0,DATOS!$C$18-(DATOS!$C$18-DATOS!$C$17)*(N($F17)+N($H17))/DATOS!$C$23,DATOS!$C$17+(DATOS!$C$18-DATOS!$C$17)*(N($F17)+N($H17))/DATOS!$C$23),DATOS!$C$17+4*(DATOS!$C$18-DATOS!$C$17)*(N($F17)+N($H17))/DATOS!$C$23*(1-(N($F17)+N($H17))/DATOS!$C$23)))),INDEX($F$51:$F$54,$N17))) -> 0 | U17: =IF(AND($K17="OK",$E17="FIJA"),1,0) -> 0 | V17: =IF($K17="OK",1,0) -> 0 | W17: =IF($N17=0,0,INDEX($D$51:$D$54,$N17)) -> 0 | Y17: =($AB$6+DATOS!$AE$13+$DL$12)/$DL$11 -> 0.069503846 | Z17: =(DATOS!$AF$13+$DL$13)/$DL$11 -> 0.71744174 | AA17: =($AC$6+DATOS!$AI$13+$DL$12)/$DL$11 -> 0.7821135 | AB17: =(DATOS!$AJ$13+$DL$13)/$DL$11 -> 0.66863286 | AC17: =($AD$6+DATOS!$AM$13+$DL$12)/$DL$11 -> 1.4947232 | AD17: =(DATOS!$AN$13+$DL$13)/$DL$11 -> 0.71744174 | AE17: =($AE$6+DATOS!$AQ$13+$DL$12)/$DL$11 -> 2.5685185 | AF17: =(DATOS!$AR$13+$DL$13)/$DL$11 -> 0.71744174
B18: 12 | J18: =IF($K18="OK",$H18*$I18,0) -> 0 | K18: =IF($D18="","",IF(OR($F18="",$G18=""),"FALTA POSICIÓN",IF(OR(N($H18)<=0,N($I18)<=0),"FALTA TAMAÑO",IF($E18="","FALTA TIPO",IF(OR(N($F18)<0,N($G18)<0,N($F18)+N($H18)>$W18+0.001),"SE SALE A LO LARGO",IF(N($G18)+N($I18)>MIN($S18,$T18)+0.001,"SE SALE POR ARRIBA","OK")))))) | N18: =IF($D18="",0,VALUE(MID($D18,6,1))) -> 0 | O18: =IF($K18="OK",N($F18),0) -> 0 | P18: =IF($K18="OK",N($F18)+N($H18),0) -> 0 | Q18: =IF($K18="OK",N($G18),0) -> 0 | R18: =IF($K18="OK",N($G18)+N($I18),0) -> 0 | S18: =IF($N18=0,0,IF(INDEX($E$51:$E$54,$N18)="SÍ",IF(DATOS!$C$14="PLANO",DATOS!$C$17,IF(DATOS!$C$14="DOS AGUAS",DATOS!$C$17+(DATOS!$C$18-DATOS!$C$17)*(1-ABS(2*(N($F18))/DATOS!$C$23-1)),IF(DATOS!$C$14="UN AGUA",IF(N(DATOS!$C$25)=0,DATOS!$C$18-(DATOS!$C$18-DATOS!$C$17)*(N($F18))/DATOS!$C$23,DATOS!$C$17+(DATOS!$C$18-DATOS!$C$17)*(N($F18))/DATOS!$C$23),DATOS!$C$17+4*(DATOS!$C$18-DATOS!$C$17)*(N($F18))/DATOS!$C$23*(1-(N($F18))/DATOS!$C$23)))),INDEX($F$51:$F$54,$N18))) -> 0 | T18: =IF($N18=0,0,IF(INDEX($E$51:$E$54,$N18)="SÍ",IF(DATOS!$C$14="PLANO",DATOS!$C$17,IF(DATOS!$C$14="DOS AGUAS",DATOS!$C$17+(DATOS!$C$18-DATOS!$C$17)*(1-ABS(2*(N($F18)+N($H18))/DATOS!$C$23-1)),IF(DATOS!$C$14="UN AGUA",IF(N(DATOS!$C$25)=0,DATOS!$C$18-(DATOS!$C$18-DATOS!$C$17)*(N($F18)+N($H18))/DATOS!$C$23,DATOS!$C$17+(DATOS!$C$18-DATOS!$C$17)*(N($F18)+N($H18))/DATOS!$C$23),DATOS!$C$17+4*(DATOS!$C$18-DATOS!$C$17)*(N($F18)+N($H18))/DATOS!$C$23*(1-(N($F18)+N($H18))/DATOS!$C$23)))),INDEX($F$51:$F$54,$N18))) -> 0 | U18: =IF(AND($K18="OK",$E18="FIJA"),1,0) -> 0 | V18: =IF($K18="OK",1,0) -> 0 | W18: =IF($N18=0,0,INDEX($D$51:$D$54,$N18)) -> 0 | Y18: =($AB$6+DATOS!$AE$14+$DL$12)/$DL$11 -> 0.069503846 | Z18: =(DATOS!$AF$14+$DL$13)/$DL$11 -> 0.069503846 | AA18: =($AC$6+DATOS!$AI$14+$DL$12)/$DL$11 -> 0.7821135 | AB18: =(DATOS!$AJ$14+$DL$13)/$DL$11 -> 0.069503846 | AC18: =($AD$6+DATOS!$AM$14+$DL$12)/$DL$11 -> 1.4947232 | AD18: =(DATOS!$AN$14+$DL$13)/$DL$11 -> 0.069503846 | AE18: =($AE$6+DATOS!$AQ$14+$DL$12)/$DL$11 -> 2.5685185 | AF18: =(DATOS!$AR$14+$DL$13)/$DL$11 -> 0.069503846
B19: 13 | J19: =IF($K19="OK",$H19*$I19,0) -> 0 | K19: =IF($D19="","",IF(OR($F19="",$G19=""),"FALTA POSICIÓN",IF(OR(N($H19)<=0,N($I19)<=0),"FALTA TAMAÑO",IF($E19="","FALTA TIPO",IF(OR(N($F19)<0,N($G19)<0,N($F19)+N($H19)>$W19+0.001),"SE SALE A LO LARGO",IF(N($G19)+N($I19)>MIN($S19,$T19)+0.001,"SE SALE POR ARRIBA","OK")))))) | N19: =IF($D19="",0,VALUE(MID($D19,6,1))) -> 0 | O19: =IF($K19="OK",N($F19),0) -> 0 | P19: =IF($K19="OK",N($F19)+N($H19),0) -> 0 | Q19: =IF($K19="OK",N($G19),0) -> 0 | R19: =IF($K19="OK",N($G19)+N($I19),0) -> 0 | S19: =IF($N19=0,0,IF(INDEX($E$51:$E$54,$N19)="SÍ",IF(DATOS!$C$14="PLANO",DATOS!$C$17,IF(DATOS!$C$14="DOS AGUAS",DATOS!$C$17+(DATOS!$C$18-DATOS!$C$17)*(1-ABS(2*(N($F19))/DATOS!$C$23-1)),IF(DATOS!$C$14="UN AGUA",IF(N(DATOS!$C$25)=0,DATOS!$C$18-(DATOS!$C$18-DATOS!$C$17)*(N($F19))/DATOS!$C$23,DATOS!$C$17+(DATOS!$C$18-DATOS!$C$17)*(N($F19))/DATOS!$C$23),DATOS!$C$17+4*(DATOS!$C$18-DATOS!$C$17)*(N($F19))/DATOS!$C$23*(1-(N($F19))/DATOS!$C$23)))),INDEX($F$51:$F$54,$N19))) -> 0 | T19: =IF($N19=0,0,IF(INDEX($E$51:$E$54,$N19)="SÍ",IF(DATOS!$C$14="PLANO",DATOS!$C$17,IF(DATOS!$C$14="DOS AGUAS",DATOS!$C$17+(DATOS!$C$18-DATOS!$C$17)*(1-ABS(2*(N($F19)+N($H19))/DATOS!$C$23-1)),IF(DATOS!$C$14="UN AGUA",IF(N(DATOS!$C$25)=0,DATOS!$C$18-(DATOS!$C$18-DATOS!$C$17)*(N($F19)+N($H19))/DATOS!$C$23,DATOS!$C$17+(DATOS!$C$18-DATOS!$C$17)*(N($F19)+N($H19))/DATOS!$C$23),DATOS!$C$17+4*(DATOS!$C$18-DATOS!$C$17)*(N($F19)+N($H19))/DATOS!$C$23*(1-(N($F19)+N($H19))/DATOS!$C$23)))),INDEX($F$51:$F$54,$N19))) -> 0 | U19: =IF(AND($K19="OK",$E19="FIJA"),1,0) -> 0 | V19: =IF($K19="OK",1,0) -> 0 | W19: =IF($N19=0,0,INDEX($D$51:$D$54,$N19)) -> 0
B20: 14 | J20: =IF($K20="OK",$H20*$I20,0) -> 0 | K20: =IF($D20="","",IF(OR($F20="",$G20=""),"FALTA POSICIÓN",IF(OR(N($H20)<=0,N($I20)<=0),"FALTA TAMAÑO",IF($E20="","FALTA TIPO",IF(OR(N($F20)<0,N($G20)<0,N($F20)+N($H20)>$W20+0.001),"SE SALE A LO LARGO",IF(N($G20)+N($I20)>MIN($S20,$T20)+0.001,"SE SALE POR ARRIBA","OK")))))) | N20: =IF($D20="",0,VALUE(MID($D20,6,1))) -> 0 | O20: =IF($K20="OK",N($F20),0) -> 0 | P20: =IF($K20="OK",N($F20)+N($H20),0) -> 0 | Q20: =IF($K20="OK",N($G20),0) -> 0 | R20: =IF($K20="OK",N($G20)+N($I20),0) -> 0 | S20: =IF($N20=0,0,IF(INDEX($E$51:$E$54,$N20)="SÍ",IF(DATOS!$C$14="PLANO",DATOS!$C$17,IF(DATOS!$C$14="DOS AGUAS",DATOS!$C$17+(DATOS!$C$18-DATOS!$C$17)*(1-ABS(2*(N($F20))/DATOS!$C$23-1)),IF(DATOS!$C$14="UN AGUA",IF(N(DATOS!$C$25)=0,DATOS!$C$18-(DATOS!$C$18-DATOS!$C$17)*(N($F20))/DATOS!$C$23,DATOS!$C$17+(DATOS!$C$18-DATOS!$C$17)*(N($F20))/DATOS!$C$23),DATOS!$C$17+4*(DATOS!$C$18-DATOS!$C$17)*(N($F20))/DATOS!$C$23*(1-(N($F20))/DATOS!$C$23)))),INDEX($F$51:$F$54,$N20))) -> 0 | T20: =IF($N20=0,0,IF(INDEX($E$51:$E$54,$N20)="SÍ",IF(DATOS!$C$14="PLANO",DATOS!$C$17,IF(DATOS!$C$14="DOS AGUAS",DATOS!$C$17+(DATOS!$C$18-DATOS!$C$17)*(1-ABS(2*(N($F20)+N($H20))/DATOS!$C$23-1)),IF(DATOS!$C$14="UN AGUA",IF(N(DATOS!$C$25)=0,DATOS!$C$18-(DATOS!$C$18-DATOS!$C$17)*(N($F20)+N($H20))/DATOS!$C$23,DATOS!$C$17+(DATOS!$C$18-DATOS!$C$17)*(N($F20)+N($H20))/DATOS!$C$23),DATOS!$C$17+4*(DATOS!$C$18-DATOS!$C$17)*(N($F20)+N($H20))/DATOS!$C$23*(1-(N($F20)+N($H20))/DATOS!$C$23)))),INDEX($F$51:$F$54,$N20))) -> 0 | U20: =IF(AND($K20="OK",$E20="FIJA"),1,0) -> 0 | V20: =IF($K20="OK",1,0) -> 0 | W20: =IF($N20=0,0,INDEX($D$51:$D$54,$N20)) -> 0
B21: 15 | J21: =IF($K21="OK",$H21*$I21,0) -> 0 | K21: =IF($D21="","",IF(OR($F21="",$G21=""),"FALTA POSICIÓN",IF(OR(N($H21)<=0,N($I21)<=0),"FALTA TAMAÑO",IF($E21="","FALTA TIPO",IF(OR(N($F21)<0,N($G21)<0,N($F21)+N($H21)>$W21+0.001),"SE SALE A LO LARGO",IF(N($G21)+N($I21)>MIN($S21,$T21)+0.001,"SE SALE POR ARRIBA","OK")))))) | N21: =IF($D21="",0,VALUE(MID($D21,6,1))) -> 0 | O21: =IF($K21="OK",N($F21),0) -> 0 | P21: =IF($K21="OK",N($F21)+N($H21),0) -> 0 | Q21: =IF($K21="OK",N($G21),0) -> 0 | R21: =IF($K21="OK",N($G21)+N($I21),0) -> 0 | S21: =IF($N21=0,0,IF(INDEX($E$51:$E$54,$N21)="SÍ",IF(DATOS!$C$14="PLANO",DATOS!$C$17,IF(DATOS!$C$14="DOS AGUAS",DATOS!$C$17+(DATOS!$C$18-DATOS!$C$17)*(1-ABS(2*(N($F21))/DATOS!$C$23-1)),IF(DATOS!$C$14="UN AGUA",IF(N(DATOS!$C$25)=0,DATOS!$C$18-(DATOS!$C$18-DATOS!$C$17)*(N($F21))/DATOS!$C$23,DATOS!$C$17+(DATOS!$C$18-DATOS!$C$17)*(N($F21))/DATOS!$C$23),DATOS!$C$17+4*(DATOS!$C$18-DATOS!$C$17)*(N($F21))/DATOS!$C$23*(1-(N($F21))/DATOS!$C$23)))),INDEX($F$51:$F$54,$N21))) -> 0 | T21: =IF($N21=0,0,IF(INDEX($E$51:$E$54,$N21)="SÍ",IF(DATOS!$C$14="PLANO",DATOS!$C$17,IF(DATOS!$C$14="DOS AGUAS",DATOS!$C$17+(DATOS!$C$18-DATOS!$C$17)*(1-ABS(2*(N($F21)+N($H21))/DATOS!$C$23-1)),IF(DATOS!$C$14="UN AGUA",IF(N(DATOS!$C$25)=0,DATOS!$C$18-(DATOS!$C$18-DATOS!$C$17)*(N($F21)+N($H21))/DATOS!$C$23,DATOS!$C$17+(DATOS!$C$18-DATOS!$C$17)*(N($F21)+N($H21))/DATOS!$C$23),DATOS!$C$17+4*(DATOS!$C$18-DATOS!$C$17)*(N($F21)+N($H21))/DATOS!$C$23*(1-(N($F21)+N($H21))/DATOS!$C$23)))),INDEX($F$51:$F$54,$N21))) -> 0 | U21: =IF(AND($K21="OK",$E21="FIJA"),1,0) -> 0 | V21: =IF($K21="OK",1,0) -> 0 | W21: =IF($N21=0,0,INDEX($D$51:$D$54,$N21)) -> 0
