Workbook

Sheet DATOS
B1: PRESIONES DE VIENTO EN NAVES — EL SALVADOR (NORMA TÉCNICA PARA DISEÑO POR VIENTO 1997) — DATOS | AA1: auxiliar del croquis (no se toca)
B2: P = C_p·C_z·K·P_o (ec. 4.1). Nave rectangular de una crujía con techo a dos aguas, a un agua (hacia el muro que elijas), plano o curvo. La hoja resuelve de una vez los cuatro vientos (±X, ±Z) con puertas cerradas y con puertas abiertas (PA) y arma las cargas para STAAD. | AA2: s_k | AB2: h_k | AC2: eje dibujo | AE2: M1 u | AF2: M1 v | AG2: M1 x' | AH2: M1 y' | AI2: M2 u | AJ2: M2 v | AK2: M2 x' | AL2: M2 y' | AM2: M3 u | AN2: M3 v | AO2: M3 x' | AP2: M3 y' | AQ2: M4 u | AR2: M4 v | AS2: M4 x' | AT2: M4 y' | AU2: techo x' | AV2: techo y' | AW2: ejes x' | AX2: ejes y' | BA2: A1 x' | BB2: A1 y' | BC2: A2 x' | BD2: A2 y' | BE2: A3 x' | BF2: A3 y' | BG2: A4 x' | BH2: A4 y' | BI2: A5 x' | BJ2: A5 y' | BK2: A6 x' | BL2: A6 y' | BM2: A7 x' | BN2: A7 y' | BO2: A8 x' | BP2: A8 y' | BQ2: A9 x' | BR2: A9 y' | BS2: A10 x' | BT2: A10 y' | BU2: A11 x' | BV2: A11 y' | BW2: A12 x' | BX2: A12 y' | BY2: A13 x' | BZ2: A13 y' | CA2: A14 x' | CB2: A14 y' | CC2: A15 x' | CD2: A15 y' | CE2: A16 x' | CF2: A16 y' | CG2: A17 x' | CH2: A17 y' | CI2: A18 x' | CJ2: A18 y' | CK2: A19 x' | CL2: A19 y' | CM2: A20 x' | CN2: A20 y'
B3: CÓMO SE LLENA: sólo celdas amarillas con letra azul (aquí, en ABERTURAS y en LINEAS). Muro 1 = atrás (Z = 0: puerta y cortina), Muro 2 = frente (Z = L: abierto, sin muro en STAAD), Muro 3 = izquierdo (X = 0), Muro 4 = derecho (X = B), como se ven en el croquis. Los marcos quedan en el plano X-Y. Lo marcado EJEMPLO es del NOSE DOCK H5-H6 (modelo R3): cámbialo para otra nave. | AA3: =$C$23*0/8 -> 0 | AB3: =IF($C$14="PLANO",$C$17,IF($C$14="DOS AGUAS",$C$17+($C$18-$C$17)*(1-ABS(2*($AA$3)/$C$23-1)),IF($C$14="UN AGUA",IF(N($C$25)=0,$C$18-($C$18-$C$17)*($AA$3)/$C$23,$C$17+($C$18-$C$17)*($AA$3)/$C$23),$C$17+4*($C$18-$C$17)*($AA$3)/$C$23*(1-($AA$3)/$C$23)))) -> 10.62 | AC3: =IF($C$22="Z","Z","X") -> Z | AE3: =0 -> 0 | AF3: =0 -> 0 | AG3: =($AE3+0.42*0+$AZ$8)/$AZ$7 -> 0.30543746 | AH3: =($AF3+0.26*0+$AZ$9)/$AZ$7 -> 0.041677003 | AI3: =0 -> 0 | AJ3: =0 -> 0 | AK3: =($AI3+0.42*$C$13+$AZ$8)/$AZ$7 -> 0.72220749 | AL3: =($AJ3+0.26*$C$13+$AZ$9)/$AZ$7 -> 0.2996775 | AM3: =0 -> 0 | AN3: =0 -> 0 | AO3: =(0+0.42*$AM3+$AZ$8)/$AZ$7 -> 0.30543746 | AP3: =($AN3+0.26*$AM3+$AZ$9)/$AZ$7 -> 0.041677003 | AQ3: =0 -> 0 | AR3: =0 -> 0 | AS3: =($C$12+0.42*$AQ3+$AZ$8)/$AZ$7 -> 0.93059251 | AT3: =($AR3+0.26*$AQ3+$AZ$9)/$AZ$7 -> 0.041677003 | AU3: =(IF($AC$3="X",$AA$3+0.42*0,0+0.42*$AA$3)+$AZ$8)/$AZ$7 -> 0.30543746 | AV3: =($AB$3+0.26*IF($AC$3="X",0,$AA$3)+$AZ$9)/$AZ$7 -> 0.7003225 | AW3: =(1.3*$C$12+$AZ$8)/$AZ$7 -> 1.118139 | AX3: =(0+$AZ$9)/$AZ$7 -> 0.041677003 | AY3: ext x' | AZ3: =MAX(1.3*$C$12,$C$12+0.42*$C$13,0.42*1.25*$C$13) -> 16.8 | BA3: =(IF(ABERTURAS!$K$7="OK",CHOOSE(ABERTURAS!$N$7,ABERTURAS!$O$7,ABERTURAS!$O$7+0.42*$C$13,0.42*ABERTURAS!$O$7,$C$12+0.42*ABERTURAS!$O$7),0)+$AZ$8)/$AZ$7 -> 0.34528489 | BB3: =(IF(ABERTURAS!$K$7="OK",ABERTURAS!$Q$7+0.26*CHOOSE(ABERTURAS!$N$7,0,$C$13,ABERTURAS!$O$7,ABERTURAS!$O$7),0)+$AZ$9)/$AZ$7 -> 0.041677003 | BC3: =(IF(ABERTURAS!$K$8="OK",CHOOSE(ABERTURAS!$N$8,ABERTURAS!$O$8,ABERTURAS!$O$8+0.42*$C$13,0.42*ABERTURAS!$O$8,$C$12+0.42*ABERTURAS!$O$8),0)+$AZ$8)/$AZ$7 -> 0.45967338 | BD3: =(IF(ABERTURAS!$K$8="OK",ABERTURAS!$Q$8+0.26*CHOOSE(ABERTURAS!$N$8,0,$C$13,ABERTURAS!$O$8,ABERTURAS!$O$8),0)+$AZ$9)/$AZ$7 -> 0.041677003 | BE3: =(IF(ABERTURAS!$K$9="OK",CHOOSE(ABERTURAS!$N$9,ABERTURAS!$O$9,ABERTURAS!$O$9+0.42*$C$13,0.42*ABERTURAS!$O$9,$C$12+0.42*ABERTURAS!$O$9),0)+$AZ$8)/$AZ$7 -> 0.72220749 | BF3: =(IF(ABERTURAS!$K$9="OK",ABERTURAS!$Q$9+0.26*CHOOSE(ABERTURAS!$N$9,0,$C$13,ABERTURAS!$O$9,ABERTURAS!$O$9),0)+$AZ$9)/$AZ$7 -> 0.2996775 | BG3: =(IF(ABERTURAS!$K$10="OK",CHOOSE(ABERTURAS!$N$10,ABERTURAS!$O$10,ABERTURAS!$O$10+0.42*$C$13,0.42*ABERTURAS!$O$10,$C$12+0.42*ABERTURAS!$O$10),0)+$AZ$8)/$AZ$7 -> 0.30543746 | BH3: =(IF(ABERTURAS!$K$10="OK",ABERTURAS!$Q$10+0.26*CHOOSE(ABERTURAS!$N$10,0,$C$13,ABERTURAS!$O$10,ABERTURAS!$O$10),0)+$AZ$9)/$AZ$7 -> 0.041677003 | BI3: =(IF(ABERTURAS!$K$11="OK",CHOOSE(ABERTURAS!$N$11,ABERTURAS!$O$11,ABERTURAS!$O$11+0.42*$C$13,0.42*ABERTURAS!$O$11,$C$12+0.42*ABERTURAS!$O$11),0)+$AZ$8)/$AZ$7 -> 0.30543746 | BJ3: =(IF(ABERTURAS!$K$11="OK",ABERTURAS!$Q$11+0.26*CHOOSE(ABERTURAS!$N$11,0,$C$13,ABERTURAS!$O$11,ABERTURAS!$O$11),0)+$AZ$9)/$AZ$7 -> 0.041677003 | BK3: =(IF(ABERTURAS!$K$12="OK",CHOOSE(ABERTURAS!$N$12,ABERTURAS!$O$12,ABERTURAS!$O$12+0.42*$C$13,0.42*ABERTURAS!$O$12,$C$12+0.42*ABERTURAS!$O$12),0)+$AZ$8)/$AZ$7 -> 0.30543746 | BL3: =(IF(ABERTURAS!$K$12="OK",ABERTURAS!$Q$12+0.26*CHOOSE(ABERTURAS!$N$12,0,$C$13,ABERTURAS!$O$12,ABERTURAS!$O$12),0)+$AZ$9)/$AZ$7 -> 0.041677003 | BM3: =(IF(ABERTURAS!$K$13="OK",CHOOSE(ABERTURAS!$N$13,ABERTURAS!$O$13,ABERTURAS!$O$13+0.42*$C$13,0.42*ABERTURAS!$O$13,$C$12+0.42*ABERTURAS!$O$13),0)+$AZ$8)/$AZ$7 -> 0.30543746 | BN3: =(IF(ABERTURAS!$K$13="OK",ABERTURAS!$Q$13+0.26*CHOOSE(ABERTURAS!$N$13,0,$C$13,ABERTURAS!$O$13,ABERTURAS!$O$13),0)+$AZ$9)/$AZ$7 -> 0.041677003 | BO3: =(IF(ABERTURAS!$K$14="OK",CHOOSE(ABERTURAS!$N$14,ABERTURAS!$O$14,ABERTURAS!$O$14+0.42*$C$13,0.42*ABERTURAS!$O$14,$C$12+0.42*ABERTURAS!$O$14),0)+$AZ$8)/$AZ$7 -> 0.30543746 | BP3: =(IF(ABERTURAS!$K$14="OK",ABERTURAS!$Q$14+0.26*CHOOSE(ABERTURAS!$N$14,0,$C$13,ABERTURAS!$O$14,ABERTURAS!$O$14),0)+$AZ$9)/$AZ$7 -> 0.041677003 | BQ3: =(IF(ABERTURAS!$K$15="OK",CHOOSE(ABERTURAS!$N$15,ABERTURAS!$O$15,ABERTURAS!$O$15+0.42*$C$13,0.42*ABERTURAS!$O$15,$C$12+0.42*ABERTURAS!$O$15),0)+$AZ$8)/$AZ$7 -> 0.30543746 | BR3: =(IF(ABERTURAS!$K$15="OK",ABERTURAS!$Q$15+0.26*CHOOSE(ABERTURAS!$N$15,0,$C$13,ABERTURAS!$O$15,ABERTURAS!$O$15),0)+$AZ$9)/$AZ$7 -> 0.041677003 | BS3: =(IF(ABERTURAS!$K$16="OK",CHOOSE(ABERTURAS!$N$16,ABERTURAS!$O$16,ABERTURAS!$O$16+0.42*$C$13,0.42*ABERTURAS!$O$16,$C$12+0.42*ABERTURAS!$O$16),0)+$AZ$8)/$AZ$7 -> 0.30543746 | BT3: =(IF(ABERTURAS!$K$16="OK",ABERTURAS!$Q$16+0.26*CHOOSE(ABERTURAS!$N$16,0,$C$13,ABERTURAS!$O$16,ABERTURAS!$O$16),0)+$AZ$9)/$AZ$7 -> 0.041677003 | BU3: =(IF(ABERTURAS!$K$17="OK",CHOOSE(ABERTURAS!$N$17,ABERTURAS!$O$17,ABERTURAS!$O$17+0.42*$C$13,0.42*ABERTURAS!$O$17,$C$12+0.42*ABERTURAS!$O$17),0)+$AZ$8)/$AZ$7 -> 0.30543746 | BV3: =(IF(ABERTURAS!$K$17="OK",ABERTURAS!$Q$17+0.26*CHOOSE(ABERTURAS!$N$17,0,$C$13,ABERTURAS!$O$17,ABERTURAS!$O$17),0)+$AZ$9)/$AZ$7 -> 0.041677003 | BW3: =(IF(ABERTURAS!$K$18="OK",CHOOSE(ABERTURAS!$N$18,ABERTURAS!$O$18,ABERTURAS!$O$18+0.42*$C$13,0.42*ABERTURAS!$O$18,$C$12+0.42*ABERTURAS!$O$18),0)+$AZ$8)/$AZ$7 -> 0.30543746 | BX3: =(IF(ABERTURAS!$K$18="OK",ABERTURAS!$Q$18+0.26*CHOOSE(ABERTURAS!$N$18,0,$C$13,ABERTURAS!$O$18,ABERTURAS!$O$18),0)+$AZ$9)/$AZ$7 -> 0.041677003 | BY3: =(IF(ABERTURAS!$K$19="OK",CHOOSE(ABERTURAS!$N$19,ABERTURAS!$O$19,ABERTURAS!$O$19+0.42*$C$13,0.42*ABERTURAS!$O$19,$C$12+0.42*ABERTURAS!$O$19),0)+$AZ$8)/$AZ$7 -> 0.30543746 | BZ3: =(IF(ABERTURAS!$K$19="OK",ABERTURAS!$Q$19+0.26*CHOOSE(ABERTURAS!$N$19,0,$C$13,ABERTURAS!$O$19,ABERTURAS!$O$19),0)+$AZ$9)/$AZ$7 -> 0.041677003 | CA3: =(IF(ABERTURAS!$K$20="OK",CHOOSE(ABERTURAS!$N$20,ABERTURAS!$O$20,ABERTURAS!$O$20+0.42*$C$13,0.42*ABERTURAS!$O$20,$C$12+0.42*ABERTURAS!$O$20),0)+$AZ$8)/$AZ$7 -> 0.30543746 | CB3: =(IF(ABERTURAS!$K$20="OK",ABERTURAS!$Q$20+0.26*CHOOSE(ABERTURAS!$N$20,0,$C$13,ABERTURAS!$O$20,ABERTURAS!$O$20),0)+$AZ$9)/$AZ$7 -> 0.041677003 | CC3: =(IF(ABERTURAS!$K$21="OK",CHOOSE(ABERTURAS!$N$21,ABERTURAS!$O$21,ABERTURAS!$O$21+0.42*$C$13,0.42*ABERTURAS!$O$21,$C$12+0.42*ABERTURAS!$O$21),0)+$AZ$8)/$AZ$7 -> 0.30543746 | CD3: =(IF(ABERTURAS!$K$21="OK",ABERTURAS!$Q$21+0.26*CHOOSE(ABERTURAS!$N$21,0,$C$13,ABERTURAS!$O$21,ABERTURAS!$O$21),0)+$AZ$9)/$AZ$7 -> 0.041677003 | CE3: =(IF(ABERTURAS!$K$22="OK",CHOOSE(ABERTURAS!$N$22,ABERTURAS!$O$22,ABERTURAS!$O$22+0.42*$C$13,0.42*ABERTURAS!$O$22,$C$12+0.42*ABERTURAS!$O$22),0)+$AZ$8)/$AZ$7 -> 0.30543746 | CF3: =(IF(ABERTURAS!$K$22="OK",ABERTURAS!$Q$22+0.26*CHOOSE(ABERTURAS!$N$22,0,$C$13,ABERTURAS!$O$22,ABERTURAS!$O$22),0)+$AZ$9)/$AZ$7 -> 0.041677003 | CG3: =(IF(ABERTURAS!$K$23="OK",CHOOSE(ABERTURAS!$N$23,ABERTURAS!$O$23,ABERTURAS!$O$23+0.42*$C$13,0.42*ABERTURAS!$O$23,$C$12+0.42*ABERTURAS!$O$23),0)+$AZ$8)/$AZ$7 -> 0.30543746 | CH3: =(IF(ABERTURAS!$K$23="OK",ABERTURAS!$Q$23+0.26*CHOOSE(ABERTURAS!$N$23,0,$C$13,ABERTURAS!$O$23,ABERTURAS!$O$23),0)+$AZ$9)/$AZ$7 -> 0.041677003 | CI3: =(IF(ABERTURAS!$K$24="OK",CHOOSE(ABERTURAS!$N$24,ABERTURAS!$O$24,ABERTURAS!$O$24+0.42*$C$13,0.42*ABERTURAS!$O$24,$C$12+0.42*ABERTURAS!$O$24),0)+$AZ$8)/$AZ$7 -> 0.30543746 | CJ3: =(IF(ABERTURAS!$K$24="OK",ABERTURAS!$Q$24+0.26*CHOOSE(ABERTURAS!$N$24,0,$C$13,ABERTURAS!$O$24,ABERTURAS!$O$24),0)+$AZ$9)/$AZ$7 -> 0.041677003 | CK3: =(IF(ABERTURAS!$K$25="OK",CHOOSE(ABERTURAS!$N$25,ABERTURAS!$O$25,ABERTURAS!$O$25+0.42*$C$13,0.42*ABERTURAS!$O$25,$C$12+0.42*ABERTURAS!$O$25),0)+$AZ$8)/$AZ$7 -> 0.30543746 | CL3: =(IF(ABERTURAS!$K$25="OK",ABERTURAS!$Q$25+0.26*CHOOSE(ABERTURAS!$N$25,0,$C$13,ABERTURAS!$O$25,ABERTURAS!$O$25),0)+$AZ$9)/$AZ$7 -> 0.041677003 | CM3: =(IF(ABERTURAS!$K$26="OK",CHOOSE(ABERTURAS!$N$26,ABERTURAS!$O$26,ABERTURAS!$O$26+0.42*$C$13,0.42*ABERTURAS!$O$26,$C$12+0.42*ABERTURAS!$O$26),0)+$AZ$8)/$AZ$7 -> 0.30543746 | CN3: =(IF(ABERTURAS!$K$26="OK",ABERTURAS!$Q$26+0.26*CHOOSE(ABERTURAS!$N$26,0,$C$13,ABERTURAS!$O$26,ABERTURAS!$O$26),0)+$AZ$9)/$AZ$7 -> 0.041677003
AA4: =$C$23*1/8 -> 2 | AB4: =IF($C$14="PLANO",$C$17,IF($C$14="DOS AGUAS",$C$17+($C$18-$C$17)*(1-ABS(2*($AA$4)/$C$23-1)),IF($C$14="UN AGUA",IF(N($C$25)=0,$C$18-($C$18-$C$17)*($AA$4)/$C$23,$C$17+($C$18-$C$17)*($AA$4)/$C$23),$C$17+4*($C$18-$C$17)*($AA$4)/$C$23*(1-($AA$4)/$C$23)))) -> 10.52 | AE4: =ABERTURAS!$D$51 -> 10.08 | AF4: =0 -> 0 | AG4: =($AE4+0.42*0+$AZ$8)/$AZ$7 -> 0.93059251 | AH4: =($AF4+0.26*0+$AZ$9)/$AZ$7 -> 0.041677003 | AI4: =ABERTURAS!$D$52 -> 10.08 | AJ4: =0 -> 0 | AK4: =($AI4+0.42*$C$13+$AZ$8)/$AZ$7 -> 1.3473625 | AL4: =($AJ4+0.26*$C$13+$AZ$9)/$AZ$7 -> 0.2996775 | AM4: =ABERTURAS!$D$53 -> 16 | AN4: =0 -> 0 | AO4: =(0+0.42*$AM4+$AZ$8)/$AZ$7 -> 0.72220749 | AP4: =($AN4+0.26*$AM4+$AZ$9)/$AZ$7 -> 0.2996775 | AQ4: =ABERTURAS!$D$54 -> 16 | AR4: =0 -> 0 | AS4: =($C$12+0.42*$AQ4+$AZ$8)/$AZ$7 -> 1.3473625 | AT4: =($AR4+0.26*$AQ4+$AZ$9)/$AZ$7 -> 0.2996775 | AU4: =(IF($AC$3="X",$AA$3+0.42*IF($AC$3="X",$C$13,$C$12),IF($AC$3="X",$C$13,$C$12)+0.42*$AA$3)+$AZ$8)/$AZ$7 -> 0.93059251 | AV4: =($AB$3+0.26*IF($AC$3="X",IF($AC$3="X",$C$13,$C$12),$AA$3)+$AZ$9)/$AZ$7 -> 0.7003225 | AW4: =(0+$AZ$8)/$AZ$7 -> 0.30543746 | AX4: =(0+$AZ$9)/$AZ$7 -> 0.041677003 | AY4: ext y' | AZ4: =MAX(1.25*$C$21,$C$21+0.26*$C$13,0.26*1.25*$C$13) -> 14.78 | BA4: =(IF(ABERTURAS!$K$7="OK",CHOOSE(ABERTURAS!$N$7,ABERTURAS!$P$7,ABERTURAS!$P$7+0.42*$C$13,0.42*ABERTURAS!$P$7,$C$12+0.42*ABERTURAS!$P$7),0)+$AZ$8)/$AZ$7 -> 0.42599687 | BB4: =(IF(ABERTURAS!$K$7="OK",ABERTURAS!$Q$7+0.26*CHOOSE(ABERTURAS!$N$7,0,$C$13,ABERTURAS!$P$7,ABERTURAS!$P$7),0)+$AZ$9)/$AZ$7 -> 0.041677003 | BC4: =(IF(ABERTURAS!$K$8="OK",CHOOSE(ABERTURAS!$N$8,ABERTURAS!$P$8,ABERTURAS!$P$8+0.42*$C$13,0.42*ABERTURAS!$P$8,$C$12+0.42*ABERTURAS!$P$8),0)+$AZ$8)/$AZ$7 -> 0.7760713 | BD4: =(IF(ABERTURAS!$K$8="OK",ABERTURAS!$Q$8+0.26*CHOOSE(ABERTURAS!$N$8,0,$C$13,ABERTURAS!$P$8,ABERTURAS!$P$8),0)+$AZ$9)/$AZ$7 -> 0.041677003 | BE4: =(IF(ABERTURAS!$K$9="OK",CHOOSE(ABERTURAS!$N$9,ABERTURAS!$P$9,ABERTURAS!$P$9+0.42*$C$13,0.42*ABERTURAS!$P$9,$C$12+0.42*ABERTURAS!$P$9),0)+$AZ$8)/$AZ$7 -> 1.3473625 | BF4: =(IF(ABERTURAS!$K$9="OK",ABERTURAS!$Q$9+0.26*CHOOSE(ABERTURAS!$N$9,0,$C$13,ABERTURAS!$P$9,ABERTURAS!$P$9),0)+$AZ$9)/$AZ$7 -> 0.2996775 | BG4: =(IF(ABERTURAS!$K$10="OK",CHOOSE(ABERTURAS!$N$10,ABERTURAS!$P$10,ABERTURAS!$P$10+0.42*$C$13,0.42*ABERTURAS!$P$10,$C$12+0.42*ABERTURAS!$P$10),0)+$AZ$8)/$AZ$7 -> 0.30543746 | BH4: =(IF(ABERTURAS!$K$10="OK",ABERTURAS!$Q$10+0.26*CHOOSE(ABERTURAS!$N$10,0,$C$13,ABERTURAS!$P$10,ABERTURAS!$P$10),0)+$AZ$9)/$AZ$7 -> 0.041677003 | BI4: =(IF(ABERTURAS!$K$11="OK",CHOOSE(ABERTURAS!$N$11,ABERTURAS!$P$11,ABERTURAS!$P$11+0.42*$C$13,0.42*ABERTURAS!$P$11,$C$12+0.42*ABERTURAS!$P$11),0)+$AZ$8)/$AZ$7 -> 0.30543746 | BJ4: =(IF(ABERTURAS!$K$11="OK",ABERTURAS!$Q$11+0.26*CHOOSE(ABERTURAS!$N$11,0,$C$13,ABERTURAS!$P$11,ABERTURAS!$P$11),0)+$AZ$9)/$AZ$7 -> 0.041677003 | BK4: =(IF(ABERTURAS!$K$12="OK",CHOOSE(ABERTURAS!$N$12,ABERTURAS!$P$12,ABERTURAS!$P$12+0.42*$C$13,0.42*ABERTURAS!$P$12,$C$12+0.42*ABERTURAS!$P$12),0)+$AZ$8)/$AZ$7 -> 0.30543746 | BL4: =(IF(ABERTURAS!$K$12="OK",ABERTURAS!$Q$12+0.26*CHOOSE(ABERTURAS!$N$12,0,$C$13,ABERTURAS!$P$12,ABERTURAS!$P$12),0)+$AZ$9)/$AZ$7 -> 0.041677003 | BM4: =(IF(ABERTURAS!$K$13="OK",CHOOSE(ABERTURAS!$N$13,ABERTURAS!$P$13,ABERTURAS!$P$13+0.42*$C$13,0.42*ABERTURAS!$P$13,$C$12+0.42*ABERTURAS!$P$13),0)+$AZ$8)/$AZ$7 -> 0.30543746 | BN4: =(IF(ABERTURAS!$K$13="OK",ABERTURAS!$Q$13+0.26*CHOOSE(ABERTURAS!$N$13,0,$C$13,ABERTURAS!$P$13,ABERTURAS!$P$13),0)+$AZ$9)/$AZ$7 -> 0.041677003 | BO4: =(IF(ABERTURAS!$K$14="OK",CHOOSE(ABERTURAS!$N$14,ABERTURAS!$P$14,ABERTURAS!$P$14+0.42*$C$13,0.42*ABERTURAS!$P$14,$C$12+0.42*ABERTURAS!$P$14),0)+$AZ$8)/$AZ$7 -> 0.30543746 | BP4: =(IF(ABERTURAS!$K$14="OK",ABERTURAS!$Q$14+0.26*CHOOSE(ABERTURAS!$N$14,0,$C$13,ABERTURAS!$P$14,ABERTURAS!$P$14),0)+$AZ$9)/$AZ$7 -> 0.041677003 | BQ4: =(IF(ABERTURAS!$K$15="OK",CHOOSE(ABERTURAS!$N$15,ABERTURAS!$P$15,ABERTURAS!$P$15+0.42*$C$13,0.42*ABERTURAS!$P$15,$C$12+0.42*ABERTURAS!$P$15),0)+$AZ$8)/$AZ$7 -> 0.30543746 | BR4: =(IF(ABERTURAS!$K$15="OK",ABERTURAS!$Q$15+0.26*CHOOSE(ABERTURAS!$N$15,0,$C$13,ABERTURAS!$P$15,ABERTURAS!$P$15),0)+$AZ$9)/$AZ$7 -> 0.041677003 | BS4: =(IF(ABERTURAS!$K$16="OK",CHOOSE(ABERTURAS!$N$16,ABERTURAS!$P$16,ABERTURAS!$P$16+0.42*$C$13,0.42*ABERTURAS!$P$16,$C$12+0.42*ABERTURAS!$P$16),0)+$AZ$8)/$AZ$7 -> 0.30543746 | BT4: =(IF(ABERTURAS!$K$16="OK",ABERTURAS!$Q$16+0.26*CHOOSE(ABERTURAS!$N$16,0,$C$13,ABERTURAS!$P$16,ABERTURAS!$P$16),0)+$AZ$9)/$AZ$7 -> 0.041677003 | BU4: =(IF(ABERTURAS!$K$17="OK",CHOOSE(ABERTURAS!$N$17,ABERTURAS!$P$17,ABERTURAS!$P$17+0.42*$C$13,0.42*ABERTURAS!$P$17,$C$12+0.42*ABERTURAS!$P$17),0)+$AZ$8)/$AZ$7 -> 0.30543746 | BV4: =(IF(ABERTURAS!$K$17="OK",ABERTURAS!$Q$17+0.26*CHOOSE(ABERTURAS!$N$17,0,$C$13,ABERTURAS!$P$17,ABERTURAS!$P$17),0)+$AZ$9)/$AZ$7 -> 0.041677003 | BW4: =(IF(ABERTURAS!$K$18="OK",CHOOSE(ABERTURAS!$N$18,ABERTURAS!$P$18,ABERTURAS!$P$18+0.42*$C$13,0.42*ABERTURAS!$P$18,$C$12+0.42*ABERTURAS!$P$18),0)+$AZ$8)/$AZ$7 -> 0.30543746 | BX4: =(IF(ABERTURAS!$K$18="OK",ABERTURAS!$Q$18+0.26*CHOOSE(ABERTURAS!$N$18,0,$C$13,ABERTURAS!$P$18,ABERTURAS!$P$18),0)+$AZ$9)/$AZ$7 -> 0.041677003 | BY4: =(IF(ABERTURAS!$K$19="OK",CHOOSE(ABERTURAS!$N$19,ABERTURAS!$P$19,ABERTURAS!$P$19+0.42*$C$13,0.42*ABERTURAS!$P$19,$C$12+0.42*ABERTURAS!$P$19),0)+$AZ$8)/$AZ$7 -> 0.30543746 | BZ4: =(IF(ABERTURAS!$K$19="OK",ABERTURAS!$Q$19+0.26*CHOOSE(ABERTURAS!$N$19,0,$C$13,ABERTURAS!$P$19,ABERTURAS!$P$19),0)+$AZ$9)/$AZ$7 -> 0.041677003 | CA4: =(IF(ABERTURAS!$K$20="OK",CHOOSE(ABERTURAS!$N$20,ABERTURAS!$P$20,ABERTURAS!$P$20+0.42*$C$13,0.42*ABERTURAS!$P$20,$C$12+0.42*ABERTURAS!$P$20),0)+$AZ$8)/$AZ$7 -> 0.30543746 | CB4: =(IF(ABERTURAS!$K$20="OK",ABERTURAS!$Q$20+0.26*CHOOSE(ABERTURAS!$N$20,0,$C$13,ABERTURAS!$P$20,ABERTURAS!$P$20),0)+$AZ$9)/$AZ$7 -> 0.041677003 | CC4: =(IF(ABERTURAS!$K$21="OK",CHOOSE(ABERTURAS!$N$21,ABERTURAS!$P$21,ABERTURAS!$P$21+0.42*$C$13,0.42*ABERTURAS!$P$21,$C$12+0.42*ABERTURAS!$P$21),0)+$AZ$8)/$AZ$7 -> 0.30543746 | CD4: =(IF(ABERTURAS!$K$21="OK",ABERTURAS!$Q$21+0.26*CHOOSE(ABERTURAS!$N$21,0,$C$13,ABERTURAS!$P$21,ABERTURAS!$P$21),0)+$AZ$9)/$AZ$7 -> 0.041677003 | CE4: =(IF(ABERTURAS!$K$22="OK",CHOOSE(ABERTURAS!$N$22,ABERTURAS!$P$22,ABERTURAS!$P$22+0.42*$C$13,0.42*ABERTURAS!$P$22,$C$12+0.42*ABERTURAS!$P$22),0)+$AZ$8)/$AZ$7 -> 0.30543746 | CF4: =(IF(ABERTURAS!$K$22="OK",ABERTURAS!$Q$22+0.26*CHOOSE(ABERTURAS!$N$22,0,$C$13,ABERTURAS!$P$22,ABERTURAS!$P$22),0)+$AZ$9)/$AZ$7 -> 0.041677003 | CG4: =(IF(ABERTURAS!$K$23="OK",CHOOSE(ABERTURAS!$N$23,ABERTURAS!$P$23,ABERTURAS!$P$23+0.42*$C$13,0.42*ABERTURAS!$P$23,$C$12+0.42*ABERTURAS!$P$23),0)+$AZ$8)/$AZ$7 -> 0.30543746 | CH4: =(IF(ABERTURAS!$K$23="OK",ABERTURAS!$Q$23+0.26*CHOOSE(ABERTURAS!$N$23,0,$C$13,ABERTURAS!$P$23,ABERTURAS!$P$23),0)+$AZ$9)/$AZ$7 -> 0.041677003 | CI4: =(IF(ABERTURAS!$K$24="OK",CHOOSE(ABERTURAS!$N$24,ABERTURAS!$P$24,ABERTURAS!$P$24+0.42*$C$13,0.42*ABERTURAS!$P$24,$C$12+0.42*ABERTURAS!$P$24),0)+$AZ$8)/$AZ$7 -> 0.30543746 | CJ4: =(IF(ABERTURAS!$K$24="OK",ABERTURAS!$Q$24+0.26*CHOOSE(ABERTURAS!$N$24,0,$C$13,ABERTURAS!$P$24,ABERTURAS!$P$24),0)+$AZ$9)/$AZ$7 -> 0.041677003 | CK4: =(IF(ABERTURAS!$K$25="OK",CHOOSE(ABERTURAS!$N$25,ABERTURAS!$P$25,ABERTURAS!$P$25+0.42*$C$13,0.42*ABERTURAS!$P$25,$C$12+0.42*ABERTURAS!$P$25),0)+$AZ$8)/$AZ$7 -> 0.30543746 | CL4: =(IF(ABERTURAS!$K$25="OK",ABERTURAS!$Q$25+0.26*CHOOSE(ABERTURAS!$N$25,0,$C$13,ABERTURAS!$P$25,ABERTURAS!$P$25),0)+$AZ$9)/$AZ$7 -> 0.041677003 | CM4: =(IF(ABERTURAS!$K$26="OK",CHOOSE(ABERTURAS!$N$26,ABERTURAS!$P$26,ABERTURAS!$P$26+0.42*$C$13,0.42*ABERTURAS!$P$26,$C$12+0.42*ABERTURAS!$P$26),0)+$AZ$8)/$AZ$7 -> 0.30543746 | CN4: =(IF(ABERTURAS!$K$26="OK",ABERTURAS!$Q$26+0.26*CHOOSE(ABERTURAS!$N$26,0,$C$13,ABERTURAS!$P$26,ABERTURAS!$P$26),0)+$AZ$9)/$AZ$7 -> 0.041677003
B5: 1. PROYECTO | AA5: =$C$23*2/8 -> 4 | AB5: =IF($C$14="PLANO",$C$17,IF($C$14="DOS AGUAS",$C$17+($C$18-$C$17)*(1-ABS(2*($AA$5)/$C$23-1)),IF($C$14="UN AGUA",IF(N($C$25)=0,$C$18-($C$18-$C$17)*($AA$5)/$C$23,$C$17+($C$18-$C$17)*($AA$5)/$C$23),$C$17+4*($C$18-$C$17)*($AA$5)/$C$23*(1-($AA$5)/$C$23)))) -> 10.42 | AE5: =ABERTURAS!$D$51*8/8 -> 10.08 | AF5: =IF(ABERTURAS!$E$51="SÍ",$AB$11,ABERTURAS!$F$51) -> 10.62 | AG5: =($AE5+0.42*0+$AZ$8)/$AZ$7 -> 0.93059251 | AH5: =($AF5+0.26*0+$AZ$9)/$AZ$7 -> 0.7003225 | AI5: =ABERTURAS!$D$52*8/8 -> 10.08 | AJ5: =IF(ABERTURAS!$E$52="SÍ",$AB$11,ABERTURAS!$F$52) -> 9.82 | AK5: =($AI5+0.42*$C$13+$AZ$8)/$AZ$7 -> 1.3473625 | AL5: =($AJ5+0.26*$C$13+$AZ$9)/$AZ$7 -> 0.90870752 | AM5: =ABERTURAS!$D$53*8/8 -> 16 | AN5: =IF(ABERTURAS!$E$53="SÍ",$AB$11,ABERTURAS!$F$53) -> 9.82 | AO5: =(0+0.42*$AM5+$AZ$8)/$AZ$7 -> 0.72220749 | AP5: =($AN5+0.26*$AM5+$AZ$9)/$AZ$7 -> 0.90870752 | AQ5: =ABERTURAS!$D$54*8/8 -> 16 | AR5: =IF(ABERTURAS!$E$54="SÍ",$AB$11,ABERTURAS!$F$54) -> 9.82 | AS5: =($C$12+0.42*$AQ5+$AZ$8)/$AZ$7 -> 1.3473625 | AT5: =($AR5+0.26*$AQ5+$AZ$9)/$AZ$7 -> 0.90870752 | AU5: =(IF($AC$3="X",$AA$5+0.42*IF($AC$3="X",$C$13,$C$12),IF($AC$3="X",$C$13,$C$12)+0.42*$AA$5)+$AZ$8)/$AZ$7 -> 1.034785 | AV5: =($AB$5+0.26*IF($AC$3="X",IF($AC$3="X",$C$13,$C$12),$AA$5)+$AZ$9)/$AZ$7 -> 0.75241875 | AW5: =(0+$AZ$8)/$AZ$7 -> 0.30543746 | AX5: =(1.25*$C$21+$AZ$9)/$AZ$7 -> 0.86498387 | AY5: margen | AZ5: =0.04*MAX($AZ$3,$AZ$4) -> 0.672 | BA5: =(IF(ABERTURAS!$K$7="OK",CHOOSE(ABERTURAS!$N$7,ABERTURAS!$P$7,ABERTURAS!$P$7+0.42*$C$13,0.42*ABERTURAS!$P$7,$C$12+0.42*ABERTURAS!$P$7),0)+$AZ$8)/$AZ$7 -> 0.42599687 | BB5: =(IF(ABERTURAS!$K$7="OK",ABERTURAS!$R$7+0.26*CHOOSE(ABERTURAS!$N$7,0,$C$13,ABERTURAS!$P$7,ABERTURAS!$P$7),0)+$AZ$9)/$AZ$7 -> 0.19052344 | BC5: =(IF(ABERTURAS!$K$8="OK",CHOOSE(ABERTURAS!$N$8,ABERTURAS!$P$8,ABERTURAS!$P$8+0.42*$C$13,0.42*ABERTURAS!$P$8,$C$12+0.42*ABERTURAS!$P$8),0)+$AZ$8)/$AZ$7 -> 0.7760713 | BD5: =(IF(ABERTURAS!$K$8="OK",ABERTURAS!$R$8+0.26*CHOOSE(ABERTURAS!$N$8,0,$C$13,ABERTURAS!$P$8,ABERTURAS!$P$8),0)+$AZ$9)/$AZ$7 -> 0.43425949 | BE5: =(IF(ABERTURAS!$K$9="OK",CHOOSE(ABERTURAS!$N$9,ABERTURAS!$P$9,ABERTURAS!$P$9+0.42*$C$13,0.42*ABERTURAS!$P$9,$C$12+0.42*ABERTURAS!$P$9),0)+$AZ$8)/$AZ$7 -> 1.3473625 | BF5: =(IF(ABERTURAS!$K$9="OK",ABERTURAS!$R$9+0.26*CHOOSE(ABERTURAS!$N$9,0,$C$13,ABERTURAS!$P$9,ABERTURAS!$P$9),0)+$AZ$9)/$AZ$7 -> 0.90870752 | BG5: =(IF(ABERTURAS!$K$10="OK",CHOOSE(ABERTURAS!$N$10,ABERTURAS!$P$10,ABERTURAS!$P$10+0.42*$C$13,0.42*ABERTURAS!$P$10,$C$12+0.42*ABERTURAS!$P$10),0)+$AZ$8)/$AZ$7 -> 0.30543746 | BH5: =(IF(ABERTURAS!$K$10="OK",ABERTURAS!$R$10+0.26*CHOOSE(ABERTURAS!$N$10,0,$C$13,ABERTURAS!$P$10,ABERTURAS!$P$10),0)+$AZ$9)/$AZ$7 -> 0.041677003 | BI5: =(IF(ABERTURAS!$K$11="OK",CHOOSE(ABERTURAS!$N$11,ABERTURAS!$P$11,ABERTURAS!$P$11+0.42*$C$13,0.42*ABERTURAS!$P$11,$C$12+0.42*ABERTURAS!$P$11),0)+$AZ$8)/$AZ$7 -> 0.30543746 | BJ5: =(IF(ABERTURAS!$K$11="OK",ABERTURAS!$R$11+0.26*CHOOSE(ABERTURAS!$N$11,0,$C$13,ABERTURAS!$P$11,ABERTURAS!$P$11),0)+$AZ$9)/$AZ$7 -> 0.041677003 | BK5: =(IF(ABERTURAS!$K$12="OK",CHOOSE(ABERTURAS!$N$12,ABERTURAS!$P$12,ABERTURAS!$P$12+0.42*$C$13,0.42*ABERTURAS!$P$12,$C$12+0.42*ABERTURAS!$P$12),0)+$AZ$8)/$AZ$7 -> 0.30543746 | BL5: =(IF(ABERTURAS!$K$12="OK",ABERTURAS!$R$12+0.26*CHOOSE(ABERTURAS!$N$12,0,$C$13,ABERTURAS!$P$12,ABERTURAS!$P$12),0)+$AZ$9)/$AZ$7 -> 0.041677003 | BM5: =(IF(ABERTURAS!$K$13="OK",CHOOSE(ABERTURAS!$N$13,ABERTURAS!$P$13,ABERTURAS!$P$13+0.42*$C$13,0.42*ABERTURAS!$P$13,$C$12+0.42*ABERTURAS!$P$13),0)+$AZ$8)/$AZ$7 -> 0.30543746 | BN5: =(IF(ABERTURAS!$K$13="OK",ABERTURAS!$R$13+0.26*CHOOSE(ABERTURAS!$N$13,0,$C$13,ABERTURAS!$P$13,ABERTURAS!$P$13),0)+$AZ$9)/$AZ$7 -> 0.041677003 | BO5: =(IF(ABERTURAS!$K$14="OK",CHOOSE(ABERTURAS!$N$14,ABERTURAS!$P$14,ABERTURAS!$P$14+0.42*$C$13,0.42*ABERTURAS!$P$14,$C$12+0.42*ABERTURAS!$P$14),0)+$AZ$8)/$AZ$7 -> 0.30543746 | BP5: =(IF(ABERTURAS!$K$14="OK",ABERTURAS!$R$14+0.26*CHOOSE(ABERTURAS!$N$14,0,$C$13,ABERTURAS!$P$14,ABERTURAS!$P$14),0)+$AZ$9)/$AZ$7 -> 0.041677003 | BQ5: =(IF(ABERTURAS!$K$15="OK",CHOOSE(ABERTURAS!$N$15,ABERTURAS!$P$15,ABERTURAS!$P$15+0.42*$C$13,0.42*ABERTURAS!$P$15,$C$12+0.42*ABERTURAS!$P$15),0)+$AZ$8)/$AZ$7 -> 0.30543746 | BR5: =(IF(ABERTURAS!$K$15="OK",ABERTURAS!$R$15+0.26*CHOOSE(ABERTURAS!$N$15,0,$C$13,ABERTURAS!$P$15,ABERTURAS!$P$15),0)+$AZ$9)/$AZ$7 -> 0.041677003 | BS5: =(IF(ABERTURAS!$K$16="OK",CHOOSE(ABERTURAS!$N$16,ABERTURAS!$P$16,ABERTURAS!$P$16+0.42*$C$13,0.42*ABERTURAS!$P$16,$C$12+0.42*ABERTURAS!$P$16),0)+$AZ$8)/$AZ$7 -> 0.30543746 | BT5: =(IF(ABERTURAS!$K$16="OK",ABERTURAS!$R$16+0.26*CHOOSE(ABERTURAS!$N$16,0,$C$13,ABERTURAS!$P$16,ABERTURAS!$P$16),0)+$AZ$9)/$AZ$7 -> 0.041677003 | BU5: =(IF(ABERTURAS!$K$17="OK",CHOOSE(ABERTURAS!$N$17,ABERTURAS!$P$17,ABERTURAS!$P$17+0.42*$C$13,0.42*ABERTURAS!$P$17,$C$12+0.42*ABERTURAS!$P$17),0)+$AZ$8)/$AZ$7 -> 0.30543746 | BV5: =(IF(ABERTURAS!$K$17="OK",ABERTURAS!$R$17+0.26*CHOOSE(ABERTURAS!$N$17,0,$C$13,ABERTURAS!$P$17,ABERTURAS!$P$17),0)+$AZ$9)/$AZ$7 -> 0.041677003 | BW5: =(IF(ABERTURAS!$K$18="OK",CHOOSE(ABERTURAS!$N$18,ABERTURAS!$P$18,ABERTURAS!$P$18+0.42*$C$13,0.42*ABERTURAS!$P$18,$C$12+0.42*ABERTURAS!$P$18),0)+$AZ$8)/$AZ$7 -> 0.30543746 | BX5: =(IF(ABERTURAS!$K$18="OK",ABERTURAS!$R$18+0.26*CHOOSE(ABERTURAS!$N$18,0,$C$13,ABERTURAS!$P$18,ABERTURAS!$P$18),0)+$AZ$9)/$AZ$7 -> 0.041677003 | BY5: =(IF(ABERTURAS!$K$19="OK",CHOOSE(ABERTURAS!$N$19,ABERTURAS!$P$19,ABERTURAS!$P$19+0.42*$C$13,0.42*ABERTURAS!$P$19,$C$12+0.42*ABERTURAS!$P$19),0)+$AZ$8)/$AZ$7 -> 0.30543746 | BZ5: =(IF(ABERTURAS!$K$19="OK",ABERTURAS!$R$19+0.26*CHOOSE(ABERTURAS!$N$19,0,$C$13,ABERTURAS!$P$19,ABERTURAS!$P$19),0)+$AZ$9)/$AZ$7 -> 0.041677003 | CA5: =(IF(ABERTURAS!$K$20="OK",CHOOSE(ABERTURAS!$N$20,ABERTURAS!$P$20,ABERTURAS!$P$20+0.42*$C$13,0.42*ABERTURAS!$P$20,$C$12+0.42*ABERTURAS!$P$20),0)+$AZ$8)/$AZ$7 -> 0.30543746 | CB5: =(IF(ABERTURAS!$K$20="OK",ABERTURAS!$R$20+0.26*CHOOSE(ABERTURAS!$N$20,0,$C$13,ABERTURAS!$P$20,ABERTURAS!$P$20),0)+$AZ$9)/$AZ$7 -> 0.041677003 | CC5: =(IF(ABERTURAS!$K$21="OK",CHOOSE(ABERTURAS!$N$21,ABERTURAS!$P$21,ABERTURAS!$P$21+0.42*$C$13,0.42*ABERTURAS!$P$21,$C$12+0.42*ABERTURAS!$P$21),0)+$AZ$8)/$AZ$7 -> 0.30543746 | CD5: =(IF(ABERTURAS!$K$21="OK",ABERTURAS!$R$21+0.26*CHOOSE(ABERTURAS!$N$21,0,$C$13,ABERTURAS!$P$21,ABERTURAS!$P$21),0)+$AZ$9)/$AZ$7 -> 0.041677003 | CE5: =(IF(ABERTURAS!$K$22="OK",CHOOSE(ABERTURAS!$N$22,ABERTURAS!$P$22,ABERTURAS!$P$22+0.42*$C$13,0.42*ABERTURAS!$P$22,$C$12+0.42*ABERTURAS!$P$22),0)+$AZ$8)/$AZ$7 -> 0.30543746 | CF5: =(IF(ABERTURAS!$K$22="OK",ABERTURAS!$R$22+0.26*CHOOSE(ABERTURAS!$N$22,0,$C$13,ABERTURAS!$P$22,ABERTURAS!$P$22),0)+$AZ$9)/$AZ$7 -> 0.041677003 | CG5: =(IF(ABERTURAS!$K$23="OK",CHOOSE(ABERTURAS!$N$23,ABERTURAS!$P$23,ABERTURAS!$P$23+0.42*$C$13,0.42*ABERTURAS!$P$23,$C$12+0.42*ABERTURAS!$P$23),0)+$AZ$8)/$AZ$7 -> 0.30543746 | CH5: =(IF(ABERTURAS!$K$23="OK",ABERTURAS!$R$23+0.26*CHOOSE(ABERTURAS!$N$23,0,$C$13,ABERTURAS!$P$23,ABERTURAS!$P$23),0)+$AZ$9)/$AZ$7 -> 0.041677003 | CI5: =(IF(ABERTURAS!$K$24="OK",CHOOSE(ABERTURAS!$N$24,ABERTURAS!$P$24,ABERTURAS!$P$24+0.42*$C$13,0.42*ABERTURAS!$P$24,$C$12+0.42*ABERTURAS!$P$24),0)+$AZ$8)/$AZ$7 -> 0.30543746 | CJ5: =(IF(ABERTURAS!$K$24="OK",ABERTURAS!$R$24+0.26*CHOOSE(ABERTURAS!$N$24,0,$C$13,ABERTURAS!$P$24,ABERTURAS!$P$24),0)+$AZ$9)/$AZ$7 -> 0.041677003 | CK5: =(IF(ABERTURAS!$K$25="OK",CHOOSE(ABERTURAS!$N$25,ABERTURAS!$P$25,ABERTURAS!$P$25+0.42*$C$13,0.42*ABERTURAS!$P$25,$C$12+0.42*ABERTURAS!$P$25),0)+$AZ$8)/$AZ$7 -> 0.30543746 | CL5: =(IF(ABERTURAS!$K$25="OK",ABERTURAS!$R$25+0.26*CHOOSE(ABERTURAS!$N$25,0,$C$13,ABERTURAS!$P$25,ABERTURAS!$P$25),0)+$AZ$9)/$AZ$7 -> 0.041677003 | CM5: =(IF(ABERTURAS!$K$26="OK",CHOOSE(ABERTURAS!$N$26,ABERTURAS!$P$26,ABERTURAS!$P$26+0.42*$C$13,0.42*ABERTURAS!$P$26,$C$12+0.42*ABERTURAS!$P$26),0)+$AZ$8)/$AZ$7 -> 0.30543746 | CN5: =(IF(ABERTURAS!$K$26="OK",ABERTURAS!$R$26+0.26*CHOOSE(ABERTURAS!$N$26,0,$C$13,ABERTURAS!$P$26,ABERTURAS!$P$26),0)+$AZ$9)/$AZ$7 -> 0.041677003
B6: Concepto | C6: Valor | D6: Unidad | E6: Cómo se calcula / de dónde sale | F6: Referencia | AA6: =$C$23*3/8 -> 6 | AB6: =IF($C$14="PLANO",$C$17,IF($C$14="DOS AGUAS",$C$17+($C$18-$C$17)*(1-ABS(2*($AA$6)/$C$23-1)),IF($C$14="UN AGUA",IF(N($C$25)=0,$C$18-($C$18-$C$17)*($AA$6)/$C$23,$C$17+($C$18-$C$17)*($AA$6)/$C$23),$C$17+4*($C$18-$C$17)*($AA$6)/$C$23*(1-($AA$6)/$C$23)))) -> 10.32 | AE6: =ABERTURAS!$D$51*7/8 -> 8.82 | AF6: =IF(ABERTURAS!$E$51="SÍ",$AB$10,ABERTURAS!$F$51) -> 10.62 | AG6: =($AE6+0.42*0+$AZ$8)/$AZ$7 -> 0.85244813 | AH6: =($AF6+0.26*0+$AZ$9)/$AZ$7 -> 0.7003225 | AI6: =ABERTURAS!$D$52*7/8 -> 8.82 | AJ6: =IF(ABERTURAS!$E$52="SÍ",$AB$10,ABERTURAS!$F$52) -> 9.82 | AK6: =($AI6+0.42*$C$13+$AZ$8)/$AZ$7 -> 1.2692182 | AL6: =($AJ6+0.26*$C$13+$AZ$9)/$AZ$7 -> 0.90870752 | AM6: =ABERTURAS!$D$53*7/8 -> 14 | AN6: =IF(ABERTURAS!$E$53="SÍ",$AB$10,ABERTURAS!$F$53) -> 9.92 | AO6: =(0+0.42*$AM6+$AZ$8)/$AZ$7 -> 0.67011124 | AP6: =($AN6+0.26*$AM6+$AZ$9)/$AZ$7 -> 0.88265939 | AQ6: =ABERTURAS!$D$54*7/8 -> 14 | AR6: =IF(ABERTURAS!$E$54="SÍ",$AB$10,ABERTURAS!$F$54) -> 9.92 | AS6: =($C$12+0.42*$AQ6+$AZ$8)/$AZ$7 -> 1.2952663 | AT6: =($AR6+0.26*$AQ6+$AZ$9)/$AZ$7 -> 0.88265939 | AU6: =(IF($AC$3="X",$AA$5+0.42*0,0+0.42*$AA$5)+$AZ$8)/$AZ$7 -> 0.40962997 | AV6: =($AB$5+0.26*IF($AC$3="X",0,$AA$5)+$AZ$9)/$AZ$7 -> 0.75241875 | AW6: =(0+$AZ$8)/$AZ$7 -> 0.30543746 | AX6: =(0+$AZ$9)/$AZ$7 -> 0.041677003 | AY6: aspecto | AZ6: =1.6528 -> 1.6528 | BA6: =(IF(ABERTURAS!$K$7="OK",CHOOSE(ABERTURAS!$N$7,ABERTURAS!$O$7,ABERTURAS!$O$7+0.42*$C$13,0.42*ABERTURAS!$O$7,$C$12+0.42*ABERTURAS!$O$7),0)+$AZ$8)/$AZ$7 -> 0.34528489 | BB6: =(IF(ABERTURAS!$K$7="OK",ABERTURAS!$R$7+0.26*CHOOSE(ABERTURAS!$N$7,0,$C$13,ABERTURAS!$O$7,ABERTURAS!$O$7),0)+$AZ$9)/$AZ$7 -> 0.19052344 | BC6: =(IF(ABERTURAS!$K$8="OK",CHOOSE(ABERTURAS!$N$8,ABERTURAS!$O$8,ABERTURAS!$O$8+0.42*$C$13,0.42*ABERTURAS!$O$8,$C$12+0.42*ABERTURAS!$O$8),0)+$AZ$8)/$AZ$7 -> 0.45967338 | BD6: =(IF(ABERTURAS!$K$8="OK",ABERTURAS!$R$8+0.26*CHOOSE(ABERTURAS!$N$8,0,$C$13,ABERTURAS!$O$8,ABERTURAS!$O$8),0)+$AZ$9)/$AZ$7 -> 0.43425949 | BE6: =(IF(ABERTURAS!$K$9="OK",CHOOSE(ABERTURAS!$N$9,ABERTURAS!$O$9,ABERTURAS!$O$9+0.42*$C$13,0.42*ABERTURAS!$O$9,$C$12+0.42*ABERTURAS!$O$9),0)+$AZ$8)/$AZ$7 -> 0.72220749 | BF6: =(IF(ABERTURAS!$K$9="OK",ABERTURAS!$R$9+0.26*CHOOSE(ABERTURAS!$N$9,0,$C$13,ABERTURAS!$O$9,ABERTURAS!$O$9),0)+$AZ$9)/$AZ$7 -> 0.90870752 | BG6: =(IF(ABERTURAS!$K$10="OK",CHOOSE(ABERTURAS!$N$10,ABERTURAS!$O$10,ABERTURAS!$O$10+0.42*$C$13,0.42*ABERTURAS!$O$10,$C$12+0.42*ABERTURAS!$O$10),0)+$AZ$8)/$AZ$7 -> 0.30543746 | BH6: =(IF(ABERTURAS!$K$10="OK",ABERTURAS!$R$10+0.26*CHOOSE(ABERTURAS!$N$10,0,$C$13,ABERTURAS!$O$10,ABERTURAS!$O$10),0)+$AZ$9)/$AZ$7 -> 0.041677003 | BI6: =(IF(ABERTURAS!$K$11="OK",CHOOSE(ABERTURAS!$N$11,ABERTURAS!$O$11,ABERTURAS!$O$11+0.42*$C$13,0.42*ABERTURAS!$O$11,$C$12+0.42*ABERTURAS!$O$11),0)+$AZ$8)/$AZ$7 -> 0.30543746 | BJ6: =(IF(ABERTURAS!$K$11="OK",ABERTURAS!$R$11+0.26*CHOOSE(ABERTURAS!$N$11,0,$C$13,ABERTURAS!$O$11,ABERTURAS!$O$11),0)+$AZ$9)/$AZ$7 -> 0.041677003 | BK6: =(IF(ABERTURAS!$K$12="OK",CHOOSE(ABERTURAS!$N$12,ABERTURAS!$O$12,ABERTURAS!$O$12+0.42*$C$13,0.42*ABERTURAS!$O$12,$C$12+0.42*ABERTURAS!$O$12),0)+$AZ$8)/$AZ$7 -> 0.30543746 | BL6: =(IF(ABERTURAS!$K$12="OK",ABERTURAS!$R$12+0.26*CHOOSE(ABERTURAS!$N$12,0,$C$13,ABERTURAS!$O$12,ABERTURAS!$O$12),0)+$AZ$9)/$AZ$7 -> 0.041677003 | BM6: =(IF(ABERTURAS!$K$13="OK",CHOOSE(ABERTURAS!$N$13,ABERTURAS!$O$13,ABERTURAS!$O$13+0.42*$C$13,0.42*ABERTURAS!$O$13,$C$12+0.42*ABERTURAS!$O$13),0)+$AZ$8)/$AZ$7 -> 0.30543746 | BN6: =(IF(ABERTURAS!$K$13="OK",ABERTURAS!$R$13+0.26*CHOOSE(ABERTURAS!$N$13,0,$C$13,ABERTURAS!$O$13,ABERTURAS!$O$13),0)+$AZ$9)/$AZ$7 -> 0.041677003 | BO6: =(IF(ABERTURAS!$K$14="OK",CHOOSE(ABERTURAS!$N$14,ABERTURAS!$O$14,ABERTURAS!$O$14+0.42*$C$13,0.42*ABERTURAS!$O$14,$C$12+0.42*ABERTURAS!$O$14),0)+$AZ$8)/$AZ$7 -> 0.30543746 | BP6: =(IF(ABERTURAS!$K$14="OK",ABERTURAS!$R$14+0.26*CHOOSE(ABERTURAS!$N$14,0,$C$13,ABERTURAS!$O$14,ABERTURAS!$O$14),0)+$AZ$9)/$AZ$7 -> 0.041677003 | BQ6: =(IF(ABERTURAS!$K$15="OK",CHOOSE(ABERTURAS!$N$15,ABERTURAS!$O$15,ABERTURAS!$O$15+0.42*$C$13,0.42*ABERTURAS!$O$15,$C$12+0.42*ABERTURAS!$O$15),0)+$AZ$8)/$AZ$7 -> 0.30543746 | BR6: =(IF(ABERTURAS!$K$15="OK",ABERTURAS!$R$15+0.26*CHOOSE(ABERTURAS!$N$15,0,$C$13,ABERTURAS!$O$15,ABERTURAS!$O$15),0)+$AZ$9)/$AZ$7 -> 0.041677003 | BS6: =(IF(ABERTURAS!$K$16="OK",CHOOSE(ABERTURAS!$N$16,ABERTURAS!$O$16,ABERTURAS!$O$16+0.42*$C$13,0.42*ABERTURAS!$O$16,$C$12+0.42*ABERTURAS!$O$16),0)+$AZ$8)/$AZ$7 -> 0.30543746 | BT6: =(IF(ABERTURAS!$K$16="OK",ABERTURAS!$R$16+0.26*CHOOSE(ABERTURAS!$N$16,0,$C$13,ABERTURAS!$O$16,ABERTURAS!$O$16),0)+$AZ$9)/$AZ$7 -> 0.041677003 | BU6: =(IF(ABERTURAS!$K$17="OK",CHOOSE(ABERTURAS!$N$17,ABERTURAS!$O$17,ABERTURAS!$O$17+0.42*$C$13,0.42*ABERTURAS!$O$17,$C$12+0.42*ABERTURAS!$O$17),0)+$AZ$8)/$AZ$7 -> 0.30543746 | BV6: =(IF(ABERTURAS!$K$17="OK",ABERTURAS!$R$17+0.26*CHOOSE(ABERTURAS!$N$17,0,$C$13,ABERTURAS!$O$17,ABERTURAS!$O$17),0)+$AZ$9)/$AZ$7 -> 0.041677003 | BW6: =(IF(ABERTURAS!$K$18="OK",CHOOSE(ABERTURAS!$N$18,ABERTURAS!$O$18,ABERTURAS!$O$18+0.42*$C$13,0.42*ABERTURAS!$O$18,$C$12+0.42*ABERTURAS!$O$18),0)+$AZ$8)/$AZ$7 -> 0.30543746 | BX6: =(IF(ABERTURAS!$K$18="OK",ABERTURAS!$R$18+0.26*CHOOSE(ABERTURAS!$N$18,0,$C$13,ABERTURAS!$O$18,ABERTURAS!$O$18),0)+$AZ$9)/$AZ$7 -> 0.041677003 | BY6: =(IF(ABERTURAS!$K$19="OK",CHOOSE(ABERTURAS!$N$19,ABERTURAS!$O$19,ABERTURAS!$O$19+0.42*$C$13,0.42*ABERTURAS!$O$19,$C$12+0.42*ABERTURAS!$O$19),0)+$AZ$8)/$AZ$7 -> 0.30543746 | BZ6: =(IF(ABERTURAS!$K$19="OK",ABERTURAS!$R$19+0.26*CHOOSE(ABERTURAS!$N$19,0,$C$13,ABERTURAS!$O$19,ABERTURAS!$O$19),0)+$AZ$9)/$AZ$7 -> 0.041677003 | CA6: =(IF(ABERTURAS!$K$20="OK",CHOOSE(ABERTURAS!$N$20,ABERTURAS!$O$20,ABERTURAS!$O$20+0.42*$C$13,0.42*ABERTURAS!$O$20,$C$12+0.42*ABERTURAS!$O$20),0)+$AZ$8)/$AZ$7 -> 0.30543746 | CB6: =(IF(ABERTURAS!$K$20="OK",ABERTURAS!$R$20+0.26*CHOOSE(ABERTURAS!$N$20,0,$C$13,ABERTURAS!$O$20,ABERTURAS!$O$20),0)+$AZ$9)/$AZ$7 -> 0.041677003 | CC6: =(IF(ABERTURAS!$K$21="OK",CHOOSE(ABERTURAS!$N$21,ABERTURAS!$O$21,ABERTURAS!$O$21+0.42*$C$13,0.42*ABERTURAS!$O$21,$C$12+0.42*ABERTURAS!$O$21),0)+$AZ$8)/$AZ$7 -> 0.30543746 | CD6: =(IF(ABERTURAS!$K$21="OK",ABERTURAS!$R$21+0.26*CHOOSE(ABERTURAS!$N$21,0,$C$13,ABERTURAS!$O$21,ABERTURAS!$O$21),0)+$AZ$9)/$AZ$7 -> 0.041677003 | CE6: =(IF(ABERTURAS!$K$22="OK",CHOOSE(ABERTURAS!$N$22,ABERTURAS!$O$22,ABERTURAS!$O$22+0.42*$C$13,0.42*ABERTURAS!$O$22,$C$12+0.42*ABERTURAS!$O$22),0)+$AZ$8)/$AZ$7 -> 0.30543746 | CF6: =(IF(ABERTURAS!$K$22="OK",ABERTURAS!$R$22+0.26*CHOOSE(ABERTURAS!$N$22,0,$C$13,ABERTURAS!$O$22,ABERTURAS!$O$22),0)+$AZ$9)/$AZ$7 -> 0.041677003 | CG6: =(IF(ABERTURAS!$K$23="OK",CHOOSE(ABERTURAS!$N$23,ABERTURAS!$O$23,ABERTURAS!$O$23+0.42*$C$13,0.42*ABERTURAS!$O$23,$C$12+0.42*ABERTURAS!$O$23),0)+$AZ$8)/$AZ$7 -> 0.30543746 | CH6: =(IF(ABERTURAS!$K$23="OK",ABERTURAS!$R$23+0.26*CHOOSE(ABERTURAS!$N$23,0,$C$13,ABERTURAS!$O$23,ABERTURAS!$O$23),0)+$AZ$9)/$AZ$7 -> 0.041677003 | CI6: =(IF(ABERTURAS!$K$24="OK",CHOOSE(ABERTURAS!$N$24,ABERTURAS!$O$24,ABERTURAS!$O$24+0.42*$C$13,0.42*ABERTURAS!$O$24,$C$12+0.42*ABERTURAS!$O$24),0)+$AZ$8)/$AZ$7 -> 0.30543746 | CJ6: =(IF(ABERTURAS!$K$24="OK",ABERTURAS!$R$24+0.26*CHOOSE(ABERTURAS!$N$24,0,$C$13,ABERTURAS!$O$24,ABERTURAS!$O$24),0)+$AZ$9)/$AZ$7 -> 0.041677003 | CK6: =(IF(ABERTURAS!$K$25="OK",CHOOSE(ABERTURAS!$N$25,ABERTURAS!$O$25,ABERTURAS!$O$25+0.42*$C$13,0.42*ABERTURAS!$O$25,$C$12+0.42*ABERTURAS!$O$25),0)+$AZ$8)/$AZ$7 -> 0.30543746 | CL6: =(IF(ABERTURAS!$K$25="OK",ABERTURAS!$R$25+0.26*CHOOSE(ABERTURAS!$N$25,0,$C$13,ABERTURAS!$O$25,ABERTURAS!$O$25),0)+$AZ$9)/$AZ$7 -> 0.041677003 | CM6: =(IF(ABERTURAS!$K$26="OK",CHOOSE(ABERTURAS!$N$26,ABERTURAS!$O$26,ABERTURAS!$O$26+0.42*$C$13,0.42*ABERTURAS!$O$26,$C$12+0.42*ABERTURAS!$O$26),0)+$AZ$8)/$AZ$7 -> 0.30543746 | CN6: =(IF(ABERTURAS!$K$26="OK",ABERTURAS!$R$26+0.26*CHOOSE(ABERTURAS!$N$26,0,$C$13,ABERTURAS!$O$26,ABERTURAS!$O$26),0)+$AZ$9)/$AZ$7 -> 0.041677003
B7: Proyecto | C7: HANGAR NOSE-DOCK H5-H6 | E7: CAPTURA. Sólo para identificar la corrida. | F7: — | AA7: =$C$23*4/8 -> 8 | AB7: =IF($C$14="PLANO",$C$17,IF($C$14="DOS AGUAS",$C$17+($C$18-$C$17)*(1-ABS(2*($AA$7)/$C$23-1)),IF($C$14="UN AGUA",IF(N($C$25)=0,$C$18-($C$18-$C$17)*($AA$7)/$C$23,$C$17+($C$18-$C$17)*($AA$7)/$C$23),$C$17+4*($C$18-$C$17)*($AA$7)/$C$23*(1-($AA$7)/$C$23)))) -> 10.22 | AE7: =ABERTURAS!$D$51*6/8 -> 7.56 | AF7: =IF(ABERTURAS!$E$51="SÍ",$AB$9,ABERTURAS!$F$51) -> 10.62 | AG7: =($AE7+0.42*0+$AZ$8)/$AZ$7 -> 0.77430375 | AH7: =($AF7+0.26*0+$AZ$9)/$AZ$7 -> 0.7003225 | AI7: =ABERTURAS!$D$52*6/8 -> 7.56 | AJ7: =IF(ABERTURAS!$E$52="SÍ",$AB$9,ABERTURAS!$F$52) -> 9.82 | AK7: =($AI7+0.42*$C$13+$AZ$8)/$AZ$7 -> 1.1910738 | AL7: =($AJ7+0.26*$C$13+$AZ$9)/$AZ$7 -> 0.90870752 | AM7: =ABERTURAS!$D$53*6/8 -> 12 | AN7: =IF(ABERTURAS!$E$53="SÍ",$AB$9,ABERTURAS!$F$53) -> 10.02 | AO7: =(0+0.42*$AM7+$AZ$8)/$AZ$7 -> 0.61801498 | AP7: =($AN7+0.26*$AM7+$AZ$9)/$AZ$7 -> 0.85661126 | AQ7: =ABERTURAS!$D$54*6/8 -> 12 | AR7: =IF(ABERTURAS!$E$54="SÍ",$AB$9,ABERTURAS!$F$54) -> 10.02 | AS7: =($C$12+0.42*$AQ7+$AZ$8)/$AZ$7 -> 1.24317 | AT7: =($AR7+0.26*$AQ7+$AZ$9)/$AZ$7 -> 0.85661126 | AU7: =(IF($AC$3="X",$AA$7+0.42*0,0+0.42*$AA$7)+$AZ$8)/$AZ$7 -> 0.51382248 | AV7: =($AB$7+0.26*IF($AC$3="X",0,$AA$7)+$AZ$9)/$AZ$7 -> 0.80451501 | AW7: =(0.42*1.25*$C$13+$AZ$8)/$AZ$7 -> 0.8264 | AX7: =(0.26*1.25*$C$13+$AZ$9)/$AZ$7 -> 0.36417762 | AY7: s | AZ7: =MAX(($AZ$3+2*$AZ$5)/$AZ$6,$AZ$4+2*$AZ$5) -> 16.124 | BA7: =(IF(ABERTURAS!$K$7="OK",CHOOSE(ABERTURAS!$N$7,ABERTURAS!$O$7,ABERTURAS!$O$7+0.42*$C$13,0.42*ABERTURAS!$O$7,$C$12+0.42*ABERTURAS!$O$7),0)+$AZ$8)/$AZ$7 -> 0.34528489 | BB7: =(IF(ABERTURAS!$K$7="OK",ABERTURAS!$Q$7+0.26*CHOOSE(ABERTURAS!$N$7,0,$C$13,ABERTURAS!$O$7,ABERTURAS!$O$7),0)+$AZ$9)/$AZ$7 -> 0.041677003 | BC7: =(IF(ABERTURAS!$K$8="OK",CHOOSE(ABERTURAS!$N$8,ABERTURAS!$O$8,ABERTURAS!$O$8+0.42*$C$13,0.42*ABERTURAS!$O$8,$C$12+0.42*ABERTURAS!$O$8),0)+$AZ$8)/$AZ$7 -> 0.45967338 | BD7: =(IF(ABERTURAS!$K$8="OK",ABERTURAS!$Q$8+0.26*CHOOSE(ABERTURAS!$N$8,0,$C$13,ABERTURAS!$O$8,ABERTURAS!$O$8),0)+$AZ$9)/$AZ$7 -> 0.041677003 | BE7: =(IF(ABERTURAS!$K$9="OK",CHOOSE(ABERTURAS!$N$9,ABERTURAS!$O$9,ABERTURAS!$O$9+0.42*$C$13,0.42*ABERTURAS!$O$9,$C$12+0.42*ABERTURAS!$O$9),0)+$AZ$8)/$AZ$7 -> 0.72220749 | BF7: =(IF(ABERTURAS!$K$9="OK",ABERTURAS!$Q$9+0.26*CHOOSE(ABERTURAS!$N$9,0,$C$13,ABERTURAS!$O$9,ABERTURAS!$O$9),0)+$AZ$9)/$AZ$7 -> 0.2996775 | BG7: =(IF(ABERTURAS!$K$10="OK",CHOOSE(ABERTURAS!$N$10,ABERTURAS!$O$10,ABERTURAS!$O$10+0.42*$C$13,0.42*ABERTURAS!$O$10,$C$12+0.42*ABERTURAS!$O$10),0)+$AZ$8)/$AZ$7 -> 0.30543746 | BH7: =(IF(ABERTURAS!$K$10="OK",ABERTURAS!$Q$10+0.26*CHOOSE(ABERTURAS!$N$10,0,$C$13,ABERTURAS!$O$10,ABERTURAS!$O$10),0)+$AZ$9)/$AZ$7 -> 0.041677003 | BI7: =(IF(ABERTURAS!$K$11="OK",CHOOSE(ABERTURAS!$N$11,ABERTURAS!$O$11,ABERTURAS!$O$11+0.42*$C$13,0.42*ABERTURAS!$O$11,$C$12+0.42*ABERTURAS!$O$11),0)+$AZ$8)/$AZ$7 -> 0.30543746 | BJ7: =(IF(ABERTURAS!$K$11="OK",ABERTURAS!$Q$11+0.26*CHOOSE(ABERTURAS!$N$11,0,$C$13,ABERTURAS!$O$11,ABERTURAS!$O$11),0)+$AZ$9)/$AZ$7 -> 0.041677003 | BK7: =(IF(ABERTURAS!$K$12="OK",CHOOSE(ABERTURAS!$N$12,ABERTURAS!$O$12,ABERTURAS!$O$12+0.42*$C$13,0.42*ABERTURAS!$O$12,$C$12+0.42*ABERTURAS!$O$12),0)+$AZ$8)/$AZ$7 -> 0.30543746 | BL7: =(IF(ABERTURAS!$K$12="OK",ABERTURAS!$Q$12+0.26*CHOOSE(ABERTURAS!$N$12,0,$C$13,ABERTURAS!$O$12,ABERTURAS!$O$12),0)+$AZ$9)/$AZ$7 -> 0.041677003 | BM7: =(IF(ABERTURAS!$K$13="OK",CHOOSE(ABERTURAS!$N$13,ABERTURAS!$O$13,ABERTURAS!$O$13+0.42*$C$13,0.42*ABERTURAS!$O$13,$C$12+0.42*ABERTURAS!$O$13),0)+$AZ$8)/$AZ$7 -> 0.30543746 | BN7: =(IF(ABERTURAS!$K$13="OK",ABERTURAS!$Q$13+0.26*CHOOSE(ABERTURAS!$N$13,0,$C$13,ABERTURAS!$O$13,ABERTURAS!$O$13),0)+$AZ$9)/$AZ$7 -> 0.041677003 | BO7: =(IF(ABERTURAS!$K$14="OK",CHOOSE(ABERTURAS!$N$14,ABERTURAS!$O$14,ABERTURAS!$O$14+0.42*$C$13,0.42*ABERTURAS!$O$14,$C$12+0.42*ABERTURAS!$O$14),0)+$AZ$8)/$AZ$7 -> 0.30543746 | BP7: =(IF(ABERTURAS!$K$14="OK",ABERTURAS!$Q$14+0.26*CHOOSE(ABERTURAS!$N$14,0,$C$13,ABERTURAS!$O$14,ABERTURAS!$O$14),0)+$AZ$9)/$AZ$7 -> 0.041677003 | BQ7: =(IF(ABERTURAS!$K$15="OK",CHOOSE(ABERTURAS!$N$15,ABERTURAS!$O$15,ABERTURAS!$O$15+0.42*$C$13,0.42*ABERTURAS!$O$15,$C$12+0.42*ABERTURAS!$O$15),0)+$AZ$8)/$AZ$7 -> 0.30543746 | BR7: =(IF(ABERTURAS!$K$15="OK",ABERTURAS!$Q$15+0.26*CHOOSE(ABERTURAS!$N$15,0,$C$13,ABERTURAS!$O$15,ABERTURAS!$O$15),0)+$AZ$9)/$AZ$7 -> 0.041677003 | BS7: =(IF(ABERTURAS!$K$16="OK",CHOOSE(ABERTURAS!$N$16,ABERTURAS!$O$16,ABERTURAS!$O$16+0.42*$C$13,0.42*ABERTURAS!$O$16,$C$12+0.42*ABERTURAS!$O$16),0)+$AZ$8)/$AZ$7 -> 0.30543746 | BT7: =(IF(ABERTURAS!$K$16="OK",ABERTURAS!$Q$16+0.26*CHOOSE(ABERTURAS!$N$16,0,$C$13,ABERTURAS!$O$16,ABERTURAS!$O$16),0)+$AZ$9)/$AZ$7 -> 0.041677003 | BU7: =(IF(ABERTURAS!$K$17="OK",CHOOSE(ABERTURAS!$N$17,ABERTURAS!$O$17,ABERTURAS!$O$17+0.42*$C$13,0.42*ABERTURAS!$O$17,$C$12+0.42*ABERTURAS!$O$17),0)+$AZ$8)/$AZ$7 -> 0.30543746 | BV7: =(IF(ABERTURAS!$K$17="OK",ABERTURAS!$Q$17+0.26*CHOOSE(ABERTURAS!$N$17,0,$C$13,ABERTURAS!$O$17,ABERTURAS!$O$17),0)+$AZ$9)/$AZ$7 -> 0.041677003 | BW7: =(IF(ABERTURAS!$K$18="OK",CHOOSE(ABERTURAS!$N$18,ABERTURAS!$O$18,ABERTURAS!$O$18+0.42*$C$13,0.42*ABERTURAS!$O$18,$C$12+0.42*ABERTURAS!$O$18),0)+$AZ$8)/$AZ$7 -> 0.30543746 | BX7: =(IF(ABERTURAS!$K$18="OK",ABERTURAS!$Q$18+0.26*CHOOSE(ABERTURAS!$N$18,0,$C$13,ABERTURAS!$O$18,ABERTURAS!$O$18),0)+$AZ$9)/$AZ$7 -> 0.041677003 | BY7: =(IF(ABERTURAS!$K$19="OK",CHOOSE(ABERTURAS!$N$19,ABERTURAS!$O$19,ABERTURAS!$O$19+0.42*$C$13,0.42*ABERTURAS!$O$19,$C$12+0.42*ABERTURAS!$O$19),0)+$AZ$8)/$AZ$7 -> 0.30543746 | BZ7: =(IF(ABERTURAS!$K$19="OK",ABERTURAS!$Q$19+0.26*CHOOSE(ABERTURAS!$N$19,0,$C$13,ABERTURAS!$O$19,ABERTURAS!$O$19),0)+$AZ$9)/$AZ$7 -> 0.041677003 | CA7: =(IF(ABERTURAS!$K$20="OK",CHOOSE(ABERTURAS!$N$20,ABERTURAS!$O$20,ABERTURAS!$O$20+0.42*$C$13,0.42*ABERTURAS!$O$20,$C$12+0.42*ABERTURAS!$O$20),0)+$AZ$8)/$AZ$7 -> 0.30543746 | CB7: =(IF(ABERTURAS!$K$20="OK",ABERTURAS!$Q$20+0.26*CHOOSE(ABERTURAS!$N$20,0,$C$13,ABERTURAS!$O$20,ABERTURAS!$O$20),0)+$AZ$9)/$AZ$7 -> 0.041677003 | CC7: =(IF(ABERTURAS!$K$21="OK",CHOOSE(ABERTURAS!$N$21,ABERTURAS!$O$21,ABERTURAS!$O$21+0.42*$C$13,0.42*ABERTURAS!$O$21,$C$12+0.42*ABERTURAS!$O$21),0)+$AZ$8)/$AZ$7 -> 0.30543746 | CD7: =(IF(ABERTURAS!$K$21="OK",ABERTURAS!$Q$21+0.26*CHOOSE(ABERTURAS!$N$21,0,$C$13,ABERTURAS!$O$21,ABERTURAS!$O$21),0)+$AZ$9)/$AZ$7 -> 0.041677003 | CE7: =(IF(ABERTURAS!$K$22="OK",CHOOSE(ABERTURAS!$N$22,ABERTURAS!$O$22,ABERTURAS!$O$22+0.42*$C$13,0.42*ABERTURAS!$O$22,$C$12+0.42*ABERTURAS!$O$22),0)+$AZ$8)/$AZ$7 -> 0.30543746 | CF7: =(IF(ABERTURAS!$K$22="OK",ABERTURAS!$Q$22+0.26*CHOOSE(ABERTURAS!$N$22,0,$C$13,ABERTURAS!$O$22,ABERTURAS!$O$22),0)+$AZ$9)/$AZ$7 -> 0.041677003 | CG7: =(IF(ABERTURAS!$K$23="OK",CHOOSE(ABERTURAS!$N$23,ABERTURAS!$O$23,ABERTURAS!$O$23+0.42*$C$13,0.42*ABERTURAS!$O$23,$C$12+0.42*ABERTURAS!$O$23),0)+$AZ$8)/$AZ$7 -> 0.30543746 | CH7: =(IF(ABERTURAS!$K$23="OK",ABERTURAS!$Q$23+0.26*CHOOSE(ABERTURAS!$N$23,0,$C$13,ABERTURAS!$O$23,ABERTURAS!$O$23),0)+$AZ$9)/$AZ$7 -> 0.041677003 | CI7: =(IF(ABERTURAS!$K$24="OK",CHOOSE(ABERTURAS!$N$24,ABERTURAS!$O$24,ABERTURAS!$O$24+0.42*$C$13,0.42*ABERTURAS!$O$24,$C$12+0.42*ABERTURAS!$O$24),0)+$AZ$8)/$AZ$7 -> 0.30543746 | CJ7: =(IF(ABERTURAS!$K$24="OK",ABERTURAS!$Q$24+0.26*CHOOSE(ABERTURAS!$N$24,0,$C$13,ABERTURAS!$O$24,ABERTURAS!$O$24),0)+$AZ$9)/$AZ$7 -> 0.041677003 | CK7: =(IF(ABERTURAS!$K$25="OK",CHOOSE(ABERTURAS!$N$25,ABERTURAS!$O$25,ABERTURAS!$O$25+0.42*$C$13,0.42*ABERTURAS!$O$25,$C$12+0.42*ABERTURAS!$O$25),0)+$AZ$8)/$AZ$7 -> 0.30543746 | CL7: =(IF(ABERTURAS!$K$25="OK",ABERTURAS!$Q$25+0.26*CHOOSE(ABERTURAS!$N$25,0,$C$13,ABERTURAS!$O$25,ABERTURAS!$O$25),0)+$AZ$9)/$AZ$7 -> 0.041677003 | CM7: =(IF(ABERTURAS!$K$26="OK",CHOOSE(ABERTURAS!$N$26,ABERTURAS!$O$26,ABERTURAS!$O$26+0.42*$C$13,0.42*ABERTURAS!$O$26,$C$12+0.42*ABERTURAS!$O$26),0)+$AZ$8)/$AZ$7 -> 0.30543746 | CN7: =(IF(ABERTURAS!$K$26="OK",ABERTURAS!$Q$26+0.26*CHOOSE(ABERTURAS!$N$26,0,$C$13,ABERTURAS!$O$26,ABERTURAS!$O$26),0)+$AZ$9)/$AZ$7 -> 0.041677003
B8: Ubicación | C8: Departamento de LA PAZ, EL SALVADOR | E8: CAPTURA. | F8: — | AA8: =$C$23*5/8 -> 10 | AB8: =IF($C$14="PLANO",$C$17,IF($C$14="DOS AGUAS",$C$17+($C$18-$C$17)*(1-ABS(2*($AA$8)/$C$23-1)),IF($C$14="UN AGUA",IF(N($C$25)=0,$C$18-($C$18-$C$17)*($AA$8)/$C$23,$C$17+($C$18-$C$17)*($AA$8)/$C$23),$C$17+4*($C$18-$C$17)*($AA$8)/$C$23*(1-($AA$8)/$C$23)))) -> 10.12 | AE8: =ABERTURAS!$D$51*5/8 -> 6.3 | AF8: =IF(ABERTURAS!$E$51="SÍ",$AB$8,ABERTURAS!$F$51) -> 10.62 | AG8: =($AE8+0.42*0+$AZ$8)/$AZ$7 -> 0.69615936 | AH8: =($AF8+0.26*0+$AZ$9)/$AZ$7 -> 0.7003225 | AI8: =ABERTURAS!$D$52*5/8 -> 6.3 | AJ8: =IF(ABERTURAS!$E$52="SÍ",$AB$8,ABERTURAS!$F$52) -> 9.82 | AK8: =($AI8+0.42*$C$13+$AZ$8)/$AZ$7 -> 1.1129294 | AL8: =($AJ8+0.26*$C$13+$AZ$9)/$AZ$7 -> 0.90870752 | AM8: =ABERTURAS!$D$53*5/8 -> 10 | AN8: =IF(ABERTURAS!$E$53="SÍ",$AB$8,ABERTURAS!$F$53) -> 10.12 | AO8: =(0+0.42*$AM8+$AZ$8)/$AZ$7 -> 0.56591873 | AP8: =($AN8+0.26*$AM8+$AZ$9)/$AZ$7 -> 0.83056314 | AQ8: =ABERTURAS!$D$54*5/8 -> 10 | AR8: =IF(ABERTURAS!$E$54="SÍ",$AB$8,ABERTURAS!$F$54) -> 10.12 | AS8: =($C$12+0.42*$AQ8+$AZ$8)/$AZ$7 -> 1.1910738 | AT8: =($AR8+0.26*$AQ8+$AZ$9)/$AZ$7 -> 0.83056314 | AU8: =(IF($AC$3="X",$AA$7+0.42*IF($AC$3="X",$C$13,$C$12),IF($AC$3="X",$C$13,$C$12)+0.42*$AA$7)+$AZ$8)/$AZ$7 -> 1.1389775 | AV8: =($AB$7+0.26*IF($AC$3="X",IF($AC$3="X",$C$13,$C$12),$AA$7)+$AZ$9)/$AZ$7 -> 0.80451501 | AY8: offX | AZ8: =($AZ$6*$AZ$7-($AZ$3+2*$AZ$5))/2+$AZ$5 -> 4.9248736
AA9: =$C$23*6/8 -> 12 | AB9: =IF($C$14="PLANO",$C$17,IF($C$14="DOS AGUAS",$C$17+($C$18-$C$17)*(1-ABS(2*($AA$9)/$C$23-1)),IF($C$14="UN AGUA",IF(N($C$25)=0,$C$18-($C$18-$C$17)*($AA$9)/$C$23,$C$17+($C$18-$C$17)*($AA$9)/$C$23),$C$17+4*($C$18-$C$17)*($AA$9)/$C$23*(1-($AA$9)/$C$23)))) -> 10.02 | AE9: =ABERTURAS!$D$51*4/8 -> 5.04 | AF9: =IF(ABERTURAS!$E$51="SÍ",$AB$7,ABERTURAS!$F$51) -> 10.62 | AG9: =($AE9+0.42*0+$AZ$8)/$AZ$7 -> 0.61801498 | AH9: =($AF9+0.26*0+$AZ$9)/$AZ$7 -> 0.7003225 | AI9: =ABERTURAS!$D$52*4/8 -> 5.04 | AJ9: =IF(ABERTURAS!$E$52="SÍ",$AB$7,ABERTURAS!$F$52) -> 9.82 | AK9: =($AI9+0.42*$C$13+$AZ$8)/$AZ$7 -> 1.034785 | AL9: =($AJ9+0.26*$C$13+$AZ$9)/$AZ$7 -> 0.90870752 | AM9: =ABERTURAS!$D$53*4/8 -> 8 | AN9: =IF(ABERTURAS!$E$53="SÍ",$AB$7,ABERTURAS!$F$53) -> 10.22 | AO9: =(0+0.42*$AM9+$AZ$8)/$AZ$7 -> 0.51382248 | AP9: =($AN9+0.26*$AM9+$AZ$9)/$AZ$7 -> 0.80451501 | AQ9: =ABERTURAS!$D$54*4/8 -> 8 | AR9: =IF(ABERTURAS!$E$54="SÍ",$AB$7,ABERTURAS!$F$54) -> 10.22 | AS9: =($C$12+0.42*$AQ9+$AZ$8)/$AZ$7 -> 1.1389775 | AT9: =($AR9+0.26*$AQ9+$AZ$9)/$AZ$7 -> 0.80451501 | AU9: =(IF($AC$3="X",$AA$9+0.42*IF($AC$3="X",$C$13,$C$12),IF($AC$3="X",$C$13,$C$12)+0.42*$AA$9)+$AZ$8)/$AZ$7 -> 1.24317 | AV9: =($AB$9+0.26*IF($AC$3="X",IF($AC$3="X",$C$13,$C$12),$AA$9)+$AZ$9)/$AZ$7 -> 0.85661126 | AY9: offY | AZ9: =($AZ$7-($AZ$4+2*$AZ$5))/2+$AZ$5 -> 0.672
B10: 2. GEOMETRÍA DE LA NAVE | AA10: =$C$23*7/8 -> 14 | AB10: =IF($C$14="PLANO",$C$17,IF($C$14="DOS AGUAS",$C$17+($C$18-$C$17)*(1-ABS(2*($AA$10)/$C$23-1)),IF($C$14="UN AGUA",IF(N($C$25)=0,$C$18-($C$18-$C$17)*($AA$10)/$C$23,$C$17+($C$18-$C$17)*($AA$10)/$C$23),$C$17+4*($C$18-$C$17)*($AA$10)/$C$23*(1-($AA$10)/$C$23)))) -> 9.92 | AE10: =ABERTURAS!$D$51*3/8 -> 3.78 | AF10: =IF(ABERTURAS!$E$51="SÍ",$AB$6,ABERTURAS!$F$51) -> 10.62 | AG10: =($AE10+0.42*0+$AZ$8)/$AZ$7 -> 0.5398706 | AH10: =($AF10+0.26*0+$AZ$9)/$AZ$7 -> 0.7003225 | AI10: =ABERTURAS!$D$52*3/8 -> 3.78 | AJ10: =IF(ABERTURAS!$E$52="SÍ",$AB$6,ABERTURAS!$F$52) -> 9.82 | AK10: =($AI10+0.42*$C$13+$AZ$8)/$AZ$7 -> 0.95664064 | AL10: =($AJ10+0.26*$C$13+$AZ$9)/$AZ$7 -> 0.90870752 | AM10: =ABERTURAS!$D$53*3/8 -> 6 | AN10: =IF(ABERTURAS!$E$53="SÍ",$AB$6,ABERTURAS!$F$53) -> 10.32 | AO10: =(0+0.42*$AM10+$AZ$8)/$AZ$7 -> 0.46172622 | AP10: =($AN10+0.26*$AM10+$AZ$9)/$AZ$7 -> 0.77846688 | AQ10: =ABERTURAS!$D$54*3/8 -> 6 | AR10: =IF(ABERTURAS!$E$54="SÍ",$AB$6,ABERTURAS!$F$54) -> 10.32 | AS10: =($C$12+0.42*$AQ10+$AZ$8)/$AZ$7 -> 1.0868813 | AT10: =($AR10+0.26*$AQ10+$AZ$9)/$AZ$7 -> 0.77846688 | AU10: =(IF($AC$3="X",$AA$9+0.42*0,0+0.42*$AA$9)+$AZ$8)/$AZ$7 -> 0.61801498 | AV10: =($AB$9+0.26*IF($AC$3="X",0,$AA$9)+$AZ$9)/$AZ$7 -> 0.85661126
B11: Concepto | C11: Valor | D11: Unidad | E11: Cómo se calcula / de dónde sale | F11: Referencia | AA11: =$C$23*8/8 -> 16 | AB11: =IF($C$14="PLANO",$C$17,IF($C$14="DOS AGUAS",$C$17+($C$18-$C$17)*(1-ABS(2*($AA$11)/$C$23-1)),IF($C$14="UN AGUA",IF(N($C$25)=0,$C$18-($C$18-$C$17)*($AA$11)/$C$23,$C$17+($C$18-$C$17)*($AA$11)/$C$23),$C$17+4*($C$18-$C$17)*($AA$11)/$C$23*(1-($AA$11)/$C$23)))) -> 9.82 | AE11: =ABERTURAS!$D$51*2/8 -> 2.52 | AF11: =IF(ABERTURAS!$E$51="SÍ",$AB$5,ABERTURAS!$F$51) -> 10.62 | AG11: =($AE11+0.42*0+$AZ$8)/$AZ$7 -> 0.46172622 | AH11: =($AF11+0.26*0+$AZ$9)/$AZ$7 -> 0.7003225 | AI11: =ABERTURAS!$D$52*2/8 -> 2.52 | AJ11: =IF(ABERTURAS!$E$52="SÍ",$AB$5,ABERTURAS!$F$52) -> 9.82 | AK11: =($AI11+0.42*$C$13+$AZ$8)/$AZ$7 -> 0.87849625 | AL11: =($AJ11+0.26*$C$13+$AZ$9)/$AZ$7 -> 0.90870752 | AM11: =ABERTURAS!$D$53*2/8 -> 4 | AN11: =IF(ABERTURAS!$E$53="SÍ",$AB$5,ABERTURAS!$F$53) -> 10.42 | AO11: =(0+0.42*$AM11+$AZ$8)/$AZ$7 -> 0.40962997 | AP11: =($AN11+0.26*$AM11+$AZ$9)/$AZ$7 -> 0.75241875 | AQ11: =ABERTURAS!$D$54*2/8 -> 4 | AR11: =IF(ABERTURAS!$E$54="SÍ",$AB$5,ABERTURAS!$F$54) -> 10.42 | AS11: =($C$12+0.42*$AQ11+$AZ$8)/$AZ$7 -> 1.034785 | AT11: =($AR11+0.26*$AQ11+$AZ$9)/$AZ$7 -> 0.75241875 | AU11: =(IF($AC$3="X",$AA$11+0.42*0,0+0.42*$AA$11)+$AZ$8)/$AZ$7 -> 0.72220749 | AV11: =($AB$11+0.26*IF($AC$3="X",0,$AA$11)+$AZ$9)/$AZ$7 -> 0.90870752
B12: B — ancho en X (de Muro 3 a Muro 4) | C12: 10.08 | D12: m | E12: CAPTURA. EJEMPLO: NOSE DOCK, X de 0 a 10.08 m (claro de los marcos). | F12: Modelo STAAD / arquitectónico | AE12: =ABERTURAS!$D$51*1/8 -> 1.26 | AF12: =IF(ABERTURAS!$E$51="SÍ",$AB$4,ABERTURAS!$F$51) -> 10.62 | AG12: =($AE12+0.42*0+$AZ$8)/$AZ$7 -> 0.38358184 | AH12: =($AF12+0.26*0+$AZ$9)/$AZ$7 -> 0.7003225 | AI12: =ABERTURAS!$D$52*1/8 -> 1.26 | AJ12: =IF(ABERTURAS!$E$52="SÍ",$AB$4,ABERTURAS!$F$52) -> 9.82 | AK12: =($AI12+0.42*$C$13+$AZ$8)/$AZ$7 -> 0.80035187 | AL12: =($AJ12+0.26*$C$13+$AZ$9)/$AZ$7 -> 0.90870752 | AM12: =ABERTURAS!$D$53*1/8 -> 2 | AN12: =IF(ABERTURAS!$E$53="SÍ",$AB$4,ABERTURAS!$F$53) -> 10.52 | AO12: =(0+0.42*$AM12+$AZ$8)/$AZ$7 -> 0.35753371 | AP12: =($AN12+0.26*$AM12+$AZ$9)/$AZ$7 -> 0.72637063 | AQ12: =ABERTURAS!$D$54*1/8 -> 2 | AR12: =IF(ABERTURAS!$E$54="SÍ",$AB$4,ABERTURAS!$F$54) -> 10.52 | AS12: =($C$12+0.42*$AQ12+$AZ$8)/$AZ$7 -> 0.98268876 | AT12: =($AR12+0.26*$AQ12+$AZ$9)/$AZ$7 -> 0.72637063 | AU12: =(IF($AC$3="X",$AA$11+0.42*IF($AC$3="X",$C$13,$C$12),IF($AC$3="X",$C$13,$C$12)+0.42*$AA$11)+$AZ$8)/$AZ$7 -> 1.3473625 | AV12: =($AB$11+0.26*IF($AC$3="X",IF($AC$3="X",$C$13,$C$12),$AA$11)+$AZ$9)/$AZ$7 -> 0.90870752
B13: L — largo en Z (de Muro 1 a Muro 2) | C13: 16 | D13: m | E13: CAPTURA. EJEMPLO: NOSE DOCK, Z de 0 a 16.00 m. | F13: Modelo STAAD / arquitectónico | AE13: =ABERTURAS!$D$51*0/8 -> 0 | AF13: =IF(ABERTURAS!$E$51="SÍ",$AB$3,ABERTURAS!$F$51) -> 10.62 | AG13: =($AE13+0.42*0+$AZ$8)/$AZ$7 -> 0.30543746 | AH13: =($AF13+0.26*0+$AZ$9)/$AZ$7 -> 0.7003225 | AI13: =ABERTURAS!$D$52*0/8 -> 0 | AJ13: =IF(ABERTURAS!$E$52="SÍ",$AB$3,ABERTURAS!$F$52) -> 9.82 | AK13: =($AI13+0.42*$C$13+$AZ$8)/$AZ$7 -> 0.72220749 | AL13: =($AJ13+0.26*$C$13+$AZ$9)/$AZ$7 -> 0.90870752 | AM13: =ABERTURAS!$D$53*0/8 -> 0 | AN13: =IF(ABERTURAS!$E$53="SÍ",$AB$3,ABERTURAS!$F$53) -> 10.62 | AO13: =(0+0.42*$AM13+$AZ$8)/$AZ$7 -> 0.30543746 | AP13: =($AN13+0.26*$AM13+$AZ$9)/$AZ$7 -> 0.7003225 | AQ13: =ABERTURAS!$D$54*0/8 -> 0 | AR13: =IF(ABERTURAS!$E$54="SÍ",$AB$3,ABERTURAS!$F$54) -> 10.62 | AS13: =($C$12+0.42*$AQ13+$AZ$8)/$AZ$7 -> 0.93059251 | AT13: =($AR13+0.26*$AQ13+$AZ$9)/$AZ$7 -> 0.7003225
B14: Tipo de techo | C14: UN AGUA | D14: — | E14: SELECTOR: DOS AGUAS, UN AGUA, PLANO o CURVO. | F14: NTV 1997 · 4.3.1, pág. 5 · Tabla 4.2, pág. 6 | AE14: =0 -> 0 | AF14: =0 -> 0 | AG14: =($AE14+0.42*0+$AZ$8)/$AZ$7 -> 0.30543746 | AH14: =($AF14+0.26*0+$AZ$9)/$AZ$7 -> 0.041677003 | AI14: =0 -> 0 | AJ14: =0 -> 0 | AK14: =($AI14+0.42*$C$13+$AZ$8)/$AZ$7 -> 0.72220749 | AL14: =($AJ14+0.26*$C$13+$AZ$9)/$AZ$7 -> 0.2996775 | AM14: =0 -> 0 | AN14: =0 -> 0 | AO14: =(0+0.42*$AM14+$AZ$8)/$AZ$7 -> 0.30543746 | AP14: =($AN14+0.26*$AM14+$AZ$9)/$AZ$7 -> 0.041677003 | AQ14: =0 -> 0 | AR14: =0 -> 0 | AS14: =($C$12+0.42*$AQ14+$AZ$8)/$AZ$7 -> 0.93059251 | AT14: =($AR14+0.26*$AQ14+$AZ$9)/$AZ$7 -> 0.041677003
B15: El agua escurre hacia (sólo UN AGUA) | C15: MURO 2 (Z = L) | D15: — | E15: SELECTOR. El muro por donde baja el agua; el lado alto queda en el muro opuesto. Muro 3 = izquierda, Muro 4 = derecha, Muro 1 = atrás, Muro 2 = frente (como en la vista de STAAD). EJEMPLO: NOSE DOCK, alto en el eje 1 y bajo en el eje 4. | F15: Croquis / arquitectónico
B16: Cumbrera (o eje del arco) paralela a (DOS AGUAS y CURVO) | C16: L (EJE Z) | D16: — | E16: SELECTOR. L (EJE Z): cumbrera a lo largo, hastiales en Muros 1 y 2. B (EJE X): cumbrera de lado a lado, hastiales en Muros 3 y 4. | F16: Croquis / arquitectónico
B17: h_a — altura baja (alero, o lado bajo en UN AGUA) | C17: 9.82 | D17: m | E17: CAPTURA. Del piso al alero. EJEMPLO: NOSE DOCK, 9.82 m en el eje 4 (nodos 13 y 16). | F17: Modelo STAAD / arquitectónico
B18: h_c — altura alta (cumbrera, clave o lado alto) | C18: 10.62 | D18: m | E18: CAPTURA. Con techo PLANO no se usa. EJEMPLO: NOSE DOCK, 10.62 m en el eje 1 (nodos 20 y 21). | F18: Modelo STAAD / arquitectónico
B19: ¿El arco arranca desde el suelo? (sólo CURVO) | C19: NO | D19: — | E19: SELECTOR. Con SÍ la zona A1 de la Tabla 4.2 pasa a empuje 1.4r ≤ 0.9. | F19: NTV 1997 · Tabla 4.2, pág. 6
B20: Separación típica entre marcos | C20: 6.75 | D20: m | E20: CAPTURA. Sólo para la carga de un marco intermedio en 2D (PRESIONES §F). EJEMPLO: ejes 1-2 y 2-3 del NOSE DOCK. | F20: Modelo STAAD / arquitectónico
B21: H — altura máxima de la nave | C21: =IF($C$14="PLANO",$C$17,MAX($C$17,$C$18)) -> 10.62 | D21: m | E21: CALCULADA. | F21: —
B22: Eje de la pendiente del techo | C22: =IF($C$14="PLANO","—",IF($C$14="UN AGUA",IF(OR(LEFT($C$15,6)="MURO 1",LEFT($C$15,6)="MURO 2"),"Z","X"),IF(LEFT($C$16,1)="L","X","Z"))) -> Z | D22: — | E22: CALCULADA. Dirección en la que cambia la altura del techo (s va de 0 a S en ese eje). | F22: Croquis
B23: S — claro en el sentido de la pendiente | C23: =IF($C$22="Z",$C$13,$C$12) -> 16 | D23: m | E23: CALCULADA. | F23: —
B24: Lado alto del techo (UN AGUA) | C24: =IF($C$14<>"UN AGUA","—",CHOOSE(VALUE(MID($C$15,6,1)),"MURO 2","MURO 1","MURO 4","MURO 3")) -> MURO 1 | D24: — | E24: CALCULADA: el muro opuesto al que escurre el agua. | F24: Croquis
B25: s del lado alto (UN AGUA) | C25: =IF($C$14<>"UN AGUA","—",IF(OR($C$24="MURO 1",$C$24="MURO 3"),0,$C$23)) -> 0 | D25: m | E25: CALCULADA. 0 si el lado alto está en X = 0 o Z = 0; S si está en el otro extremo. | F25: —
B26: θ — inclinación del techo | C26: =IF($C$14="DOS AGUAS",DEGREES(ATAN(($C$18-$C$17)/($C$23/2))),IF($C$14="UN AGUA",DEGREES(ATAN(($C$18-$C$17)/$C$23)),0)) -> 2.8624052 | D26: ° | E26: CALCULADA. Decide el C_p del faldón de barlovento. | F26: NTV 1997 · 4.3.1, pág. 5
B27: Pendiente del techo | C27: =TAN(RADIANS($C$26)) -> 0.05 | D27: % | E27: CALCULADA. | F27: —
B28: Revisión de la geometría | C28: =IF(OR(N($C$12)<=0,N($C$13)<=0),"FALTA B o L",IF(AND(N($C$17)<=0,NOT(AND($C$14="CURVO",$C$19="SÍ"))),"FALTA h_a",IF(AND($C$14<>"PLANO",N($C$18)<=N($C$17)),"h_c debe ser mayor que h_a (salvo techo PLANO)",IF(AND($C$14="CURVO",PRESIONES!$C$17>0.6),"Techo curvo con r > 0.6: fuera de la Tabla 4.2","OK")))) -> OK | D28: — | E28: CALCULADA. Debe decir OK. | F28: —
B29: Croquis con tus datos (se actualiza solo): muros numerados como en ABERTURAS, PRESIONES y LINEAS; en rojo las aberturas. Proyección oblicua: X a la derecha, Y arriba y Z hacia el fondo del dibujo (el Muro 1, Z = 0, con puerta y cortina, se dibuja adelante; en la vista de STAAD queda atrás).
B52: 3. EXPOSICIÓN Y TIPO DE ESTRUCTURA
B53: Concepto | C53: Valor | D53: Unidad | E53: Cómo se calcula / de dónde sale | F53: Referencia
B54: Zona de exposición | C54: C | D54: — | E54: SELECTOR. A: muchos edificios altos alrededor; B: construcciones medianas o bajas, o árboles; C: terreno abierto (aeropuertos, campo, costa). EJEMPLO: C por estar en aeropuerto. | F54: NTV 1997 · Tabla 4.1, pág. 5
B55: K — factor de exposición | C55: =INDEX(TABLAS!$D$7:$D$9,MATCH($C$54,TABLAS!$B$7:$B$9,0)) -> 1.6 | D55: — | E55: CALCULADA de la Tabla 4.1. | F55: NTV 1997 · Tabla 4.1, pág. 5
B56: a — exponente de variación con la altura | C56: =INDEX(TABLAS!$E$7:$E$9,MATCH($C$54,TABLAS!$B$7:$B$9,0)) -> 7 | D56: — | E56: CALCULADA. C_z = 1 hasta 10 m y (z/10)^(2/a) arriba. | F56: NTV 1997 · 4.2 y Tabla 4.1, pág. 5
B57: P_o — presión básica de diseño | C57: 30 | D57: kg/m² | E57: FIJA por la norma (80 km/h a 10 m). | F57: NTV 1997 · 2.1, pág. 2 · 4.1, pág. 5
B58: T — periodo natural de la nave | C58: 0.579 | D58: s | E58: CAPTURA. Periodo del modo dominante de STAAD (R1.5: réplica del modelo con HSS16x8x5/16, T = 0.579 s en Z y 0.489 s en X); cámbialo por el de tu output. | F58: NTV 1997 · 3.1, pág. 3
B59: Esbeltez = H / dimensión menor en planta | C59: =$C$21/MIN($C$12,$C$13) -> 1.0535714 | D59: — | E59: CALCULADA. | F59: NTV 1997 · 2.1, pág. 2 · 3.1, pág. 3
B60: Tipo de estructura | C60: =IF(AND($C$59<=5,$C$58<=2),"TIPO 1","TIPO 2") -> TIPO 1 | D60: — | E60: CALCULADA. Tipo 1: esbeltez ≤ 5 y T ≤ 2 s. Tipo 2: presiones × 1.3 por ráfaga. El Tipo 3 (vórtices) no lo cubre esta hoja. | F60: NTV 1997 · 3.1, pág. 3 · 4.6.1, pág. 7
B61: FR — factor por ráfaga | C61: =IF($C$60="TIPO 2",1.3,1) -> 1 | D61: — | E61: CALCULADA. | F61: NTV 1997 · 4.6.1, pág. 7
B63: 4. CASOS DE VIENTO PARA STAAD
B64: Concepto | C64: Valor | D64: Unidad | E64: Cómo se calcula / de dónde sale | F64: Referencia
B65: Unidades del modelo STAAD | C65: CM KG | D65: — | E65: SELECTOR: CM KG (NOSE DOCK, Walmart), METER KG o METER KN. Las cargas salen en kg/cm, kg/m o kN/m. | F65: Encabezado del .STD (UNIT)
B66: Número del primer caso de viento | C66: 8 | D66: — | E66: CAPTURA. Los 8 casos quedan seguidos. EJEMPLO: en el NOSE DOCK R3 los vientos son LOAD 8 a 15. | F66: 001_NOSE_DOCK_H5_H6_R3.STD
B67: Factor de unidades de la carga lineal | C67: =IF($C$65="CM KG",0.01,IF($C$65="METER KG",1,0.00980665)) -> 0.01 | D67: — | E67: CALCULADA. kg/m × factor = unidades de STAAD. | F67: —
B68: Formato del número en STAAD | C68: =IF($C$65="METER KG","0.00","0.0000") -> 0.0000 | D68: — | E68: CALCULADA. | F68: —
B69: Número del primer caso B (sólo si hace falta) | C69: 101 | D69: — | E69: CAPTURA. Los casos B sólo existen con techo de 30° a 50° (±0.4) o curvo con 0.2 ≤ r ≤ 0.3 (+0.3). Usa números libres. | F69: NTV 1997 · 4.3.1, pág. 5 · Tabla 4.2, pág. 6
B71: Caso en STAAD | C71: Viento | D71: Puertas | E71: Título en STAAD (lo puedes cambiar) | F71: Qué es
B72: ="LOAD "&($C$66+0) -> LOAD 8 | C72: +X | D72: CERRADAS | E72: VIENTO X | F72: Operables cerradas; sólo cuentan las aberturas FIJAS. Viento sopla hacia +X: pega primero en el Muro 3 (X = 0).
B73: ="LOAD "&($C$66+1) -> LOAD 9 | C73: −X | D73: CERRADAS | E73: VIENTO -X | F73: Operables cerradas; sólo cuentan las aberturas FIJAS. Viento sopla hacia −X: pega primero en el Muro 4 (X = B).
B74: ="LOAD "&($C$66+2) -> LOAD 10 | C74: +Z | D74: CERRADAS | E74: VIENTO Z | F74: Operables cerradas; sólo cuentan las aberturas FIJAS. Viento sopla hacia +Z: pega primero en el Muro 1 (Z = 0).
B75: ="LOAD "&($C$66+3) -> LOAD 11 | C75: −Z | D75: CERRADAS | E75: VIENTO -Z | F75: Operables cerradas; sólo cuentan las aberturas FIJAS. Viento sopla hacia −Z: pega primero en el Muro 2 (Z = L).
B76: ="LOAD "&($C$66+4) -> LOAD 12 | C76: +X | D76: ABIERTAS (PA) | E76: VIENTO X PA | F76: Operables abiertas (puerta o cortina abierta en la tormenta). Viento sopla hacia +X: pega primero en el Muro 3 (X = 0).
B77: ="LOAD "&($C$66+5) -> LOAD 13 | C77: −X | D77: ABIERTAS (PA) | E77: VIENTO -X PA | F77: Operables abiertas (puerta o cortina abierta en la tormenta). Viento sopla hacia −X: pega primero en el Muro 4 (X = B).
B78: ="LOAD "&($C$66+6) -> LOAD 14 | C78: +Z | D78: ABIERTAS (PA) | E78: VIENTO Z PA | F78: Operables abiertas (puerta o cortina abierta en la tormenta). Viento sopla hacia +Z: pega primero en el Muro 1 (Z = 0).
B79: ="LOAD "&($C$66+7) -> LOAD 15 | C79: −Z | D79: ABIERTAS (PA) | E79: VIENTO -Z PA | F79: Operables abiertas (puerta o cortina abierta en la tormenta). Viento sopla hacia −Z: pega primero en el Muro 2 (Z = L).

Sheet ABERTURAS
B1: ABERTURAS POR MURO (POSICIÓN Y TAMAÑO) Y PRESIÓN INTERIOR
B2: Captura cada abertura donde está: portones, cortinas, puertas, ventanas, louvers o un muro que no se forra. Con eso la hoja dibuja los muros, saca el área abierta de cada escenario, decide la presión interior (NTV 4.4, pág. 7) y descuenta las aberturas de las cargas de LINEAS.
B3: CÓMO SE LLENA: un renglón por abertura. x = distancia horizontal desde la esquina con el Muro 3 (en Muros 1 y 2, igual a la X de STAAD) o desde la esquina con el Muro 1 (en Muros 3 y 4, igual a la Z de STAAD); y = altura del piso a la parte baja. FIJA = siempre abierta (vano sin cerrar, louver, muro sin forro). OPERABLE = puerta o cortina: cerrada en los casos normales y abierta en los casos PA. Deja en blanco lo que no uses.
B5: A. LISTA DE ABERTURAS | N5: auxiliares (no se tocan) | Y5: auxiliares de la elevación (no se tocan)
B6: # | C6: Descripción | D6: Muro | E6: Tipo | F6: x desde (m) | G6: y desde (m) | H6: Ancho (m) | I6: Alto (m) | J6: Área (m²) | K6: ¿Cabe en el muro? | L6: Nota / de dónde sale | N6: nº muro | O6: u₁ | P6: u₂ | Q6: v₁ | R6: v₂ | S6: tope en u₁ | T6: tope en u₂ | U6: abierta CERR | V6: abierta PA | W6: largo muro | Y6: hueco | Z6: =MAX(1.5,0.1*MAX(DATOS!$C$12,DATOS!$C$13)) -> 1.6 | AA6: desfase | AB6: =0 -> 0 | AC6: =$D$51+$Z$6 -> 11.68 | AD6: =$D$51+$D$52+2*$Z$6 -> 23.36 | AE6: =$D$51+$D$52+$D$53+3*$Z$6 -> 40.96
B7: 1 | C7: Puerta de servicio (muro de atrás) | D7: MURO 1 | E7: OPERABLE | F7: 0.6425 | G7: 0 | H7: 1.3014 | I7: 2.4 | J7: =IF($K7="OK",$H7*$I7,0) -> 3.12336 | K7: =IF($D7="","",IF(OR($F7="",$G7=""),"FALTA POSICIÓN",IF(OR(N($H7)<=0,N($I7)<=0),"FALTA TAMAÑO",IF($E7="","FALTA TIPO",IF(OR(N($F7)<0,N($G7)<0,N($F7)+N($H7)>$W7+0.001),"SE SALE A LO LARGO",IF(N($G7)+N($I7)>MIN($S7,$T7)+0.001,"SE SALE POR ARRIBA","OK")))))) -> OK | L7: Modelo R1.5: jambas en X = 64.25 y 194.39 cm, dintel a 240 cm | N7: =IF($D7="",0,VALUE(MID($D7,6,1))) -> 1 | O7: =IF($K7="OK",N($F7),0) -> 0.6425 | P7: =IF($K7="OK",N($F7)+N($H7),0) -> 1.9439 | Q7: =IF($K7="OK",N($G7),0) -> 0 | R7: =IF($K7="OK",N($G7)+N($I7),0) -> 2.4 | S7: =IF($N7=0,0,IF(INDEX($E$51:$E$54,$N7)="SÍ",IF(DATOS!$C$14="PLANO",DATOS!$C$17,IF(DATOS!$C$14="DOS AGUAS",DATOS!$C$17+(DATOS!$C$18-DATOS!$C$17)*(1-ABS(2*(N($F7))/DATOS!$C$23-1)),IF(DATOS!$C$14="UN AGUA",IF(N(DATOS!$C$25)=0,DATOS!$C$18-(DATOS!$C$18-DATOS!$C$17)*(N($F7))/DATOS!$C$23,DATOS!$C$17+(DATOS!$C$18-DATOS!$C$17)*(N($F7))/DATOS!$C$23),DATOS!$C$17+4*(DATOS!$C$18-DATOS!$C$17)*(N($F7))/DATOS!$C$23*(1-(N($F7))/DATOS!$C$23)))),INDEX($F$51:$F$54,$N7))) -> 10.62 | T7: =IF($N7=0,0,IF(INDEX($E$51:$E$54,$N7)="SÍ",IF(DATOS!$C$14="PLANO",DATOS!$C$17,IF(DATOS!$C$14="DOS AGUAS",DATOS!$C$17+(DATOS!$C$18-DATOS!$C$17)*(1-ABS(2*(N($F7)+N($H7))/DATOS!$C$23-1)),IF(DATOS!$C$14="UN AGUA",IF(N(DATOS!$C$25)=0,DATOS!$C$18-(DATOS!$C$18-DATOS!$C$17)*(N($F7)+N($H7))/DATOS!$C$23,DATOS!$C$17+(DATOS!$C$18-DATOS!$C$17)*(N($F7)+N($H7))/DATOS!$C$23),DATOS!$C$17+4*(DATOS!$C$18-DATOS!$C$17)*(N($F7)+N($H7))/DATOS!$C$23*(1-(N($F7)+N($H7))/DATOS!$C$23)))),INDEX($F$51:$F$54,$N7))) -> 10.62 | U7: =IF(AND($K7="OK",$E7="FIJA"),1,0) -> 0 | V7: =IF($K7="OK",1,0) -> 1 | W7: =IF($N7=0,0,INDEX($D$51:$D$54,$N7)) -> 10.08 | Y7: =($AB$6+DATOS!$AE$3+$DL$12)/$DL$11 -> 0.069503846 | Z7: =(DATOS!$AF$3+$DL$13)/$DL$11 -> 0.069503846 | AA7: =($AC$6+DATOS!$AI$3+$DL$12)/$DL$11 -> 0.7821135 | AB7: =(DATOS!$AJ$3+$DL$13)/$DL$11 -> 0.069503846 | AC7: =($AD$6+DATOS!$AM$3+$DL$12)/$DL$11 -> 1.4947232 | AD7: =(DATOS!$AN$3+$DL$13)/$DL$11 -> 0.069503846 | AE7: =($AE$6+DATOS!$AQ$3+$DL$12)/$DL$11 -> 2.5685185 | AF7: =(DATOS!$AR$3+$DL$13)/$DL$11 -> 0.069503846 | AH7: =(IF(AND($K$7="OK",$E$7="FIJA"),CHOOSE($N$7,$AB$6,$AC$6,$AD$6,$AE$6)+$O$7,0)+$DL$12)/$DL$11 -> 0.069503846 | AI7: =(IF(AND($K$7="OK",$E$7="FIJA"),$Q$7,0)+$DL$13)/$DL$11 -> 0.069503846 | AJ7: =(IF(AND($K$7="OK",$E$7="OPERABLE"),CHOOSE($N$7,$AB$6,$AC$6,$AD$6,$AE$6)+$O$7,0)+$DL$12)/$DL$11 -> 0.10870348 | AK7: =(IF(AND($K$7="OK",$E$7="OPERABLE"),$Q$7,0)+$DL$13)/$DL$11 -> 0.069503846 | AL7: =(IF(AND($K$8="OK",$E$8="FIJA"),CHOOSE($N$8,$AB$6,$AC$6,$AD$6,$AE$6)+$O$8,0)+$DL$12)/$DL$11 -> 0.069503846 | AM7: =(IF(AND($K$8="OK",$E$8="FIJA"),$Q$8,0)+$DL$13)/$DL$11 -> 0.069503846 | AN7: =(IF(AND($K$8="OK",$E$8="OPERABLE"),CHOOSE($N$8,$AB$6,$AC$6,$AD$6,$AE$6)+$O$8,0)+$DL$12)/$DL$11 -> 0.22123235 | AO7: =(IF(AND($K$8="OK",$E$8="OPERABLE"),$Q$8,0)+$DL$13)/$DL$11 -> 0.069503846 | AP7: =(IF(AND($K$9="OK",$E$9="FIJA"),CHOOSE($N$9,$AB$6,$AC$6,$AD$6,$AE$6)+$O$9,0)+$DL$12)/$DL$11 -> 0.7821135 | AQ7: =(IF(AND($K$9="OK",$E$9="FIJA"),$Q$9,0)+$DL$13)/$DL$11 -> 0.069503846 | AR7: =(IF(AND($K$9="OK",$E$9="OPERABLE"),CHOOSE($N$9,$AB$6,$AC$6,$AD$6,$AE$6)+$O$9,0)+$DL$12)/$DL$11 -> 0.069503846 | AS7: =(IF(AND($K$9="OK",$E$9="OPERABLE"),$Q$9,0)+$DL$13)/$DL$11 -> 0.069503846 | AT7: =(IF(AND($K$10="OK",$E$10="FIJA"),CHOOSE($N$10,$AB$6,$AC$6,$AD$6,$AE$6)+$O$10,0)+$DL$12)/$DL$11 -> 0.069503846 | AU7: =(IF(AND($K$10="OK",$E$10="FIJA"),$Q$10,0)+$DL$13)/$DL$11 -> 0.069503846 | AV7: =(IF(AND($K$10="OK",$E$10="OPERABLE"),CHOOSE($N$10,$AB$6,$AC$6,$AD$6,$AE$6)+$O$10,0)+$DL$12)/$DL$11 -> 0.069503846 | AW7: =(IF(AND($K$10="OK",$E$10="OPERABLE"),$Q$10,0)+$DL$13)/$DL$11 -> 0.069503846 | AX7: =(IF(AND($K$11="OK",$E$11="FIJA"),CHOOSE($N$11,$AB$6,$AC$6,$AD$6,$AE$6)+$O$11,0)+$DL$12)/$DL$11 -> 0.069503846 | AY7: =(IF(AND($K$11="OK",$E$11="FIJA"),$Q$11,0)+$DL$13)/$DL$11 -> 0.069503846 | AZ7: =(IF(AND($K$11="OK",$E$11="OPERABLE"),CHOOSE($N$11,$AB$6,$AC$6,$AD$6,$AE$6)+$O$11,0)+$DL$12)/$DL$11 -> 0.069503846 | BA7: =(IF(AND($K$11="OK",$E$11="OPERABLE"),$Q$11,0)+$DL$13)/$DL$11 -> 0.069503846 | BB7: =(IF(AND($K$12="OK",$E$12="FIJA"),CHOOSE($N$12,$AB$6,$AC$6,$AD$6,$AE$6)+$O$12,0)+$DL$12)/$DL$11 -> 0.069503846 | BC7: =(IF(AND($K$12="OK",$E$12="FIJA"),$Q$12,0)+$DL$13)/$DL$11 -> 0.069503846 | BD7: =(IF(AND($K$12="OK",$E$12="OPERABLE"),CHOOSE($N$12,$AB$6,$AC$6,$AD$6,$AE$6)+$O$12,0)+$DL$12)/$DL$11 -> 0.069503846 | BE7: =(IF(AND($K$12="OK",$E$12="OPERABLE"),$Q$12,0)+$DL$13)/$DL$11 -> 0.069503846 | BF7: =(IF(AND($K$13="OK",$E$13="FIJA"),CHOOSE($N$13,$AB$6,$AC$6,$AD$6,$AE$6)+$O$13,0)+$DL$12)/$DL$11 -> 0.069503846 | BG7: =(IF(AND($K$13="OK",$E$13="FIJA"),$Q$13,0)+$DL$13)/$DL$11 -> 0.069503846 | BH7: =(IF(AND($K$13="OK",$E$13="OPERABLE"),CHOOSE($N$13,$AB$6,$AC$6,$AD$6,$AE$6)+$O$13,0)+$DL$12)/$DL$11 -> 0.069503846 | BI7: =(IF(AND($K$13="OK",$E$13="OPERABLE"),$Q$13,0)+$DL$13)/$DL$11 -> 0.069503846 | BJ7: =(IF(AND($K$14="OK",$E$14="FIJA"),CHOOSE($N$14,$AB$6,$AC$6,$AD$6,$AE$6)+$O$14,0)+$DL$12)/$DL$11 -> 0.069503846 | BK7: =(IF(AND($K$14="OK",$E$14="FIJA"),$Q$14,0)+$DL$13)/$DL$11 -> 0.069503846 | BL7: =(IF(AND($K$14="OK",$E$14="OPERABLE"),CHOOSE($N$14,$AB$6,$AC$6,$AD$6,$AE$6)+$O$14,0)+$DL$12)/$DL$11 -> 0.069503846 | BM7: =(IF(AND($K$14="OK",$E$14="OPERABLE"),$Q$14,0)+$DL$13)/$DL$11 -> 0.069503846 | BN7: =(IF(AND($K$15="OK",$E$15="FIJA"),CHOOSE($N$15,$AB$6,$AC$6,$AD$6,$AE$6)+$O$15,0)+$DL$12)/$DL$11 -> 0.069503846 | BO7: =(IF(AND($K$15="OK",$E$15="FIJA"),$Q$15,0)+$DL$13)/$DL$11 -> 0.069503846 | BP7: =(IF(AND($K$15="OK",$E$15="OPERABLE"),CHOOSE($N$15,$AB$6,$AC$6,$AD$6,$AE$6)+$O$15,0)+$DL$12)/$DL$11 -> 0.069503846 | BQ7: =(IF(AND($K$15="OK",$E$15="OPERABLE"),$Q$15,0)+$DL$13)/$DL$11 -> 0.069503846 | BR7: =(IF(AND($K$16="OK",$E$16="FIJA"),CHOOSE($N$16,$AB$6,$AC$6,$AD$6,$AE$6)+$O$16,0)+$DL$12)/$DL$11 -> 0.069503846 | BS7: =(IF(AND($K$16="OK",$E$16="FIJA"),$Q$16,0)+$DL$13)/$DL$11 -> 0.069503846 | BT7: =(IF(AND($K$16="OK",$E$16="OPERABLE"),CHOOSE($N$16,$AB$6,$AC$6,$AD$6,$AE$6)+$O$16,0)+$DL$12)/$DL$11 -> 0.069503846 | BU7: =(IF(AND($K$16="OK",$E$16="OPERABLE"),$Q$16,0)+$DL$13)/$DL$11 -> 0.069503846 | BV7: =(IF(AND($K$17="OK",$E$17="FIJA"),CHOOSE($N$17,$AB$6,$AC$6,$AD$6,$AE$6)+$O$17,0)+$DL$12)/$DL$11 -> 0.069503846 | BW7: =(IF(AND($K$17="OK",$E$17="FIJA"),$Q$17,0)+$DL$13)/$DL$11 -> 0.069503846 | BX7: =(IF(AND($K$17="OK",$E$17="OPERABLE"),CHOOSE($N$17,$AB$6,$AC$6,$AD$6,$AE$6)+$O$17,0)+$DL$12)/$DL$11 -> 0.069503846 | BY7: =(IF(AND($K$17="OK",$E$17="OPERABLE"),$Q$17,0)+$DL$13)/$DL$11 -> 0.069503846 | BZ7: =(IF(AND($K$18="OK",$E$18="FIJA"),CHOOSE($N$18,$AB$6,$AC$6,$AD$6,$AE$6)+$O$18,0)+$DL$12)/$DL$11 -> 0.069503846 | CA7: =(IF(AND($K$18="OK",$E$18="FIJA"),$Q$18,0)+$DL$13)/$DL$11 -> 0.069503846 | CB7: =(IF(AND($K$18="OK",$E$18="OPERABLE"),CHOOSE($N$18,$AB$6,$AC$6,$AD$6,$AE$6)+$O$18,0)+$DL$12)/$DL$11 -> 0.069503846 | CC7: =(IF(AND($K$18="OK",$E$18="OPERABLE"),$Q$18,0)+$DL$13)/$DL$11 -> 0.069503846 | CD7: =(IF(AND($K$19="OK",$E$19="FIJA"),CHOOSE($N$19,$AB$6,$AC$6,$AD$6,$AE$6)+$O$19,0)+$DL$12)/$DL$11 -> 0.069503846 | CE7: =(IF(AND($K$19="OK",$E$19="FIJA"),$Q$19,0)+$DL$13)/$DL$11 -> 0.069503846 | CF7: =(IF(AND($K$19="OK",$E$19="OPERABLE"),CHOOSE($N$19,$AB$6,$AC$6,$AD$6,$AE$6)+$O$19,0)+$DL$12)/$DL$11 -> 0.069503846 | CG7: =(IF(AND($K$19="OK",$E$19="OPERABLE"),$Q$19,0)+$DL$13)/$DL$11 -> 0.069503846 | CH7: =(IF(AND($K$20="OK",$E$20="FIJA"),CHOOSE($N$20,$AB$6,$AC$6,$AD$6,$AE$6)+$O$20,0)+$DL$12)/$DL$11 -> 0.069503846 | CI7: =(IF(AND($K$20="OK",$E$20="FIJA"),$Q$20,0)+$DL$13)/$DL$11 -> 0.069503846 | CJ7: =(IF(AND($K$20="OK",$E$20="OPERABLE"),CHOOSE($N$20,$AB$6,$AC$6,$AD$6,$AE$6)+$O$20,0)+$DL$12)/$DL$11 -> 0.069503846 | CK7: =(IF(AND($K$20="OK",$E$20="OPERABLE"),$Q$20,0)+$DL$13)/$DL$11 -> 0.069503846 | CL7: =(IF(AND($K$21="OK",$E$21="FIJA"),CHOOSE($N$21,$AB$6,$AC$6,$AD$6,$AE$6)+$O$21,0)+$DL$12)/$DL$11 -> 0.069503846 | CM7: =(IF(AND($K$21="OK",$E$21="FIJA"),$Q$21,0)+$DL$13)/$DL$11 -> 0.069503846 | CN7: =(IF(AND($K$21="OK",$E$21="OPERABLE"),CHOOSE($N$21,$AB$6,$AC$6,$AD$6,$AE$6)+$O$21,0)+$DL$12)/$DL$11 -> 0.069503846 | CO7: =(IF(AND($K$21="OK",$E$21="OPERABLE"),$Q$21,0)+$DL$13)/$DL$11 -> 0.069503846 | CP7: =(IF(AND($K$22="OK",$E$22="FIJA"),CHOOSE($N$22,$AB$6,$AC$6,$AD$6,$AE$6)+$O$22,0)+$DL$12)/$DL$11 -> 0.069503846 | CQ7: =(IF(AND($K$22="OK",$E$22="FIJA"),$Q$22,0)+$DL$13)/$DL$11 -> 0.069503846 | CR7: =(IF(AND($K$22="OK",$E$22="OPERABLE"),CHOOSE($N$22,$AB$6,$AC$6,$AD$6,$AE$6)+$O$22,0)+$DL$12)/$DL$11 -> 0.069503846 | CS7: =(IF(AND($K$22="OK",$E$22="OPERABLE"),$Q$22,0)+$DL$13)/$DL$11 -> 0.069503846 | CT7: =(IF(AND($K$23="OK",$E$23="FIJA"),CHOOSE($N$23,$AB$6,$AC$6,$AD$6,$AE$6)+$O$23,0)+$DL$12)/$DL$11 -> 0.069503846 | CU7: =(IF(AND($K$23="OK",$E$23="FIJA"),$Q$23,0)+$DL$13)/$DL$11 -> 0.069503846 | CV7: =(IF(AND($K$23="OK",$E$23="OPERABLE"),CHOOSE($N$23,$AB$6,$AC$6,$AD$6,$AE$6)+$O$23,0)+$DL$12)/$DL$11 -> 0.069503846 | CW7: =(IF(AND($K$23="OK",$E$23="OPERABLE"),$Q$23,0)+$DL$13)/$DL$11 -> 0.069503846 | CX7: =(IF(AND($K$24="OK",$E$24="FIJA"),CHOOSE($N$24,$AB$6,$AC$6,$AD$6,$AE$6)+$O$24,0)+$DL$12)/$DL$11 -> 0.069503846 | CY7: =(IF(AND($K$24="OK",$E$24="FIJA"),$Q$24,0)+$DL$13)/$DL$11 -> 0.069503846 | CZ7: =(IF(AND($K$24="OK",$E$24="OPERABLE"),CHOOSE($N$24,$AB$6,$AC$6,$AD$6,$AE$6)+$O$24,0)+$DL$12)/$DL$11 -> 0.069503846 | DA7: =(IF(AND($K$24="OK",$E$24="OPERABLE"),$Q$24,0)+$DL$13)/$DL$11 -> 0.069503846 | DB7: =(IF(AND($K$25="OK",$E$25="FIJA"),CHOOSE($N$25,$AB$6,$AC$6,$AD$6,$AE$6)+$O$25,0)+$DL$12)/$DL$11 -> 0.069503846 | DC7: =(IF(AND($K$25="OK",$E$25="FIJA"),$Q$25,0)+$DL$13)/$DL$11 -> 0.069503846 | DD7: =(IF(AND($K$25="OK",$E$25="OPERABLE"),CHOOSE($N$25,$AB$6,$AC$6,$AD$6,$AE$6)+$O$25,0)+$DL$12)/$DL$11 -> 0.069503846 | DE7: =(IF(AND($K$25="OK",$E$25="OPERABLE"),$Q$25,0)+$DL$13)/$DL$11 -> 0.069503846 | DF7: =(IF(AND($K$26="OK",$E$26="FIJA"),CHOOSE($N$26,$AB$6,$AC$6,$AD$6,$AE$6)+$O$26,0)+$DL$12)/$DL$11 -> 0.069503846 | DG7: =(IF(AND($K$26="OK",$E$26="FIJA"),$Q$26,0)+$DL$13)/$DL$11 -> 0.069503846 | DH7: =(IF(AND($K$26="OK",$E$26="OPERABLE"),CHOOSE($N$26,$AB$6,$AC$6,$AD$6,$AE$6)+$O$26,0)+$DL$12)/$DL$11 -> 0.069503846 | DI7: =(IF(AND($K$26="OK",$E$26="OPERABLE"),$Q$26,0)+$DL$13)/$DL$11 -> 0.069503846 | DK7: ext x | DL7: =$AE$6+$D$54 -> 56.96
B8: 2 | C8: Vano del nose dock, cortina de oruga (muro de atrás) | D8: MURO 1 | E8: OPERABLE | F8: 2.4869 | G8: 0 | H8: 5.1016 | I8: 6.33 | J8: =IF($K8="OK",$H8*$I8,0) -> 32.293128 | K8: =IF($D8="","",IF(OR($F8="",$G8=""),"FALTA POSICIÓN",IF(OR(N($H8)<=0,N($I8)<=0),"FALTA TAMAÑO",IF($E8="","FALTA TIPO",IF(OR(N($F8)<0,N($G8)<0,N($F8)+N($H8)>$W8+0.001),"SE SALE A LO LARGO",IF(N($G8)+N($I8)>MIN($S8,$T8)+0.001,"SE SALE POR ARRIBA","OK")))))) -> OK | L8: Modelo R1.5: jambas en X = 248.69 y 758.85 cm, dintel a 633 cm | N8: =IF($D8="",0,VALUE(MID($D8,6,1))) -> 1 | O8: =IF($K8="OK",N($F8),0) -> 2.4869 | P8: =IF($K8="OK",N($F8)+N($H8),0) -> 7.5885 | Q8: =IF($K8="OK",N($G8),0) -> 0 | R8: =IF($K8="OK",N($G8)+N($I8),0) -> 6.33 | S8: =IF($N8=0,0,IF(INDEX($E$51:$E$54,$N8)="SÍ",IF(DATOS!$C$14="PLANO",DATOS!$C$17,IF(DATOS!$C$14="DOS AGUAS",DATOS!$C$17+(DATOS!$C$18-DATOS!$C$17)*(1-ABS(2*(N($F8))/DATOS!$C$23-1)),IF(DATOS!$C$14="UN AGUA",IF(N(DATOS!$C$25)=0,DATOS!$C$18-(DATOS!$C$18-DATOS!$C$17)*(N($F8))/DATOS!$C$23,DATOS!$C$17+(DATOS!$C$18-DATOS!$C$17)*(N($F8))/DATOS!$C$23),DATOS!$C$17+4*(DATOS!$C$18-DATOS!$C$17)*(N($F8))/DATOS!$C$23*(1-(N($F8))/DATOS!$C$23)))),INDEX($F$51:$F$54,$N8))) -> 10.62 | T8: =IF($N8=0,0,IF(INDEX($E$51:$E$54,$N8)="SÍ",IF(DATOS!$C$14="PLANO",DATOS!$C$17,IF(DATOS!$C$14="DOS AGUAS",DATOS!$C$17+(DATOS!$C$18-DATOS!$C$17)*(1-ABS(2*(N($F8)+N($H8))/DATOS!$C$23-1)),IF(DATOS!$C$14="UN AGUA",IF(N(DATOS!$C$25)=0,DATOS!$C$18-(DATOS!$C$18-DATOS!$C$17)*(N($F8)+N($H8))/DATOS!$C$23,DATOS!$C$17+(DATOS!$C$18-DATOS!$C$17)*(N($F8)+N($H8))/DATOS!$C$23),DATOS!$C$17+4*(DATOS!$C$18-DATOS!$C$17)*(N($F8)+N($H8))/DATOS!$C$23*(1-(N($F8)+N($H8))/DATOS!$C$23)))),INDEX($F$51:$F$54,$N8))) -> 10.62 | U8: =IF(AND($K8="OK",$E8="FIJA"),1,0) -> 0 | V8: =IF($K8="OK",1,0) -> 1 | W8: =IF($N8=0,0,INDEX($D$51:$D$54,$N8)) -> 10.08 | Y8: =($AB$6+DATOS!$AE$4+$DL$12)/$DL$11 -> 0.68449574 | Z8: =(DATOS!$AF$4+$DL$13)/$DL$11 -> 0.069503846 | AA8: =($AC$6+DATOS!$AI$4+$DL$12)/$DL$11 -> 1.3971054 | AB8: =(DATOS!$AJ$4+$DL$13)/$DL$11 -> 0.069503846 | AC8: =($AD$6+DATOS!$AM$4+$DL$12)/$DL$11 -> 2.4709008 | AD8: =(DATOS!$AN$4+$DL$13)/$DL$11 -> 0.069503846 | AE8: =($AE$6+DATOS!$AQ$4+$DL$12)/$DL$11 -> 3.5446962 | AF8: =(DATOS!$AR$4+$DL$13)/$DL$11 -> 0.069503846 | AH8: =(IF(AND($K$7="OK",$E$7="FIJA"),CHOOSE($N$7,$AB$6,$AC$6,$AD$6,$AE$6)+$P$7,0)+$DL$12)/$DL$11 -> 0.069503846 | AI8: =(IF(AND($K$7="OK",$E$7="FIJA"),$Q$7,0)+$DL$13)/$DL$11 -> 0.069503846 | AJ8: =(IF(AND($K$7="OK",$E$7="OPERABLE"),CHOOSE($N$7,$AB$6,$AC$6,$AD$6,$AE$6)+$P$7,0)+$DL$12)/$DL$11 -> 0.18810333 | AK8: =(IF(AND($K$7="OK",$E$7="OPERABLE"),$Q$7,0)+$DL$13)/$DL$11 -> 0.069503846 | AL8: =(IF(AND($K$8="OK",$E$8="FIJA"),CHOOSE($N$8,$AB$6,$AC$6,$AD$6,$AE$6)+$P$8,0)+$DL$12)/$DL$11 -> 0.069503846 | AM8: =(IF(AND($K$8="OK",$E$8="FIJA"),$Q$8,0)+$DL$13)/$DL$11 -> 0.069503846 | AN8: =(IF(AND($K$8="OK",$E$8="OPERABLE"),CHOOSE($N$8,$AB$6,$AC$6,$AD$6,$AE$6)+$P$8,0)+$DL$12)/$DL$11 -> 0.53248659 | AO8: =(IF(AND($K$8="OK",$E$8="OPERABLE"),$Q$8,0)+$DL$13)/$DL$11 -> 0.069503846 | AP8: =(IF(AND($K$9="OK",$E$9="FIJA"),CHOOSE($N$9,$AB$6,$AC$6,$AD$6,$AE$6)+$P$9,0)+$DL$12)/$DL$11 -> 1.3971054 | AQ8: =(IF(AND($K$9="OK",$E$9="FIJA"),$Q$9,0)+$DL$13)/$DL$11 -> 0.069503846 | AR8: =(IF(AND($K$9="OK",$E$9="OPERABLE"),CHOOSE($N$9,$AB$6,$AC$6,$AD$6,$AE$6)+$P$9,0)+$DL$12)/$DL$11 -> 0.069503846 | AS8: =(IF(AND($K$9="OK",$E$9="OPERABLE"),$Q$9,0)+$DL$13)/$DL$11 -> 0.069503846 | AT8: =(IF(AND($K$10="OK",$E$10="FIJA"),CHOOSE($N$10,$AB$6,$AC$6,$AD$6,$AE$6)+$P$10,0)+$DL$12)/$DL$11 -> 0.069503846 | AU8: =(IF(AND($K$10="OK",$E$10="FIJA"),$Q$10,0)+$DL$13)/$DL$11 -> 0.069503846 | AV8: =(IF(AND($K$10="OK",$E$10="OPERABLE"),CHOOSE($N$10,$AB$6,$AC$6,$AD$6,$AE$6)+$P$10,0)+$DL$12)/$DL$11 -> 0.069503846 | AW8: =(IF(AND($K$10="OK",$E$10="OPERABLE"),$Q$10,0)+$DL$13)/$DL$11 -> 0.069503846 | AX8: =(IF(AND($K$11="OK",$E$11="FIJA"),CHOOSE($N$11,$AB$6,$AC$6,$AD$6,$AE$6)+$P$11,0)+$DL$12)/$DL$11 -> 0.069503846 | AY8: =(IF(AND($K$11="OK",$E$11="FIJA"),$Q$11,0)+$DL$13)/$DL$11 -> 0.069503846 | AZ8: =(IF(AND($K$11="OK",$E$11="OPERABLE"),CHOOSE($N$11,$AB$6,$AC$6,$AD$6,$AE$6)+$P$11,0)+$DL$12)/$DL$11 -> 0.069503846 | BA8: =(IF(AND($K$11="OK",$E$11="OPERABLE"),$Q$11,0)+$DL$13)/$DL$11 -> 0.069503846 | BB8: =(IF(AND($K$12="OK",$E$12="FIJA"),CHOOSE($N$12,$AB$6,$AC$6,$AD$6,$AE$6)+$P$12,0)+$DL$12)/$DL$11 -> 0.069503846 | BC8: =(IF(AND($K$12="OK",$E$12="FIJA"),$Q$12,0)+$DL$13)/$DL$11 -> 0.069503846 | BD8: =(IF(AND($K$12="OK",$E$12="OPERABLE"),CHOOSE($N$12,$AB$6,$AC$6,$AD$6,$AE$6)+$P$12,0)+$DL$12)/$DL$11 -> 0.069503846 | BE8: =(IF(AND($K$12="OK",$E$12="OPERABLE"),$Q$12,0)+$DL$13)/$DL$11 -> 0.069503846 | BF8: =(IF(AND($K$13="OK",$E$13="FIJA"),CHOOSE($N$13,$AB$6,$AC$6,$AD$6,$AE$6)+$P$13,0)+$DL$12)/$DL$11 -> 0.069503846 | BG8: =(IF(AND($K$13="OK",$E$13="FIJA"),$Q$13,0)+$DL$13)/$DL$11 -> 0.069503846 | BH8: =(IF(AND($K$13="OK",$E$13="OPERABLE"),CHOOSE($N$13,$AB$6,$AC$6,$AD$6,$AE$6)+$P$13,0)+$DL$12)/$DL$11 -> 0.069503846 | BI8: =(IF(AND($K$13="OK",$E$13="OPERABLE"),$Q$13,0)+$DL$13)/$DL$11 -> 0.069503846 | BJ8: =(IF(AND($K$14="OK",$E$14="FIJA"),CHOOSE($N$14,$AB$6,$AC$6,$AD$6,$AE$6)+$P$14,0)+$DL$12)/$DL$11 -> 0.069503846 | BK8: =(IF(AND($K$14="OK",$E$14="FIJA"),$Q$14,0)+$DL$13)/$DL$11 -> 0.069503846 | BL8: =(IF(AND($K$14="OK",$E$14="OPERABLE"),CHOOSE($N$14,$AB$6,$AC$6,$AD$6,$AE$6)+$P$14,0)+$DL$12)/$DL$11 -> 0.069503846 | BM8: =(IF(AND($K$14="OK",$E$14="OPERABLE"),$Q$14,0)+$DL$13)/$DL$11 -> 0.069503846 | BN8: =(IF(AND($K$15="OK",$E$15="FIJA"),CHOOSE($N$15,$AB$6,$AC$6,$AD$6,$AE$6)+$P$15,0)+$DL$12)/$DL$11 -> 0.069503846 | BO8: =(IF(AND($K$15="OK",$E$15="FIJA"),$Q$15,0)+$DL$13)/$DL$11 -> 0.069503846 | BP8: =(IF(AND($K$15="OK",$E$15="OPERABLE"),CHOOSE($N$15,$AB$6,$AC$6,$AD$6,$AE$6)+$P$15,0)+$DL$12)/$DL$11 -> 0.069503846 | BQ8: =(IF(AND($K$15="OK",$E$15="OPERABLE"),$Q$15,0)+$DL$13)/$DL$11 -> 0.069503846 | BR8: =(IF(AND($K$16="OK",$E$16="FIJA"),CHOOSE($N$16,$AB$6,$AC$6,$AD$6,$AE$6)+$P$16,0)+$DL$12)/$DL$11 -> 0.069503846 | BS8: =(IF(AND($K$16="OK",$E$16="FIJA"),$Q$16,0)+$DL$13)/$DL$11 -> 0.069503846 | BT8: =(IF(AND($K$16="OK",$E$16="OPERABLE"),CHOOSE($N$16,$AB$6,$AC$6,$AD$6,$AE$6)+$P$16,0)+$DL$12)/$DL$11 -> 0.069503846 | BU8: =(IF(AND($K$16="OK",$E$16="OPERABLE"),$Q$16,0)+$DL$13)/$DL$11 -> 0.069503846 | BV8: =(IF(AND($K$17="OK",$E$17="FIJA"),CHOOSE($N$17,$AB$6,$AC$6,$AD$6,$AE$6)+$P$17,0)+$DL$12)/$DL$11 -> 0.069503846 | BW8: =(IF(AND($K$17="OK",$E$17="FIJA"),$Q$17,0)+$DL$13)/$DL$11 -> 0.069503846 | BX8: =(IF(AND($K$17="OK",$E$17="OPERABLE"),CHOOSE($N$17,$AB$6,$AC$6,$AD$6,$AE$6)+$P$17,0)+$DL$12)/$DL$11 -> 0.069503846 | BY8: =(IF(AND($K$17="OK",$E$17="OPERABLE"),$Q$17,0)+$DL$13)/$DL$11 -> 0.069503846 | BZ8: =(IF(AND($K$18="OK",$E$18="FIJA"),CHOOSE($N$18,$AB$6,$AC$6,$AD$6,$AE$6)+$P$18,0)+$DL$12)/$DL$11 -> 0.069503846 | CA8: =(IF(AND($K$18="OK",$E$18="FIJA"),$Q$18,0)+$DL$13)/$DL$11 -> 0.069503846 | CB8: =(IF(AND($K$18="OK",$E$18="OPERABLE"),CHOOSE($N$18,$AB$6,$AC$6,$AD$6,$AE$6)+$P$18,0)+$DL$12)/$DL$11 -> 0.069503846 | CC8: =(IF(AND($K$18="OK",$E$18="OPERABLE"),$Q$18,0)+$DL$13)/$DL$11 -> 0.069503846 | CD8: =(IF(AND($K$19="OK",$E$19="FIJA"),CHOOSE($N$19,$AB$6,$AC$6,$AD$6,$AE$6)+$P$19,0)+$DL$12)/$DL$11 -> 0.069503846 | CE8: =(IF(AND($K$19="OK",$E$19="FIJA"),$Q$19,0)+$DL$13)/$DL$11 -> 0.069503846 | CF8: =(IF(AND($K$19="OK",$E$19="OPERABLE"),CHOOSE($N$19,$AB$6,$AC$6,$AD$6,$AE$6)+$P$19,0)+$DL$12)/$DL$11 -> 0.069503846 | CG8: =(IF(AND($K$19="OK",$E$19="OPERABLE"),$Q$19,0)+$DL$13)/$DL$11 -> 0.069503846 | CH8: =(IF(AND($K$20="OK",$E$20="FIJA"),CHOOSE($N$20,$AB$6,$AC$6,$AD$6,$AE$6)+$P$20,0)+$DL$12)/$DL$11 -> 0.069503846 | CI8: =(IF(AND($K$20="OK",$E$20="FIJA"),$Q$20,0)+$DL$13)/$DL$11 -> 0.069503846 | CJ8: =(IF(AND($K$20="OK",$E$20="OPERABLE"),CHOOSE($N$20,$AB$6,$AC$6,$AD$6,$AE$6)+$P$20,0)+$DL$12)/$DL$11 -> 0.069503846 | CK8: =(IF(AND($K$20="OK",$E$20="OPERABLE"),$Q$20,0)+$DL$13)/$DL$11 -> 0.069503846 | CL8: =(IF(AND($K$21="OK",$E$21="FIJA"),CHOOSE($N$21,$AB$6,$AC$6,$AD$6,$AE$6)+$P$21,0)+$DL$12)/$DL$11 -> 0.069503846 | CM8: =(IF(AND($K$21="OK",$E$21="FIJA"),$Q$21,0)+$DL$13)/$DL$11 -> 0.069503846 | CN8: =(IF(AND($K$21="OK",$E$21="OPERABLE"),CHOOSE($N$21,$AB$6,$AC$6,$AD$6,$AE$6)+$P$21,0)+$DL$12)/$DL$11 -> 0.069503846 | CO8: =(IF(AND($K$21="OK",$E$21="OPERABLE"),$Q$21,0)+$DL$13)/$DL$11 -> 0.069503846 | CP8: =(IF(AND($K$22="OK",$E$22="FIJA"),CHOOSE($N$22,$AB$6,$AC$6,$AD$6,$AE$6)+$P$22,0)+$DL$12)/$DL$11 -> 0.069503846 | CQ8: =(IF(AND($K$22="OK",$E$22="FIJA"),$Q$22,0)+$DL$13)/$DL$11 -> 0.069503846 | CR8: =(IF(AND($K$22="OK",$E$22="OPERABLE"),CHOOSE($N$22,$AB$6,$AC$6,$AD$6,$AE$6)+$P$22,0)+$DL$12)/$DL$11 -> 0.069503846 | CS8: =(IF(AND($K$22="OK",$E$22="OPERABLE"),$Q$22,0)+$DL$13)/$DL$11 -> 0.069503846 | CT8: =(IF(AND($K$23="OK",$E$23="FIJA"),CHOOSE($N$23,$AB$6,$AC$6,$AD$6,$AE$6)+$P$23,0)+$DL$12)/$DL$11 -> 0.069503846 | CU8: =(IF(AND($K$23="OK",$E$23="FIJA"),$Q$23,0)+$DL$13)/$DL$11 -> 0.069503846 | CV8: =(IF(AND($K$23="OK",$E$23="OPERABLE"),CHOOSE($N$23,$AB$6,$AC$6,$AD$6,$AE$6)+$P$23,0)+$DL$12)/$DL$11 -> 0.069503846 | CW8: =(IF(AND($K$23="OK",$E$23="OPERABLE"),$Q$23,0)+$DL$13)/$DL$11 -> 0.069503846 | CX8: =(IF(AND($K$24="OK",$E$24="FIJA"),CHOOSE($N$24,$AB$6,$AC$6,$AD$6,$AE$6)+$P$24,0)+$DL$12)/$DL$11 -> 0.069503846 | CY8: =(IF(AND($K$24="OK",$E$24="FIJA"),$Q$24,0)+$DL$13)/$DL$11 -> 0.069503846 | CZ8: =(IF(AND($K$24="OK",$E$24="OPERABLE"),CHOOSE($N$24,$AB$6,$AC$6,$AD$6,$AE$6)+$P$24,0)+$DL$12)/$DL$11 -> 0.069503846 | DA8: =(IF(AND($K$24="OK",$E$24="OPERABLE"),$Q$24,0)+$DL$13)/$DL$11 -> 0.069503846 | DB8: =(IF(AND($K$25="OK",$E$25="FIJA"),CHOOSE($N$25,$AB$6,$AC$6,$AD$6,$AE$6)+$P$25,0)+$DL$12)/$DL$11 -> 0.069503846 | DC8: =(IF(AND($K$25="OK",$E$25="FIJA"),$Q$25,0)+$DL$13)/$DL$11 -> 0.069503846 | DD8: =(IF(AND($K$25="OK",$E$25="OPERABLE"),CHOOSE($N$25,$AB$6,$AC$6,$AD$6,$AE$6)+$P$25,0)+$DL$12)/$DL$11 -> 0.069503846 | DE8: =(IF(AND($K$25="OK",$E$25="OPERABLE"),$Q$25,0)+$DL$13)/$DL$11 -> 0.069503846 | DF8: =(IF(AND($K$26="OK",$E$26="FIJA"),CHOOSE($N$26,$AB$6,$AC$6,$AD$6,$AE$6)+$P$26,0)+$DL$12)/$DL$11 -> 0.069503846 | DG8: =(IF(AND($K$26="OK",$E$26="FIJA"),$Q$26,0)+$DL$13)/$DL$11 -> 0.069503846 | DH8: =(IF(AND($K$26="OK",$E$26="OPERABLE"),CHOOSE($N$26,$AB$6,$AC$6,$AD$6,$AE$6)+$P$26,0)+$DL$12)/$DL$11 -> 0.069503846 | DI8: =(IF(AND($K$26="OK",$E$26="OPERABLE"),$Q$26,0)+$DL$13)/$DL$11 -> 0.069503846 | DK8: ext y | DL8: =DATOS!$C$21*1.22 -> 12.9564
B9: 3 | C9: Frente abierto (Z = L): en STAAD no hay muro ni largueros | D9: MURO 2 | E9: FIJA | F9: 0 | G9: 0 | H9: 10.08 | I9: 9.82 | J9: =IF($K9="OK",$H9*$I9,0) -> 98.9856 | K9: =IF($D9="","",IF(OR($F9="",$G9=""),"FALTA POSICIÓN",IF(OR(N($H9)<=0,N($I9)<=0),"FALTA TAMAÑO",IF($E9="","FALTA TIPO",IF(OR(N($F9)<0,N($G9)<0,N($F9)+N($H9)>$W9+0.001),"SE SALE A LO LARGO",IF(N($G9)+N($I9)>MIN($S9,$T9)+0.001,"SE SALE POR ARRIBA","OK")))))) -> OK | L9: Modelo R1.5: el eje 4 (Z = 16 m) no tiene muro ni largueros; se toma como frente abierto (NTV 4.4, pág. 7) | N9: =IF($D9="",0,VALUE(MID($D9,6,1))) -> 2 | O9: =IF($K9="OK",N($F9),0) -> 0 | P9: =IF($K9="OK",N($F9)+N($H9),0) -> 10.08 | Q9: =IF($K9="OK",N($G9),0) -> 0 | R9: =IF($K9="OK",N($G9)+N($I9),0) -> 9.82 | S9: =IF($N9=0,0,IF(INDEX($E$51:$E$54,$N9)="SÍ",IF(DATOS!$C$14="PLANO",DATOS!$C$17,IF(DATOS!$C$14="DOS AGUAS",DATOS!$C$17+(DATOS!$C$18-DATOS!$C$17)*(1-ABS(2*(N($F9))/DATOS!$C$23-1)),IF(DATOS!$C$14="UN AGUA",IF(N(DATOS!$C$25)=0,DATOS!$C$18-(DATOS!$C$18-DATOS!$C$17)*(N($F9))/DATOS!$C$23,DATOS!$C$17+(DATOS!$C$18-DATOS!$C$17)*(N($F9))/DATOS!$C$23),DATOS!$C$17+4*(DATOS!$C$18-DATOS!$C$17)*(N($F9))/DATOS!$C$23*(1-(N($F9))/DATOS!$C$23)))),INDEX($F$51:$F$54,$N9))) -> 9.82 | T9: =IF($N9=0,0,IF(INDEX($E$51:$E$54,$N9)="SÍ",IF(DATOS!$C$14="PLANO",DATOS!$C$17,IF(DATOS!$C$14="DOS AGUAS",DATOS!$C$17+(DATOS!$C$18-DATOS!$C$17)*(1-ABS(2*(N($F9)+N($H9))/DATOS!$C$23-1)),IF(DATOS!$C$14="UN AGUA",IF(N(DATOS!$C$25)=0,DATOS!$C$18-(DATOS!$C$18-DATOS!$C$17)*(N($F9)+N($H9))/DATOS!$C$23,DATOS!$C$17+(DATOS!$C$18-DATOS!$C$17)*(N($F9)+N($H9))/DATOS!$C$23),DATOS!$C$17+4*(DATOS!$C$18-DATOS!$C$17)*(N($F9)+N($H9))/DATOS!$C$23*(1-(N($F9)+N($H9))/DATOS!$C$23)))),INDEX($F$51:$F$54,$N9))) -> 9.82 | U9: =IF(AND($K9="OK",$E9="FIJA"),1,0) -> 1 | V9: =IF($K9="OK",1,0) -> 1 | W9: =IF($N9=0,0,INDEX($D$51:$D$54,$N9)) -> 10.08 | Y9: =($AB$6+DATOS!$AE$5+$DL$12)/$DL$11 -> 0.68449574 | Z9: =(DATOS!$AF$5+$DL$13)/$DL$11 -> 0.71744174 | AA9: =($AC$6+DATOS!$AI$5+$DL$12)/$DL$11 -> 1.3971054 | AB9: =(DATOS!$AJ$5+$DL$13)/$DL$11 -> 0.66863286 | AC9: =($AD$6+DATOS!$AM$5+$DL$12)/$DL$11 -> 2.4709008 | AD9: =(DATOS!$AN$5+$DL$13)/$DL$11 -> 0.66863286 | AE9: =($AE$6+DATOS!$AQ$5+$DL$12)/$DL$11 -> 3.5446962 | AF9: =(DATOS!$AR$5+$DL$13)/$DL$11 -> 0.66863286 | AH9: =(IF(AND($K$7="OK",$E$7="FIJA"),CHOOSE($N$7,$AB$6,$AC$6,$AD$6,$AE$6)+$P$7,0)+$DL$12)/$DL$11 -> 0.069503846 | AI9: =(IF(AND($K$7="OK",$E$7="FIJA"),$R$7,0)+$DL$13)/$DL$11 -> 0.069503846 | AJ9: =(IF(AND($K$7="OK",$E$7="OPERABLE"),CHOOSE($N$7,$AB$6,$AC$6,$AD$6,$AE$6)+$P$7,0)+$DL$12)/$DL$11 -> 0.18810333 | AK9: =(IF(AND($K$7="OK",$E$7="OPERABLE"),$R$7,0)+$DL$13)/$DL$11 -> 0.21593049 | AL9: =(IF(AND($K$8="OK",$E$8="FIJA"),CHOOSE($N$8,$AB$6,$AC$6,$AD$6,$AE$6)+$P$8,0)+$DL$12)/$DL$11 -> 0.069503846 | AM9: =(IF(AND($K$8="OK",$E$8="FIJA"),$R$8,0)+$DL$13)/$DL$11 -> 0.069503846 | AN9: =(IF(AND($K$8="OK",$E$8="OPERABLE"),CHOOSE($N$8,$AB$6,$AC$6,$AD$6,$AE$6)+$P$8,0)+$DL$12)/$DL$11 -> 0.53248659 | AO9: =(IF(AND($K$8="OK",$E$8="OPERABLE"),$R$8,0)+$DL$13)/$DL$11 -> 0.45570411 | AP9: =(IF(AND($K$9="OK",$E$9="FIJA"),CHOOSE($N$9,$AB$6,$AC$6,$AD$6,$AE$6)+$P$9,0)+$DL$12)/$DL$11 -> 1.3971054 | AQ9: =(IF(AND($K$9="OK",$E$9="FIJA"),$R$9,0)+$DL$13)/$DL$11 -> 0.66863286 | AR9: =(IF(AND($K$9="OK",$E$9="OPERABLE"),CHOOSE($N$9,$AB$6,$AC$6,$AD$6,$AE$6)+$P$9,0)+$DL$12)/$DL$11 -> 0.069503846 | AS9: =(IF(AND($K$9="OK",$E$9="OPERABLE"),$R$9,0)+$DL$13)/$DL$11 -> 0.069503846 | AT9: =(IF(AND($K$10="OK",$E$10="FIJA"),CHOOSE($N$10,$AB$6,$AC$6,$AD$6,$AE$6)+$P$10,0)+$DL$12)/$DL$11 -> 0.069503846 | AU9: =(IF(AND($K$10="OK",$E$10="FIJA"),$R$10,0)+$DL$13)/$DL$11 -> 0.069503846 | AV9: =(IF(AND($K$10="OK",$E$10="OPERABLE"),CHOOSE($N$10,$AB$6,$AC$6,$AD$6,$AE$6)+$P$10,0)+$DL$12)/$DL$11 -> 0.069503846 | AW9: =(IF(AND($K$10="OK",$E$10="OPERABLE"),$R$10,0)+$DL$13)/$DL$11 -> 0.069503846 | AX9: =(IF(AND($K$11="OK",$E$11="FIJA"),CHOOSE($N$11,$AB$6,$AC$6,$AD$6,$AE$6)+$P$11,0)+$DL$12)/$DL$11 -> 0.069503846 | AY9: =(IF(AND($K$11="OK",$E$11="FIJA"),$R$11,0)+$DL$13)/$DL$11 -> 0.069503846 | AZ9: =(IF(AND($K$11="OK",$E$11="OPERABLE"),CHOOSE($N$11,$AB$6,$AC$6,$AD$6,$AE$6)+$P$11,0)+$DL$12)/$DL$11 -> 0.069503846 | BA9: =(IF(AND($K$11="OK",$E$11="OPERABLE"),$R$11,0)+$DL$13)/$DL$11 -> 0.069503846 | BB9: =(IF(AND($K$12="OK",$E$12="FIJA"),CHOOSE($N$12,$AB$6,$AC$6,$AD$6,$AE$6)+$P$12,0)+$DL$12)/$DL$11 -> 0.069503846 | BC9: =(IF(AND($K$12="OK",$E$12="FIJA"),$R$12,0)+$DL$13)/$DL$11 -> 0.069503846 | BD9: =(IF(AND($K$12="OK",$E$12="OPERABLE"),CHOOSE($N$12,$AB$6,$AC$6,$AD$6,$AE$6)+$P$12,0)+$DL$12)/$DL$11 -> 0.069503846 | BE9: =(IF(AND($K$12="OK",$E$12="OPERABLE"),$R$12,0)+$DL$13)/$DL$11 -> 0.069503846 | BF9: =(IF(AND($K$13="OK",$E$13="FIJA"),CHOOSE($N$13,$AB$6,$AC$6,$AD$6,$AE$6)+$P$13,0)+$DL$12)/$DL$11 -> 0.069503846 | BG9: =(IF(AND($K$13="OK",$E$13="FIJA"),$R$13,0)+$DL$13)/$DL$11 -> 0.069503846 | BH9: =(IF(AND($K$13="OK",$E$13="OPERABLE"),CHOOSE($N$13,$AB$6,$AC$6,$AD$6,$AE$6)+$P$13,0)+$DL$12)/$DL$11 -> 0.069503846 | BI9: =(IF(AND($K$13="OK",$E$13="OPERABLE"),$R$13,0)+$DL$13)/$DL$11 -> 0.069503846 | BJ9: =(IF(AND($K$14="OK",$E$14="FIJA"),CHOOSE($N$14,$AB$6,$AC$6,$AD$6,$AE$6)+$P$14,0)+$DL$12)/$DL$11 -> 0.069503846 | BK9: =(IF(AND($K$14="OK",$E$14="FIJA"),$R$14,0)+$DL$13)/$DL$11 -> 0.069503846 | BL9: =(IF(AND($K$14="OK",$E$14="OPERABLE"),CHOOSE($N$14,$AB$6,$AC$6,$AD$6,$AE$6)+$P$14,0)+$DL$12)/$DL$11 -> 0.069503846 | BM9: =(IF(AND($K$14="OK",$E$14="OPERABLE"),$R$14,0)+$DL$13)/$DL$11 -> 0.069503846 | BN9: =(IF(AND($K$15="OK",$E$15="FIJA"),CHOOSE($N$15,$AB$6,$AC$6,$AD$6,$AE$6)+$P$15,0)+$DL$12)/$DL$11 -> 0.069503846 | BO9: =(IF(AND($K$15="OK",$E$15="FIJA"),$R$15,0)+$DL$13)/$DL$11 -> 0.069503846 | BP9: =(IF(AND($K$15="OK",$E$15="OPERABLE"),CHOOSE($N$15,$AB$6,$AC$6,$AD$6,$AE$6)+$P$15,0)+$DL$12)/$DL$11 -> 0.069503846 | BQ9: =(IF(AND($K$15="OK",$E$15="OPERABLE"),$R$15,0)+$DL$13)/$DL$11 -> 0.069503846 | BR9: =(IF(AND($K$16="OK",$E$16="FIJA"),CHOOSE($N$16,$AB$6,$AC$6,$AD$6,$AE$6)+$P$16,0)+$DL$12)/$DL$11 -> 0.069503846 | BS9: =(IF(AND($K$16="OK",$E$16="FIJA"),$R$16,0)+$DL$13)/$DL$11 -> 0.069503846 | BT9: =(IF(AND($K$16="OK",$E$16="OPERABLE"),CHOOSE($N$16,$AB$6,$AC$6,$AD$6,$AE$6)+$P$16,0)+$DL$12)/$DL$11 -> 0.069503846 | BU9: =(IF(AND($K$16="OK",$E$16="OPERABLE"),$R$16,0)+$DL$13)/$DL$11 -> 0.069503846 | BV9: =(IF(AND($K$17="OK",$E$17="FIJA"),CHOOSE($N$17,$AB$6,$AC$6,$AD$6,$AE$6)+$P$17,0)+$DL$12)/$DL$11 -> 0.069503846 | BW9: =(IF(AND($K$17="OK",$E$17="FIJA"),$R$17,0)+$DL$13)/$DL$11 -> 0.069503846 | BX9: =(IF(AND($K$17="OK",$E$17="OPERABLE"),CHOOSE($N$17,$AB$6,$AC$6,$AD$6,$AE$6)+$P$17,0)+$DL$12)/$DL$11 -> 0.069503846 | BY9: =(IF(AND($K$17="OK",$E$17="OPERABLE"),$R$17,0)+$DL$13)/$DL$11 -> 0.069503846 | BZ9: =(IF(AND($K$18="OK",$E$18="FIJA"),CHOOSE($N$18,$AB$6,$AC$6,$AD$6,$AE$6)+$P$18,0)+$DL$12)/$DL$11 -> 0.069503846 | CA9: =(IF(AND($K$18="OK",$E$18="FIJA"),$R$18,0)+$DL$13)/$DL$11 -> 0.069503846 | CB9: =(IF(AND($K$18="OK",$E$18="OPERABLE"),CHOOSE($N$18,$AB$6,$AC$6,$AD$6,$AE$6)+$P$18,0)+$DL$12)/$DL$11 -> 0.069503846 | CC9: =(IF(AND($K$18="OK",$E$18="OPERABLE"),$R$18,0)+$DL$13)/$DL$11 -> 0.069503846 | CD9: =(IF(AND($K$19="OK",$E$19="FIJA"),CHOOSE($N$19,$AB$6,$AC$6,$AD$6,$AE$6)+$P$19,0)+$DL$12)/$DL$11 -> 0.069503846 | CE9: =(IF(AND($K$19="OK",$E$19="FIJA"),$R$19,0)+$DL$13)/$DL$11 -> 0.069503846 | CF9: =(IF(AND($K$19="OK",$E$19="OPERABLE"),CHOOSE($N$19,$AB$6,$AC$6,$AD$6,$AE$6)+$P$19,0)+$DL$12)/$DL$11 -> 0.069503846 | CG9: =(IF(AND($K$19="OK",$E$19="OPERABLE"),$R$19,0)+$DL$13)/$DL$11 -> 0.069503846 | CH9: =(IF(AND($K$20="OK",$E$20="FIJA"),CHOOSE($N$20,$AB$6,$AC$6,$AD$6,$AE$6)+$P$20,0)+$DL$12)/$DL$11 -> 0.069503846 | CI9: =(IF(AND($K$20="OK",$E$20="FIJA"),$R$20,0)+$DL$13)/$DL$11 -> 0.069503846 | CJ9: =(IF(AND($K$20="OK",$E$20="OPERABLE"),CHOOSE($N$20,$AB$6,$AC$6,$AD$6,$AE$6)+$P$20,0)+$DL$12)/$DL$11 -> 0.069503846 | CK9: =(IF(AND($K$20="OK",$E$20="OPERABLE"),$R$20,0)+$DL$13)/$DL$11 -> 0.069503846 | CL9: =(IF(AND($K$21="OK",$E$21="FIJA"),CHOOSE($N$21,$AB$6,$AC$6,$AD$6,$AE$6)+$P$21,0)+$DL$12)/$DL$11 -> 0.069503846 | CM9: =(IF(AND($K$21="OK",$E$21="FIJA"),$R$21,0)+$DL$13)/$DL$11 -> 0.069503846 | CN9: =(IF(AND($K$21="OK",$E$21="OPERABLE"),CHOOSE($N$21,$AB$6,$AC$6,$AD$6,$AE$6)+$P$21,0)+$DL$12)/$DL$11 -> 0.069503846 | CO9: =(IF(AND($K$21="OK",$E$21="OPERABLE"),$R$21,0)+$DL$13)/$DL$11 -> 0.069503846 | CP9: =(IF(AND($K$22="OK",$E$22="FIJA"),CHOOSE($N$22,$AB$6,$AC$6,$AD$6,$AE$6)+$P$22,0)+$DL$12)/$DL$11 -> 0.069503846 | CQ9: =(IF(AND($K$22="OK",$E$22="FIJA"),$R$22,0)+$DL$13)/$DL$11 -> 0.069503846 | CR9: =(IF(AND($K$22="OK",$E$22="OPERABLE"),CHOOSE($N$22,$AB$6,$AC$6,$AD$6,$AE$6)+$P$22,0)+$DL$12)/$DL$11 -> 0.069503846 | CS9: =(IF(AND($K$22="OK",$E$22="OPERABLE"),$R$22,0)+$DL$13)/$DL$11 -> 0.069503846 | CT9: =(IF(AND($K$23="OK",$E$23="FIJA"),CHOOSE($N$23,$AB$6,$AC$6,$AD$6,$AE$6)+$P$23,0)+$DL$12)/$DL$11 -> 0.069503846 | CU9: =(IF(AND($K$23="OK",$E$23="FIJA"),$R$23,0)+$DL$13)/$DL$11 -> 0.069503846 | CV9: =(IF(AND($K$23="OK",$E$23="OPERABLE"),CHOOSE($N$23,$AB$6,$AC$6,$AD$6,$AE$6)+$P$23,0)+$DL$12)/$DL$11 -> 0.069503846 | CW9: =(IF(AND($K$23="OK",$E$23="OPERABLE"),$R$23,0)+$DL$13)/$DL$11 -> 0.069503846 | CX9: =(IF(AND($K$24="OK",$E$24="FIJA"),CHOOSE($N$24,$AB$6,$AC$6,$AD$6,$AE$6)+$P$24,0)+$DL$12)/$DL$11 -> 0.069503846 | CY9: =(IF(AND($K$24="OK",$E$24="FIJA"),$R$24,0)+$DL$13)/$DL$11 -> 0.069503846 | CZ9: =(IF(AND($K$24="OK",$E$24="OPERABLE"),CHOOSE($N$24,$AB$6,$AC$6,$AD$6,$AE$6)+$P$24,0)+$DL$12)/$DL$11 -> 0.069503846 | DA9: =(IF(AND($K$24="OK",$E$24="OPERABLE"),$R$24,0)+$DL$13)/$DL$11 -> 0.069503846 | DB9: =(IF(AND($K$25="OK",$E$25="FIJA"),CHOOSE($N$25,$AB$6,$AC$6,$AD$6,$AE$6)+$P$25,0)+$DL$12)/$DL$11 -> 0.069503846 | DC9: =(IF(AND($K$25="OK",$E$25="FIJA"),$R$25,0)+$DL$13)/$DL$11 -> 0.069503846 | DD9: =(IF(AND($K$25="OK",$E$25="OPERABLE"),CHOOSE($N$25,$AB$6,$AC$6,$AD$6,$AE$6)+$P$25,0)+$DL$12)/$DL$11 -> 0.069503846 | DE9: =(IF(AND($K$25="OK",$E$25="OPERABLE"),$R$25,0)+$DL$13)/$DL$11 -> 0.069503846 | DF9: =(IF(AND($K$26="OK",$E$26="FIJA"),CHOOSE($N$26,$AB$6,$AC$6,$AD$6,$AE$6)+$P$26,0)+$DL$12)/$DL$11 -> 0.069503846 | DG9: =(IF(AND($K$26="OK",$E$26="FIJA"),$R$26,0)+$DL$13)/$DL$11 -> 0.069503846 | DH9: =(IF(AND($K$26="OK",$E$26="OPERABLE"),CHOOSE($N$26,$AB$6,$AC$6,$AD$6,$AE$6)+$P$26,0)+$DL$12)/$DL$11 -> 0.069503846 | DI9: =(IF(AND($K$26="OK",$E$26="OPERABLE"),$R$26,0)+$DL$13)/$DL$11 -> 0.069503846 | DK9: margen | DL9: =0.02*$DL$7 -> 1.1392
B10: 4 | J10: =IF($K10="OK",$H10*$I10,0) -> 0 | K10: =IF($D10="","",IF(OR($F10="",$G10=""),"FALTA POSICIÓN",IF(OR(N($H10)<=0,N($I10)<=0),"FALTA TAMAÑO",IF($E10="","FALTA TIPO",IF(OR(N($F10)<0,N($G10)<0,N($F10)+N($H10)>$W10+0.001),"SE SALE A LO LARGO",IF(N($G10)+N($I10)>MIN($S10,$T10)+0.001,"SE SALE POR ARRIBA","OK")))))) | N10: =IF($D10="",0,VALUE(MID($D10,6,1))) -> 0 | O10: =IF($K10="OK",N($F10),0) -> 0 | P10: =IF($K10="OK",N($F10)+N($H10),0) -> 0 | Q10: =IF($K10="OK",N($G10),0) -> 0 | R10: =IF($K10="OK",N($G10)+N($I10),0) -> 0 | S10: =IF($N10=0,0,IF(INDEX($E$51:$E$54,$N10)="SÍ",IF(DATOS!$C$14="PLANO",DATOS!$C$17,IF(DATOS!$C$14="DOS AGUAS",DATOS!$C$17+(DATOS!$C$18-DATOS!$C$17)*(1-ABS(2*(N($F10))/DATOS!$C$23-1)),IF(DATOS!$C$14="UN AGUA",IF(N(DATOS!$C$25)=0,DATOS!$C$18-(DATOS!$C$18-DATOS!$C$17)*(N($F10))/DATOS!$C$23,DATOS!$C$17+(DATOS!$C$18-DATOS!$C$17)*(N($F10))/DATOS!$C$23),DATOS!$C$17+4*(DATOS!$C$18-DATOS!$C$17)*(N($F10))/DATOS!$C$23*(1-(N($F10))/DATOS!$C$23)))),INDEX($F$51:$F$54,$N10))) -> 0 | T10: =IF($N10=0,0,IF(INDEX($E$51:$E$54,$N10)="SÍ",IF(DATOS!$C$14="PLANO",DATOS!$C$17,IF(DATOS!$C$14="DOS AGUAS",DATOS!$C$17+(DATOS!$C$18-DATOS!$C$17)*(1-ABS(2*(N($F10)+N($H10))/DATOS!$C$23-1)),IF(DATOS!$C$14="UN AGUA",IF(N(DATOS!$C$25)=0,DATOS!$C$18-(DATOS!$C$18-DATOS!$C$17)*(N($F10)+N($H10))/DATOS!$C$23,DATOS!$C$17+(DATOS!$C$18-DATOS!$C$17)*(N($F10)+N($H10))/DATOS!$C$23),DATOS!$C$17+4*(DATOS!$C$18-DATOS!$C$17)*(N($F10)+N($H10))/DATOS!$C$23*(1-(N($F10)+N($H10))/DATOS!$C$23)))),INDEX($F$51:$F$54,$N10))) -> 0 | U10: =IF(AND($K10="OK",$E10="FIJA"),1,0) -> 0 | V10: =IF($K10="OK",1,0) -> 0 | W10: =IF($N10=0,0,INDEX($D$51:$D$54,$N10)) -> 0 | Y10: =($AB$6+DATOS!$AE$6+$DL$12)/$DL$11 -> 0.60762176 | Z10: =(DATOS!$AF$6+$DL$13)/$DL$11 -> 0.71744174 | AA10: =($AC$6+DATOS!$AI$6+$DL$12)/$DL$11 -> 1.3202314 | AB10: =(DATOS!$AJ$6+$DL$13)/$DL$11 -> 0.66863286 | AC10: =($AD$6+DATOS!$AM$6+$DL$12)/$DL$11 -> 2.3488786 | AD10: =(DATOS!$AN$6+$DL$13)/$DL$11 -> 0.67473397 | AE10: =($AE$6+DATOS!$AQ$6+$DL$12)/$DL$11 -> 3.422674 | AF10: =(DATOS!$AR$6+$DL$13)/$DL$11 -> 0.67473397 | AH10: =(IF(AND($K$7="OK",$E$7="FIJA"),CHOOSE($N$7,$AB$6,$AC$6,$AD$6,$AE$6)+$O$7,0)+$DL$12)/$DL$11 -> 0.069503846 | AI10: =(IF(AND($K$7="OK",$E$7="FIJA"),$R$7,0)+$DL$13)/$DL$11 -> 0.069503846 | AJ10: =(IF(AND($K$7="OK",$E$7="OPERABLE"),CHOOSE($N$7,$AB$6,$AC$6,$AD$6,$AE$6)+$O$7,0)+$DL$12)/$DL$11 -> 0.10870348 | AK10: =(IF(AND($K$7="OK",$E$7="OPERABLE"),$R$7,0)+$DL$13)/$DL$11 -> 0.21593049 | AL10: =(IF(AND($K$8="OK",$E$8="FIJA"),CHOOSE($N$8,$AB$6,$AC$6,$AD$6,$AE$6)+$O$8,0)+$DL$12)/$DL$11 -> 0.069503846 | AM10: =(IF(AND($K$8="OK",$E$8="FIJA"),$R$8,0)+$DL$13)/$DL$11 -> 0.069503846 | AN10: =(IF(AND($K$8="OK",$E$8="OPERABLE"),CHOOSE($N$8,$AB$6,$AC$6,$AD$6,$AE$6)+$O$8,0)+$DL$12)/$DL$11 -> 0.22123235 | AO10: =(IF(AND($K$8="OK",$E$8="OPERABLE"),$R$8,0)+$DL$13)/$DL$11 -> 0.45570411 | AP10: =(IF(AND($K$9="OK",$E$9="FIJA"),CHOOSE($N$9,$AB$6,$AC$6,$AD$6,$AE$6)+$O$9,0)+$DL$12)/$DL$11 -> 0.7821135 | AQ10: =(IF(AND($K$9="OK",$E$9="FIJA"),$R$9,0)+$DL$13)/$DL$11 -> 0.66863286 | AR10: =(IF(AND($K$9="OK",$E$9="OPERABLE"),CHOOSE($N$9,$AB$6,$AC$6,$AD$6,$AE$6)+$O$9,0)+$DL$12)/$DL$11 -> 0.069503846 | AS10: =(IF(AND($K$9="OK",$E$9="OPERABLE"),$R$9,0)+$DL$13)/$DL$11 -> 0.069503846 | AT10: =(IF(AND($K$10="OK",$E$10="FIJA"),CHOOSE($N$10,$AB$6,$AC$6,$AD$6,$AE$6)+$O$10,0)+$DL$12)/$DL$11 -> 0.069503846 | AU10: =(IF(AND($K$10="OK",$E$10="FIJA"),$R$10,0)+$DL$13)/$DL$11 -> 0.069503846 | AV10: =(IF(AND($K$10="OK",$E$10="OPERABLE"),CHOOSE($N$10,$AB$6,$AC$6,$AD$6,$AE$6)+$O$10,0)+$DL$12)/$DL$11 -> 0.069503846 | AW10: =(IF(AND($K$10="OK",$E$10="OPERABLE"),$R$10,0)+$DL$13)/$DL$11 -> 0.069503846 | AX10: =(IF(AND($K$11="OK",$E$11="FIJA"),CHOOSE($N$11,$AB$6,$AC$6,$AD$6,$AE$6)+$O$11,0)+$DL$12)/$DL$11 -> 0.069503846 | AY10: =(IF(AND($K$11="OK",$E$11="FIJA"),$R$11,0)+$DL$13)/$DL$11 -> 0.069503846 | AZ10: =(IF(AND($K$11="OK",$E$11="OPERABLE"),CHOOSE($N$11,$AB$6,$AC$6,$AD$6,$AE$6)+$O$11,0)+$DL$12)/$DL$11 -> 0.069503846 | BA10: =(IF(AND($K$11="OK",$E$11="OPERABLE"),$R$11,0)+$DL$13)/$DL$11 -> 0.069503846 | BB10: =(IF(AND($K$12="OK",$E$12="FIJA"),CHOOSE($N$12,$AB$6,$AC$6,$AD$6,$AE$6)+$O$12,0)+$DL$12)/$DL$11 -> 0.069503846 | BC10: =(IF(AND($K$12="OK",$E$12="FIJA"),$R$12,0)+$DL$13)/$DL$11 -> 0.069503846 | BD10: =(IF(AND($K$12="OK",$E$12="OPERABLE"),CHOOSE($N$12,$AB$6,$AC$6,$AD$6,$AE$6)+$O$12,0)+$DL$12)/$DL$11 -> 0.069503846 | BE10: =(IF(AND($K$12="OK",$E$12="OPERABLE"),$R$12,0)+$DL$13)/$DL$11 -> 0.069503846 | BF10: =(IF(AND($K$13="OK",$E$13="FIJA"),CHOOSE($N$13,$AB$6,$AC$6,$AD$6,$AE$6)+$O$13,0)+$DL$12)/$DL$11 -> 0.069503846 | BG10: =(IF(AND($K$13="OK",$E$13="FIJA"),$R$13,0)+$DL$13)/$DL$11 -> 0.069503846 | BH10: =(IF(AND($K$13="OK",$E$13="OPERABLE"),CHOOSE($N$13,$AB$6,$AC$6,$AD$6,$AE$6)+$O$13,0)+$DL$12)/$DL$11 -> 0.069503846 | BI10: =(IF(AND($K$13="OK",$E$13="OPERABLE"),$R$13,0)+$DL$13)/$DL$11 -> 0.069503846 | BJ10: =(IF(AND($K$14="OK",$E$14="FIJA"),CHOOSE($N$14,$AB$6,$AC$6,$AD$6,$AE$6)+$O$14,0)+$DL$12)/$DL$11 -> 0.069503846 | BK10: =(IF(AND($K$14="OK",$E$14="FIJA"),$R$14,0)+$DL$13)/$DL$11 -> 0.069503846 | BL10: =(IF(AND($K$14="OK",$E$14="OPERABLE"),CHOOSE($N$14,$AB$6,$AC$6,$AD$6,$AE$6)+$O$14,0)+$DL$12)/$DL$11 -> 0.069503846 | BM10: =(IF(AND($K$14="OK",$E$14="OPERABLE"),$R$14,0)+$DL$13)/$DL$11 -> 0.069503846 | BN10: =(IF(AND($K$15="OK",$E$15="FIJA"),CHOOSE($N$15,$AB$6,$AC$6,$AD$6,$AE$6)+$O$15,0)+$DL$12)/$DL$11 -> 0.069503846 | BO10: =(IF(AND($K$15="OK",$E$15="FIJA"),$R$15,0)+$DL$13)/$DL$11 -> 0.069503846 | BP10: =(IF(AND($K$15="OK",$E$15="OPERABLE"),CHOOSE($N$15,$AB$6,$AC$6,$AD$6,$AE$6)+$O$15,0)+$DL$12)/$DL$11 -> 0.069503846 | BQ10: =(IF(AND($K$15="OK",$E$15="OPERABLE"),$R$15,0)+$DL$13)/$DL$11 -> 0.069503846 | BR10: =(IF(AND($K$16="OK",$E$16="FIJA"),CHOOSE($N$16,$AB$6,$AC$6,$AD$6,$AE$6)+$O$16,0)+$DL$12)/$DL$11 -> 0.069503846 | BS10: =(IF(AND($K$16="OK",$E$16="FIJA"),$R$16,0)+$DL$13)/$DL$11 -> 0.069503846 | BT10: =(IF(AND($K$16="OK",$E$16="OPERABLE"),CHOOSE($N$16,$AB$6,$AC$6,$AD$6,$AE$6)+$O$16,0)+$DL$12)/$DL$11 -> 0.069503846 | BU10: =(IF(AND($K$16="OK",$E$16="OPERABLE"),$R$16,0)+$DL$13)/$DL$11 -> 0.069503846 | BV10: =(IF(AND($K$17="OK",$E$17="FIJA"),CHOOSE($N$17,$AB$6,$AC$6,$AD$6,$AE$6)+$O$17,0)+$DL$12)/$DL$11 -> 0.069503846 | BW10: =(IF(AND($K$17="OK",$E$17="FIJA"),$R$17,0)+$DL$13)/$DL$11 -> 0.069503846 | BX10: =(IF(AND($K$17="OK",$E$17="OPERABLE"),CHOOSE($N$17,$AB$6,$AC$6,$AD$6,$AE$6)+$O$17,0)+$DL$12)/$DL$11 -> 0.069503846 | BY10: =(IF(AND($K$17="OK",$E$17="OPERABLE"),$R$17,0)+$DL$13)/$DL$11 -> 0.069503846 | BZ10: =(IF(AND($K$18="OK",$E$18="FIJA"),CHOOSE($N$18,$AB$6,$AC$6,$AD$6,$AE$6)+$O$18,0)+$DL$12)/$DL$11 -> 0.069503846 | CA10: =(IF(AND($K$18="OK",$E$18="FIJA"),$R$18,0)+$DL$13)/$DL$11 -> 0.069503846 | CB10: =(IF(AND($K$18="OK",$E$18="OPERABLE"),CHOOSE($N$18,$AB$6,$AC$6,$AD$6,$AE$6)+$O$18,0)+$DL$12)/$DL$11 -> 0.069503846 | CC10: =(IF(AND($K$18="OK",$E$18="OPERABLE"),$R$18,0)+$DL$13)/$DL$11 -> 0.069503846 | CD10: =(IF(AND($K$19="OK",$E$19="FIJA"),CHOOSE($N$19,$AB$6,$AC$6,$AD$6,$AE$6)+$O$19,0)+$DL$12)/$DL$11 -> 0.069503846 | CE10: =(IF(AND($K$19="OK",$E$19="FIJA"),$R$19,0)+$DL$13)/$DL$11 -> 0.069503846 | CF10: =(IF(AND($K$19="OK",$E$19="OPERABLE"),CHOOSE($N$19,$AB$6,$AC$6,$AD$6,$AE$6)+$O$19,0)+$DL$12)/$DL$11 -> 0.069503846 | CG10: =(IF(AND($K$19="OK",$E$19="OPERABLE"),$R$19,0)+$DL$13)/$DL$11 -> 0.069503846 | CH10: =(IF(AND($K$20="OK",$E$20="FIJA"),CHOOSE($N$20,$AB$6,$AC$6,$AD$6,$AE$6)+$O$20,0)+$DL$12)/$DL$11 -> 0.069503846 | CI10: =(IF(AND($K$20="OK",$E$20="FIJA"),$R$20,0)+$DL$13)/$DL$11 -> 0.069503846 | CJ10: =(IF(AND($K$20="OK",$E$20="OPERABLE"),CHOOSE($N$20,$AB$6,$AC$6,$AD$6,$AE$6)+$O$20,0)+$DL$12)/$DL$11 -> 0.069503846 | CK10: =(IF(AND($K$20="OK",$E$20="OPERABLE"),$R$20,0)+$DL$13)/$DL$11 -> 0.069503846 | CL10: =(IF(AND($K$21="OK",$E$21="FIJA"),CHOOSE($N$21,$AB$6,$AC$6,$AD$6,$AE$6)+$O$21,0)+$DL$12)/$DL$11 -> 0.069503846 | CM10: =(IF(AND($K$21="OK",$E$21="FIJA"),$R$21,0)+$DL$13)/$DL$11 -> 0.069503846 | CN10: =(IF(AND($K$21="OK",$E$21="OPERABLE"),CHOOSE($N$21,$AB$6,$AC$6,$AD$6,$AE$6)+$O$21,0)+$DL$12)/$DL$11 -> 0.069503846 | CO10: =(IF(AND($K$21="OK",$E$21="OPERABLE"),$R$21,0)+$DL$13)/$DL$11 -> 0.069503846 | CP10: =(IF(AND($K$22="OK",$E$22="FIJA"),CHOOSE($N$22,$AB$6,$AC$6,$AD$6,$AE$6)+$O$22,0)+$DL$12)/$DL$11 -> 0.069503846 | CQ10: =(IF(AND($K$22="OK",$E$22="FIJA"),$R$22,0)+$DL$13)/$DL$11 -> 0.069503846 | CR10: =(IF(AND($K$22="OK",$E$22="OPERABLE"),CHOOSE($N$22,$AB$6,$AC$6,$AD$6,$AE$6)+$O$22,0)+$DL$12)/$DL$11 -> 0.069503846 | CS10: =(IF(AND($K$22="OK",$E$22="OPERABLE"),$R$22,0)+$DL$13)/$DL$11 -> 0.069503846 | CT10: =(IF(AND($K$23="OK",$E$23="FIJA"),CHOOSE($N$23,$AB$6,$AC$6,$AD$6,$AE$6)+$O$23,0)+$DL$12)/$DL$11 -> 0.069503846 | CU10: =(IF(AND($K$23="OK",$E$23="FIJA"),$R$23,0)+$DL$13)/$DL$11 -> 0.069503846 | CV10: =(IF(AND($K$23="OK",$E$23="OPERABLE"),CHOOSE($N$23,$AB$6,$AC$6,$AD$6,$AE$6)+$O$23,0)+$DL$12)/$DL$11 -> 0.069503846 | CW10: =(IF(AND($K$23="OK",$E$23="OPERABLE"),$R$23,0)+$DL$13)/$DL$11 -> 0.069503846 | CX10: =(IF(AND($K$24="OK",$E$24="FIJA"),CHOOSE($N$24,$AB$6,$AC$6,$AD$6,$AE$6)+$O$24,0)+$DL$12)/$DL$11 -> 0.069503846 | CY10: =(IF(AND($K$24="OK",$E$24="FIJA"),$R$24,0)+$DL$13)/$DL$11 -> 0.069503846 | CZ10: =(IF(AND($K$24="OK",$E$24="OPERABLE"),CHOOSE($N$24,$AB$6,$AC$6,$AD$6,$AE$6)+$O$24,0)+$DL$12)/$DL$11 -> 0.069503846 | DA10: =(IF(AND($K$24="OK",$E$24="OPERABLE"),$R$24,0)+$DL$13)/$DL$11 -> 0.069503846 | DB10: =(IF(AND($K$25="OK",$E$25="FIJA"),CHOOSE($N$25,$AB$6,$AC$6,$AD$6,$AE$6)+$O$25,0)+$DL$12)/$DL$11 -> 0.069503846 | DC10: =(IF(AND($K$25="OK",$E$25="FIJA"),$R$25,0)+$DL$13)/$DL$11 -> 0.069503846 | DD10: =(IF(AND($K$25="OK",$E$25="OPERABLE"),CHOOSE($N$25,$AB$6,$AC$6,$AD$6,$AE$6)+$O$25,0)+$DL$12)/$DL$11 -> 0.069503846 | DE10: =(IF(AND($K$25="OK",$E$25="OPERABLE"),$R$25,0)+$DL$13)/$DL$11 -> 0.069503846 | DF10: =(IF(AND($K$26="OK",$E$26="FIJA"),CHOOSE($N$26,$AB$6,$AC$6,$AD$6,$AE$6)+$O$26,0)+$DL$12)/$DL$11 -> 0.069503846 | DG10: =(IF(AND($K$26="OK",$E$26="FIJA"),$R$26,0)+$DL$13)/$DL$11 -> 0.069503846 | DH10: =(IF(AND($K$26="OK",$E$26="OPERABLE"),CHOOSE($N$26,$AB$6,$AC$6,$AD$6,$AE$6)+$O$26,0)+$DL$12)/$DL$11 -> 0.069503846 | DI10: =(IF(AND($K$26="OK",$E$26="OPERABLE"),$R$26,0)+$DL$13)/$DL$11 -> 0.069503846 | DK10: aspecto | DL10: =3.6142 -> 3.6142
B11: 5 | J11: =IF($K11="OK",$H11*$I11,0) -> 0 | K11: =IF($D11="","",IF(OR($F11="",$G11=""),"FALTA POSICIÓN",IF(OR(N($H11)<=0,N($I11)<=0),"FALTA TAMAÑO",IF($E11="","FALTA TIPO",IF(OR(N($F11)<0,N($G11)<0,N($F11)+N($H11)>$W11+0.001),"SE SALE A LO LARGO",IF(N($G11)+N($I11)>MIN($S11,$T11)+0.001,"SE SALE POR ARRIBA","OK")))))) | N11: =IF($D11="",0,VALUE(MID($D11,6,1))) -> 0 | O11: =IF($K11="OK",N($F11),0) -> 0 | P11: =IF($K11="OK",N($F11)+N($H11),0) -> 0 | Q11: =IF($K11="OK",N($G11),0) -> 0 | R11: =IF($K11="OK",N($G11)+N($I11),0) -> 0 | S11: =IF($N11=0,0,IF(INDEX($E$51:$E$54,$N11)="SÍ",IF(DATOS!$C$14="PLANO",DATOS!$C$17,IF(DATOS!$C$14="DOS AGUAS",DATOS!$C$17+(DATOS!$C$18-DATOS!$C$17)*(1-ABS(2*(N($F11))/DATOS!$C$23-1)),IF(DATOS!$C$14="UN AGUA",IF(N(DATOS!$C$25)=0,DATOS!$C$18-(DATOS!$C$18-DATOS!$C$17)*(N($F11))/DATOS!$C$23,DATOS!$C$17+(DATOS!$C$18-DATOS!$C$17)*(N($F11))/DATOS!$C$23),DATOS!$C$17+4*(DATOS!$C$18-DATOS!$C$17)*(N($F11))/DATOS!$C$23*(1-(N($F11))/DATOS!$C$23)))),INDEX($F$51:$F$54,$N11))) -> 0 | T11: =IF($N11=0,0,IF(INDEX($E$51:$E$54,$N11)="SÍ",IF(DATOS!$C$14="PLANO",DATOS!$C$17,IF(DATOS!$C$14="DOS AGUAS",DATOS!$C$17+(DATOS!$C$18-DATOS!$C$17)*(1-ABS(2*(N($F11)+N($H11))/DATOS!$C$23-1)),IF(DATOS!$C$14="UN AGUA",IF(N(DATOS!$C$25)=0,DATOS!$C$18-(DATOS!$C$18-DATOS!$C$17)*(N($F11)+N($H11))/DATOS!$C$23,DATOS!$C$17+(DATOS!$C$18-DATOS!$C$17)*(N($F11)+N($H11))/DATOS!$C$23),DATOS!$C$17+4*(DATOS!$C$18-DATOS!$C$17)*(N($F11)+N($H11))/DATOS!$C$23*(1-(N($F11)+N($H11))/DATOS!$C$23)))),INDEX($F$51:$F$54,$N11))) -> 0 | U11: =IF(AND($K11="OK",$E11="FIJA"),1,0) -> 0 | V11: =IF($K11="OK",1,0) -> 0 | W11: =IF($N11=0,0,INDEX($D$51:$D$54,$N11)) -> 0 | Y11: =($AB$6+DATOS!$AE$7+$DL$12)/$DL$11 -> 0.53074777 | Z11: =(DATOS!$AF$7+$DL$13)/$DL$11 -> 0.71744174 | AA11: =($AC$6+DATOS!$AI$7+$DL$12)/$DL$11 -> 1.2433574 | AB11: =(DATOS!$AJ$7+$DL$13)/$DL$11 -> 0.66863286 | AC11: =($AD$6+DATOS!$AM$7+$DL$12)/$DL$11 -> 2.2268564 | AD11: =(DATOS!$AN$7+$DL$13)/$DL$11 -> 0.68083508 | AE11: =($AE$6+DATOS!$AQ$7+$DL$12)/$DL$11 -> 3.3006518 | AF11: =(DATOS!$AR$7+$DL$13)/$DL$11 -> 0.68083508 | AH11: =(IF(AND($K$7="OK",$E$7="FIJA"),CHOOSE($N$7,$AB$6,$AC$6,$AD$6,$AE$6)+$O$7,0)+$DL$12)/$DL$11 -> 0.069503846 | AI11: =(IF(AND($K$7="OK",$E$7="FIJA"),$Q$7,0)+$DL$13)/$DL$11 -> 0.069503846 | AJ11: =(IF(AND($K$7="OK",$E$7="OPERABLE"),CHOOSE($N$7,$AB$6,$AC$6,$AD$6,$AE$6)+$O$7,0)+$DL$12)/$DL$11 -> 0.10870348 | AK11: =(IF(AND($K$7="OK",$E$7="OPERABLE"),$Q$7,0)+$DL$13)/$DL$11 -> 0.069503846 | AL11: =(IF(AND($K$8="OK",$E$8="FIJA"),CHOOSE($N$8,$AB$6,$AC$6,$AD$6,$AE$6)+$O$8,0)+$DL$12)/$DL$11 -> 0.069503846 | AM11: =(IF(AND($K$8="OK",$E$8="FIJA"),$Q$8,0)+$DL$13)/$DL$11 -> 0.069503846 | AN11: =(IF(AND($K$8="OK",$E$8="OPERABLE"),CHOOSE($N$8,$AB$6,$AC$6,$AD$6,$AE$6)+$O$8,0)+$DL$12)/$DL$11 -> 0.22123235 | AO11: =(IF(AND($K$8="OK",$E$8="OPERABLE"),$Q$8,0)+$DL$13)/$DL$11 -> 0.069503846 | AP11: =(IF(AND($K$9="OK",$E$9="FIJA"),CHOOSE($N$9,$AB$6,$AC$6,$AD$6,$AE$6)+$O$9,0)+$DL$12)/$DL$11 -> 0.7821135 | AQ11: =(IF(AND($K$9="OK",$E$9="FIJA"),$Q$9,0)+$DL$13)/$DL$11 -> 0.069503846 | AR11: =(IF(AND($K$9="OK",$E$9="OPERABLE"),CHOOSE($N$9,$AB$6,$AC$6,$AD$6,$AE$6)+$O$9,0)+$DL$12)/$DL$11 -> 0.069503846 | AS11: =(IF(AND($K$9="OK",$E$9="OPERABLE"),$Q$9,0)+$DL$13)/$DL$11 -> 0.069503846 | AT11: =(IF(AND($K$10="OK",$E$10="FIJA"),CHOOSE($N$10,$AB$6,$AC$6,$AD$6,$AE$6)+$O$10,0)+$DL$12)/$DL$11 -> 0.069503846 | AU11: =(IF(AND($K$10="OK",$E$10="FIJA"),$Q$10,0)+$DL$13)/$DL$11 -> 0.069503846 | AV11: =(IF(AND($K$10="OK",$E$10="OPERABLE"),CHOOSE($N$10,$AB$6,$AC$6,$AD$6,$AE$6)+$O$10,0)+$DL$12)/$DL$11 -> 0.069503846 | AW11: =(IF(AND($K$10="OK",$E$10="OPERABLE"),$Q$10,0)+$DL$13)/$DL$11 -> 0.069503846 | AX11: =(IF(AND($K$11="OK",$E$11="FIJA"),CHOOSE($N$11,$AB$6,$AC$6,$AD$6,$AE$6)+$O$11,0)+$DL$12)/$DL$11 -> 0.069503846 | AY11: =(IF(AND($K$11="OK",$E$11="FIJA"),$Q$11,0)+$DL$13)/$DL$11 -> 0.069503846 | AZ11: =(IF(AND($K$11="OK",$E$11="OPERABLE"),CHOOSE($N$11,$AB$6,$AC$6,$AD$6,$AE$6)+$O$11,0)+$DL$12)/$DL$11 -> 0.069503846 | BA11: =(IF(AND($K$11="OK",$E$11="OPERABLE"),$Q$11,0)+$DL$13)/$DL$11 -> 0.069503846 | BB11: =(IF(AND($K$12="OK",$E$12="FIJA"),CHOOSE($N$12,$AB$6,$AC$6,$AD$6,$AE$6)+$O$12,0)+$DL$12)/$DL$11 -> 0.069503846 | BC11: =(IF(AND($K$12="OK",$E$12="FIJA"),$Q$12,0)+$DL$13)/$DL$11 -> 0.069503846 | BD11: =(IF(AND($K$12="OK",$E$12="OPERABLE"),CHOOSE($N$12,$AB$6,$AC$6,$AD$6,$AE$6)+$O$12,0)+$DL$12)/$DL$11 -> 0.069503846 | BE11: =(IF(AND($K$12="OK",$E$12="OPERABLE"),$Q$12,0)+$DL$13)/$DL$11 -> 0.069503846 | BF11: =(IF(AND($K$13="OK",$E$13="FIJA"),CHOOSE($N$13,$AB$6,$AC$6,$AD$6,$AE$6)+$O$13,0)+$DL$12)/$DL$11 -> 0.069503846 | BG11: =(IF(AND($K$13="OK",$E$13="FIJA"),$Q$13,0)+$DL$13)/$DL$11 -> 0.069503846 | BH11: =(IF(AND($K$13="OK",$E$13="OPERABLE"),CHOOSE($N$13,$AB$6,$AC$6,$AD$6,$AE$6)+$O$13,0)+$DL$12)/$DL$11 -> 0.069503846 | BI11: =(IF(AND($K$13="OK",$E$13="OPERABLE"),$Q$13,0)+$DL$13)/$DL$11 -> 0.069503846 | BJ11: =(IF(AND($K$14="OK",$E$14="FIJA"),CHOOSE($N$14,$AB$6,$AC$6,$AD$6,$AE$6)+$O$14,0)+$DL$12)/$DL$11 -> 0.069503846 | BK11: =(IF(AND($K$14="OK",$E$14="FIJA"),$Q$14,0)+$DL$13)/$DL$11 -> 0.069503846 | BL11: =(IF(AND($K$14="OK",$E$14="OPERABLE"),CHOOSE($N$14,$AB$6,$AC$6,$AD$6,$AE$6)+$O$14,0)+$DL$12)/$DL$11 -> 0.069503846 | BM11: =(IF(AND($K$14="OK",$E$14="OPERABLE"),$Q$14,0)+$DL$13)/$DL$11 -> 0.069503846 | BN11: =(IF(AND($K$15="OK",$E$15="FIJA"),CHOOSE($N$15,$AB$6,$AC$6,$AD$6,$AE$6)+$O$15,0)+$DL$12)/$DL$11 -> 0.069503846 | BO11: =(IF(AND($K$15="OK",$E$15="FIJA"),$Q$15,0)+$DL$13)/$DL$11 -> 0.069503846 | BP11: =(IF(AND($K$15="OK",$E$15="OPERABLE"),CHOOSE($N$15,$AB$6,$AC$6,$AD$6,$AE$6)+$O$15,0)+$DL$12)/$DL$11 -> 0.069503846 | BQ11: =(IF(AND($K$15="OK",$E$15="OPERABLE"),$Q$15,0)+$DL$13)/$DL$11 -> 0.069503846 | BR11: =(IF(AND($K$16="OK",$E$16="FIJA"),CHOOSE($N$16,$AB$6,$AC$6,$AD$6,$AE$6)+$O$16,0)+$DL$12)/$DL$11 -> 0.069503846 | BS11: =(IF(AND($K$16="OK",$E$16="FIJA"),$Q$16,0)+$DL$13)/$DL$11 -> 0.069503846 | BT11: =(IF(AND($K$16="OK",$E$16="OPERABLE"),CHOOSE($N$16,$AB$6,$AC$6,$AD$6,$AE$6)+$O$16,0)+$DL$12)/$DL$11 -> 0.069503846 | BU11: =(IF(AND($K$16="OK",$E$16="OPERABLE"),$Q$16,0)+$DL$13)/$DL$11 -> 0.069503846 | BV11: =(IF(AND($K$17="OK",$E$17="FIJA"),CHOOSE($N$17,$AB$6,$AC$6,$AD$6,$AE$6)+$O$17,0)+$DL$12)/$DL$11 -> 0.069503846 | BW11: =(IF(AND($K$17="OK",$E$17="FIJA"),$Q$17,0)+$DL$13)/$DL$11 -> 0.069503846 | BX11: =(IF(AND($K$17="OK",$E$17="OPERABLE"),CHOOSE($N$17,$AB$6,$AC$6,$AD$6,$AE$6)+$O$17,0)+$DL$12)/$DL$11 -> 0.069503846 | BY11: =(IF(AND($K$17="OK",$E$17="OPERABLE"),$Q$17,0)+$DL$13)/$DL$11 -> 0.069503846 | BZ11: =(IF(AND($K$18="OK",$E$18="FIJA"),CHOOSE($N$18,$AB$6,$AC$6,$AD$6,$AE$6)+$O$18,0)+$DL$12)/$DL$11 -> 0.069503846 | CA11: =(IF(AND($K$18="OK",$E$18="FIJA"),$Q$18,0)+$DL$13)/$DL$11 -> 0.069503846 | CB11: =(IF(AND($K$18="OK",$E$18="OPERABLE"),CHOOSE($N$18,$AB$6,$AC$6,$AD$6,$AE$6)+$O$18,0)+$DL$12)/$DL$11 -> 0.069503846 | CC11: =(IF(AND($K$18="OK",$E$18="OPERABLE"),$Q$18,0)+$DL$13)/$DL$11 -> 0.069503846 | CD11: =(IF(AND($K$19="OK",$E$19="FIJA"),CHOOSE($N$19,$AB$6,$AC$6,$AD$6,$AE$6)+$O$19,0)+$DL$12)/$DL$11 -> 0.069503846 | CE11: =(IF(AND($K$19="OK",$E$19="FIJA"),$Q$19,0)+$DL$13)/$DL$11 -> 0.069503846 | CF11: =(IF(AND($K$19="OK",$E$19="OPERABLE"),CHOOSE($N$19,$AB$6,$AC$6,$AD$6,$AE$6)+$O$19,0)+$DL$12)/$DL$11 -> 0.069503846 | CG11: =(IF(AND($K$19="OK",$E$19="OPERABLE"),$Q$19,0)+$DL$13)/$DL$11 -> 0.069503846 | CH11: =(IF(AND($K$20="OK",$E$20="FIJA"),CHOOSE($N$20,$AB$6,$AC$6,$AD$6,$AE$6)+$O$20,0)+$DL$12)/$DL$11 -> 0.069503846 | CI11: =(IF(AND($K$20="OK",$E$20="FIJA"),$Q$20,0)+$DL$13)/$DL$11 -> 0.069503846 | CJ11: =(IF(AND($K$20="OK",$E$20="OPERABLE"),CHOOSE($N$20,$AB$6,$AC$6,$AD$6,$AE$6)+$O$20,0)+$DL$12)/$DL$11 -> 0.069503846 | CK11: =(IF(AND($K$20="OK",$E$20="OPERABLE"),$Q$20,0)+$DL$13)/$DL$11 -> 0.069503846 | CL11: =(IF(AND($K$21="OK",$E$21="FIJA"),CHOOSE($N$21,$AB$6,$AC$6,$AD$6,$AE$6)+$O$21,0)+$DL$12)/$DL$11 -> 0.069503846 | CM11: =(IF(AND($K$21="OK",$E$21="FIJA"),$Q$21,0)+$DL$13)/$DL$11 -> 0.069503846 | CN11: =(IF(AND($K$21="OK",$E$21="OPERABLE"),CHOOSE($N$21,$AB$6,$AC$6,$AD$6,$AE$6)+$O$21,0)+$DL$12)/$DL$11 -> 0.069503846 | CO11: =(IF(AND($K$21="OK",$E$21="OPERABLE"),$Q$21,0)+$DL$13)/$DL$11 -> 0.069503846 | CP11: =(IF(AND($K$22="OK",$E$22="FIJA"),CHOOSE($N$22,$AB$6,$AC$6,$AD$6,$AE$6)+$O$22,0)+$DL$12)/$DL$11 -> 0.069503846 | CQ11: =(IF(AND($K$22="OK",$E$22="FIJA"),$Q$22,0)+$DL$13)/$DL$11 -> 0.069503846 | CR11: =(IF(AND($K$22="OK",$E$22="OPERABLE"),CHOOSE($N$22,$AB$6,$AC$6,$AD$6,$AE$6)+$O$22,0)+$DL$12)/$DL$11 -> 0.069503846 | CS11: =(IF(AND($K$22="OK",$E$22="OPERABLE"),$Q$22,0)+$DL$13)/$DL$11 -> 0.069503846 | CT11: =(IF(AND($K$23="OK",$E$23="FIJA"),CHOOSE($N$23,$AB$6,$AC$6,$AD$6,$AE$6)+$O$23,0)+$DL$12)/$DL$11 -> 0.069503846 | CU11: =(IF(AND($K$23="OK",$E$23="FIJA"),$Q$23,0)+$DL$13)/$DL$11 -> 0.069503846 | CV11: =(IF(AND($K$23="OK",$E$23="OPERABLE"),CHOOSE($N$23,$AB$6,$AC$6,$AD$6,$AE$6)+$O$23,0)+$DL$12)/$DL$11 -> 0.069503846 | CW11: =(IF(AND($K$23="OK",$E$23="OPERABLE"),$Q$23,0)+$DL$13)/$DL$11 -> 0.069503846 | CX11: =(IF(AND($K$24="OK",$E$24="FIJA"),CHOOSE($N$24,$AB$6,$AC$6,$AD$6,$AE$6)+$O$24,0)+$DL$12)/$DL$11 -> 0.069503846 | CY11: =(IF(AND($K$24="OK",$E$24="FIJA"),$Q$24,0)+$DL$13)/$DL$11 -> 0.069503846 | CZ11: =(IF(AND($K$24="OK",$E$24="OPERABLE"),CHOOSE($N$24,$AB$6,$AC$6,$AD$6,$AE$6)+$O$24,0)+$DL$12)/$DL$11 -> 0.069503846 | DA11: =(IF(AND($K$24="OK",$E$24="OPERABLE"),$Q$24,0)+$DL$13)/$DL$11 -> 0.069503846 | DB11: =(IF(AND($K$25="OK",$E$25="FIJA"),CHOOSE($N$25,$AB$6,$AC$6,$AD$6,$AE$6)+$O$25,0)+$DL$12)/$DL$11 -> 0.069503846 | DC11: =(IF(AND($K$25="OK",$E$25="FIJA"),$Q$25,0)+$DL$13)/$DL$11 -> 0.069503846 | DD11: =(IF(AND($K$25="OK",$E$25="OPERABLE"),CHOOSE($N$25,$AB$6,$AC$6,$AD$6,$AE$6)+$O$25,0)+$DL$12)/$DL$11 -> 0.069503846 | DE11: =(IF(AND($K$25="OK",$E$25="OPERABLE"),$Q$25,0)+$DL$13)/$DL$11 -> 0.069503846 | DF11: =(IF(AND($K$26="OK",$E$26="FIJA"),CHOOSE($N$26,$AB$6,$AC$6,$AD$6,$AE$6)+$O$26,0)+$DL$12)/$DL$11 -> 0.069503846 | DG11: =(IF(AND($K$26="OK",$E$26="FIJA"),$Q$26,0)+$DL$13)/$DL$11 -> 0.069503846 | DH11: =(IF(AND($K$26="OK",$E$26="OPERABLE"),CHOOSE($N$26,$AB$6,$AC$6,$AD$6,$AE$6)+$O$26,0)+$DL$12)/$DL$11 -> 0.069503846 | DI11: =(IF(AND($K$26="OK",$E$26="OPERABLE"),$Q$26,0)+$DL$13)/$DL$11 -> 0.069503846 | DK11: s | DL11: =MAX(($DL$7+2*$DL$9)/$DL$10,$DL$8+2*$DL$9) -> 16.39046
B12: 6 | J12: =IF($K12="OK",$H12*$I12,0) -> 0 | K12: =IF($D12="","",IF(OR($F12="",$G12=""),"FALTA POSICIÓN",IF(OR(N($H12)<=0,N($I12)<=0),"FALTA TAMAÑO",IF($E12="","FALTA TIPO",IF(OR(N($F12)<0,N($G12)<0,N($F12)+N($H12)>$W12+0.001),"SE SALE A LO LARGO",IF(N($G12)+N($I12)>MIN($S12,$T12)+0.001,"SE SALE POR ARRIBA","OK")))))) | N12: =IF($D12="",0,VALUE(MID($D12,6,1))) -> 0 | O12: =IF($K12="OK",N($F12),0) -> 0 | P12: =IF($K12="OK",N($F12)+N($H12),0) -> 0 | Q12: =IF($K12="OK",N($G12),0) -> 0 | R12: =IF($K12="OK",N($G12)+N($I12),0) -> 0 | S12: =IF($N12=0,0,IF(INDEX($E$51:$E$54,$N12)="SÍ",IF(DATOS!$C$14="PLANO",DATOS!$C$17,IF(DATOS!$C$14="DOS AGUAS",DATOS!$C$17+(DATOS!$C$18-DATOS!$C$17)*(1-ABS(2*(N($F12))/DATOS!$C$23-1)),IF(DATOS!$C$14="UN AGUA",IF(N(DATOS!$C$25)=0,DATOS!$C$18-(DATOS!$C$18-DATOS!$C$17)*(N($F12))/DATOS!$C$23,DATOS!$C$17+(DATOS!$C$18-DATOS!$C$17)*(N($F12))/DATOS!$C$23),DATOS!$C$17+4*(DATOS!$C$18-DATOS!$C$17)*(N($F12))/DATOS!$C$23*(1-(N($F12))/DATOS!$C$23)))),INDEX($F$51:$F$54,$N12))) -> 0 | T12: =IF($N12=0,0,IF(INDEX($E$51:$E$54,$N12)="SÍ",IF(DATOS!$C$14="PLANO",DATOS!$C$17,IF(DATOS!$C$14="DOS AGUAS",DATOS!$C$17+(DATOS!$C$18-DATOS!$C$17)*(1-ABS(2*(N($F12)+N($H12))/DATOS!$C$23-1)),IF(DATOS!$C$14="UN AGUA",IF(N(DATOS!$C$25)=0,DATOS!$C$18-(DATOS!$C$18-DATOS!$C$17)*(N($F12)+N($H12))/DATOS!$C$23,DATOS!$C$17+(DATOS!$C$18-DATOS!$C$17)*(N($F12)+N($H12))/DATOS!$C$23),DATOS!$C$17+4*(DATOS!$C$18-DATOS!$C$17)*(N($F12)+N($H12))/DATOS!$C$23*(1-(N($F12)+N($H12))/DATOS!$C$23)))),INDEX($F$51:$F$54,$N12))) -> 0 | U12: =IF(AND($K12="OK",$E12="FIJA"),1,0) -> 0 | V12: =IF($K12="OK",1,0) -> 0 | W12: =IF($N12=0,0,INDEX($D$51:$D$54,$N12)) -> 0 | Y12: =($AB$6+DATOS!$AE$8+$DL$12)/$DL$11 -> 0.45387378 | Z12: =(DATOS!$AF$8+$DL$13)/$DL$11 -> 0.71744174 | AA12: =($AC$6+DATOS!$AI$8+$DL$12)/$DL$11 -> 1.1664834 | AB12: =(DATOS!$AJ$8+$DL$13)/$DL$11 -> 0.66863286 | AC12: =($AD$6+DATOS!$AM$8+$DL$12)/$DL$11 -> 2.1048342 | AD12: =(DATOS!$AN$8+$DL$13)/$DL$11 -> 0.68693619 | AE12: =($AE$6+DATOS!$AQ$8+$DL$12)/$DL$11 -> 3.1786295 | AF12: =(DATOS!$AR$8+$DL$13)/$DL$11 -> 0.68693619 | DK12: offX | DL12: =($DL$10*$DL$11-($DL$7+2*$DL$9))/2+$DL$9 -> 1.1392
B13: 7 | J13: =IF($K13="OK",$H13*$I13,0) -> 0 | K13: =IF($D13="","",IF(OR($F13="",$G13=""),"FALTA POSICIÓN",IF(OR(N($H13)<=0,N($I13)<=0),"FALTA TAMAÑO",IF($E13="","FALTA TIPO",IF(OR(N($F13)<0,N($G13)<0,N($F13)+N($H13)>$W13+0.001),"SE SALE A LO LARGO",IF(N($G13)+N($I13)>MIN($S13,$T13)+0.001,"SE SALE POR ARRIBA","OK")))))) | N13: =IF($D13="",0,VALUE(MID($D13,6,1))) -> 0 | O13: =IF($K13="OK",N($F13),0) -> 0 | P13: =IF($K13="OK",N($F13)+N($H13),0) -> 0 | Q13: =IF($K13="OK",N($G13),0) -> 0 | R13: =IF($K13="OK",N($G13)+N($I13),0) -> 0 | S13: =IF($N13=0,0,IF(INDEX($E$51:$E$54,$N13)="SÍ",IF(DATOS!$C$14="PLANO",DATOS!$C$17,IF(DATOS!$C$14="DOS AGUAS",DATOS!$C$17+(DATOS!$C$18-DATOS!$C$17)*(1-ABS(2*(N($F13))/DATOS!$C$23-1)),IF(DATOS!$C$14="UN AGUA",IF(N(DATOS!$C$25)=0,DATOS!$C$18-(DATOS!$C$18-DATOS!$C$17)*(N($F13))/DATOS!$C$23,DATOS!$C$17+(DATOS!$C$18-DATOS!$C$17)*(N($F13))/DATOS!$C$23),DATOS!$C$17+4*(DATOS!$C$18-DATOS!$C$17)*(N($F13))/DATOS!$C$23*(1-(N($F13))/DATOS!$C$23)))),INDEX($F$51:$F$54,$N13))) -> 0 | T13: =IF($N13=0,0,IF(INDEX($E$51:$E$54,$N13)="SÍ",IF(DATOS!$C$14="PLANO",DATOS!$C$17,IF(DATOS!$C$14="DOS AGUAS",DATOS!$C$17+(DATOS!$C$18-DATOS!$C$17)*(1-ABS(2*(N($F13)+N($H13))/DATOS!$C$23-1)),IF(DATOS!$C$14="UN AGUA",IF(N(DATOS!$C$25)=0,DATOS!$C$18-(DATOS!$C$18-DATOS!$C$17)*(N($F13)+N($H13))/DATOS!$C$23,DATOS!$C$17+(DATOS!$C$18-DATOS!$C$17)*(N($F13)+N($H13))/DATOS!$C$23),DATOS!$C$17+4*(DATOS!$C$18-DATOS!$C$17)*(N($F13)+N($H13))/DATOS!$C$23*(1-(N($F13)+N($H13))/DATOS!$C$23)))),INDEX($F$51:$F$54,$N13))) -> 0 | U13: =IF(AND($K13="OK",$E13="FIJA"),1,0) -> 0 | V13: =IF($K13="OK",1,0) -> 0 | W13: =IF($N13=0,0,INDEX($D$51:$D$54,$N13)) -> 0 | Y13: =($AB$6+DATOS!$AE$9+$DL$12)/$DL$11 -> 0.37699979 | Z13: =(DATOS!$AF$9+$DL$13)/$DL$11 -> 0.71744174 | AA13: =($AC$6+DATOS!$AI$9+$DL$12)/$DL$11 -> 1.0896095 | AB13: =(DATOS!$AJ$9+$DL$13)/$DL$11 -> 0.66863286 | AC13: =($AD$6+DATOS!$AM$9+$DL$12)/$DL$11 -> 1.982812 | AD13: =(DATOS!$AN$9+$DL$13)/$DL$11 -> 0.6930373 | AE13: =($AE$6+DATOS!$AQ$9+$DL$12)/$DL$11 -> 3.0566073 | AF13: =(DATOS!$AR$9+$DL$13)/$DL$11 -> 0.6930373 | DK13: offY | DL13: =$DL$9 -> 1.1392
B14: 8 | J14: =IF($K14="OK",$H14*$I14,0) -> 0 | K14: =IF($D14="","",IF(OR($F14="",$G14=""),"FALTA POSICIÓN",IF(OR(N($H14)<=0,N($I14)<=0),"FALTA TAMAÑO",IF($E14="","FALTA TIPO",IF(OR(N($F14)<0,N($G14)<0,N($F14)+N($H14)>$W14+0.001),"SE SALE A LO LARGO",IF(N($G14)+N($I14)>MIN($S14,$T14)+0.001,"SE SALE POR ARRIBA","OK")))))) | N14: =IF($D14="",0,VALUE(MID($D14,6,1))) -> 0 | O14: =IF($K14="OK",N($F14),0) -> 0 | P14: =IF($K14="OK",N($F14)+N($H14),0) -> 0 | Q14: =IF($K14="OK",N($G14),0) -> 0 | R14: =IF($K14="OK",N($G14)+N($I14),0) -> 0 | S14: =IF($N14=0,0,IF(INDEX($E$51:$E$54,$N14)="SÍ",IF(DATOS!$C$14="PLANO",DATOS!$C$17,IF(DATOS!$C$14="DOS AGUAS",DATOS!$C$17+(DATOS!$C$18-DATOS!$C$17)*(1-ABS(2*(N($F14))/DATOS!$C$23-1)),IF(DATOS!$C$14="UN AGUA",IF(N(DATOS!$C$25)=0,DATOS!$C$18-(DATOS!$C$18-DATOS!$C$17)*(N($F14))/DATOS!$C$23,DATOS!$C$17+(DATOS!$C$18-DATOS!$C$17)*(N($F14))/DATOS!$C$23),DATOS!$C$17+4*(DATOS!$C$18-DATOS!$C$17)*(N($F14))/DATOS!$C$23*(1-(N($F14))/DATOS!$C$23)))),INDEX($F$51:$F$54,$N14))) -> 0 | T14: =IF($N14=0,0,IF(INDEX($E$51:$E$54,$N14)="SÍ",IF(DATOS!$C$14="PLANO",DATOS!$C$17,IF(DATOS!$C$14="DOS AGUAS",DATOS!$C$17+(DATOS!$C$18-DATOS!$C$17)*(1-ABS(2*(N($F14)+N($H14))/DATOS!$C$23-1)),IF(DATOS!$C$14="UN AGUA",IF(N(DATOS!$C$25)=0,DATOS!$C$18-(DATOS!$C$18-DATOS!$C$17)*(N($F14)+N($H14))/DATOS!$C$23,DATOS!$C$17+(DATOS!$C$18-DATOS!$C$17)*(N($F14)+N($H14))/DATOS!$C$23),DATOS!$C$17+4*(DATOS!$C$18-DATOS!$C$17)*(N($F14)+N($H14))/DATOS!$C$23*(1-(N($F14)+N($H14))/DATOS!$C$23)))),INDEX($F$51:$F$54,$N14))) -> 0 | U14: =IF(AND($K14="OK",$E14="FIJA"),1,0) -> 0 | V14: =IF($K14="OK",1,0) -> 0 | W14: =IF($N14=0,0,INDEX($D$51:$D$54,$N14)) -> 0 | Y14: =($AB$6+DATOS!$AE$10+$DL$12)/$DL$11 -> 0.30012581 | Z14: =(DATOS!$AF$10+$DL$13)/$DL$11 -> 0.71744174 | AA14: =($AC$6+DATOS!$AI$10+$DL$12)/$DL$11 -> 1.0127355 | AB14: =(DATOS!$AJ$10+$DL$13)/$DL$11 -> 0.66863286 | AC14: =($AD$6+DATOS!$AM$10+$DL$12)/$DL$11 -> 1.8607898 | AD14: =(DATOS!$AN$10+$DL$13)/$DL$11 -> 0.69913841 | AE14: =($AE$6+DATOS!$AQ$10+$DL$12)/$DL$11 -> 2.9345851 | AF14: =(DATOS!$AR$10+$DL$13)/$DL$11 -> 0.69913841
B15: 9 | J15: =IF($K15="OK",$H15*$I15,0) -> 0 | K15: =IF($D15="","",IF(OR($F15="",$G15=""),"FALTA POSICIÓN",IF(OR(N($H15)<=0,N($I15)<=0),"FALTA TAMAÑO",IF($E15="","FALTA TIPO",IF(OR(N($F15)<0,N($G15)<0,N($F15)+N($H15)>$W15+0.001),"SE SALE A LO LARGO",IF(N($G15)+N($I15)>MIN($S15,$T15)+0.001,"SE SALE POR ARRIBA","OK")))))) | N15: =IF($D15="",0,VALUE(MID($D15,6,1))) -> 0 | O15: =IF($K15="OK",N($F15),0) -> 0 | P15: =IF($K15="OK",N($F15)+N($H15),0) -> 0 | Q15: =IF($K15="OK",N($G15),0) -> 0 | R15: =IF($K15="OK",N($G15)+N($I15),0) -> 0 | S15: =IF($N15=0,0,IF(INDEX($E$51:$E$54,$N15)="SÍ",IF(DATOS!$C$14="PLANO",DATOS!$C$17,IF(DATOS!$C$14="DOS AGUAS",DATOS!$C$17+(DATOS!$C$18-DATOS!$C$17)*(1-ABS(2*(N($F15))/DATOS!$C$23-1)),IF(DATOS!$C$14="UN AGUA",IF(N(DATOS!$C$25)=0,DATOS!$C$18-(DATOS!$C$18-DATOS!$C$17)*(N($F15))/DATOS!$C$23,DATOS!$C$17+(DATOS!$C$18-DATOS!$C$17)*(N($F15))/DATOS!$C$23),DATOS!$C$17+4*(DATOS!$C$18-DATOS!$C$17)*(N($F15))/DATOS!$C$23*(1-(N($F15))/DATOS!$C$23)))),INDEX($F$51:$F$54,$N15))) -> 0 | T15: =IF($N15=0,0,IF(INDEX($E$51:$E$54,$N15)="SÍ",IF(DATOS!$C$14="PLANO",DATOS!$C$17,IF(DATOS!$C$14="DOS AGUAS",DATOS!$C$17+(DATOS!$C$18-DATOS!$C$17)*(1-ABS(2*(N($F15)+N($H15))/DATOS!$C$23-1)),IF(DATOS!$C$14="UN AGUA",IF(N(DATOS!$C$25)=0,DATOS!$C$18-(DATOS!$C$18-DATOS!$C$17)*(N($F15)+N($H15))/DATOS!$C$23,DATOS!$C$17+(DATOS!$C$18-DATOS!$C$17)*(N($F15)+N($H15))/DATOS!$C$23),DATOS!$C$17+4*(DATOS!$C$18-DATOS!$C$17)*(N($F15)+N($H15))/DATOS!$C$23*(1-(N($F15)+N($H15))/DATOS!$C$23)))),INDEX($F$51:$F$54,$N15))) -> 0 | U15: =IF(AND($K15="OK",$E15="FIJA"),1,0) -> 0 | V15: =IF($K15="OK",1,0) -> 0 | W15: =IF($N15=0,0,INDEX($D$51:$D$54,$N15)) -> 0 | Y15: =($AB$6+DATOS!$AE$11+$DL$12)/$DL$11 -> 0.22325182 | Z15: =(DATOS!$AF$11+$DL$13)/$DL$11 -> 0.71744174 | AA15: =($AC$6+DATOS!$AI$11+$DL$12)/$DL$11 -> 0.93586148 | AB15: =(DATOS!$AJ$11+$DL$13)/$DL$11 -> 0.66863286 | AC15: =($AD$6+DATOS!$AM$11+$DL$12)/$DL$11 -> 1.7387676 | AD15: =(DATOS!$AN$11+$DL$13)/$DL$11 -> 0.70523952 | AE15: =($AE$6+DATOS!$AQ$11+$DL$12)/$DL$11 -> 2.8125629 | AF15: =(DATOS!$AR$11+$DL$13)/$DL$11 -> 0.70523952
B16: 10 | J16: =IF($K16="OK",$H16*$I16,0) -> 0 | K16: =IF($D16="","",IF(OR($F16="",$G16=""),"FALTA POSICIÓN",IF(OR(N($H16)<=0,N($I16)<=0),"FALTA TAMAÑO",IF($E16="","FALTA TIPO",IF(OR(N($F16)<0,N($G16)<0,N($F16)+N($H16)>$W16+0.001),"SE SALE A LO LARGO",IF(N($G16)+N($I16)>MIN($S16,$T16)+0.001,"SE SALE POR ARRIBA","OK")))))) | N16: =IF($D16="",0,VALUE(MID($D16,6,1))) -> 0 | O16: =IF($K16="OK",N($F16),0) -> 0 | P16: =IF($K16="OK",N($F16)+N($H16),0) -> 0 | Q16: =IF($K16="OK",N($G16),0) -> 0 | R16: =IF($K16="OK",N($G16)+N($I16),0) -> 0 | S16: =IF($N16=0,0,IF(INDEX($E$51:$E$54,$N16)="SÍ",IF(DATOS!$C$14="PLANO",DATOS!$C$17,IF(DATOS!$C$14="DOS AGUAS",DATOS!$C$17+(DATOS!$C$18-DATOS!$C$17)*(1-ABS(2*(N($F16))/DATOS!$C$23-1)),IF(DATOS!$C$14="UN AGUA",IF(N(DATOS!$C$25)=0,DATOS!$C$18-(DATOS!$C$18-DATOS!$C$17)*(N($F16))/DATOS!$C$23,DATOS!$C$17+(DATOS!$C$18-DATOS!$C$17)*(N($F16))/DATOS!$C$23),DATOS!$C$17+4*(DATOS!$C$18-DATOS!$C$17)*(N($F16))/DATOS!$C$23*(1-(N($F16))/DATOS!$C$23)))),INDEX($F$51:$F$54,$N16))) -> 0 | T16: =IF($N16=0,0,IF(INDEX($E$51:$E$54,$N16)="SÍ",IF(DATOS!$C$14="PLANO",DATOS!$C$17,IF(DATOS!$C$14="DOS AGUAS",DATOS!$C$17+(DATOS!$C$18-DATOS!$C$17)*(1-ABS(2*(N($F16)+N($H16))/DATOS!$C$23-1)),IF(DATOS!$C$14="UN AGUA",IF(N(DATOS!$C$25)=0,DATOS!$C$18-(DATOS!$C$18-DATOS!$C$17)*(N($F16)+N($H16))/DATOS!$C$23,DATOS!$C$17+(DATOS!$C$18-DATOS!$C$17)*(N($F16)+N($H16))/DATOS!$C$23),DATOS!$C$17+4*(DATOS!$C$18-DATOS!$C$17)*(N($F16)+N($H16))/DATOS!$C$23*(1-(N($F16)+N($H16))/DATOS!$C$23)))),INDEX($F$51:$F$54,$N16))) -> 0 | U16: =IF(AND($K16="OK",$E16="FIJA"),1,0) -> 0 | V16: =IF($K16="OK",1,0) -> 0 | W16: =IF($N16=0,0,INDEX($D$51:$D$54,$N16)) -> 0 | Y16: =($AB$6+DATOS!$AE$12+$DL$12)/$DL$11 -> 0.14637783 | Z16: =(DATOS!$AF$12+$DL$13)/$DL$11 -> 0.71744174 | AA16: =($AC$6+DATOS!$AI$12+$DL$12)/$DL$11 -> 0.85898749 | AB16: =(DATOS!$AJ$12+$DL$13)/$DL$11 -> 0.66863286 | AC16: =($AD$6+DATOS!$AM$12+$DL$12)/$DL$11 -> 1.6167454 | AD16: =(DATOS!$AN$12+$DL$13)/$DL$11 -> 0.71134063 | AE16: =($AE$6+DATOS!$AQ$12+$DL$12)/$DL$11 -> 2.6905407 | AF16: =(DATOS!$AR$12+$DL$13)/$DL$11 -> 0.71134063
B17: 11 | J17: =IF($K17="OK",$H17*$I17,0) -> 0 | K17: =IF($D17="","",IF(OR($F17="",$G17=""),"FALTA POSICIÓN",IF(OR(N($H17)<=0,N($I17)<=0),"FALTA TAMAÑO",IF($E17="","FALTA TIPO",IF(OR(N($F17)<0,N($G17)<0,N($F17)+N($H17)>$W17+0.001),"SE SALE A LO LARGO",IF(N($G17)+N($I17)>MIN($S17,$T17)+0.001,"SE SALE POR ARRIBA","OK")))))) | N17: =IF($D17="",0,VALUE(MID($D17,6,1))) -> 0 | O17: =IF($K17="OK",N($F17),0) -> 0 | P17: =IF($K17="OK",N($F17)+N($H17),0) -> 0 | Q17: =IF($K17="OK",N($G17),0) -> 0 | R17: =IF($K17="OK",N($G17)+N($I17),0) -> 0 | S17: =IF($N17=0,0,IF(INDEX($E$51:$E$54,$N17)="SÍ",IF(DATOS!$C$14="PLANO",DATOS!$C$17,IF(DATOS!$C$14="DOS AGUAS",DATOS!$C$17+(DATOS!$C$18-DATOS!$C$17)*(1-ABS(2*(N($F17))/DATOS!$C$23-1)),IF(DATOS!$C$14="UN AGUA",IF(N(DATOS!$C$25)=0,DATOS!$C$18-(DATOS!$C$18-DATOS!$C$17)*(N($F17))/DATOS!$C$23,DATOS!$C$17+(DATOS!$C$18-DATOS!$C$17)*(N($F17))/DATOS!$C$23),DATOS!$C$17+4*(DATOS!$C$18-DATOS!$C$17)*(N($F17))/DATOS!$C$23*(1-(N($F17))/DATOS!$C$23)))),INDEX($F$51:$F$54,$N17))) -> 0 | T17: =IF($N17=0,0,IF(INDEX($E$51:$E$54,$N17)="SÍ",IF(DATOS!$C$14="PLANO",DATOS!$C$17,IF(DATOS!$C$14="DOS AGUAS",DATOS!$C$17+(DATOS!$C$18-DATOS!$C$17)*(1-ABS(2*(N($F17)+N($H17))/DATOS!$C$23-1)),IF(DATOS!$C$14="UN AGUA",IF(N(DATOS!$C$25)=0,DATOS!$C$18-(DATOS!$C$18-DATOS!$C$17)*(N($F17)+N($H17))/DATOS!$C$23,DATOS!$C$17+(DATOS!$C$18-DATOS!$C$17)*(N($F17)+N($H17))/DATOS!$C$23),DATOS!$C$17+4*(DATOS!$C$18-DATOS!$C$17)*(N($F17)+N($H17))/DATOS!$C$23*(1-(N($F17)+N($H17))/DATOS!$C$23)))),INDEX($F$51:$F$54,$N17))) -> 0 | U17: =IF(AND($K17="OK",$E17="FIJA"),1,0) -> 0 | V17: =IF($K17="OK",1,0) -> 0 | W17: =IF($N17=0,0,INDEX($D$51:$D$54,$N17)) -> 0 | Y17: =($AB$6+DATOS!$AE$13+$DL$12)/$DL$11 -> 0.069503846 | Z17: =(DATOS!$AF$13+$DL$13)/$DL$11 -> 0.71744174 | AA17: =($AC$6+DATOS!$AI$13+$DL$12)/$DL$11 -> 0.7821135 | AB17: =(DATOS!$AJ$13+$DL$13)/$DL$11 -> 0.66863286 | AC17: =($AD$6+DATOS!$AM$13+$DL$12)/$DL$11 -> 1.4947232 | AD17: =(DATOS!$AN$13+$DL$13)/$DL$11 -> 0.71744174 | AE17: =($AE$6+DATOS!$AQ$13+$DL$12)/$DL$11 -> 2.5685185 | AF17: =(DATOS!$AR$13+$DL$13)/$DL$11 -> 0.71744174
B18: 12 | J18: =IF($K18="OK",$H18*$I18,0) -> 0 | K18: =IF($D18="","",IF(OR($F18="",$G18=""),"FALTA POSICIÓN",IF(OR(N($H18)<=0,N($I18)<=0),"FALTA TAMAÑO",IF($E18="","FALTA TIPO",IF(OR(N($F18)<0,N($G18)<0,N($F18)+N($H18)>$W18+0.001),"SE SALE A LO LARGO",IF(N($G18)+N($I18)>MIN($S18,$T18)+0.001,"SE SALE POR ARRIBA","OK")))))) | N18: =IF($D18="",0,VALUE(MID($D18,6,1))) -> 0 | O18: =IF($K18="OK",N($F18),0) -> 0 | P18: =IF($K18="OK",N($F18)+N($H18),0) -> 0 | Q18: =IF($K18="OK",N($G18),0) -> 0 | R18: =IF($K18="OK",N($G18)+N($I18),0) -> 0 | S18: =IF($N18=0,0,IF(INDEX($E$51:$E$54,$N18)="SÍ",IF(DATOS!$C$14="PLANO",DATOS!$C$17,IF(DATOS!$C$14="DOS AGUAS",DATOS!$C$17+(DATOS!$C$18-DATOS!$C$17)*(1-ABS(2*(N($F18))/DATOS!$C$23-1)),IF(DATOS!$C$14="UN AGUA",IF(N(DATOS!$C$25)=0,DATOS!$C$18-(DATOS!$C$18-DATOS!$C$17)*(N($F18))/DATOS!$C$23,DATOS!$C$17+(DATOS!$C$18-DATOS!$C$17)*(N($F18))/DATOS!$C$23),DATOS!$C$17+4*(DATOS!$C$18-DATOS!$C$17)*(N($F18))/DATOS!$C$23*(1-(N($F18))/DATOS!$C$23)))),INDEX($F$51:$F$54,$N18))) -> 0 | T18: =IF($N18=0,0,IF(INDEX($E$51:$E$54,$N18)="SÍ",IF(DATOS!$C$14="PLANO",DATOS!$C$17,IF(DATOS!$C$14="DOS AGUAS",DATOS!$C$17+(DATOS!$C$18-DATOS!$C$17)*(1-ABS(2*(N($F18)+N($H18))/DATOS!$C$23-1)),IF(DATOS!$C$14="UN AGUA",IF(N(DATOS!$C$25)=0,DATOS!$C$18-(DATOS!$C$18-DATOS!$C$17)*(N($F18)+N($H18))/DATOS!$C$23,DATOS!$C$17+(DATOS!$C$18-DATOS!$C$17)*(N($F18)+N($H18))/DATOS!$C$23),DATOS!$C$17+4*(DATOS!$C$18-DATOS!$C$17)*(N($F18)+N($H18))/DATOS!$C$23*(1-(N($F18)+N($H18))/DATOS!$C$23)))),INDEX($F$51:$F$54,$N18))) -> 0 | U18: =IF(AND($K18="OK",$E18="FIJA"),1,0) -> 0 | V18: =IF($K18="OK",1,0) -> 0 | W18: =IF($N18=0,0,INDEX($D$51:$D$54,$N18)) -> 0 | Y18: =($AB$6+DATOS!$AE$14+$DL$12)/$DL$11 -> 0.069503846 | Z18: =(DATOS!$AF$14+$DL$13)/$DL$11 -> 0.069503846 | AA18: =($AC$6+DATOS!$AI$14+$DL$12)/$DL$11 -> 0.7821135 | AB18: =(DATOS!$AJ$14+$DL$13)/$DL$11 -> 0.069503846 | AC18: =($AD$6+DATOS!$AM$14+$DL$12)/$DL$11 -> 1.4947232 | AD18: =(DATOS!$AN$14+$DL$13)/$DL$11 -> 0.069503846 | AE18: =($AE$6+DATOS!$AQ$14+$DL$12)/$DL$11 -> 2.5685185 | AF18: =(DATOS!$AR$14+$DL$13)/$DL$11 -> 0.069503846
B19: 13 | J19: =IF($K19="OK",$H19*$I19,0) -> 0 | K19: =IF($D19="","",IF(OR($F19="",$G19=""),"FALTA POSICIÓN",IF(OR(N($H19)<=0,N($I19)<=0),"FALTA TAMAÑO",IF($E19="","FALTA TIPO",IF(OR(N($F19)<0,N($G19)<0,N($F19)+N($H19)>$W19+0.001),"SE SALE A LO LARGO",IF(N($G19)+N($I19)>MIN($S19,$T19)+0.001,"SE SALE POR ARRIBA","OK")))))) | N19: =IF($D19="",0,VALUE(MID($D19,6,1))) -> 0 | O19: =IF($K19="OK",N($F19),0) -> 0 | P19: =IF($K19="OK",N($F19)+N($H19),0) -> 0 | Q19: =IF($K19="OK",N($G19),0) -> 0 | R19: =IF($K19="OK",N($G19)+N($I19),0) -> 0 | S19: =IF($N19=0,0,IF(INDEX($E$51:$E$54,$N19)="SÍ",IF(DATOS!$C$14="PLANO",DATOS!$C$17,IF(DATOS!$C$14="DOS AGUAS",DATOS!$C$17+(DATOS!$C$18-DATOS!$C$17)*(1-ABS(2*(N($F19))/DATOS!$C$23-1)),IF(DATOS!$C$14="UN AGUA",IF(N(DATOS!$C$25)=0,DATOS!$C$18-(DATOS!$C$18-DATOS!$C$17)*(N($F19))/DATOS!$C$23,DATOS!$C$17+(DATOS!$C$18-DATOS!$C$17)*(N($F19))/DATOS!$C$23),DATOS!$C$17+4*(DATOS!$C$18-DATOS!$C$17)*(N($F19))/DATOS!$C$23*(1-(N($F19))/DATOS!$C$23)))),INDEX($F$51:$F$54,$N19))) -> 0 | T19: =IF($N19=0,0,IF(INDEX($E$51:$E$54,$N19)="SÍ",IF(DATOS!$C$14="PLANO",DATOS!$C$17,IF(DATOS!$C$14="DOS AGUAS",DATOS!$C$17+(DATOS!$C$18-DATOS!$C$17)*(1-ABS(2*(N($F19)+N($H19))/DATOS!$C$23-1)),IF(DATOS!$C$14="UN AGUA",IF(N(DATOS!$C$25)=0,DATOS!$C$18-(DATOS!$C$18-DATOS!$C$17)*(N($F19)+N($H19))/DATOS!$C$23,DATOS!$C$17+(DATOS!$C$18-DATOS!$C$17)*(N($F19)+N($H19))/DATOS!$C$23),DATOS!$C$17+4*(DATOS!$C$18-DATOS!$C$17)*(N($F19)+N($H19))/DATOS!$C$23*(1-(N($F19)+N($H19))/DATOS!$C$23)))),INDEX($F$51:$F$54,$N19))) -> 0 | U19: =IF(AND($K19="OK",$E19="FIJA"),1,0) -> 0 | V19: =IF($K19="OK",1,0) -> 0 | W19: =IF($N19=0,0,INDEX($D$51:$D$54,$N19)) -> 0
B20: 14 | J20: =IF($K20="OK",$H20*$I20,0) -> 0 | K20: =IF($D20="","",IF(OR($F20="",$G20=""),"FALTA POSICIÓN",IF(OR(N($H20)<=0,N($I20)<=0),"FALTA TAMAÑO",IF($E20="","FALTA TIPO",IF(OR(N($F20)<0,N($G20)<0,N($F20)+N($H20)>$W20+0.001),"SE SALE A LO LARGO",IF(N($G20)+N($I20)>MIN($S20,$T20)+0.001,"SE SALE POR ARRIBA","OK")))))) | N20: =IF($D20="",0,VALUE(MID($D20,6,1))) -> 0 | O20: =IF($K20="OK",N($F20),0) -> 0 | P20: =IF($K20="OK",N($F20)+N($H20),0) -> 0 | Q20: =IF($K20="OK",N($G20),0) -> 0 | R20: =IF($K20="OK",N($G20)+N($I20),0) -> 0 | S20: =IF($N20=0,0,IF(INDEX($E$51:$E$54,$N20)="SÍ",IF(DATOS!$C$14="PLANO",DATOS!$C$17,IF(DATOS!$C$14="DOS AGUAS",DATOS!$C$17+(DATOS!$C$18-DATOS!$C$17)*(1-ABS(2*(N($F20))/DATOS!$C$23-1)),IF(DATOS!$C$14="UN AGUA",IF(N(DATOS!$C$25)=0,DATOS!$C$18-(DATOS!$C$18-DATOS!$C$17)*(N($F20))/DATOS!$C$23,DATOS!$C$17+(DATOS!$C$18-DATOS!$C$17)*(N($F20))/DATOS!$C$23),DATOS!$C$17+4*(DATOS!$C$18-DATOS!$C$17)*(N($F20))/DATOS!$C$23*(1-(N($F20))/DATOS!$C$23)))),INDEX($F$51:$F$54,$N20))) -> 0 | T20: =IF($N20=0,0,IF(INDEX($E$51:$E$54,$N20)="SÍ",IF(DATOS!$C$14="PLANO",DATOS!$C$17,IF(DATOS!$C$14="DOS AGUAS",DATOS!$C$17+(DATOS!$C$18-DATOS!$C$17)*(1-ABS(2*(N($F20)+N($H20))/DATOS!$C$23-1)),IF(DATOS!$C$14="UN AGUA",IF(N(DATOS!$C$25)=0,DATOS!$C$18-(DATOS!$C$18-DATOS!$C$17)*(N($F20)+N($H20))/DATOS!$C$23,DATOS!$C$17+(DATOS!$C$18-DATOS!$C$17)*(N($F20)+N($H20))/DATOS!$C$23),DATOS!$C$17+4*(DATOS!$C$18-DATOS!$C$17)*(N($F20)+N($H20))/DATOS!$C$23*(1-(N($F20)+N($H20))/DATOS!$C$23)))),INDEX($F$51:$F$54,$N20))) -> 0 | U20: =IF(AND($K20="OK",$E20="FIJA"),1,0) -> 0 | V20: =IF($K20="OK",1,0) -> 0 | W20: =IF($N20=0,0,INDEX($D$51:$D$54,$N20)) -> 0
B21: 15 | J21: =IF($K21="OK",$H21*$I21,0) -> 0 | K21: =IF($D21="","",IF(OR($F21="",$G21=""),"FALTA POSICIÓN",IF(OR(N($H21)<=0,N($I21)<=0),"FALTA TAMAÑO",IF($E21="","FALTA TIPO",IF(OR(N($F21)<0,N($G21)<0,N($F21)+N($H21)>$W21+0.001),"SE SALE A LO LARGO",IF(N($G21)+N($I21)>MIN($S21,$T21)+0.001,"SE SALE POR ARRIBA","OK")))))) | N21: =IF($D21="",0,VALUE(MID($D21,6,1))) -> 0 | O21: =IF($K21="OK",N($F21),0) -> 0 | P21: =IF($K21="OK",N($F21)+N($H21),0) -> 0 | Q21: =IF($K21="OK",N($G21),0) -> 0 | R21: =IF($K21="OK",N($G21)+N($I21),0) -> 0 | S21: =IF($N21=0,0,IF(INDEX($E$51:$E$54,$N21)="SÍ",IF(DATOS!$C$14="PLANO",DATOS!$C$17,IF(DATOS!$C$14="DOS AGUAS",DATOS!$C$17+(DATOS!$C$18-DATOS!$C$17)*(1-ABS(2*(N($F21))/DATOS!$C$23-1)),IF(DATOS!$C$14="UN AGUA",IF(N(DATOS!$C$25)=0,DATOS!$C$18-(DATOS!$C$18-DATOS!$C$17)*(N($F21))/DATOS!$C$23,DATOS!$C$17+(DATOS!$C$18-DATOS!$C$17)*(N($F21))/DATOS!$C$23),DATOS!$C$17+4*(DATOS!$C$18-DATOS!$C$17)*(N($F21))/DATOS!$C$23*(1-(N($F21))/DATOS!$C$23)))),INDEX($F$51:$F$54,$N21))) -> 0 | T21: =IF($N21=0,0,IF(INDEX($E$51:$E$54,$N21)="SÍ",IF(DATOS!$C$14="PLANO",DATOS!$C$17,IF(DATOS!$C$14="DOS AGUAS",DATOS!$C$17+(DATOS!$C$18-DATOS!$C$17)*(1-ABS(2*(N($F21)+N($H21))/DATOS!$C$23-1)),IF(DATOS!$C$14="UN AGUA",IF(N(DATOS!$C$25)=0,DATOS!$C$18-(DATOS!$C$18-DATOS!$C$17)*(N($F21)+N($H21))/DATOS!$C$23,DATOS!$C$17+(DATOS!$C$18-DATOS!$C$17)*(N($F21)+N($H21))/DATOS!$C$23),DATOS!$C$17+4*(DATOS!$C$18-DATOS!$C$17)*(N($F21)+N($H21))/DATOS!$C$23*(1-(N($F21)+N($H21))/DATOS!$C$23)))),INDEX($F$51:$F$54,$N21))) -> 0 | U21: =IF(AND($K21="OK",$E21="FIJA"),1,0) -> 0 | V21: =IF($K21="OK",1,0) -> 0 | W21: =IF($N21=0,0,INDEX($D$51:$D$54,$N21)) -> 0
B22: 16 | J22: =IF($K22="OK",$H22*$I22,0) -> 0 | K22: =IF($D22="","",IF(OR($F22="",$G22=""),"FALTA POSICIÓN",IF(OR(N($H22)<=0,N($I22)<=0),"FALTA TAMAÑO",IF($E22="","FALTA TIPO",IF(OR(N($F22)<0,N($G22)<0,N($F22)+N($H22)>$W22+0.001),"SE SALE A LO LARGO",IF(N($G22)+N($I22)>MIN($S22,$T22)+0.001,"SE SALE POR ARRIBA","OK")))))) | N22: =IF($D22="",0,VALUE(MID($D22,6,1))) -> 0 | O22: =IF($K22="OK",N($F22),0) -> 0 | P22: =IF($K22="OK",N($F22)+N($H22),0) -> 0 | Q22: =IF($K22="OK",N($G22),0) -> 0 | R22: =IF($K22="OK",N($G22)+N($I22),0) -> 0 | S22: =IF($N22=0,0,IF(INDEX($E$51:$E$54,$N22)="SÍ",IF(DATOS!$C$14="PLANO",DATOS!$C$17,IF(DATOS!$C$14="DOS AGUAS",DATOS!$C$17+(DATOS!$C$18-DATOS!$C$17)*(1-ABS(2*(N($F22))/DATOS!$C$23-1)),IF(DATOS!$C$14="UN AGUA",IF(N(DATOS!$C$25)=0,DATOS!$C$18-(DATOS!$C$18-DATOS!$C$17)*(N($F22))/DATOS!$C$23,DATOS!$C$17+(DATOS!$C$18-DATOS!$C$17)*(N($F22))/DATOS!$C$23),DATOS!$C$17+4*(DATOS!$C$18-DATOS!$C$17)*(N($F22))/DATOS!$C$23*(1-(N($F22))/DATOS!$C$23)))),INDEX($F$51:$F$54,$N22))) -> 0 | T22: =IF($N22=0,0,IF(INDEX($E$51:$E$54,$N22)="SÍ",IF(DATOS!$C$14="PLANO",DATOS!$C$17,IF(DATOS!$C$14="DOS AGUAS",DATOS!$C$17+(DATOS!$C$18-DATOS!$C$17)*(1-ABS(2*(N($F22)+N($H22))/DATOS!$C$23-1)),IF(DATOS!$C$14="UN AGUA",IF(N(DATOS!$C$25)=0,DATOS!$C$18-(DATOS!$C$18-DATOS!$C$17)*(N($F22)+N($H22))/DATOS!$C$23,DATOS!$C$17+(DATOS!$C$18-DATOS!$C$17)*(N($F22)+N($H22))/DATOS!$C$23),DATOS!$C$17+4*(DATOS!$C$18-DATOS!$C$17)*(N($F22)+N($H22))/DATOS!$C$23*(1-(N($F22)+N($H22))/DATOS!$C$23)))),INDEX($F$51:$F$54,$N22))) -> 0 | U22: =IF(AND($K22="OK",$E22="FIJA"),1,0) -> 0 | V22: =IF($K22="OK",1,0) -> 0 | W22: =IF($N22=0,0,INDEX($D$51:$D$54,$N22)) -> 0
B23: 17 | J23: =IF($K23="OK",$H23*$I23,0) -> 0 | K23: =IF($D23="","",IF(OR($F23="",$G23=""),"FALTA POSICIÓN",IF(OR(N($H23)<=0,N($I23)<=0),"FALTA TAMAÑO",IF($E23="","FALTA TIPO",IF(OR(N($F23)<0,N($G23)<0,N($F23)+N($H23)>$W23+0.001),"SE SALE A LO LARGO",IF(N($G23)+N($I23)>MIN($S23,$T23)+0.001,"SE SALE POR ARRIBA","OK")))))) | N23: =IF($D23="",0,VALUE(MID($D23,6,1))) -> 0 | O23: =IF($K23="OK",N($F23),0) -> 0 | P23: =IF($K23="OK",N($F23)+N($H23),0) -> 0 | Q23: =IF($K23="OK",N($G23),0) -> 0 | R23: =IF($K23="OK",N($G23)+N($I23),0) -> 0 | S23: =IF($N23=0,0,IF(INDEX($E$51:$E$54,$N23)="SÍ",IF(DATOS!$C$14="PLANO",DATOS!$C$17,IF(DATOS!$C$14="DOS AGUAS",DATOS!$C$17+(DATOS!$C$18-DATOS!$C$17)*(1-ABS(2*(N($F23))/DATOS!$C$23-1)),IF(DATOS!$C$14="UN AGUA",IF(N(DATOS!$C$25)=0,DATOS!$C$18-(DATOS!$C$18-DATOS!$C$17)*(N($F23))/DATOS!$C$23,DATOS!$C$17+(DATOS!$C$18-DATOS!$C$17)*(N($F23))/DATOS!$C$23),DATOS!$C$17+4*(DATOS!$C$18-DATOS!$C$17)*(N($F23))/DATOS!$C$23*(1-(N($F23))/DATOS!$C$23)))),INDEX($F$51:$F$54,$N23))) -> 0 | T23: =IF($N23=0,0,IF(INDEX($E$51:$E$54,$N23)="SÍ",IF(DATOS!$C$14="PLANO",DATOS!$C$17,IF(DATOS!$C$14="DOS AGUAS",DATOS!$C$17+(DATOS!$C$18-DATOS!$C$17)*(1-ABS(2*(N($F23)+N($H23))/DATOS!$C$23-1)),IF(DATOS!$C$14="UN AGUA",IF(N(DATOS!$C$25)=0,DATOS!$C$18-(DATOS!$C$18-DATOS!$C$17)*(N($F23)+N($H23))/DATOS!$C$23,DATOS!$C$17+(DATOS!$C$18-DATOS!$C$17)*(N($F23)+N($H23))/DATOS!$C$23),DATOS!$C$17+4*(DATOS!$C$18-DATOS!$C$17)*(N($F23)+N($H23))/DATOS!$C$23*(1-(N($F23)+N($H23))/DATOS!$C$23)))),INDEX($F$51:$F$54,$N23))) -> 0 | U23: =IF(AND($K23="OK",$E23="FIJA"),1,0) -> 0 | V23: =IF($K23="OK",1,0) -> 0 | W23: =IF($N23=0,0,INDEX($D$51:$D$54,$N23)) -> 0
B24: 18 | J24: =IF($K24="OK",$H24*$I24,0) -> 0 | K24: =IF($D24="","",IF(OR($F24="",$G24=""),"FALTA POSICIÓN",IF(OR(N($H24)<=0,N($I24)<=0),"FALTA TAMAÑO",IF($E24="","FALTA TIPO",IF(OR(N($F24)<0,N($G24)<0,N($F24)+N($H24)>$W24+0.001),"SE SALE A LO LARGO",IF(N($G24)+N($I24)>MIN($S24,$T24)+0.001,"SE SALE POR ARRIBA","OK")))))) | N24: =IF($D24="",0,VALUE(MID($D24,6,1))) -> 0 | O24: =IF($K24="OK",N($F24),0) -> 0 | P24: =IF($K24="OK",N($F24)+N($H24),0) -> 0 | Q24: =IF($K24="OK",N($G24),0) -> 0 | R24: =IF($K24="OK",N($G24)+N($I24),0) -> 0 | S24: =IF($N24=0,0,IF(INDEX($E$51:$E$54,$N24)="SÍ",IF(DATOS!$C$14="PLANO",DATOS!$C$17,IF(DATOS!$C$14="DOS AGUAS",DATOS!$C$17+(DATOS!$C$18-DATOS!$C$17)*(1-ABS(2*(N($F24))/DATOS!$C$23-1)),IF(DATOS!$C$14="UN AGUA",IF(N(DATOS!$C$25)=0,DATOS!$C$18-(DATOS!$C$18-DATOS!$C$17)*(N($F24))/DATOS!$C$23,DATOS!$C$17+(DATOS!$C$18-DATOS!$C$17)*(N($F24))/DATOS!$C$23),DATOS!$C$17+4*(DATOS!$C$18-DATOS!$C$17)*(N($F24))/DATOS!$C$23*(1-(N($F24))/DATOS!$C$23)))),INDEX($F$51:$F$54,$N24))) -> 0 | T24: =IF($N24=0,0,IF(INDEX($E$51:$E$54,$N24)="SÍ",IF(DATOS!$C$14="PLANO",DATOS!$C$17,IF(DATOS!$C$14="DOS AGUAS",DATOS!$C$17+(DATOS!$C$18-DATOS!$C$17)*(1-ABS(2*(N($F24)+N($H24))/DATOS!$C$23-1)),IF(DATOS!$C$14="UN AGUA",IF(N(DATOS!$C$25)=0,DATOS!$C$18-(DATOS!$C$18-DATOS!$C$17)*(N($F24)+N($H24))/DATOS!$C$23,DATOS!$C$17+(DATOS!$C$18-DATOS!$C$17)*(N($F24)+N($H24))/DATOS!$C$23),DATOS!$C$17+4*(DATOS!$C$18-DATOS!$C$17)*(N($F24)+N($H24))/DATOS!$C$23*(1-(N($F24)+N($H24))/DATOS!$C$23)))),INDEX($F$51:$F$54,$N24))) -> 0 | U24: =IF(AND($K24="OK",$E24="FIJA"),1,0) -> 0 | V24: =IF($K24="OK",1,0) -> 0 | W24: =IF($N24=0,0,INDEX($D$51:$D$54,$N24)) -> 0
B25: 19 | J25: =IF($K25="OK",$H25*$I25,0) -> 0 | K25: =IF($D25="","",IF(OR($F25="",$G25=""),"FALTA POSICIÓN",IF(OR(N($H25)<=0,N($I25)<=0),"FALTA TAMAÑO",IF($E25="","FALTA TIPO",IF(OR(N($F25)<0,N($G25)<0,N($F25)+N($H25)>$W25+0.001),"SE SALE A LO LARGO",IF(N($G25)+N($I25)>MIN($S25,$T25)+0.001,"SE SALE POR ARRIBA","OK")))))) | N25: =IF($D25="",0,VALUE(MID($D25,6,1))) -> 0 | O25: =IF($K25="OK",N($F25),0) -> 0 | P25: =IF($K25="OK",N($F25)+N($H25),0) -> 0 | Q25: =IF($K25="OK",N($G25),0) -> 0 | R25: =IF($K25="OK",N($G25)+N($I25),0) -> 0 | S25: =IF($N25=0,0,IF(INDEX($E$51:$E$54,$N25)="SÍ",IF(DATOS!$C$14="PLANO",DATOS!$C$17,IF(DATOS!$C$14="DOS AGUAS",DATOS!$C$17+(DATOS!$C$18-DATOS!$C$17)*(1-ABS(2*(N($F25))/DATOS!$C$23-1)),IF(DATOS!$C$14="UN AGUA",IF(N(DATOS!$C$25)=0,DATOS!$C$18-(DATOS!$C$18-DATOS!$C$17)*(N($F25))/DATOS!$C$23,DATOS!$C$17+(DATOS!$C$18-DATOS!$C$17)*(N($F25))/DATOS!$C$23),DATOS!$C$17+4*(DATOS!$C$18-DATOS!$C$17)*(N($F25))/DATOS!$C$23*(1-(N($F25))/DATOS!$C$23)))),INDEX($F$51:$F$54,$N25))) -> 0 | T25: =IF($N25=0,0,IF(INDEX($E$51:$E$54,$N25)="SÍ",IF(DATOS!$C$14="PLANO",DATOS!$C$17,IF(DATOS!$C$14="DOS AGUAS",DATOS!$C$17+(DATOS!$C$18-DATOS!$C$17)*(1-ABS(2*(N($F25)+N($H25))/DATOS!$C$23-1)),IF(DATOS!$C$14="UN AGUA",IF(N(DATOS!$C$25)=0,DATOS!$C$18-(DATOS!$C$18-DATOS!$C$17)*(N($F25)+N($H25))/DATOS!$C$23,DATOS!$C$17+(DATOS!$C$18-DATOS!$C$17)*(N($F25)+N($H25))/DATOS!$C$23),DATOS!$C$17+4*(DATOS!$C$18-DATOS!$C$17)*(N($F25)+N($H25))/DATOS!$C$23*(1-(N($F25)+N($H25))/DATOS!$C$23)))),INDEX($F$51:$F$54,$N25))) -> 0 | U25: =IF(AND($K25="OK",$E25="FIJA"),1,0) -> 0 | V25: =IF($K25="OK",1,0) -> 0 | W25: =IF($N25=0,0,INDEX($D$51:$D$54,$N25)) -> 0
B26: 20 | J26: =IF($K26="OK",$H26*$I26,0) -> 0 | K26: =IF($D26="","",IF(OR($F26="",$G26=""),"FALTA POSICIÓN",IF(OR(N($H26)<=0,N($I26)<=0),"FALTA TAMAÑO",IF($E26="","FALTA TIPO",IF(OR(N($F26)<0,N($G26)<0,N($F26)+N($H26)>$W26+0.001),"SE SALE A LO LARGO",IF(N($G26)+N($I26)>MIN($S26,$T26)+0.001,"SE SALE POR ARRIBA","OK")))))) | N26: =IF($D26="",0,VALUE(MID($D26,6,1))) -> 0 | O26: =IF($K26="OK",N($F26),0) -> 0 | P26: =IF($K26="OK",N($F26)+N($H26),0) -> 0 | Q26: =IF($K26="OK",N($G26),0) -> 0 | R26: =IF($K26="OK",N($G26)+N($I26),0) -> 0 | S26: =IF($N26=0,0,IF(INDEX($E$51:$E$54,$N26)="SÍ",IF(DATOS!$C$14="PLANO",DATOS!$C$17,IF(DATOS!$C$14="DOS AGUAS",DATOS!$C$17+(DATOS!$C$18-DATOS!$C$17)*(1-ABS(2*(N($F26))/DATOS!$C$23-1)),IF(DATOS!$C$14="UN AGUA",IF(N(DATOS!$C$25)=0,DATOS!$C$18-(DATOS!$C$18-DATOS!$C$17)*(N($F26))/DATOS!$C$23,DATOS!$C$17+(DATOS!$C$18-DATOS!$C$17)*(N($F26))/DATOS!$C$23),DATOS!$C$17+4*(DATOS!$C$18-DATOS!$C$17)*(N($F26))/DATOS!$C$23*(1-(N($F26))/DATOS!$C$23)))),INDEX($F$51:$F$54,$N26))) -> 0 | T26: =IF($N26=0,0,IF(INDEX($E$51:$E$54,$N26)="SÍ",IF(DATOS!$C$14="PLANO",DATOS!$C$17,IF(DATOS!$C$14="DOS AGUAS",DATOS!$C$17+(DATOS!$C$18-DATOS!$C$17)*(1-ABS(2*(N($F26)+N($H26))/DATOS!$C$23-1)),IF(DATOS!$C$14="UN AGUA",IF(N(DATOS!$C$25)=0,DATOS!$C$18-(DATOS!$C$18-DATOS!$C$17)*(N($F26)+N($H26))/DATOS!$C$23,DATOS!$C$17+(DATOS!$C$18-DATOS!$C$17)*(N($F26)+N($H26))/DATOS!$C$23),DATOS!$C$17+4*(DATOS!$C$18-DATOS!$C$17)*(N($F26)+N($H26))/DATOS!$C$23*(1-(N($F26)+N($H26))/DATOS!$C$23)))),INDEX($F$51:$F$54,$N26))) -> 0 | U26: =IF(AND($K26="OK",$E26="FIJA"),1,0) -> 0 | V26: =IF($K26="OK",1,0) -> 0 | W26: =IF($N26=0,0,INDEX($D$51:$D$54,$N26)) -> 0
B27: =IF(COUNTA($D$7:$D$26)=0,"Sin aberturas: nave cerrada.",IF(COUNTIF($K$7:$K$26,"OK")=COUNTA($D$7:$D$26),"OK: todas las aberturas caben en su muro. Revisa que no se encimen entre sí (la hoja no lo checa).","OJO: hay aberturas con problema (columna K). Mientras no digan OK no cuentan.")) -> OK: todas las aberturas caben en su muro. Revisa que no se encimen entre sí (la hoja no lo checa).
B29: B. ELEVACIÓN DE LOS CUATRO MUROS (X o Z crecen a la derecha, como en STAAD)
B30: Rojo = abertura FIJA; naranja punteado = OPERABLE (puerta o cortina). Cada muro se dibuja visto desde fuera con su coordenada creciendo a la derecha: Muros 1 y 2 con X, Muros 3 y 4 con Z. Así checas de un vistazo que cada abertura quedó donde va.
B48: C. LOS CUATRO MUROS: GEOMETRÍA Y ÁREA ABIERTA EN CADA ESCENARIO
B49: Un muro con 30% o más de su área abierta hace que la nave cuente como abierta de ese lado (NTV 2.1, pág. 2) y obliga a considerar presión interior (4.4, pág. 7). El área de los hastiales incluye la parte bajo el techo. CERR = operables cerradas; PA = operables abiertas.
B50: # | C50: Muro | D50: Longitud (m) | E50: ¿Hastial? | F50: Altura (m) | G50: Área (m²) | H50: Área arriba de 10 m (m²) | I50: Abierta CERR (m²) | J50: % abierto CERR | K50: Abierta PA (m²) | L50: % abierto PA | M50: ¿≥ 30%? CERR | N50: ¿≥ 30%? PA | O50: Maciza CERR (m²) | P50: Maciza PA (m²)
B51: 1 | C51: Muro 1 — atrás (Z = 0) | D51: =DATOS!$C$12 -> 10.08 | E51: =IF(AND(DATOS!$C$14<>"PLANO",DATOS!$C$22="X"),"SÍ","NO") -> NO | F51: =IF($E51="SÍ",DATOS!$C$21,IF(DATOS!$C$14="PLANO",DATOS!$C$17,IF(DATOS!$C$14="DOS AGUAS",DATOS!$C$17+(DATOS!$C$18-DATOS!$C$17)*(1-ABS(2*(0)/DATOS!$C$23-1)),IF(DATOS!$C$14="UN AGUA",IF(N(DATOS!$C$25)=0,DATOS!$C$18-(DATOS!$C$18-DATOS!$C$17)*(0)/DATOS!$C$23,DATOS!$C$17+(DATOS!$C$18-DATOS!$C$17)*(0)/DATOS!$C$23),DATOS!$C$17+4*(DATOS!$C$18-DATOS!$C$17)*(0)/DATOS!$C$23*(1-(0)/DATOS!$C$23))))) -> 10.62 | G51: =IF($E51="SÍ",IF(DATOS!$C$14="CURVO",DATOS!$C$23*DATOS!$C$17+2/3*DATOS!$C$23*(DATOS!$C$18-DATOS!$C$17),DATOS!$C$23*(DATOS!$C$17+DATOS!$C$18)/2),$D51*$F51) -> 107.0496 | H51: =IF($E51="SÍ",DATOS!$C$23/8*(SUMPRODUCT((DATOS!$AB$3:$AB$11-10+ABS(DATOS!$AB$3:$AB$11-10))/2)-(((DATOS!$AB$3-10)+ABS(DATOS!$AB$3-10))/2+((DATOS!$AB$11-10)+ABS(DATOS!$AB$11-10))/2)/2),$D51*MAX(0,$F51-10)) -> 6.2496 | I51: =SUMPRODUCT(($N$7:$N$26=$B51)*$U$7:$U$26*$J$7:$J$26) -> 0 | J51: =IF($G51>0,$I51/$G51,0) -> 0 | K51: =SUMPRODUCT(($N$7:$N$26=$B51)*$V$7:$V$26*$J$7:$J$26) -> 35.416488 | L51: =IF($G51>0,$K51/$G51,0) -> 0.33084185 | M51: =IF($J51>=0.3,"SÍ","NO") -> NO | N51: =IF($L51>=0.3,"SÍ","NO") -> SÍ | O51: =MAX(0,$G51-$I51) -> 107.0496 | P51: =MAX(0,$G51-$K51) -> 71.633112
B52: 2 | C52: Muro 2 — frente (Z = L) | D52: =DATOS!$C$12 -> 10.08 | E52: =IF(AND(DATOS!$C$14<>"PLANO",DATOS!$C$22="X"),"SÍ","NO") -> NO | F52: =IF($E52="SÍ",DATOS!$C$21,IF(DATOS!$C$14="PLANO",DATOS!$C$17,IF(DATOS!$C$14="DOS AGUAS",DATOS!$C$17+(DATOS!$C$18-DATOS!$C$17)*(1-ABS(2*(DATOS!$C$23)/DATOS!$C$23-1)),IF(DATOS!$C$14="UN AGUA",IF(N(DATOS!$C$25)=0,DATOS!$C$18-(DATOS!$C$18-DATOS!$C$17)*(DATOS!$C$23)/DATOS!$C$23,DATOS!$C$17+(DATOS!$C$18-DATOS!$C$17)*(DATOS!$C$23)/DATOS!$C$23),DATOS!$C$17+4*(DATOS!$C$18-DATOS!$C$17)*(DATOS!$C$23)/DATOS!$C$23*(1-(DATOS!$C$23)/DATOS!$C$23))))) -> 9.82 | G52: =IF($E52="SÍ",IF(DATOS!$C$14="CURVO",DATOS!$C$23*DATOS!$C$17+2/3*DATOS!$C$23*(DATOS!$C$18-DATOS!$C$17),DATOS!$C$23*(DATOS!$C$17+DATOS!$C$18)/2),$D52*$F52) -> 98.9856 | H52: =IF($E52="SÍ",DATOS!$C$23/8*(SUMPRODUCT((DATOS!$AB$3:$AB$11-10+ABS(DATOS!$AB$3:$AB$11-10))/2)-(((DATOS!$AB$3-10)+ABS(DATOS!$AB$3-10))/2+((DATOS!$AB$11-10)+ABS(DATOS!$AB$11-10))/2)/2),$D52*MAX(0,$F52-10)) -> 0 | I52: =SUMPRODUCT(($N$7:$N$26=$B52)*$U$7:$U$26*$J$7:$J$26) -> 98.9856 | J52: =IF($G52>0,$I52/$G52,0) -> 1 | K52: =SUMPRODUCT(($N$7:$N$26=$B52)*$V$7:$V$26*$J$7:$J$26) -> 98.9856 | L52: =IF($G52>0,$K52/$G52,0) -> 1 | M52: =IF($J52>=0.3,"SÍ","NO") -> SÍ | N52: =IF($L52>=0.3,"SÍ","NO") -> SÍ | O52: =MAX(0,$G52-$I52) -> 0 | P52: =MAX(0,$G52-$K52) -> 0
B53: 3 | C53: Muro 3 — izquierdo (X = 0) | D53: =DATOS!$C$13 -> 16 | E53: =IF(AND(DATOS!$C$14<>"PLANO",DATOS!$C$22="Z"),"SÍ","NO") -> SÍ | F53: =IF($E53="SÍ",DATOS!$C$21,IF(DATOS!$C$14="PLANO",DATOS!$C$17,IF(DATOS!$C$14="DOS AGUAS",DATOS!$C$17+(DATOS!$C$18-DATOS!$C$17)*(1-ABS(2*(0)/DATOS!$C$23-1)),IF(DATOS!$C$14="UN AGUA",IF(N(DATOS!$C$25)=0,DATOS!$C$18-(DATOS!$C$18-DATOS!$C$17)*(0)/DATOS!$C$23,DATOS!$C$17+(DATOS!$C$18-DATOS!$C$17)*(0)/DATOS!$C$23),DATOS!$C$17+4*(DATOS!$C$18-DATOS!$C$17)*(0)/DATOS!$C$23*(1-(0)/DATOS!$C$23))))) -> 10.62 | G53: =IF($E53="SÍ",IF(DATOS!$C$14="CURVO",DATOS!$C$23*DATOS!$C$17+2/3*DATOS!$C$23*(DATOS!$C$18-DATOS!$C$17),DATOS!$C$23*(DATOS!$C$17+DATOS!$C$18)/2),$D53*$F53) -> 163.52 | H53: =IF($E53="SÍ",DATOS!$C$23/8*(SUMPRODUCT((DATOS!$AB$3:$AB$11-10+ABS(DATOS!$AB$3:$AB$11-10))/2)-(((DATOS!$AB$3-10)+ABS(DATOS!$AB$3-10))/2+((DATOS!$AB$11-10)+ABS(DATOS!$AB$11-10))/2)/2),$D53*MAX(0,$F53-10)) -> 3.86 | I53: =SUMPRODUCT(($N$7:$N$26=$B53)*$U$7:$U$26*$J$7:$J$26) -> 0 | J53: =IF($G53>0,$I53/$G53,0) -> 0 | K53: =SUMPRODUCT(($N$7:$N$26=$B53)*$V$7:$V$26*$J$7:$J$26) -> 0 | L53: =IF($G53>0,$K53/$G53,0) -> 0 | M53: =IF($J53>=0.3,"SÍ","NO") -> NO | N53: =IF($L53>=0.3,"SÍ","NO") -> NO | O53: =MAX(0,$G53-$I53) -> 163.52 | P53: =MAX(0,$G53-$K53) -> 163.52
B54: 4 | C54: Muro 4 — derecho (X = B) | D54: =DATOS!$C$13 -> 16 | E54: =IF(AND(DATOS!$C$14<>"PLANO",DATOS!$C$22="Z"),"SÍ","NO") -> SÍ | F54: =IF($E54="SÍ",DATOS!$C$21,IF(DATOS!$C$14="PLANO",DATOS!$C$17,IF(DATOS!$C$14="DOS AGUAS",DATOS!$C$17+(DATOS!$C$18-DATOS!$C$17)*(1-ABS(2*(DATOS!$C$23)/DATOS!$C$23-1)),IF(DATOS!$C$14="UN AGUA",IF(N(DATOS!$C$25)=0,DATOS!$C$18-(DATOS!$C$18-DATOS!$C$17)*(DATOS!$C$23)/DATOS!$C$23,DATOS!$C$17+(DATOS!$C$18-DATOS!$C$17)*(DATOS!$C$23)/DATOS!$C$23),DATOS!$C$17+4*(DATOS!$C$18-DATOS!$C$17)*(DATOS!$C$23)/DATOS!$C$23*(1-(DATOS!$C$23)/DATOS!$C$23))))) -> 10.62 | G54: =IF($E54="SÍ",IF(DATOS!$C$14="CURVO",DATOS!$C$23*DATOS!$C$17+2/3*DATOS!$C$23*(DATOS!$C$18-DATOS!$C$17),DATOS!$C$23*(DATOS!$C$17+DATOS!$C$18)/2),$D54*$F54) -> 163.52 | H54: =IF($E54="SÍ",DATOS!$C$23/8*(SUMPRODUCT((DATOS!$AB$3:$AB$11-10+ABS(DATOS!$AB$3:$AB$11-10))/2)-(((DATOS!$AB$3-10)+ABS(DATOS!$AB$3-10))/2+((DATOS!$AB$11-10)+ABS(DATOS!$AB$11-10))/2)/2),$D54*MAX(0,$F54-10)) -> 3.86 | I54: =SUMPRODUCT(($N$7:$N$26=$B54)*$U$7:$U$26*$J$7:$J$26) -> 0 | J54: =IF($G54>0,$I54/$G54,0) -> 0 | K54: =SUMPRODUCT(($N$7:$N$26=$B54)*$V$7:$V$26*$J$7:$J$26) -> 0 | L54: =IF($G54>0,$K54/$G54,0) -> 0 | M54: =IF($J54>=0.3,"SÍ","NO") -> NO | N54: =IF($L54>=0.3,"SÍ","NO") -> NO | O54: =MAX(0,$G54-$I54) -> 163.52 | P54: =MAX(0,$G54-$K54) -> 163.52
B55: =IF(OR($I$51>$G$51+0.001,$I$52>$G$52+0.001,$I$53>$G$53+0.001,$I$54>$G$54+0.001,$K$51>$G$51+0.001,$K$52>$G$52+0.001,$K$53>$G$53+0.001,$K$54>$G$54+0.001),"OJO: hay un muro con más área abierta que área de muro; revisa que no se encimen aberturas.","OK: el área abierta de cada muro cabe en el muro.") -> OK: el área abierta de cada muro cabe en el muro.
B57: D. PRESIÓN INTERIOR DE CADA CASO (NTV 4.4, pág. 7)
B58: Si en el escenario ningún muro llega a 30% abierto no hay presión interior. Si alguno llega, se ve dónde están principalmente las aberturas: barlovento +0.75, sotavento −0.6, caras paralelas al viento −0.5, uniformemente distribuidas −0.3. Criterio de esta hoja: «principalmente» = el área abierta de esa cara es por lo menos el doble de la del resto. + empuja las caras interiores hacia afuera (levanta el techo); − las jala hacia adentro.
B59: Caso | C59: Viento · puertas | D59: Muro de barlovento | E59: Muro de sotavento | F59: Abierta barlovento (m²) | G59: Abierta sotavento (m²) | H59: Abierta paralelas (m²) | I59: ¿Algún muro ≥ 30%? | J59: Caso de la norma | L59: C_pi
B60: =DATOS!$B$72 -> LOAD 8 | C60: =DATOS!$C$72&" · "&DATOS!$D$72 -> +X · CERRADAS | D60: 3 | E60: 4 | F60: =INDEX($I$51:$I$54,$D60) -> 0 | G60: =INDEX($I$51:$I$54,$E60) -> 0 | H60: =SUM($I$51:$I$54)-$F60-$G60 -> 98.9856 | I60: =IF(COUNTIF($M$51:$M$54,"SÍ")>0,"SÍ","NO") -> SÍ | J60: =IF($I60="NO","Cerrada: sin presión interior",IF($F60>=2*($G60+$H60),"Principalmente en barlovento",IF($G60>=2*($F60+$H60),"Principalmente en sotavento",IF($H60>=2*($F60+$G60),"Principalmente en caras paralelas","Uniformemente distribuidas")))) -> Principalmente en caras paralelas | L60: =IF($I60="NO",0,IF($F60>=2*($G60+$H60),TABLAS!$D$35,IF($G60>=2*($F60+$H60),TABLAS!$D$36,IF($H60>=2*($F60+$G60),TABLAS!$D$37,TABLAS!$D$38)))) -> -0.5
B61: =DATOS!$B$73 -> LOAD 9 | C61: =DATOS!$C$73&" · "&DATOS!$D$73 -> −X · CERRADAS | D61: 4 | E61: 3 | F61: =INDEX($I$51:$I$54,$D61) -> 0 | G61: =INDEX($I$51:$I$54,$E61) -> 0 | H61: =SUM($I$51:$I$54)-$F61-$G61 -> 98.9856 | I61: =IF(COUNTIF($M$51:$M$54,"SÍ")>0,"SÍ","NO") -> SÍ | J61: =IF($I61="NO","Cerrada: sin presión interior",IF($F61>=2*($G61+$H61),"Principalmente en barlovento",IF($G61>=2*($F61+$H61),"Principalmente en sotavento",IF($H61>=2*($F61+$G61),"Principalmente en caras paralelas","Uniformemente distribuidas")))) -> Principalmente en caras paralelas | L61: =IF($I61="NO",0,IF($F61>=2*($G61+$H61),TABLAS!$D$35,IF($G61>=2*($F61+$H61),TABLAS!$D$36,IF($H61>=2*($F61+$G61),TABLAS!$D$37,TABLAS!$D$38)))) -> -0.5
B62: =DATOS!$B$74 -> LOAD 10 | C62: =DATOS!$C$74&" · "&DATOS!$D$74 -> +Z · CERRADAS | D62: 1 | E62: 2 | F62: =INDEX($I$51:$I$54,$D62) -> 0 | G62: =INDEX($I$51:$I$54,$E62) -> 98.9856 | H62: =SUM($I$51:$I$54)-$F62-$G62 -> 0 | I62: =IF(COUNTIF($M$51:$M$54,"SÍ")>0,"SÍ","NO") -> SÍ | J62: =IF($I62="NO","Cerrada: sin presión interior",IF($F62>=2*($G62+$H62),"Principalmente en barlovento",IF($G62>=2*($F62+$H62),"Principalmente en sotavento",IF($H62>=2*($F62+$G62),"Principalmente en caras paralelas","Uniformemente distribuidas")))) -> Principalmente en sotavento | L62: =IF($I62="NO",0,IF($F62>=2*($G62+$H62),TABLAS!$D$35,IF($G62>=2*($F62+$H62),TABLAS!$D$36,IF($H62>=2*($F62+$G62),TABLAS!$D$37,TABLAS!$D$38)))) -> -0.6
B63: =DATOS!$B$75 -> LOAD 11 | C63: =DATOS!$C$75&" · "&DATOS!$D$75 -> −Z · CERRADAS | D63: 2 | E63: 1 | F63: =INDEX($I$51:$I$54,$D63) -> 98.9856 | G63: =INDEX($I$51:$I$54,$E63) -> 0 | H63: =SUM($I$51:$I$54)-$F63-$G63 -> 0 | I63: =IF(COUNTIF($M$51:$M$54,"SÍ")>0,"SÍ","NO") -> SÍ | J63: =IF($I63="NO","Cerrada: sin presión interior",IF($F63>=2*($G63+$H63),"Principalmente en barlovento",IF($G63>=2*($F63+$H63),"Principalmente en sotavento",IF($H63>=2*($F63+$G63),"Principalmente en caras paralelas","Uniformemente distribuidas")))) -> Principalmente en barlovento | L63: =IF($I63="NO",0,IF($F63>=2*($G63+$H63),TABLAS!$D$35,IF($G63>=2*($F63+$H63),TABLAS!$D$36,IF($H63>=2*($F63+$G63),TABLAS!$D$37,TABLAS!$D$38)))) -> 0.75
B64: =DATOS!$B$76 -> LOAD 12 | C64: =DATOS!$C$76&" · "&DATOS!$D$76 -> +X · ABIERTAS (PA) | D64: 3 | E64: 4 | F64: =INDEX($K$51:$K$54,$D64) -> 0 | G64: =INDEX($K$51:$K$54,$E64) -> 0 | H64: =SUM($K$51:$K$54)-$F64-$G64 -> 134.40209 | I64: =IF(COUNTIF($N$51:$N$54,"SÍ")>0,"SÍ","NO") -> SÍ | J64: =IF($I64="NO","Cerrada: sin presión interior",IF($F64>=2*($G64+$H64),"Principalmente en barlovento",IF($G64>=2*($F64+$H64),"Principalmente en sotavento",IF($H64>=2*($F64+$G64),"Principalmente en caras paralelas","Uniformemente distribuidas")))) -> Principalmente en caras paralelas | L64: =IF($I64="NO",0,IF($F64>=2*($G64+$H64),TABLAS!$D$35,IF($G64>=2*($F64+$H64),TABLAS!$D$36,IF($H64>=2*($F64+$G64),TABLAS!$D$37,TABLAS!$D$38)))) -> -0.5
B65: =DATOS!$B$77 -> LOAD 13 | C65: =DATOS!$C$77&" · "&DATOS!$D$77 -> −X · ABIERTAS (PA) | D65: 4 | E65: 3 | F65: =INDEX($K$51:$K$54,$D65) -> 0 | G65: =INDEX($K$51:$K$54,$E65) -> 0 | H65: =SUM($K$51:$K$54)-$F65-$G65 -> 134.40209 | I65: =IF(COUNTIF($N$51:$N$54,"SÍ")>0,"SÍ","NO") -> SÍ | J65: =IF($I65="NO","Cerrada: sin presión interior",IF($F65>=2*($G65+$H65),"Principalmente en barlovento",IF($G65>=2*($F65+$H65),"Principalmente en sotavento",IF($H65>=2*($F65+$G65),"Principalmente en caras paralelas","Uniformemente distribuidas")))) -> Principalmente en caras paralelas | L65: =IF($I65="NO",0,IF($F65>=2*($G65+$H65),TABLAS!$D$35,IF($G65>=2*($F65+$H65),TABLAS!$D$36,IF($H65>=2*($F65+$G65),TABLAS!$D$37,TABLAS!$D$38)))) -> -0.5
B66: =DATOS!$B$78 -> LOAD 14 | C66: =DATOS!$C$78&" · "&DATOS!$D$78 -> +Z · ABIERTAS (PA) | D66: 1 | E66: 2 | F66: =INDEX($K$51:$K$54,$D66) -> 35.416488 | G66: =INDEX($K$51:$K$54,$E66) -> 98.9856 | H66: =SUM($K$51:$K$54)-$F66-$G66 -> 0 | I66: =IF(COUNTIF($N$51:$N$54,"SÍ")>0,"SÍ","NO") -> SÍ | J66: =IF($I66="NO","Cerrada: sin presión interior",IF($F66>=2*($G66+$H66),"Principalmente en barlovento",IF($G66>=2*($F66+$H66),"Principalmente en sotavento",IF($H66>=2*($F66+$G66),"Principalmente en caras paralelas","Uniformemente distribuidas")))) -> Principalmente en sotavento | L66: =IF($I66="NO",0,IF($F66>=2*($G66+$H66),TABLAS!$D$35,IF($G66>=2*($F66+$H66),TABLAS!$D$36,IF($H66>=2*($F66+$G66),TABLAS!$D$37,TABLAS!$D$38)))) -> -0.6
B67: =DATOS!$B$79 -> LOAD 15 | C67: =DATOS!$C$79&" · "&DATOS!$D$79 -> −Z · ABIERTAS (PA) | D67: 2 | E67: 1 | F67: =INDEX($K$51:$K$54,$D67) -> 98.9856 | G67: =INDEX($K$51:$K$54,$E67) -> 35.416488 | H67: =SUM($K$51:$K$54)-$F67-$G67 -> 0 | I67: =IF(COUNTIF($N$51:$N$54,"SÍ")>0,"SÍ","NO") -> SÍ | J67: =IF($I67="NO","Cerrada: sin presión interior",IF($F67>=2*($G67+$H67),"Principalmente en barlovento",IF($G67>=2*($F67+$H67),"Principalmente en sotavento",IF($H67>=2*($F67+$G67),"Principalmente en caras paralelas","Uniformemente distribuidas")))) -> Principalmente en barlovento | L67: =IF($I67="NO",0,IF($F67>=2*($G67+$H67),TABLAS!$D$35,IF($G67>=2*($F67+$H67),TABLAS!$D$36,IF($H67>=2*($F67+$G67),TABLAS!$D$37,TABLAS!$D$38)))) -> 0.75
L68: NTV 1997 · 2.1, pág. 2 · 4.4, pág. 7 · criterio del doble: REFERENCIAS

Sheet PRESIONES
B1: PRESIONES DE VIENTO — LOS 8 CASOS (4 DIRECCIONES × PUERTAS CERRADAS / ABIERTAS)
B2: =DATOS!$C$7&" · techo "&DATOS!$C$14&IF(DATOS!$C$14="UN AGUA"," (alto en "&DATOS!$C$24&", pendiente en "&DATOS!$C$22&")",IF(OR(DATOS!$C$14="DOS AGUAS",DATOS!$C$14="CURVO")," (pendiente en "&DATOS!$C$22&")",""))&" · θ = "&TEXT(DATOS!$C$26,"0.00")&"° · zona "&DATOS!$C$54&" · "&DATOS!$C$60&" · q_H = "&TEXT($C$12,"0.00")&" kg/m²" -> HANGAR NOSE-DOCK H5-H6 · techo UN AGUA (alto en MURO 1, pendiente en Z) · θ = 2.86° · zona C · TIPO 1 · q_H = 48.83 kg/m²
B3: =IF(DATOS!$C$28<>"OK","¡ATENCIÓN! Geometría: "&DATOS!$C$28,IF(LEFT(ABERTURAS!$B$27,3)="OJO","¡ATENCIÓN! "&ABERTURAS!$B$27,IF(COUNTIF($I$76:$I$79,"SIN MIEMBROS*")>0,"OJO: hay un muro con presión que no tiene miembros en LINEAS (sección E): esa carga no entraría a STAAD.",IF(DATOS!$C$60="TIPO 2","OJO: estructura Tipo 2, las presiones ya van × 1.3 por ráfaga (4.6.1, pág. 7).",IF($C$22="SÍ","OJO: el techo tiene casos B (±0.4 o +0.3): mete también los casos B de la hoja STAAD.","Sin alertas: revisa los resultados de las secciones C a E."))))) -> Sin alertas: revisa los resultados de las secciones C a E.
B5: SIGNOS: p neta = C_pe·q − C_pi·q_H. + empuja hacia la superficie (hacia adentro en muros, hacia abajo en el techo); − succión (hacia afuera, levanta el techo). En STAAD (ejes globales): Muro 1 → GZ con el mismo signo; Muro 2 → GZ con signo contrario; Muro 3 → GX con el mismo signo; Muro 4 → GX con signo contrario; techo → GY con signo contrario, más la componente horizontal de la presión normal al techo en el eje de la pendiente. La hoja STAAD ya lo trae aplicado.
B7: A. PRESIÓN DINÁMICA q = C_z·K·P_o·FR
B8: Concepto | C8: Valor | D8: Unidad | E8: Cómo se calcula | O8: Referencia
B9: q hasta 10 m = K·P_o·FR | C9: =DATOS!$C$55*DATOS!$C$57*DATOS!$C$61 -> 48 | D9: kg/m² | E9: C_z = 1 hasta 10 m de altura. | O9: NTV 1997 · 4.1 y 4.2, pág. 5
B10: H — altura máxima | C10: =DATOS!$C$21 -> 10.62 | D10: m | E10: De DATOS. | O10: —
B11: C_z a la altura H | C11: =IF($C$10<=10,1,($C$10/10)^(2/DATOS!$C$56)) -> 1.0173354 | D11: — | E11: (z/10)^(2/a) arriba de 10 m. | O11: NTV 1997 · 4.2, pág. 5
B12: q_H = C_z(H)·K·P_o·FR (techo y presión interior) | C12: =$C$11*$C$9 -> 48.832098 | D12: kg/m² | E12: Techo, presión interior y recubrimiento a la altura máxima: criterio del lado seguro. | O12: NTV 1997 · 4.1, pág. 5
B13: z de sotavento y laterales = H/2 | C13: =$C$10/2 -> 5.31 | D13: m | E13: La succión es constante en toda la altura y se calcula a la mitad de la altura total del edificio. | O13: NTV 1997 · 4.3.1 nota, pág. 5 · Comentarios C4.3.1, págs. 4 y 5
B14: C_z a H/2 | C14: =IF($C$13<=10,1,($C$13/10)^(2/DATOS!$C$56)) -> 1 | D14: — | E14: Igual que arriba. | O14: NTV 1997 · 4.2, pág. 5
B15: q de sotavento y laterales | C15: =$C$14*$C$9 -> 48 | D15: kg/m² | E15: CALCULADA. | O15: Comentarios C4.3.1, págs. 4 y 5
B16: θ — inclinación del techo | C16: =DATOS!$C$26 -> 2.8624052 | D16: ° | E16: De DATOS. | O16: NTV 1997 · 4.3.1, pág. 5
B17: r = flecha / claro (sólo CURVO) | C17: =IF(DATOS!$C$14="CURVO",IF(DATOS!$C$19="SÍ",$C$10/DATOS!$C$23,(DATOS!$C$18-DATOS!$C$17)/DATOS!$C$23),0) -> 0 | D17: — | E17: Con arco desde el suelo la flecha es H. | O17: NTV 1997 · Tabla 4.2, pág. 6
B18: m — pendiente media del cuarto 1 del techo (dh/ds) | C18: =IF(DATOS!$C$14="PLANO",0,IF(DATOS!$C$14="UN AGUA",IF(N(DATOS!$C$25)=0,-1,1)*(DATOS!$C$18-DATOS!$C$17)/DATOS!$C$23,IF(DATOS!$C$14="DOS AGUAS",1*2*(DATOS!$C$18-DATOS!$C$17)/DATOS!$C$23,3*(DATOS!$C$18-DATOS!$C$17)/DATOS!$C$23))) -> -0.05 | D18: — | E18: Sirve para la componente horizontal de la presión normal al techo (s crece en el eje de la pendiente). Curvo: pendiente media de la parábola en ese cuarto. | O18: NTV 1997 · 4.5, pág. 7
B19: m — pendiente media del cuarto 2 del techo (dh/ds) | C19: =IF(DATOS!$C$14="PLANO",0,IF(DATOS!$C$14="UN AGUA",IF(N(DATOS!$C$25)=0,-1,1)*(DATOS!$C$18-DATOS!$C$17)/DATOS!$C$23,IF(DATOS!$C$14="DOS AGUAS",1*2*(DATOS!$C$18-DATOS!$C$17)/DATOS!$C$23,1*(DATOS!$C$18-DATOS!$C$17)/DATOS!$C$23))) -> -0.05 | D19: — | E19: Sirve para la componente horizontal de la presión normal al techo (s crece en el eje de la pendiente). Curvo: pendiente media de la parábola en ese cuarto. | O19: NTV 1997 · 4.5, pág. 7
B20: m — pendiente media del cuarto 3 del techo (dh/ds) | C20: =IF(DATOS!$C$14="PLANO",0,IF(DATOS!$C$14="UN AGUA",IF(N(DATOS!$C$25)=0,-1,1)*(DATOS!$C$18-DATOS!$C$17)/DATOS!$C$23,IF(DATOS!$C$14="DOS AGUAS",-1*2*(DATOS!$C$18-DATOS!$C$17)/DATOS!$C$23,-1*(DATOS!$C$18-DATOS!$C$17)/DATOS!$C$23))) -> -0.05 | D20: — | E20: Sirve para la componente horizontal de la presión normal al techo (s crece en el eje de la pendiente). Curvo: pendiente media de la parábola en ese cuarto. | O20: NTV 1997 · 4.5, pág. 7
B21: m — pendiente media del cuarto 4 del techo (dh/ds) | C21: =IF(DATOS!$C$14="PLANO",0,IF(DATOS!$C$14="UN AGUA",IF(N(DATOS!$C$25)=0,-1,1)*(DATOS!$C$18-DATOS!$C$17)/DATOS!$C$23,IF(DATOS!$C$14="DOS AGUAS",-1*2*(DATOS!$C$18-DATOS!$C$17)/DATOS!$C$23,-3*(DATOS!$C$18-DATOS!$C$17)/DATOS!$C$23))) -> -0.05 | D21: — | E21: Sirve para la componente horizontal de la presión normal al techo (s crece en el eje de la pendiente). Curvo: pendiente media de la parábola en ese cuarto. | O21: NTV 1997 · 4.5, pág. 7
B22: ¿Hay casos B distintos de los A? | C22: =IF(SUMPRODUCT(ABS($D$32:$D$35-$E$32:$E$35)+ABS($G$32:$G$35-$H$32:$H$35)+ABS($J$32:$J$35-$K$32:$K$35)+ABS($M$32:$M$35-$N$32:$N$35))>0.0001,"SÍ","NO") -> NO | D22: — | E22: SÍ sólo con faldón de 30° a 50° (±0.4) o curvo con 0.2 ≤ r ≤ 0.3 (−0.8 ó +0.3). | O22: NTV 1997 · 4.3.1, pág. 5 · Tabla 4.2, pág. 6
B24: B. ROL Y C_pe DE CADA SUPERFICIE EN CADA DIRECCIÓN DEL VIENTO
B25: Techo por cuartos a lo largo del eje de la pendiente (s de 0 a S): cuarto 1 = 0 a S/4, …, cuarto 4 = 3S/4 a S. Dos aguas: faldones = cuartos 1-2 y 3-4. Curvo: A1 = cuarto de barlovento, A2 = mitad central, A3 = cuarto de sotavento. Un agua: el techo es de barlovento cuando el viento entra por el lado bajo. Viento paralelo a la cumbrera o techo plano: −0.7.
B26: Dirección del viento | C26: +X (pega en el Muro 3) | F26: −X (pega en el Muro 4) | I26: +Z (pega en el Muro 1) | L26: −Z (pega en el Muro 2)
B27: Superficie | C27: Rol | D27: C_pe A | E27: C_pe B | F27: Rol | G27: C_pe A | H27: C_pe B | I27: Rol | J27: C_pe A | K27: C_pe B | L27: Rol | M27: C_pe A | N27: C_pe B | O27: Referencia
B28: Muro 1 — atrás (Z = 0) | C28: LATERAL | D28: =TABLAS!$D$16 -> -0.7 | E28: =$D$28 -> -0.7 | F28: LATERAL | G28: =TABLAS!$D$16 -> -0.7 | H28: =$G$28 -> -0.7 | I28: BARLOVENTO | J28: =TABLAS!$D$14 -> 0.8 | K28: =$J$28 -> 0.8 | L28: SOTAVENTO | M28: =TABLAS!$D$15 -> -0.5 | N28: =$M$28 -> -0.5 | O28: NTV 1997 · 4.3.1, pág. 5
B29: Muro 2 — frente (Z = L) | C29: LATERAL | D29: =TABLAS!$D$16 -> -0.7 | E29: =$D$29 -> -0.7 | F29: LATERAL | G29: =TABLAS!$D$16 -> -0.7 | H29: =$G$29 -> -0.7 | I29: SOTAVENTO | J29: =TABLAS!$D$15 -> -0.5 | K29: =$J$29 -> -0.5 | L29: BARLOVENTO | M29: =TABLAS!$D$14 -> 0.8 | N29: =$M$29 -> 0.8 | O29: NTV 1997 · 4.3.1, pág. 5
B30: Muro 3 — izquierdo (X = 0) | C30: BARLOVENTO | D30: =TABLAS!$D$14 -> 0.8 | E30: =$D$30 -> 0.8 | F30: SOTAVENTO | G30: =TABLAS!$D$15 -> -0.5 | H30: =$G$30 -> -0.5 | I30: LATERAL | J30: =TABLAS!$D$16 -> -0.7 | K30: =$J$30 -> -0.7 | L30: LATERAL | M30: =TABLAS!$D$16 -> -0.7 | N30: =$M$30 -> -0.7 | O30: NTV 1997 · 4.3.1, pág. 5
B31: Muro 4 — derecho (X = B) | C31: SOTAVENTO | D31: =TABLAS!$D$15 -> -0.5 | E31: =$D$31 -> -0.5 | F31: BARLOVENTO | G31: =TABLAS!$D$14 -> 0.8 | H31: =$G$31 -> 0.8 | I31: LATERAL | J31: =TABLAS!$D$16 -> -0.7 | K31: =$J$31 -> -0.7 | L31: LATERAL | M31: =TABLAS!$D$16 -> -0.7 | N31: =$M$31 -> -0.7 | O31: NTV 1997 · 4.3.1, pág. 5
B32: ="Techo — cuarto 1 (s = "&TEXT(DATOS!$C$23*0/4,"0.00")&" a "&TEXT(DATOS!$C$23*1/4,"0.00")&" m)" -> Techo — cuarto 1 (s = 0.00 a 4.00 m) | C32: =IF(DATOS!$C$14="PLANO","HORIZONTAL",IF(NOT(DATOS!$C$22="X"),"PARALELO",IF(DATOS!$C$14="UN AGUA",IF(N(DATOS!$C$25)>0,"BARLOVENTO","SOTAVENTO"),IF(DATOS!$C$14="DOS AGUAS","BARLOVENTO","A1 BARLOVENTO")))) -> PARALELO | D32: =IF(DATOS!$C$14="PLANO",-0.7,IF(NOT(DATOS!$C$22="X"),-0.7,IF(DATOS!$C$14="UN AGUA",IF(N(DATOS!$C$25)>0,IF($C$16<30,-0.7,IF($C$16<=50,-0.4,0.8)),-0.7),IF(DATOS!$C$14="DOS AGUAS",IF($C$16<30,-0.7,IF($C$16<=50,-0.4,0.8)),IF(DATOS!$C$19="SÍ",MIN(1.4*$C$17,0.9),IF($C$17<0.2,-0.8,IF($C$17<=0.3,-0.8,2*$C$17-0.3))))))) -> -0.7 | E32: =IF(DATOS!$C$14="PLANO",-0.7,IF(NOT(DATOS!$C$22="X"),-0.7,IF(DATOS!$C$14="UN AGUA",IF(N(DATOS!$C$25)>0,IF($C$16<30,-0.7,IF($C$16<=50,0.4,0.8)),-0.7),IF(DATOS!$C$14="DOS AGUAS",IF($C$16<30,-0.7,IF($C$16<=50,0.4,0.8)),IF(DATOS!$C$19="SÍ",MIN(1.4*$C$17,0.9),IF($C$17<0.2,-0.8,IF($C$17<=0.3,0.3,2*$C$17-0.3))))))) -> -0.7 | F32: =IF(DATOS!$C$14="PLANO","HORIZONTAL",IF(NOT(DATOS!$C$22="X"),"PARALELO",IF(DATOS!$C$14="UN AGUA",IF(N(DATOS!$C$25)=0,"BARLOVENTO","SOTAVENTO"),IF(DATOS!$C$14="DOS AGUAS","SOTAVENTO","A3 SOTAVENTO")))) -> PARALELO | G32: =IF(DATOS!$C$14="PLANO",-0.7,IF(NOT(DATOS!$C$22="X"),-0.7,IF(DATOS!$C$14="UN AGUA",IF(N(DATOS!$C$25)=0,IF($C$16<30,-0.7,IF($C$16<=50,-0.4,0.8)),-0.7),IF(DATOS!$C$14="DOS AGUAS",-0.7,-0.5)))) -> -0.7 | H32: =IF(DATOS!$C$14="PLANO",-0.7,IF(NOT(DATOS!$C$22="X"),-0.7,IF(DATOS!$C$14="UN AGUA",IF(N(DATOS!$C$25)=0,IF($C$16<30,-0.7,IF($C$16<=50,0.4,0.8)),-0.7),IF(DATOS!$C$14="DOS AGUAS",-0.7,-0.5)))) -> -0.7 | I32: =IF(DATOS!$C$14="PLANO","HORIZONTAL",IF(NOT(DATOS!$C$22="Z"),"PARALELO",IF(DATOS!$C$14="UN AGUA",IF(N(DATOS!$C$25)>0,"BARLOVENTO","SOTAVENTO"),IF(DATOS!$C$14="DOS AGUAS","BARLOVENTO","A1 BARLOVENTO")))) -> SOTAVENTO | J32: =IF(DATOS!$C$14="PLANO",-0.7,IF(NOT(DATOS!$C$22="Z"),-0.7,IF(DATOS!$C$14="UN AGUA",IF(N(DATOS!$C$25)>0,IF($C$16<30,-0.7,IF($C$16<=50,-0.4,0.8)),-0.7),IF(DATOS!$C$14="DOS AGUAS",IF($C$16<30,-0.7,IF($C$16<=50,-0.4,0.8)),IF(DATOS!$C$19="SÍ",MIN(1.4*$C$17,0.9),IF($C$17<0.2,-0.8,IF($C$17<=0.3,-0.8,2*$C$17-0.3))))))) -> -0.7 | K32: =IF(DATOS!$C$14="PLANO",-0.7,IF(NOT(DATOS!$C$22="Z"),-0.7,IF(DATOS!$C$14="UN AGUA",IF(N(DATOS!$C$25)>0,IF($C$16<30,-0.7,IF($C$16<=50,0.4,0.8)),-0.7),IF(DATOS!$C$14="DOS AGUAS",IF($C$16<30,-0.7,IF($C$16<=50,0.4,0.8)),IF(DATOS!$C$19="SÍ",MIN(1.4*$C$17,0.9),IF($C$17<0.2,-0.8,IF($C$17<=0.3,0.3,2*$C$17-0.3))))))) -> -0.7 | L32: =IF(DATOS!$C$14="PLANO","HORIZONTAL",IF(NOT(DATOS!$C$22="Z"),"PARALELO",IF(DATOS!$C$14="UN AGUA",IF(N(DATOS!$C$25)=0,"BARLOVENTO","SOTAVENTO"),IF(DATOS!$C$14="DOS AGUAS","SOTAVENTO","A3 SOTAVENTO")))) -> BARLOVENTO | M32: =IF(DATOS!$C$14="PLANO",-0.7,IF(NOT(DATOS!$C$22="Z"),-0.7,IF(DATOS!$C$14="UN AGUA",IF(N(DATOS!$C$25)=0,IF($C$16<30,-0.7,IF($C$16<=50,-0.4,0.8)),-0.7),IF(DATOS!$C$14="DOS AGUAS",-0.7,-0.5)))) -> -0.7 | N32: =IF(DATOS!$C$14="PLANO",-0.7,IF(NOT(DATOS!$C$22="Z"),-0.7,IF(DATOS!$C$14="UN AGUA",IF(N(DATOS!$C$25)=0,IF($C$16<30,-0.7,IF($C$16<=50,0.4,0.8)),-0.7),IF(DATOS!$C$14="DOS AGUAS",-0.7,-0.5)))) -> -0.7 | O32: NTV 1997 · 4.3.1, pág. 5 · Tabla 4.2, pág. 6
B33: ="Techo — cuarto 2 (s = "&TEXT(DATOS!$C$23*1/4,"0.00")&" a "&TEXT(DATOS!$C$23*2/4,"0.00")&" m)" -> Techo — cuarto 2 (s = 4.00 a 8.00 m) | C33: =IF(DATOS!$C$14="PLANO","HORIZONTAL",IF(NOT(DATOS!$C$22="X"),"PARALELO",IF(DATOS!$C$14="UN AGUA",IF(N(DATOS!$C$25)>0,"BARLOVENTO","SOTAVENTO"),IF(DATOS!$C$14="DOS AGUAS","BARLOVENTO","A2 CENTRAL")))) -> PARALELO | D33: =IF(DATOS!$C$14="PLANO",-0.7,IF(NOT(DATOS!$C$22="X"),-0.7,IF(DATOS!$C$14="UN AGUA",IF(N(DATOS!$C$25)>0,IF($C$16<30,-0.7,IF($C$16<=50,-0.4,0.8)),-0.7),IF(DATOS!$C$14="DOS AGUAS",IF($C$16<30,-0.7,IF($C$16<=50,-0.4,0.8)),-0.7-$C$17)))) -> -0.7 | E33: =IF(DATOS!$C$14="PLANO",-0.7,IF(NOT(DATOS!$C$22="X"),-0.7,IF(DATOS!$C$14="UN AGUA",IF(N(DATOS!$C$25)>0,IF($C$16<30,-0.7,IF($C$16<=50,0.4,0.8)),-0.7),IF(DATOS!$C$14="DOS AGUAS",IF($C$16<30,-0.7,IF($C$16<=50,0.4,0.8)),-0.7-$C$17)))) -> -0.7 | F33: =IF(DATOS!$C$14="PLANO","HORIZONTAL",IF(NOT(DATOS!$C$22="X"),"PARALELO",IF(DATOS!$C$14="UN AGUA",IF(N(DATOS!$C$25)=0,"BARLOVENTO","SOTAVENTO"),IF(DATOS!$C$14="DOS AGUAS","SOTAVENTO","A2 CENTRAL")))) -> PARALELO | G33: =IF(DATOS!$C$14="PLANO",-0.7,IF(NOT(DATOS!$C$22="X"),-0.7,IF(DATOS!$C$14="UN AGUA",IF(N(DATOS!$C$25)=0,IF($C$16<30,-0.7,IF($C$16<=50,-0.4,0.8)),-0.7),IF(DATOS!$C$14="DOS AGUAS",-0.7,-0.7-$C$17)))) -> -0.7 | H33: =IF(DATOS!$C$14="PLANO",-0.7,IF(NOT(DATOS!$C$22="X"),-0.7,IF(DATOS!$C$14="UN AGUA",IF(N(DATOS!$C$25)=0,IF($C$16<30,-0.7,IF($C$16<=50,0.4,0.8)),-0.7),IF(DATOS!$C$14="DOS AGUAS",-0.7,-0.7-$C$17)))) -> -0.7 | I33: =IF(DATOS!$C$14="PLANO","HORIZONTAL",IF(NOT(DATOS!$C$22="Z"),"PARALELO",IF(DATOS!$C$14="UN AGUA",IF(N(DATOS!$C$25)>0,"BARLOVENTO","SOTAVENTO"),IF(DATOS!$C$14="DOS AGUAS","BARLOVENTO","A2 CENTRAL")))) -> SOTAVENTO | J33: =IF(DATOS!$C$14="PLANO",-0.7,IF(NOT(DATOS!$C$22="Z"),-0.7,IF(DATOS!$C$14="UN AGUA",IF(N(DATOS!$C$25)>0,IF($C$16<30,-0.7,IF($C$16<=50,-0.4,0.8)),-0.7),IF(DATOS!$C$14="DOS AGUAS",IF($C$16<30,-0.7,IF($C$16<=50,-0.4,0.8)),-0.7-$C$17)))) -> -0.7 | K33: =IF(DATOS!$C$14="PLANO",-0.7,IF(NOT(DATOS!$C$22="Z"),-0.7,IF(DATOS!$C$14="UN AGUA",IF(N(DATOS!$C$25)>0,IF($C$16<30,-0.7,IF($C$16<=50,0.4,0.8)),-0.7),IF(DATOS!$C$14="DOS AGUAS",IF($C$16<30,-0.7,IF($C$16<=50,0.4,0.8)),-0.7-$C$17)))) -> -0.7 | L33: =IF(DATOS!$C$14="PLANO","HORIZONTAL",IF(NOT(DATOS!$C$22="Z"),"PARALELO",IF(DATOS!$C$14="UN AGUA",IF(N(DATOS!$C$25)=0,"BARLOVENTO","SOTAVENTO"),IF(DATOS!$C$14="DOS AGUAS","SOTAVENTO","A2 CENTRAL")))) -> BARLOVENTO | M33: =IF(DATOS!$C$14="PLANO",-0.7,IF(NOT(DATOS!$C$22="Z"),-0.7,IF(DATOS!$C$14="UN AGUA",IF(N(DATOS!$C$25)=0,IF($C$16<30,-0.7,IF($C$16<=50,-0.4,0.8)),-0.7),IF(DATOS!$C$14="DOS AGUAS",-0.7,-0.7-$C$17)))) -> -0.7 | N33: =IF(DATOS!$C$14="PLANO",-0.7,IF(NOT(DATOS!$C$22="Z"),-0.7,IF(DATOS!$C$14="UN AGUA",IF(N(DATOS!$C$25)=0,IF($C$16<30,-0.7,IF($C$16<=50,0.4,0.8)),-0.7),IF(DATOS!$C$14="DOS AGUAS",-0.7,-0.7-$C$17)))) -> -0.7 | O33: NTV 1997 · 4.3.1, pág. 5 · Tabla 4.2, pág. 6
B34: ="Techo — cuarto 3 (s = "&TEXT(DATOS!$C$23*2/4,"0.00")&" a "&TEXT(DATOS!$C$23*3/4,"0.00")&" m)" -> Techo — cuarto 3 (s = 8.00 a 12.00 m) | C34: =IF(DATOS!$C$14="PLANO","HORIZONTAL",IF(NOT(DATOS!$C$22="X"),"PARALELO",IF(DATOS!$C$14="UN AGUA",IF(N(DATOS!$C$25)>0,"BARLOVENTO","SOTAVENTO"),IF(DATOS!$C$14="DOS AGUAS","SOTAVENTO","A2 CENTRAL")))) -> PARALELO | D34: =IF(DATOS!$C$14="PLANO",-0.7,IF(NOT(DATOS!$C$22="X"),-0.7,IF(DATOS!$C$14="UN AGUA",IF(N(DATOS!$C$25)>0,IF($C$16<30,-0.7,IF($C$16<=50,-0.4,0.8)),-0.7),IF(DATOS!$C$14="DOS AGUAS",-0.7,-0.7-$C$17)))) -> -0.7 | E34: =IF(DATOS!$C$14="PLANO",-0.7,IF(NOT(DATOS!$C$22="X"),-0.7,IF(DATOS!$C$14="UN AGUA",IF(N(DATOS!$C$25)>0,IF($C$16<30,-0.7,IF($C$16<=50,0.4,0.8)),-0.7),IF(DATOS!$C$14="DOS AGUAS",-0.7,-0.7-$C$17)))) -> -0.7 | F34: =IF(DATOS!$C$14="PLANO","HORIZONTAL",IF(NOT(DATOS!$C$22="X"),"PARALELO",IF(DATOS!$C$14="UN AGUA",IF(N(DATOS!$C$25)=0,"BARLOVENTO","SOTAVENTO"),IF(DATOS!$C$14="DOS AGUAS","BARLOVENTO","A2 CENTRAL")))) -> PARALELO | G34: =IF(DATOS!$C$14="PLANO",-0.7,IF(NOT(DATOS!$C$22="X"),-0.7,IF(DATOS!$C$14="UN AGUA",IF(N(DATOS!$C$25)=0,IF($C$16<30,-0.7,IF($C$16<=50,-0.4,0.8)),-0.7),IF(DATOS!$C$14="DOS AGUAS",IF($C$16<30,-0.7,IF($C$16<=50,-0.4,0.8)),-0.7-$C$17)))) -> -0.7 | H34: =IF(DATOS!$C$14="PLANO",-0.7,IF(NOT(DATOS!$C$22="X"),-0.7,IF(DATOS!$C$14="UN AGUA",IF(N(DATOS!$C$25)=0,IF($C$16<30,-0.7,IF($C$16<=50,0.4,0.8)),-0.7),IF(DATOS!$C$14="DOS AGUAS",IF($C$16<30,-0.7,IF($C$16<=50,0.4,0.8)),-0.7-$C$17)))) -> -0.7 | I34: =IF(DATOS!$C$14="PLANO","HORIZONTAL",IF(NOT(DATOS!$C$22="Z"),"PARALELO",IF(DATOS!$C$14="UN AGUA",IF(N(DATOS!$C$25)>0,"BARLOVENTO","SOTAVENTO"),IF(DATOS!$C$14="DOS AGUAS","SOTAVENTO","A2 CENTRAL")))) -> SOTAVENTO | J34: =IF(DATOS!$C$14="PLANO",-0.7,IF(NOT(DATOS!$C$22="Z"),-0.7,IF(DATOS!$C$14="UN AGUA",IF(N(DATOS!$C$25)>0,IF($C$16<30,-0.7,IF($C$16<=50,-0.4,0.8)),-0.7),IF(DATOS!$C$14="DOS AGUAS",-0.7,-0.7-$C$17)))) -> -0.7 | K34: =IF(DATOS!$C$14="PLANO",-0.7,IF(NOT(DATOS!$C$22="Z"),-0.7,IF(DATOS!$C$14="UN AGUA",IF(N(DATOS!$C$25)>0,IF($C$16<30,-0.7,IF($C$16<=50,0.4,0.8)),-0.7),IF(DATOS!$C$14="DOS AGUAS",-0.7,-0.7-$C$17)))) -> -0.7 | L34: =IF(DATOS!$C$14="PLANO","HORIZONTAL",IF(NOT(DATOS!$C$22="Z"),"PARALELO",IF(DATOS!$C$14="UN AGUA",IF(N(DATOS!$C$25)=0,"BARLOVENTO","SOTAVENTO"),IF(DATOS!$C$14="DOS AGUAS","BARLOVENTO","A2 CENTRAL")))) -> BARLOVENTO | M34: =IF(DATOS!$C$14="PLANO",-0.7,IF(NOT(DATOS!$C$22="Z"),-0.7,IF(DATOS!$C$14="UN AGUA",IF(N(DATOS!$C$25)=0,IF($C$16<30,-0.7,IF($C$16<=50,-0.4,0.8)),-0.7),IF(DATOS!$C$14="DOS AGUAS",IF($C$16<30,-0.7,IF($C$16<=50,-0.4,0.8)),-0.7-$C$17)))) -> -0.7 | N34: =IF(DATOS!$C$14="PLANO",-0.7,IF(NOT(DATOS!$C$22="Z"),-0.7,IF(DATOS!$C$14="UN AGUA",IF(N(DATOS!$C$25)=0,IF($C$16<30,-0.7,IF($C$16<=50,0.4,0.8)),-0.7),IF(DATOS!$C$14="DOS AGUAS",IF($C$16<30,-0.7,IF($C$16<=50,0.4,0.8)),-0.7-$C$17)))) -> -0.7 | O34: NTV 1997 · 4.3.1, pág. 5 · Tabla 4.2, pág. 6
B35: ="Techo — cuarto 4 (s = "&TEXT(DATOS!$C$23*3/4,"0.00")&" a "&TEXT(DATOS!$C$23*4/4,"0.00")&" m)" -> Techo — cuarto 4 (s = 12.00 a 16.00 m) | C35: =IF(DATOS!$C$14="PLANO","HORIZONTAL",IF(NOT(DATOS!$C$22="X"),"PARALELO",IF(DATOS!$C$14="UN AGUA",IF(N(DATOS!$C$25)>0,"BARLOVENTO","SOTAVENTO"),IF(DATOS!$C$14="DOS AGUAS","SOTAVENTO","A3 SOTAVENTO")))) -> PARALELO | D35: =IF(DATOS!$C$14="PLANO",-0.7,IF(NOT(DATOS!$C$22="X"),-0.7,IF(DATOS!$C$14="UN AGUA",IF(N(DATOS!$C$25)>0,IF($C$16<30,-0.7,IF($C$16<=50,-0.4,0.8)),-0.7),IF(DATOS!$C$14="DOS AGUAS",-0.7,-0.5)))) -> -0.7 | E35: =IF(DATOS!$C$14="PLANO",-0.7,IF(NOT(DATOS!$C$22="X"),-0.7,IF(DATOS!$C$14="UN AGUA",IF(N(DATOS!$C$25)>0,IF($C$16<30,-0.7,IF($C$16<=50,0.4,0.8)),-0.7),IF(DATOS!$C$14="DOS AGUAS",-0.7,-0.5)))) -> -0.7 | F35: =IF(DATOS!$C$14="PLANO","HORIZONTAL",IF(NOT(DATOS!$C$22="X"),"PARALELO",IF(DATOS!$C$14="UN AGUA",IF(N(DATOS!$C$25)=0,"BARLOVENTO","SOTAVENTO"),IF(DATOS!$C$14="DOS AGUAS","BARLOVENTO","A1 BARLOVENTO")))) -> PARALELO | G35: =IF(DATOS!$C$14="PLANO",-0.7,IF(NOT(DATOS!$C$22="X"),-0.7,IF(DATOS!$C$14="UN AGUA",IF(N(DATOS!$C$25)=0,IF($C$16<30,-0.7,IF($C$16<=50,-0.4,0.8)),-0.7),IF(DATOS!$C$14="DOS AGUAS",IF($C$16<30,-0.7,IF($C$16<=50,-0.4,0.8)),IF(DATOS!$C$19="SÍ",MIN(1.4*$C$17,0.9),IF($C$17<0.2,-0.8,IF($C$17<=0.3,-0.8,2*$C$17-0.3))))))) -> -0.7 | H35: =IF(DATOS!$C$14="PLANO",-0.7,IF(NOT(DATOS!$C$22="X"),-0.7,IF(DATOS!$C$14="UN AGUA",IF(N(DATOS!$C$25)=0,IF($C$16<30,-0.7,IF($C$16<=50,0.4,0.8)),-0.7),IF(DATOS!$C$14="DOS AGUAS",IF($C$16<30,-0.7,IF($C$16<=50,0.4,0.8)),IF(DATOS!$C$19="SÍ",MIN(1.4*$C$17,0.9),IF($C$17<0.2,-0.8,IF($C$17<=0.3,0.3,2*$C$17-0.3))))))) -> -0.7 | I35: =IF(DATOS!$C$14="PLANO","HORIZONTAL",IF(NOT(DATOS!$C$22="Z"),"PARALELO",IF(DATOS!$C$14="UN AGUA",IF(N(DATOS!$C$25)>0,"BARLOVENTO","SOTAVENTO"),IF(DATOS!$C$14="DOS AGUAS","SOTAVENTO","A3 SOTAVENTO")))) -> SOTAVENTO | J35: =IF(DATOS!$C$14="PLANO",-0.7,IF(NOT(DATOS!$C$22="Z"),-0.7,IF(DATOS!$C$14="UN AGUA",IF(N(DATOS!$C$25)>0,IF($C$16<30,-0.7,IF($C$16<=50,-0.4,0.8)),-0.7),IF(DATOS!$C$14="DOS AGUAS",-0.7,-0.5)))) -> -0.7 | K35: =IF(DATOS!$C$14="PLANO",-0.7,IF(NOT(DATOS!$C$22="Z"),-0.7,IF(DATOS!$C$14="UN AGUA",IF(N(DATOS!$C$25)>0,IF($C$16<30,-0.7,IF($C$16<=50,0.4,0.8)),-0.7),IF(DATOS!$C$14="DOS AGUAS",-0.7,-0.5)))) -> -0.7 | L35: =IF(DATOS!$C$14="PLANO","HORIZONTAL",IF(NOT(DATOS!$C$22="Z"),"PARALELO",IF(DATOS!$C$14="UN AGUA",IF(N(DATOS!$C$25)=0,"BARLOVENTO","SOTAVENTO"),IF(DATOS!$C$14="DOS AGUAS","BARLOVENTO","A1 BARLOVENTO")))) -> BARLOVENTO | M35: =IF(DATOS!$C$14="PLANO",-0.7,IF(NOT(DATOS!$C$22="Z"),-0.7,IF(DATOS!$C$14="UN AGUA",IF(N(DATOS!$C$25)=0,IF($C$16<30,-0.7,IF($C$16<=50,-0.4,0.8)),-0.7),IF(DATOS!$C$14="DOS AGUAS",IF($C$16<30,-0.7,IF($C$16<=50,-0.4,0.8)),IF(DATOS!$C$19="SÍ",MIN(1.4*$C$17,0.9),IF($C$17<0.2,-0.8,IF($C$17<=0.3,-0.8,2*$C$17-0.3))))))) -> -0.7 | N35: =IF(DATOS!$C$14="PLANO",-0.7,IF(NOT(DATOS!$C$22="Z"),-0.7,IF(DATOS!$C$14="UN AGUA",IF(N(DATOS!$C$25)=0,IF($C$16<30,-0.7,IF($C$16<=50,0.4,0.8)),-0.7),IF(DATOS!$C$14="DOS AGUAS",IF($C$16<30,-0.7,IF($C$16<=50,0.4,0.8)),IF(DATOS!$C$19="SÍ",MIN(1.4*$C$17,0.9),IF($C$17<0.2,-0.8,IF($C$17<=0.3,0.3,2*$C$17-0.3))))))) -> -0.7 | O35: NTV 1997 · 4.3.1, pág. 5 · Tabla 4.2, pág. 6
B37: C. PRESIONES NETAS DE CADA CASO (kg/m²; + hacia la superficie, − succión)
B38: Muros de barlovento: C_z = 1 hasta 10 m y, arriba, el C_z de lo alto del muro (renglón «en lo alto»). Sotavento y laterales: q a H/2. Techo: q_H. Las presiones de cada renglón de LINEAS salen de aquí.
B39: Superficie | C39: =DATOS!$B$72 -> LOAD 8 | D39: =DATOS!$B$73 -> LOAD 9 | E39: =DATOS!$B$74 -> LOAD 10 | F39: =DATOS!$B$75 -> LOAD 11 | G39: =DATOS!$B$76 -> LOAD 12 | H39: =DATOS!$B$77 -> LOAD 13 | I39: =DATOS!$B$78 -> LOAD 14 | J39: =DATOS!$B$79 -> LOAD 15 | O39: Referencia
B40: Viento | C40: =DATOS!$C$72 -> +X | D40: =DATOS!$C$73 -> −X | E40: =DATOS!$C$74 -> +Z | F40: =DATOS!$C$75 -> −Z | G40: =DATOS!$C$76 -> +X | H40: =DATOS!$C$77 -> −X | I40: =DATOS!$C$78 -> +Z | J40: =DATOS!$C$79 -> −Z
B41: Puertas | C41: =DATOS!$D$72 -> CERRADAS | D41: =DATOS!$D$73 -> CERRADAS | E41: =DATOS!$D$74 -> CERRADAS | F41: =DATOS!$D$75 -> CERRADAS | G41: =DATOS!$D$76 -> ABIERTAS (PA) | H41: =DATOS!$D$77 -> ABIERTAS (PA) | I41: =DATOS!$D$78 -> ABIERTAS (PA) | J41: =DATOS!$D$79 -> ABIERTAS (PA)
B42: C_pi del caso | C42: =ABERTURAS!$L$60 -> -0.5 | D42: =ABERTURAS!$L$61 -> -0.5 | E42: =ABERTURAS!$L$62 -> -0.6 | F42: =ABERTURAS!$L$63 -> 0.75 | G42: =ABERTURAS!$L$64 -> -0.5 | H42: =ABERTURAS!$L$65 -> -0.5 | I42: =ABERTURAS!$L$66 -> -0.6 | J42: =ABERTURAS!$L$67 -> 0.75 | O42: ABERTURAS §D · NTV 1997 · 4.4, pág. 7
B43: Muro 1 — atrás (Z = 0) — hasta 10 m | C43: =$D$28*IF($D$28>0,$C$9,$C$15)-C$42*$C$12 -> -9.1839509 | D43: =$G$28*IF($G$28>0,$C$9,$C$15)-D$42*$C$12 -> -9.1839509 | E43: =$J$28*IF($J$28>0,$C$9,$C$15)-E$42*$C$12 -> 67.699259 | F43: =$M$28*IF($M$28>0,$C$9,$C$15)-F$42*$C$12 -> -60.624074 | G43: =$D$28*IF($D$28>0,$C$9,$C$15)-G$42*$C$12 -> -9.1839509 | H43: =$G$28*IF($G$28>0,$C$9,$C$15)-H$42*$C$12 -> -9.1839509 | I43: =$J$28*IF($J$28>0,$C$9,$C$15)-I$42*$C$12 -> 67.699259 | J43: =$M$28*IF($M$28>0,$C$9,$C$15)-J$42*$C$12 -> -60.624074 | O43: NTV 1997 · 4.1 y 4.3.1, pág. 5 · 4.4, pág. 7
B44: Muro 2 — frente (Z = L) — hasta 10 m | C44: =$D$29*IF($D$29>0,$C$9,$C$15)-C$42*$C$12 -> -9.1839509 | D44: =$G$29*IF($G$29>0,$C$9,$C$15)-D$42*$C$12 -> -9.1839509 | E44: =$J$29*IF($J$29>0,$C$9,$C$15)-E$42*$C$12 -> 5.2992589 | F44: =$M$29*IF($M$29>0,$C$9,$C$15)-F$42*$C$12 -> 1.7759264 | G44: =$D$29*IF($D$29>0,$C$9,$C$15)-G$42*$C$12 -> -9.1839509 | H44: =$G$29*IF($G$29>0,$C$9,$C$15)-H$42*$C$12 -> -9.1839509 | I44: =$J$29*IF($J$29>0,$C$9,$C$15)-I$42*$C$12 -> 5.2992589 | J44: =$M$29*IF($M$29>0,$C$9,$C$15)-J$42*$C$12 -> 1.7759264 | O44: NTV 1997 · 4.1 y 4.3.1, pág. 5 · 4.4, pág. 7
B45: Muro 3 — izquierdo (X = 0) — hasta 10 m | C45: =$D$30*IF($D$30>0,$C$9,$C$15)-C$42*$C$12 -> 62.816049 | D45: =$G$30*IF($G$30>0,$C$9,$C$15)-D$42*$C$12 -> 0.41604908 | E45: =$J$30*IF($J$30>0,$C$9,$C$15)-E$42*$C$12 -> -4.3007411 | F45: =$M$30*IF($M$30>0,$C$9,$C$15)-F$42*$C$12 -> -70.224074 | G45: =$D$30*IF($D$30>0,$C$9,$C$15)-G$42*$C$12 -> 62.816049 | H45: =$G$30*IF($G$30>0,$C$9,$C$15)-H$42*$C$12 -> 0.41604908 | I45: =$J$30*IF($J$30>0,$C$9,$C$15)-I$42*$C$12 -> -4.3007411 | J45: =$M$30*IF($M$30>0,$C$9,$C$15)-J$42*$C$12 -> -70.224074 | O45: NTV 1997 · 4.1 y 4.3.1, pág. 5 · 4.4, pág. 7
B46: Muro 4 — derecho (X = B) — hasta 10 m | C46: =$D$31*IF($D$31>0,$C$9,$C$15)-C$42*$C$12 -> 0.41604908 | D46: =$G$31*IF($G$31>0,$C$9,$C$15)-D$42*$C$12 -> 62.816049 | E46: =$J$31*IF($J$31>0,$C$9,$C$15)-E$42*$C$12 -> -4.3007411 | F46: =$M$31*IF($M$31>0,$C$9,$C$15)-F$42*$C$12 -> -70.224074 | G46: =$D$31*IF($D$31>0,$C$9,$C$15)-G$42*$C$12 -> 0.41604908 | H46: =$G$31*IF($G$31>0,$C$9,$C$15)-H$42*$C$12 -> 62.816049 | I46: =$J$31*IF($J$31>0,$C$9,$C$15)-I$42*$C$12 -> -4.3007411 | J46: =$M$31*IF($M$31>0,$C$9,$C$15)-J$42*$C$12 -> -70.224074 | O46: NTV 1997 · 4.1 y 4.3.1, pág. 5 · 4.4, pág. 7
B47: Muro 1 — atrás (Z = 0) — en lo alto | C47: =$D$28*IF($D$28>0,$C$9*IF(ABERTURAS!$F$51<=10,1,(ABERTURAS!$F$51/10)^(2/DATOS!$C$56)),$C$15)-C$42*$C$12 -> -9.1839509 | D47: =$G$28*IF($G$28>0,$C$9*IF(ABERTURAS!$F$51<=10,1,(ABERTURAS!$F$51/10)^(2/DATOS!$C$56)),$C$15)-D$42*$C$12 -> -9.1839509 | E47: =$J$28*IF($J$28>0,$C$9*IF(ABERTURAS!$F$51<=10,1,(ABERTURAS!$F$51/10)^(2/DATOS!$C$56)),$C$15)-E$42*$C$12 -> 68.364937 | F47: =$M$28*IF($M$28>0,$C$9*IF(ABERTURAS!$F$51<=10,1,(ABERTURAS!$F$51/10)^(2/DATOS!$C$56)),$C$15)-F$42*$C$12 -> -60.624074 | G47: =$D$28*IF($D$28>0,$C$9*IF(ABERTURAS!$F$51<=10,1,(ABERTURAS!$F$51/10)^(2/DATOS!$C$56)),$C$15)-G$42*$C$12 -> -9.1839509 | H47: =$G$28*IF($G$28>0,$C$9*IF(ABERTURAS!$F$51<=10,1,(ABERTURAS!$F$51/10)^(2/DATOS!$C$56)),$C$15)-H$42*$C$12 -> -9.1839509 | I47: =$J$28*IF($J$28>0,$C$9*IF(ABERTURAS!$F$51<=10,1,(ABERTURAS!$F$51/10)^(2/DATOS!$C$56)),$C$15)-I$42*$C$12 -> 68.364937 | J47: =$M$28*IF($M$28>0,$C$9*IF(ABERTURAS!$F$51<=10,1,(ABERTURAS!$F$51/10)^(2/DATOS!$C$56)),$C$15)-J$42*$C$12 -> -60.624074 | O47: NTV 1997 · 4.2, pág. 5 (franja arriba de 10 m)
B48: Muro 2 — frente (Z = L) — en lo alto | C48: =$D$29*IF($D$29>0,$C$9*IF(ABERTURAS!$F$52<=10,1,(ABERTURAS!$F$52/10)^(2/DATOS!$C$56)),$C$15)-C$42*$C$12 -> -9.1839509 | D48: =$G$29*IF($G$29>0,$C$9*IF(ABERTURAS!$F$52<=10,1,(ABERTURAS!$F$52/10)^(2/DATOS!$C$56)),$C$15)-D$42*$C$12 -> -9.1839509 | E48: =$J$29*IF($J$29>0,$C$9*IF(ABERTURAS!$F$52<=10,1,(ABERTURAS!$F$52/10)^(2/DATOS!$C$56)),$C$15)-E$42*$C$12 -> 5.2992589 | F48: =$M$29*IF($M$29>0,$C$9*IF(ABERTURAS!$F$52<=10,1,(ABERTURAS!$F$52/10)^(2/DATOS!$C$56)),$C$15)-F$42*$C$12 -> 1.7759264 | G48: =$D$29*IF($D$29>0,$C$9*IF(ABERTURAS!$F$52<=10,1,(ABERTURAS!$F$52/10)^(2/DATOS!$C$56)),$C$15)-G$42*$C$12 -> -9.1839509 | H48: =$G$29*IF($G$29>0,$C$9*IF(ABERTURAS!$F$52<=10,1,(ABERTURAS!$F$52/10)^(2/DATOS!$C$56)),$C$15)-H$42*$C$12 -> -9.1839509 | I48: =$J$29*IF($J$29>0,$C$9*IF(ABERTURAS!$F$52<=10,1,(ABERTURAS!$F$52/10)^(2/DATOS!$C$56)),$C$15)-I$42*$C$12 -> 5.2992589 | J48: =$M$29*IF($M$29>0,$C$9*IF(ABERTURAS!$F$52<=10,1,(ABERTURAS!$F$52/10)^(2/DATOS!$C$56)),$C$15)-J$42*$C$12 -> 1.7759264 | O48: NTV 1997 · 4.2, pág. 5 (franja arriba de 10 m)
B49: Muro 3 — izquierdo (X = 0) — en lo alto | C49: =$D$30*IF($D$30>0,$C$9*IF(ABERTURAS!$F$53<=10,1,(ABERTURAS!$F$53/10)^(2/DATOS!$C$56)),$C$15)-C$42*$C$12 -> 63.481728 | D49: =$G$30*IF($G$30>0,$C$9*IF(ABERTURAS!$F$53<=10,1,(ABERTURAS!$F$53/10)^(2/DATOS!$C$56)),$C$15)-D$42*$C$12 -> 0.41604908 | E49: =$J$30*IF($J$30>0,$C$9*IF(ABERTURAS!$F$53<=10,1,(ABERTURAS!$F$53/10)^(2/DATOS!$C$56)),$C$15)-E$42*$C$12 -> -4.3007411 | F49: =$M$30*IF($M$30>0,$C$9*IF(ABERTURAS!$F$53<=10,1,(ABERTURAS!$F$53/10)^(2/DATOS!$C$56)),$C$15)-F$42*$C$12 -> -70.224074 | G49: =$D$30*IF($D$30>0,$C$9*IF(ABERTURAS!$F$53<=10,1,(ABERTURAS!$F$53/10)^(2/DATOS!$C$56)),$C$15)-G$42*$C$12 -> 63.481728 | H49: =$G$30*IF($G$30>0,$C$9*IF(ABERTURAS!$F$53<=10,1,(ABERTURAS!$F$53/10)^(2/DATOS!$C$56)),$C$15)-H$42*$C$12 -> 0.41604908 | I49: =$J$30*IF($J$30>0,$C$9*IF(ABERTURAS!$F$53<=10,1,(ABERTURAS!$F$53/10)^(2/DATOS!$C$56)),$C$15)-I$42*$C$12 -> -4.3007411 | J49: =$M$30*IF($M$30>0,$C$9*IF(ABERTURAS!$F$53<=10,1,(ABERTURAS!$F$53/10)^(2/DATOS!$C$56)),$C$15)-J$42*$C$12 -> -70.224074 | O49: NTV 1997 · 4.2, pág. 5 (franja arriba de 10 m)
B50: Muro 4 — derecho (X = B) — en lo alto | C50: =$D$31*IF($D$31>0,$C$9*IF(ABERTURAS!$F$54<=10,1,(ABERTURAS!$F$54/10)^(2/DATOS!$C$56)),$C$15)-C$42*$C$12 -> 0.41604908 | D50: =$G$31*IF($G$31>0,$C$9*IF(ABERTURAS!$F$54<=10,1,(ABERTURAS!$F$54/10)^(2/DATOS!$C$56)),$C$15)-D$42*$C$12 -> 63.481728 | E50: =$J$31*IF($J$31>0,$C$9*IF(ABERTURAS!$F$54<=10,1,(ABERTURAS!$F$54/10)^(2/DATOS!$C$56)),$C$15)-E$42*$C$12 -> -4.3007411 | F50: =$M$31*IF($M$31>0,$C$9*IF(ABERTURAS!$F$54<=10,1,(ABERTURAS!$F$54/10)^(2/DATOS!$C$56)),$C$15)-F$42*$C$12 -> -70.224074 | G50: =$D$31*IF($D$31>0,$C$9*IF(ABERTURAS!$F$54<=10,1,(ABERTURAS!$F$54/10)^(2/DATOS!$C$56)),$C$15)-G$42*$C$12 -> 0.41604908 | H50: =$G$31*IF($G$31>0,$C$9*IF(ABERTURAS!$F$54<=10,1,(ABERTURAS!$F$54/10)^(2/DATOS!$C$56)),$C$15)-H$42*$C$12 -> 63.481728 | I50: =$J$31*IF($J$31>0,$C$9*IF(ABERTURAS!$F$54<=10,1,(ABERTURAS!$F$54/10)^(2/DATOS!$C$56)),$C$15)-I$42*$C$12 -> -4.3007411 | J50: =$M$31*IF($M$31>0,$C$9*IF(ABERTURAS!$F$54<=10,1,(ABERTURAS!$F$54/10)^(2/DATOS!$C$56)),$C$15)-J$42*$C$12 -> -70.224074 | O50: NTV 1997 · 4.2, pág. 5 (franja arriba de 10 m)
B51: Techo — cuarto 1, caso A | C51: =($D$32-C$42)*$C$12 -> -9.7664196 | D51: =($G$32-D$42)*$C$12 -> -9.7664196 | E51: =($J$32-E$42)*$C$12 -> -4.8832098 | F51: =($M$32-F$42)*$C$12 -> -70.806542 | G51: =($D$32-G$42)*$C$12 -> -9.7664196 | H51: =($G$32-H$42)*$C$12 -> -9.7664196 | I51: =($J$32-I$42)*$C$12 -> -4.8832098 | J51: =($M$32-J$42)*$C$12 -> -70.806542 | O51: NTV 1997 · 4.3.1, pág. 5 · 4.4, pág. 7
B52: Techo — cuarto 2, caso A | C52: =($D$33-C$42)*$C$12 -> -9.7664196 | D52: =($G$33-D$42)*$C$12 -> -9.7664196 | E52: =($J$33-E$42)*$C$12 -> -4.8832098 | F52: =($M$33-F$42)*$C$12 -> -70.806542 | G52: =($D$33-G$42)*$C$12 -> -9.7664196 | H52: =($G$33-H$42)*$C$12 -> -9.7664196 | I52: =($J$33-I$42)*$C$12 -> -4.8832098 | J52: =($M$33-J$42)*$C$12 -> -70.806542 | O52: NTV 1997 · 4.3.1, pág. 5 · 4.4, pág. 7
B53: Techo — cuarto 3, caso A | C53: =($D$34-C$42)*$C$12 -> -9.7664196 | D53: =($G$34-D$42)*$C$12 -> -9.7664196 | E53: =($J$34-E$42)*$C$12 -> -4.8832098 | F53: =($M$34-F$42)*$C$12 -> -70.806542 | G53: =($D$34-G$42)*$C$12 -> -9.7664196 | H53: =($G$34-H$42)*$C$12 -> -9.7664196 | I53: =($J$34-I$42)*$C$12 -> -4.8832098 | J53: =($M$34-J$42)*$C$12 -> -70.806542 | O53: NTV 1997 · 4.3.1, pág. 5 · 4.4, pág. 7
B54: Techo — cuarto 4, caso A | C54: =($D$35-C$42)*$C$12 -> -9.7664196 | D54: =($G$35-D$42)*$C$12 -> -9.7664196 | E54: =($J$35-E$42)*$C$12 -> -4.8832098 | F54: =($M$35-F$42)*$C$12 -> -70.806542 | G54: =($D$35-G$42)*$C$12 -> -9.7664196 | H54: =($G$35-H$42)*$C$12 -> -9.7664196 | I54: =($J$35-I$42)*$C$12 -> -4.8832098 | J54: =($M$35-J$42)*$C$12 -> -70.806542 | O54: NTV 1997 · 4.3.1, pág. 5 · 4.4, pág. 7
B55: Techo — cuarto 1, caso B | C55: =($E$32-C$42)*$C$12 -> -9.7664196 | D55: =($H$32-D$42)*$C$12 -> -9.7664196 | E55: =($K$32-E$42)*$C$12 -> -4.8832098 | F55: =($N$32-F$42)*$C$12 -> -70.806542 | G55: =($E$32-G$42)*$C$12 -> -9.7664196 | H55: =($H$32-H$42)*$C$12 -> -9.7664196 | I55: =($K$32-I$42)*$C$12 -> -4.8832098 | J55: =($N$32-J$42)*$C$12 -> -70.806542 | O55: NTV 1997 · 4.3.1, pág. 5 · 4.4, pág. 7
B56: Techo — cuarto 2, caso B | C56: =($E$33-C$42)*$C$12 -> -9.7664196 | D56: =($H$33-D$42)*$C$12 -> -9.7664196 | E56: =($K$33-E$42)*$C$12 -> -4.8832098 | F56: =($N$33-F$42)*$C$12 -> -70.806542 | G56: =($E$33-G$42)*$C$12 -> -9.7664196 | H56: =($H$33-H$42)*$C$12 -> -9.7664196 | I56: =($K$33-I$42)*$C$12 -> -4.8832098 | J56: =($N$33-J$42)*$C$12 -> -70.806542 | O56: NTV 1997 · 4.3.1, pág. 5 · 4.4, pág. 7
B57: Techo — cuarto 3, caso B | C57: =($E$34-C$42)*$C$12 -> -9.7664196 | D57: =($H$34-D$42)*$C$12 -> -9.7664196 | E57: =($K$34-E$42)*$C$12 -> -4.8832098 | F57: =($N$34-F$42)*$C$12 -> -70.806542 | G57: =($E$34-G$42)*$C$12 -> -9.7664196 | H57: =($H$34-H$42)*$C$12 -> -9.7664196 | I57: =($K$34-I$42)*$C$12 -> -4.8832098 | J57: =($N$34-J$42)*$C$12 -> -70.806542 | O57: NTV 1997 · 4.3.1, pág. 5 · 4.4, pág. 7
B58: Techo — cuarto 4, caso B | C58: =($E$35-C$42)*$C$12 -> -9.7664196 | D58: =($H$35-D$42)*$C$12 -> -9.7664196 | E58: =($K$35-E$42)*$C$12 -> -4.8832098 | F58: =($N$35-F$42)*$C$12 -> -70.806542 | G58: =($E$35-G$42)*$C$12 -> -9.7664196 | H58: =($H$35-H$42)*$C$12 -> -9.7664196 | I58: =($K$35-I$42)*$C$12 -> -4.8832098 | J58: =($N$35-J$42)*$C$12 -> -70.806542 | O58: NTV 1997 · 4.3.1, pág. 5 · 4.4, pág. 7
B60: D. FUERZAS TOTALES: LO QUE ENTRA A STAAD (LINEAS) CONTRA LO QUE DA LA NORMA (t)
B61: STAAD = Σ w·largo de los renglones de LINEAS (lo que vas a pegar), en ejes globales. Norma = Σ p·área maciza de cada muro y del techo. Diferencia normal: la franja de la base que baja directo a la cimentación (≈ 3 a 6%); en amarillo si pasa de 10% o de 0.2 t. Con succión pareja por todos lados la fuerza neta es casi cero: ahí sólo importa la diferencia.
B62: Concepto | C62: =DATOS!$B$72 -> LOAD 8 | D62: =DATOS!$B$73 -> LOAD 9 | E62: =DATOS!$B$74 -> LOAD 10 | F62: =DATOS!$B$75 -> LOAD 11 | G62: =DATOS!$B$76 -> LOAD 12 | H62: =DATOS!$B$77 -> LOAD 13 | I62: =DATOS!$B$78 -> LOAD 14 | J62: =DATOS!$B$79 -> LOAD 15 | O62: Referencia
B63: ΣFX que entra a STAAD | C63: =(SUMPRODUCT((LINEAS!$U$45:$U$194=3)*LINEAS!$AB$45:$AB$194*LINEAS!$M$45:$M$194)-SUMPRODUCT((LINEAS!$U$45:$U$194=4)*LINEAS!$AB$45:$AB$194*LINEAS!$M$45:$M$194)+IF(DATOS!$C$22="X",SUMPRODUCT(LINEAS!$AJ$9:$AJ$38*LINEAS!$M$9:$M$38),0))/1000 -> 9.6060132 | D63: =(SUMPRODUCT((LINEAS!$U$45:$U$194=3)*LINEAS!$AC$45:$AC$194*LINEAS!$M$45:$M$194)-SUMPRODUCT((LINEAS!$U$45:$U$194=4)*LINEAS!$AC$45:$AC$194*LINEAS!$M$45:$M$194)+IF(DATOS!$C$22="X",SUMPRODUCT(LINEAS!$AK$9:$AK$38*LINEAS!$M$9:$M$38),0))/1000 -> -9.6060132 | E63: =(SUMPRODUCT((LINEAS!$U$45:$U$194=3)*LINEAS!$AD$45:$AD$194*LINEAS!$M$45:$M$194)-SUMPRODUCT((LINEAS!$U$45:$U$194=4)*LINEAS!$AD$45:$AD$194*LINEAS!$M$45:$M$194)+IF(DATOS!$C$22="X",SUMPRODUCT(LINEAS!$AL$9:$AL$38*LINEAS!$M$9:$M$38),0))/1000 -> 0 | F63: =(SUMPRODUCT((LINEAS!$U$45:$U$194=3)*LINEAS!$AE$45:$AE$194*LINEAS!$M$45:$M$194)-SUMPRODUCT((LINEAS!$U$45:$U$194=4)*LINEAS!$AE$45:$AE$194*LINEAS!$M$45:$M$194)+IF(DATOS!$C$22="X",SUMPRODUCT(LINEAS!$AM$9:$AM$38*LINEAS!$M$9:$M$38),0))/1000 -> 0 | G63: =(SUMPRODUCT((LINEAS!$U$45:$U$194=3)*LINEAS!$AF$45:$AF$194*LINEAS!$M$45:$M$194)-SUMPRODUCT((LINEAS!$U$45:$U$194=4)*LINEAS!$AF$45:$AF$194*LINEAS!$M$45:$M$194)+IF(DATOS!$C$22="X",SUMPRODUCT(LINEAS!$AN$9:$AN$38*LINEAS!$M$9:$M$38),0))/1000 -> 9.6060132 | H63: =(SUMPRODUCT((LINEAS!$U$45:$U$194=3)*LINEAS!$AG$45:$AG$194*LINEAS!$M$45:$M$194)-SUMPRODUCT((LINEAS!$U$45:$U$194=4)*LINEAS!$AG$45:$AG$194*LINEAS!$M$45:$M$194)+IF(DATOS!$C$22="X",SUMPRODUCT(LINEAS!$AO$9:$AO$38*LINEAS!$M$9:$M$38),0))/1000 -> -9.6060132 | I63: =(SUMPRODUCT((LINEAS!$U$45:$U$194=3)*LINEAS!$AH$45:$AH$194*LINEAS!$M$45:$M$194)-SUMPRODUCT((LINEAS!$U$45:$U$194=4)*LINEAS!$AH$45:$AH$194*LINEAS!$M$45:$M$194)+IF(DATOS!$C$22="X",SUMPRODUCT(LINEAS!$AP$9:$AP$38*LINEAS!$M$9:$M$38),0))/1000 -> 0 | J63: =(SUMPRODUCT((LINEAS!$U$45:$U$194=3)*LINEAS!$AI$45:$AI$194*LINEAS!$M$45:$M$194)-SUMPRODUCT((LINEAS!$U$45:$U$194=4)*LINEAS!$AI$45:$AI$194*LINEAS!$M$45:$M$194)+IF(DATOS!$C$22="X",SUMPRODUCT(LINEAS!$AQ$9:$AQ$38*LINEAS!$M$9:$M$38),0))/1000 -> 0 | O63: NTV 1997 · 4.5, pág. 7
B64: FX según la norma | C64: =((C45*(ABERTURAS!$O$53-ABERTURAS!$H$53)+C49*ABERTURAS!$H$53)-(C46*(ABERTURAS!$O$54-ABERTURAS!$H$54)+C50*ABERTURAS!$H$54)+IF(DATOS!$C$22="X",(C51*$C$18+C52*$C$19+C53*$C$20+C54*$C$21)*DATOS!$C$23/4*IF(DATOS!$C$22="X",DATOS!$C$13,DATOS!$C$12),0))/1000 -> 10.206218 | D64: =((D45*(ABERTURAS!$O$53-ABERTURAS!$H$53)+D49*ABERTURAS!$H$53)-(D46*(ABERTURAS!$O$54-ABERTURAS!$H$54)+D50*ABERTURAS!$H$54)+IF(DATOS!$C$22="X",(D51*$C$18+D52*$C$19+D53*$C$20+D54*$C$21)*DATOS!$C$23/4*IF(DATOS!$C$22="X",DATOS!$C$13,DATOS!$C$12),0))/1000 -> -10.206218 | E64: =((E45*(ABERTURAS!$O$53-ABERTURAS!$H$53)+E49*ABERTURAS!$H$53)-(E46*(ABERTURAS!$O$54-ABERTURAS!$H$54)+E50*ABERTURAS!$H$54)+IF(DATOS!$C$22="X",(E51*$C$18+E52*$C$19+E53*$C$20+E54*$C$21)*DATOS!$C$23/4*IF(DATOS!$C$22="X",DATOS!$C$13,DATOS!$C$12),0))/1000 -> 0 | F64: =((F45*(ABERTURAS!$O$53-ABERTURAS!$H$53)+F49*ABERTURAS!$H$53)-(F46*(ABERTURAS!$O$54-ABERTURAS!$H$54)+F50*ABERTURAS!$H$54)+IF(DATOS!$C$22="X",(F51*$C$18+F52*$C$19+F53*$C$20+F54*$C$21)*DATOS!$C$23/4*IF(DATOS!$C$22="X",DATOS!$C$13,DATOS!$C$12),0))/1000 -> 0 | G64: =((G45*(ABERTURAS!$P$53-ABERTURAS!$H$53)+G49*ABERTURAS!$H$53)-(G46*(ABERTURAS!$P$54-ABERTURAS!$H$54)+G50*ABERTURAS!$H$54)+IF(DATOS!$C$22="X",(G51*$C$18+G52*$C$19+G53*$C$20+G54*$C$21)*DATOS!$C$23/4*IF(DATOS!$C$22="X",DATOS!$C$13,DATOS!$C$12),0))/1000 -> 10.206218 | H64: =((H45*(ABERTURAS!$P$53-ABERTURAS!$H$53)+H49*ABERTURAS!$H$53)-(H46*(ABERTURAS!$P$54-ABERTURAS!$H$54)+H50*ABERTURAS!$H$54)+IF(DATOS!$C$22="X",(H51*$C$18+H52*$C$19+H53*$C$20+H54*$C$21)*DATOS!$C$23/4*IF(DATOS!$C$22="X",DATOS!$C$13,DATOS!$C$12),0))/1000 -> -10.206218 | I64: =((I45*(ABERTURAS!$P$53-ABERTURAS!$H$53)+I49*ABERTURAS!$H$53)-(I46*(ABERTURAS!$P$54-ABERTURAS!$H$54)+I50*ABERTURAS!$H$54)+IF(DATOS!$C$22="X",(I51*$C$18+I52*$C$19+I53*$C$20+I54*$C$21)*DATOS!$C$23/4*IF(DATOS!$C$22="X",DATOS!$C$13,DATOS!$C$12),0))/1000 -> 0 | J64: =((J45*(ABERTURAS!$P$53-ABERTURAS!$H$53)+J49*ABERTURAS!$H$53)-(J46*(ABERTURAS!$P$54-ABERTURAS!$H$54)+J50*ABERTURAS!$H$54)+IF(DATOS!$C$22="X",(J51*$C$18+J52*$C$19+J53*$C$20+J54*$C$21)*DATOS!$C$23/4*IF(DATOS!$C$22="X",DATOS!$C$13,DATOS!$C$12),0))/1000 -> 0
B65: Diferencia en X (STAAD − norma) | C65: =C63-C64 -> -0.60020429 | D65: =D63-D64 -> 0.60020429 | E65: =E63-E64 -> 0 | F65: =F63-F64 -> 0 | G65: =G63-G64 -> -0.60020429 | H65: =H63-H64 -> 0.60020429 | I65: =I63-I64 -> 0 | J65: =J63-J64 -> 0
B66: ΣFZ que entra a STAAD | C66: =(SUMPRODUCT((LINEAS!$U$45:$U$194=1)*LINEAS!$AB$45:$AB$194*LINEAS!$M$45:$M$194)-SUMPRODUCT((LINEAS!$U$45:$U$194=2)*LINEAS!$AB$45:$AB$194*LINEAS!$M$45:$M$194)+IF(DATOS!$C$22="Z",SUMPRODUCT(LINEAS!$AJ$9:$AJ$38*LINEAS!$M$9:$M$38),0))/1000 -> -0.86977784 | D66: =(SUMPRODUCT((LINEAS!$U$45:$U$194=1)*LINEAS!$AC$45:$AC$194*LINEAS!$M$45:$M$194)-SUMPRODUCT((LINEAS!$U$45:$U$194=2)*LINEAS!$AC$45:$AC$194*LINEAS!$M$45:$M$194)+IF(DATOS!$C$22="Z",SUMPRODUCT(LINEAS!$AK$9:$AK$38*LINEAS!$M$9:$M$38),0))/1000 -> -0.86977784 | E66: =(SUMPRODUCT((LINEAS!$U$45:$U$194=1)*LINEAS!$AD$45:$AD$194*LINEAS!$M$45:$M$194)-SUMPRODUCT((LINEAS!$U$45:$U$194=2)*LINEAS!$AD$45:$AD$194*LINEAS!$M$45:$M$194)+IF(DATOS!$C$22="Z",SUMPRODUCT(LINEAS!$AL$9:$AL$38*LINEAS!$M$9:$M$38),0))/1000 -> 7.0362413 | F66: =(SUMPRODUCT((LINEAS!$U$45:$U$194=1)*LINEAS!$AE$45:$AE$194*LINEAS!$M$45:$M$194)-SUMPRODUCT((LINEAS!$U$45:$U$194=2)*LINEAS!$AE$45:$AE$194*LINEAS!$M$45:$M$194)+IF(DATOS!$C$22="Z",SUMPRODUCT(LINEAS!$AM$9:$AM$38*LINEAS!$M$9:$M$38),0))/1000 -> -5.6903746 | G66: =(SUMPRODUCT((LINEAS!$U$45:$U$194=1)*LINEAS!$AF$45:$AF$194*LINEAS!$M$45:$M$194)-SUMPRODUCT((LINEAS!$U$45:$U$194=2)*LINEAS!$AF$45:$AF$194*LINEAS!$M$45:$M$194)+IF(DATOS!$C$22="Z",SUMPRODUCT(LINEAS!$AN$9:$AN$38*LINEAS!$M$9:$M$38),0))/1000 -> -0.55885694 | H66: =(SUMPRODUCT((LINEAS!$U$45:$U$194=1)*LINEAS!$AG$45:$AG$194*LINEAS!$M$45:$M$194)-SUMPRODUCT((LINEAS!$U$45:$U$194=2)*LINEAS!$AG$45:$AG$194*LINEAS!$M$45:$M$194)+IF(DATOS!$C$22="Z",SUMPRODUCT(LINEAS!$AO$9:$AO$38*LINEAS!$M$9:$M$38),0))/1000 -> -0.55885694 | I66: =(SUMPRODUCT((LINEAS!$U$45:$U$194=1)*LINEAS!$AH$45:$AH$194*LINEAS!$M$45:$M$194)-SUMPRODUCT((LINEAS!$U$45:$U$194=2)*LINEAS!$AH$45:$AH$194*LINEAS!$M$45:$M$194)+IF(DATOS!$C$22="Z",SUMPRODUCT(LINEAS!$AP$9:$AP$38*LINEAS!$M$9:$M$38),0))/1000 -> 4.7442959 | J66: =(SUMPRODUCT((LINEAS!$U$45:$U$194=1)*LINEAS!$AI$45:$AI$194*LINEAS!$M$45:$M$194)-SUMPRODUCT((LINEAS!$U$45:$U$194=2)*LINEAS!$AI$45:$AI$194*LINEAS!$M$45:$M$194)+IF(DATOS!$C$22="Z",SUMPRODUCT(LINEAS!$AQ$9:$AQ$38*LINEAS!$M$9:$M$38),0))/1000 -> -3.6379583
B67: FZ según la norma | C67: =((C43*(ABERTURAS!$O$51-ABERTURAS!$H$51)+C47*ABERTURAS!$H$51)-(C44*(ABERTURAS!$O$52-ABERTURAS!$H$52)+C48*ABERTURAS!$H$52)+IF(DATOS!$C$22="Z",(C51*$C$18+C52*$C$19+C53*$C$20+C54*$C$21)*DATOS!$C$23/4*IF(DATOS!$C$22="X",DATOS!$C$13,DATOS!$C$12),0))/1000 -> -0.90438186 | D67: =((D43*(ABERTURAS!$O$51-ABERTURAS!$H$51)+D47*ABERTURAS!$H$51)-(D44*(ABERTURAS!$O$52-ABERTURAS!$H$52)+D48*ABERTURAS!$H$52)+IF(DATOS!$C$22="Z",(D51*$C$18+D52*$C$19+D53*$C$20+D54*$C$21)*DATOS!$C$23/4*IF(DATOS!$C$22="X",DATOS!$C$13,DATOS!$C$12),0))/1000 -> -0.90438186 | E67: =((E43*(ABERTURAS!$O$51-ABERTURAS!$H$51)+E47*ABERTURAS!$H$51)-(E44*(ABERTURAS!$O$52-ABERTURAS!$H$52)+E48*ABERTURAS!$H$52)+IF(DATOS!$C$22="Z",(E51*$C$18+E52*$C$19+E53*$C$20+E54*$C$21)*DATOS!$C$23/4*IF(DATOS!$C$22="X",DATOS!$C$13,DATOS!$C$12),0))/1000 -> 7.290717 | F67: =((F43*(ABERTURAS!$O$51-ABERTURAS!$H$51)+F47*ABERTURAS!$H$51)-(F44*(ABERTURAS!$O$52-ABERTURAS!$H$52)+F48*ABERTURAS!$H$52)+IF(DATOS!$C$22="Z",(F51*$C$18+F52*$C$19+F53*$C$20+F54*$C$21)*DATOS!$C$23/4*IF(DATOS!$C$22="X",DATOS!$C$13,DATOS!$C$12),0))/1000 -> -5.9187989 | G67: =((G43*(ABERTURAS!$P$51-ABERTURAS!$H$51)+G47*ABERTURAS!$H$51)-(G44*(ABERTURAS!$P$52-ABERTURAS!$H$52)+G48*ABERTURAS!$H$52)+IF(DATOS!$C$22="Z",(G51*$C$18+G52*$C$19+G53*$C$20+G54*$C$21)*DATOS!$C$23/4*IF(DATOS!$C$22="X",DATOS!$C$13,DATOS!$C$12),0))/1000 -> -0.57911858 | H67: =((H43*(ABERTURAS!$P$51-ABERTURAS!$H$51)+H47*ABERTURAS!$H$51)-(H44*(ABERTURAS!$P$52-ABERTURAS!$H$52)+H48*ABERTURAS!$H$52)+IF(DATOS!$C$22="Z",(H51*$C$18+H52*$C$19+H53*$C$20+H54*$C$21)*DATOS!$C$23/4*IF(DATOS!$C$22="X",DATOS!$C$13,DATOS!$C$12),0))/1000 -> -0.57911858 | I67: =((I43*(ABERTURAS!$P$51-ABERTURAS!$H$51)+I47*ABERTURAS!$H$51)-(I44*(ABERTURAS!$P$52-ABERTURAS!$H$52)+I48*ABERTURAS!$H$52)+IF(DATOS!$C$22="Z",(I51*$C$18+I52*$C$19+I53*$C$20+I54*$C$21)*DATOS!$C$23/4*IF(DATOS!$C$22="X",DATOS!$C$13,DATOS!$C$12),0))/1000 -> 4.893047 | J67: =((J43*(ABERTURAS!$P$51-ABERTURAS!$H$51)+J47*ABERTURAS!$H$51)-(J44*(ABERTURAS!$P$52-ABERTURAS!$H$52)+J48*ABERTURAS!$H$52)+IF(DATOS!$C$22="Z",(J51*$C$18+J52*$C$19+J53*$C$20+J54*$C$21)*DATOS!$C$23/4*IF(DATOS!$C$22="X",DATOS!$C$13,DATOS!$C$12),0))/1000 -> -3.7717071
B68: Diferencia en Z (STAAD − norma) | C68: =C66-C67 -> 0.034604025 | D68: =D66-D67 -> 0.034604025 | E68: =E66-E67 -> -0.25447573 | F68: =F66-F67 -> 0.22842423 | G68: =G66-G67 -> 0.020261633 | H68: =H66-H67 -> 0.020261633 | I68: =I66-I67 -> -0.14875115 | J68: =J66-J67 -> 0.13374883
B69: ΣFY que entra a STAAD (+ = hacia arriba) | C69: =-SUMPRODUCT(LINEAS!$AB$9:$AB$38*LINEAS!$M$9:$M$38)/1000 -> 1.5751282 | D69: =-SUMPRODUCT(LINEAS!$AC$9:$AC$38*LINEAS!$M$9:$M$38)/1000 -> 1.5751282 | E69: =-SUMPRODUCT(LINEAS!$AD$9:$AD$38*LINEAS!$M$9:$M$38)/1000 -> 0.78756408 | F69: =-SUMPRODUCT(LINEAS!$AE$9:$AE$38*LINEAS!$M$9:$M$38)/1000 -> 11.419679 | G69: =-SUMPRODUCT(LINEAS!$AF$9:$AF$38*LINEAS!$M$9:$M$38)/1000 -> 1.5751282 | H69: =-SUMPRODUCT(LINEAS!$AG$9:$AG$38*LINEAS!$M$9:$M$38)/1000 -> 1.5751282 | I69: =-SUMPRODUCT(LINEAS!$AH$9:$AH$38*LINEAS!$M$9:$M$38)/1000 -> 0.78756408 | J69: =-SUMPRODUCT(LINEAS!$AI$9:$AI$38*LINEAS!$M$9:$M$38)/1000 -> 11.419679 | O69: RESESCO Art. 21, pág. 8 (volteo y anclas con 0.9 CM + 1.301 V)
B70: FY según la norma | C70: =-(C51+C52+C53+C54)*DATOS!$C$23/4*IF(DATOS!$C$22="X",DATOS!$C$13,DATOS!$C$12)/1000 -> 1.5751282 | D70: =-(D51+D52+D53+D54)*DATOS!$C$23/4*IF(DATOS!$C$22="X",DATOS!$C$13,DATOS!$C$12)/1000 -> 1.5751282 | E70: =-(E51+E52+E53+E54)*DATOS!$C$23/4*IF(DATOS!$C$22="X",DATOS!$C$13,DATOS!$C$12)/1000 -> 0.78756408 | F70: =-(F51+F52+F53+F54)*DATOS!$C$23/4*IF(DATOS!$C$22="X",DATOS!$C$13,DATOS!$C$12)/1000 -> 11.419679 | G70: =-(G51+G52+G53+G54)*DATOS!$C$23/4*IF(DATOS!$C$22="X",DATOS!$C$13,DATOS!$C$12)/1000 -> 1.5751282 | H70: =-(H51+H52+H53+H54)*DATOS!$C$23/4*IF(DATOS!$C$22="X",DATOS!$C$13,DATOS!$C$12)/1000 -> 1.5751282 | I70: =-(I51+I52+I53+I54)*DATOS!$C$23/4*IF(DATOS!$C$22="X",DATOS!$C$13,DATOS!$C$12)/1000 -> 0.78756408 | J70: =-(J51+J52+J53+J54)*DATOS!$C$23/4*IF(DATOS!$C$22="X",DATOS!$C$13,DATOS!$C$12)/1000 -> 11.419679
B71: Diferencia en Y (STAAD − norma) | C71: =C69-C70 -> 0 | D71: =D69-D70 -> 0 | E71: =E69-E70 -> 0 | F71: =F69-F70 -> 0 | G71: =G69-G70 -> 0 | H71: =H69-H70 -> 0 | I71: =I69-I70 -> 0 | J71: =J69-J70 -> 0
B73: E. COBERTURA DE CADA MURO: ÁREA MACIZA CONTRA ÁREA CARGADA EN LINEAS
B74: OK si LINEAS carga por lo menos 85% del área maciza (lo demás es la franja de la base). «SIN MIEMBROS» = el muro existe y tiene presión, pero no hay renglones suyos en LINEAS: en STAAD esa presión no entraría.
B75: Superficie | C75: Maciza CERR (m²) | D75: Cargada CERR (m²) | E75: % CERR | F75: Maciza PA (m²) | G75: Cargada PA (m²) | H75: % PA | I75: Estado | O75: Referencia
B76: Muro 1 — atrás (Z = 0) | C76: =ABERTURAS!$O$51 -> 107.0496 | D76: =SUMIF(LINEAS!$U$45:$U$194,1,LINEAS!$R$45:$R$194) -> 103.28172 | E76: =IF($C76<=0,"—",$D76/$C76) -> 0.96480248 | F76: =ABERTURAS!$P$51 -> 71.633112 | G76: =SUMIF(LINEAS!$U$45:$U$194,1,LINEAS!$S$45:$S$194) -> 69.426912 | H76: =IF($F76<=0,"—",$G76/$F76) -> 0.96920139 | I76: =IF(AND($C76<=0,$F76<=0),"TODO ABIERTO: no lleva carga",IF(AND($D76=0,$G76=0),"SIN MIEMBROS: su presión no entra a STAAD",IF(MIN($E76,$H76)>=0.85,"OK",IF(MIN($E76,$H76)>=0.6,"REVISA: falta cargar parte del muro","OJO: falta mucho muro")))) -> OK | O76: LINEAS §B · NTV 1997 · 4.5, pág. 7
B77: Muro 2 — frente (Z = L) | C77: =ABERTURAS!$O$52 -> 0 | D77: =SUMIF(LINEAS!$U$45:$U$194,2,LINEAS!$R$45:$R$194) -> 0 | E77: =IF($C77<=0,"—",$D77/$C77) -> — | F77: =ABERTURAS!$P$52 -> 0 | G77: =SUMIF(LINEAS!$U$45:$U$194,2,LINEAS!$S$45:$S$194) -> 0 | H77: =IF($F77<=0,"—",$G77/$F77) -> — | I77: =IF(AND($C77<=0,$F77<=0),"TODO ABIERTO: no lleva carga",IF(AND($D77=0,$G77=0),"SIN MIEMBROS: su presión no entra a STAAD",IF(MIN($E77,$H77)>=0.85,"OK",IF(MIN($E77,$H77)>=0.6,"REVISA: falta cargar parte del muro","OJO: falta mucho muro")))) -> TODO ABIERTO: no lleva carga | O77: LINEAS §B · NTV 1997 · 4.5, pág. 7
B78: Muro 3 — izquierdo (X = 0) | C78: =ABERTURAS!$O$53 -> 163.52 | D78: =SUMIF(LINEAS!$U$45:$U$194,3,LINEAS!$R$45:$R$194) -> 153.8996 | E78: =IF($C78<=0,"—",$D78/$C78) -> 0.94116683 | F78: =ABERTURAS!$P$53 -> 163.52 | G78: =SUMIF(LINEAS!$U$45:$U$194,3,LINEAS!$S$45:$S$194) -> 153.8996 | H78: =IF($F78<=0,"—",$G78/$F78) -> 0.94116683 | I78: =IF(AND($C78<=0,$F78<=0),"TODO ABIERTO: no lleva carga",IF(AND($D78=0,$G78=0),"SIN MIEMBROS: su presión no entra a STAAD",IF(MIN($E78,$H78)>=0.85,"OK",IF(MIN($E78,$H78)>=0.6,"REVISA: falta cargar parte del muro","OJO: falta mucho muro")))) -> OK | O78: LINEAS §B · NTV 1997 · 4.5, pág. 7
B79: Muro 4 — derecho (X = B) | C79: =ABERTURAS!$O$54 -> 163.52 | D79: =SUMIF(LINEAS!$U$45:$U$194,4,LINEAS!$R$45:$R$194) -> 153.8996 | E79: =IF($C79<=0,"—",$D79/$C79) -> 0.94116683 | F79: =ABERTURAS!$P$54 -> 163.52 | G79: =SUMIF(LINEAS!$U$45:$U$194,4,LINEAS!$S$45:$S$194) -> 153.8996 | H79: =IF($F79<=0,"—",$G79/$F79) -> 0.94116683 | I79: =IF(AND($C79<=0,$F79<=0),"TODO ABIERTO: no lleva carga",IF(AND($D79=0,$G79=0),"SIN MIEMBROS: su presión no entra a STAAD",IF(MIN($E79,$H79)>=0.85,"OK",IF(MIN($E79,$H79)>=0.6,"REVISA: falta cargar parte del muro","OJO: falta mucho muro")))) -> OK | O79: LINEAS §B · NTV 1997 · 4.5, pág. 7
B80: Techo (área en planta) | C80: =DATOS!$C$12*DATOS!$C$13 -> 161.28 | D80: =SUM(LINEAS!$O$9:$O$38) -> 161.28 | E80: =IF($C80<=0,"—",$D80/$C80) -> 1 | I80: =IF(ABS($D80-$C80)<=0.01*$C80,"OK",IF($D80<$C80,"REVISA: falta techo en LINEAS §A","REVISA: hay techo repetido")) -> OK | O80: LINEAS §A
B82: F. CARGA EN UN MARCO INTERMEDIO EN 2D (p × separación, kg/m)
B83: Sólo para revisar un marco aislado en el plano X-Y: columna del Muro 3, columna del Muro 4 y viga del techo por cuartos (los cuartos van a lo largo del marco sólo si la pendiente es en X). El marco extremo lleva la mitad. En el modelo 3D usa la hoja STAAD.
B84: Elemento | C84: =DATOS!$B$72 -> LOAD 8 | D84: =DATOS!$B$73 -> LOAD 9 | E84: =DATOS!$B$74 -> LOAD 10 | F84: =DATOS!$B$75 -> LOAD 11 | G84: =DATOS!$B$76 -> LOAD 12 | H84: =DATOS!$B$77 -> LOAD 13 | I84: =DATOS!$B$78 -> LOAD 14 | J84: =DATOS!$B$79 -> LOAD 15 | O84: Referencia
B85: Columna del Muro 3 (hasta 10 m) | C85: =C45*DATOS!$C$20 -> 424.00833 | D85: =D45*DATOS!$C$20 -> 2.8083313 | E85: =E45*DATOS!$C$20 -> -29.030002 | F85: =F45*DATOS!$C$20 -> -474.0125 | G85: =G45*DATOS!$C$20 -> 424.00833 | H85: =H45*DATOS!$C$20 -> 2.8083313 | I85: =I45*DATOS!$C$20 -> -29.030002 | J85: =J45*DATOS!$C$20 -> -474.0125 | O85: Criterio de esta hoja (REFERENCIAS)
B86: Columna del Muro 4 (hasta 10 m) | C86: =C46*DATOS!$C$20 -> 2.8083313 | D86: =D46*DATOS!$C$20 -> 424.00833 | E86: =E46*DATOS!$C$20 -> -29.030002 | F86: =F46*DATOS!$C$20 -> -474.0125 | G86: =G46*DATOS!$C$20 -> 2.8083313 | H86: =H46*DATOS!$C$20 -> 424.00833 | I86: =I46*DATOS!$C$20 -> -29.030002 | J86: =J46*DATOS!$C$20 -> -474.0125 | O86: Criterio de esta hoja (REFERENCIAS)
B87: Techo — cuarto 1 (caso A) | C87: =C51*DATOS!$C$20 -> -65.923333 | D87: =D51*DATOS!$C$20 -> -65.923333 | E87: =E51*DATOS!$C$20 -> -32.961666 | F87: =F51*DATOS!$C$20 -> -477.94416 | G87: =G51*DATOS!$C$20 -> -65.923333 | H87: =H51*DATOS!$C$20 -> -65.923333 | I87: =I51*DATOS!$C$20 -> -32.961666 | J87: =J51*DATOS!$C$20 -> -477.94416 | O87: Criterio de esta hoja (REFERENCIAS)
